Workbook

Sheet Dashboard
B2: =C3&" – Dashboard" -> Project Bana – Dashboard
C3: Project Bana
C4: 50 MVA onshore wind, Ács Katódgyár – sale at COD vs hold to maturity
C5: Version | E5: v2
C6: Model date | E6: 46309
C7: Key-assumption set | E7: =Scenario_Name -> Base: Raiffeisen
C8: Master check | E8: =IF(Master_Check=0,"OK","CHECK") -> OK
C9: Item | D9: Unit | E9: European turbine | F9: Chinese turbine | X9: Key assumptions | Y9: Unit | Z9: Live
A11: x | C11: The bid: commitments and points | E11: European turbine | F11: Chinese turbine | H11: Offerable range | I11: Points EU | J11: Points CN | X11: Key-assumption set
C12: Municipal one-off (ÖSZ-1) | D12: EUR k/MW | E12: 50 | F12: 50 | H12: 0 or 10–50 | I12: =Calc_1!$F$34 -> 20 | J12: =Calc_2!$F$34 -> 20 | X12: Key-assumption set | Y12: text | Z12: Base: Raiffeisen
C13: Community contribution (ÖSZ-2) | D13: EUR/MWh | E13: 3 | F13: 3 | H13: 0 or 2–3 | I13: =Calc_1!$F$35 -> 15 | J13: =Calc_2!$F$35 -> 15
C14: Overbuild committed (ÖSZ-3) | D14: % | E14: 0.2 | F14: 0.2 | H14: ≥ 0 % | I14: =Calc_1!$F$36 -> 5 | J14: =Calc_2!$F$36 -> 5 | X14: Key assumptions (live)
C15: BESS power, share of MVA (ÖSZ-4) | D15: % | E15: 0.2 | F15: 0.2 | H15: ≤ wind MW | I15: =Calc_1!$F$37 -> 7.5 | J15: =Calc_2!$F$37 -> 7.5 | X15: Purchase price | Y15: EUR k | Z15: =In_Purchase_Price -> 4500
C16: BESS duration | D16: h | E16: 4 | F16: 4 | H16: ≥ 4 h | X16: COD | Y16: date | Z16: =In_COD -> 47756
C17: Performance security multiple (ÖSZ-6) | D17: x | E17: 1 | F17: 1 | H17: ≥ 1.0 | I17: =Calc_1!$F$39 -> 0 | J17: =Calc_2!$F$39 -> 0 | X17: Overbuild built | Y17: % | Z17: =In_Overbuild_Built -> 0.1
C18: Partial award accepted (ÖSZ-5) | D18: flag | E18: 0 | F18: 0 | H18: 0 / 1 | I18: =Calc_1!$F$38 -> 0 | J18: =Calc_2!$F$38 -> 0 | X18: Sanction regime (1 pro rata, 2 full) | Y18: flag | Z18: =In_Sanction_Regime -> 1
C19: Shared connection (ÖSZ-8) | D19: flag | E19: 0 | F19: 0 | H19: 0 / 1 | I19: =Calc_1!$F$40 -> 0 | J19: =Calc_2!$F$40 -> 0 | X19: COD price, EU | Y19: EUR k/MW | Z19: =In_COD_Price -> 2450
C20: EU turbines ≥ 80 % (ÖSZ-9), sets the route | D20: flag | E20: 1 | F20: 0 | H20: 0 / 1 | I20: =Calc_1!$F$41 -> 12 | J20: =Calc_2!$F$41 -> 0 | X20: COD price, CN | Y20: EUR k/MW | Z20: =In_COD_Price_CN -> 2100
C21: EU transformers ≥ 80 % (ÖSZ-9) | D21: flag | E21: 0 | F21: 0 | H21: 0 / 1 | I21: =Calc_1!$F$42 -> 0 | J21: =Calc_2!$F$42 -> 0 | X21: Turbine price, EU | Y21: EUR k/MW | Z21: =In_Turbine -> 950
C22: Points total | D22: points | E22: =Calc_1!$E43 -> 59.5 | F22: =Calc_2!$E43 -> 47.5 | X22: Turbine price, CN | Y22: EUR k/MW | Z22: =In_Turbine_CN -> 500
C23: Commitments within the offerable range | D23: flag | E23: =IF(Calc_1!$E45+Calc_1!$F45=0,"OK","CHECK") -> OK | F23: =IF(Calc_2!$E45+Calc_2!$F45=0,"OK","CHECK") -> OK | X23: Net P50 hours | Y23: h/yr | Z23: =In_P50_Hours -> 2600
X24: PPA price at COD, whole life | Y24: EUR/MWh | Z24: =In_PPA_Price -> 90
A25: x | C25: Capacity: committed vs built | E25: European turbine | F25: Chinese turbine | X25: Debt rate | Y25: % | Z25: =In_Debt_Rate -> 0.05
C26: Wind committed in the bid | D26: MW | E26: =Calc_1!$E25 -> 60 | F26: =Calc_2!$E25 -> 60 | X26: Target DSCR | Y26: x | Z26: =In_DSCR -> 1.2
C27: Wind built | D27: MW | E27: =Calc_1!$F25 -> 55 | F27: =Calc_2!$F25 -> 55 | X27: Tenor from COD | Y27: years | Z27: =In_Debt_Tenor -> 15
C28: BESS committed | D28: MW | E28: =Calc_1!$E27 -> 10 | F28: =Calc_2!$E27 -> 10 | X28: Debt share cap | Y28: % | Z28: =In_Gearing -> 0.7
C29: BESS energy committed | D29: MWh | E29: =Calc_1!$E28 -> 40 | F29: =Calc_2!$E28 -> 40 | X29: CIT | Y29: % | Z29: =In_CIT -> 0.15
C30: BESS built | D30: MW | E30: =Calc_1!$F27 -> 10 | F30: =Calc_2!$F27 -> 10 | X30: Robin Hood tax on (1 = yes) | Y30: flag | Z30: =In_RH_On -> 0
C31: Wind build shortfall vs commitment | D31: % | E31: =Calc_1!$E30 -> 0.083333333 | F31: =Calc_2!$E30 -> 0.083333333 | X31: Discount rate | Y31: % | Z31: =In_Discount_Rate -> 0.08
C32: Memo: connection right lost pro rata | D32: MVA | E32: =Calc_1!$E31 -> 0 | F32: =Calc_2!$E31 -> 0 | X32: FX | Y32: HUF/EUR | Z32: =In_FX -> 365
C33: Grid-bottleneck energy loss | D33: % | E33: =Calc_1!$E29 -> 0.0045454545 | F33: =Calc_2!$E29 -> 0.0045454545
C34: PB call if the pro-rata rule applies (GYIK 28/30) | D34: EUR m | E34: =Calc_1!$E61/Thousand -> 0 | F34: =Calc_2!$E61/Thousand -> 0
C35: PB call if the full-call rule applies (GYIK 72) | D35: EUR m | E35: =Calc_1!$F61/Thousand -> 2.2164384 | F35: =Calc_2!$F61/Thousand -> 2.2164384
C36: PB call paid, selected regime | D36: EUR m | E36: =(-Calc_1!$I62)/Thousand -> 0 | F36: =(-Calc_2!$I62)/Thousand -> 0
A38: x | C38: Returns at a glance | E38: European turbine | F38: Chinese turbine
C39: FEP profit – sale at COD | D39: EUR m | E39: =Calc_1!$I139/Thousand -> 20.88859 | F39: =Calc_2!$I139/Thousand -> 28.953814
C40: FEP IRR – sale at COD | D40: % | E40: =Calc_1!$E140 -> 0.2480759 | F40: =Calc_2!$E140 -> 0.43059013
C41: FEP MOIC – sale at COD | D41: x | E41: =Calc_1!$E141 -> 1.3302601 | F41: =Calc_2!$E141 -> 1.8037996
C42: FEP NPV – sale at COD | D42: EUR m | E42: =Calc_1!$E142/Thousand -> 11.024428 | F42: =Calc_2!$E142/Thousand -> 18.540429
C43: FEP profit – hold to maturity | D43: EUR m | E43: =Calc_1!$I152/Thousand -> 137.25447 | F43: =Calc_2!$I152/Thousand -> 160.39804
C44: FEP IRR – hold to maturity | D44: % | E44: =Calc_1!$E153 -> 0.074058513 | F44: =Calc_2!$E153 -> 0.1184652
C45: FEP MOIC – hold to maturity | D45: x | E45: =Calc_1!$E154 -> 3.1304036 | F45: =Calc_2!$E154 -> 5.3119157
C46: FEP NPV – hold to maturity | D46: EUR m | E46: =Calc_1!$E155/Thousand -> -3.7260999 | F46: =Calc_2!$E155/Thousand -> 16.612562
C47: Project IRR, actual tax, before financing | D47: % | E47: =Calc_1!$E151 -> 0.069659503 | F47: =Calc_2!$E151 -> 0.096343319
A49: x | C49: Funding to COD | E49: European turbine | F49: Chinese turbine
C50: Purchase price, DD and devex | D50: EUR m | E50: =Calc_1!$E121/Thousand -> 5.15 | F50: =Calc_2!$E121/Thousand -> 5.15
C51: Participation fee, TSO security, guarantee fees | D51: EUR m | E51: =Calc_1!$E122/Thousand -> 1.1149216 | F51: =Calc_2!$E122/Thousand -> 1.1149216
C52: Construction capex (wind, substation, BESS) | D52: EUR m | E52: =Calc_1!$E123/Thousand -> 91.96375 | F52: =Calc_2!$E123/Thousand -> 64.71625
C53: Connection fees, net of TSO security | D53: EUR m | E53: =Calc_1!$E124/Thousand -> 8.1548232 | F53: =Calc_2!$E124/Thousand -> 8.1548232
C54: Municipal one-off | D54: EUR m | E54: =Calc_1!$E125/Thousand -> 2.5 | F54: =Calc_2!$E125/Thousand -> 2.5
C55: Capitalised interest and debt fees | D55: EUR m | E55: =Calc_1!$E126/Thousand -> 3.5252448 | F55: =Calc_2!$E126/Thousand -> 3.5450214
C56: Land lease during construction | D56: EUR m | E56: =Calc_1!$E127/Thousand -> 0.3401702 | F56: =Calc_2!$E127/Thousand -> 0.3401702
C57: Total uses | D57: EUR m | E57: =Calc_1!$E128/Thousand -> 112.74891 | F57: =Calc_2!$E128/Thousand -> 85.521186
C58: Senior debt at COD (incl. capitalised interest) | D58: EUR m | E58: =Calc_1!$E103/Thousand -> 49.5 | F58: =Calc_2!$E103/Thousand -> 49.5
C59: FEP equity to COD | D59: EUR m | E59: =Calc_1!$E129/Thousand -> 63.24891 | F59: =Calc_2!$E129/Thousand -> 36.021186
C60: FEP peak equity, hold (incl. DSRA) | D60: EUR m | E60: =Calc_1!$F129/Thousand -> 64.426511 | F60: =Calc_2!$F129/Thousand -> 37.198788
C61: Debt share of total uses | D61: % | E61: =Calc_1!$E130 -> 0.43902864 | F61: =Calc_2!$E130 -> 0.57880395
A63: x | C63: Securities and fees | E63: European turbine | F63: Chinese turbine | H63: Form | I63: Posted | J63: Released
C64: Participation fee | D64: EUR m | E64: =Calc_1!$E52/Thousand -> 0.0082191781 | F64: =Calc_2!$E52/Thousand -> 0.0082191781 | H64: cash | I64: =In_Bid_Date -> 46325 | J64: –
C65: Bid security | D65: EUR m | E65: =Calc_1!$E53/Thousand -> 0.44328767 | F65: =Calc_2!$E53/Thousand -> 0.44328767 | H65: guarantee | I65: =In_Bid_Date -> 46325 | J65: =Calc_1!$F$54 -> 46433
C66: Performance security | D66: EUR m | E66: =Calc_1!$E54/Thousand -> 2.2164384 | F66: =Calc_2!$E54/Thousand -> 2.2164384 | H66: guarantee | I66: =Calc_1!$F$54 -> 46433 | J66: =In_PB_Release -> 48669
C67: TSO connection-request security | D67: EUR m | E67: =Calc_1!$E55/Thousand -> 0.61643836 | F67: =Calc_2!$E55/Thousand -> 0.61643836 | H67: cash | I67: =Calc_1!$F$54 -> 46433 | J67: credited
C68: Direct connection fee | D68: EUR m | E68: =Calc_1!$E56/Thousand -> 1.260274 | F68: =Calc_2!$E56/Thousand -> 1.260274 | H68: cash | I68: =In_HCSSZ_Date -> 47126 | J68: –
C69: Indirect connection fee, net | D69: EUR m | E69: =Calc_1!$E57/Thousand -> 6.8945492 | F69: =Calc_2!$E57/Thousand -> 6.8945492 | H69: cash | I69: =In_HCSSZ_Date -> 47126 | J69: –
C70: Guarantee fees to COD | D70: EUR m | E70: =(-Calc_1!$E59)/Thousand -> 0.49026402 | F70: =(-Calc_2!$E59)/Thousand -> 0.49026402
A72: x | C72: Sale at COD | E72: European turbine | F72: Chinese turbine
C73: Sale price (enterprise value) | D73: EUR m | E73: =Calc_1!$E136/Thousand -> 134.1375 | F73: =Calc_2!$E136/Thousand -> 114.975
C74: Net proceeds to FEP (after debt and sale costs) | D74: EUR m | E74: =Calc_1!$E137/Thousand -> 84.1375 | F74: =Calc_2!$E137/Thousand -> 64.975
C75: Tax on the gain | D75: EUR m | E75: =Calc_1!$E138/Thousand -> 0 | F75: =Calc_2!$E138/Thousand -> 0
C76: Buyer IRR, unlevered, at the SPV's actual tax | D76: % | E76: =Calc_1!$E145 -> 0.056296123 | F76: =Calc_2!$E145 -> 0.069882997
C77: Buyer IRR, levered (takes the debt, funds the DSRA) | D77: % | E77: =Calc_1!$E147 -> 0.057209447 | F77: =Calc_2!$E147 -> 0.07579169
A79: x | C79: Hold to maturity: debt and tax | E79: European turbine | F79: Chinese turbine
C80: Debt capacity at target DSCR (PV at COD) | D80: EUR m | E80: =Calc_1!$E88/Thousand -> 80.084339 | F80: =Calc_2!$E88/Thousand -> 77.983992
C81: Debt share of construction cost, sized | D81: % | E81: =Calc_1!$E90 -> 0.46100704 | F81: =Calc_2!$E90 -> 0.62734265
C82: Share of the DSCR capacity used | D82: % | E82: =Calc_1!$F90 -> 0.61809838 | F82: =Calc_2!$F90 -> 0.63474565
C83: Info: DSCR for maximum debt, low | D83: x | E83: =In_DSCR_Max_Low -> 1.1 | F83: =In_DSCR_Max_Low -> 1.1
C84: Info: maximum debt at COD, low DSCR, no cap | D84: EUR m | E84: =Calc_1!$E131/Thousand -> 87.364733 | F84: =Calc_2!$E131/Thousand -> 85.073446
C85: Info: maximum debt, share of total uses, low DSCR | D85: % | E85: =Calc_1!$E132 -> 0.774861 | F85: =Calc_2!$E132 -> 0.99476457
C86: Info: DSCR for maximum debt, high | D86: x | E86: =In_DSCR_Max_High -> 1.2 | F86: =In_DSCR_Max_High -> 1.2
C87: Info: maximum debt at COD, high DSCR, no cap | D87: EUR m | E87: =Calc_1!$F131/Thousand -> 80.084339 | F87: =Calc_2!$F131/Thousand -> 77.983992
C88: Info: maximum debt, share of total uses, high DSCR | D88: % | E88: =Calc_1!$F132 -> 0.71028925 | F88: =Calc_2!$F132 -> 0.91186752
C89: DSRA funded at COD | D89: EUR m | E89: =Calc_1!$E106/Thousand -> 1.1776015 | F89: =Calc_2!$E106/Thousand -> 1.1776015
C90: Minimum DSCR | D90: x | E90: =Calc_1!$E107 -> 1.9414385 | F90: =Calc_2!$E107 -> 1.890521
C91: Net generation, first full year | D91: GWh | E91: =Calc_1!$E75/Thousand -> 139.39751 | F91: =Calc_2!$E75/Thousand -> 139.39751
C92: Revenue, first full year | D92: EUR m | E92: =Calc_1!$E76/Thousand -> 12.671234 | F92: =Calc_2!$E76/Thousand -> 12.671234
C93: EBITDA, first full year | D93: EUR m | E93: =Calc_1!$E83/Thousand -> 9.5568841 | F93: =Calc_2!$E83/Thousand -> 9.5568841
C94: Lifetime revenue | D94: EUR m | E94: =Calc_1!$I76/Thousand -> 420.75271 | F94: =Calc_2!$I76/Thousand -> 420.75271
C95: Lifetime EBITDA | D95: EUR m | E95: =Calc_1!$I83/Thousand -> 295.37333 | F95: =Calc_2!$I83/Thousand -> 295.37333
C96: Lifetime corporate income tax and Robin Hood tax | D96: EUR m | E96: =(SUM(Calc_1!$J117:$EO117))/Thousand -> -24.221377 | F96: =(SUM(Calc_2!$J117:$EO117))/Thousand -> -28.305536
C97: Tax losses lapsed | D97: EUR m | E97: =(-Calc_1!$I115)/Thousand -> 0 | F97: =(-Calc_2!$I115)/Thousand -> 0
C98: Checks failed in this set (0 = OK) | D98: # | E98: =Model_Checks -> 0 | F98: =Model_Checks -> 0
A100: x | C100: Stored results by key-assumption set | E100: Live | H100: =Inputs!H$7 -> Base: Raiffeisen | I100: =Inputs!I$7 -> Base: UniCredit | J100: =Inputs!J$7 -> COD price −10% | K100: =Inputs!K$7 -> COD price +10% | L100: =Inputs!L$7 -> Turbine +10% | M100: =Inputs!M$7 -> Yield −10% | N100: =Inputs!N$7 -> PPA +10% | O100: =Inputs!O$7 -> Full PB call | ... V100: =Inputs!V$7 -> Full cash sweep
C101: Points total – European turbine | D101: points | E101: =Calc_1!$E43 -> 59.5 | H101: 59.5 | I101: 59.5 | J101: 59.5 | K101: 59.5 | L101: 59.5 | M101: 59.5 | N101: 59.5 | O101: 59.5 | P101: 59.5 | Q101: 59.5 | R101: 59.5 | S101: 59.5 | T101: 65.5 | U101: 59.5 | V101: 59.5
C102: Points total – Chinese turbine | D102: points | E102: =Calc_2!$E43 -> 47.5 | H102: 47.5 | I102: 47.5 | J102: 47.5 | K102: 47.5 | L102: 47.5 | M102: 47.5 | N102: 47.5 | O102: 47.5 | P102: 47.5 | Q102: 47.5 | R102: 47.5 | S102: 47.5 | T102: 53.5 | U102: 47.5 | V102: 47.5
C103: Memo: connection right lost pro rata – European turbine | D103: MVA | E103: =Calc_1!$E31 -> 0 | H103: 0 | I103: 0 | J103: 0 | K103: 0 | L103: 0 | M103: 0 | N103: 0 | O103: 0 | P103: 0 | Q103: 0 | R103: 0 | S103: 0 | T103: 0 | U103: 0 | V103: 0
C104: Memo: connection right lost pro rata – Chinese turbine | D104: MVA | E104: =Calc_2!$E31 -> 0 | H104: 0 | I104: 0 | J104: 0 | K104: 0 | L104: 0 | M104: 0 | N104: 0 | O104: 0 | P104: 0 | Q104: 0 | R104: 0 | S104: 0 | T104: 0 | U104: 0 | V104: 0
C105: PB call paid, selected regime – European turbine | D105: EUR m | E105: =(-Calc_1!$I62)/Thousand -> 0 | H105: 0 | I105: 0 | J105: 0 | K105: 0 | L105: 0 | M105: 0 | N105: 0 | O105: 2.2164384 | P105: 0 | Q105: 0 | R105: 0 | S105: 0 | T105: 0 | U105: 2.2164384 | V105: 0
C106: PB call paid, selected regime – Chinese turbine | D106: EUR m | E106: =(-Calc_2!$I62)/Thousand -> 0 | H106: 0 | I106: 0 | J106: 0 | K106: 0 | L106: 0 | M106: 0 | N106: 0 | O106: 2.2164384 | P106: 0 | Q106: 0 | R106: 0 | S106: 0 | T106: 0 | U106: 2.2164384 | V106: 0
C107: FEP profit – sale at COD – European turbine | D107: EUR m | E107: =Calc_1!$I139/Thousand -> 20.88859 | H107: 20.88859 | I107: 21.632809 | J107: 7.4748403 | K107: 34.30234 | L107: 15.405118 | M107: 20.88859 | N107: 20.88859 | O107: 18.672152 | P107: 20.464616 | Q107: 20.88859 | R107: 20.88859 | S107: 20.88859 | T107: 14.70981 | U107: 28.035256 | V107: 20.88859
C108: FEP profit – sale at COD – Chinese turbine | D108: EUR m | E108: =Calc_2!$I139/Thousand -> 28.953814 | H108: 28.953814 | I108: 29.702207 | J108: 17.456314 | K108: 40.451314 | L108: 26.069061 | M108: 28.953814 | N108: 28.953814 | O108: 26.737375 | P108: 28.525205 | Q108: 28.953814 | R108: 28.953814 | S108: 28.953814 | T108: 22.7775 | U108: 28.035256 | V108: 28.953814
...

Sheet Inputs
B2: =Dashboard!$C$3&" – Inputs and scenarios" -> Project Bana – Inputs and scenarios
B4: Scenario selected | D4: Set on the Dashboard | F4: =Scenario_Name -> Base: Raiffeisen
B5: Scenario number | F5: =MATCH(Scenario_Name,Scenario_Names,0) -> 1
B7: Input | C7: Unit | D7: Source / note | F7: Live | H7: Base: Raiffeisen | I7: Base: UniCredit | J7: COD price −10% | K7: COD price +10% | L7: Turbine +10% | M7: Yield −10% | N7: PPA +10% | O7: Full PB call | P7: Rate +1 pp | Q7: Tenor 10 years | R7: Robin Hood 31% | S7: CIT 9% | T7: BESS 100 MWh | U7: Promise all, deliver nothing | V7: Full cash sweep
A10: x | C10: Constants
B11: Thousand | C11: # | D11: Scale | F11: 1000
B12: Million | C12: # | D12: Scale | F12: 1000000
B13: Days In Year | C13: days | D13: Day count for year fractions and XIRR | F13: 365
B14: Months In Year | C14: months | F14: 12
B15: Months Per Period | C15: months | D15: Timeline periodicity (quarterly) | F15: 3
B16: Tolerance | C16: # | D16: Check and solver tolerance | F16: 1e-06
A18: x | C18: Timing
B19: Model start date | C19: date | D19: Timeline start | F19: =IF(INDEX($H19:$W19,1,Scenario_Selected)="",$H19,INDEX($H19:$W19,1,Scenario_Selected)) -> 46296 | H19: 46296
B20: Sensitivity step for the turbine and yield sets | C20: % | D20: User 13-Oct-26 | F20: 0.1
B21: Bid submission: fee paid, bid security posted, DD | C21: date | D21: Kiírás VI.5 | F21: =IF(INDEX($H21:$W21,1,Scenario_Selected)="",$H21,INDEX($H21:$W21,1,Scenario_Selected)) -> 46325 | H21: 46325
B22: Award decision | C22: date | D22: Bana v3 Inputs E96 | F22: =IF(INDEX($H22:$W22,1,Scenario_Selected)="",$H22,INDEX($H22:$W22,1,Scenario_Selected)) -> 46369 | H22: 46369
B23: Award decision received | C23: date | D23: GYIK Q68 | F23: =IF(INDEX($H23:$W23,1,Scenario_Selected)="",$H23,INDEX($H23:$W23,1,Scenario_Selected)) -> 46418 | H23: 46418
B24: PB posted, TSO security paid after the decision | C24: days | D24: Kiírás XII.5, XIII.6 | F24: =IF(INDEX($H24:$W24,1,Scenario_Selected)="",$H24,INDEX($H24:$W24,1,Scenario_Selected)) -> 15 | H24: 15
B25: Closing of the rights transfer: price paid | C25: date | D25: Bana deck p2: closing after the award | F25: =IF(INDEX($H25:$W25,1,Scenario_Selected)="",$H25,INDEX($H25:$W25,1,Scenario_Selected)) -> 46387 | H25: 46387
B26: Notice to proceed | C26: date | D26: Bana v3 Inputs E154 | F26: =IF(INDEX($H26:$W26,1,Scenario_Selected)="",$H26,INDEX($H26:$W26,1,Scenario_Selected)) -> 47026 | H26: 47026
B27: Connection agreement (HCSSZ): fees paid | C27: date | D27: Bana v3 Inputs E99 | F27: =IF(INDEX($H27:$W27,1,Scenario_Selected)="",$H27,INDEX($H27:$W27,1,Scenario_Selected)) -> 47126 | H27: 47126
B28: Commercial operation date | C28: date | D28: Bana v3 Inputs E155, E237 | F28: =IF(INDEX($H28:$W28,1,Scenario_Selected)="",$H28,INDEX($H28:$W28,1,Scenario_Selected)) -> 47756 | H28: 47756
B29: Operating life | C29: years | D29: Bana v3 Inputs E157 | F29: =IF(INDEX($H29:$W29,1,Scenario_Selected)="",$H29,INDEX($H29:$W29,1,Scenario_Selected)) -> 30 | H29: 30
B30: Performance security released (hold route) | C30: date | D30: Kiírás XII.8 (COD deadline + 6 m) | F30: =IF(INDEX($H30:$W30,1,Scenario_Selected)="",$H30,INDEX($H30:$W30,1,Scenario_Selected)) -> 48669 | H30: 48669
A32: x | C32: Acquisition, exit and tax
B33: FX rate | C33: HUF/EUR | D33: Bana v3 Inputs E11 | F33: =IF(INDEX($H33:$W33,1,Scenario_Selected)="",$H33,INDEX($H33:$W33,1,Scenario_Selected)) -> 365 | H33: 365
B34: Purchase price to GEI | C34: EUR k | D34: Bana v3 Inputs E283 | F34: =IF(INDEX($H34:$W34,1,Scenario_Selected)="",$H34,INDEX($H34:$W34,1,Scenario_Selected)) -> 4500 | H34: 4500
B35: Transaction and DD costs | C35: EUR k | D35: Bana v3 Inputs E25 | F35: =IF(INDEX($H35:$W35,1,Scenario_Selected)="",$H35,INDEX($H35:$W35,1,Scenario_Selected)) -> 150 | H35: 150
B36: Devex to NTP incl. contingency | C36: EUR k | D36: Bana v3 Inputs E292 | F36: =IF(INDEX($H36:$W36,1,Scenario_Selected)="",$H36,INDEX($H36:$W36,1,Scenario_Selected)) -> 500 | H36: 500
B37: Sale price at COD per MW, EU turbines | C37: EUR k/MW | D37: Bana v3 Inputs M230 | F37: =IF(INDEX($H37:$W37,1,Scenario_Selected)="",$H37,INDEX($H37:$W37,1,Scenario_Selected)) -> 2450 | H37: 2450 | J37: =H37*(1-Sens_Step) -> 2205 | K37: =H37*(1+Sens_Step) -> 2695
B38: Sale price at COD per MW, CN turbines | C38: EUR k/MW | D38: Bana v3 Inputs N230 | F38: =IF(INDEX($H38:$W38,1,Scenario_Selected)="",$H38,INDEX($H38:$W38,1,Scenario_Selected)) -> 2100 | H38: 2100 | J38: =H38*(1-Sens_Step) -> 1890 | K38: =H38*(1+Sens_Step) -> 2310
B39: Sale costs at COD | C39: EUR k | D39: Bana v3 Inputs E26 | F39: =IF(INDEX($H39:$W39,1,Scenario_Selected)="",$H39,INDEX($H39:$W39,1,Scenario_Selected)) -> 500 | H39: 500
B40: FEP discount rate (NPV) | C40: % | D40: Bana v3 Inputs E253 | F40: =IF(INDEX($H40:$W40,1,Scenario_Selected)="",$H40,INDEX($H40:$W40,1,Scenario_Selected)) -> 0.08 | H40: 0.08
B41: Corporate income tax: 9 % + possible Pillar Two top-up (proxy) | C41: % | D41: User 14-Oct-26; set 12: Tao. 19. § | F41: =IF(INDEX($H41:$W41,1,Scenario_Selected)="",$H41,INDEX($H41:$W41,1,Scenario_Selected)) -> 0.15 | H41: 0.15 | S41: 0.09
B42: Robin Hood tax applies (1 = yes) | C42: flag | D42: User 14-Oct-26: sensitivity only (Thtv.) | F42: =IF(INDEX($H42:$W42,1,Scenario_Selected)="",$H42,INDEX($H42:$W42,1,Scenario_Selected)) -> 0 | H42: 0 | R42: 1
B43: Robin Hood tax on positive pre-tax profit | C43: % | D43: Thtv.; 41 % to 2025, 31 % from 2026 | F43: =IF(INDEX($H43:$W43,1,Scenario_Selected)="",$H43,INDEX($H43:$W43,1,Scenario_Selected)) -> 0.31 | H43: 0.31
B44: Gain on the COD share sale taxed (0 = exempt) | C44: flag | D44: Bana v3 E231; participation exemption | F44: =IF(INDEX($H44:$W44,1,Scenario_Selected)="",$H44,INDEX($H44:$W44,1,Scenario_Selected)) -> 0 | H44: 0
B45: Tax depreciation period | C45: years | D45: Bana v3 Inputs E213 (to confirm) | F45: =IF(INDEX($H45:$W45,1,Scenario_Selected)="",$H45,INDEX($H45:$W45,1,Scenario_Selected)) -> 20 | H45: 20
B46: Tax losses usable, share of the tax base | C46: % | D46: Tao. 17. § (2); Bana v3 E214 | F46: =IF(INDEX($H46:$W46,1,Scenario_Selected)="",$H46,INDEX($H46:$W46,1,Scenario_Selected)) -> 0.5 | H46: 0.5
B47: Tax losses usable within | C47: years | D47: Tao. 17. § (1) | F47: =IF(INDEX($H47:$W47,1,Scenario_Selected)="",$H47,INDEX($H47:$W47,1,Scenario_Selected)) -> 5 | H47: 5
A49: x | C49: Tender and grid
B50: Points rounded to decimals | C50: # | D50: Kiírás X.1 b | F50: 2
B51: Net connection capacity | C51: MVA | D51: MEKH Annex 1; Bana v3 Inputs E281 | F51: =IF(INDEX($H51:$W51,1,Scenario_Selected)="",$H51,INDEX($H51:$W51,1,Scenario_Selected)) -> 50 | H51: 50
B52: Overbuild built, share of MVA (bid: Dashboard) | C52: % | D52: User 13-Oct-26 | F52: =IF(INDEX($H52:$W52,1,Scenario_Selected)="",$H52,INDEX($H52:$W52,1,Scenario_Selected)) -> 0.1 | H52: 0.1 | U52: 0
B53: Commitments delivered (0 = none: no municipal, community, EU kit) | C53: flag | D53: User 15-Oct-26 | F53: =IF(INDEX($H53:$W53,1,Scenario_Selected)="",$H53,INDEX($H53:$W53,1,Scenario_Selected)) -> 1 | H53: 1 | U53: 0
B54: BESS commitment, share of MVA (0 = Dashboard bid) | C54: % | D54: User 15-Oct-26: 100 MWh = 25 MW x 4 h | F54: =IF(INDEX($H54:$W54,1,Scenario_Selected)="",$H54,INDEX($H54:$W54,1,Scenario_Selected)) -> 0 | H54: 0 | T54: 0.5
B55: Energy lost on overbuilt MW | C55: % | D55: Bora!N18 (as Bora) | F55: =IF(INDEX($H55:$W55,1,Scenario_Selected)="",$H55,INDEX($H55:$W55,1,Scenario_Selected)) -> 0.05 | H55: 0.05
B56: BESS built (1 = yes) | C56: flag | D56: User 13-Oct-26 | F56: =IF(INDEX($H56:$W56,1,Scenario_Selected)="",$H56,INDEX($H56:$W56,1,Scenario_Selected)) -> 1 | H56: 1 | U56: 0
B57: Minimum BESS duration for ÖSZ-4 | C57: h | D57: Kiírás Annex 8; GYIK Q5 | F57: =IF(INDEX($H57:$W57,1,Scenario_Selected)="",$H57,INDEX($H57:$W57,1,Scenario_Selected)) -> 4 | H57: 4
B58: Build shortfall tolerated without sanction | C58: % | D58: GYIK 28, 30 | F58: =IF(INDEX($H58:$W58,1,Scenario_Selected)="",$H58,INDEX($H58:$W58,1,Scenario_Selected)) -> 0.1 | H58: 0.1
B59: Sanction regime (1 pro rata, 2 full PB call) | C59: flag | D59: GYIK 28/30 (1); Kiírás XIII.17, GYIK 72 (2) | F59: =IF(INDEX($H59:$W59,1,Scenario_Selected)="",$H59,INDEX($H59:$W59,1,Scenario_Selected)) -> 1 | H59: 1 | O59: 2 | U59: 2
B60: Sanction paid after COD | C60: months | D60: Kiírás XIII.17 | F60: =IF(INDEX($H60:$W60,1,Scenario_Selected)="",$H60,INDEX($H60:$W60,1,Scenario_Selected)) -> 6 | H60: 6
B61: Security base: benchmark investment, BESS | C61: mHUF/MWh | D61: Kiírás Annex 2 | F61: =IF(INDEX($H61:$W61,1,Scenario_Selected)="",$H61,INDEX($H61:$W61,1,Scenario_Selected)) -> 200 | H61: 200
B62: Security base: benchmark investment, wind | C62: mHUF/MW | D62: Kiírás Annex 2 | F62: =IF(INDEX($H62:$W62,1,Scenario_Selected)="",$H62,INDEX($H62:$W62,1,Scenario_Selected)) -> 406 | H62: 406
B63: Participation fee (cash, not refunded) | C63: mHUF | D63: Kiírás VI.4 | F63: =IF(INDEX($H63:$W63,1,Scenario_Selected)="",$H63,INDEX($H63:$W63,1,Scenario_Selected)) -> 3 | H63: 3
B64: Bid security (guarantee), share of base | C64: % | D64: Kiírás VIII.2 | F64: =IF(INDEX($H64:$W64,1,Scenario_Selected)="",$H64,INDEX($H64:$W64,1,Scenario_Selected)) -> 0.005 | H64: 0.005
B65: Performance security (guarantee), minimum share | C65: % | D65: Kiírás XII.3 | F65: =IF(INDEX($H65:$W65,1,Scenario_Selected)="",$H65,INDEX($H65:$W65,1,Scenario_Selected)) -> 0.025 | H65: 0.025
B66: TSO security (cash, credited to the indirect fee) | C66: mHUF/MVA | D66: Bana v3 Inputs E83 | F66: =IF(INDEX($H66:$W66,1,Scenario_Selected)="",$H66,INDEX($H66:$W66,1,Scenario_Selected)) -> 4.5 | H66: 4.5
B67: Direct connection fee per connection point (cash) | C67: mHUF | D67: MEKH Annex 1; Bana v3 Inputs E289 | F67: =IF(INDEX($H67:$W67,1,Scenario_Selected)="",$H67,INDEX($H67:$W67,1,Scenario_Selected)) -> 460 | H67: 460
B68: Indirect connection fee (cash) | C68: mHUF/MVA | D68: MEKH Annex 1; Bana v3 Inputs E288 | F68: =IF(INDEX($H68:$W68,1,Scenario_Selected)="",$H68,INDEX($H68:$W68,1,Scenario_Selected)) -> 54.830209 | H68: 54.830209
B69: Bank guarantee fee on guarantees outstanding | C69: % | D69: Bana v3 Inputs E113 | F69: =IF(INDEX($H69:$W69,1,Scenario_Selected)="",$H69,INDEX($H69:$W69,1,Scenario_Selected)) -> 0.06 | H69: 0.06
A71: x | C71: Capex
B72: Turbine supply, EU | C72: EUR k/MW | D72: User 13-Oct-26 (Bana v3 E162) | F72: =IF(INDEX($H72:$W72,1,Scenario_Selected)="",$H72,INDEX($H72:$W72,1,Scenario_Selected)) -> 950 | H72: 950 | L72: =H72*(1+Sens_Step) -> 1045
B73: Turbine supply, CN | C73: EUR k/MW | D73: Bana v3 Inputs I162 | F73: =IF(INDEX($H73:$W73,1,Scenario_Selected)="",$H73,INDEX($H73:$W73,1,Scenario_Selected)) -> 500 | H73: 500 | L73: =H73*(1+Sens_Step) -> 550
B74: Other wind capex (install, foundations, BoP, owner, land) | C74: EUR k/MW | D74: Bana v3 Inputs E163:E166, E169:E170 | F74: =IF(INDEX($H74:$W74,1,Scenario_Selected)="",$H74,INDEX($H74:$W74,1,Scenario_Selected)) -> 355 | H74: 355
B75: Substation and 132 kV bay, EU | C75: EUR k | D75: Bana v3 Inputs E167 | F75: =IF(INDEX($H75:$W75,1,Scenario_Selected)="",$H75,INDEX($H75:$W75,1,Scenario_Selected)) -> 12000 | H75: 12000
B76: Substation and 132 kV bay, CN transformer | C76: EUR k | D76: Bana v3 Inputs I167 | F76: =IF(INDEX($H76:$W76,1,Scenario_Selected)="",$H76,INDEX($H76:$W76,1,Scenario_Selected)) -> 10800 | H76: 10800
B77: Contingency on wind and substation capex | C77: % | D77: Bana v3 Inputs E171 | F77: =IF(INDEX($H77:$W77,1,Scenario_Selected)="",$H77,INDEX($H77:$W77,1,Scenario_Selected)) -> 0.05 | H77: 0.05
B78: BESS capex, all-in (no BESS revenue or opex) | C78: EUR k/MWh | D78: User 15-Oct-26 | F78: =IF(INDEX($H78:$W78,1,Scenario_Selected)="",$H78,INDEX($H78:$W78,1,Scenario_Selected)) -> 100 | H78: 100
A80: x | C80: Operations
B81: Net P50 hours | C81: h/yr | D81: User 13-Oct-26 | F81: =IF(INDEX($H81:$W81,1,Scenario_Selected)="",$H81,INDEX($H81:$W81,1,Scenario_Selected)) -> 2600 | H81: 2600 | M81: =H81*(1-Sens_Step) -> 2340
B82: Curtailment | C82: % | D82: Bana v3 Inputs E181 | F82: =IF(INDEX($H82:$W82,1,Scenario_Selected)="",$H82,INDEX($H82:$W82,1,Scenario_Selected)) -> 0.02 | H82: 0.02
B83: Degradation per year | C83: % | D83: Bana v3 Inputs E182 | F83: =IF(INDEX($H83:$W83,1,Scenario_Selected)="",$H83,INDEX($H83:$W83,1,Scenario_Selected)) -> 0.003 | H83: 0.003
B84: PPA price at COD, whole life, 100 % of output | C84: EUR/MWh | D84: User 13-Oct-26 | F84: =IF(INDEX($H84:$W84,1,Scenario_Selected)="",$H84,INDEX($H84:$W84,1,Scenario_Selected)) -> 90 | H84: 90 | N84: 99
B85: PPA escalation | C85: % | D85: Bana v3 Inputs E192 | F85: =IF(INDEX($H85:$W85,1,Scenario_Selected)="",$H85,INDEX($H85:$W85,1,Scenario_Selected)) -> 0.01 | H85: 0.01
B86: Variable opex (balancing 4, grid 1) | C86: EUR/MWh | D86: Bana v3 Inputs E194:E195 | F86: =IF(INDEX($H86:$W86,1,Scenario_Selected)="",$H86,INDEX($H86:$W86,1,Scenario_Selected)) -> 5 | H86: 5
B87: Fixed opex (O&M, BoP, insurance, AM, property tax) | C87: EUR k/MW | D87: Bana v3 Inputs E201:E202, E204:E206 | F87: =IF(INDEX($H87:$W87,1,Scenario_Selected)="",$H87,INDEX($H87:$W87,1,Scenario_Selected)) -> 22 | H87: 22
B88: Land lease from NTP | C88: EUR k/MW | D88: Bana v3 Inputs E203 | F88: =IF(INDEX($H88:$W88,1,Scenario_Selected)="",$H88,INDEX($H88:$W88,1,Scenario_Selected)) -> 3 | H88: 3
B89: Administration | C89: EUR k | D89: Bana v3 Inputs E207 | F89: =IF(INDEX($H89:$W89,1,Scenario_Selected)="",$H89,INDEX($H89:$W89,1,Scenario_Selected)) -> 150 | H89: 150
B90: Opex contingency | C90: % | D90: Bana v3 Inputs E208 | F90: =IF(INDEX($H90:$W90,1,Scenario_Selected)="",$H90,INDEX($H90:$W90,1,Scenario_Selected)) -> 0.05 | H90: 0.05
B91: Opex escalation from the COD year | C91: % | D91: Bana v3 Inputs E209 | F91: =IF(INDEX($H91:$W91,1,Scenario_Selected)="",$H91,INDEX($H91:$W91,1,Scenario_Selected)) -> 0.025 | H91: 0.025
B92: MEKH supervisory fee | C92: % | D92: Bana v3 Inputs E196 | F92: =IF(INDEX($H92:$W92,1,Scenario_Selected)="",$H92,INDEX($H92:$W92,1,Scenario_Selected)) -> 0.001 | H92: 0.001
B93: Local business tax (HIPA), on revenue | C93: % | D93: Bana v3 Inputs E210 | F93: =IF(INDEX($H93:$W93,1,Scenario_Selected)="",$H93,INDEX($H93:$W93,1,Scenario_Selected)) -> 0.02 | H93: 0.02
B94: Innovation contribution, on the HIPA base | C94: % | D94: Act LXXVI of 2014, 15. § | F94: =IF(INDEX($H94:$W94,1,Scenario_Selected)="",$H94,INDEX($H94:$W94,1,Scenario_Selected)) -> 0.003 | H94: 0.003
A96: x | C96: Senior debt
B97: Debt per built wind MW (bank indication) | C97: EUR k/MW | D97: Raiffeisen 0.9 M€/MW; UniCredit pro rata 12y/1.30x | F97: =IF(INDEX($H97:$W97,1,Scenario_Selected)="",$H97,INDEX($H97:$W97,1,Scenario_Selected)) -> 900 | H97: 900 | I97: 710
B98: Maximum debt share of construction cost (LTC) | C98: % | D98: Info cap; Raiffeisen ~48-58 %, UniCredit lower | F98: =IF(INDEX($H98:$W98,1,Scenario_Selected)="",$H98,INDEX($H98:$W98,1,Scenario_Selected)) -> 0.7 | H98: 0.7
B99: Cash sweep, share of cash after debt service | C99: % | D99: Raiffeisen: significant, up to full | F99: =IF(INDEX($H99:$W99,1,Scenario_Selected)="",$H99,INDEX($H99:$W99,1,Scenario_Selected)) -> 0 | H99: 0 | V99: 1
B100: Info: DSCR for maximum debt, low | C100: x | D100: User 14-Oct-26 | F100: =IF(INDEX($H100:$W100,1,Scenario_Selected)="",$H100,INDEX($H100:$W100,1,Scenario_Selected)) -> 1.1 | H100: 1.1
B101: Info: DSCR for maximum debt, high | C101: x | D101: User 14-Oct-26 | F101: =IF(INDEX($H101:$W101,1,Scenario_Selected)="",$H101,INDEX($H101:$W101,1,Scenario_Selected)) -> 1.2 | H101: 1.2
B102: Minimum DSCR on PPA revenue (sizing) | C102: x | D102: Raiffeisen 1.20x; UniCredit 1.30x | F102: =IF(INDEX($H102:$W102,1,Scenario_Selected)="",$H102,INDEX($H102:$W102,1,Scenario_Selected)) -> 1.2 | H102: 1.2 | I102: 1.3
B103: Annuity tenor from COD | C103: years | D103: Raiffeisen 15 y; UniCredit 12 y | F103: =IF(INDEX($H103:$W103,1,Scenario_Selected)="",$H103,INDEX($H103:$W103,1,Scenario_Selected)) -> 15 | H103: 15 | I103: 12 | Q103: 10
B104: All-in fixed interest rate | C104: % | D104: Bana v3 E218; UniCredit margin >2.3 % | F104: =IF(INDEX($H104:$W104,1,Scenario_Selected)="",$H104,INDEX($H104:$W104,1,Scenario_Selected)) -> 0.05 | H104: 0.05 | P104: 0.06
B105: Upfront fee on the facility | C105: % | D105: Bana v3 Inputs E219 | F105: =IF(INDEX($H105:$W105,1,Scenario_Selected)="",$H105,INDEX($H105:$W105,1,Scenario_Selected)) -> 0.0175 | H105: 0.0175
B106: Commitment fee on undrawn debt | C106: % | D106: Bana v3 Inputs E222 | F106: =IF(INDEX($H106:$W106,1,Scenario_Selected)="",$H106,INDEX($H106:$W106,1,Scenario_Selected)) -> 0.009 | H106: 0.009
B107: DSRA: months of debt service, funded at COD | C107: months | D107: Bana v3 Inputs E268 | F107: =IF(INDEX($H107:$W107,1,Scenario_Selected)="",$H107,INDEX($H107:$W107,1,Scenario_Selected)) -> 6 | H107: 6
A109: x | C109: Macro control
B110: Solver Topics | C110: text | D110: COPY/PASTE topics for Solver.bas | F110: Tax_1,Tax_2
B111: GoalSeek Topics | C111: text | D111: Topics for GoalSeek.bas
C113: ***END***

Sheet Curves
B2: =Dashboard!$C$3&" – Time-series inputs" -> Project Bana – Time-series inputs
A5: x | C5: Tender scoring bands | E5: Kiírás Annex 3-4
E6: Weight / min | F6: Max | J6: Bands →
C7: ÖSZ-1 municipal one-off – lower bound | D7: EUR k/MW | E7: 10 | F7: 50 | J7: 10 | K7: 15 | L7: 20 | M7: 25 | N7: 30 | O7: 35 | P7: 40 | Q7: 45 | R7: 50
C8: ÖSZ-1 municipal one-off – lower bound included | D8: flag | J8: 0 | K8: 0 | L8: 0 | M8: 0 | N8: 0 | O8: 0 | P8: 0 | Q8: 0 | R8: 1
C9: ÖSZ-1 municipal one-off – inner points (below, bands) | D9: points | E9: 0.2 | J9: 0 | K9: 10 | L9: 20 | M9: 30 | N9: 40 | O9: 55 | P9: 70 | Q9: 80 | R9: 90 | S9: 100
C10: ÖSZ-2 community contribution – lower bound | D10: EUR/MWh | E10: 2 | F10: 3 | J10: 2 | K10: 2.1 | L10: 2.2 | M10: 2.3 | N10: 2.4 | O10: 2.5 | P10: 2.6 | Q10: 2.7 | R10: 2.8 | S10: 2.9 | T10: 3
C11: ÖSZ-2 community contribution – lower bound included | D11: flag | J11: 0 | K11: 0 | L11: 0 | M11: 0 | N11: 0 | O11: 0 | P11: 0 | Q11: 0 | R11: 0 | S11: 0 | T11: 1
C12: ÖSZ-2 community contribution – inner points (below, bands) | D12: points | E12: 0.15 | J12: 0 | K12: 5 | L12: 10 | M12: 20 | N12: 30 | O12: 40 | P12: 50 | Q12: 60 | R12: 70 | S12: 80 | T12: 90 | U12: 100
C13: ÖSZ-4 BESS ratio – lower bound | D13: % | E13: 0.05 | J13: 0.02 | K13: 0.05 | L13: 0.1 | M13: 0.15 | N13: 0.2 | O13: 0.25 | P13: 0.3 | Q13: 0.35 | R13: 0.4 | S13: 0.5
C14: ÖSZ-4 BESS ratio – lower bound included | D14: flag | J14: 0 | K14: 1 | L14: 1 | M14: 1 | N14: 1 | O14: 1 | P14: 1 | Q14: 1 | R14: 1 | S14: 0
C15: ÖSZ-4 BESS ratio – inner points (below, bands) | D15: points | E15: 0.15 | J15: 0 | K15: 10 | L15: 20 | M15: 30 | N15: 40 | O15: 50 | P15: 60 | Q15: 70 | R15: 80 | S15: 90 | T15: 100
C16: ÖSZ-3 overbuild – lower bound | D16: % | J16: 0.02 | K16: 0.05 | L16: 0.1 | M16: 0.15 | N16: 0.2 | O16: 0.25 | P16: 0.3 | Q16: 0.35 | R16: 0.4 | S16: 0.5
C17: ÖSZ-3 overbuild – lower bound included | D17: flag | J17: 0 | K17: 1 | L17: 1 | M17: 1 | N17: 1 | O17: 1 | P17: 1 | Q17: 1 | R17: 1 | S17: 0
C18: ÖSZ-3 overbuild – inner points (below, bands) | D18: points | E18: 0.1 | J18: 0 | K18: 10 | L18: 20 | M18: 30 | N18: 40 | O18: 50 | P18: 60 | Q18: 70 | R18: 80 | S18: 90 | T18: 100
C19: ÖSZ-6 performance security multiple – lower bound | D19: x | J19: 1 | K19: 1.2 | L19: 1.3 | M19: 1.4 | N19: 1.5 | O19: 1.6 | P19: 1.7 | Q19: 1.8 | R19: 1.9 | S19: 2
C20: ÖSZ-6 performance security multiple – lower bound included | D20: flag | J20: 0 | K20: 1 | L20: 1 | M20: 1 | N20: 1 | O20: 1 | P20: 1 | Q20: 1 | R20: 1 | S20: 1
C21: ÖSZ-6 performance security multiple – inner points (below, bands) | D21: points | E21: 0.05 | J21: 0 | K21: 10 | L21: 20 | M21: 30 | N21: 40 | O21: 50 | P21: 60 | Q21: 70 | R21: 80 | S21: 90 | T21: 100
C22: ÖSZ-5 partial award – inner points | D22: points | E22: 0.05 | J22: 100
C23: ÖSZ-8 shared connection – inner points | D23: points | E23: 0.05 | J23: 100
C24: ÖSZ-9 EU turbines – inner points | D24: points | E24: 0.15 | J24: 80
C25: ÖSZ-9 EU transformers – inner points | D25: points | J25: 20
C27: ***END***

Sheet Calc_1
A1: 1 | C1: Bid number
B2: =Dashboard!$C$3&" – Calculations – "&INDEX(Bid_Labels,1,$A$1) -> Project Bana – Calculations – European turbine
C3: Period start | D3: date | J3: =I$4+1 -> 46296 | K3: =J$4+1 -> 46388 | L3: =K$4+1 -> 46478 | M3: =L$4+1 -> 46569 | N3: =M$4+1 -> 46661 | O3: =N$4+1 -> 46753 | P3: =O$4+1 -> 46844 | Q3: =P$4+1 -> 46935 | ... EO3: =EN$4+1 -> 58623
C4: Period end | D4: date | I4: =In_Model_Start-1 -> 46295 | J4: =EOMONTH(J$3,Months_Per_Period-1) -> 46387 | K4: =EOMONTH(K$3,Months_Per_Period-1) -> 46477 | L4: =EOMONTH(L$3,Months_Per_Period-1) -> 46568 | M4: =EOMONTH(M$3,Months_Per_Period-1) -> 46660 | N4: =EOMONTH(N$3,Months_Per_Period-1) -> 46752 | O4: =EOMONTH(O$3,Months_Per_Period-1) -> 46843 | P4: =EOMONTH(P$3,Months_Per_Period-1) -> 46934 | Q4: =EOMONTH(Q$3,Months_Per_Period-1) -> 47026 | ... EO4: =EOMONTH(EO$3,Months_Per_Period-1) -> 58714
C5: Days in period | D5: days | J5: =J$4-J$3+1 -> 92 | K5: =K$4-K$3+1 -> 90 | L5: =L$4-L$3+1 -> 91 | M5: =M$4-M$3+1 -> 92 | N5: =N$4-N$3+1 -> 92 | O5: =O$4-O$3+1 -> 91 | P5: =P$4-P$3+1 -> 91 | Q5: =Q$4-Q$3+1 -> 92 | ... EO5: =EO$4-EO$3+1 -> 92
C6: Year fraction | D6: factor | J6: =J$5/Days_In_Year -> 0.25205479 | K6: =K$5/Days_In_Year -> 0.24657534 | L6: =L$5/Days_In_Year -> 0.24931507 | M6: =M$5/Days_In_Year -> 0.25205479 | N6: =N$5/Days_In_Year -> 0.25205479 | O6: =O$5/Days_In_Year -> 0.24931507 | P6: =P$5/Days_In_Year -> 0.24931507 | Q6: =Q$5/Days_In_Year -> 0.25205479 | ... EO6: =EO$5/Days_In_Year -> 0.25205479
C7: Year | D7: year | J7: =YEAR(J$4) -> 2026 | K7: =YEAR(K$4) -> 2027 | L7: =YEAR(L$4) -> 2027 | M7: =YEAR(M$4) -> 2027 | N7: =YEAR(N$4) -> 2027 | O7: =YEAR(O$4) -> 2028 | P7: =YEAR(P$4) -> 2028 | Q7: =YEAR(Q$4) -> 2028 | ... EO7: =YEAR(EO$4) -> 2060
C8: Period counter | D8: # | J8: =I$8+1 -> 1 | K8: =J$8+1 -> 2 | L8: =K$8+1 -> 3 | M8: =L$8+1 -> 4 | N8: =M$8+1 -> 5 | O8: =N$8+1 -> 6 | P8: =O$8+1 -> 7 | Q8: =P$8+1 -> 8 | ... EO8: =EN$8+1 -> 136
A11: x | C11: Timing and flags
C12: Construction share (NTP → COD) | D12: factor | E12: =In_NTP+1 -> 47027 | F12: =In_COD -> 47756 | I12: =SUM(J12:EO12) -> 1 | J12: =MAX(0,MIN($F12,J$4)-MAX($E12,J$3)+1)/($F12-$E12+1) -> 0 | K12: =MAX(0,MIN($F12,K$4)-MAX($E12,K$3)+1)/($F12-$E12+1) -> 0 | L12: =MAX(0,MIN($F12,L$4)-MAX($E12,L$3)+1)/($F12-$E12+1) -> 0 | M12: =MAX(0,MIN($F12,M$4)-MAX($E12,M$3)+1)/($F12-$E12+1) -> 0 | N12: =MAX(0,MIN($F12,N$4)-MAX($E12,N$3)+1)/($F12-$E12+1) -> 0 | O12: =MAX(0,MIN($F12,O$4)-MAX($E12,O$3)+1)/($F12-$E12+1) -> 0 | P12: =MAX(0,MIN($F12,P$4)-MAX($E12,P$3)+1)/($F12-$E12+1) -> 0 | Q12: =MAX(0,MIN($F12,Q$4)-MAX($E12,Q$3)+1)/($F12-$E12+1) -> 0 | ... EO12: =MAX(0,MIN($F12,EO$4)-MAX($E12,EO$3)+1)/($F12-$E12+1) -> 0
C13: Devex share (closing → NTP) | D13: factor | E13: =In_Closing+1 -> 46388 | F13: =In_NTP -> 47026 | I13: =SUM(J13:EO13) -> 1 | J13: =MAX(0,MIN($F13,J$4)-MAX($E13,J$3)+1)/($F13-$E13+1) -> 0 | K13: =MAX(0,MIN($F13,K$4)-MAX($E13,K$3)+1)/($F13-$E13+1) -> 0.14084507 | L13: =MAX(0,MIN($F13,L$4)-MAX($E13,L$3)+1)/($F13-$E13+1) -> 0.14241002 | M13: =MAX(0,MIN($F13,M$4)-MAX($E13,M$3)+1)/($F13-$E13+1) -> 0.14397496 | N13: =MAX(0,MIN($F13,N$4)-MAX($E13,N$3)+1)/($F13-$E13+1) -> 0.14397496 | O13: =MAX(0,MIN($F13,O$4)-MAX($E13,O$3)+1)/($F13-$E13+1) -> 0.14241002 | P13: =MAX(0,MIN($F13,P$4)-MAX($E13,P$3)+1)/($F13-$E13+1) -> 0.14241002 | Q13: =MAX(0,MIN($F13,Q$4)-MAX($E13,Q$3)+1)/($F13-$E13+1) -> 0.14397496 | ... EO13: =MAX(0,MIN($F13,EO$4)-MAX($E13,EO$3)+1)/($F13-$E13+1) -> 0
C14: COD | D14: flag | E14: =In_COD -> 47756 | I14: =SUM(J14:EO14) -> 1 | J14: =N(AND(J$3<=$E14,J$4>=$E14)) -> 0 | K14: =N(AND(K$3<=$E14,K$4>=$E14)) -> 0 | L14: =N(AND(L$3<=$E14,L$4>=$E14)) -> 0 | M14: =N(AND(M$3<=$E14,M$4>=$E14)) -> 0 | N14: =N(AND(N$3<=$E14,N$4>=$E14)) -> 0 | O14: =N(AND(O$3<=$E14,O$4>=$E14)) -> 0 | P14: =N(AND(P$3<=$E14,P$4>=$E14)) -> 0 | Q14: =N(AND(Q$3<=$E14,Q$4>=$E14)) -> 0 | ... EO14: =N(AND(EO$3<=$E14,EO$4>=$E14)) -> 0
C15: COD column on the timeline (buyer IRR start) | D15: # | E15: =MATCH(In_COD,$J$4:$EO$4,0) -> 16
C16: Operations | D16: flag | E16: =In_COD+1 -> 47757 | F16: =EDATE(In_COD,In_Life*Months_In_Year) -> 58714 | J16: =MAX(0,(MIN($F16,J$4)-MAX($E16,J$3)+1)/J$5) -> 0 | K16: =MAX(0,(MIN($F16,K$4)-MAX($E16,K$3)+1)/K$5) -> 0 | L16: =MAX(0,(MIN($F16,L$4)-MAX($E16,L$3)+1)/L$5) -> 0 | M16: =MAX(0,(MIN($F16,M$4)-MAX($E16,M$3)+1)/M$5) -> 0 | N16: =MAX(0,(MIN($F16,N$4)-MAX($E16,N$3)+1)/N$5) -> 0 | O16: =MAX(0,(MIN($F16,O$4)-MAX($E16,O$3)+1)/O$5) -> 0 | P16: =MAX(0,(MIN($F16,P$4)-MAX($E16,P$3)+1)/P$5) -> 0 | Q16: =MAX(0,(MIN($F16,Q$4)-MAX($E16,Q$3)+1)/Q$5) -> 0 | ... EO16: =MAX(0,(MIN($F16,EO$4)-MAX($E16,EO$3)+1)/EO$5) -> 1
C17: Land lease period (NTP → end of life) | D17: flag | E17: =In_NTP+1 -> 47027 | F17: =EDATE(In_COD,In_Life*Months_In_Year) -> 58714 | J17: =MAX(0,(MIN($F17,J$4)-MAX($E17,J$3)+1)/J$5) -> 0 | K17: =MAX(0,(MIN($F17,K$4)-MAX($E17,K$3)+1)/K$5) -> 0 | L17: =MAX(0,(MIN($F17,L$4)-MAX($E17,L$3)+1)/L$5) -> 0 | M17: =MAX(0,(MIN($F17,M$4)-MAX($E17,M$3)+1)/M$5) -> 0 | N17: =MAX(0,(MIN($F17,N$4)-MAX($E17,N$3)+1)/N$5) -> 0 | O17: =MAX(0,(MIN($F17,O$4)-MAX($E17,O$3)+1)/O$5) -> 0 | P17: =MAX(0,(MIN($F17,P$4)-MAX($E17,P$3)+1)/P$5) -> 0 | Q17: =MAX(0,(MIN($F17,Q$4)-MAX($E17,Q$3)+1)/Q$5) -> 0 | ... EO17: =MAX(0,(MIN($F17,EO$4)-MAX($E17,EO$3)+1)/EO$5) -> 1
C18: Debt repayment period | D18: flag | E18: =In_COD+1 -> 47757 | F18: =EDATE(In_COD,In_Debt_Tenor*Months_In_Year) -> 53235 | J18: =MAX(0,(MIN($F18,J$4)-MAX($E18,J$3)+1)/J$5) -> 0 | K18: =MAX(0,(MIN($F18,K$4)-MAX($E18,K$3)+1)/K$5) -> 0 | L18: =MAX(0,(MIN($F18,L$4)-MAX($E18,L$3)+1)/L$5) -> 0 | M18: =MAX(0,(MIN($F18,M$4)-MAX($E18,M$3)+1)/M$5) -> 0 | N18: =MAX(0,(MIN($F18,N$4)-MAX($E18,N$3)+1)/N$5) -> 0 | O18: =MAX(0,(MIN($F18,O$4)-MAX($E18,O$3)+1)/O$5) -> 0 | P18: =MAX(0,(MIN($F18,P$4)-MAX($E18,P$3)+1)/P$5) -> 0 | Q18: =MAX(0,(MIN($F18,Q$4)-MAX($E18,Q$3)+1)/Q$5) -> 0 | ... EO18: =MAX(0,(MIN($F18,EO$4)-MAX($E18,EO$3)+1)/EO$5) -> 0
C19: Last debt repayment | D19: flag | E19: =EDATE(In_COD,In_Debt_Tenor*Months_In_Year) -> 53235 | I19: =SUM(J19:EO19) -> 1 | J19: =N(AND(J$3<=$E19,J$4>=$E19)) -> 0 | K19: =N(AND(K$3<=$E19,K$4>=$E19)) -> 0 | L19: =N(AND(L$3<=$E19,L$4>=$E19)) -> 0 | M19: =N(AND(M$3<=$E19,M$4>=$E19)) -> 0 | N19: =N(AND(N$3<=$E19,N$4>=$E19)) -> 0 | O19: =N(AND(O$3<=$E19,O$4>=$E19)) -> 0 | P19: =N(AND(P$3<=$E19,P$4>=$E19)) -> 0 | Q19: =N(AND(Q$3<=$E19,Q$4>=$E19)) -> 0 | ... EO19: =N(AND(EO$3<=$E19,EO$4>=$E19)) -> 0
C20: Tax depreciation share | D20: factor | E20: =In_COD+1 -> 47757 | F20: =EDATE(In_COD,In_Dep_Years*Months_In_Year) -> 55061 | I20: =SUM(J20:EO20) -> 1 | J20: =MAX(0,MIN($F20,J$4)-MAX($E20,J$3)+1)/($F20-$E20+1) -> 0 | K20: =MAX(0,MIN($F20,K$4)-MAX($E20,K$3)+1)/($F20-$E20+1) -> 0 | L20: =MAX(0,MIN($F20,L$4)-MAX($E20,L$3)+1)/($F20-$E20+1) -> 0 | M20: =MAX(0,MIN($F20,M$4)-MAX($E20,M$3)+1)/($F20-$E20+1) -> 0 | N20: =MAX(0,MIN($F20,N$4)-MAX($E20,N$3)+1)/($F20-$E20+1) -> 0 | O20: =MAX(0,MIN($F20,O$4)-MAX($E20,O$3)+1)/($F20-$E20+1) -> 0 | P20: =MAX(0,MIN($F20,P$4)-MAX($E20,P$3)+1)/($F20-$E20+1) -> 0 | Q20: =MAX(0,MIN($F20,Q$4)-MAX($E20,Q$3)+1)/($F20-$E20+1) -> 0 | ... EO20: =MAX(0,MIN($F20,EO$4)-MAX($E20,EO$3)+1)/($F20-$E20+1) -> 0
C21: Operating year | D21: # | J21: =ROUNDUP(YEARFRAC(In_COD,J$4),0)*(J$4>In_COD) -> 0 | K21: =ROUNDUP(YEARFRAC(In_COD,K$4),0)*(K$4>In_COD) -> 0 | L21: =ROUNDUP(YEARFRAC(In_COD,L$4),0)*(L$4>In_COD) -> 0 | M21: =ROUNDUP(YEARFRAC(In_COD,M$4),0)*(M$4>In_COD) -> 0 | N21: =ROUNDUP(YEARFRAC(In_COD,N$4),0)*(N$4>In_COD) -> 0 | O21: =ROUNDUP(YEARFRAC(In_COD,O$4),0)*(O$4>In_COD) -> 0 | P21: =ROUNDUP(YEARFRAC(In_COD,P$4),0)*(P$4>In_COD) -> 0 | Q21: =ROUNDUP(YEARFRAC(In_COD,Q$4),0)*(Q$4>In_COD) -> 0 | ... EO21: =ROUNDUP(YEARFRAC(In_COD,EO$4),0)*(EO$4>In_COD) -> 30
C22: Debt compounding index (E: at COD, F: rate per period) | D22: factor | E22: =SUMIF($J$4:$EO$4,In_COD,$J22:$EO22) -> 1.2198895 | F22: =In_Debt_Rate*Months_Per_Period/Months_In_Year -> 0.0125 | J22: =(1+$F22)^J$8 -> 1.0125 | K22: =(1+$F22)^K$8 -> 1.0251562 | L22: =(1+$F22)^L$8 -> 1.0379707 | M22: =(1+$F22)^M$8 -> 1.0509453 | N22: =(1+$F22)^N$8 -> 1.0640822 | O22: =(1+$F22)^O$8 -> 1.0773832 | P22: =(1+$F22)^P$8 -> 1.0908505 | Q22: =(1+$F22)^Q$8 -> 1.1044861 | ... EO22: =(1+$F22)^EO$8 -> 5.4165697
A24: x | C24: Capacity (E: committed in the bid, F: built)
C25: Wind | D25: MW | E25: =In_MVA*(1+INDEX(Dash_Overbuild,1,$A$1)) -> 60 | F25: =In_MVA*(1+In_Overbuild_Built) -> 55
C26: BESS power, share of MVA (bid, or the set's commitment) | D26: % | E26: =IF(In_BESS_Set>0,In_BESS_Set,INDEX(Dash_BESS,1,$A$1)) -> 0.2
C27: BESS power | D27: MW | E27: =$E26*In_MVA -> 10 | F27: =$E27*In_BESS_Built -> 10
C28: BESS energy | D28: MWh | E28: =$E27*INDEX(Dash_BESS_Hours,1,$A$1) -> 40
C29: Grid-bottleneck loss on built wind | D29: % | E29: =($F25-In_MVA)/$F25*In_Bottleneck_Loss -> 0.0045454545
C30: Build shortfall vs commitment (E: wind, F: BESS) | D30: % | E30: =MAX(0,1-$F25/$E25) -> 0.083333333 | F30: =(1-In_BESS_Built)*($E27>0) -> 0
C31: Memo: connection right lost pro rata (GYIK 28/30) | D31: MVA | E31: =($E30>In_Tolerance_Cap)*$E30*In_MVA*(In_Sanction_Regime=1) -> 0
A33: x | C33: Tender points (E: commitment, F: weighted points)
C34: ÖSZ-1 municipal one-off | D34: EUR k/MW | E34: =INDEX(Dash_Municipal,1,$A$1) -> 50 | F34: =INDEX(Osz1_Pts,1+SUMPRODUCT((Osz1_LB<$E34)+(Osz1_LB=$E34)*Osz1_Incl))*Osz1_W -> 20
C35: ÖSZ-2 community contribution | D35: EUR/MWh | E35: =INDEX(Dash_Community,1,$A$1) -> 3 | F35: =INDEX(Osz2_Pts,1+SUMPRODUCT((Osz2_LB<$E35)+(Osz2_LB=$E35)*Osz2_Incl))*Osz2_W -> 15
C36: ÖSZ-3 overbuild | D36: % | E36: =INDEX(Dash_Overbuild,1,$A$1) -> 0.2 | F36: =INDEX(Osz3_Pts,1+SUMPRODUCT((Osz3_LB<$E36)+(Osz3_LB=$E36)*Osz3_Incl))*Osz3_W -> 5
C37: ÖSZ-4 BESS power, share of MVA | D37: % | E37: =$E26 -> 0.2 | F37: =INDEX(Osz4_Pts,1+SUMPRODUCT((Osz4_LB<$E37)+(Osz4_LB=$E37)*Osz4_Incl))*Osz4_W*($E37>=Osz4_Min) -> 7.5
C38: ÖSZ-5 partial award | D38: flag | E38: =INDEX(Dash_Partial,1,$A$1) -> 0 | F38: =$E38*Osz5_Pts*Osz5_W -> 0
C39: ÖSZ-6 performance security multiple | D39: x | E39: =INDEX(Dash_PB_Mult,1,$A$1) -> 1 | F39: =INDEX(Osz6_Pts,1+SUMPRODUCT((Osz6_LB<$E39)+(Osz6_LB=$E39)*Osz6_Incl))*Osz6_W -> 0
C40: ÖSZ-8 shared connection | D40: flag | E40: =INDEX(Dash_Shared,1,$A$1) -> 0 | F40: =$E40*Osz8_Pts*Osz8_W -> 0
C41: ÖSZ-9 EU turbines (1 = European turbine route) | D41: flag | E41: =INDEX(Dash_EU_Turbine,1,$A$1) -> 1 | F41: =$E41*Osz9a_Pts*Osz9_W -> 12
C42: ÖSZ-9 EU transformers | D42: flag | E42: =INDEX(Dash_EU_Transformer,1,$A$1) -> 0 | F42: =$E42*Osz9b_Pts*Osz9_W -> 0
C43: Points total | D43: points | E43: =ROUND(SUM($F34:$F42),Points_Decimals) -> 59.5
C44: European turbines installed (bid and delivered) | D44: flag | E44: =$E41*In_Deliver -> 1
C45: Failed tests (E: ÖSZ-1 and -2 range, F: ÖSZ-6, BESS ≤ wind, 4 h) | D45: # | E45: =($E34<>0)*($E34<Osz1_Min)+($E34>Osz1_Max)+($E35<>0)*($E35<Osz2_Min)+($E35>Osz2_Max) -> 0 | F45: =N($E39<1)+N($E27>$E25)+N($E28<$E27*In_Min_Hours) -> 0
A47: x | C47: Development, securities and fees (E: amount, F: date)
C48: Purchase price | D48: EUR k | E48: =In_Purchase_Price -> 4500 | F48: =In_Closing -> 46387 | I48: =SUM(J48:EO48) -> -4500 | J48: =-$E48*N(AND(J$3<=$F48,J$4>=$F48)) -> -4500 | K48: =-$E48*N(AND(K$3<=$F48,K$4>=$F48)) -> 0 | L48: =-$E48*N(AND(L$3<=$F48,L$4>=$F48)) -> 0 | M48: =-$E48*N(AND(M$3<=$F48,M$4>=$F48)) -> 0 | N48: =-$E48*N(AND(N$3<=$F48,N$4>=$F48)) -> 0 | O48: =-$E48*N(AND(O$3<=$F48,O$4>=$F48)) -> 0 | P48: =-$E48*N(AND(P$3<=$F48,P$4>=$F48)) -> 0 | Q48: =-$E48*N(AND(Q$3<=$F48,Q$4>=$F48)) -> 0 | ... EO48: =-$E48*N(AND(EO$3<=$F48,EO$4>=$F48)) -> 0
C49: Transaction and DD costs | D49: EUR k | E49: =In_DD -> 150 | F49: =In_Bid_Date -> 46325 | I49: =SUM(J49:EO49) -> -150 | J49: =-$E49*N(AND(J$3<=$F49,J$4>=$F49)) -> -150 | K49: =-$E49*N(AND(K$3<=$F49,K$4>=$F49)) -> 0 | L49: =-$E49*N(AND(L$3<=$F49,L$4>=$F49)) -> 0 | M49: =-$E49*N(AND(M$3<=$F49,M$4>=$F49)) -> 0 | N49: =-$E49*N(AND(N$3<=$F49,N$4>=$F49)) -> 0 | O49: =-$E49*N(AND(O$3<=$F49,O$4>=$F49)) -> 0 | P49: =-$E49*N(AND(P$3<=$F49,P$4>=$F49)) -> 0 | Q49: =-$E49*N(AND(Q$3<=$F49,Q$4>=$F49)) -> 0 | ... EO49: =-$E49*N(AND(EO$3<=$F49,EO$4>=$F49)) -> 0
C50: Devex | D50: EUR k | I50: =SUM(J50:EO50) -> -500 | J50: =-In_Devex*J13 -> 0 | K50: =-In_Devex*K13 -> -70.422535 | L50: =-In_Devex*L13 -> -71.205008 | M50: =-In_Devex*M13 -> -71.98748 | N50: =-In_Devex*N13 -> -71.98748 | O50: =-In_Devex*O13 -> -71.205008 | P50: =-In_Devex*P13 -> -71.205008 | Q50: =-In_Devex*Q13 -> -71.98748 | ... EO50: =-In_Devex*EO13 -> 0
C51: Security base | D51: mHUF | E51: =$E25*In_Bench_Wind+$E28*In_Bench_BESS -> 32360
C52: Participation fee (cash) | D52: EUR k | E52: =In_Part_Fee*Thousand/In_FX -> 8.2191781 | F52: =In_Bid_Date -> 46325 | I52: =SUM(J52:EO52) -> -8.2191781 | J52: =-$E52*N(AND(J$3<=$F52,J$4>=$F52)) -> -8.2191781 | K52: =-$E52*N(AND(K$3<=$F52,K$4>=$F52)) -> 0 | L52: =-$E52*N(AND(L$3<=$F52,L$4>=$F52)) -> 0 | M52: =-$E52*N(AND(M$3<=$F52,M$4>=$F52)) -> 0 | N52: =-$E52*N(AND(N$3<=$F52,N$4>=$F52)) -> 0 | O52: =-$E52*N(AND(O$3<=$F52,O$4>=$F52)) -> 0 | P52: =-$E52*N(AND(P$3<=$F52,P$4>=$F52)) -> 0 | Q52: =-$E52*N(AND(Q$3<=$F52,Q$4>=$F52)) -> 0 | ... EO52: =-$E52*N(AND(EO$3<=$F52,EO$4>=$F52)) -> 0
C53: Bid security outstanding (guarantee) | D53: EUR k | E53: =In_Bid_Rate*$E51*Thousand/In_FX -> 443.28767 | F53: =In_Bid_Date -> 46325 | J53: =$E53*MAX(0,(MIN(In_Decision_Date+In_PB_Days-1,J$4)-MAX($F53,J$3)+1)/J$5) -> 303.55569 | K53: =$E53*MAX(0,(MIN(In_Decision_Date+In_PB_Days-1,K$4)-MAX($F53,K$3)+1)/K$5) -> 221.64384 | L53: =$E53*MAX(0,(MIN(In_Decision_Date+In_PB_Days-1,L$4)-MAX($F53,L$3)+1)/L$5) -> 0 | M53: =$E53*MAX(0,(MIN(In_Decision_Date+In_PB_Days-1,M$4)-MAX($F53,M$3)+1)/M$5) -> 0 | N53: =$E53*MAX(0,(MIN(In_Decision_Date+In_PB_Days-1,N$4)-MAX($F53,N$3)+1)/N$5) -> 0 | O53: =$E53*MAX(0,(MIN(In_Decision_Date+In_PB_Days-1,O$4)-MAX($F53,O$3)+1)/O$5) -> 0 | P53: =$E53*MAX(0,(MIN(In_Decision_Date+In_PB_Days-1,P$4)-MAX($F53,P$3)+1)/P$5) -> 0 | Q53: =$E53*MAX(0,(MIN(In_Decision_Date+In_PB_Days-1,Q$4)-MAX($F53,Q$3)+1)/Q$5) -> 0 | ... EO53: =$E53*MAX(0,(MIN(In_Decision_Date+In_PB_Days-1,EO$4)-MAX($F53,EO$3)+1)/EO$5) -> 0
C54: Performance security outstanding (guarantee) | D54: EUR k | E54: =In_PB_Rate*$E39*$E51*Thousand/In_FX -> 2216.4384 | F54: =In_Decision_Date+In_PB_Days -> 46433 | J54: =$E54*MAX(0,(MIN(In_PB_Release,J$4)-MAX($F54,J$3)+1)/J$5) -> 0 | K54: =$E54*MAX(0,(MIN(In_PB_Release,K$4)-MAX($F54,K$3)+1)/K$5) -> 1108.2192 | L54: =$E54*MAX(0,(MIN(In_PB_Release,L$4)-MAX($F54,L$3)+1)/L$5) -> 2216.4384 | M54: =$E54*MAX(0,(MIN(In_PB_Release,M$4)-MAX($F54,M$3)+1)/M$5) -> 2216.4384 | N54: =$E54*MAX(0,(MIN(In_PB_Release,N$4)-MAX($F54,N$3)+1)/N$5) -> 2216.4384 | O54: =$E54*MAX(0,(MIN(In_PB_Release,O$4)-MAX($F54,O$3)+1)/O$5) -> 2216.4384 | P54: =$E54*MAX(0,(MIN(In_PB_Release,P$4)-MAX($F54,P$3)+1)/P$5) -> 2216.4384 | Q54: =$E54*MAX(0,(MIN(In_PB_Release,Q$4)-MAX($F54,Q$3)+1)/Q$5) -> 2216.4384 | ... EO54: =$E54*MAX(0,(MIN(In_PB_Release,EO$4)-MAX($F54,EO$3)+1)/EO$5) -> 0
C55: TSO connection-request security (cash) | D55: EUR k | E55: =In_TSO_Security*In_MVA*Thousand/In_FX -> 616.43836 | F55: =In_Decision_Date+In_PB_Days -> 46433 | I55: =SUM(J55:EO55) -> -616.43836 | J55: =-$E55*N(AND(J$3<=$F55,J$4>=$F55)) -> 0 | K55: =-$E55*N(AND(K$3<=$F55,K$4>=$F55)) -> -616.43836 | L55: =-$E55*N(AND(L$3<=$F55,L$4>=$F55)) -> 0 | M55: =-$E55*N(AND(M$3<=$F55,M$4>=$F55)) -> 0 | N55: =-$E55*N(AND(N$3<=$F55,N$4>=$F55)) -> 0 | O55: =-$E55*N(AND(O$3<=$F55,O$4>=$F55)) -> 0 | P55: =-$E55*N(AND(P$3<=$F55,P$4>=$F55)) -> 0 | Q55: =-$E55*N(AND(Q$3<=$F55,Q$4>=$F55)) -> 0 | ... EO55: =-$E55*N(AND(EO$3<=$F55,EO$4>=$F55)) -> 0
C56: Direct connection fee (cash) | D56: EUR k | E56: =In_Direct_Fee*Thousand/In_FX -> 1260.274 | F56: =In_HCSSZ_Date -> 47126 | I56: =SUM(J56:EO56) -> -1260.274 | J56: =-$E56*N(AND(J$3<=$F56,J$4>=$F56)) -> 0 | K56: =-$E56*N(AND(K$3<=$F56,K$4>=$F56)) -> 0 | L56: =-$E56*N(AND(L$3<=$F56,L$4>=$F56)) -> 0 | M56: =-$E56*N(AND(M$3<=$F56,M$4>=$F56)) -> 0 | N56: =-$E56*N(AND(N$3<=$F56,N$4>=$F56)) -> 0 | O56: =-$E56*N(AND(O$3<=$F56,O$4>=$F56)) -> 0 | P56: =-$E56*N(AND(P$3<=$F56,P$4>=$F56)) -> 0 | Q56: =-$E56*N(AND(Q$3<=$F56,Q$4>=$F56)) -> 0 | ... EO56: =-$E56*N(AND(EO$3<=$F56,EO$4>=$F56)) -> 0
C57: Indirect connection fee, net of TSO security | D57: EUR k | E57: =(In_Indirect_Fee-In_TSO_Security)*In_MVA*Thousand/In_FX -> 6894.5492 | F57: =In_HCSSZ_Date -> 47126 | I57: =SUM(J57:EO57) -> -6894.5492 | J57: =-$E57*N(AND(J$3<=$F57,J$4>=$F57)) -> 0 | K57: =-$E57*N(AND(K$3<=$F57,K$4>=$F57)) -> 0 | L57: =-$E57*N(AND(L$3<=$F57,L$4>=$F57)) -> 0 | M57: =-$E57*N(AND(M$3<=$F57,M$4>=$F57)) -> 0 | N57: =-$E57*N(AND(N$3<=$F57,N$4>=$F57)) -> 0 | O57: =-$E57*N(AND(O$3<=$F57,O$4>=$F57)) -> 0 | P57: =-$E57*N(AND(P$3<=$F57,P$4>=$F57)) -> 0 | Q57: =-$E57*N(AND(Q$3<=$F57,Q$4>=$F57)) -> 0 | ... EO57: =-$E57*N(AND(EO$3<=$F57,EO$4>=$F57)) -> 0
C58: Connection fees | D58: EUR k | I58: =SUM(J58:EO58) -> -8154.8232 | J58: =J56+J57 -> 0 | K58: =K56+K57 -> 0 | L58: =L56+L57 -> 0 | M58: =M56+M57 -> 0 | N58: =N56+N57 -> 0 | O58: =O56+O57 -> 0 | P58: =P56+P57 -> 0 | Q58: =Q56+Q57 -> 0 | ... EO58: =EO56+EO57 -> 0
C59: Guarantee fees (E: to COD) | D59: EUR k | E59: =SUMIF($J$4:$EO$4,"<="&In_COD,$J59:$EO59) -> -490.26402 | I59: =SUM(J59:EO59) -> -822.91195 | J59: =-(J53+J54)*In_Guarantee_Fee*J$5/Days_In_Year -> -4.59076 | K59: =-(K53+K54)*In_Guarantee_Fee*K$5/Days_In_Year -> -19.674686 | L59: =-(L53+L54)*In_Guarantee_Fee*L$5/Days_In_Year -> -33.155489 | M59: =-(M53+M54)*In_Guarantee_Fee*M$5/Days_In_Year -> -33.519835 | N59: =-(N53+N54)*In_Guarantee_Fee*N$5/Days_In_Year -> -33.519835 | O59: =-(O53+O54)*In_Guarantee_Fee*O$5/Days_In_Year -> -33.155489 | P59: =-(P53+P54)*In_Guarantee_Fee*P$5/Days_In_Year -> -33.155489 | Q59: =-(Q53+Q54)*In_Guarantee_Fee*Q$5/Days_In_Year -> -33.519835 | ... EO59: =-(EO53+EO54)*In_Guarantee_Fee*EO$5/Days_In_Year -> 0
C60: Performance security by technology (E: wind, F: BESS) | D60: EUR k | E60: =$E54*$E25*In_Bench_Wind/$E51 -> 1668.4932 | F60: =$E54-$E60 -> 547.94521
C61: PB call (E: pro rata above the tolerance, F: full call) | D61: EUR k | E61: =($E30>In_Tolerance_Cap)*$E30*$E60+($F30>In_Tolerance_Cap)*$F30*$F60 -> 0 | F61: =(($E30+$F30>0)+(In_Deliver=0)>0)*$E54 -> 2216.4384
C62: PB call paid, selected regime (E: date) | D62: EUR k | E62: =EDATE(In_COD,In_Sanction_Lag) -> 47937 | I62: =SUM(J62:EO62) -> 0 | J62: =-CHOOSE(In_Sanction_Regime,$E61,$F61)*N(AND(J$3<=$E62,J$4>=$E62)) -> 0 | K62: =-CHOOSE(In_Sanction_Regime,$E61,$F61)*N(AND(K$3<=$E62,K$4>=$E62)) -> 0 | L62: =-CHOOSE(In_Sanction_Regime,$E61,$F61)*N(AND(L$3<=$E62,L$4>=$E62)) -> 0 | M62: =-CHOOSE(In_Sanction_Regime,$E61,$F61)*N(AND(M$3<=$E62,M$4>=$E62)) -> 0 | N62: =-CHOOSE(In_Sanction_Regime,$E61,$F61)*N(AND(N$3<=$E62,N$4>=$E62)) -> 0 | O62: =-CHOOSE(In_Sanction_Regime,$E61,$F61)*N(AND(O$3<=$E62,O$4>=$E62)) -> 0 | P62: =-CHOOSE(In_Sanction_Regime,$E61,$F61)*N(AND(P$3<=$E62,P$4>=$E62)) -> 0 | Q62: =-CHOOSE(In_Sanction_Regime,$E61,$F61)*N(AND(Q$3<=$E62,Q$4>=$E62)) -> 0 | ... EO62: =-CHOOSE(In_Sanction_Regime,$E61,$F61)*N(AND(EO$3<=$E62,EO$4>=$E62)) -> 0
C63: Development cash flow | D63: EUR k | I63: =SUM(J63:EO63) -> -6597.5695 | J63: =J48+J49+J50+J52+J55+J59 -> -4662.8099 | K63: =K48+K49+K50+K52+K55+K59 -> -706.53558 | L63: =L48+L49+L50+L52+L55+L59 -> -104.3605 | M63: =M48+M49+M50+M52+M55+M59 -> -105.50732 | N63: =N48+N49+N50+N52+N55+N59 -> -105.50732 | O63: =O48+O49+O50+O52+O55+O59 -> -104.3605 | P63: =P48+P49+P50+P52+P55+P59 -> -104.3605 | Q63: =Q48+Q49+Q50+Q52+Q55+Q59 -> -105.50732 | ... EO63: =EO48+EO49+EO50+EO52+EO55+EO59 -> 0
A65: x | C65: Construction
C66: Turbine supply, this route | D66: EUR k/MW | E66: =IF($E44=1,In_Turbine,In_Turbine_CN) -> 950
C67: Substation and 132 kV bay, this route | D67: EUR k | E67: =IF($E44=1,In_Substation,In_Substation_CN) -> 12000
C68: Capex (E: total) | D68: EUR k | E68: =(($E66+In_Other_Wind)*$F25+$E67)*(1+In_Capex_Contingency)+In_BESS_Capex*$E28*In_BESS_Built -> 91963.75 | I68: =SUM(J68:EO68) -> -91963.75 | J68: =-$E68*J12 -> 0 | K68: =-$E68*K12 -> 0 | L68: =-$E68*L12 -> 0 | M68: =-$E68*M12 -> 0 | N68: =-$E68*N12 -> 0 | O68: =-$E68*O12 -> 0 | P68: =-$E68*P12 -> 0 | Q68: =-$E68*Q12 -> 0 | ... EO68: =-$E68*EO12 -> 0
C69: Municipal one-off at COD | D69: EUR k | E69: =$E34*In_MVA*In_Deliver -> 2500 | I69: =SUM(J69:EO69) -> -2500 | J69: =-$E69*J14 -> 0 | K69: =-$E69*K14 -> 0 | L69: =-$E69*L14 -> 0 | M69: =-$E69*M14 -> 0 | N69: =-$E69*N14 -> 0 | O69: =-$E69*O14 -> 0 | P69: =-$E69*P14 -> 0 | Q69: =-$E69*Q14 -> 0 | ... EO69: =-$E69*EO14 -> 0
C70: Construction cost (E: compounded to COD at the debt rate) | D70: EUR k | E70: =SUMPRODUCT($J70:$EO70/$J22:$EO22)*$E22 -> -107373.63 | I70: =SUM(J70:EO70) -> -102618.57 | J70: =J68+J58+J69 -> 0 | K70: =K68+K58+K69 -> 0 | L70: =L68+L58+L69 -> 0 | M70: =M68+M58+M69 -> 0 | N70: =N68+N58+N69 -> 0 | O70: =O68+O58+O69 -> 0 | P70: =P68+P58+P69 -> 0 | Q70: =Q68+Q58+Q69 -> 0 | ... EO70: =EO68+EO58+EO69 -> 0
A72: x | C72: Operations
C73: Opex escalation index | D73: factor | J73: =(1+In_Opex_Esc)^(J$7-YEAR(In_COD)) -> 0.90595064 | K73: =(1+In_Opex_Esc)^(K$7-YEAR(In_COD)) -> 0.92859941 | L73: =(1+In_Opex_Esc)^(L$7-YEAR(In_COD)) -> 0.92859941 | M73: =(1+In_Opex_Esc)^(M$7-YEAR(In_COD)) -> 0.92859941 | N73: =(1+In_Opex_Esc)^(N$7-YEAR(In_COD)) -> 0.92859941 | O73: =(1+In_Opex_Esc)^(O$7-YEAR(In_COD)) -> 0.9518144 | P73: =(1+In_Opex_Esc)^(P$7-YEAR(In_COD)) -> 0.9518144 | Q73: =(1+In_Opex_Esc)^(Q$7-YEAR(In_COD)) -> 0.9518144 | ... EO73: =(1+In_Opex_Esc)^(EO$7-YEAR(In_COD)) -> 2.0975676
C74: PPA price | D74: EUR/MWh | J74: =In_PPA_Price*(1+In_PPA_Esc)^(J$7-YEAR(In_COD)) -> 86.488231 | K74: =In_PPA_Price*(1+In_PPA_Esc)^(K$7-YEAR(In_COD)) -> 87.353113 | L74: =In_PPA_Price*(1+In_PPA_Esc)^(L$7-YEAR(In_COD)) -> 87.353113 | M74: =In_PPA_Price*(1+In_PPA_Esc)^(M$7-YEAR(In_COD)) -> 87.353113 | N74: =In_PPA_Price*(1+In_PPA_Esc)^(N$7-YEAR(In_COD)) -> 87.353113 | O74: =In_PPA_Price*(1+In_PPA_Esc)^(O$7-YEAR(In_COD)) -> 88.226644 | P74: =In_PPA_Price*(1+In_PPA_Esc)^(P$7-YEAR(In_COD)) -> 88.226644 | Q74: =In_PPA_Price*(1+In_PPA_Esc)^(Q$7-YEAR(In_COD)) -> 88.226644 | ... EO74: =In_PPA_Price*(1+In_PPA_Esc)^(EO$7-YEAR(In_COD)) -> 121.3064
C75: Net generation (E: first full year) | D75: MWh | E75: =SUMIF($J$7:$EO$7,YEAR(In_COD)+1,$J75:$EO75) -> 139397.51 | I75: =SUM(J75:EO75) -> 4010958.4 | J75: =$F25*In_P50_Hours*(1-In_Curtailment)*(1-$E29)*(1-In_Degradation)^(J21-1)*J16*J$6 -> 0 | K75: =$F25*In_P50_Hours*(1-In_Curtailment)*(1-$E29)*(1-In_Degradation)^(K21-1)*K16*K$6 -> 0 | L75: =$F25*In_P50_Hours*(1-In_Curtailment)*(1-$E29)*(1-In_Degradation)^(L21-1)*L16*L$6 -> 0 | M75: =$F25*In_P50_Hours*(1-In_Curtailment)*(1-$E29)*(1-In_Degradation)^(M21-1)*M16*M$6 -> 0 | N75: =$F25*In_P50_Hours*(1-In_Curtailment)*(1-$E29)*(1-In_Degradation)^(N21-1)*N16*N$6 -> 0 | O75: =$F25*In_P50_Hours*(1-In_Curtailment)*(1-$E29)*(1-In_Degradation)^(O21-1)*O16*O$6 -> 0 | P75: =$F25*In_P50_Hours*(1-In_Curtailment)*(1-$E29)*(1-In_Degradation)^(P21-1)*P16*P$6 -> 0 | Q75: =$F25*In_P50_Hours*(1-In_Curtailment)*(1-$E29)*(1-In_Degradation)^(Q21-1)*Q16*Q$6 -> 0 | ... EO75: =$F25*In_P50_Hours*(1-In_Curtailment)*(1-$E29)*(1-In_Degradation)^(EO21-1)*EO16*EO$6 -> 32228.352
C76: Revenue (E: first full year) | D76: EUR k | E76: =SUMIF($J$7:$EO$7,YEAR(In_COD)+1,$J76:$EO76) -> 12671.234 | I76: =SUM(J76:EO76) -> 420752.71 | J76: =J75*J74/Thousand -> 0 | K76: =K75*K74/Thousand -> 0 | L76: =L75*L74/Thousand -> 0 | M76: =M75*M74/Thousand -> 0 | N76: =N75*N74/Thousand -> 0 | O76: =O75*O74/Thousand -> 0 | P76: =P75*P74/Thousand -> 0 | Q76: =Q75*Q74/Thousand -> 0 | ... EO76: =EO75*EO74/Thousand -> 3909.5055
C77: Variable opex (balancing, grid) | D77: EUR k | I77: =SUM(J77:EO77) -> -29733.419 | J77: =-In_Var_Opex*J75*J73/Thousand -> 0 | K77: =-In_Var_Opex*K75*K73/Thousand -> 0 | L77: =-In_Var_Opex*L75*L73/Thousand -> 0 | M77: =-In_Var_Opex*M75*M73/Thousand -> 0 | N77: =-In_Var_Opex*N75*N73/Thousand -> 0 | O77: =-In_Var_Opex*O75*O73/Thousand -> 0 | P77: =-In_Var_Opex*P75*P73/Thousand -> 0 | Q77: =-In_Var_Opex*Q75*Q73/Thousand -> 0 | ... EO77: =-In_Var_Opex*EO75*EO73/Thousand -> -338.00573
C78: Fixed opex and administration | D78: EUR k | I78: =SUM(J78:EO78) -> -60869.52 | J78: =-(In_Fixed_Opex*$F25+In_Admin)*J73*J16*J$6 -> 0 | K78: =-(In_Fixed_Opex*$F25+In_Admin)*K73*K16*K$6 -> 0 | L78: =-(In_Fixed_Opex*$F25+In_Admin)*L73*L16*L$6 -> 0 | M78: =-(In_Fixed_Opex*$F25+In_Admin)*M73*M16*M$6 -> 0 | N78: =-(In_Fixed_Opex*$F25+In_Admin)*N73*N16*N$6 -> 0 | O78: =-(In_Fixed_Opex*$F25+In_Admin)*O73*O16*O$6 -> 0 | P78: =-(In_Fixed_Opex*$F25+In_Admin)*P73*P16*P$6 -> 0 | Q78: =-(In_Fixed_Opex*$F25+In_Admin)*Q73*Q16*Q$6 -> 0 | ... EO78: =-(In_Fixed_Opex*$F25+In_Admin)*EO73*EO16*EO$6 -> -719.03467
C79: Land lease | D79: EUR k | I79: =SUM(J79:EO79) -> -7708.8766 | J79: =-In_Lease*$F25*J73*J17*J$6 -> 0 | K79: =-In_Lease*$F25*K73*K17*K$6 -> 0 | L79: =-In_Lease*$F25*L73*L17*L$6 -> 0 | M79: =-In_Lease*$F25*M73*M17*M$6 -> 0 | N79: =-In_Lease*$F25*N73*N17*N$6 -> 0 | O79: =-In_Lease*$F25*O73*O17*O$6 -> 0 | P79: =-In_Lease*$F25*P73*P17*P$6 -> 0 | Q79: =-In_Lease*$F25*Q73*Q17*Q$6 -> 0 | ... EO79: =-In_Lease*$F25*EO73*EO17*EO$6 -> -87.235824
C80: MEKH fee, HIPA and innovation contribution | D80: EUR k | I80: =SUM(J80:EO80) -> -10098.065 | J80: =-J76*(In_MEKH+In_HIPA+In_Innovation) -> 0 | K80: =-K76*(In_MEKH+In_HIPA+In_Innovation) -> 0 | L80: =-L76*(In_MEKH+In_HIPA+In_Innovation) -> 0 | M80: =-M76*(In_MEKH+In_HIPA+In_Innovation) -> 0 | N80: =-N76*(In_MEKH+In_HIPA+In_Innovation) -> 0 | O80: =-O76*(In_MEKH+In_HIPA+In_Innovation) -> 0 | P80: =-P76*(In_MEKH+In_HIPA+In_Innovation) -> 0 | Q80: =-Q76*(In_MEKH+In_HIPA+In_Innovation) -> 0 | ... EO80: =-EO76*(In_MEKH+In_HIPA+In_Innovation) -> -93.828131
C81: Opex contingency | D81: EUR k | I81: =SUM(J81:EO81) -> -4936.6284 | J81: =In_Opex_Contingency*(J77+J78+J79-J76*In_MEKH) -> 0 | K81: =In_Opex_Contingency*(K77+K78+K79-K76*In_MEKH) -> 0 | L81: =In_Opex_Contingency*(L77+L78+L79-L76*In_MEKH) -> 0 | M81: =In_Opex_Contingency*(M77+M78+M79-M76*In_MEKH) -> 0 | N81: =In_Opex_Contingency*(N77+N78+N79-N76*In_MEKH) -> 0 | O81: =In_Opex_Contingency*(O77+O78+O79-O76*In_MEKH) -> 0 | P81: =In_Opex_Contingency*(P77+P78+P79-P76*In_MEKH) -> 0 | Q81: =In_Opex_Contingency*(Q77+Q78+Q79-Q76*In_MEKH) -> 0 | ... EO81: =In_Opex_Contingency*(EO77+EO78+EO79-EO76*In_MEKH) -> -57.409287
C82: Community contribution (ÖSZ-2) | D82: EUR k | I82: =SUM(J82:EO82) -> -12032.875 | J82: =-$E35*In_Deliver*J75/Thousand -> 0 | K82: =-$E35*In_Deliver*K75/Thousand -> 0 | L82: =-$E35*In_Deliver*L75/Thousand -> 0 | M82: =-$E35*In_Deliver*M75/Thousand -> 0 | N82: =-$E35*In_Deliver*N75/Thousand -> 0 | O82: =-$E35*In_Deliver*O75/Thousand -> 0 | P82: =-$E35*In_Deliver*P75/Thousand -> 0 | Q82: =-$E35*In_Deliver*Q75/Thousand -> 0 | ... EO82: =-$E35*In_Deliver*EO75/Thousand -> -96.685057
C83: EBITDA (E: first full year) | D83: EUR k | E83: =SUMIF($J$7:$EO$7,YEAR(In_COD)+1,$J83:$EO83) -> 9556.8841 | I83: =SUM(J83:EO83) -> 295373.33 | J83: =SUM(J76:J82) -> 0 | K83: =SUM(K76:K82) -> 0 | L83: =SUM(L76:L82) -> 0 | M83: =SUM(M76:M82) -> 0 | N83: =SUM(N76:N82) -> 0 | O83: =SUM(O76:O82) -> 0 | P83: =SUM(P76:P82) -> 0 | Q83: =SUM(Q76:Q82) -> 0 | ... EO83: =SUM(EO76:EO82) -> 2517.3068
A85: x | C85: Debt sizing on CFADS
C86: Corporate income tax – paste (macro) | D86: EUR k | J86: 0 | K86: 0 | L86: 0 | M86: 0 | N86: 0 | O86: 0 | P86: 0 | Q86: 0 | R86: 0 | S86: 0 | T86: 0 | U86: 0 | V86: 0 | W86: 0 | X86: 0 | Y86: 0 | Z86: -26.244278 | AA86: -26.375957 | AB86: -27.709299 | AC86: -29.049272 | AD86: -28.957535 | AE86: -29.902243 | AF86: -30.45974 | AG86: -31.833246 | AH86: -31.765183 | AI86: -31.906 | AJ86: -40.022579 | AK86: -74.458405 | AL86: -74.372427 | AM86: -74.557499 | AN86: -77.485418 | AO86: -80.42873 | AP86: -80.395839 | AQ86: -80.596242 | AR86: -83.598229 | AS86: -86.616394 | AT86: -86.639681 | AU86: -88.576871 | AV86: -89.937041 | AW86: -93.032933 | AX86: -93.11565 | AY86: -93.355078 | AZ86: -96.513855 | BA86: -99.690501 | BB86: -99.836066 | BC86: -100.09951 | BD86: -103.34131 | BE86: -106.6019 | BF86: -106.81391 | BG86: -107.10459 | BH86: -110.43273 | BI86: -113.78061 | BJ86: -114.06284 | BK86: -116.14287 | BL86: -117.80213 | BM86: -121.24084 | BN86: -121.59726 | BO86: -121.95283 | BP86: -125.46429 | BQ86: -128.99754 | BR86: -129.43234 | BS86: -129.82595 | BT86: -133.43475 | BU86: -137.06647 | BV86: -137.58403 | BW86: -138.01969 | BX86: -141.72991 | BY86: -145.4642 | BZ86: -146.06915 | CA86: -148.34289 | CB86: -150.367 | CC86: -154.20822 | CD86: -154.90541 | CE86: -155.43809 | CF86: -159.3642 | CG86: -163.31691 | CH86: -164.11144 | CI86: -162.49156 | CJ86: -164.29702 | CK86: -166.10249 | CL86: -164.70788 | CM86: -163.03593 | CN86: -164.84744 | CO86: -166.65895 | CP86: -165.25594 | CQ86: -165.34843 | CR86: -165.34843 | CS86: -167.16544 | CT86: -165.754 | CU86: -163.97641 | CV86: -165.79837 | CW86: -167.62033 | CX86: -166.20044 | CY86: -164.36927 | CZ86: -166.19559 | DA86: -168.02192 | DB86: -375.4867 | DC86: -369.06028 | DD86: -373.16095 | DE86: -377.26162 | DF86: -375.82478 | DG86: -373.44756 | DH86: -373.44756 | DI86: -377.55138 | DJ86: -376.10605 | DK86: -369.56986 | DL86: -373.67619 | DM86: -377.78253 | DN86: -376.32869 | DO86: -369.73681 | DP86: -373.845 | DQ86: -377.95318 | DR86: -376.49082 | DS86: -369.84271 | DT86: -373.95207 | DU86: -378.06144 | DV86: -376.59054 | DW86: -373.99548 | DX86: -373.99548 | DY86: -378.10532 | DZ86: -376.62587 | EA86: -369.86362 | EB86: -373.97322 | EC86: -378.08282 | ED86: -376.59481 | EE86: -369.77464 | EF86: -373.88325 | EG86: -377.99186 | EH86: -376.49527 | EI86: -369.61661 | EJ86: -373.72346 | EK86: -377.83031 | EL86: -376.32515 | EM86: -373.49171 | EN86: -373.49171 | EO86: -377.59601
C87: CFADS (EBITDA, guarantee fees, tax; after COD) | D87: EUR k | I87: =SUM(J87:EO87) -> 271159.47 | J87: =(J83+J59+J86)*(J$4>In_COD) -> 0 | K87: =(K83+K59+K86)*(K$4>In_COD) -> 0 | L87: =(L83+L59+L86)*(L$4>In_COD) -> 0 | M87: =(M83+M59+M86)*(M$4>In_COD) -> 0 | N87: =(N83+N59+N86)*(N$4>In_COD) -> 0 | O87: =(O83+O59+O86)*(O$4>In_COD) -> 0 | P87: =(P83+P59+P86)*(P$4>In_COD) -> 0 | Q87: =(Q83+Q59+Q86)*(Q$4>In_COD) -> 0 | ... EO87: =(EO83+EO59+EO86)*(EO$4>In_COD) -> 2139.7107
C88: CFADS ÷ target DSCR (E: annuity debt capacity, F: lowest quarter) | D88: EUR k | E88: =PV($F22,In_Debt_Tenor*Months_In_Year/Months_Per_Period,-$F88) -> 80084.339 | F88: =MIN($J88:$EO88) -> 1905.2008 | J88: =IF(J18=1,J87/In_DSCR,"") | K88: =IF(K18=1,K87/In_DSCR,"") | L88: =IF(L18=1,L87/In_DSCR,"") | M88: =IF(M18=1,M87/In_DSCR,"") | N88: =IF(N18=1,N87/In_DSCR,"") | O88: =IF(O18=1,O87/In_DSCR,"") | P88: =IF(P18=1,P87/In_DSCR,"") | Q88: =IF(Q18=1,Q87/In_DSCR,"") | ... EO88: =IF(EO18=1,EO87/In_DSCR,"")
C89: Debt quantum: per built wind MW | D89: EUR k | E89: =In_Debt_Per_MW*$F25 -> 49500
C90: Debt share of construction cost (E), share of capacity used (F) | D90: % | E90: =MIN(In_Gearing,$E88/-$E70,$E89/-$E70) -> 0.46100704 | F90: =$E90*-$E70/$E88 -> 0.61809838
C91: Debt at COD (E) and level annuity per quarter (F) | D91: EUR k | E91: =$E90*-$E70 -> 49500 | F91: =PMT($F22,In_Debt_Tenor*Months_In_Year/Months_Per_Period,-$E91) -> 1177.6015
A93: x | C93: Senior debt
C94: Interest paid | D94: EUR k | I94: =SUM(J94:EO94) -> -21156.092 | J94: =-I103*$F22*(J$4>In_COD) -> 0 | K94: =-J103*$F22*(K$4>In_COD) -> 0 | L94: =-K103*$F22*(L$4>In_COD) -> 0 | M94: =-L103*$F22*(M$4>In_COD) -> 0 | N94: =-M103*$F22*(N$4>In_COD) -> 0 | O94: =-N103*$F22*(O$4>In_COD) -> 0 | P94: =-O103*$F22*(P$4>In_COD) -> 0 | Q94: =-P103*$F22*(Q$4>In_COD) -> 0 | ... EO94: =-EN103*$F22*(EO$4>In_COD) -> 0
C95: Scheduled repayment (annuity) | D95: EUR k | I95: =SUM(J95:EO95) -> -49500 | J95: =-MIN(I103,$F91+J94)*J18 -> 0 | K95: =-MIN(J103,$F91+K94)*K18 -> 0 | L95: =-MIN(K103,$F91+L94)*L18 -> 0 | M95: =-MIN(L103,$F91+M94)*M18 -> 0 | N95: =-MIN(M103,$F91+N94)*N18 -> 0 | O95: =-MIN(N103,$F91+O94)*O18 -> 0 | P95: =-MIN(O103,$F91+P94)*P18 -> 0 | Q95: =-MIN(P103,$F91+Q94)*Q18 -> 0 | ... EO95: =-MIN(EN103,$F91+EO94)*EO18 -> 0
C96: Scheduled debt service | D96: EUR k | I96: =SUM(J96:EO96) -> -70656.092 | J96: =J94+J95 -> 0 | K96: =K94+K95 -> 0 | L96: =L94+L95 -> 0 | M96: =M94+M95 -> 0 | N96: =N94+N95 -> 0 | O96: =O94+O95 -> 0 | P96: =P94+P95 -> 0 | Q96: =Q94+Q95 -> 0 | ... EO96: =EO94+EO95 -> 0
C97: Cash sweep | D97: EUR k | I97: =SUM(J97:EO97) -> 0 | J97: =-MIN(I103+J95,In_Sweep*MAX(0,J87+J96))*(J$4>In_COD) -> 0 | K97: =-MIN(J103+K95,In_Sweep*MAX(0,K87+K96))*(K$4>In_COD) -> 0 | L97: =-MIN(K103+L95,In_Sweep*MAX(0,L87+L96))*(L$4>In_COD) -> 0 | M97: =-MIN(L103+M95,In_Sweep*MAX(0,M87+M96))*(M$4>In_COD) -> 0 | N97: =-MIN(M103+N95,In_Sweep*MAX(0,N87+N96))*(N$4>In_COD) -> 0 | O97: =-MIN(N103+O95,In_Sweep*MAX(0,O87+O96))*(O$4>In_COD) -> 0 | P97: =-MIN(O103+P95,In_Sweep*MAX(0,P87+P96))*(P$4>In_COD) -> 0 | Q97: =-MIN(P103+Q95,In_Sweep*MAX(0,Q87+Q96))*(Q$4>In_COD) -> 0 | ... EO97: =-MIN(EN103+EO95,In_Sweep*MAX(0,EO87+EO96))*(EO$4>In_COD) -> 0
C98: Debt service incl. sweep | D98: EUR k | I98: =SUM(J98:EO98) -> -70656.092 | J98: =J96+J97 -> 0 | K98: =K96+K97 -> 0 | L98: =L96+L97 -> 0 | M98: =M96+M97 -> 0 | N98: =N96+N97 -> 0 | O98: =O96+O97 -> 0 | P98: =P96+P97 -> 0 | Q98: =Q96+Q97 -> 0 | ... EO98: =EO96+EO97 -> 0
C99: Opening balance | D99: EUR k | J99: =I103 -> 0 | K99: =J103 -> 0 | L99: =K103 -> 0 | M99: =L103 -> 0 | N99: =M103 -> 0 | O99: =N103 -> 0 | P99: =O103 -> 0 | Q99: =P103 -> 0 | ... EO99: =EN103 -> 0
C100: Drawdown | D100: EUR k | I100: =SUM(J100:EO100) -> 47307.884 | J100: =-$E90*J70 -> 0 | K100: =-$E90*K70 -> 0 | L100: =-$E90*L70 -> 0 | M100: =-$E90*M70 -> 0 | N100: =-$E90*N70 -> 0 | O100: =-$E90*O70 -> 0 | P100: =-$E90*P70 -> 0 | Q100: =-$E90*Q70 -> 0 | ... EO100: =-$E90*EO70 -> 0
C101: Interest capitalised | D101: EUR k | I101: =SUM(J101:EO101) -> 2192.1156 | J101: =J99*$F22*(J$4<=In_COD) -> 0 | K101: =K99*$F22*(K$4<=In_COD) -> 0 | L101: =L99*$F22*(L$4<=In_COD) -> 0 | M101: =M99*$F22*(M$4<=In_COD) -> 0 | N101: =N99*$F22*(N$4<=In_COD) -> 0 | O101: =O99*$F22*(O$4<=In_COD) -> 0 | P101: =P99*$F22*(P$4<=In_COD) -> 0 | Q101: =Q99*$F22*(Q$4<=In_COD) -> 0 | ... EO101: =EO99*$F22*(EO$4<=In_COD) -> 0
C102: Repayment | D102: EUR k | I102: =SUM(J102:EO102) -> -49500 | J102: =J95+J97 -> 0 | K102: =K95+K97 -> 0 | L102: =L95+L97 -> 0 | M102: =M95+M97 -> 0 | N102: =N95+N97 -> 0 | O102: =O95+O97 -> 0 | P102: =P95+P97 -> 0 | Q102: =Q95+Q97 -> 0 | ... EO102: =EO95+EO97 -> 0
C103: Closing balance (E: at COD) | D103: EUR k | E103: =SUMIF($J$4:$EO$4,In_COD,$J103:$EO103) -> 49500 | J103: =SUM(J99:J102) -> 0 | K103: =SUM(K99:K102) -> 0 | L103: =SUM(L99:L102) -> 0 | M103: =SUM(M99:M102) -> 0 | N103: =SUM(N99:N102) -> 0 | O103: =SUM(O99:O102) -> 0 | P103: =SUM(P99:P102) -> 0 | Q103: =SUM(Q99:Q102) -> 0 | ... EO103: =SUM(EO99:EO102) -> 0
C104: Upfront fee | D104: EUR k | I104: =SUM(J104:EO104) -> -866.25 | J104: =-In_Upfront_Fee*$E103*(J99=0)*(J100>0) -> 0 | K104: =-In_Upfront_Fee*$E103*(K99=0)*(K100>0) -> 0 | L104: =-In_Upfront_Fee*$E103*(L99=0)*(L100>0) -> 0 | M104: =-In_Upfront_Fee*$E103*(M99=0)*(M100>0) -> 0 | N104: =-In_Upfront_Fee*$E103*(N99=0)*(N100>0) -> 0 | O104: =-In_Upfront_Fee*$E103*(O99=0)*(O100>0) -> 0 | P104: =-In_Upfront_Fee*$E103*(P99=0)*(P100>0) -> 0 | Q104: =-In_Upfront_Fee*$E103*(Q99=0)*(Q100>0) -> 0 | ... EO104: =-In_Upfront_Fee*$E103*(EO99=0)*(EO100>0) -> 0
C105: Commitment fee | D105: EUR k | I105: =SUM(J105:EO105) -> -466.8792 | J105: =-In_Commitment_Fee*($I100-SUM($J100:J100)+J100)*J$6*(J12>0) -> 0 | K105: =-In_Commitment_Fee*($I100-SUM($J100:K100)+K100)*K$6*(K12>0) -> 0 | L105: =-In_Commitment_Fee*($I100-SUM($J100:L100)+L100)*L$6*(L12>0) -> 0 | M105: =-In_Commitment_Fee*($I100-SUM($J100:M100)+M100)*M$6*(M12>0) -> 0 | N105: =-In_Commitment_Fee*($I100-SUM($J100:N100)+N100)*N$6*(N12>0) -> 0 | O105: =-In_Commitment_Fee*($I100-SUM($J100:O100)+O100)*O$6*(O12>0) -> 0 | P105: =-In_Commitment_Fee*($I100-SUM($J100:P100)+P100)*P$6*(P12>0) -> 0 | Q105: =-In_Commitment_Fee*($I100-SUM($J100:Q100)+Q100)*Q$6*(Q12>0) -> 0 | ... EO105: =-In_Commitment_Fee*($I100-SUM($J100:EO100)+EO100)*EO$6*(EO12>0) -> 0
C106: DSRA funded at COD, released at the end (E: balance) | D106: EUR k | E106: =-SUMIFS($J96:$EO96,$J$4:$EO$4,">"&In_COD,$J$4:$EO$4,"<="&EDATE(In_COD,In_DSRA_Months)) -> 1177.6015 | I106: =SUM(J106:EO106) -> 0 | J106: =$E106*(J19-J14) -> 0 | K106: =$E106*(K19-K14) -> 0 | L106: =$E106*(L19-L14) -> 0 | M106: =$E106*(M19-M14) -> 0 | N106: =$E106*(N19-N14) -> 0 | O106: =$E106*(O19-O14) -> 0 | P106: =$E106*(P19-P14) -> 0 | Q106: =$E106*(Q19-Q14) -> 0 | ... EO106: =$E106*(EO19-EO14) -> 0
C107: DSCR on scheduled debt service (E: minimum) | D107: x | E107: =MIN($J107:$EO107) -> 1.9414385 | J107: =IF(J96<0,J87/-J96,"") | K107: =IF(K96<0,K87/-K96,"") | L107: =IF(L96<0,L87/-L96,"") | M107: =IF(M96<0,M87/-M96,"") | N107: =IF(N96<0,N87/-N96,"") | O107: =IF(O96<0,O87/-O96,"") | P107: =IF(P96<0,P87/-P96,"") | Q107: =IF(Q96<0,Q87/-Q96,"") | ... EO107: =IF(EO96<0,EO87/-EO96,"")
A109: x | C109: Tax
C110: Tax depreciation (E: base) | D110: EUR k | E110: =$I101-($I68+$I58+$I69+$I55+$I48+$I49+$I50) -> 110577.13 | I110: =SUM(J110:EO110) -> -110577.13 | J110: =-$E110*J20 -> 0 | K110: =-$E110*K20 -> 0 | L110: =-$E110*L20 -> 0 | M110: =-$E110*M20 -> 0 | N110: =-$E110*N20 -> 0 | O110: =-$E110*O20 -> 0 | P110: =-$E110*P20 -> 0 | Q110: =-$E110*Q20 -> 0 | ... EO110: =-$E110*EO20 -> 0
...

Sheet Calc_2
A1: 2 | C1: Bid number
B2: =Dashboard!$C$3&" – Calculations – "&INDEX(Bid_Labels,1,$A$1) -> Project Bana – Calculations – Chinese turbine
C3: Period start | D3: date | J3: =I$4+1 -> 46296 | K3: =J$4+1 -> 46388 | L3: =K$4+1 -> 46478 | M3: =L$4+1 -> 46569 | N3: =M$4+1 -> 46661 | O3: =N$4+1 -> 46753 | P3: =O$4+1 -> 46844 | Q3: =P$4+1 -> 46935 | ... EO3: =EN$4+1 -> 58623
C4: Period end | D4: date | I4: =In_Model_Start-1 -> 46295 | J4: =EOMONTH(J$3,Months_Per_Period-1) -> 46387 | K4: =EOMONTH(K$3,Months_Per_Period-1) -> 46477 | L4: =EOMONTH(L$3,Months_Per_Period-1) -> 46568 | M4: =EOMONTH(M$3,Months_Per_Period-1) -> 46660 | N4: =EOMONTH(N$3,Months_Per_Period-1) -> 46752 | O4: =EOMONTH(O$3,Months_Per_Period-1) -> 46843 | P4: =EOMONTH(P$3,Months_Per_Period-1) -> 46934 | Q4: =EOMONTH(Q$3,Months_Per_Period-1) -> 47026 | ... EO4: =EOMONTH(EO$3,Months_Per_Period-1) -> 58714
C5: Days in period | D5: days | J5: =J$4-J$3+1 -> 92 | K5: =K$4-K$3+1 -> 90 | L5: =L$4-L$3+1 -> 91 | M5: =M$4-M$3+1 -> 92 | N5: =N$4-N$3+1 -> 92 | O5: =O$4-O$3+1 -> 91 | P5: =P$4-P$3+1 -> 91 | Q5: =Q$4-Q$3+1 -> 92 | ... EO5: =EO$4-EO$3+1 -> 92
C6: Year fraction | D6: factor | J6: =J$5/Days_In_Year -> 0.25205479 | K6: =K$5/Days_In_Year -> 0.24657534 | L6: =L$5/Days_In_Year -> 0.24931507 | M6: =M$5/Days_In_Year -> 0.25205479 | N6: =N$5/Days_In_Year -> 0.25205479 | O6: =O$5/Days_In_Year -> 0.24931507 | P6: =P$5/Days_In_Year -> 0.24931507 | Q6: =Q$5/Days_In_Year -> 0.25205479 | ... EO6: =EO$5/Days_In_Year -> 0.25205479
C7: Year | D7: year | J7: =YEAR(J$4) -> 2026 | K7: =YEAR(K$4) -> 2027 | L7: =YEAR(L$4) -> 2027 | M7: =YEAR(M$4) -> 2027 | N7: =YEAR(N$4) -> 2027 | O7: =YEAR(O$4) -> 2028 | P7: =YEAR(P$4) -> 2028 | Q7: =YEAR(Q$4) -> 2028 | ... EO7: =YEAR(EO$4) -> 2060
C8: Period counter | D8: # | J8: =I$8+1 -> 1 | K8: =J$8+1 -> 2 | L8: =K$8+1 -> 3 | M8: =L$8+1 -> 4 | N8: =M$8+1 -> 5 | O8: =N$8+1 -> 6 | P8: =O$8+1 -> 7 | Q8: =P$8+1 -> 8 | ... EO8: =EN$8+1 -> 136
A11: x | C11: Timing and flags
C12: Construction share (NTP → COD) | D12: factor | E12: =In_NTP+1 -> 47027 | F12: =In_COD -> 47756 | I12: =SUM(J12:EO12) -> 1 | J12: =MAX(0,MIN($F12,J$4)-MAX($E12,J$3)+1)/($F12-$E12+1) -> 0 | K12: =MAX(0,MIN($F12,K$4)-MAX($E12,K$3)+1)/($F12-$E12+1) -> 0 | L12: =MAX(0,MIN($F12,L$4)-MAX($E12,L$3)+1)/($F12-$E12+1) -> 0 | M12: =MAX(0,MIN($F12,M$4)-MAX($E12,M$3)+1)/($F12-$E12+1) -> 0 | N12: =MAX(0,MIN($F12,N$4)-MAX($E12,N$3)+1)/($F12-$E12+1) -> 0 | O12: =MAX(0,MIN($F12,O$4)-MAX($E12,O$3)+1)/($F12-$E12+1) -> 0 | P12: =MAX(0,MIN($F12,P$4)-MAX($E12,P$3)+1)/($F12-$E12+1) -> 0 | Q12: =MAX(0,MIN($F12,Q$4)-MAX($E12,Q$3)+1)/($F12-$E12+1) -> 0 | ... EO12: =MAX(0,MIN($F12,EO$4)-MAX($E12,EO$3)+1)/($F12-$E12+1) -> 0
C13: Devex share (closing → NTP) | D13: factor | E13: =In_Closing+1 -> 46388 | F13: =In_NTP -> 47026 | I13: =SUM(J13:EO13) -> 1 | J13: =MAX(0,MIN($F13,J$4)-MAX($E13,J$3)+1)/($F13-$E13+1) -> 0 | K13: =MAX(0,MIN($F13,K$4)-MAX($E13,K$3)+1)/($F13-$E13+1) -> 0.14084507 | L13: =MAX(0,MIN($F13,L$4)-MAX($E13,L$3)+1)/($F13-$E13+1) -> 0.14241002 | M13: =MAX(0,MIN($F13,M$4)-MAX($E13,M$3)+1)/($F13-$E13+1) -> 0.14397496 | N13: =MAX(0,MIN($F13,N$4)-MAX($E13,N$3)+1)/($F13-$E13+1) -> 0.14397496 | O13: =MAX(0,MIN($F13,O$4)-MAX($E13,O$3)+1)/($F13-$E13+1) -> 0.14241002 | P13: =MAX(0,MIN($F13,P$4)-MAX($E13,P$3)+1)/($F13-$E13+1) -> 0.14241002 | Q13: =MAX(0,MIN($F13,Q$4)-MAX($E13,Q$3)+1)/($F13-$E13+1) -> 0.14397496 | ... EO13: =MAX(0,MIN($F13,EO$4)-MAX($E13,EO$3)+1)/($F13-$E13+1) -> 0
C14: COD | D14: flag | E14: =In_COD -> 47756 | I14: =SUM(J14:EO14) -> 1 | J14: =N(AND(J$3<=$E14,J$4>=$E14)) -> 0 | K14: =N(AND(K$3<=$E14,K$4>=$E14)) -> 0 | L14: =N(AND(L$3<=$E14,L$4>=$E14)) -> 0 | M14: =N(AND(M$3<=$E14,M$4>=$E14)) -> 0 | N14: =N(AND(N$3<=$E14,N$4>=$E14)) -> 0 | O14: =N(AND(O$3<=$E14,O$4>=$E14)) -> 0 | P14: =N(AND(P$3<=$E14,P$4>=$E14)) -> 0 | Q14: =N(AND(Q$3<=$E14,Q$4>=$E14)) -> 0 | ... EO14: =N(AND(EO$3<=$E14,EO$4>=$E14)) -> 0
C15: COD column on the timeline (buyer IRR start) | D15: # | E15: =MATCH(In_COD,$J$4:$EO$4,0) -> 16
C16: Operations | D16: flag | E16: =In_COD+1 -> 47757 | F16: =EDATE(In_COD,In_Life*Months_In_Year) -> 58714 | J16: =MAX(0,(MIN($F16,J$4)-MAX($E16,J$3)+1)/J$5) -> 0 | K16: =MAX(0,(MIN($F16,K$4)-MAX($E16,K$3)+1)/K$5) -> 0 | L16: =MAX(0,(MIN($F16,L$4)-MAX($E16,L$3)+1)/L$5) -> 0 | M16: =MAX(0,(MIN($F16,M$4)-MAX($E16,M$3)+1)/M$5) -> 0 | N16: =MAX(0,(MIN($F16,N$4)-MAX($E16,N$3)+1)/N$5) -> 0 | O16: =MAX(0,(MIN($F16,O$4)-MAX($E16,O$3)+1)/O$5) -> 0 | P16: =MAX(0,(MIN($F16,P$4)-MAX($E16,P$3)+1)/P$5) -> 0 | Q16: =MAX(0,(MIN($F16,Q$4)-MAX($E16,Q$3)+1)/Q$5) -> 0 | ... EO16: =MAX(0,(MIN($F16,EO$4)-MAX($E16,EO$3)+1)/EO$5) -> 1
C17: Land lease period (NTP → end of life) | D17: flag | E17: =In_NTP+1 -> 47027 | F17: =EDATE(In_COD,In_Life*Months_In_Year) -> 58714 | J17: =MAX(0,(MIN($F17,J$4)-MAX($E17,J$3)+1)/J$5) -> 0 | K17: =MAX(0,(MIN($F17,K$4)-MAX($E17,K$3)+1)/K$5) -> 0 | L17: =MAX(0,(MIN($F17,L$4)-MAX($E17,L$3)+1)/L$5) -> 0 | M17: =MAX(0,(MIN($F17,M$4)-MAX($E17,M$3)+1)/M$5) -> 0 | N17: =MAX(0,(MIN($F17,N$4)-MAX($E17,N$3)+1)/N$5) -> 0 | O17: =MAX(0,(MIN($F17,O$4)-MAX($E17,O$3)+1)/O$5) -> 0 | P17: =MAX(0,(MIN($F17,P$4)-MAX($E17,P$3)+1)/P$5) -> 0 | Q17: =MAX(0,(MIN($F17,Q$4)-MAX($E17,Q$3)+1)/Q$5) -> 0 | ... EO17: =MAX(0,(MIN($F17,EO$4)-MAX($E17,EO$3)+1)/EO$5) -> 1
C18: Debt repayment period | D18: flag | E18: =In_COD+1 -> 47757 | F18: =EDATE(In_COD,In_Debt_Tenor*Months_In_Year) -> 53235 | J18: =MAX(0,(MIN($F18,J$4)-MAX($E18,J$3)+1)/J$5) -> 0 | K18: =MAX(0,(MIN($F18,K$4)-MAX($E18,K$3)+1)/K$5) -> 0 | L18: =MAX(0,(MIN($F18,L$4)-MAX($E18,L$3)+1)/L$5) -> 0 | M18: =MAX(0,(MIN($F18,M$4)-MAX($E18,M$3)+1)/M$5) -> 0 | N18: =MAX(0,(MIN($F18,N$4)-MAX($E18,N$3)+1)/N$5) -> 0 | O18: =MAX(0,(MIN($F18,O$4)-MAX($E18,O$3)+1)/O$5) -> 0 | P18: =MAX(0,(MIN($F18,P$4)-MAX($E18,P$3)+1)/P$5) -> 0 | Q18: =MAX(0,(MIN($F18,Q$4)-MAX($E18,Q$3)+1)/Q$5) -> 0 | ... EO18: =MAX(0,(MIN($F18,EO$4)-MAX($E18,EO$3)+1)/EO$5) -> 0
C19: Last debt repayment | D19: flag | E19: =EDATE(In_COD,In_Debt_Tenor*Months_In_Year) -> 53235 | I19: =SUM(J19:EO19) -> 1 | J19: =N(AND(J$3<=$E19,J$4>=$E19)) -> 0 | K19: =N(AND(K$3<=$E19,K$4>=$E19)) -> 0 | L19: =N(AND(L$3<=$E19,L$4>=$E19)) -> 0 | M19: =N(AND(M$3<=$E19,M$4>=$E19)) -> 0 | N19: =N(AND(N$3<=$E19,N$4>=$E19)) -> 0 | O19: =N(AND(O$3<=$E19,O$4>=$E19)) -> 0 | P19: =N(AND(P$3<=$E19,P$4>=$E19)) -> 0 | Q19: =N(AND(Q$3<=$E19,Q$4>=$E19)) -> 0 | ... EO19: =N(AND(EO$3<=$E19,EO$4>=$E19)) -> 0
C20: Tax depreciation share | D20: factor | E20: =In_COD+1 -> 47757 | F20: =EDATE(In_COD,In_Dep_Years*Months_In_Year) -> 55061 | I20: =SUM(J20:EO20) -> 1 | J20: =MAX(0,MIN($F20,J$4)-MAX($E20,J$3)+1)/($F20-$E20+1) -> 0 | K20: =MAX(0,MIN($F20,K$4)-MAX($E20,K$3)+1)/($F20-$E20+1) -> 0 | L20: =MAX(0,MIN($F20,L$4)-MAX($E20,L$3)+1)/($F20-$E20+1) -> 0 | M20: =MAX(0,MIN($F20,M$4)-MAX($E20,M$3)+1)/($F20-$E20+1) -> 0 | N20: =MAX(0,MIN($F20,N$4)-MAX($E20,N$3)+1)/($F20-$E20+1) -> 0 | O20: =MAX(0,MIN($F20,O$4)-MAX($E20,O$3)+1)/($F20-$E20+1) -> 0 | P20: =MAX(0,MIN($F20,P$4)-MAX($E20,P$3)+1)/($F20-$E20+1) -> 0 | Q20: =MAX(0,MIN($F20,Q$4)-MAX($E20,Q$3)+1)/($F20-$E20+1) -> 0 | ... EO20: =MAX(0,MIN($F20,EO$4)-MAX($E20,EO$3)+1)/($F20-$E20+1) -> 0
C21: Operating year | D21: # | J21: =ROUNDUP(YEARFRAC(In_COD,J$4),0)*(J$4>In_COD) -> 0 | K21: =ROUNDUP(YEARFRAC(In_COD,K$4),0)*(K$4>In_COD) -> 0 | L21: =ROUNDUP(YEARFRAC(In_COD,L$4),0)*(L$4>In_COD) -> 0 | M21: =ROUNDUP(YEARFRAC(In_COD,M$4),0)*(M$4>In_COD) -> 0 | N21: =ROUNDUP(YEARFRAC(In_COD,N$4),0)*(N$4>In_COD) -> 0 | O21: =ROUNDUP(YEARFRAC(In_COD,O$4),0)*(O$4>In_COD) -> 0 | P21: =ROUNDUP(YEARFRAC(In_COD,P$4),0)*(P$4>In_COD) -> 0 | Q21: =ROUNDUP(YEARFRAC(In_COD,Q$4),0)*(Q$4>In_COD) -> 0 | ... EO21: =ROUNDUP(YEARFRAC(In_COD,EO$4),0)*(EO$4>In_COD) -> 30
C22: Debt compounding index (E: at COD, F: rate per period) | D22: factor | E22: =SUMIF($J$4:$EO$4,In_COD,$J22:$EO22) -> 1.2198895 | F22: =In_Debt_Rate*Months_Per_Period/Months_In_Year -> 0.0125 | J22: =(1+$F22)^J$8 -> 1.0125 | K22: =(1+$F22)^K$8 -> 1.0251562 | L22: =(1+$F22)^L$8 -> 1.0379707 | M22: =(1+$F22)^M$8 -> 1.0509453 | N22: =(1+$F22)^N$8 -> 1.0640822 | O22: =(1+$F22)^O$8 -> 1.0773832 | P22: =(1+$F22)^P$8 -> 1.0908505 | Q22: =(1+$F22)^Q$8 -> 1.1044861 | ... EO22: =(1+$F22)^EO$8 -> 5.4165697
A24: x | C24: Capacity (E: committed in the bid, F: built)
C25: Wind | D25: MW | E25: =In_MVA*(1+INDEX(Dash_Overbuild,1,$A$1)) -> 60 | F25: =In_MVA*(1+In_Overbuild_Built) -> 55
C26: BESS power, share of MVA (bid, or the set's commitment) | D26: % | E26: =IF(In_BESS_Set>0,In_BESS_Set,INDEX(Dash_BESS,1,$A$1)) -> 0.2
C27: BESS power | D27: MW | E27: =$E26*In_MVA -> 10 | F27: =$E27*In_BESS_Built -> 10
C28: BESS energy | D28: MWh | E28: =$E27*INDEX(Dash_BESS_Hours,1,$A$1) -> 40
C29: Grid-bottleneck loss on built wind | D29: % | E29: =($F25-In_MVA)/$F25*In_Bottleneck_Loss -> 0.0045454545
C30: Build shortfall vs commitment (E: wind, F: BESS) | D30: % | E30: =MAX(0,1-$F25/$E25) -> 0.083333333 | F30: =(1-In_BESS_Built)*($E27>0) -> 0
C31: Memo: connection right lost pro rata (GYIK 28/30) | D31: MVA | E31: =($E30>In_Tolerance_Cap)*$E30*In_MVA*(In_Sanction_Regime=1) -> 0
A33: x | C33: Tender points (E: commitment, F: weighted points)
C34: ÖSZ-1 municipal one-off | D34: EUR k/MW | E34: =INDEX(Dash_Municipal,1,$A$1) -> 50 | F34: =INDEX(Osz1_Pts,1+SUMPRODUCT((Osz1_LB<$E34)+(Osz1_LB=$E34)*Osz1_Incl))*Osz1_W -> 20
C35: ÖSZ-2 community contribution | D35: EUR/MWh | E35: =INDEX(Dash_Community,1,$A$1) -> 3 | F35: =INDEX(Osz2_Pts,1+SUMPRODUCT((Osz2_LB<$E35)+(Osz2_LB=$E35)*Osz2_Incl))*Osz2_W -> 15
C36: ÖSZ-3 overbuild | D36: % | E36: =INDEX(Dash_Overbuild,1,$A$1) -> 0.2 | F36: =INDEX(Osz3_Pts,1+SUMPRODUCT((Osz3_LB<$E36)+(Osz3_LB=$E36)*Osz3_Incl))*Osz3_W -> 5
C37: ÖSZ-4 BESS power, share of MVA | D37: % | E37: =$E26 -> 0.2 | F37: =INDEX(Osz4_Pts,1+SUMPRODUCT((Osz4_LB<$E37)+(Osz4_LB=$E37)*Osz4_Incl))*Osz4_W*($E37>=Osz4_Min) -> 7.5
C38: ÖSZ-5 partial award | D38: flag | E38: =INDEX(Dash_Partial,1,$A$1) -> 0 | F38: =$E38*Osz5_Pts*Osz5_W -> 0
C39: ÖSZ-6 performance security multiple | D39: x | E39: =INDEX(Dash_PB_Mult,1,$A$1) -> 1 | F39: =INDEX(Osz6_Pts,1+SUMPRODUCT((Osz6_LB<$E39)+(Osz6_LB=$E39)*Osz6_Incl))*Osz6_W -> 0
C40: ÖSZ-8 shared connection | D40: flag | E40: =INDEX(Dash_Shared,1,$A$1) -> 0 | F40: =$E40*Osz8_Pts*Osz8_W -> 0
C41: ÖSZ-9 EU turbines (1 = European turbine route) | D41: flag | E41: =INDEX(Dash_EU_Turbine,1,$A$1) -> 0 | F41: =$E41*Osz9a_Pts*Osz9_W -> 0
C42: ÖSZ-9 EU transformers | D42: flag | E42: =INDEX(Dash_EU_Transformer,1,$A$1) -> 0 | F42: =$E42*Osz9b_Pts*Osz9_W -> 0
C43: Points total | D43: points | E43: =ROUND(SUM($F34:$F42),Points_Decimals) -> 47.5
C44: European turbines installed (bid and delivered) | D44: flag | E44: =$E41*In_Deliver -> 0
C45: Failed tests (E: ÖSZ-1 and -2 range, F: ÖSZ-6, BESS ≤ wind, 4 h) | D45: # | E45: =($E34<>0)*($E34<Osz1_Min)+($E34>Osz1_Max)+($E35<>0)*($E35<Osz2_Min)+($E35>Osz2_Max) -> 0 | F45: =N($E39<1)+N($E27>$E25)+N($E28<$E27*In_Min_Hours) -> 0
A47: x | C47: Development, securities and fees (E: amount, F: date)
C48: Purchase price | D48: EUR k | E48: =In_Purchase_Price -> 4500 | F48: =In_Closing -> 46387 | I48: =SUM(J48:EO48) -> -4500 | J48: =-$E48*N(AND(J$3<=$F48,J$4>=$F48)) -> -4500 | K48: =-$E48*N(AND(K$3<=$F48,K$4>=$F48)) -> 0 | L48: =-$E48*N(AND(L$3<=$F48,L$4>=$F48)) -> 0 | M48: =-$E48*N(AND(M$3<=$F48,M$4>=$F48)) -> 0 | N48: =-$E48*N(AND(N$3<=$F48,N$4>=$F48)) -> 0 | O48: =-$E48*N(AND(O$3<=$F48,O$4>=$F48)) -> 0 | P48: =-$E48*N(AND(P$3<=$F48,P$4>=$F48)) -> 0 | Q48: =-$E48*N(AND(Q$3<=$F48,Q$4>=$F48)) -> 0 | ... EO48: =-$E48*N(AND(EO$3<=$F48,EO$4>=$F48)) -> 0
C49: Transaction and DD costs | D49: EUR k | E49: =In_DD -> 150 | F49: =In_Bid_Date -> 46325 | I49: =SUM(J49:EO49) -> -150 | J49: =-$E49*N(AND(J$3<=$F49,J$4>=$F49)) -> -150 | K49: =-$E49*N(AND(K$3<=$F49,K$4>=$F49)) -> 0 | L49: =-$E49*N(AND(L$3<=$F49,L$4>=$F49)) -> 0 | M49: =-$E49*N(AND(M$3<=$F49,M$4>=$F49)) -> 0 | N49: =-$E49*N(AND(N$3<=$F49,N$4>=$F49)) -> 0 | O49: =-$E49*N(AND(O$3<=$F49,O$4>=$F49)) -> 0 | P49: =-$E49*N(AND(P$3<=$F49,P$4>=$F49)) -> 0 | Q49: =-$E49*N(AND(Q$3<=$F49,Q$4>=$F49)) -> 0 | ... EO49: =-$E49*N(AND(EO$3<=$F49,EO$4>=$F49)) -> 0
C50: Devex | D50: EUR k | I50: =SUM(J50:EO50) -> -500 | J50: =-In_Devex*J13 -> 0 | K50: =-In_Devex*K13 -> -70.422535 | L50: =-In_Devex*L13 -> -71.205008 | M50: =-In_Devex*M13 -> -71.98748 | N50: =-In_Devex*N13 -> -71.98748 | O50: =-In_Devex*O13 -> -71.205008 | P50: =-In_Devex*P13 -> -71.205008 | Q50: =-In_Devex*Q13 -> -71.98748 | ... EO50: =-In_Devex*EO13 -> 0
C51: Security base | D51: mHUF | E51: =$E25*In_Bench_Wind+$E28*In_Bench_BESS -> 32360
C52: Participation fee (cash) | D52: EUR k | E52: =In_Part_Fee*Thousand/In_FX -> 8.2191781 | F52: =In_Bid_Date -> 46325 | I52: =SUM(J52:EO52) -> -8.2191781 | J52: =-$E52*N(AND(J$3<=$F52,J$4>=$F52)) -> -8.2191781 | K52: =-$E52*N(AND(K$3<=$F52,K$4>=$F52)) -> 0 | L52: =-$E52*N(AND(L$3<=$F52,L$4>=$F52)) -> 0 | M52: =-$E52*N(AND(M$3<=$F52,M$4>=$F52)) -> 0 | N52: =-$E52*N(AND(N$3<=$F52,N$4>=$F52)) -> 0 | O52: =-$E52*N(AND(O$3<=$F52,O$4>=$F52)) -> 0 | P52: =-$E52*N(AND(P$3<=$F52,P$4>=$F52)) -> 0 | Q52: =-$E52*N(AND(Q$3<=$F52,Q$4>=$F52)) -> 0 | ... EO52: =-$E52*N(AND(EO$3<=$F52,EO$4>=$F52)) -> 0
C53: Bid security outstanding (guarantee) | D53: EUR k | E53: =In_Bid_Rate*$E51*Thousand/In_FX -> 443.28767 | F53: =In_Bid_Date -> 46325 | J53: =$E53*MAX(0,(MIN(In_Decision_Date+In_PB_Days-1,J$4)-MAX($F53,J$3)+1)/J$5) -> 303.55569 | K53: =$E53*MAX(0,(MIN(In_Decision_Date+In_PB_Days-1,K$4)-MAX($F53,K$3)+1)/K$5) -> 221.64384 | L53: =$E53*MAX(0,(MIN(In_Decision_Date+In_PB_Days-1,L$4)-MAX($F53,L$3)+1)/L$5) -> 0 | M53: =$E53*MAX(0,(MIN(In_Decision_Date+In_PB_Days-1,M$4)-MAX($F53,M$3)+1)/M$5) -> 0 | N53: =$E53*MAX(0,(MIN(In_Decision_Date+In_PB_Days-1,N$4)-MAX($F53,N$3)+1)/N$5) -> 0 | O53: =$E53*MAX(0,(MIN(In_Decision_Date+In_PB_Days-1,O$4)-MAX($F53,O$3)+1)/O$5) -> 0 | P53: =$E53*MAX(0,(MIN(In_Decision_Date+In_PB_Days-1,P$4)-MAX($F53,P$3)+1)/P$5) -> 0 | Q53: =$E53*MAX(0,(MIN(In_Decision_Date+In_PB_Days-1,Q$4)-MAX($F53,Q$3)+1)/Q$5) -> 0 | ... EO53: =$E53*MAX(0,(MIN(In_Decision_Date+In_PB_Days-1,EO$4)-MAX($F53,EO$3)+1)/EO$5) -> 0
C54: Performance security outstanding (guarantee) | D54: EUR k | E54: =In_PB_Rate*$E39*$E51*Thousand/In_FX -> 2216.4384 | F54: =In_Decision_Date+In_PB_Days -> 46433 | J54: =$E54*MAX(0,(MIN(In_PB_Release,J$4)-MAX($F54,J$3)+1)/J$5) -> 0 | K54: =$E54*MAX(0,(MIN(In_PB_Release,K$4)-MAX($F54,K$3)+1)/K$5) -> 1108.2192 | L54: =$E54*MAX(0,(MIN(In_PB_Release,L$4)-MAX($F54,L$3)+1)/L$5) -> 2216.4384 | M54: =$E54*MAX(0,(MIN(In_PB_Release,M$4)-MAX($F54,M$3)+1)/M$5) -> 2216.4384 | N54: =$E54*MAX(0,(MIN(In_PB_Release,N$4)-MAX($F54,N$3)+1)/N$5) -> 2216.4384 | O54: =$E54*MAX(0,(MIN(In_PB_Release,O$4)-MAX($F54,O$3)+1)/O$5) -> 2216.4384 | P54: =$E54*MAX(0,(MIN(In_PB_Release,P$4)-MAX($F54,P$3)+1)/P$5) -> 2216.4384 | Q54: =$E54*MAX(0,(MIN(In_PB_Release,Q$4)-MAX($F54,Q$3)+1)/Q$5) -> 2216.4384 | ... EO54: =$E54*MAX(0,(MIN(In_PB_Release,EO$4)-MAX($F54,EO$3)+1)/EO$5) -> 0
C55: TSO connection-request security (cash) | D55: EUR k | E55: =In_TSO_Security*In_MVA*Thousand/In_FX -> 616.43836 | F55: =In_Decision_Date+In_PB_Days -> 46433 | I55: =SUM(J55:EO55) -> -616.43836 | J55: =-$E55*N(AND(J$3<=$F55,J$4>=$F55)) -> 0 | K55: =-$E55*N(AND(K$3<=$F55,K$4>=$F55)) -> -616.43836 | L55: =-$E55*N(AND(L$3<=$F55,L$4>=$F55)) -> 0 | M55: =-$E55*N(AND(M$3<=$F55,M$4>=$F55)) -> 0 | N55: =-$E55*N(AND(N$3<=$F55,N$4>=$F55)) -> 0 | O55: =-$E55*N(AND(O$3<=$F55,O$4>=$F55)) -> 0 | P55: =-$E55*N(AND(P$3<=$F55,P$4>=$F55)) -> 0 | Q55: =-$E55*N(AND(Q$3<=$F55,Q$4>=$F55)) -> 0 | ... EO55: =-$E55*N(AND(EO$3<=$F55,EO$4>=$F55)) -> 0
C56: Direct connection fee (cash) | D56: EUR k | E56: =In_Direct_Fee*Thousand/In_FX -> 1260.274 | F56: =In_HCSSZ_Date -> 47126 | I56: =SUM(J56:EO56) -> -1260.274 | J56: =-$E56*N(AND(J$3<=$F56,J$4>=$F56)) -> 0 | K56: =-$E56*N(AND(K$3<=$F56,K$4>=$F56)) -> 0 | L56: =-$E56*N(AND(L$3<=$F56,L$4>=$F56)) -> 0 | M56: =-$E56*N(AND(M$3<=$F56,M$4>=$F56)) -> 0 | N56: =-$E56*N(AND(N$3<=$F56,N$4>=$F56)) -> 0 | O56: =-$E56*N(AND(O$3<=$F56,O$4>=$F56)) -> 0 | P56: =-$E56*N(AND(P$3<=$F56,P$4>=$F56)) -> 0 | Q56: =-$E56*N(AND(Q$3<=$F56,Q$4>=$F56)) -> 0 | ... EO56: =-$E56*N(AND(EO$3<=$F56,EO$4>=$F56)) -> 0
C57: Indirect connection fee, net of TSO security | D57: EUR k | E57: =(In_Indirect_Fee-In_TSO_Security)*In_MVA*Thousand/In_FX -> 6894.5492 | F57: =In_HCSSZ_Date -> 47126 | I57: =SUM(J57:EO57) -> -6894.5492 | J57: =-$E57*N(AND(J$3<=$F57,J$4>=$F57)) -> 0 | K57: =-$E57*N(AND(K$3<=$F57,K$4>=$F57)) -> 0 | L57: =-$E57*N(AND(L$3<=$F57,L$4>=$F57)) -> 0 | M57: =-$E57*N(AND(M$3<=$F57,M$4>=$F57)) -> 0 | N57: =-$E57*N(AND(N$3<=$F57,N$4>=$F57)) -> 0 | O57: =-$E57*N(AND(O$3<=$F57,O$4>=$F57)) -> 0 | P57: =-$E57*N(AND(P$3<=$F57,P$4>=$F57)) -> 0 | Q57: =-$E57*N(AND(Q$3<=$F57,Q$4>=$F57)) -> 0 | ... EO57: =-$E57*N(AND(EO$3<=$F57,EO$4>=$F57)) -> 0
C58: Connection fees | D58: EUR k | I58: =SUM(J58:EO58) -> -8154.8232 | J58: =J56+J57 -> 0 | K58: =K56+K57 -> 0 | L58: =L56+L57 -> 0 | M58: =M56+M57 -> 0 | N58: =N56+N57 -> 0 | O58: =O56+O57 -> 0 | P58: =P56+P57 -> 0 | Q58: =Q56+Q57 -> 0 | ... EO58: =EO56+EO57 -> 0
C59: Guarantee fees (E: to COD) | D59: EUR k | E59: =SUMIF($J$4:$EO$4,"<="&In_COD,$J59:$EO59) -> -490.26402 | I59: =SUM(J59:EO59) -> -822.91195 | J59: =-(J53+J54)*In_Guarantee_Fee*J$5/Days_In_Year -> -4.59076 | K59: =-(K53+K54)*In_Guarantee_Fee*K$5/Days_In_Year -> -19.674686 | L59: =-(L53+L54)*In_Guarantee_Fee*L$5/Days_In_Year -> -33.155489 | M59: =-(M53+M54)*In_Guarantee_Fee*M$5/Days_In_Year -> -33.519835 | N59: =-(N53+N54)*In_Guarantee_Fee*N$5/Days_In_Year -> -33.519835 | O59: =-(O53+O54)*In_Guarantee_Fee*O$5/Days_In_Year -> -33.155489 | P59: =-(P53+P54)*In_Guarantee_Fee*P$5/Days_In_Year -> -33.155489 | Q59: =-(Q53+Q54)*In_Guarantee_Fee*Q$5/Days_In_Year -> -33.519835 | ... EO59: =-(EO53+EO54)*In_Guarantee_Fee*EO$5/Days_In_Year -> 0
C60: Performance security by technology (E: wind, F: BESS) | D60: EUR k | E60: =$E54*$E25*In_Bench_Wind/$E51 -> 1668.4932 | F60: =$E54-$E60 -> 547.94521
C61: PB call (E: pro rata above the tolerance, F: full call) | D61: EUR k | E61: =($E30>In_Tolerance_Cap)*$E30*$E60+($F30>In_Tolerance_Cap)*$F30*$F60 -> 0 | F61: =(($E30+$F30>0)+(In_Deliver=0)>0)*$E54 -> 2216.4384
C62: PB call paid, selected regime (E: date) | D62: EUR k | E62: =EDATE(In_COD,In_Sanction_Lag) -> 47937 | I62: =SUM(J62:EO62) -> 0 | J62: =-CHOOSE(In_Sanction_Regime,$E61,$F61)*N(AND(J$3<=$E62,J$4>=$E62)) -> 0 | K62: =-CHOOSE(In_Sanction_Regime,$E61,$F61)*N(AND(K$3<=$E62,K$4>=$E62)) -> 0 | L62: =-CHOOSE(In_Sanction_Regime,$E61,$F61)*N(AND(L$3<=$E62,L$4>=$E62)) -> 0 | M62: =-CHOOSE(In_Sanction_Regime,$E61,$F61)*N(AND(M$3<=$E62,M$4>=$E62)) -> 0 | N62: =-CHOOSE(In_Sanction_Regime,$E61,$F61)*N(AND(N$3<=$E62,N$4>=$E62)) -> 0 | O62: =-CHOOSE(In_Sanction_Regime,$E61,$F61)*N(AND(O$3<=$E62,O$4>=$E62)) -> 0 | P62: =-CHOOSE(In_Sanction_Regime,$E61,$F61)*N(AND(P$3<=$E62,P$4>=$E62)) -> 0 | Q62: =-CHOOSE(In_Sanction_Regime,$E61,$F61)*N(AND(Q$3<=$E62,Q$4>=$E62)) -> 0 | ... EO62: =-CHOOSE(In_Sanction_Regime,$E61,$F61)*N(AND(EO$3<=$E62,EO$4>=$E62)) -> 0
C63: Development cash flow | D63: EUR k | I63: =SUM(J63:EO63) -> -6597.5695 | J63: =J48+J49+J50+J52+J55+J59 -> -4662.8099 | K63: =K48+K49+K50+K52+K55+K59 -> -706.53558 | L63: =L48+L49+L50+L52+L55+L59 -> -104.3605 | M63: =M48+M49+M50+M52+M55+M59 -> -105.50732 | N63: =N48+N49+N50+N52+N55+N59 -> -105.50732 | O63: =O48+O49+O50+O52+O55+O59 -> -104.3605 | P63: =P48+P49+P50+P52+P55+P59 -> -104.3605 | Q63: =Q48+Q49+Q50+Q52+Q55+Q59 -> -105.50732 | ... EO63: =EO48+EO49+EO50+EO52+EO55+EO59 -> 0
A65: x | C65: Construction
C66: Turbine supply, this route | D66: EUR k/MW | E66: =IF($E44=1,In_Turbine,In_Turbine_CN) -> 500
C67: Substation and 132 kV bay, this route | D67: EUR k | E67: =IF($E44=1,In_Substation,In_Substation_CN) -> 10800
C68: Capex (E: total) | D68: EUR k | E68: =(($E66+In_Other_Wind)*$F25+$E67)*(1+In_Capex_Contingency)+In_BESS_Capex*$E28*In_BESS_Built -> 64716.25 | I68: =SUM(J68:EO68) -> -64716.25 | J68: =-$E68*J12 -> 0 | K68: =-$E68*K12 -> 0 | L68: =-$E68*L12 -> 0 | M68: =-$E68*M12 -> 0 | N68: =-$E68*N12 -> 0 | O68: =-$E68*O12 -> 0 | P68: =-$E68*P12 -> 0 | Q68: =-$E68*Q12 -> 0 | ... EO68: =-$E68*EO12 -> 0
C69: Municipal one-off at COD | D69: EUR k | E69: =$E34*In_MVA*In_Deliver -> 2500 | I69: =SUM(J69:EO69) -> -2500 | J69: =-$E69*J14 -> 0 | K69: =-$E69*K14 -> 0 | L69: =-$E69*L14 -> 0 | M69: =-$E69*M14 -> 0 | N69: =-$E69*N14 -> 0 | O69: =-$E69*O14 -> 0 | P69: =-$E69*P14 -> 0 | Q69: =-$E69*Q14 -> 0 | ... EO69: =-$E69*EO14 -> 0
C70: Construction cost (E: compounded to COD at the debt rate) | D70: EUR k | E70: =SUMPRODUCT($J70:$EO70/$J22:$EO22)*$E22 -> -78904.248 | I70: =SUM(J70:EO70) -> -75371.073 | J70: =J68+J58+J69 -> 0 | K70: =K68+K58+K69 -> 0 | L70: =L68+L58+L69 -> 0 | M70: =M68+M58+M69 -> 0 | N70: =N68+N58+N69 -> 0 | O70: =O68+O58+O69 -> 0 | P70: =P68+P58+P69 -> 0 | Q70: =Q68+Q58+Q69 -> 0 | ... EO70: =EO68+EO58+EO69 -> 0
A72: x | C72: Operations
C73: Opex escalation index | D73: factor | J73: =(1+In_Opex_Esc)^(J$7-YEAR(In_COD)) -> 0.90595064 | K73: =(1+In_Opex_Esc)^(K$7-YEAR(In_COD)) -> 0.92859941 | L73: =(1+In_Opex_Esc)^(L$7-YEAR(In_COD)) -> 0.92859941 | M73: =(1+In_Opex_Esc)^(M$7-YEAR(In_COD)) -> 0.92859941 | N73: =(1+In_Opex_Esc)^(N$7-YEAR(In_COD)) -> 0.92859941 | O73: =(1+In_Opex_Esc)^(O$7-YEAR(In_COD)) -> 0.9518144 | P73: =(1+In_Opex_Esc)^(P$7-YEAR(In_COD)) -> 0.9518144 | Q73: =(1+In_Opex_Esc)^(Q$7-YEAR(In_COD)) -> 0.9518144 | ... EO73: =(1+In_Opex_Esc)^(EO$7-YEAR(In_COD)) -> 2.0975676
C74: PPA price | D74: EUR/MWh | J74: =In_PPA_Price*(1+In_PPA_Esc)^(J$7-YEAR(In_COD)) -> 86.488231 | K74: =In_PPA_Price*(1+In_PPA_Esc)^(K$7-YEAR(In_COD)) -> 87.353113 | L74: =In_PPA_Price*(1+In_PPA_Esc)^(L$7-YEAR(In_COD)) -> 87.353113 | M74: =In_PPA_Price*(1+In_PPA_Esc)^(M$7-YEAR(In_COD)) -> 87.353113 | N74: =In_PPA_Price*(1+In_PPA_Esc)^(N$7-YEAR(In_COD)) -> 87.353113 | O74: =In_PPA_Price*(1+In_PPA_Esc)^(O$7-YEAR(In_COD)) -> 88.226644 | P74: =In_PPA_Price*(1+In_PPA_Esc)^(P$7-YEAR(In_COD)) -> 88.226644 | Q74: =In_PPA_Price*(1+In_PPA_Esc)^(Q$7-YEAR(In_COD)) -> 88.226644 | ... EO74: =In_PPA_Price*(1+In_PPA_Esc)^(EO$7-YEAR(In_COD)) -> 121.3064
C75: Net generation (E: first full year) | D75: MWh | E75: =SUMIF($J$7:$EO$7,YEAR(In_COD)+1,$J75:$EO75) -> 139397.51 | I75: =SUM(J75:EO75) -> 4010958.4 | J75: =$F25*In_P50_Hours*(1-In_Curtailment)*(1-$E29)*(1-In_Degradation)^(J21-1)*J16*J$6 -> 0 | K75: =$F25*In_P50_Hours*(1-In_Curtailment)*(1-$E29)*(1-In_Degradation)^(K21-1)*K16*K$6 -> 0 | L75: =$F25*In_P50_Hours*(1-In_Curtailment)*(1-$E29)*(1-In_Degradation)^(L21-1)*L16*L$6 -> 0 | M75: =$F25*In_P50_Hours*(1-In_Curtailment)*(1-$E29)*(1-In_Degradation)^(M21-1)*M16*M$6 -> 0 | N75: =$F25*In_P50_Hours*(1-In_Curtailment)*(1-$E29)*(1-In_Degradation)^(N21-1)*N16*N$6 -> 0 | O75: =$F25*In_P50_Hours*(1-In_Curtailment)*(1-$E29)*(1-In_Degradation)^(O21-1)*O16*O$6 -> 0 | P75: =$F25*In_P50_Hours*(1-In_Curtailment)*(1-$E29)*(1-In_Degradation)^(P21-1)*P16*P$6 -> 0 | Q75: =$F25*In_P50_Hours*(1-In_Curtailment)*(1-$E29)*(1-In_Degradation)^(Q21-1)*Q16*Q$6 -> 0 | ... EO75: =$F25*In_P50_Hours*(1-In_Curtailment)*(1-$E29)*(1-In_Degradation)^(EO21-1)*EO16*EO$6 -> 32228.352
C76: Revenue (E: first full year) | D76: EUR k | E76: =SUMIF($J$7:$EO$7,YEAR(In_COD)+1,$J76:$EO76) -> 12671.234 | I76: =SUM(J76:EO76) -> 420752.71 | J76: =J75*J74/Thousand -> 0 | K76: =K75*K74/Thousand -> 0 | L76: =L75*L74/Thousand -> 0 | M76: =M75*M74/Thousand -> 0 | N76: =N75*N74/Thousand -> 0 | O76: =O75*O74/Thousand -> 0 | P76: =P75*P74/Thousand -> 0 | Q76: =Q75*Q74/Thousand -> 0 | ... EO76: =EO75*EO74/Thousand -> 3909.5055
C77: Variable opex (balancing, grid) | D77: EUR k | I77: =SUM(J77:EO77) -> -29733.419 | J77: =-In_Var_Opex*J75*J73/Thousand -> 0 | K77: =-In_Var_Opex*K75*K73/Thousand -> 0 | L77: =-In_Var_Opex*L75*L73/Thousand -> 0 | M77: =-In_Var_Opex*M75*M73/Thousand -> 0 | N77: =-In_Var_Opex*N75*N73/Thousand -> 0 | O77: =-In_Var_Opex*O75*O73/Thousand -> 0 | P77: =-In_Var_Opex*P75*P73/Thousand -> 0 | Q77: =-In_Var_Opex*Q75*Q73/Thousand -> 0 | ... EO77: =-In_Var_Opex*EO75*EO73/Thousand -> -338.00573
C78: Fixed opex and administration | D78: EUR k | I78: =SUM(J78:EO78) -> -60869.52 | J78: =-(In_Fixed_Opex*$F25+In_Admin)*J73*J16*J$6 -> 0 | K78: =-(In_Fixed_Opex*$F25+In_Admin)*K73*K16*K$6 -> 0 | L78: =-(In_Fixed_Opex*$F25+In_Admin)*L73*L16*L$6 -> 0 | M78: =-(In_Fixed_Opex*$F25+In_Admin)*M73*M16*M$6 -> 0 | N78: =-(In_Fixed_Opex*$F25+In_Admin)*N73*N16*N$6 -> 0 | O78: =-(In_Fixed_Opex*$F25+In_Admin)*O73*O16*O$6 -> 0 | P78: =-(In_Fixed_Opex*$F25+In_Admin)*P73*P16*P$6 -> 0 | Q78: =-(In_Fixed_Opex*$F25+In_Admin)*Q73*Q16*Q$6 -> 0 | ... EO78: =-(In_Fixed_Opex*$F25+In_Admin)*EO73*EO16*EO$6 -> -719.03467
C79: Land lease | D79: EUR k | I79: =SUM(J79:EO79) -> -7708.8766 | J79: =-In_Lease*$F25*J73*J17*J$6 -> 0 | K79: =-In_Lease*$F25*K73*K17*K$6 -> 0 | L79: =-In_Lease*$F25*L73*L17*L$6 -> 0 | M79: =-In_Lease*$F25*M73*M17*M$6 -> 0 | N79: =-In_Lease*$F25*N73*N17*N$6 -> 0 | O79: =-In_Lease*$F25*O73*O17*O$6 -> 0 | P79: =-In_Lease*$F25*P73*P17*P$6 -> 0 | Q79: =-In_Lease*$F25*Q73*Q17*Q$6 -> 0 | ... EO79: =-In_Lease*$F25*EO73*EO17*EO$6 -> -87.235824
C80: MEKH fee, HIPA and innovation contribution | D80: EUR k | I80: =SUM(J80:EO80) -> -10098.065 | J80: =-J76*(In_MEKH+In_HIPA+In_Innovation) -> 0 | K80: =-K76*(In_MEKH+In_HIPA+In_Innovation) -> 0 | L80: =-L76*(In_MEKH+In_HIPA+In_Innovation) -> 0 | M80: =-M76*(In_MEKH+In_HIPA+In_Innovation) -> 0 | N80: =-N76*(In_MEKH+In_HIPA+In_Innovation) -> 0 | O80: =-O76*(In_MEKH+In_HIPA+In_Innovation) -> 0 | P80: =-P76*(In_MEKH+In_HIPA+In_Innovation) -> 0 | Q80: =-Q76*(In_MEKH+In_HIPA+In_Innovation) -> 0 | ... EO80: =-EO76*(In_MEKH+In_HIPA+In_Innovation) -> -93.828131
C81: Opex contingency | D81: EUR k | I81: =SUM(J81:EO81) -> -4936.6284 | J81: =In_Opex_Contingency*(J77+J78+J79-J76*In_MEKH) -> 0 | K81: =In_Opex_Contingency*(K77+K78+K79-K76*In_MEKH) -> 0 | L81: =In_Opex_Contingency*(L77+L78+L79-L76*In_MEKH) -> 0 | M81: =In_Opex_Contingency*(M77+M78+M79-M76*In_MEKH) -> 0 | N81: =In_Opex_Contingency*(N77+N78+N79-N76*In_MEKH) -> 0 | O81: =In_Opex_Contingency*(O77+O78+O79-O76*In_MEKH) -> 0 | P81: =In_Opex_Contingency*(P77+P78+P79-P76*In_MEKH) -> 0 | Q81: =In_Opex_Contingency*(Q77+Q78+Q79-Q76*In_MEKH) -> 0 | ... EO81: =In_Opex_Contingency*(EO77+EO78+EO79-EO76*In_MEKH) -> -57.409287
C82: Community contribution (ÖSZ-2) | D82: EUR k | I82: =SUM(J82:EO82) -> -12032.875 | J82: =-$E35*In_Deliver*J75/Thousand -> 0 | K82: =-$E35*In_Deliver*K75/Thousand -> 0 | L82: =-$E35*In_Deliver*L75/Thousand -> 0 | M82: =-$E35*In_Deliver*M75/Thousand -> 0 | N82: =-$E35*In_Deliver*N75/Thousand -> 0 | O82: =-$E35*In_Deliver*O75/Thousand -> 0 | P82: =-$E35*In_Deliver*P75/Thousand -> 0 | Q82: =-$E35*In_Deliver*Q75/Thousand -> 0 | ... EO82: =-$E35*In_Deliver*EO75/Thousand -> -96.685057
C83: EBITDA (E: first full year) | D83: EUR k | E83: =SUMIF($J$7:$EO$7,YEAR(In_COD)+1,$J83:$EO83) -> 9556.8841 | I83: =SUM(J83:EO83) -> 295373.33 | J83: =SUM(J76:J82) -> 0 | K83: =SUM(K76:K82) -> 0 | L83: =SUM(L76:L82) -> 0 | M83: =SUM(M76:M82) -> 0 | N83: =SUM(N76:N82) -> 0 | O83: =SUM(O76:O82) -> 0 | P83: =SUM(P76:P82) -> 0 | Q83: =SUM(Q76:Q82) -> 0 | ... EO83: =SUM(EO76:EO82) -> 2517.3068
A85: x | C85: Debt sizing on CFADS
C86: Corporate income tax – paste (macro) | D86: EUR k | J86: 0 | K86: 0 | L86: 0 | M86: 0 | N86: 0 | O86: 0 | P86: 0 | Q86: 0 | R86: 0 | S86: 0 | T86: 0 | U86: 0 | V86: 0 | W86: 0 | X86: 0 | Y86: 0 | Z86: -51.958093 | AA86: -51.530776 | AB86: -53.143616 | AC86: -54.763087 | AD86: -54.67135 | AE86: -55.33656 | AF86: -108.11708 | AG86: -115.09412 | AH86: -114.958 | AI86: -114.12164 | AJ86: -122.45585 | AK86: -125.88604 | AL86: -125.80006 | AM86: -124.86714 | AN86: -128.35405 | AO86: -131.85636 | AP86: -131.82347 | AQ86: -130.90588 | AR86: -134.46686 | AS86: -138.04402 | AT86: -138.06731 | AU86: -139.4455 | AV86: -140.80568 | AW86: -144.46056 | AX86: -144.54328 | AY86: -143.66472 | AZ86: -147.38249 | BA86: -151.11813 | BB86: -151.2637 | BC86: -150.40914 | BD86: -154.20995 | BE86: -158.02953 | BF86: -158.24154 | BG86: -157.41422 | BH86: -161.30137 | BI86: -165.20824 | BJ86: -165.49047 | BK86: -167.01151 | BL86: -168.67077 | BM86: -172.66847 | BN86: -173.0249 | BO86: -172.26247 | BP86: -176.33292 | BQ86: -180.42517 | BR86: -180.85997 | BS86: -180.13559 | BT86: -184.30339 | BU86: -188.4941 | BV86: -189.01166 | BW86: -188.32933 | BX86: -192.59854 | BY86: -196.89183 | BZ86: -197.49678 | CA86: -199.21153 | CB86: -201.23564 | CC86: -205.63585 | CD86: -206.33304 | CE86: -205.74772 | CF86: -210.23284 | CG86: -214.74454 | CH86: -215.53907 | CI86: -212.8012 | CJ86: -215.16566 | CK86: -217.53012 | CL86: -216.13551 | CM86: -213.34557 | CN86: -215.71607 | CO86: -218.08658 | CP86: -216.68357 | CQ86: -216.21706 | CR86: -216.21706 | CS86: -218.59307 | CT86: -217.18163 | CU86: -214.28605 | CV86: -216.667 | CW86: -219.04796 | CX86: -217.62807 | CY86: -214.67891 | CZ86: -217.06423 | DA86: -219.44955 | DB86: -375.4867 | DC86: -369.06028 | DD86: -373.16095 | DE86: -377.26162 | DF86: -375.82478 | DG86: -373.44756 | DH86: -373.44756 | DI86: -377.55138 | DJ86: -376.10605 | DK86: -369.56986 | DL86: -373.67619 | DM86: -377.78253 | DN86: -376.32869 | DO86: -369.73681 | DP86: -373.845 | DQ86: -377.95318 | DR86: -376.49082 | DS86: -369.84271 | DT86: -373.95207 | DU86: -378.06144 | DV86: -376.59054 | DW86: -373.99548 | DX86: -373.99548 | DY86: -378.10532 | DZ86: -376.62587 | EA86: -369.86362 | EB86: -373.97322 | EC86: -378.08282 | ED86: -376.59481 | EE86: -369.77464 | EF86: -373.88325 | EG86: -377.99186 | EH86: -376.49527 | EI86: -369.61661 | EJ86: -373.72346 | EK86: -377.83031 | EL86: -376.32515 | EM86: -373.49171 | EN86: -373.49171 | EO86: -377.59601
C87: CFADS (EBITDA, guarantee fees, tax; after COD) | D87: EUR k | I87: =SUM(J87:EO87) -> 267075.31 | J87: =(J83+J59+J86)*(J$4>In_COD) -> 0 | K87: =(K83+K59+K86)*(K$4>In_COD) -> 0 | L87: =(L83+L59+L86)*(L$4>In_COD) -> 0 | M87: =(M83+M59+M86)*(M$4>In_COD) -> 0 | N87: =(N83+N59+N86)*(N$4>In_COD) -> 0 | O87: =(O83+O59+O86)*(O$4>In_COD) -> 0 | P87: =(P83+P59+P86)*(P$4>In_COD) -> 0 | Q87: =(Q83+Q59+Q86)*(Q$4>In_COD) -> 0 | ... EO87: =(EO83+EO59+EO86)*(EO$4>In_COD) -> 2139.7107
C88: CFADS ÷ target DSCR (E: annuity debt capacity, F: lowest quarter) | D88: EUR k | E88: =PV($F22,In_Debt_Tenor*Months_In_Year/Months_Per_Period,-$F88) -> 77983.992 | F88: =MIN($J88:$EO88) -> 1855.2337 | J88: =IF(J18=1,J87/In_DSCR,"") | K88: =IF(K18=1,K87/In_DSCR,"") | L88: =IF(L18=1,L87/In_DSCR,"") | M88: =IF(M18=1,M87/In_DSCR,"") | N88: =IF(N18=1,N87/In_DSCR,"") | O88: =IF(O18=1,O87/In_DSCR,"") | P88: =IF(P18=1,P87/In_DSCR,"") | Q88: =IF(Q18=1,Q87/In_DSCR,"") | ... EO88: =IF(EO18=1,EO87/In_DSCR,"")
C89: Debt quantum: per built wind MW | D89: EUR k | E89: =In_Debt_Per_MW*$F25 -> 49500
C90: Debt share of construction cost (E), share of capacity used (F) | D90: % | E90: =MIN(In_Gearing,$E88/-$E70,$E89/-$E70) -> 0.62734265 | F90: =$E90*-$E70/$E88 -> 0.63474565
C91: Debt at COD (E) and level annuity per quarter (F) | D91: EUR k | E91: =$E90*-$E70 -> 49500 | F91: =PMT($F22,In_Debt_Tenor*Months_In_Year/Months_Per_Period,-$E91) -> 1177.6015
A93: x | C93: Senior debt
C94: Interest paid | D94: EUR k | I94: =SUM(J94:EO94) -> -21156.092 | J94: =-I103*$F22*(J$4>In_COD) -> 0 | K94: =-J103*$F22*(K$4>In_COD) -> 0 | L94: =-K103*$F22*(L$4>In_COD) -> 0 | M94: =-L103*$F22*(M$4>In_COD) -> 0 | N94: =-M103*$F22*(N$4>In_COD) -> 0 | O94: =-N103*$F22*(O$4>In_COD) -> 0 | P94: =-O103*$F22*(P$4>In_COD) -> 0 | Q94: =-P103*$F22*(Q$4>In_COD) -> 0 | ... EO94: =-EN103*$F22*(EO$4>In_COD) -> 0
C95: Scheduled repayment (annuity) | D95: EUR k | I95: =SUM(J95:EO95) -> -49500 | J95: =-MIN(I103,$F91+J94)*J18 -> 0 | K95: =-MIN(J103,$F91+K94)*K18 -> 0 | L95: =-MIN(K103,$F91+L94)*L18 -> 0 | M95: =-MIN(L103,$F91+M94)*M18 -> 0 | N95: =-MIN(M103,$F91+N94)*N18 -> 0 | O95: =-MIN(N103,$F91+O94)*O18 -> 0 | P95: =-MIN(O103,$F91+P94)*P18 -> 0 | Q95: =-MIN(P103,$F91+Q94)*Q18 -> 0 | ... EO95: =-MIN(EN103,$F91+EO94)*EO18 -> 0
C96: Scheduled debt service | D96: EUR k | I96: =SUM(J96:EO96) -> -70656.092 | J96: =J94+J95 -> 0 | K96: =K94+K95 -> 0 | L96: =L94+L95 -> 0 | M96: =M94+M95 -> 0 | N96: =N94+N95 -> 0 | O96: =O94+O95 -> 0 | P96: =P94+P95 -> 0 | Q96: =Q94+Q95 -> 0 | ... EO96: =EO94+EO95 -> 0
C97: Cash sweep | D97: EUR k | I97: =SUM(J97:EO97) -> 0 | J97: =-MIN(I103+J95,In_Sweep*MAX(0,J87+J96))*(J$4>In_COD) -> 0 | K97: =-MIN(J103+K95,In_Sweep*MAX(0,K87+K96))*(K$4>In_COD) -> 0 | L97: =-MIN(K103+L95,In_Sweep*MAX(0,L87+L96))*(L$4>In_COD) -> 0 | M97: =-MIN(L103+M95,In_Sweep*MAX(0,M87+M96))*(M$4>In_COD) -> 0 | N97: =-MIN(M103+N95,In_Sweep*MAX(0,N87+N96))*(N$4>In_COD) -> 0 | O97: =-MIN(N103+O95,In_Sweep*MAX(0,O87+O96))*(O$4>In_COD) -> 0 | P97: =-MIN(O103+P95,In_Sweep*MAX(0,P87+P96))*(P$4>In_COD) -> 0 | Q97: =-MIN(P103+Q95,In_Sweep*MAX(0,Q87+Q96))*(Q$4>In_COD) -> 0 | ... EO97: =-MIN(EN103+EO95,In_Sweep*MAX(0,EO87+EO96))*(EO$4>In_COD) -> 0
C98: Debt service incl. sweep | D98: EUR k | I98: =SUM(J98:EO98) -> -70656.092 | J98: =J96+J97 -> 0 | K98: =K96+K97 -> 0 | L98: =L96+L97 -> 0 | M98: =M96+M97 -> 0 | N98: =N96+N97 -> 0 | O98: =O96+O97 -> 0 | P98: =P96+P97 -> 0 | Q98: =Q96+Q97 -> 0 | ... EO98: =EO96+EO97 -> 0
C99: Opening balance | D99: EUR k | J99: =I103 -> 0 | K99: =J103 -> 0 | L99: =K103 -> 0 | M99: =L103 -> 0 | N99: =M103 -> 0 | O99: =N103 -> 0 | P99: =O103 -> 0 | Q99: =P103 -> 0 | ... EO99: =EN103 -> 0
C100: Drawdown | D100: EUR k | I100: =SUM(J100:EO100) -> 47283.489 | J100: =-$E90*J70 -> 0 | K100: =-$E90*K70 -> 0 | L100: =-$E90*L70 -> 0 | M100: =-$E90*M70 -> 0 | N100: =-$E90*N70 -> 0 | O100: =-$E90*O70 -> 0 | P100: =-$E90*P70 -> 0 | Q100: =-$E90*Q70 -> 0 | ... EO100: =-$E90*EO70 -> 0
C101: Interest capitalised | D101: EUR k | I101: =SUM(J101:EO101) -> 2216.5113 | J101: =J99*$F22*(J$4<=In_COD) -> 0 | K101: =K99*$F22*(K$4<=In_COD) -> 0 | L101: =L99*$F22*(L$4<=In_COD) -> 0 | M101: =M99*$F22*(M$4<=In_COD) -> 0 | N101: =N99*$F22*(N$4<=In_COD) -> 0 | O101: =O99*$F22*(O$4<=In_COD) -> 0 | P101: =P99*$F22*(P$4<=In_COD) -> 0 | Q101: =Q99*$F22*(Q$4<=In_COD) -> 0 | ... EO101: =EO99*$F22*(EO$4<=In_COD) -> 0
C102: Repayment | D102: EUR k | I102: =SUM(J102:EO102) -> -49500 | J102: =J95+J97 -> 0 | K102: =K95+K97 -> 0 | L102: =L95+L97 -> 0 | M102: =M95+M97 -> 0 | N102: =N95+N97 -> 0 | O102: =O95+O97 -> 0 | P102: =P95+P97 -> 0 | Q102: =Q95+Q97 -> 0 | ... EO102: =EO95+EO97 -> 0
C103: Closing balance (E: at COD) | D103: EUR k | E103: =SUMIF($J$4:$EO$4,In_COD,$J103:$EO103) -> 49500 | J103: =SUM(J99:J102) -> 0 | K103: =SUM(K99:K102) -> 0 | L103: =SUM(L99:L102) -> 0 | M103: =SUM(M99:M102) -> 0 | N103: =SUM(N99:N102) -> 0 | O103: =SUM(O99:O102) -> 0 | P103: =SUM(P99:P102) -> 0 | Q103: =SUM(Q99:Q102) -> 0 | ... EO103: =SUM(EO99:EO102) -> 0
C104: Upfront fee | D104: EUR k | I104: =SUM(J104:EO104) -> -866.25 | J104: =-In_Upfront_Fee*$E103*(J99=0)*(J100>0) -> 0 | K104: =-In_Upfront_Fee*$E103*(K99=0)*(K100>0) -> 0 | L104: =-In_Upfront_Fee*$E103*(L99=0)*(L100>0) -> 0 | M104: =-In_Upfront_Fee*$E103*(M99=0)*(M100>0) -> 0 | N104: =-In_Upfront_Fee*$E103*(N99=0)*(N100>0) -> 0 | O104: =-In_Upfront_Fee*$E103*(O99=0)*(O100>0) -> 0 | P104: =-In_Upfront_Fee*$E103*(P99=0)*(P100>0) -> 0 | Q104: =-In_Upfront_Fee*$E103*(Q99=0)*(Q100>0) -> 0 | ... EO104: =-In_Upfront_Fee*$E103*(EO99=0)*(EO100>0) -> 0
C105: Commitment fee | D105: EUR k | I105: =SUM(J105:EO105) -> -462.26007 | J105: =-In_Commitment_Fee*($I100-SUM($J100:J100)+J100)*J$6*(J12>0) -> 0 | K105: =-In_Commitment_Fee*($I100-SUM($J100:K100)+K100)*K$6*(K12>0) -> 0 | L105: =-In_Commitment_Fee*($I100-SUM($J100:L100)+L100)*L$6*(L12>0) -> 0 | M105: =-In_Commitment_Fee*($I100-SUM($J100:M100)+M100)*M$6*(M12>0) -> 0 | N105: =-In_Commitment_Fee*($I100-SUM($J100:N100)+N100)*N$6*(N12>0) -> 0 | O105: =-In_Commitment_Fee*($I100-SUM($J100:O100)+O100)*O$6*(O12>0) -> 0 | P105: =-In_Commitment_Fee*($I100-SUM($J100:P100)+P100)*P$6*(P12>0) -> 0 | Q105: =-In_Commitment_Fee*($I100-SUM($J100:Q100)+Q100)*Q$6*(Q12>0) -> 0 | ... EO105: =-In_Commitment_Fee*($I100-SUM($J100:EO100)+EO100)*EO$6*(EO12>0) -> 0
C106: DSRA funded at COD, released at the end (E: balance) | D106: EUR k | E106: =-SUMIFS($J96:$EO96,$J$4:$EO$4,">"&In_COD,$J$4:$EO$4,"<="&EDATE(In_COD,In_DSRA_Months)) -> 1177.6015 | I106: =SUM(J106:EO106) -> 0 | J106: =$E106*(J19-J14) -> 0 | K106: =$E106*(K19-K14) -> 0 | L106: =$E106*(L19-L14) -> 0 | M106: =$E106*(M19-M14) -> 0 | N106: =$E106*(N19-N14) -> 0 | O106: =$E106*(O19-O14) -> 0 | P106: =$E106*(P19-P14) -> 0 | Q106: =$E106*(Q19-Q14) -> 0 | ... EO106: =$E106*(EO19-EO14) -> 0
C107: DSCR on scheduled debt service (E: minimum) | D107: x | E107: =MIN($J107:$EO107) -> 1.890521 | J107: =IF(J96<0,J87/-J96,"") | K107: =IF(K96<0,K87/-K96,"") | L107: =IF(L96<0,L87/-L96,"") | M107: =IF(M96<0,M87/-M96,"") | N107: =IF(N96<0,N87/-N96,"") | O107: =IF(O96<0,O87/-O96,"") | P107: =IF(P96<0,P87/-P96,"") | Q107: =IF(Q96<0,Q87/-Q96,"") | ... EO107: =IF(EO96<0,EO87/-EO96,"")
A109: x | C109: Tax
C110: Tax depreciation (E: base) | D110: EUR k | E110: =$I101-($I68+$I58+$I69+$I55+$I48+$I49+$I50) -> 83354.023 | I110: =SUM(J110:EO110) -> -83354.023 | J110: =-$E110*J20 -> 0 | K110: =-$E110*K20 -> 0 | L110: =-$E110*L20 -> 0 | M110: =-$E110*M20 -> 0 | N110: =-$E110*N20 -> 0 | O110: =-$E110*O20 -> 0 | P110: =-$E110*P20 -> 0 | Q110: =-$E110*Q20 -> 0 | ... EO110: =-$E110*EO20 -> 0
...

Sheet Checks
B2: =Dashboard!$C$3&" – Checks" -> Project Bana – Checks
C4: Period end | J4: =Calc_1!J$4 -> 46387 | K4: =Calc_1!K$4 -> 46477 | L4: =Calc_1!L$4 -> 46568 | M4: =Calc_1!M$4 -> 46660 | N4: =Calc_1!N$4 -> 46752 | O4: =Calc_1!O$4 -> 46843 | P4: =Calc_1!P$4 -> 46934 | Q4: =Calc_1!Q$4 -> 47026 | ... EO4: =Calc_1!EO$4 -> 58714
E9: Status | F9: Fails
A11: x | C11: Checks (0 = OK)
C12: Solver Tax_1: delta = 0 | D12: flag | E12: =IF(F12=0,"OK","CHECK") -> OK | F12: =N(Tax_1_Delta>Tolerance) -> 0
C13: Solver Tax_2: delta = 0 | D13: flag | E13: =IF(F13=0,"OK","CHECK") -> OK | F13: =N(Tax_2_Delta>Tolerance) -> 0
C14: Levers within the tender rules – Calc_1 | D14: flag | E14: =IF(F14=0,"OK","CHECK") -> OK | F14: =N(Calc_1!$E45+Calc_1!$F45>0) -> 0
C15: Levers within the tender rules – Calc_2 | D15: flag | E15: =IF(F15=0,"OK","CHECK") -> OK | F15: =N(Calc_2!$E45+Calc_2!$F45>0) -> 0
C16: COD falls on a quarter end – Calc_1 | D16: flag | E16: =IF(F16=0,"OK","CHECK") -> OK | F16: =N(COUNTIF(Calc_1!$J$4:$EO$4,In_COD)=0) -> 0
C17: COD falls on a quarter end – Calc_2 | D17: flag | E17: =IF(F17=0,"OK","CHECK") -> OK | F17: =N(COUNTIF(Calc_2!$J$4:$EO$4,In_COD)=0) -> 0
C18: Debt at COD within the DSCR capacity – Calc_1 | D18: flag | E18: =IF(F18=0,"OK","CHECK") -> OK | F18: =N(Calc_1!$F90>1+Tolerance) -> 0
C19: Debt at COD within the DSCR capacity – Calc_2 | D19: flag | E19: =IF(F19=0,"OK","CHECK") -> OK | F19: =N(Calc_2!$F90>1+Tolerance) -> 0
C20: Debt repaid by the end of the tenor – Calc_1 | D20: flag | E20: =IF(F20=0,"OK","CHECK") -> OK | F20: =SUM(J20:EO20) -> 0 | J20: =N((Calc_1!J$4>=Calc_1!$F18)*ABS(Calc_1!J103)>Tolerance) -> 0 | K20: =N((Calc_1!K$4>=Calc_1!$F18)*ABS(Calc_1!K103)>Tolerance) -> 0 | L20: =N((Calc_1!L$4>=Calc_1!$F18)*ABS(Calc_1!L103)>Tolerance) -> 0 | M20: =N((Calc_1!M$4>=Calc_1!$F18)*ABS(Calc_1!M103)>Tolerance) -> 0 | N20: =N((Calc_1!N$4>=Calc_1!$F18)*ABS(Calc_1!N103)>Tolerance) -> 0 | O20: =N((Calc_1!O$4>=Calc_1!$F18)*ABS(Calc_1!O103)>Tolerance) -> 0 | P20: =N((Calc_1!P$4>=Calc_1!$F18)*ABS(Calc_1!P103)>Tolerance) -> 0 | Q20: =N((Calc_1!Q$4>=Calc_1!$F18)*ABS(Calc_1!Q103)>Tolerance) -> 0 | ... EO20: =N((Calc_1!EO$4>=Calc_1!$F18)*ABS(Calc_1!EO103)>Tolerance) -> 0
C21: Debt repaid by the end of the tenor – Calc_2 | D21: flag | E21: =IF(F21=0,"OK","CHECK") -> OK | F21: =SUM(J21:EO21) -> 0 | J21: =N((Calc_2!J$4>=Calc_2!$F18)*ABS(Calc_2!J103)>Tolerance) -> 0 | K21: =N((Calc_2!K$4>=Calc_2!$F18)*ABS(Calc_2!K103)>Tolerance) -> 0 | L21: =N((Calc_2!L$4>=Calc_2!$F18)*ABS(Calc_2!L103)>Tolerance) -> 0 | M21: =N((Calc_2!M$4>=Calc_2!$F18)*ABS(Calc_2!M103)>Tolerance) -> 0 | N21: =N((Calc_2!N$4>=Calc_2!$F18)*ABS(Calc_2!N103)>Tolerance) -> 0 | O21: =N((Calc_2!O$4>=Calc_2!$F18)*ABS(Calc_2!O103)>Tolerance) -> 0 | P21: =N((Calc_2!P$4>=Calc_2!$F18)*ABS(Calc_2!P103)>Tolerance) -> 0 | Q21: =N((Calc_2!Q$4>=Calc_2!$F18)*ABS(Calc_2!Q103)>Tolerance) -> 0 | ... EO21: =N((Calc_2!EO$4>=Calc_2!$F18)*ABS(Calc_2!EO103)>Tolerance) -> 0
C22: DSCR not below target – Calc_1 | D22: flag | E22: =IF(F22=0,"OK","CHECK") -> OK | F22: =N(Calc_1!$E107<In_DSCR-Tolerance) -> 0
C23: DSCR not below target – Calc_2 | D23: flag | E23: =IF(F23=0,"OK","CHECK") -> OK | F23: =N(Calc_2!$E107<In_DSCR-Tolerance) -> 0
C24: Sources = uses to COD – Calc_1 | D24: flag | E24: =IF(F24=0,"OK","CHECK") -> OK | F24: =N(ABS(Calc_1!$E128+Calc_1!$I135-Calc_1!$E103)>Tolerance) -> 0
C25: Sources = uses to COD – Calc_2 | D25: flag | E25: =IF(F25=0,"OK","CHECK") -> OK | F25: =N(ABS(Calc_2!$E128+Calc_2!$I135-Calc_2!$E103)>Tolerance) -> 0
C26: XIRR returned a number on every route – Calc_1 | D26: flag | E26: =IF(F26=0,"OK","CHECK") -> OK | F26: =N(ISERROR(Calc_1!$E140))+N(ISERROR(Calc_1!$E153))+N(ISERROR(Calc_1!$E151))+N(ISERROR(Calc_1!$E147)) -> 0
C27: XIRR returned a number on every route – Calc_2 | D27: flag | E27: =IF(F27=0,"OK","CHECK") -> OK | F27: =N(ISERROR(Calc_2!$E140))+N(ISERROR(Calc_2!$E153))+N(ISERROR(Calc_2!$E151))+N(ISERROR(Calc_2!$E147)) -> 0
C28: Stored results = live case | D28: flag | E28: =IF(F28=0,"OK","CHECK") -> OK | F28: =--(SUMPRODUCT(ABS(Stored_Results-Live_Results)*(Scenario_Names=Scenario_Name))>Tolerance) -> 0
C30: Checks excluding stored = live | F30: =SUMPRODUCT(ABS(F12:F27)) -> 0
C32: Master check | E32: =IF(F32=0,"OK","CHECK") -> OK | F32: =SUMPRODUCT(ABS(F12:F28)) -> 0
C34: ***END***
