Workbook

Sheet Dashboard
B2: =C3&" – Dashboard" -> Project Bora – Dashboard
C3: Project Bora
C4: Bid strategy – BORA 1 / BORA 2 (2 x 100 MVA, Szombathely)
C5: Version | E5: v2
C6: Model date | E6: 46307
C7: Key-assumption set | E7: =Scenario_Name -> Base
C8: Master check | E8: =IF(Master_Check=0,"OK","CHECK") -> OK
C9: Item | D9: Unit | E9: BORA 1 | F9: BORA 2 | T9: Key assumptions | U9: Unit | V9: Live
A11: x | C11: The bid: commitments, points and impact vs the zero bid (macro) | E11: BORA 1 | F11: BORA 2 | H11: Offerable range | I11: Points B1 | J11: Points B2 | K11: Δ RtB profit €m B1 | L11: Δ RtB profit €m B2 | M11: Δ COD IRR B1 | N11: Δ COD IRR B2 | O11: Δ HTM IRR B1 | P11: Δ HTM IRR B2 | Q11: Δ securities €m B1 | R11: Δ securities €m B2 | T11: Key-assumption set
C12: Municipal one-off (ÖSZ-1) | D12: EUR k/MW | E12: 50 | F12: 50 | H12: 0 or 10–50 | I12: =Calc_1!$F$30 -> 20 | J12: =Calc_2!$F$30 -> 20 | K12: 0 | L12: 0 | M12: -0.011627184 | N12: -0.011627184 | O12: -0.0042666176 | P12: -0.0042666176 | Q12: 0 | R12: 0 | T12: Key-assumption set | U12: text | V12: Base
C13: Community contribution (ÖSZ-2) | D13: EUR/MWh | E13: 3 | F13: 2.01 | H13: 0 or 2–3 | I13: =Calc_1!$F$31 -> 15 | J13: =Calc_2!$F$31 -> 0.75 | K13: 0 | L13: 0 | M13: -0.025663154 | N13: -0.017097995 | O13: -0.0060842806 | P13: -0.0040713948 | Q13: 0 | R13: 0
C14: Overbuild (ÖSZ-3) | D14: % | E14: 0.51 | F14: 0.4 | H14: ≥ 0 % | I14: =Calc_1!$F$32 -> 10 | J14: =Calc_2!$F$32 -> 9 | K14: -0.47201652 | L14: -0.37020904 | M14: -0.011488431 | N14: -0.0090180271 | O14: -0.0024539818 | P14: -0.001931658 | Q14: 1.4182192 | R14: 1.1123288 | T14: Key assumptions (live)
C15: BESS power, share of MVA (ÖSZ-4) | D15: % | E15: 0.51 | F15: 0.4 | H15: ≤ wind MW | I15: =Calc_1!$F$33 -> 15 | J15: =Calc_2!$F$33 -> 13.5 | K15: -0.37074274 | L15: -0.29077862 | M15: -0.06507612 | N15: -0.051092496 | O15: -0.012392661 | P15: -0.0098626548 | Q15: 2.7945205 | R15: 2.1917808 | T15: Chinese turbines (0 EU, 1 CN) | U15: flag | V15: =In_CN_Turbine -> 0
C16: BESS duration | D16: h | E16: 4 | F16: 4 | H16: ≥ 4 h | T16: RtB price | U16: EUR k/MVA | V16: =In_RtB_Premium -> 150
C17: Performance security multiple (ÖSZ-6) | D17: x | E17: 1 | F17: 1 | H17: ≥ 1.0 | I17: =Calc_1!$F$35 -> 0 | J17: =Calc_2!$F$35 -> 0 | K17: 0 | L17: 0 | M17: 0 | N17: 0 | O17: 0 | P17: 0 | Q17: 0 | R17: 0 | T17: COD price, EU | U17: EUR k/MW | V17: =In_COD_Price -> 2450
C18: Partial award accepted (ÖSZ-5) | D18: flag | E18: 1 | F18: 1 | H18: 0 / 1 | I18: =Calc_1!$F$34 -> 5 | J18: =Calc_2!$F$34 -> 5 | K18: 0 | L18: 0 | M18: 0 | N18: 0 | O18: 0 | P18: 0 | Q18: 0 | R18: 0 | T18: Turbine price, EU | U18: EUR k/MW | V18: =In_Turbine -> 600
C19: Brownfield site (ÖSZ-7) | D19: flag | E19: 0 | F19: 0 | H19: 0 / 1 | I19: =Calc_1!$F$36 -> 0 | J19: =Calc_2!$F$36 -> 0 | K19: 0 | L19: 0 | M19: 0 | N19: 0 | O19: 0 | P19: 0 | Q19: 0 | R19: 0 | T19: PPA price at COD | U19: EUR/MWh | V19: =In_PPA_Price -> 90
C20: Shared connection (ÖSZ-8) | D20: flag | E20: 1 | F20: 1 | H20: 0 / 1 | I20: =Calc_1!$F$37 -> 5 | J20: =Calc_2!$F$37 -> 5 | K20: 0 | L20: 0 | M20: 0 | N20: 0 | O20: 0 | P20: 0 | Q20: 0 | R20: 0 | T20: Gearing, EU | U20: % | V20: =In_Gearing -> 0.6
C21: EU turbines ≥ 80 % (ÖSZ-9) | D21: flag | E21: 1 | F21: 1 | H21: 0 / 1 | I21: =Calc_1!$F$38 -> 12 | J21: =Calc_2!$F$38 -> 12 | K21: 0 | L21: 0 | M21: 0 | N21: 0 | O21: 0 | P21: 0 | Q21: 0 | R21: 0 | T21: Debt rate | U21: % | V21: =In_Debt_Rate -> 0.05
C22: EU transformers ≥ 80 % (ÖSZ-9) | D22: flag | E22: 1 | F22: 1 | H22: 0 / 1 | I22: =Calc_1!$F$39 -> 3 | J22: =Calc_2!$F$39 -> 3 | K22: 0 | L22: 0 | M22: 0 | N22: 0 | O22: 0 | P22: 0 | Q22: 0 | R22: 0 | T22: Discount rate | U22: % | V22: =In_Discount_Rate -> 0.08
T23: COD | U23: date | V23: =In_COD -> 48121
A24: x | C24: Returns at a glance | E24: BORA 1 | F24: BORA 2 | H24: Zero bid | I24: Δ B1 | J24: Δ B2 | T24: FX | U24: HUF/EUR | V24: =In_FX -> 365
C25: Points, live turbine route | D25: points | E25: =Calc_1!$E41 -> 85 | F25: =Calc_2!$E41 -> 68.25 | H25: 0 | T25: Interest freeze on | U25: flag | V25: =In_Freeze_On -> 1
C26: FEP profit – RtB route | D26: EUR m | E26: =Calc_1!$I151/Thousand -> 6.5467587 | F26: =Calc_2!$I151/Thousand -> 6.7285303 | H26: 7.389518 | I26: -0.84275926 | J26: -0.66098766 | T26: Overbuild built | U26: flag | V26: =In_Overbuild_Built -> 0
C27: FEP IRR – RtB route | D27: % | E27: =Calc_1!$E152 -> 0.22151076 | F27: =Calc_2!$E152 -> 0.22914856 | H27: 0.25782628 | I27: -0.036315523 | J27: -0.028677728 | T27: BESS built | U27: flag | V27: =In_BESS_Built -> 1
C28: FEP IRR – sale at COD | D28: % | E28: =Calc_1!$E169 -> 0.37845437 | F28: =Calc_2!$E169 -> 0.40458152 | H28: 0.49563542 | I28: -0.11718105 | J28: -0.091053893 | T28: Sanction regime (1 pro rata, 2 full) | U28: flag | V28: =In_Sanction_Regime -> 1
C29: FEP NPV – sale at COD | D29: EUR m | E29: =Calc_1!$E171/Thousand -> 30.754863 | F29: =Calc_2!$E171/Thousand -> 33.641147 | H29: 44.610552 | I29: -13.855689 | J29: -10.969406 | T29: ÖSZ-4 basis (0 MVA, 1 wind) | U29: flag | V29: =In_OSZ4_Basis -> 0
C30: FEP IRR – hold to maturity | D30: % | E30: =Calc_1!$E184 -> 0.094907301 | F30: =Calc_2!$E184 -> 0.099496579 | H30: 0.11865423 | I30: -0.023746933 | J30: -0.019157655
C31: FEP NPV – hold to maturity | D31: EUR m | E31: =Calc_1!$E186/Thousand -> 13.363165 | F31: =Calc_2!$E186/Thousand -> 17.199101 | H31: 31.424829 | I31: -18.061664 | J31: -14.225728
C32: Total commitment | D32: EUR m | E32: =Calc_1!$E177/Thousand -> 171.21379 | F32: =Calc_2!$E177/Thousand -> 167.28901 | H32: 147.79968 | I32: 23.414104 | J32: 19.489327
A34: x | C34: Commitment overview (total in Returns at a glance) | E34: BORA 1 | F34: BORA 2
C35: Securities: cash posted and guarantee outstanding | D35: EUR m | E35: =Calc_1!$E173/Thousand -> 8.2346575 | F35: =Calc_2!$E173/Thousand -> 7.3260274
C36: Devex, land, signing and DD | D36: EUR m | E36: =Calc_1!$E174/Thousand -> 3.5196245 | F36: =Calc_2!$E174/Thousand -> 3.5196245
C37: Construction capex incl. connection fees, municipal, pre-COD lease | D37: EUR m | E37: =Calc_1!$E175/Thousand -> 150.91288 | F37: =Calc_2!$E175/Thousand -> 148.27288
C38: Financing: IDC, debt fees, guarantee fees | D38: EUR m | E38: =Calc_1!$E176/Thousand -> 8.5466259 | F38: =Calc_2!$E176/Thousand -> 8.1704781
C39: Memo, not in the total: PB call if overbuild not built | D39: EUR m | E39: =Calc_1!$E178/Thousand -> 1.4182192 | F39: =Calc_2!$E178/Thousand -> 1.1123288
C40: Memo, not in the total: full PB call | D40: EUR m | E40: =Calc_1!$F178/Thousand -> 6.9935616 | F40: =Calc_2!$F178/Thousand -> 6.0849315
A42: x | C42: Points and validity | E42: BORA 1 | F42: BORA 2
C43: Wind committed | D43: MW | E43: =Calc_1!$E24 -> 151 | F43: =Calc_2!$E24 -> 140
C44: Wind built | D44: MW | E44: =Calc_1!$F24 -> 100 | F44: =Calc_2!$F24 -> 100
C45: BESS committed | D45: MW | E45: =Calc_1!$E25 -> 51 | F45: =Calc_2!$E25 -> 40
C46: Capacity tests (group cap, overbuild, BESS ≤ wind, 4 h) | D46: flag | E46: =IF(Calc_1!$E42=0,"OK","CHECK") -> OK | F46: =IF(Calc_2!$E42=0,"OK","CHECK") -> OK
C47: Commitments within the offerable range | D47: flag | E47: =IF(Calc_1!$F42=0,"OK","CHECK") -> OK | F47: =IF(Calc_2!$F42=0,"OK","CHECK") -> OK
A49: x | C49: Securities and fees | E49: BORA 1 | F49: BORA 2 | H49: Form | I49: Posted | J49: Released
C50: Participation fee | D50: EUR m | E50: =Calc_1!$E47/Thousand -> 0.0082191781 | F50: =Calc_2!$E47/Thousand -> 0.0082191781 | H50: cash | I50: =In_Bid_Date -> 46325 | J50: –
C51: Bid security | D51: EUR m | E51: =Calc_1!$E48/Thousand -> 1.3987123 | F51: =Calc_2!$E48/Thousand -> 1.2169863 | H51: guarantee | I51: =In_Bid_Date -> 46325 | J51: =Calc_1!$F$49 -> 46384
C52: Performance security | D52: EUR m | E52: =Calc_1!$E49/Thousand -> 6.9935616 | F52: =Calc_2!$E49/Thousand -> 6.0849315 | H52: guarantee | I52: =Calc_1!$F$49 -> 46384 | J52: exit / PB release
C53: TSO connection-request security | D53: EUR m | E53: =Calc_1!$E50/Thousand -> 1.2328767 | F53: =Calc_2!$E50/Thousand -> 1.2328767 | H53: cash | I53: =In_TSO_Date -> 46386 | J53: credited
C54: Direct connection fee | D54: EUR m | E54: =Calc_1!$E51/Thousand -> 1.3927282 | F54: =Calc_2!$E51/Thousand -> 1.3927282 | H54: cash | I54: =In_HCSSZ_Date -> 47126 | J54: –
C55: Indirect connection fee, net | D55: EUR m | E55: =Calc_1!$E52/Thousand -> 18.786659 | F55: =Calc_2!$E52/Thousand -> 18.786659 | H55: cash | I55: =In_HCSSZ_Date -> 47126 | J55: –
C56: Connection capacity at risk | D56: MVA | E56: =Calc_1!$E87 -> 33.774834 | F56: =Calc_2!$E87 -> 28.571429
C57: 3-year group exclusion possible (if the PB loss counts as a call) | D57: flag | E57: =Calc_1!$E88 -> 1 | F57: =Calc_2!$E88 -> 1
A59: x | C59: RtB exit | E59: BORA 1 | F59: BORA 2
C60: RtB exit date (a quarter end) | D60: date | E60: 47483 | F60: 47483
C61: RtB price | D61: EUR m | E61: =Calc_1!$E130/Thousand -> 15 | F61: =Calc_2!$E130/Thousand -> 15
C62: Exit waterfall (paid) | E62: BORA 1 | F62: BORA 2
C63: Cash available (price + buyer reimbursement) | D63: EUR m | E63: =Calc_1!$F132/Thousand -> 36.842709 | F63: =Calc_2!$F132/Thousand -> 36.842709
C64: Sale costs | D64: EUR m | E64: =Calc_1!$F133/Thousand -> 0.5 | F64: =Calc_2!$F133/Thousand -> 0.5
C65: Recoverable principal | D65: EUR m | E65: =Calc_1!$F134/Thousand -> 21.412264 | F65: =Calc_2!$F134/Thousand -> 21.412264
C66: 12 % return | D66: EUR m | E66: =Calc_1!$F135/Thousand -> 1.5645366 | F66: =Calc_2!$F135/Thousand -> 1.5645366
C67: Land principal | D67: EUR m | E67: =Calc_1!$F136/Thousand -> 0.43044452 | F67: =Calc_2!$F136/Thousand -> 0.43044452
C68: At-risk return (20 %, 2x floor) | D68: EUR m | E68: =Calc_1!$F137/Thousand -> 3.1196245 | F68: =Calc_2!$F137/Thousand -> 3.1196245
C69: 6 % guarantee return | D69: EUR m | E69: =Calc_1!$F138/Thousand -> 1.1204802 | F69: =Calc_2!$F138/Thousand -> 0.97490312
C70: DSA | D70: EUR m | E70: =Calc_1!$F139/Thousand -> 1.2006597 | F70: =Calc_2!$F139/Thousand -> 1.1131944
C71: Distributable at the exit | D71: EUR m | E71: =Calc_1!$F140/Thousand -> 7.494699 | F71: =Calc_2!$F140/Thousand -> 7.7277413
C72: Exit split, devex-file view | E72: BORA 1 | F72: BORA 2
C73: FEP: claims + 70 % | D73: EUR m | E73: =Calc_1!$E144/Thousand -> 11.050931 | F73: =Calc_2!$E144/Thousand -> 11.068483
C74: A.RES: DSA + 30 % | D74: EUR m | E74: =Calc_1!$F144/Thousand -> 3.4490694 | F74: =Calc_2!$F144/Thousand -> 3.4315168
C75: Total | D75: EUR m | E75: =Calc_1!$E145/Thousand -> 14.5 | F75: =Calc_2!$E145/Thousand -> 14.5
C76: FEP per installed wind MW | D76: EUR k/MW | E76: =Calc_1!$E146 -> 73.184971 | F76: =Calc_2!$E146 -> 79.060594
C77: A.RES per installed wind MW | D77: EUR k/MW | E77: =Calc_1!$F146 -> 22.841519 | F77: =Calc_2!$F146 -> 24.510834
C78: Total per installed wind MW | D78: EUR k/MW | E78: =Calc_1!$E148 -> 96.02649 | F78: =Calc_2!$E148 -> 103.57143
C79: FEP result – RtB route | E79: BORA 1 | F79: BORA 2
C80: Receipts at the exit | D80: EUR m | E80: =Calc_1!$F141/Thousand -> 32.893639 | F80: =Calc_2!$F141/Thousand -> 32.911192
C81: Outlays: devex, land, deposits, connection fees, signing | D81: EUR m | E81: =Calc_1!$E147/Thousand -> -24.940108 | F81: =Calc_2!$E147/Thousand -> -24.940108
C82: Guarantee fees (6 % carry) | D82: EUR m | E82: =Calc_1!$E58/Thousand -> -1.2781548 | F82: =Calc_2!$E58/Thousand -> -1.1120921
C83: Tax at the exit | D83: EUR m | E83: =Calc_1!$E150/Thousand -> -0.12861786 | F83: =Calc_2!$E150/Thousand -> -0.13046157
C84: FEP profit | D84: EUR m | E84: =Calc_1!$I151/Thousand -> 6.5467587 | F84: =Calc_2!$I151/Thousand -> 6.7285303
C85: FEP MOIC – RtB route | D85: x | E85: =Calc_1!$E153 -> 1.2497022 | F85: =Calc_2!$E153 -> 1.2582711
C86: FEP NPV – RtB route | D86: EUR m | E86: =Calc_1!$E154/Thousand -> 3.3285425 | F86: =Calc_2!$E154/Thousand -> 3.4850654
A88: x | C88: Sale at COD | E88: BORA 1 | F88: BORA 2
C89: All-in cost to COD | D89: EUR m | E89: =Calc_1!$E179/Thousand -> 164.22022 | F89: =Calc_2!$E179/Thousand -> 161.20408
C90: All-in cost per built MW | D90: EUR k/MW | E90: =Calc_1!$E180 -> 1642.2022 | F90: =Calc_2!$E180 -> 1612.0408
C91: Sale price (built MW, after bottleneck loss) | D91: EUR m | E91: =Calc_1!$E159/Thousand -> 245 | F91: =Calc_2!$E159/Thousand -> 245
C92: COD price effect (community, sanction) | D92: EUR m | E92: =Calc_1!$F159/Thousand -> -3.8390812 | F92: =Calc_2!$F159/Thousand -> -1.0949714
C93: Debt repaid at COD | D93: EUR m | E93: =Calc_1!$E161/Thousand -> 94.220504 | F93: =Calc_2!$E161/Thousand -> 92.565471
C94: FEP proceeds at COD | D94: EUR m | E94: =Calc_1!$F167/Thousand -> 124.44236 | F94: =Calc_2!$F167/Thousand -> 127.19114
C95: FEP profit – sale at COD | D95: EUR m | E95: =Calc_1!$I168/Thousand -> 54.442643 | F95: =Calc_2!$I168/Thousand -> 58.552537
C96: FEP MOIC – sale at COD | D96: x | E96: =Calc_1!$E170 -> 1.7777551 | F96: =Calc_2!$E170 -> 1.8530555
A98: x | C98: Hold to maturity | E98: BORA 1 | F98: BORA 2
C99: FEP MOIC – hold to maturity | D99: x | E99: =Calc_1!$E185 -> 4.8933539 | F99: =Calc_2!$E185 -> 5.1257317
C100: Minimum DSCR (memo) | D100: x | E100: =Calc_1!$E187 -> 1.3284735 | F100: =Calc_2!$E187 -> 1.3687904
A102: x | C102: Stored results by key-assumption set | E102: Live | H102: =Inputs!H$7 -> Base | I102: =Inputs!I$7 -> Overbuild built | J102: =Inputs!J$7 -> Full PB call | K102: =Inputs!K$7 -> Freeze off | L102: =Inputs!L$7 -> Low premium | M102: =Inputs!M$7 -> ÖSZ-4 on wind
C103: Points, live turbine route – BORA 1 | D103: points | E103: =Calc_1!$E41 -> 85 | H103: 85 | I103: 85 | J103: 85 | K103: 85 | L103: 85 | M103: 80.5
C104: Points, live turbine route – BORA 2 | D104: points | E104: =Calc_2!$E41 -> 68.25 | H104: 68.25 | I104: 68.25 | J104: 68.25 | K104: 68.25 | L104: 68.25 | M104: 63.75
C105: FEP profit – RtB route – BORA 1 | D105: EUR m | E105: =Calc_1!$I151/Thousand -> 6.5467587 | H105: 6.5467587 | I105: 6.5467587 | J105: 6.5467587 | K105: 6.872957 | L105: 3.0467587 | M105: 6.5467587
C106: FEP profit – RtB route – BORA 2 | D106: EUR m | E106: =Calc_2!$I151/Thousand -> 6.7285303 | H106: 6.7285303 | I106: 6.7285303 | J106: 6.7285303 | K106: 7.048226 | L106: 3.2285303 | M106: 6.7285303
C107: FEP IRR – sale at COD – BORA 1 | D107: % | E107: =Calc_1!$E169 -> 0.37845437 | H107: 0.37845437 | I107: 0.54445554 | J107: 0.35780279 | K107: 0.38148941 | L107: 0.37845437 | M107: 0.37845437
C108: FEP IRR – sale at COD – BORA 2 | D108: % | E108: =Calc_2!$E169 -> 0.40458152 | H108: 0.40458152 | I108: 0.53841888 | J108: 0.38660193 | K108: 0.40749532 | L108: 0.40458152 | M108: 0.40458152
C109: FEP IRR – hold to maturity – BORA 1 | D109: % | E109: =Calc_1!$E184 -> 0.094907301 | H109: 0.094907301 | I109: 0.11488286 | J109: 0.090505034 | K109: 0.09537475 | L109: 0.09642627 | M109: 0.094907301
...

Sheet Inputs
B2: =Dashboard!$C$3&" – Inputs and scenarios" -> Project Bora – Inputs and scenarios
B4: Scenario selected | D4: Set on the Dashboard | F4: =Scenario_Name -> Base
B5: Scenario number | F5: =MATCH(Scenario_Name,Scenario_Names,0) -> 1
B7: Input | C7: Unit | D7: Source / note | F7: Live | H7: Base | I7: Overbuild built | J7: Full PB call | K7: Freeze off | L7: Low premium | M7: ÖSZ-4 on wind
A10: x | C10: Constants
B11: Thousand | C11: # | D11: Scale | F11: 1000
B12: Million | C12: # | D12: Scale | F12: 1000000
B13: Days In Year | C13: days | D13: Day count for year fractions and XIRR | F13: 365
B14: Months In Year | C14: months | F14: 12
B15: Months Per Period | C15: months | D15: Timeline periodicity (quarterly) | F15: 3
B16: Tolerance | C16: # | D16: Check and solver tolerance | F16: 1e-06
A18: x | C18: Timing
B19: Model start date | C19: date | D19: Timeline start | F19: =IF(INDEX($H19:$O19,1,Scenario_Selected)="",$H19,INDEX($H19:$O19,1,Scenario_Selected)) -> 46204 | H19: 46204
B20: Signing fee and DD paid | C20: date | D20: Old engine Inputs E27 | F20: =IF(INDEX($H20:$O20,1,Scenario_Selected)="",$H20,INDEX($H20:$O20,1,Scenario_Selected)) -> 46234 | H20: 46234
B21: Signing (DSA accrual start) | C21: date | D21: Old engine Inputs E70 | F21: =IF(INDEX($H21:$O21,1,Scenario_Selected)="",$H21,INDEX($H21:$O21,1,Scenario_Selected)) -> 46321 | H21: 46321
B22: Devex contingency paid | C22: date | D22: Old engine Devex_FEP row 38 | F22: =IF(INDEX($H22:$O22,1,Scenario_Selected)="",$H22,INDEX($H22:$O22,1,Scenario_Selected)) -> 47118 | H22: 47118
B23: Notice to proceed | C23: date | D23: Old engine Inputs E154 | F23: =IF(INDEX($H23:$O23,1,Scenario_Selected)="",$H23,INDEX($H23:$O23,1,Scenario_Selected)) -> 47391 | H23: 47391
B24: Commercial operation date | C24: date | D24: Bora!N16 | F24: =IF(INDEX($H24:$O24,1,Scenario_Selected)="",$H24,INDEX($H24:$O24,1,Scenario_Selected)) -> 48121 | H24: 48121
B25: Operating life | C25: years | D25: Old engine Inputs E157 | F25: =IF(INDEX($H25:$O25,1,Scenario_Selected)="",$H25,INDEX($H25:$O25,1,Scenario_Selected)) -> 30 | H25: 30
B26: Interest freeze start | C26: date | D26: Old engine Inputs E64 | F26: =IF(INDEX($H26:$O26,1,Scenario_Selected)="",$H26,INDEX($H26:$O26,1,Scenario_Selected)) -> 47299 | H26: 47299
B27: Interest freeze end (accrual resumes) | C27: date | D27: Old engine Inputs E73 | F27: =IF(INDEX($H27:$O27,1,Scenario_Selected)="",$H27,INDEX($H27:$O27,1,Scenario_Selected)) -> 47484 | H27: 47484
B28: Interest freeze on (1 = yes) | C28: flag | D28: User 09-Oct-26 (Inputs E64) | F28: =IF(INDEX($H28:$O28,1,Scenario_Selected)="",$H28,INDEX($H28:$O28,1,Scenario_Selected)) -> 1 | H28: 1 | K28: 0
B29: Sanction paid after COD | C29: months | D29: Kiírás XIII.17; old Tender E31 | F29: =IF(INDEX($H29:$O29,1,Scenario_Selected)="",$H29,INDEX($H29:$O29,1,Scenario_Selected)) -> 6 | H29: 6
A31: x | C31: Money, tax and JV
B32: FX rate | C32: HUF/EUR | D32: Old engine Inputs E11 | F32: =IF(INDEX($H32:$O32,1,Scenario_Selected)="",$H32,INDEX($H32:$O32,1,Scenario_Selected)) -> 365 | H32: 365
B33: Corporate income tax | C33: % | D33: Old engine Inputs E12 | F33: =IF(INDEX($H33:$O33,1,Scenario_Selected)="",$H33,INDEX($H33:$O33,1,Scenario_Selected)) -> 0.09 | H33: 0.09
B34: Signing fee to current owners | C34: EUR k | D34: Old engine Inputs E24 | F34: =IF(INDEX($H34:$O34,1,Scenario_Selected)="",$H34,INDEX($H34:$O34,1,Scenario_Selected)) -> 250 | H34: 250
B35: Transaction and DD costs | C35: EUR k | D35: Old engine Inputs E25 | F35: =IF(INDEX($H35:$O35,1,Scenario_Selected)="",$H35,INDEX($H35:$O35,1,Scenario_Selected)) -> 150 | H35: 150
B36: Sale costs at exit | C36: EUR k | D36: Old engine Inputs E26 | F36: =IF(INDEX($H36:$O36,1,Scenario_Selected)="",$H36,INDEX($H36:$O36,1,Scenario_Selected)) -> 500 | H36: 500
B37: FEP share of distributable proceeds | C37: % | D37: Old engine Inputs E33 | F37: =IF(INDEX($H37:$O37,1,Scenario_Selected)="",$H37,INDEX($H37:$O37,1,Scenario_Selected)) -> 0.7 | H37: 0.7
B38: Developer success fee (DSA) per year | C38: EUR k/MW | D38: Old engine Inputs E36 | F38: =IF(INDEX($H38:$O38,1,Scenario_Selected)="",$H38,INDEX($H38:$O38,1,Scenario_Selected)) -> 2.5 | H38: 2.5
B39: DSA cap | C39: EUR k/MW | D39: Old engine Inputs E37 | F39: =IF(INDEX($H39:$O39,1,Scenario_Selected)="",$H39,INDEX($H39:$O39,1,Scenario_Selected)) -> 10 | H39: 10
A41: x | C41: Tender
B42: Points rounded to decimals | C42: # | D42: Kiírás X.1 b | F42: 2
B43: Net connection capacity per bid | C43: MVA | D43: Old engine Calc E74 | F43: =IF(INDEX($H43:$O43,1,Scenario_Selected)="",$H43,INDEX($H43:$O43,1,Scenario_Selected)) -> 100 | H43: 100
B44: Cap per group per node | C44: MVA | D44: Kiírás V.2 | F44: =IF(INDEX($H44:$O44,1,Scenario_Selected)="",$H44,INDEX($H44:$O44,1,Scenario_Selected)) -> 100 | H44: 100
B45: Build shortfall tolerated without sanction | C45: % | D45: GYIK 28, 30 | F45: =IF(INDEX($H45:$O45,1,Scenario_Selected)="",$H45,INDEX($H45:$O45,1,Scenario_Selected)) -> 0.1 | H45: 0.1
B46: Minimum BESS duration | C46: h | D46: Kiírás Annex 8; GYIK Q5 | F46: =IF(INDEX($H46:$O46,1,Scenario_Selected)="",$H46,INDEX($H46:$O46,1,Scenario_Selected)) -> 4 | H46: 4
B47: ÖSZ-4 basis (0 = net MVA, 1 = committed wind) | C47: flag | D47: User 12-Oct-26; GYIK Q20 = 1 | F47: =IF(INDEX($H47:$O47,1,Scenario_Selected)="",$H47,INDEX($H47:$O47,1,Scenario_Selected)) -> 0 | H47: 0 | M47: 1
A49: x | C49: Deposits and fees (timeline order)
B50: Security base: benchmark investment, wind | C50: mHUF/MW | D50: Kiírás Annex 2 | F50: =IF(INDEX($H50:$O50,1,Scenario_Selected)="",$H50,INDEX($H50:$O50,1,Scenario_Selected)) -> 406 | H50: 406
B51: Security base: benchmark investment, BESS | C51: mHUF/MWh | D51: Kiírás Annex 2 | F51: =IF(INDEX($H51:$O51,1,Scenario_Selected)="",$H51,INDEX($H51:$O51,1,Scenario_Selected)) -> 200 | H51: 200
B52: Bid submission: fee paid, bid security posted | C52: date | D52: Kiírás VI.5; Old engine Inputs E95 | F52: =IF(INDEX($H52:$O52,1,Scenario_Selected)="",$H52,INDEX($H52:$O52,1,Scenario_Selected)) -> 46325 | H52: 46325
B53: Participation fee per bid (cash, not refunded) | C53: mHUF | D53: Kiírás VI.4 | F53: =IF(INDEX($H53:$O53,1,Scenario_Selected)="",$H53,INDEX($H53:$O53,1,Scenario_Selected)) -> 3 | H53: 3
B54: Bid security (guarantee), share of base | C54: % | D54: Kiírás VIII.2 | F54: =IF(INDEX($H54:$O54,1,Scenario_Selected)="",$H54,INDEX($H54:$O54,1,Scenario_Selected)) -> 0.005 | H54: 0.005
B55: Award decision | C55: date | D55: Old engine Inputs E96 | F55: =IF(INDEX($H55:$O55,1,Scenario_Selected)="",$H55,INDEX($H55:$O55,1,Scenario_Selected)) -> 46369 | H55: 46369
B56: Performance security posted after award (bid released) | C56: days | D56: Kiírás XII.5, GYIK 68 | F56: =IF(INDEX($H56:$O56,1,Scenario_Selected)="",$H56,INDEX($H56:$O56,1,Scenario_Selected)) -> 15 | H56: 15
B57: Performance security (guarantee), minimum share of base | C57: % | D57: Kiírás XII.3 | F57: =IF(INDEX($H57:$O57,1,Scenario_Selected)="",$H57,INDEX($H57:$O57,1,Scenario_Selected)) -> 0.025 | H57: 0.025
B58: Connection request: TSO security posted | C58: date | D58: Old engine Inputs E97 | F58: =IF(INDEX($H58:$O58,1,Scenario_Selected)="",$H58,INDEX($H58:$O58,1,Scenario_Selected)) -> 46386 | H58: 46386
B59: TSO security (cash, credited to the indirect fee) | C59: mHUF/MVA | D59: Old engine Inputs E83 | F59: =IF(INDEX($H59:$O59,1,Scenario_Selected)="",$H59,INDEX($H59:$O59,1,Scenario_Selected)) -> 4.5 | H59: 4.5
B60: Connection agreement (HCSSZ): fees paid | C60: date | D60: Old engine Inputs E99 | F60: =IF(INDEX($H60:$O60,1,Scenario_Selected)="",$H60,INDEX($H60:$O60,1,Scenario_Selected)) -> 47126 | H60: 47126
B61: Direct connection fee per connection point (cash) | C61: mHUF | D61: BORA_Devex 02-Oct row 19 | F61: =IF(INDEX($H61:$O61,1,Scenario_Selected)="",$H61,INDEX($H61:$O61,1,Scenario_Selected)) -> 508.3458 | H61: 508.3458
... B64: Bank guarantee fee on guarantees outstanding | C64: % | D64: Old engine Inputs E113 | F64: =IF(INDEX($H64:$O64,1,Scenario_Selected)="",$H64,INDEX($H64:$O64,1,Scenario_Selected)) -> 0.06 | H64: 0.06
A66: x | C66: FEP claims and fees
B67: Return on cash lines | C67: % | D67: BORA_Devex 02-Oct V18 | F67: =IF(INDEX($H67:$O67,1,Scenario_Selected)="",$H67,INDEX($H67:$O67,1,Scenario_Selected)) -> 0.12 | H67: 0.12
B68: Return on guarantee face value | C68: % | D68: BORA_Devex 02-Oct V17 | F68: =IF(INDEX($H68:$O68,1,Scenario_Selected)="",$H68,INDEX($H68:$O68,1,Scenario_Selected)) -> 0.06 | H68: 0.06
B69: Return on devex and land (at risk) | C69: % | D69: BORA_Devex 02-Oct V19 | F69: =IF(INDEX($H69:$O69,1,Scenario_Selected)="",$H69,INDEX($H69:$O69,1,Scenario_Selected)) -> 0.2 | H69: 0.2
B70: Minimum multiple on at-risk principal | C70: x | D70: BORA_Devex 02-Oct V20 | F70: =IF(INDEX($H70:$O70,1,Scenario_Selected)="",$H70,INDEX($H70:$O70,1,Scenario_Selected)) -> 2 | H70: 2
B71: Contingency on devex, land and fee | C71: % | D71: Old engine Inputs E68 | F71: =IF(INDEX($H71:$O71,1,Scenario_Selected)="",$H71,INDEX($H71:$O71,1,Scenario_Selected)) -> 0.1 | H71: 0.1
A73: x | C73: Exit prices
B74: RtB price (no price effect) | C74: EUR k/MVA | D74: Bora!N5; user 12-Oct-26 | F74: =IF(INDEX($H74:$O74,1,Scenario_Selected)="",$H74,INDEX($H74:$O74,1,Scenario_Selected)) -> 150 | H74: 150 | L74: 100
B75: FEP discount rate (NPV, price PV) | C75: % | D75: Old engine Inputs E253 | F75: =IF(INDEX($H75:$O75,1,Scenario_Selected)="",$H75,INDEX($H75:$O75,1,Scenario_Selected)) -> 0.08 | H75: 0.08
B76: Sale price at COD per built MW, EU turbines | C76: EUR k/MW | D76: Bora!N6 | F76: =IF(INDEX($H76:$O76,1,Scenario_Selected)="",$H76,INDEX($H76:$O76,1,Scenario_Selected)) -> 2450 | H76: 2450
B77: Sale price at COD per built MW, CN turbines | C77: EUR k/MW | D77: Bora!N7 | F77: =IF(INDEX($H77:$O77,1,Scenario_Selected)="",$H77,INDEX($H77:$O77,1,Scenario_Selected)) -> 2100 | H77: 2100
B78: COD price reference: community contribution | C78: EUR/MWh | D78: Bora!E7 | F78: =IF(INDEX($H78:$O78,1,Scenario_Selected)="",$H78,INDEX($H78:$O78,1,Scenario_Selected)) -> 2 | H78: 2
B79: COD price effect passed into the price | C79: % | D79: Old engine Tender E30 | F79: =IF(INDEX($H79:$O79,1,Scenario_Selected)="",$H79,INDEX($H79:$O79,1,Scenario_Selected)) -> 1 | H79: 1
B80: Buyer discount rate | C80: % | D80: Old engine Inputs E224 | F80: =IF(INDEX($H80:$O80,1,Scenario_Selected)="",$H80,INDEX($H80:$O80,1,Scenario_Selected)) -> 0.08 | H80: 0.08
A82: x | C82: Build switches
B83: Overbuild built (1 = yes) | C83: flag | D83: SPEC v2 §6 (set = meeting file) | F83: =IF(INDEX($H83:$O83,1,Scenario_Selected)="",$H83,INDEX($H83:$O83,1,Scenario_Selected)) -> 0 | H83: 0 | I83: 1
B84: BESS built (1 = yes) | C84: flag | D84: SPEC v2 §6 | F84: =IF(INDEX($H84:$O84,1,Scenario_Selected)="",$H84,INDEX($H84:$O84,1,Scenario_Selected)) -> 1 | H84: 1
B85: Sanction regime (1 pro rata, 2 full call) | C85: flag | D85: GYIK 28/30 (1); Kiírás XIII.17, GYIK 72 (2) | F85: =IF(INDEX($H85:$O85,1,Scenario_Selected)="",$H85,INDEX($H85:$O85,1,Scenario_Selected)) -> 1 | H85: 1 | J85: 2
B86: Energy lost on overbuilt MW | C86: % | D86: Bora!N18 | F86: =IF(INDEX($H86:$O86,1,Scenario_Selected)="",$H86,INDEX($H86:$O86,1,Scenario_Selected)) -> 0.05 | H86: 0.05
A88: x | C88: Capex
B89: Chinese turbines (0 EU, 1 CN) | C89: flag | D89: User 12-Oct-26 (SPEC v2.1) | F89: =IF(INDEX($H89:$O89,1,Scenario_Selected)="",$H89,INDEX($H89:$O89,1,Scenario_Selected)) -> 0 | H89: 0
B90: Turbine supply, EU | C90: EUR k/MW | D90: User 12-Oct-26 (SPEC v2.1) | F90: =IF(INDEX($H90:$O90,1,Scenario_Selected)="",$H90,INDEX($H90:$O90,1,Scenario_Selected)) -> 600 | H90: 600
B91: Turbine supply, CN | C91: EUR k/MW | D91: Old engine Calc G101 | F91: =IF(INDEX($H91:$O91,1,Scenario_Selected)="",$H91,INDEX($H91:$O91,1,Scenario_Selected)) -> 500 | H91: 500
B92: Other wind capex (install, foundations, BoP, owner, land) | C92: EUR k/MW | D92: Old engine Inputs E163:E166, E169:E170 | F92: =IF(INDEX($H92:$O92,1,Scenario_Selected)="",$H92,INDEX($H92:$O92,1,Scenario_Selected)) -> 355 | H92: 355
B93: Substation and 132 kV bay, EU | C93: EUR k | D93: Old engine Inputs E167 | F93: =IF(INDEX($H93:$O93,1,Scenario_Selected)="",$H93,INDEX($H93:$O93,1,Scenario_Selected)) -> 12000 | H93: 12000
B94: Substation and 132 kV bay, CN | C94: EUR k | D94: Old engine Tender E29 | F94: =IF(INDEX($H94:$O94,1,Scenario_Selected)="",$H94,INDEX($H94:$O94,1,Scenario_Selected)) -> 10800 | H94: 10800
B95: Contingency on wind and substation capex | C95: % | D95: Old engine Inputs E171 | F95: =IF(INDEX($H95:$O95,1,Scenario_Selected)="",$H95,INDEX($H95:$O95,1,Scenario_Selected)) -> 0.05 | H95: 0.05
B96: BESS capex | C96: EUR k/MW | D96: User 12-Oct-26 | F96: =IF(INDEX($H96:$O96,1,Scenario_Selected)="",$H96,INDEX($H96:$O96,1,Scenario_Selected)) -> 240 | H96: 240
A98: x | C98: Operations
B99: Net P50 hours | C99: h/yr | D99: Old engine Inputs E179 | F99: =IF(INDEX($H99:$O99,1,Scenario_Selected)="",$H99,INDEX($H99:$O99,1,Scenario_Selected)) -> 2460 | H99: 2460
B100: Curtailment | C100: % | D100: Old engine Inputs E181 | F100: =IF(INDEX($H100:$O100,1,Scenario_Selected)="",$H100,INDEX($H100:$O100,1,Scenario_Selected)) -> 0.02 | H100: 0.02
B101: Degradation per year | C101: % | D101: Old engine Inputs E182 | F101: =IF(INDEX($H101:$O101,1,Scenario_Selected)="",$H101,INDEX($H101:$O101,1,Scenario_Selected)) -> 0.003 | H101: 0.003
B102: PPA price at COD (whole life) | C102: EUR/MWh | D102: User 12-Oct-26 (SPEC v2.1) | F102: =IF(INDEX($H102:$O102,1,Scenario_Selected)="",$H102,INDEX($H102:$O102,1,Scenario_Selected)) -> 90 | H102: 90
B103: PPA escalation | C103: % | D103: Old engine Inputs E192 | F103: =IF(INDEX($H103:$O103,1,Scenario_Selected)="",$H103,INDEX($H103:$O103,1,Scenario_Selected)) -> 0.01 | H103: 0.01
B104: Variable opex (balancing 4, grid 1) | C104: EUR/MWh | D104: Old engine Inputs E194:E195 | F104: =IF(INDEX($H104:$O104,1,Scenario_Selected)="",$H104,INDEX($H104:$O104,1,Scenario_Selected)) -> 5 | H104: 5
B105: Fixed opex (O&M, BoP, insurance, AM, property tax) | C105: EUR k/MW | D105: Old engine Inputs E201:E202, E204:E206 | F105: =IF(INDEX($H105:$O105,1,Scenario_Selected)="",$H105,INDEX($H105:$O105,1,Scenario_Selected)) -> 22 | H105: 22
B106: Land lease from NTP | C106: EUR k/MW | D106: Old engine Inputs E203 | F106: =IF(INDEX($H106:$O106,1,Scenario_Selected)="",$H106,INDEX($H106:$O106,1,Scenario_Selected)) -> 3 | H106: 3
B107: Administration | C107: EUR k | D107: Old engine Inputs E207 | F107: =IF(INDEX($H107:$O107,1,Scenario_Selected)="",$H107,INDEX($H107:$O107,1,Scenario_Selected)) -> 150 | H107: 150
B108: Opex contingency | C108: % | D108: Old engine Inputs E208 | F108: =IF(INDEX($H108:$O108,1,Scenario_Selected)="",$H108,INDEX($H108:$O108,1,Scenario_Selected)) -> 0.05 | H108: 0.05
B109: Opex escalation from the COD year | C109: % | D109: Old engine Inputs E209 | F109: =IF(INDEX($H109:$O109,1,Scenario_Selected)="",$H109,INDEX($H109:$O109,1,Scenario_Selected)) -> 0.025 | H109: 0.025
B110: MEKH fee | C110: % | D110: Old engine Inputs E196 | F110: =IF(INDEX($H110:$O110,1,Scenario_Selected)="",$H110,INDEX($H110:$O110,1,Scenario_Selected)) -> 0.001 | H110: 0.001
B111: Local business tax (HIPA) | C111: % | D111: Old engine Inputs E210 | F111: =IF(INDEX($H111:$O111,1,Scenario_Selected)="",$H111,INDEX($H111:$O111,1,Scenario_Selected)) -> 0.02 | H111: 0.02
A113: x | C113: Debt and tax
B114: Gearing on capex, connection, municipal, EU | C114: % | D114: Old engine Inputs E217 | F114: =IF(INDEX($H114:$O114,1,Scenario_Selected)="",$H114,INDEX($H114:$O114,1,Scenario_Selected)) -> 0.6 | H114: 0.6
B115: Gearing on capex, connection, municipal, CN | C115: % | D115: Old engine case 3 | F115: =IF(INDEX($H115:$O115,1,Scenario_Selected)="",$H115,INDEX($H115:$O115,1,Scenario_Selected)) -> 0.5 | H115: 0.5
B116: Debt interest rate | C116: % | D116: Old engine Inputs E218 | F116: =IF(INDEX($H116:$O116,1,Scenario_Selected)="",$H116,INDEX($H116:$O116,1,Scenario_Selected)) -> 0.05 | H116: 0.05
B117: Upfront fee | C117: % | D117: Old engine Inputs E219 | F117: =IF(INDEX($H117:$O117,1,Scenario_Selected)="",$H117,INDEX($H117:$O117,1,Scenario_Selected)) -> 0.0175 | H117: 0.0175
...

Sheet Curves
B2: =Dashboard!$C$3&" – Time-series inputs" -> Project Bora – Time-series inputs
A5: x | C5: Tender scoring bands | E5: Kiírás Annex 3-4; old engine Tender D93:F161
E6: Weight / min | F6: Max | J6: Bands →
C7: ÖSZ-1 municipal one-off – lower bound | D7: EUR k/MW | E7: 10 | F7: 50 | J7: 10 | K7: 15 | L7: 20 | M7: 25 | N7: 30 | O7: 35 | P7: 40 | Q7: 45 | R7: 50
C8: ÖSZ-1 municipal one-off – lower bound included | D8: flag | J8: 0 | K8: 0 | L8: 0 | M8: 0 | N8: 0 | O8: 0 | P8: 0 | Q8: 0 | R8: 1
C9: ÖSZ-1 municipal one-off – inner points (below, bands) | D9: points | E9: 0.2 | J9: 0 | K9: 10 | L9: 20 | M9: 30 | N9: 40 | O9: 55 | P9: 70 | Q9: 80 | R9: 90 | S9: 100
C10: ÖSZ-2 community contribution – lower bound | D10: EUR/MWh | E10: 2 | F10: 3 | J10: 2 | K10: 2.1 | L10: 2.2 | M10: 2.3 | N10: 2.4 | O10: 2.5 | P10: 2.6 | Q10: 2.7 | R10: 2.8 | S10: 2.9 | T10: 3
C11: ÖSZ-2 community contribution – lower bound included | D11: flag | J11: 0 | K11: 0 | L11: 0 | M11: 0 | N11: 0 | O11: 0 | P11: 0 | Q11: 0 | R11: 0 | S11: 0 | T11: 1
C12: ÖSZ-2 community contribution – inner points (below, bands) | D12: points | E12: 0.15 | J12: 0 | K12: 5 | L12: 10 | M12: 20 | N12: 30 | O12: 40 | P12: 50 | Q12: 60 | R12: 70 | S12: 80 | T12: 90 | U12: 100
C13: ÖSZ-3 overbuild – lower bound | D13: % | J13: 0.02 | K13: 0.05 | L13: 0.1 | M13: 0.15 | N13: 0.2 | O13: 0.25 | P13: 0.3 | Q13: 0.35 | R13: 0.4 | S13: 0.5
C14: ÖSZ-3 overbuild – lower bound included | D14: flag | J14: 0 | K14: 1 | L14: 1 | M14: 1 | N14: 1 | O14: 1 | P14: 1 | Q14: 1 | R14: 1 | S14: 0
C15: ÖSZ-3 overbuild – inner points (below, bands) | D15: points | E15: 0.1 | J15: 0 | K15: 10 | L15: 20 | M15: 30 | N15: 40 | O15: 50 | P15: 60 | Q15: 70 | R15: 80 | S15: 90 | T15: 100
C16: ÖSZ-4 BESS ratio – lower bound | D16: % | E16: 0.05 | J16: 0.02 | K16: 0.05 | L16: 0.1 | M16: 0.15 | N16: 0.2 | O16: 0.25 | P16: 0.3 | Q16: 0.35 | R16: 0.4 | S16: 0.5
C17: ÖSZ-4 BESS ratio – lower bound included | D17: flag | J17: 0 | K17: 1 | L17: 1 | M17: 1 | N17: 1 | O17: 1 | P17: 1 | Q17: 1 | R17: 1 | S17: 0
C18: ÖSZ-4 BESS ratio – inner points (below, bands) | D18: points | E18: 0.15 | J18: 0 | K18: 10 | L18: 20 | M18: 30 | N18: 40 | O18: 50 | P18: 60 | Q18: 70 | R18: 80 | S18: 90 | T18: 100
C19: ÖSZ-6 performance security multiple – lower bound | D19: x | J19: 1 | K19: 1.2 | L19: 1.3 | M19: 1.4 | N19: 1.5 | O19: 1.6 | P19: 1.7 | Q19: 1.8 | R19: 1.9 | S19: 2
C20: ÖSZ-6 performance security multiple – lower bound included | D20: flag | J20: 0 | K20: 1 | L20: 1 | M20: 1 | N20: 1 | O20: 1 | P20: 1 | Q20: 1 | R20: 1 | S20: 1
C21: ÖSZ-6 performance security multiple – inner points (below, bands) | D21: points | E21: 0.05 | J21: 0 | K21: 10 | L21: 20 | M21: 30 | N21: 40 | O21: 50 | P21: 60 | Q21: 70 | R21: 80 | S21: 90 | T21: 100
C22: ÖSZ-5 partial award – inner points | D22: points | E22: 0.05 | J22: 100
C23: ÖSZ-7 brownfield – inner points | D23: points | E23: 0.1 | J23: 100
C24: ÖSZ-8 shared connection – inner points | D24: points | E24: 0.05 | J24: 100
C25: ÖSZ-9 EU turbines – inner points | D25: points | E25: 0.15 | J25: 80
C26: ÖSZ-9 EU transformers – inner points | D26: points | J26: 20
A28: x | C28: Devex schedule | E28: BORA_Devex 25-Sep (meeting file Devex_FEP); excl. Other costs
C29: Line (BORA_Devex row) | E29: HUF m | F29: EUR k | I29: EUR k at FX | J29: Pay date | K29: Land
C30: r14 Capacity allocation process - Awarding – Land reservation fee | E30: 0 | F30: 55.65 | I30: =E30*Thousand/In_FX+F30 -> 55.65 | J30: 46431 | K30: 1
C31: r15 Land purchase price | E31: 45.6 | F31: 0 | I31: =E31*Thousand/In_FX+F31 -> 124.93151 | J31: 46431 | K31: 1
C32: r16 Grid connection plan – Design fee | E32: 59.142857 | F32: 0 | I32: =E32*Thousand/In_FX+F32 -> 162.03523 | J32: 46976 | K32: 0
C33: r17 Administrative fee | E33: 0.750544 | F33: 0 | I33: =E33*Thousand/In_FX+F33 -> 2.0562849 | J33: 46976 | K33: 0
C34: r20 Land contracting (additional land) – Legal fee, agent fee | E34: 34.5 | F34: 84 | I34: =E34*Thousand/In_FX+F34 -> 178.52055 | J34: 46296 | K34: 0
C35: r21 Wind measurement – Met Masts | E35: 0 | F35: 398 | I35: =E35*Thousand/In_FX+F35 -> 398 | J35: 46447 | K35: 0
C36: r22 Design fee | E36: 3.6 | F36: 0 | I36: =E36*Thousand/In_FX+F36 -> 9.8630137 | J36: 46388 | K36: 0
C37: r23 EYA | E37: 0 | F37: 4.5 | I37: =E37*Thousand/In_FX+F37 -> 4.5 | J37: 46932 | K37: 0
C38: r24 Land reclassification – Administrative fee | E38: 0.96 | F38: 0 | I38: =E38*Thousand/In_FX+F38 -> 2.630137 | J38: 46746 | K38: 0
C39: r25 Report fee | E39: 8 | F39: 0 | I39: =E39*Thousand/In_FX+F39 -> 21.917808 | J39: 46596 | K39: 0
C40: r26 Zoning plan modification – Design fee | E40: 50 | F40: 0 | I40: =E40*Thousand/In_FX+F40 -> 136.9863 | J40: 46806 | K40: 0
C41: r27 Municipality donation – Donation | E41: 35 | F41: 0 | I41: =E41*Thousand/In_FX+F41 -> 95.890411 | J41: 46806 | K41: 0
... C61: r48 RtB – Land purchase price | E61: 91.2 | F61: 0 | I61: =E61*Thousand/In_FX+F61 -> 249.86301 | J61: 47201 | K61: 1
I62: =E62*Thousand/In_FX+F62 -> 0
I63: =E63*Thousand/In_FX+F63 -> 0
C65: ***END***

Sheet Calc_1
A1: 1 | C1: Bid number
B2: =Dashboard!$C$3&" – Calculations – "&INDEX(Bid_Labels,1,$A$1) -> Project Bora – Calculations – BORA 1
C3: Period start | D3: date | J3: =I$4+1 -> 46204 | K3: =J$4+1 -> 46296 | L3: =K$4+1 -> 46388 | M3: =L$4+1 -> 46478 | N3: =M$4+1 -> 46569 | O3: =N$4+1 -> 46661 | P3: =O$4+1 -> 46753 | Q3: =P$4+1 -> 46844 | ... ET3: =ES$4+1 -> 58988
C4: Period end | D4: date | I4: =In_Model_Start-1 -> 46203 | J4: =EOMONTH(J$3,Months_Per_Period-1) -> 46295 | K4: =EOMONTH(K$3,Months_Per_Period-1) -> 46387 | L4: =EOMONTH(L$3,Months_Per_Period-1) -> 46477 | M4: =EOMONTH(M$3,Months_Per_Period-1) -> 46568 | N4: =EOMONTH(N$3,Months_Per_Period-1) -> 46660 | O4: =EOMONTH(O$3,Months_Per_Period-1) -> 46752 | P4: =EOMONTH(P$3,Months_Per_Period-1) -> 46843 | Q4: =EOMONTH(Q$3,Months_Per_Period-1) -> 46934 | ... ET4: =EOMONTH(ET$3,Months_Per_Period-1) -> 59079
C5: Days in period | D5: days | J5: =J$4-J$3+1 -> 92 | K5: =K$4-K$3+1 -> 92 | L5: =L$4-L$3+1 -> 90 | M5: =M$4-M$3+1 -> 91 | N5: =N$4-N$3+1 -> 92 | O5: =O$4-O$3+1 -> 92 | P5: =P$4-P$3+1 -> 91 | Q5: =Q$4-Q$3+1 -> 91 | ... ET5: =ET$4-ET$3+1 -> 92
C6: Year fraction | D6: factor | J6: =J$5/Days_In_Year -> 0.25205479 | K6: =K$5/Days_In_Year -> 0.25205479 | L6: =L$5/Days_In_Year -> 0.24657534 | M6: =M$5/Days_In_Year -> 0.24931507 | N6: =N$5/Days_In_Year -> 0.25205479 | O6: =O$5/Days_In_Year -> 0.25205479 | P6: =P$5/Days_In_Year -> 0.24931507 | Q6: =Q$5/Days_In_Year -> 0.24931507 | ... ET6: =ET$5/Days_In_Year -> 0.25205479
C7: Year | D7: year | J7: =YEAR(J$4) -> 2026 | K7: =YEAR(K$4) -> 2026 | L7: =YEAR(L$4) -> 2027 | M7: =YEAR(M$4) -> 2027 | N7: =YEAR(N$4) -> 2027 | O7: =YEAR(O$4) -> 2027 | P7: =YEAR(P$4) -> 2028 | Q7: =YEAR(Q$4) -> 2028 | ... ET7: =YEAR(ET$4) -> 2061
C8: Period counter | D8: # | J8: =I$8+1 -> 1 | K8: =J$8+1 -> 2 | L8: =K$8+1 -> 3 | M8: =L$8+1 -> 4 | N8: =M$8+1 -> 5 | O8: =N$8+1 -> 6 | P8: =O$8+1 -> 7 | Q8: =P$8+1 -> 8 | ... ET8: =ES$8+1 -> 141
A11: x | C11: Timing and flags
C12: RtB exit | D12: flag | E12: =INDEX(Dash_Exit_Date,1,$A$1) -> 47483 | I12: =SUM(J12:ET12) -> 1 | J12: =N(AND(J$3<=$E12,J$4>=$E12)) -> 0 | K12: =N(AND(K$3<=$E12,K$4>=$E12)) -> 0 | L12: =N(AND(L$3<=$E12,L$4>=$E12)) -> 0 | M12: =N(AND(M$3<=$E12,M$4>=$E12)) -> 0 | N12: =N(AND(N$3<=$E12,N$4>=$E12)) -> 0 | O12: =N(AND(O$3<=$E12,O$4>=$E12)) -> 0 | P12: =N(AND(P$3<=$E12,P$4>=$E12)) -> 0 | Q12: =N(AND(Q$3<=$E12,Q$4>=$E12)) -> 0 | ... ET12: =N(AND(ET$3<=$E12,ET$4>=$E12)) -> 0
C13: Construction share (NTP → COD) | D13: factor | E13: =In_NTP+1 -> 47392 | F13: =In_COD -> 48121 | I13: =SUM(J13:ET13) -> 1 | J13: =MAX(0,MIN($F13,J$4)-MAX($E13,J$3)+1)/($F13-$E13+1) -> 0 | K13: =MAX(0,MIN($F13,K$4)-MAX($E13,K$3)+1)/($F13-$E13+1) -> 0 | L13: =MAX(0,MIN($F13,L$4)-MAX($E13,L$3)+1)/($F13-$E13+1) -> 0 | M13: =MAX(0,MIN($F13,M$4)-MAX($E13,M$3)+1)/($F13-$E13+1) -> 0 | N13: =MAX(0,MIN($F13,N$4)-MAX($E13,N$3)+1)/($F13-$E13+1) -> 0 | O13: =MAX(0,MIN($F13,O$4)-MAX($E13,O$3)+1)/($F13-$E13+1) -> 0 | P13: =MAX(0,MIN($F13,P$4)-MAX($E13,P$3)+1)/($F13-$E13+1) -> 0 | Q13: =MAX(0,MIN($F13,Q$4)-MAX($E13,Q$3)+1)/($F13-$E13+1) -> 0 | ... ET13: =MAX(0,MIN($F13,ET$4)-MAX($E13,ET$3)+1)/($F13-$E13+1) -> 0
C14: COD | D14: flag | E14: =In_COD -> 48121 | I14: =SUM(J14:ET14) -> 1 | J14: =N(AND(J$3<=$E14,J$4>=$E14)) -> 0 | K14: =N(AND(K$3<=$E14,K$4>=$E14)) -> 0 | L14: =N(AND(L$3<=$E14,L$4>=$E14)) -> 0 | M14: =N(AND(M$3<=$E14,M$4>=$E14)) -> 0 | N14: =N(AND(N$3<=$E14,N$4>=$E14)) -> 0 | O14: =N(AND(O$3<=$E14,O$4>=$E14)) -> 0 | P14: =N(AND(P$3<=$E14,P$4>=$E14)) -> 0 | Q14: =N(AND(Q$3<=$E14,Q$4>=$E14)) -> 0 | ... ET14: =N(AND(ET$3<=$E14,ET$4>=$E14)) -> 0
C15: Operations | D15: flag | E15: =In_COD+1 -> 48122 | F15: =EDATE(In_COD,In_Life*Months_In_Year) -> 59079 | J15: =MAX(0,(MIN($F15,J$4)-MAX($E15,J$3)+1)/J$5) -> 0 | K15: =MAX(0,(MIN($F15,K$4)-MAX($E15,K$3)+1)/K$5) -> 0 | L15: =MAX(0,(MIN($F15,L$4)-MAX($E15,L$3)+1)/L$5) -> 0 | M15: =MAX(0,(MIN($F15,M$4)-MAX($E15,M$3)+1)/M$5) -> 0 | N15: =MAX(0,(MIN($F15,N$4)-MAX($E15,N$3)+1)/N$5) -> 0 | O15: =MAX(0,(MIN($F15,O$4)-MAX($E15,O$3)+1)/O$5) -> 0 | P15: =MAX(0,(MIN($F15,P$4)-MAX($E15,P$3)+1)/P$5) -> 0 | Q15: =MAX(0,(MIN($F15,Q$4)-MAX($E15,Q$3)+1)/Q$5) -> 0 | ... ET15: =MAX(0,(MIN($F15,ET$4)-MAX($E15,ET$3)+1)/ET$5) -> 1
C16: Land lease period (NTP → end of life) | D16: flag | E16: =In_NTP+1 -> 47392 | F16: =EDATE(In_COD,In_Life*Months_In_Year) -> 59079 | J16: =MAX(0,(MIN($F16,J$4)-MAX($E16,J$3)+1)/J$5) -> 0 | K16: =MAX(0,(MIN($F16,K$4)-MAX($E16,K$3)+1)/K$5) -> 0 | L16: =MAX(0,(MIN($F16,L$4)-MAX($E16,L$3)+1)/L$5) -> 0 | M16: =MAX(0,(MIN($F16,M$4)-MAX($E16,M$3)+1)/M$5) -> 0 | N16: =MAX(0,(MIN($F16,N$4)-MAX($E16,N$3)+1)/N$5) -> 0 | O16: =MAX(0,(MIN($F16,O$4)-MAX($E16,O$3)+1)/O$5) -> 0 | P16: =MAX(0,(MIN($F16,P$4)-MAX($E16,P$3)+1)/P$5) -> 0 | Q16: =MAX(0,(MIN($F16,Q$4)-MAX($E16,Q$3)+1)/Q$5) -> 0 | ... ET16: =MAX(0,(MIN($F16,ET$4)-MAX($E16,ET$3)+1)/ET$5) -> 1
C17: Debt repayment period | D17: flag | E17: =In_COD+1 -> 48122 | F17: =EDATE(In_COD,In_Debt_Tenor*Months_In_Year) -> 51774 | J17: =MAX(0,(MIN($F17,J$4)-MAX($E17,J$3)+1)/J$5) -> 0 | K17: =MAX(0,(MIN($F17,K$4)-MAX($E17,K$3)+1)/K$5) -> 0 | L17: =MAX(0,(MIN($F17,L$4)-MAX($E17,L$3)+1)/L$5) -> 0 | M17: =MAX(0,(MIN($F17,M$4)-MAX($E17,M$3)+1)/M$5) -> 0 | N17: =MAX(0,(MIN($F17,N$4)-MAX($E17,N$3)+1)/N$5) -> 0 | O17: =MAX(0,(MIN($F17,O$4)-MAX($E17,O$3)+1)/O$5) -> 0 | P17: =MAX(0,(MIN($F17,P$4)-MAX($E17,P$3)+1)/P$5) -> 0 | Q17: =MAX(0,(MIN($F17,Q$4)-MAX($E17,Q$3)+1)/Q$5) -> 0 | ... ET17: =MAX(0,(MIN($F17,ET$4)-MAX($E17,ET$3)+1)/ET$5) -> 0
C18: Tax depreciation share | D18: factor | E18: =In_COD+1 -> 48122 | F18: =EDATE(In_COD,In_Dep_Years*Months_In_Year) -> 55426 | I18: =SUM(J18:ET18) -> 1 | J18: =MAX(0,MIN($F18,J$4)-MAX($E18,J$3)+1)/($F18-$E18+1) -> 0 | K18: =MAX(0,MIN($F18,K$4)-MAX($E18,K$3)+1)/($F18-$E18+1) -> 0 | L18: =MAX(0,MIN($F18,L$4)-MAX($E18,L$3)+1)/($F18-$E18+1) -> 0 | M18: =MAX(0,MIN($F18,M$4)-MAX($E18,M$3)+1)/($F18-$E18+1) -> 0 | N18: =MAX(0,MIN($F18,N$4)-MAX($E18,N$3)+1)/($F18-$E18+1) -> 0 | O18: =MAX(0,MIN($F18,O$4)-MAX($E18,O$3)+1)/($F18-$E18+1) -> 0 | P18: =MAX(0,MIN($F18,P$4)-MAX($E18,P$3)+1)/($F18-$E18+1) -> 0 | Q18: =MAX(0,MIN($F18,Q$4)-MAX($E18,Q$3)+1)/($F18-$E18+1) -> 0 | ... ET18: =MAX(0,MIN($F18,ET$4)-MAX($E18,ET$3)+1)/($F18-$E18+1) -> 0
C19: Interest freeze (no accrual) | D19: flag | E19: =In_Freeze_Start+1 -> 47300 | F19: =In_Freeze_Start+In_Freeze_On*(In_Freeze_End-In_Freeze_Start)-1 -> 47483 | J19: =MAX(0,(MIN($F19,J$4)-MAX($E19,J$3)+1)/J$5) -> 0 | K19: =MAX(0,(MIN($F19,K$4)-MAX($E19,K$3)+1)/K$5) -> 0 | L19: =MAX(0,(MIN($F19,L$4)-MAX($E19,L$3)+1)/L$5) -> 0 | M19: =MAX(0,(MIN($F19,M$4)-MAX($E19,M$3)+1)/M$5) -> 0 | N19: =MAX(0,(MIN($F19,N$4)-MAX($E19,N$3)+1)/N$5) -> 0 | O19: =MAX(0,(MIN($F19,O$4)-MAX($E19,O$3)+1)/O$5) -> 0 | P19: =MAX(0,(MIN($F19,P$4)-MAX($E19,P$3)+1)/P$5) -> 0 | Q19: =MAX(0,(MIN($F19,Q$4)-MAX($E19,Q$3)+1)/Q$5) -> 0 | ... ET19: =MAX(0,(MIN($F19,ET$4)-MAX($E19,ET$3)+1)/ET$5) -> 0
C20: 31-Dec capitalisation | D20: flag | J20: =N(MONTH(J$4)=Months_In_Year) -> 0 | K20: =N(MONTH(K$4)=Months_In_Year) -> 1 | L20: =N(MONTH(L$4)=Months_In_Year) -> 0 | M20: =N(MONTH(M$4)=Months_In_Year) -> 0 | N20: =N(MONTH(N$4)=Months_In_Year) -> 0 | O20: =N(MONTH(O$4)=Months_In_Year) -> 1 | P20: =N(MONTH(P$4)=Months_In_Year) -> 0 | Q20: =N(MONTH(Q$4)=Months_In_Year) -> 0 | ... ET20: =N(MONTH(ET$4)=Months_In_Year) -> 0
C21: Buyer discount factor to COD | D21: factor | J21: =1/(1+In_Buyer_Rate)^(MAX(0,J$4-In_COD)/Days_In_Year) -> 1 | K21: =1/(1+In_Buyer_Rate)^(MAX(0,K$4-In_COD)/Days_In_Year) -> 1 | L21: =1/(1+In_Buyer_Rate)^(MAX(0,L$4-In_COD)/Days_In_Year) -> 1 | M21: =1/(1+In_Buyer_Rate)^(MAX(0,M$4-In_COD)/Days_In_Year) -> 1 | N21: =1/(1+In_Buyer_Rate)^(MAX(0,N$4-In_COD)/Days_In_Year) -> 1 | O21: =1/(1+In_Buyer_Rate)^(MAX(0,O$4-In_COD)/Days_In_Year) -> 1 | P21: =1/(1+In_Buyer_Rate)^(MAX(0,P$4-In_COD)/Days_In_Year) -> 1 | Q21: =1/(1+In_Buyer_Rate)^(MAX(0,Q$4-In_COD)/Days_In_Year) -> 1 | ... ET21: =1/(1+In_Buyer_Rate)^(MAX(0,ET$4-In_COD)/Days_In_Year) -> 0.099209842
A23: x | C23: Capacity (E: committed, F: built)
C24: Wind | D24: MW | E24: =In_MVA*(1+INDEX(Dash_Overbuild,1,$A$1)) -> 151 | F24: =In_MVA+($E24-In_MVA)*In_Overbuild_Built -> 100
C25: BESS power | D25: MW | E25: =INDEX(Dash_BESS,1,$A$1)*In_MVA -> 51 | F25: =$E25*In_BESS_Built -> 51
C26: BESS energy | D26: MWh | E26: =$E25*INDEX(Dash_BESS_Hours,1,$A$1) -> 204
C27: Grid-bottleneck loss on built wind | D27: % | E27: =($F24-In_MVA)/$F24*In_Bottleneck_Loss -> 0
A29: x | C29: Tender points (E: commitment, F: weighted points)
C30: ÖSZ-1 municipal one-off | D30: EUR k/MW | E30: =INDEX(Dash_Municipal,1,$A$1) -> 50 | F30: =INDEX(Osz1_Pts,1+SUMPRODUCT((Osz1_LB<$E30)+(Osz1_LB=$E30)*Osz1_Incl))*Osz1_W -> 20
C31: ÖSZ-2 community contribution | D31: EUR/MWh | E31: =INDEX(Dash_Community,1,$A$1) -> 3 | F31: =INDEX(Osz2_Pts,1+SUMPRODUCT((Osz2_LB<$E31)+(Osz2_LB=$E31)*Osz2_Incl))*Osz2_W -> 15
C32: ÖSZ-3 overbuild | D32: % | E32: =INDEX(Dash_Overbuild,1,$A$1) -> 0.51 | F32: =INDEX(Osz3_Pts,1+SUMPRODUCT((Osz3_LB<$E32)+(Osz3_LB=$E32)*Osz3_Incl))*Osz3_W -> 10
C33: ÖSZ-4 BESS ratio | D33: % | E33: =INDEX(Dash_BESS,1,$A$1)/IF(In_OSZ4_Basis=1,$E24/In_MVA,1) -> 0.51 | F33: =INDEX(Osz4_Pts,1+SUMPRODUCT((Osz4_LB<$E33)+(Osz4_LB=$E33)*Osz4_Incl))*Osz4_W*($E33>=Osz4_Min) -> 15
C34: ÖSZ-5 partial award | D34: flag | E34: =INDEX(Dash_Partial,1,$A$1) -> 1 | F34: =$E34*Osz5_Pts*Osz5_W -> 5
C35: ÖSZ-6 performance security multiple | D35: x | E35: =INDEX(Dash_PB_Mult,1,$A$1) -> 1 | F35: =INDEX(Osz6_Pts,1+SUMPRODUCT((Osz6_LB<$E35)+(Osz6_LB=$E35)*Osz6_Incl))*Osz6_W -> 0
C36: ÖSZ-7 brownfield | D36: flag | E36: =INDEX(Dash_Brownfield,1,$A$1) -> 0 | F36: =$E36*Osz7_Pts*Osz7_W -> 0
C37: ÖSZ-8 shared connection | D37: flag | E37: =INDEX(Dash_Shared,1,$A$1) -> 1 | F37: =$E37*Osz8_Pts*Osz8_W -> 5
C38: ÖSZ-9 EU turbines | D38: flag | E38: =INDEX(Dash_EU_Turbine,1,$A$1) -> 1 | F38: =$E38*Osz9a_Pts*Osz9_W -> 12
C39: ÖSZ-9 EU transformers | D39: flag | E39: =INDEX(Dash_EU_Transformer,1,$A$1) -> 1 | F39: =$E39*Osz9b_Pts*Osz9_W -> 3
C40: Points total (E: EU route, F: CN route) | D40: points | E40: =ROUND(SUM($F30:$F39),Points_Decimals) -> 85 | F40: =ROUND(SUM($F30:$F37),Points_Decimals) -> 70
C41: Points, live turbine route | D41: points | E41: =IF(In_CN_Turbine=1,$F40,$E40) -> 85
C42: Failed tests (E: capacity, F: offerable range) | D42: # | E42: =N(In_MVA>In_Group_Cap)+N($E24<In_MVA)+N($E25>$E24)+N($E26<$E25*In_Min_Hours) -> 0 | F42: =($E30<>0)*($E30<Osz1_Min)+($E30>Osz1_Max)+($E31<>0)*($E31<Osz2_Min)+($E31>Osz2_Max) -> 0
A44: x | C44: Securities, fees and development costs (E: amount, F: date)
C45: Security base | D45: mHUF | E45: =$E24*In_Bench_Wind+$E26*In_Bench_BESS -> 102106
C46: Signing fee and DD | D46: EUR k | E46: =In_Signing_Fee+In_DD -> 400 | F46: =In_Invest_Date -> 46234 | I46: =SUM(J46:ET46) -> -400 | J46: =-$E46*N(AND(J$3<=$F46,J$4>=$F46)) -> -400 | K46: =-$E46*N(AND(K$3<=$F46,K$4>=$F46)) -> 0 | L46: =-$E46*N(AND(L$3<=$F46,L$4>=$F46)) -> 0 | M46: =-$E46*N(AND(M$3<=$F46,M$4>=$F46)) -> 0 | N46: =-$E46*N(AND(N$3<=$F46,N$4>=$F46)) -> 0 | O46: =-$E46*N(AND(O$3<=$F46,O$4>=$F46)) -> 0 | P46: =-$E46*N(AND(P$3<=$F46,P$4>=$F46)) -> 0 | Q46: =-$E46*N(AND(Q$3<=$F46,Q$4>=$F46)) -> 0 | ... ET46: =-$E46*N(AND(ET$3<=$F46,ET$4>=$F46)) -> 0
C47: Participation fee (cash) | D47: EUR k | E47: =In_Part_Fee*Thousand/In_FX -> 8.2191781 | F47: =In_Bid_Date -> 46325 | I47: =SUM(J47:ET47) -> -8.2191781 | J47: =-$E47*N(AND(J$3<=$F47,J$4>=$F47)) -> 0 | K47: =-$E47*N(AND(K$3<=$F47,K$4>=$F47)) -> -8.2191781 | L47: =-$E47*N(AND(L$3<=$F47,L$4>=$F47)) -> 0 | M47: =-$E47*N(AND(M$3<=$F47,M$4>=$F47)) -> 0 | N47: =-$E47*N(AND(N$3<=$F47,N$4>=$F47)) -> 0 | O47: =-$E47*N(AND(O$3<=$F47,O$4>=$F47)) -> 0 | P47: =-$E47*N(AND(P$3<=$F47,P$4>=$F47)) -> 0 | Q47: =-$E47*N(AND(Q$3<=$F47,Q$4>=$F47)) -> 0 | ... ET47: =-$E47*N(AND(ET$3<=$F47,ET$4>=$F47)) -> 0
C48: Bid security outstanding (guarantee) | D48: EUR k | E48: =In_Bid_Rate*$E45*Thousand/In_FX -> 1398.7123 | F48: =In_Bid_Date -> 46325 | J48: =$E48*MAX(0,(MIN(In_Award_Date+In_PB_Days-1,J$4)-MAX($F48,J$3)+1)/J$5) -> 0 | K48: =$E48*MAX(0,(MIN(In_Award_Date+In_PB_Days-1,K$4)-MAX($F48,K$3)+1)/K$5) -> 897.0003 | L48: =$E48*MAX(0,(MIN(In_Award_Date+In_PB_Days-1,L$4)-MAX($F48,L$3)+1)/L$5) -> 0 | M48: =$E48*MAX(0,(MIN(In_Award_Date+In_PB_Days-1,M$4)-MAX($F48,M$3)+1)/M$5) -> 0 | N48: =$E48*MAX(0,(MIN(In_Award_Date+In_PB_Days-1,N$4)-MAX($F48,N$3)+1)/N$5) -> 0 | O48: =$E48*MAX(0,(MIN(In_Award_Date+In_PB_Days-1,O$4)-MAX($F48,O$3)+1)/O$5) -> 0 | P48: =$E48*MAX(0,(MIN(In_Award_Date+In_PB_Days-1,P$4)-MAX($F48,P$3)+1)/P$5) -> 0 | Q48: =$E48*MAX(0,(MIN(In_Award_Date+In_PB_Days-1,Q$4)-MAX($F48,Q$3)+1)/Q$5) -> 0 | ... ET48: =$E48*MAX(0,(MIN(In_Award_Date+In_PB_Days-1,ET$4)-MAX($F48,ET$3)+1)/ET$5) -> 0
C49: Performance security outstanding (guarantee) | D49: EUR k | E49: =In_PB_Rate*$E35*$E45*Thousand/In_FX -> 6993.5616 | F49: =In_Award_Date+In_PB_Days -> 46384 | J49: =$E49*MAX(0,(MIN(In_PB_Release,J$4)-MAX($F49,J$3)+1)/J$5) -> 0 | K49: =$E49*MAX(0,(MIN(In_PB_Release,K$4)-MAX($F49,K$3)+1)/K$5) -> 304.0679 | L49: =$E49*MAX(0,(MIN(In_PB_Release,L$4)-MAX($F49,L$3)+1)/L$5) -> 6993.5616 | M49: =$E49*MAX(0,(MIN(In_PB_Release,M$4)-MAX($F49,M$3)+1)/M$5) -> 6993.5616 | N49: =$E49*MAX(0,(MIN(In_PB_Release,N$4)-MAX($F49,N$3)+1)/N$5) -> 6993.5616 | O49: =$E49*MAX(0,(MIN(In_PB_Release,O$4)-MAX($F49,O$3)+1)/O$5) -> 6993.5616 | P49: =$E49*MAX(0,(MIN(In_PB_Release,P$4)-MAX($F49,P$3)+1)/P$5) -> 6993.5616 | Q49: =$E49*MAX(0,(MIN(In_PB_Release,Q$4)-MAX($F49,Q$3)+1)/Q$5) -> 6993.5616 | ... ET49: =$E49*MAX(0,(MIN(In_PB_Release,ET$4)-MAX($F49,ET$3)+1)/ET$5) -> 0
C50: TSO connection-request security (cash) | D50: EUR k | E50: =In_TSO_Security*In_MVA*Thousand/In_FX -> 1232.8767 | F50: =In_TSO_Date -> 46386 | I50: =SUM(J50:ET50) -> -1232.8767 | J50: =-$E50*N(AND(J$3<=$F50,J$4>=$F50)) -> 0 | K50: =-$E50*N(AND(K$3<=$F50,K$4>=$F50)) -> -1232.8767 | L50: =-$E50*N(AND(L$3<=$F50,L$4>=$F50)) -> 0 | M50: =-$E50*N(AND(M$3<=$F50,M$4>=$F50)) -> 0 | N50: =-$E50*N(AND(N$3<=$F50,N$4>=$F50)) -> 0 | O50: =-$E50*N(AND(O$3<=$F50,O$4>=$F50)) -> 0 | P50: =-$E50*N(AND(P$3<=$F50,P$4>=$F50)) -> 0 | Q50: =-$E50*N(AND(Q$3<=$F50,Q$4>=$F50)) -> 0 | ... ET50: =-$E50*N(AND(ET$3<=$F50,ET$4>=$F50)) -> 0
C51: Direct connection fee (cash) | D51: EUR k | E51: =In_Direct_Fee*Thousand/In_FX -> 1392.7282 | F51: =In_HCSSZ_Date -> 47126 | I51: =SUM(J51:ET51) -> -1392.7282 | J51: =-$E51*N(AND(J$3<=$F51,J$4>=$F51)) -> 0 | K51: =-$E51*N(AND(K$3<=$F51,K$4>=$F51)) -> 0 | L51: =-$E51*N(AND(L$3<=$F51,L$4>=$F51)) -> 0 | M51: =-$E51*N(AND(M$3<=$F51,M$4>=$F51)) -> 0 | N51: =-$E51*N(AND(N$3<=$F51,N$4>=$F51)) -> 0 | O51: =-$E51*N(AND(O$3<=$F51,O$4>=$F51)) -> 0 | P51: =-$E51*N(AND(P$3<=$F51,P$4>=$F51)) -> 0 | Q51: =-$E51*N(AND(Q$3<=$F51,Q$4>=$F51)) -> 0 | ... ET51: =-$E51*N(AND(ET$3<=$F51,ET$4>=$F51)) -> 0
C52: Indirect connection fee, net of TSO security | D52: EUR k | E52: =(In_Indirect_Fee-In_TSO_Security)*In_MVA*Thousand/In_FX -> 18786.659 | F52: =In_HCSSZ_Date -> 47126 | I52: =SUM(J52:ET52) -> -18786.659 | J52: =-$E52*N(AND(J$3<=$F52,J$4>=$F52)) -> 0 | K52: =-$E52*N(AND(K$3<=$F52,K$4>=$F52)) -> 0 | L52: =-$E52*N(AND(L$3<=$F52,L$4>=$F52)) -> 0 | M52: =-$E52*N(AND(M$3<=$F52,M$4>=$F52)) -> 0 | N52: =-$E52*N(AND(N$3<=$F52,N$4>=$F52)) -> 0 | O52: =-$E52*N(AND(O$3<=$F52,O$4>=$F52)) -> 0 | P52: =-$E52*N(AND(P$3<=$F52,P$4>=$F52)) -> 0 | Q52: =-$E52*N(AND(Q$3<=$F52,Q$4>=$F52)) -> 0 | ... ET52: =-$E52*N(AND(ET$3<=$F52,ET$4>=$F52)) -> 0
C53: Connection fees | D53: EUR k | I53: =SUM(J53:ET53) -> -20179.387 | J53: =J51+J52 -> 0 | K53: =K51+K52 -> 0 | L53: =L51+L52 -> 0 | M53: =M51+M52 -> 0 | N53: =N51+N52 -> 0 | O53: =O51+O52 -> 0 | P53: =P51+P52 -> 0 | Q53: =Q51+Q52 -> 0 | ... ET53: =ET51+ET52 -> 0
C54: Devex (FEP-borne) | D54: EUR k | I54: =SUM(J54:ET54) -> -2404.8306 | J54: =-SUMIFS(Devex_Keur,Devex_Date,">="&J$3,Devex_Date,"<="&J$4,Devex_Land,0) -> 0 | K54: =-SUMIFS(Devex_Keur,Devex_Date,">="&K$3,Devex_Date,"<="&K$4,Devex_Land,0) -> -178.52055 | L54: =-SUMIFS(Devex_Keur,Devex_Date,">="&L$3,Devex_Date,"<="&L$4,Devex_Land,0) -> -407.86301 | M54: =-SUMIFS(Devex_Keur,Devex_Date,">="&M$3,Devex_Date,"<="&M$4,Devex_Land,0) -> -43.835616 | N54: =-SUMIFS(Devex_Keur,Devex_Date,">="&N$3,Devex_Date,"<="&N$4,Devex_Land,0) -> -43.835616 | O54: =-SUMIFS(Devex_Keur,Devex_Date,">="&O$3,Devex_Date,"<="&O$4,Devex_Land,0) -> -184.36164 | P54: =-SUMIFS(Devex_Keur,Devex_Date,">="&P$3,Devex_Date,"<="&P$4,Devex_Land,0) -> -1290.0418 | Q54: =-SUMIFS(Devex_Keur,Devex_Date,">="&Q$3,Devex_Date,"<="&Q$4,Devex_Land,0) -> -4.609589 | ... ET54: =-SUMIFS(Devex_Keur,Devex_Date,">="&ET$3,Devex_Date,"<="&ET$4,Devex_Land,0) -> 0
C55: Land (E: paid to the exit) | D55: EUR k | E55: =-SUMIF($J$4:$ET$4,"<="&$E12,$J55:$ET55) -> 430.44452 | I55: =SUM(J55:ET55) -> -430.44452 | J55: =-SUMIFS(Devex_Keur,Devex_Date,">="&J$3,Devex_Date,"<="&J$4,Devex_Land,1) -> 0 | K55: =-SUMIFS(Devex_Keur,Devex_Date,">="&K$3,Devex_Date,"<="&K$4,Devex_Land,1) -> 0 | L55: =-SUMIFS(Devex_Keur,Devex_Date,">="&L$3,Devex_Date,"<="&L$4,Devex_Land,1) -> -180.58151 | M55: =-SUMIFS(Devex_Keur,Devex_Date,">="&M$3,Devex_Date,"<="&M$4,Devex_Land,1) -> 0 | N55: =-SUMIFS(Devex_Keur,Devex_Date,">="&N$3,Devex_Date,"<="&N$4,Devex_Land,1) -> 0 | O55: =-SUMIFS(Devex_Keur,Devex_Date,">="&O$3,Devex_Date,"<="&O$4,Devex_Land,1) -> 0 | P55: =-SUMIFS(Devex_Keur,Devex_Date,">="&P$3,Devex_Date,"<="&P$4,Devex_Land,1) -> 0 | Q55: =-SUMIFS(Devex_Keur,Devex_Date,">="&Q$3,Devex_Date,"<="&Q$4,Devex_Land,1) -> 0 | ... ET55: =-SUMIFS(Devex_Keur,Devex_Date,">="&ET$3,Devex_Date,"<="&ET$4,Devex_Land,1) -> 0
C56: Devex contingency | D56: EUR k | E56: =In_Devex_Contingency*(SUM(Devex_Keur)+$E47) -> 284.34943 | F56: =In_Contingency_Date -> 47118 | I56: =SUM(J56:ET56) -> -284.34943 | J56: =-$E56*N(AND(J$3<=$F56,J$4>=$F56)) -> 0 | K56: =-$E56*N(AND(K$3<=$F56,K$4>=$F56)) -> 0 | L56: =-$E56*N(AND(L$3<=$F56,L$4>=$F56)) -> 0 | M56: =-$E56*N(AND(M$3<=$F56,M$4>=$F56)) -> 0 | N56: =-$E56*N(AND(N$3<=$F56,N$4>=$F56)) -> 0 | O56: =-$E56*N(AND(O$3<=$F56,O$4>=$F56)) -> 0 | P56: =-$E56*N(AND(P$3<=$F56,P$4>=$F56)) -> 0 | Q56: =-$E56*N(AND(Q$3<=$F56,Q$4>=$F56)) -> 0 | ... ET56: =-$E56*N(AND(ET$3<=$F56,ET$4>=$F56)) -> 0
C57: Devex, land and contingency (E: to the exit, F: to COD) | D57: EUR k | E57: =-SUMIF($J$4:$ET$4,"<="&$E12,$J57:$ET57) -> 3119.6245 | F57: =-SUMIF($J$4:$ET$4,"<="&In_COD,$J57:$ET57) -> 3119.6245 | I57: =SUM(J57:ET57) -> -3119.6245 | J57: =J54+J55+J56 -> 0 | K57: =K54+K55+K56 -> -178.52055 | L57: =L54+L55+L56 -> -588.44452 | M57: =M54+M55+M56 -> -43.835616 | N57: =N54+N55+N56 -> -43.835616 | O57: =O54+O55+O56 -> -184.36164 | P57: =P54+P55+P56 -> -1290.0418 | Q57: =Q54+Q55+Q56 -> -4.609589 | ... ET57: =ET54+ET55+ET56 -> 0
C58: Guarantee fees (E: to the exit, F: to COD) | D58: EUR k | E58: =SUMIF($J$4:$ET$4,"<="&$E12,$J58:$ET58) -> -1278.1548 | F58: =SUMIF($J$4:$ET$4,"<="&In_COD,$J58:$ET58) -> -2011.6166 | I58: =SUM(J58:ET58) -> -2641.6119 | J58: =-(J48+J49)*In_Guarantee_Fee*J$5/Days_In_Year -> 0 | K58: =-(K48+K49)*In_Guarantee_Fee*K$5/Days_In_Year -> -18.1641 | L58: =-(L48+L49)*In_Guarantee_Fee*L$5/Days_In_Year -> -103.46639 | M58: =-(M48+M49)*In_Guarantee_Fee*M$5/Days_In_Year -> -104.61602 | N58: =-(N48+N49)*In_Guarantee_Fee*N$5/Days_In_Year -> -105.76564 | O58: =-(O48+O49)*In_Guarantee_Fee*O$5/Days_In_Year -> -105.76564 | P58: =-(P48+P49)*In_Guarantee_Fee*P$5/Days_In_Year -> -104.61602 | Q58: =-(Q48+Q49)*In_Guarantee_Fee*Q$5/Days_In_Year -> -104.61602 | ... ET58: =-(ET48+ET49)*In_Guarantee_Fee*ET$5/Days_In_Year -> 0
C59: Development cash flow (excl. connection fees) | D59: EUR k | I59: =SUM(J59:ET59) -> -7402.3323 | J59: =J46+J47+J50+J57+J58 -> -400 | K59: =K46+K47+K50+K57+K58 -> -1437.7805 | L59: =L46+L47+L50+L57+L58 -> -691.91091 | M59: =M46+M47+M50+M57+M58 -> -148.45163 | N59: =N46+N47+N50+N57+N58 -> -149.60126 | O59: =O46+O47+O50+O57+O58 -> -290.12729 | P59: =P46+P47+P50+P57+P58 -> -1394.6578 | Q59: =Q46+Q47+Q50+Q57+Q58 -> -109.22561 | ... ET59: =ET46+ET47+ET50+ET57+ET58 -> 0
C60: Cash posted incl. land, cumulative (E: at the exit) | D60: EUR k | E60: =SUMIF($J$4:$ET$4,$E12,$J60:$ET60) -> 21850.928 | J60: =I60-J47-J50-J53-J55 -> 0 | K60: =J60-K47-K50-K53-K55 -> 1241.0959 | L60: =K60-L47-L50-L53-L55 -> 1421.6774 | M60: =L60-M47-M50-M53-M55 -> 1421.6774 | N60: =M60-N47-N50-N53-N55 -> 1421.6774 | O60: =N60-O47-O50-O53-O55 -> 1421.6774 | P60: =O60-P47-P50-P53-P55 -> 1421.6774 | Q60: =P60-Q47-Q50-Q53-Q55 -> 1421.6774 | ... ET60: =ES60-ET47-ET50-ET53-ET55 -> 21850.928
A62: x | C62: FEP claims, devex-file method, accrued to COD (E: to the exit, F: to COD)
C63: Cash 12 %: participation fee, TSO security, connection fees
C64: New principal (E: recoverable, to the exit) | D64: EUR k | E64: =SUMIF($J$4:$ET$4,"<="&$E12,$J64:$ET64)+$I47 -> 21412.264 | I64: =SUM(J64:ET64) -> 21420.483 | J64: =-(J47+J50+J53) -> 0 | K64: =-(K47+K50+K53) -> 1241.0959 | L64: =-(L47+L50+L53) -> 0 | M64: =-(M47+M50+M53) -> 0 | N64: =-(N47+N50+N53) -> 0 | O64: =-(O47+O50+O53) -> 0 | P64: =-(P47+P50+P53) -> 0 | Q64: =-(Q47+Q50+Q53) -> 0 | ... ET64: =-(ET47+ET50+ET53) -> 0
C65: Date-weighted new principal | D65: # | J65: =-(J47*$F47+J50*$F50+J51*$F51+J52*$F52) -> 0 | K65: =-(K47*$F47+K50*$F50+K51*$F51+K52*$F52) -> 57568973 | L65: =-(L47*$F47+L50*$F50+L51*$F51+L52*$F52) -> 0 | M65: =-(M47*$F47+M50*$F50+M51*$F51+M52*$F52) -> 0 | N65: =-(N47*$F47+N50*$F50+N51*$F51+N52*$F52) -> 0 | O65: =-(O47*$F47+O50*$F50+O51*$F51+O52*$F52) -> 0 | P65: =-(P47*$F47+P50*$F50+P51*$F51+P52*$F52) -> 0 | Q65: =-(Q47*$F47+Q50*$F50+Q51*$F51+Q52*$F52) -> 0 | ... ET65: =-(ET47*$F47+ET50*$F50+ET51*$F51+ET52*$F52) -> 0
C66: Opening balance | D66: EUR k | J66: =I69 -> 0 | K66: =J69 -> 0 | L66: =K69 -> 1242.0768 | M66: =L69 -> 1242.0768 | N66: =M69 -> 1242.0768 | O66: =N69 -> 1242.0768 | P66: =O69 -> 1391.126 | Q66: =P69 -> 1391.126 | ... ET66: =ES69 -> 28053.765
C67: Return accrued | D67: EUR k | E67: =SUMIF($J$4:$ET$4,"<="&$E12,$J67:$ET67) -> 1564.5366 | F67: =SUMIF($J$4:$ET$4,"<="&In_COD,$J67:$ET67) -> 6633.2814 | I67: =SUM(J67:ET67) -> 6633.2814 | J67: =In_Cash_Rate/Days_In_Year*(1-J19)*(J66*J$5+(J$4+1)*J64-J65)*(J$4<=In_COD) -> 0 | K67: =In_Cash_Rate/Days_In_Year*(1-K19)*(K66*K$5+(K$4+1)*K64-K65)*(K$4<=In_COD) -> 0.98089698 | L67: =In_Cash_Rate/Days_In_Year*(1-L19)*(L66*L$5+(L$4+1)*L64-L65)*(L$4<=In_COD) -> 36.751861 | M67: =In_Cash_Rate/Days_In_Year*(1-M19)*(M66*M$5+(M$4+1)*M64-M65)*(M$4<=In_COD) -> 37.160215 | N67: =In_Cash_Rate/Days_In_Year*(1-N19)*(N66*N$5+(N$4+1)*N64-N65)*(N$4<=In_COD) -> 37.568569 | O67: =In_Cash_Rate/Days_In_Year*(1-O19)*(O66*O$5+(O$4+1)*O64-O65)*(O$4<=In_COD) -> 37.568569 | P67: =In_Cash_Rate/Days_In_Year*(1-P19)*(P66*P$5+(P$4+1)*P64-P65)*(P$4<=In_COD) -> 41.619441 | Q67: =In_Cash_Rate/Days_In_Year*(1-Q19)*(Q66*Q$5+(Q$4+1)*Q64-Q65)*(Q$4<=In_COD) -> 41.619441 | ... ET67: =In_Cash_Rate/Days_In_Year*(1-ET19)*(ET66*ET$5+(ET$4+1)*ET64-ET65)*(ET$4<=In_COD) -> 0
C68: Capitalised at 31-Dec | D68: EUR k | I68: =SUM(J68:ET68) -> 6633.2814 | J68: =J20*SUMIF($J$7:J$7,J$7,$J67:J67) -> 0 | K68: =K20*SUMIF($J$7:K$7,K$7,$J67:K67) -> 0.98089698 | L68: =L20*SUMIF($J$7:L$7,L$7,$J67:L67) -> 0 | M68: =M20*SUMIF($J$7:M$7,M$7,$J67:M67) -> 0 | N68: =N20*SUMIF($J$7:N$7,N$7,$J67:N67) -> 0 | O68: =O20*SUMIF($J$7:O$7,O$7,$J67:O67) -> 149.04921 | P68: =P20*SUMIF($J$7:P$7,P$7,$J67:P67) -> 0 | Q68: =Q20*SUMIF($J$7:Q$7,Q$7,$J67:Q67) -> 0 | ... ET68: =ET20*SUMIF($J$7:ET$7,ET$7,$J67:ET67) -> 0
C69: Closing balance | D69: EUR k | J69: =J66+J64+J68 -> 0 | K69: =K66+K64+K68 -> 1242.0768 | L69: =L66+L64+L68 -> 1242.0768 | M69: =M66+M64+M68 -> 1242.0768 | N69: =N66+N64+N68 -> 1242.0768 | O69: =O66+O64+O68 -> 1391.126 | P69: =P66+P64+P68 -> 1391.126 | Q69: =Q66+Q64+Q68 -> 1391.126 | ... ET69: =ET66+ET64+ET68 -> 28053.765
C70: Guarantee 6 %: bid security and performance security face value
C71: Opening capitalised return | D71: EUR k | J71: =I74 -> 0 | K71: =J74 -> 0 | L71: =K74 -> 18.1641 | M71: =L74 -> 18.1641 | N71: =M74 -> 18.1641 | O71: =N74 -> 18.1641 | P71: =O74 -> 438.86764 | Q71: =P74 -> 438.86764 | ... ET71: =ES74 -> 1993.3021
C72: Return accrued | D72: EUR k | E72: =SUMIF($J$4:$ET$4,"<="&$E12,$J72:$ET72) -> 1120.4802 | F72: =SUMIF($J$4:$ET$4,"<="&In_COD,$J72:$ET72) -> 1993.3021 | I72: =SUM(J72:ET72) -> 1993.3021 | J72: =In_Guar_Credit*(1-J19)*(J71+J48+J49)*J$5/Days_In_Year*(J$4<=In_COD) -> 0 | K72: =In_Guar_Credit*(1-K19)*(K71+K48+K49)*K$5/Days_In_Year*(K$4<=In_COD) -> 18.1641 | L72: =In_Guar_Credit*(1-L19)*(L71+L48+L49)*L$5/Days_In_Year*(L$4<=In_COD) -> 103.73512 | M72: =In_Guar_Credit*(1-M19)*(M71+M48+M49)*M$5/Days_In_Year*(M$4<=In_COD) -> 104.88773 | N72: =In_Guar_Credit*(1-N19)*(N71+N48+N49)*N$5/Days_In_Year*(N$4<=In_COD) -> 106.04035 | O72: =In_Guar_Credit*(1-O19)*(O71+O48+O49)*O$5/Days_In_Year*(O$4<=In_COD) -> 106.04035 | P72: =In_Guar_Credit*(1-P19)*(P71+P48+P49)*P$5/Days_In_Year*(P$4<=In_COD) -> 111.181 | Q72: =In_Guar_Credit*(1-Q19)*(Q71+Q48+Q49)*Q$5/Days_In_Year*(Q$4<=In_COD) -> 111.181 | ... ET72: =In_Guar_Credit*(1-ET19)*(ET71+ET48+ET49)*ET$5/Days_In_Year*(ET$4<=In_COD) -> 0
C73: Capitalised at 31-Dec | D73: EUR k | I73: =SUM(J73:ET73) -> 1993.3021 | J73: =J20*SUMIF($J$7:J$7,J$7,$J72:J72) -> 0 | K73: =K20*SUMIF($J$7:K$7,K$7,$J72:K72) -> 18.1641 | L73: =L20*SUMIF($J$7:L$7,L$7,$J72:L72) -> 0 | M73: =M20*SUMIF($J$7:M$7,M$7,$J72:M72) -> 0 | N73: =N20*SUMIF($J$7:N$7,N$7,$J72:N72) -> 0 | O73: =O20*SUMIF($J$7:O$7,O$7,$J72:O72) -> 420.70354 | P73: =P20*SUMIF($J$7:P$7,P$7,$J72:P72) -> 0 | Q73: =Q20*SUMIF($J$7:Q$7,Q$7,$J72:Q72) -> 0 | ... ET73: =ET20*SUMIF($J$7:ET$7,ET$7,$J72:ET72) -> 0
C74: Closing capitalised return | D74: EUR k | J74: =J71+J73 -> 0 | K74: =K71+K73 -> 18.1641 | L74: =L71+L73 -> 18.1641 | M74: =M71+M73 -> 18.1641 | N74: =N71+N73 -> 18.1641 | O74: =O71+O73 -> 438.86764 | P74: =P71+P73 -> 438.86764 | Q74: =Q71+Q73 -> 438.86764 | ... ET74: =ET71+ET73 -> 1993.3021
C75: At risk 20 % with 2x floor: devex, land, contingency
C76: Date-weighted new principal | D76: # | J76: =SUMPRODUCT(Devex_Keur*Devex_Date*(Devex_Date>=J$3)*(Devex_Date<=J$4))-J56*$F56 -> 0 | K76: =SUMPRODUCT(Devex_Keur*Devex_Date*(Devex_Date>=K$3)*(Devex_Date<=K$4))-K56*$F56 -> 8264787.3 | L76: =SUMPRODUCT(Devex_Keur*Devex_Date*(Devex_Date>=L$3)*(Devex_Date<=L$4))-L56*$F56 -> 27328011 | M76: =SUMPRODUCT(Devex_Keur*Devex_Date*(Devex_Date>=M$3)*(Devex_Date<=M$4))-M56*$F56 -> 2041249.3 | N76: =SUMPRODUCT(Devex_Keur*Devex_Date*(Devex_Date>=N$3)*(Devex_Date<=N$4))-N56*$F56 -> 2042564.4 | O76: =SUMPRODUCT(Devex_Keur*Devex_Date*(Devex_Date>=O$3)*(Devex_Date<=O$4))-O56*$F56 -> 8617904.1 | P76: =SUMPRODUCT(Devex_Keur*Devex_Date*(Devex_Date>=P$3)*(Devex_Date<=P$4))-P56*$F56 -> 60359660 | Q76: =SUMPRODUCT(Devex_Keur*Devex_Date*(Devex_Date>=Q$3)*(Devex_Date<=Q$4))-Q56*$F56 -> 216330.55 | ... ET76: =SUMPRODUCT(Devex_Keur*Devex_Date*(Devex_Date>=ET$3)*(Devex_Date<=ET$4))-ET56*$F56 -> 0
C77: Opening balance | D77: EUR k | J77: =I80 -> 0 | K77: =J80 -> 0 | L77: =K80 -> 187.51994 | M77: =L80 -> 775.96446 | N77: =M80 -> 819.80008 | O77: =N80 -> 863.63569 | P77: =O80 -> 1195.1838 | Q77: =P80 -> 2485.2256 | ... ET77: =ES80 -> 5690.5611
C78: Return accrued (E, F: with the floor) | D78: EUR k | E78: =MAX(SUMIF($J$4:$ET$4,"<="&$E12,$J78:$ET78),(In_Min_Multiple-1)*$E57) -> 3119.6245 | F78: =MAX(SUMIF($J$4:$ET$4,"<="&In_COD,$J78:$ET78),(In_Min_Multiple-1)*$F57) -> 3119.6245 | I78: =SUM(J78:ET78) -> 2570.9366 | J78: =In_AtRisk_Rate/Days_In_Year*(1-J19)*(J77*J$5-(J$4+1)*J57-J76)*(J$4<=In_COD) -> 0 | K78: =In_AtRisk_Rate/Days_In_Year*(1-K19)*(K77*K$5-(K$4+1)*K57-K76)*(K$4<=In_COD) -> 8.999392 | L78: =In_AtRisk_Rate/Days_In_Year*(1-L19)*(L77*L$5-(L$4+1)*L57-L76)*(L$4<=In_COD) -> 21.145094 | M78: =In_AtRisk_Rate/Days_In_Year*(1-M19)*(M77*M$5-(M$4+1)*M57-M76)*(M$4<=In_COD) -> 38.763985 | N78: =In_AtRisk_Rate/Days_In_Year*(1-N19)*(N77*N$5-(N$4+1)*N57-N76)*(N$4<=In_COD) -> 42.888177 | O78: =In_AtRisk_Rate/Days_In_Year*(1-O19)*(O77*O$5-(O$4+1)*O57-O76)*(O$4<=In_COD) -> 44.389222 | P78: =In_AtRisk_Rate/Days_In_Year*(1-P19)*(P77*P$5-(P$4+1)*P57-P76)*(P$4<=In_COD) -> 98.531352 | Q78: =In_AtRisk_Rate/Days_In_Year*(1-Q19)*(Q77*Q$5-(Q$4+1)*Q57-Q76)*(Q$4<=In_COD) -> 123.93208 | ... ET78: =In_AtRisk_Rate/Days_In_Year*(1-ET19)*(ET77*ET$5-(ET$4+1)*ET57-ET76)*(ET$4<=In_COD) -> 0
C79: Capitalised at 31-Dec | D79: EUR k | I79: =SUM(J79:ET79) -> 2570.9366 | J79: =J20*SUMIF($J$7:J$7,J$7,$J78:J78) -> 0 | K79: =K20*SUMIF($J$7:K$7,K$7,$J78:K78) -> 8.999392 | L79: =L20*SUMIF($J$7:L$7,L$7,$J78:L78) -> 0 | M79: =M20*SUMIF($J$7:M$7,M$7,$J78:M78) -> 0 | N79: =N20*SUMIF($J$7:N$7,N$7,$J78:N78) -> 0 | O79: =O20*SUMIF($J$7:O$7,O$7,$J78:O78) -> 147.18648 | P79: =P20*SUMIF($J$7:P$7,P$7,$J78:P78) -> 0 | Q79: =Q20*SUMIF($J$7:Q$7,Q$7,$J78:Q78) -> 0 | ... ET79: =ET20*SUMIF($J$7:ET$7,ET$7,$J78:ET78) -> 0
C80: Closing balance | D80: EUR k | J80: =J77-J57+J79 -> 0 | K80: =K77-K57+K79 -> 187.51994 | L80: =L77-L57+L79 -> 775.96446 | M80: =M77-M57+M79 -> 819.80008 | N80: =N77-N57+N79 -> 863.63569 | O80: =O77-O57+O79 -> 1195.1838 | P80: =P77-P57+P79 -> 2485.2256 | Q80: =Q77-Q57+Q79 -> 2489.8352 | ... ET80: =ET77-ET57+ET79 -> 5690.5611
A82: x | C82: Overbuild and BESS sanction (E: wind / pro rata, F: BESS / full call)
C83: Build shortfall share | D83: % | E83: =1-$F24/$E24 -> 0.33774834 | F83: =(1-In_BESS_Built)*($E25>0) -> 0
C84: Performance security by technology | D84: EUR k | E84: =$E49*$E24*In_Bench_Wind/$E45 -> 4199.0411 | F84: =$E49-$E84 -> 2794.5205
C85: Sanction amount | D85: EUR k | E85: =($E83>In_Tolerance_Cap)*$E83*$E84+($F83>In_Tolerance_Cap)*$F83*$F84 -> 1418.2192 | F85: =($E83+$F83>0)*$E49 -> 6993.5616
C86: Sanction paid, selected regime (E: date) | D86: EUR k | E86: =EDATE(In_COD,In_Sanction_Lag) -> 48303 | I86: =SUM(J86:ET86) -> -1418.2192 | J86: =-CHOOSE(In_Sanction_Regime,$E85,$F85)*N(AND(J$3<=$E86,J$4>=$E86)) -> 0 | K86: =-CHOOSE(In_Sanction_Regime,$E85,$F85)*N(AND(K$3<=$E86,K$4>=$E86)) -> 0 | L86: =-CHOOSE(In_Sanction_Regime,$E85,$F85)*N(AND(L$3<=$E86,L$4>=$E86)) -> 0 | M86: =-CHOOSE(In_Sanction_Regime,$E85,$F85)*N(AND(M$3<=$E86,M$4>=$E86)) -> 0 | N86: =-CHOOSE(In_Sanction_Regime,$E85,$F85)*N(AND(N$3<=$E86,N$4>=$E86)) -> 0 | O86: =-CHOOSE(In_Sanction_Regime,$E85,$F85)*N(AND(O$3<=$E86,O$4>=$E86)) -> 0 | P86: =-CHOOSE(In_Sanction_Regime,$E85,$F85)*N(AND(P$3<=$E86,P$4>=$E86)) -> 0 | Q86: =-CHOOSE(In_Sanction_Regime,$E85,$F85)*N(AND(Q$3<=$E86,Q$4>=$E86)) -> 0 | ... ET86: =-CHOOSE(In_Sanction_Regime,$E85,$F85)*N(AND(ET$3<=$E86,ET$4>=$E86)) -> 0
C87: Connection capacity lost pro rata | D87: MVA | E87: =($E83>In_Tolerance_Cap)*$E83*In_MVA -> 33.774834
C88: 3-year group exclusion possible (if the PB loss counts as a call) | D88: flag | E88: =N($I86<0) -> 1
A90: x | C90: Build and debt
C91: Turbine supply, live route | D91: EUR k/MW | E91: =IF(In_CN_Turbine=1,In_Turbine_CN,In_Turbine) -> 600
C92: Substation and 132 kV bay, live route | D92: EUR k | E92: =IF(In_CN_Turbine=1,In_Substation_CN,In_Substation) -> 12000
C93: Capex on built MW (E: total) | D93: EUR k | E93: =(($E91+In_Other_Wind)*$F24+$E92)*(1+In_Capex_Contingency)+In_BESS_Capex*$F25 -> 125115 | I93: =SUM(J93:ET93) -> -125115 | J93: =-$E93*J13 -> 0 | K93: =-$E93*K13 -> 0 | L93: =-$E93*L13 -> 0 | M93: =-$E93*M13 -> 0 | N93: =-$E93*N13 -> 0 | O93: =-$E93*O13 -> 0 | P93: =-$E93*P13 -> 0 | Q93: =-$E93*Q13 -> 0 | ... ET93: =-$E93*ET13 -> 0
C94: Municipal one-off at COD | D94: EUR k | E94: =$E30*In_MVA -> 5000 | I94: =SUM(J94:ET94) -> -5000 | J94: =-$E94*J14 -> 0 | K94: =-$E94*K14 -> 0 | L94: =-$E94*L14 -> 0 | M94: =-$E94*M14 -> 0 | N94: =-$E94*N14 -> 0 | O94: =-$E94*O14 -> 0 | P94: =-$E94*P14 -> 0 | Q94: =-$E94*Q14 -> 0 | ... ET94: =-$E94*ET14 -> 0
C95: Senior debt
C96: Opening balance | D96: EUR k | J96: =I100 -> 0 | K96: =J100 -> 0 | L96: =K100 -> 0 | M96: =L100 -> 0 | N96: =M100 -> 0 | O96: =N100 -> 0 | P96: =O100 -> 0 | Q96: =P100 -> 0 | ... ET96: =ES100 -> 0
C97: Drawdown (E: debt size) | D97: EUR k | E97: =-IF(In_CN_Turbine=1,In_Gearing_CN,In_Gearing)*($I93+$I53+$I94) -> 90176.632 | I97: =SUM(J97:ET97) -> 90176.632 | J97: =$E97*J13 -> 0 | K97: =$E97*K13 -> 0 | L97: =$E97*L13 -> 0 | M97: =$E97*M13 -> 0 | N97: =$E97*N13 -> 0 | O97: =$E97*O13 -> 0 | P97: =$E97*P13 -> 0 | Q97: =$E97*Q13 -> 0 | ... ET97: =$E97*ET13 -> 0
C98: Interest capitalised (F: rate per period) | D98: EUR k | F98: =In_Debt_Rate*Months_Per_Period/Months_In_Year -> 0.0125 | I98: =SUM(J98:ET98) -> 4043.8715 | J98: =J96*$F98*(J$4<=In_COD) -> 0 | K98: =K96*$F98*(K$4<=In_COD) -> 0 | L98: =L96*$F98*(L$4<=In_COD) -> 0 | M98: =M96*$F98*(M$4<=In_COD) -> 0 | N98: =N96*$F98*(N$4<=In_COD) -> 0 | O98: =O96*$F98*(O$4<=In_COD) -> 0 | P98: =P96*$F98*(P$4<=In_COD) -> 0 | Q98: =Q96*$F98*(Q$4<=In_COD) -> 0 | ... ET98: =ET96*$F98*(ET$4<=In_COD) -> 0
C99: Repayment (level annuity) | D99: EUR k | I99: =SUM(J99:ET99) -> -94220.504 | J99: =PPMT($F98,1,In_Debt_Tenor*Months_In_Year/Months_Per_Period-SUM($J17:J17)+1,J96)*J17 -> 0 | K99: =PPMT($F98,1,In_Debt_Tenor*Months_In_Year/Months_Per_Period-SUM($J17:K17)+1,K96)*K17 -> 0 | L99: =PPMT($F98,1,In_Debt_Tenor*Months_In_Year/Months_Per_Period-SUM($J17:L17)+1,L96)*L17 -> 0 | M99: =PPMT($F98,1,In_Debt_Tenor*Months_In_Year/Months_Per_Period-SUM($J17:M17)+1,M96)*M17 -> 0 | N99: =PPMT($F98,1,In_Debt_Tenor*Months_In_Year/Months_Per_Period-SUM($J17:N17)+1,N96)*N17 -> 0 | O99: =PPMT($F98,1,In_Debt_Tenor*Months_In_Year/Months_Per_Period-SUM($J17:O17)+1,O96)*O17 -> 0 | P99: =PPMT($F98,1,In_Debt_Tenor*Months_In_Year/Months_Per_Period-SUM($J17:P17)+1,P96)*P17 -> 0 | Q99: =PPMT($F98,1,In_Debt_Tenor*Months_In_Year/Months_Per_Period-SUM($J17:Q17)+1,Q96)*Q17 -> 0 | ... ET99: =PPMT($F98,1,In_Debt_Tenor*Months_In_Year/Months_Per_Period-SUM($J17:ET17)+1,ET96)*ET17 -> 0
C100: Closing balance | D100: EUR k | J100: =SUM(J96:J99) -> 0 | K100: =SUM(K96:K99) -> 0 | L100: =SUM(L96:L99) -> 0 | M100: =SUM(M96:M99) -> 0 | N100: =SUM(N96:N99) -> 0 | O100: =SUM(O96:O99) -> 0 | P100: =SUM(P96:P99) -> 0 | Q100: =SUM(Q96:Q99) -> 0 | ... ET100: =SUM(ET96:ET99) -> 0
C101: Interest paid | D101: EUR k | I101: =SUM(J101:ET101) -> -26085.564 | J101: =-J96*$F98*(J$4>In_COD) -> 0 | K101: =-K96*$F98*(K$4>In_COD) -> 0 | L101: =-L96*$F98*(L$4>In_COD) -> 0 | M101: =-M96*$F98*(M$4>In_COD) -> 0 | N101: =-N96*$F98*(N$4>In_COD) -> 0 | O101: =-O96*$F98*(O$4>In_COD) -> 0 | P101: =-P96*$F98*(P$4>In_COD) -> 0 | Q101: =-Q96*$F98*(Q$4>In_COD) -> 0 | ... ET101: =-ET96*$F98*(ET$4>In_COD) -> 0
C102: Upfront fee | D102: EUR k | I102: =SUM(J102:ET102) -> -1578.0911 | J102: =-In_Upfront_Fee*$E97*(J96=0)*(J97>0) -> 0 | K102: =-In_Upfront_Fee*$E97*(K96=0)*(K97>0) -> 0 | L102: =-In_Upfront_Fee*$E97*(L96=0)*(L97>0) -> 0 | M102: =-In_Upfront_Fee*$E97*(M96=0)*(M97>0) -> 0 | N102: =-In_Upfront_Fee*$E97*(N96=0)*(N97>0) -> 0 | O102: =-In_Upfront_Fee*$E97*(O96=0)*(O97>0) -> 0 | P102: =-In_Upfront_Fee*$E97*(P96=0)*(P97>0) -> 0 | Q102: =-In_Upfront_Fee*$E97*(Q96=0)*(Q97>0) -> 0 | ... ET102: =-In_Upfront_Fee*$E97*(ET96=0)*(ET97>0) -> 0
C103: Commitment fee | D103: EUR k | I103: =SUM(J103:ET103) -> -913.04678 | J103: =-In_Commitment_Fee*($E97-SUM($J97:J97)+J97)*J$6*(J13>0) -> 0 | K103: =-In_Commitment_Fee*($E97-SUM($J97:K97)+K97)*K$6*(K13>0) -> 0 | L103: =-In_Commitment_Fee*($E97-SUM($J97:L97)+L97)*L$6*(L13>0) -> 0 | M103: =-In_Commitment_Fee*($E97-SUM($J97:M97)+M97)*M$6*(M13>0) -> 0 | N103: =-In_Commitment_Fee*($E97-SUM($J97:N97)+N97)*N$6*(N13>0) -> 0 | O103: =-In_Commitment_Fee*($E97-SUM($J97:O97)+O97)*O$6*(O13>0) -> 0 | P103: =-In_Commitment_Fee*($E97-SUM($J97:P97)+P97)*P$6*(P13>0) -> 0 | Q103: =-In_Commitment_Fee*($E97-SUM($J97:Q97)+Q97)*Q$6*(Q13>0) -> 0 | ... ET103: =-In_Commitment_Fee*($E97-SUM($J97:ET97)+ET97)*ET$6*(ET13>0) -> 0
C104: Build cost (capex, connection, municipal, debt fees) | D104: EUR k | I104: =SUM(J104:ET104) -> -152785.53 | J104: =J93+J53+J94+J102+J103 -> 0 | K104: =K93+K53+K94+K102+K103 -> 0 | L104: =L93+L53+L94+L102+L103 -> 0 | M104: =M93+M53+M94+M102+M103 -> 0 | N104: =N93+N53+N94+N102+N103 -> 0 | O104: =O93+O53+O94+O102+O103 -> 0 | P104: =P93+P53+P94+P102+P103 -> 0 | Q104: =Q93+Q53+Q94+Q102+Q103 -> 0 | ... ET104: =ET93+ET53+ET94+ET102+ET103 -> 0
A106: x | C106: Operations
C107: Operating year | D107: # | J107: =ROUNDUP(YEARFRAC(In_COD,J$4),0)*(J$4>In_COD) -> 0 | K107: =ROUNDUP(YEARFRAC(In_COD,K$4),0)*(K$4>In_COD) -> 0 | L107: =ROUNDUP(YEARFRAC(In_COD,L$4),0)*(L$4>In_COD) -> 0 | M107: =ROUNDUP(YEARFRAC(In_COD,M$4),0)*(M$4>In_COD) -> 0 | N107: =ROUNDUP(YEARFRAC(In_COD,N$4),0)*(N$4>In_COD) -> 0 | O107: =ROUNDUP(YEARFRAC(In_COD,O$4),0)*(O$4>In_COD) -> 0 | P107: =ROUNDUP(YEARFRAC(In_COD,P$4),0)*(P$4>In_COD) -> 0 | Q107: =ROUNDUP(YEARFRAC(In_COD,Q$4),0)*(Q$4>In_COD) -> 0 | ... ET107: =ROUNDUP(YEARFRAC(In_COD,ET$4),0)*(ET$4>In_COD) -> 30
C108: Opex escalation index | D108: factor | J108: =(1+In_Opex_Esc)^(J$7-YEAR(In_COD)) -> 0.88385429 | K108: =(1+In_Opex_Esc)^(K$7-YEAR(In_COD)) -> 0.88385429 | L108: =(1+In_Opex_Esc)^(L$7-YEAR(In_COD)) -> 0.90595064 | M108: =(1+In_Opex_Esc)^(M$7-YEAR(In_COD)) -> 0.90595064 | N108: =(1+In_Opex_Esc)^(N$7-YEAR(In_COD)) -> 0.90595064 | O108: =(1+In_Opex_Esc)^(O$7-YEAR(In_COD)) -> 0.90595064 | P108: =(1+In_Opex_Esc)^(P$7-YEAR(In_COD)) -> 0.92859941 | Q108: =(1+In_Opex_Esc)^(Q$7-YEAR(In_COD)) -> 0.92859941 | ... ET108: =(1+In_Opex_Esc)^(ET$7-YEAR(In_COD)) -> 2.0975676
C109: PPA price | D109: EUR/MWh | J109: =In_PPA_Price*(1+In_PPA_Esc)^(J$7-YEAR(In_COD)) -> 85.631912 | K109: =In_PPA_Price*(1+In_PPA_Esc)^(K$7-YEAR(In_COD)) -> 85.631912 | L109: =In_PPA_Price*(1+In_PPA_Esc)^(L$7-YEAR(In_COD)) -> 86.488231 | M109: =In_PPA_Price*(1+In_PPA_Esc)^(M$7-YEAR(In_COD)) -> 86.488231 | N109: =In_PPA_Price*(1+In_PPA_Esc)^(N$7-YEAR(In_COD)) -> 86.488231 | O109: =In_PPA_Price*(1+In_PPA_Esc)^(O$7-YEAR(In_COD)) -> 86.488231 | P109: =In_PPA_Price*(1+In_PPA_Esc)^(P$7-YEAR(In_COD)) -> 87.353113 | Q109: =In_PPA_Price*(1+In_PPA_Esc)^(Q$7-YEAR(In_COD)) -> 87.353113 | ... ET109: =In_PPA_Price*(1+In_PPA_Esc)^(ET$7-YEAR(In_COD)) -> 121.3064
...

Sheet Calc_2
A1: 2 | C1: Bid number
B2: =Dashboard!$C$3&" – Calculations – "&INDEX(Bid_Labels,1,$A$1) -> Project Bora – Calculations – BORA 2
C3: Period start | D3: date | J3: =I$4+1 -> 46204 | K3: =J$4+1 -> 46296 | L3: =K$4+1 -> 46388 | M3: =L$4+1 -> 46478 | N3: =M$4+1 -> 46569 | O3: =N$4+1 -> 46661 | P3: =O$4+1 -> 46753 | Q3: =P$4+1 -> 46844 | ... ET3: =ES$4+1 -> 58988
C4: Period end | D4: date | I4: =In_Model_Start-1 -> 46203 | J4: =EOMONTH(J$3,Months_Per_Period-1) -> 46295 | K4: =EOMONTH(K$3,Months_Per_Period-1) -> 46387 | L4: =EOMONTH(L$3,Months_Per_Period-1) -> 46477 | M4: =EOMONTH(M$3,Months_Per_Period-1) -> 46568 | N4: =EOMONTH(N$3,Months_Per_Period-1) -> 46660 | O4: =EOMONTH(O$3,Months_Per_Period-1) -> 46752 | P4: =EOMONTH(P$3,Months_Per_Period-1) -> 46843 | Q4: =EOMONTH(Q$3,Months_Per_Period-1) -> 46934 | ... ET4: =EOMONTH(ET$3,Months_Per_Period-1) -> 59079
C5: Days in period | D5: days | J5: =J$4-J$3+1 -> 92 | K5: =K$4-K$3+1 -> 92 | L5: =L$4-L$3+1 -> 90 | M5: =M$4-M$3+1 -> 91 | N5: =N$4-N$3+1 -> 92 | O5: =O$4-O$3+1 -> 92 | P5: =P$4-P$3+1 -> 91 | Q5: =Q$4-Q$3+1 -> 91 | ... ET5: =ET$4-ET$3+1 -> 92
C6: Year fraction | D6: factor | J6: =J$5/Days_In_Year -> 0.25205479 | K6: =K$5/Days_In_Year -> 0.25205479 | L6: =L$5/Days_In_Year -> 0.24657534 | M6: =M$5/Days_In_Year -> 0.24931507 | N6: =N$5/Days_In_Year -> 0.25205479 | O6: =O$5/Days_In_Year -> 0.25205479 | P6: =P$5/Days_In_Year -> 0.24931507 | Q6: =Q$5/Days_In_Year -> 0.24931507 | ... ET6: =ET$5/Days_In_Year -> 0.25205479
C7: Year | D7: year | J7: =YEAR(J$4) -> 2026 | K7: =YEAR(K$4) -> 2026 | L7: =YEAR(L$4) -> 2027 | M7: =YEAR(M$4) -> 2027 | N7: =YEAR(N$4) -> 2027 | O7: =YEAR(O$4) -> 2027 | P7: =YEAR(P$4) -> 2028 | Q7: =YEAR(Q$4) -> 2028 | ... ET7: =YEAR(ET$4) -> 2061
C8: Period counter | D8: # | J8: =I$8+1 -> 1 | K8: =J$8+1 -> 2 | L8: =K$8+1 -> 3 | M8: =L$8+1 -> 4 | N8: =M$8+1 -> 5 | O8: =N$8+1 -> 6 | P8: =O$8+1 -> 7 | Q8: =P$8+1 -> 8 | ... ET8: =ES$8+1 -> 141
A11: x | C11: Timing and flags
C12: RtB exit | D12: flag | E12: =INDEX(Dash_Exit_Date,1,$A$1) -> 47483 | I12: =SUM(J12:ET12) -> 1 | J12: =N(AND(J$3<=$E12,J$4>=$E12)) -> 0 | K12: =N(AND(K$3<=$E12,K$4>=$E12)) -> 0 | L12: =N(AND(L$3<=$E12,L$4>=$E12)) -> 0 | M12: =N(AND(M$3<=$E12,M$4>=$E12)) -> 0 | N12: =N(AND(N$3<=$E12,N$4>=$E12)) -> 0 | O12: =N(AND(O$3<=$E12,O$4>=$E12)) -> 0 | P12: =N(AND(P$3<=$E12,P$4>=$E12)) -> 0 | Q12: =N(AND(Q$3<=$E12,Q$4>=$E12)) -> 0 | ... ET12: =N(AND(ET$3<=$E12,ET$4>=$E12)) -> 0
C13: Construction share (NTP → COD) | D13: factor | E13: =In_NTP+1 -> 47392 | F13: =In_COD -> 48121 | I13: =SUM(J13:ET13) -> 1 | J13: =MAX(0,MIN($F13,J$4)-MAX($E13,J$3)+1)/($F13-$E13+1) -> 0 | K13: =MAX(0,MIN($F13,K$4)-MAX($E13,K$3)+1)/($F13-$E13+1) -> 0 | L13: =MAX(0,MIN($F13,L$4)-MAX($E13,L$3)+1)/($F13-$E13+1) -> 0 | M13: =MAX(0,MIN($F13,M$4)-MAX($E13,M$3)+1)/($F13-$E13+1) -> 0 | N13: =MAX(0,MIN($F13,N$4)-MAX($E13,N$3)+1)/($F13-$E13+1) -> 0 | O13: =MAX(0,MIN($F13,O$4)-MAX($E13,O$3)+1)/($F13-$E13+1) -> 0 | P13: =MAX(0,MIN($F13,P$4)-MAX($E13,P$3)+1)/($F13-$E13+1) -> 0 | Q13: =MAX(0,MIN($F13,Q$4)-MAX($E13,Q$3)+1)/($F13-$E13+1) -> 0 | ... ET13: =MAX(0,MIN($F13,ET$4)-MAX($E13,ET$3)+1)/($F13-$E13+1) -> 0
C14: COD | D14: flag | E14: =In_COD -> 48121 | I14: =SUM(J14:ET14) -> 1 | J14: =N(AND(J$3<=$E14,J$4>=$E14)) -> 0 | K14: =N(AND(K$3<=$E14,K$4>=$E14)) -> 0 | L14: =N(AND(L$3<=$E14,L$4>=$E14)) -> 0 | M14: =N(AND(M$3<=$E14,M$4>=$E14)) -> 0 | N14: =N(AND(N$3<=$E14,N$4>=$E14)) -> 0 | O14: =N(AND(O$3<=$E14,O$4>=$E14)) -> 0 | P14: =N(AND(P$3<=$E14,P$4>=$E14)) -> 0 | Q14: =N(AND(Q$3<=$E14,Q$4>=$E14)) -> 0 | ... ET14: =N(AND(ET$3<=$E14,ET$4>=$E14)) -> 0
C15: Operations | D15: flag | E15: =In_COD+1 -> 48122 | F15: =EDATE(In_COD,In_Life*Months_In_Year) -> 59079 | J15: =MAX(0,(MIN($F15,J$4)-MAX($E15,J$3)+1)/J$5) -> 0 | K15: =MAX(0,(MIN($F15,K$4)-MAX($E15,K$3)+1)/K$5) -> 0 | L15: =MAX(0,(MIN($F15,L$4)-MAX($E15,L$3)+1)/L$5) -> 0 | M15: =MAX(0,(MIN($F15,M$4)-MAX($E15,M$3)+1)/M$5) -> 0 | N15: =MAX(0,(MIN($F15,N$4)-MAX($E15,N$3)+1)/N$5) -> 0 | O15: =MAX(0,(MIN($F15,O$4)-MAX($E15,O$3)+1)/O$5) -> 0 | P15: =MAX(0,(MIN($F15,P$4)-MAX($E15,P$3)+1)/P$5) -> 0 | Q15: =MAX(0,(MIN($F15,Q$4)-MAX($E15,Q$3)+1)/Q$5) -> 0 | ... ET15: =MAX(0,(MIN($F15,ET$4)-MAX($E15,ET$3)+1)/ET$5) -> 1
C16: Land lease period (NTP → end of life) | D16: flag | E16: =In_NTP+1 -> 47392 | F16: =EDATE(In_COD,In_Life*Months_In_Year) -> 59079 | J16: =MAX(0,(MIN($F16,J$4)-MAX($E16,J$3)+1)/J$5) -> 0 | K16: =MAX(0,(MIN($F16,K$4)-MAX($E16,K$3)+1)/K$5) -> 0 | L16: =MAX(0,(MIN($F16,L$4)-MAX($E16,L$3)+1)/L$5) -> 0 | M16: =MAX(0,(MIN($F16,M$4)-MAX($E16,M$3)+1)/M$5) -> 0 | N16: =MAX(0,(MIN($F16,N$4)-MAX($E16,N$3)+1)/N$5) -> 0 | O16: =MAX(0,(MIN($F16,O$4)-MAX($E16,O$3)+1)/O$5) -> 0 | P16: =MAX(0,(MIN($F16,P$4)-MAX($E16,P$3)+1)/P$5) -> 0 | Q16: =MAX(0,(MIN($F16,Q$4)-MAX($E16,Q$3)+1)/Q$5) -> 0 | ... ET16: =MAX(0,(MIN($F16,ET$4)-MAX($E16,ET$3)+1)/ET$5) -> 1
C17: Debt repayment period | D17: flag | E17: =In_COD+1 -> 48122 | F17: =EDATE(In_COD,In_Debt_Tenor*Months_In_Year) -> 51774 | J17: =MAX(0,(MIN($F17,J$4)-MAX($E17,J$3)+1)/J$5) -> 0 | K17: =MAX(0,(MIN($F17,K$4)-MAX($E17,K$3)+1)/K$5) -> 0 | L17: =MAX(0,(MIN($F17,L$4)-MAX($E17,L$3)+1)/L$5) -> 0 | M17: =MAX(0,(MIN($F17,M$4)-MAX($E17,M$3)+1)/M$5) -> 0 | N17: =MAX(0,(MIN($F17,N$4)-MAX($E17,N$3)+1)/N$5) -> 0 | O17: =MAX(0,(MIN($F17,O$4)-MAX($E17,O$3)+1)/O$5) -> 0 | P17: =MAX(0,(MIN($F17,P$4)-MAX($E17,P$3)+1)/P$5) -> 0 | Q17: =MAX(0,(MIN($F17,Q$4)-MAX($E17,Q$3)+1)/Q$5) -> 0 | ... ET17: =MAX(0,(MIN($F17,ET$4)-MAX($E17,ET$3)+1)/ET$5) -> 0
C18: Tax depreciation share | D18: factor | E18: =In_COD+1 -> 48122 | F18: =EDATE(In_COD,In_Dep_Years*Months_In_Year) -> 55426 | I18: =SUM(J18:ET18) -> 1 | J18: =MAX(0,MIN($F18,J$4)-MAX($E18,J$3)+1)/($F18-$E18+1) -> 0 | K18: =MAX(0,MIN($F18,K$4)-MAX($E18,K$3)+1)/($F18-$E18+1) -> 0 | L18: =MAX(0,MIN($F18,L$4)-MAX($E18,L$3)+1)/($F18-$E18+1) -> 0 | M18: =MAX(0,MIN($F18,M$4)-MAX($E18,M$3)+1)/($F18-$E18+1) -> 0 | N18: =MAX(0,MIN($F18,N$4)-MAX($E18,N$3)+1)/($F18-$E18+1) -> 0 | O18: =MAX(0,MIN($F18,O$4)-MAX($E18,O$3)+1)/($F18-$E18+1) -> 0 | P18: =MAX(0,MIN($F18,P$4)-MAX($E18,P$3)+1)/($F18-$E18+1) -> 0 | Q18: =MAX(0,MIN($F18,Q$4)-MAX($E18,Q$3)+1)/($F18-$E18+1) -> 0 | ... ET18: =MAX(0,MIN($F18,ET$4)-MAX($E18,ET$3)+1)/($F18-$E18+1) -> 0
C19: Interest freeze (no accrual) | D19: flag | E19: =In_Freeze_Start+1 -> 47300 | F19: =In_Freeze_Start+In_Freeze_On*(In_Freeze_End-In_Freeze_Start)-1 -> 47483 | J19: =MAX(0,(MIN($F19,J$4)-MAX($E19,J$3)+1)/J$5) -> 0 | K19: =MAX(0,(MIN($F19,K$4)-MAX($E19,K$3)+1)/K$5) -> 0 | L19: =MAX(0,(MIN($F19,L$4)-MAX($E19,L$3)+1)/L$5) -> 0 | M19: =MAX(0,(MIN($F19,M$4)-MAX($E19,M$3)+1)/M$5) -> 0 | N19: =MAX(0,(MIN($F19,N$4)-MAX($E19,N$3)+1)/N$5) -> 0 | O19: =MAX(0,(MIN($F19,O$4)-MAX($E19,O$3)+1)/O$5) -> 0 | P19: =MAX(0,(MIN($F19,P$4)-MAX($E19,P$3)+1)/P$5) -> 0 | Q19: =MAX(0,(MIN($F19,Q$4)-MAX($E19,Q$3)+1)/Q$5) -> 0 | ... ET19: =MAX(0,(MIN($F19,ET$4)-MAX($E19,ET$3)+1)/ET$5) -> 0
C20: 31-Dec capitalisation | D20: flag | J20: =N(MONTH(J$4)=Months_In_Year) -> 0 | K20: =N(MONTH(K$4)=Months_In_Year) -> 1 | L20: =N(MONTH(L$4)=Months_In_Year) -> 0 | M20: =N(MONTH(M$4)=Months_In_Year) -> 0 | N20: =N(MONTH(N$4)=Months_In_Year) -> 0 | O20: =N(MONTH(O$4)=Months_In_Year) -> 1 | P20: =N(MONTH(P$4)=Months_In_Year) -> 0 | Q20: =N(MONTH(Q$4)=Months_In_Year) -> 0 | ... ET20: =N(MONTH(ET$4)=Months_In_Year) -> 0
C21: Buyer discount factor to COD | D21: factor | J21: =1/(1+In_Buyer_Rate)^(MAX(0,J$4-In_COD)/Days_In_Year) -> 1 | K21: =1/(1+In_Buyer_Rate)^(MAX(0,K$4-In_COD)/Days_In_Year) -> 1 | L21: =1/(1+In_Buyer_Rate)^(MAX(0,L$4-In_COD)/Days_In_Year) -> 1 | M21: =1/(1+In_Buyer_Rate)^(MAX(0,M$4-In_COD)/Days_In_Year) -> 1 | N21: =1/(1+In_Buyer_Rate)^(MAX(0,N$4-In_COD)/Days_In_Year) -> 1 | O21: =1/(1+In_Buyer_Rate)^(MAX(0,O$4-In_COD)/Days_In_Year) -> 1 | P21: =1/(1+In_Buyer_Rate)^(MAX(0,P$4-In_COD)/Days_In_Year) -> 1 | Q21: =1/(1+In_Buyer_Rate)^(MAX(0,Q$4-In_COD)/Days_In_Year) -> 1 | ... ET21: =1/(1+In_Buyer_Rate)^(MAX(0,ET$4-In_COD)/Days_In_Year) -> 0.099209842
A23: x | C23: Capacity (E: committed, F: built)
C24: Wind | D24: MW | E24: =In_MVA*(1+INDEX(Dash_Overbuild,1,$A$1)) -> 140 | F24: =In_MVA+($E24-In_MVA)*In_Overbuild_Built -> 100
C25: BESS power | D25: MW | E25: =INDEX(Dash_BESS,1,$A$1)*In_MVA -> 40 | F25: =$E25*In_BESS_Built -> 40
C26: BESS energy | D26: MWh | E26: =$E25*INDEX(Dash_BESS_Hours,1,$A$1) -> 160
C27: Grid-bottleneck loss on built wind | D27: % | E27: =($F24-In_MVA)/$F24*In_Bottleneck_Loss -> 0
A29: x | C29: Tender points (E: commitment, F: weighted points)
C30: ÖSZ-1 municipal one-off | D30: EUR k/MW | E30: =INDEX(Dash_Municipal,1,$A$1) -> 50 | F30: =INDEX(Osz1_Pts,1+SUMPRODUCT((Osz1_LB<$E30)+(Osz1_LB=$E30)*Osz1_Incl))*Osz1_W -> 20
C31: ÖSZ-2 community contribution | D31: EUR/MWh | E31: =INDEX(Dash_Community,1,$A$1) -> 2.01 | F31: =INDEX(Osz2_Pts,1+SUMPRODUCT((Osz2_LB<$E31)+(Osz2_LB=$E31)*Osz2_Incl))*Osz2_W -> 0.75
C32: ÖSZ-3 overbuild | D32: % | E32: =INDEX(Dash_Overbuild,1,$A$1) -> 0.4 | F32: =INDEX(Osz3_Pts,1+SUMPRODUCT((Osz3_LB<$E32)+(Osz3_LB=$E32)*Osz3_Incl))*Osz3_W -> 9
C33: ÖSZ-4 BESS ratio | D33: % | E33: =INDEX(Dash_BESS,1,$A$1)/IF(In_OSZ4_Basis=1,$E24/In_MVA,1) -> 0.4 | F33: =INDEX(Osz4_Pts,1+SUMPRODUCT((Osz4_LB<$E33)+(Osz4_LB=$E33)*Osz4_Incl))*Osz4_W*($E33>=Osz4_Min) -> 13.5
C34: ÖSZ-5 partial award | D34: flag | E34: =INDEX(Dash_Partial,1,$A$1) -> 1 | F34: =$E34*Osz5_Pts*Osz5_W -> 5
C35: ÖSZ-6 performance security multiple | D35: x | E35: =INDEX(Dash_PB_Mult,1,$A$1) -> 1 | F35: =INDEX(Osz6_Pts,1+SUMPRODUCT((Osz6_LB<$E35)+(Osz6_LB=$E35)*Osz6_Incl))*Osz6_W -> 0
C36: ÖSZ-7 brownfield | D36: flag | E36: =INDEX(Dash_Brownfield,1,$A$1) -> 0 | F36: =$E36*Osz7_Pts*Osz7_W -> 0
C37: ÖSZ-8 shared connection | D37: flag | E37: =INDEX(Dash_Shared,1,$A$1) -> 1 | F37: =$E37*Osz8_Pts*Osz8_W -> 5
C38: ÖSZ-9 EU turbines | D38: flag | E38: =INDEX(Dash_EU_Turbine,1,$A$1) -> 1 | F38: =$E38*Osz9a_Pts*Osz9_W -> 12
C39: ÖSZ-9 EU transformers | D39: flag | E39: =INDEX(Dash_EU_Transformer,1,$A$1) -> 1 | F39: =$E39*Osz9b_Pts*Osz9_W -> 3
C40: Points total (E: EU route, F: CN route) | D40: points | E40: =ROUND(SUM($F30:$F39),Points_Decimals) -> 68.25 | F40: =ROUND(SUM($F30:$F37),Points_Decimals) -> 53.25
C41: Points, live turbine route | D41: points | E41: =IF(In_CN_Turbine=1,$F40,$E40) -> 68.25
C42: Failed tests (E: capacity, F: offerable range) | D42: # | E42: =N(In_MVA>In_Group_Cap)+N($E24<In_MVA)+N($E25>$E24)+N($E26<$E25*In_Min_Hours) -> 0 | F42: =($E30<>0)*($E30<Osz1_Min)+($E30>Osz1_Max)+($E31<>0)*($E31<Osz2_Min)+($E31>Osz2_Max) -> 0
A44: x | C44: Securities, fees and development costs (E: amount, F: date)
C45: Security base | D45: mHUF | E45: =$E24*In_Bench_Wind+$E26*In_Bench_BESS -> 88840
C46: Signing fee and DD | D46: EUR k | E46: =In_Signing_Fee+In_DD -> 400 | F46: =In_Invest_Date -> 46234 | I46: =SUM(J46:ET46) -> -400 | J46: =-$E46*N(AND(J$3<=$F46,J$4>=$F46)) -> -400 | K46: =-$E46*N(AND(K$3<=$F46,K$4>=$F46)) -> 0 | L46: =-$E46*N(AND(L$3<=$F46,L$4>=$F46)) -> 0 | M46: =-$E46*N(AND(M$3<=$F46,M$4>=$F46)) -> 0 | N46: =-$E46*N(AND(N$3<=$F46,N$4>=$F46)) -> 0 | O46: =-$E46*N(AND(O$3<=$F46,O$4>=$F46)) -> 0 | P46: =-$E46*N(AND(P$3<=$F46,P$4>=$F46)) -> 0 | Q46: =-$E46*N(AND(Q$3<=$F46,Q$4>=$F46)) -> 0 | ... ET46: =-$E46*N(AND(ET$3<=$F46,ET$4>=$F46)) -> 0
C47: Participation fee (cash) | D47: EUR k | E47: =In_Part_Fee*Thousand/In_FX -> 8.2191781 | F47: =In_Bid_Date -> 46325 | I47: =SUM(J47:ET47) -> -8.2191781 | J47: =-$E47*N(AND(J$3<=$F47,J$4>=$F47)) -> 0 | K47: =-$E47*N(AND(K$3<=$F47,K$4>=$F47)) -> -8.2191781 | L47: =-$E47*N(AND(L$3<=$F47,L$4>=$F47)) -> 0 | M47: =-$E47*N(AND(M$3<=$F47,M$4>=$F47)) -> 0 | N47: =-$E47*N(AND(N$3<=$F47,N$4>=$F47)) -> 0 | O47: =-$E47*N(AND(O$3<=$F47,O$4>=$F47)) -> 0 | P47: =-$E47*N(AND(P$3<=$F47,P$4>=$F47)) -> 0 | Q47: =-$E47*N(AND(Q$3<=$F47,Q$4>=$F47)) -> 0 | ... ET47: =-$E47*N(AND(ET$3<=$F47,ET$4>=$F47)) -> 0
C48: Bid security outstanding (guarantee) | D48: EUR k | E48: =In_Bid_Rate*$E45*Thousand/In_FX -> 1216.9863 | F48: =In_Bid_Date -> 46325 | J48: =$E48*MAX(0,(MIN(In_Award_Date+In_PB_Days-1,J$4)-MAX($F48,J$3)+1)/J$5) -> 0 | K48: =$E48*MAX(0,(MIN(In_Award_Date+In_PB_Days-1,K$4)-MAX($F48,K$3)+1)/K$5) -> 780.45861 | L48: =$E48*MAX(0,(MIN(In_Award_Date+In_PB_Days-1,L$4)-MAX($F48,L$3)+1)/L$5) -> 0 | M48: =$E48*MAX(0,(MIN(In_Award_Date+In_PB_Days-1,M$4)-MAX($F48,M$3)+1)/M$5) -> 0 | N48: =$E48*MAX(0,(MIN(In_Award_Date+In_PB_Days-1,N$4)-MAX($F48,N$3)+1)/N$5) -> 0 | O48: =$E48*MAX(0,(MIN(In_Award_Date+In_PB_Days-1,O$4)-MAX($F48,O$3)+1)/O$5) -> 0 | P48: =$E48*MAX(0,(MIN(In_Award_Date+In_PB_Days-1,P$4)-MAX($F48,P$3)+1)/P$5) -> 0 | Q48: =$E48*MAX(0,(MIN(In_Award_Date+In_PB_Days-1,Q$4)-MAX($F48,Q$3)+1)/Q$5) -> 0 | ... ET48: =$E48*MAX(0,(MIN(In_Award_Date+In_PB_Days-1,ET$4)-MAX($F48,ET$3)+1)/ET$5) -> 0
C49: Performance security outstanding (guarantee) | D49: EUR k | E49: =In_PB_Rate*$E35*$E45*Thousand/In_FX -> 6084.9315 | F49: =In_Award_Date+In_PB_Days -> 46384 | J49: =$E49*MAX(0,(MIN(In_PB_Release,J$4)-MAX($F49,J$3)+1)/J$5) -> 0 | K49: =$E49*MAX(0,(MIN(In_PB_Release,K$4)-MAX($F49,K$3)+1)/K$5) -> 264.56224 | L49: =$E49*MAX(0,(MIN(In_PB_Release,L$4)-MAX($F49,L$3)+1)/L$5) -> 6084.9315 | M49: =$E49*MAX(0,(MIN(In_PB_Release,M$4)-MAX($F49,M$3)+1)/M$5) -> 6084.9315 | N49: =$E49*MAX(0,(MIN(In_PB_Release,N$4)-MAX($F49,N$3)+1)/N$5) -> 6084.9315 | O49: =$E49*MAX(0,(MIN(In_PB_Release,O$4)-MAX($F49,O$3)+1)/O$5) -> 6084.9315 | P49: =$E49*MAX(0,(MIN(In_PB_Release,P$4)-MAX($F49,P$3)+1)/P$5) -> 6084.9315 | Q49: =$E49*MAX(0,(MIN(In_PB_Release,Q$4)-MAX($F49,Q$3)+1)/Q$5) -> 6084.9315 | ... ET49: =$E49*MAX(0,(MIN(In_PB_Release,ET$4)-MAX($F49,ET$3)+1)/ET$5) -> 0
C50: TSO connection-request security (cash) | D50: EUR k | E50: =In_TSO_Security*In_MVA*Thousand/In_FX -> 1232.8767 | F50: =In_TSO_Date -> 46386 | I50: =SUM(J50:ET50) -> -1232.8767 | J50: =-$E50*N(AND(J$3<=$F50,J$4>=$F50)) -> 0 | K50: =-$E50*N(AND(K$3<=$F50,K$4>=$F50)) -> -1232.8767 | L50: =-$E50*N(AND(L$3<=$F50,L$4>=$F50)) -> 0 | M50: =-$E50*N(AND(M$3<=$F50,M$4>=$F50)) -> 0 | N50: =-$E50*N(AND(N$3<=$F50,N$4>=$F50)) -> 0 | O50: =-$E50*N(AND(O$3<=$F50,O$4>=$F50)) -> 0 | P50: =-$E50*N(AND(P$3<=$F50,P$4>=$F50)) -> 0 | Q50: =-$E50*N(AND(Q$3<=$F50,Q$4>=$F50)) -> 0 | ... ET50: =-$E50*N(AND(ET$3<=$F50,ET$4>=$F50)) -> 0
C51: Direct connection fee (cash) | D51: EUR k | E51: =In_Direct_Fee*Thousand/In_FX -> 1392.7282 | F51: =In_HCSSZ_Date -> 47126 | I51: =SUM(J51:ET51) -> -1392.7282 | J51: =-$E51*N(AND(J$3<=$F51,J$4>=$F51)) -> 0 | K51: =-$E51*N(AND(K$3<=$F51,K$4>=$F51)) -> 0 | L51: =-$E51*N(AND(L$3<=$F51,L$4>=$F51)) -> 0 | M51: =-$E51*N(AND(M$3<=$F51,M$4>=$F51)) -> 0 | N51: =-$E51*N(AND(N$3<=$F51,N$4>=$F51)) -> 0 | O51: =-$E51*N(AND(O$3<=$F51,O$4>=$F51)) -> 0 | P51: =-$E51*N(AND(P$3<=$F51,P$4>=$F51)) -> 0 | Q51: =-$E51*N(AND(Q$3<=$F51,Q$4>=$F51)) -> 0 | ... ET51: =-$E51*N(AND(ET$3<=$F51,ET$4>=$F51)) -> 0
C52: Indirect connection fee, net of TSO security | D52: EUR k | E52: =(In_Indirect_Fee-In_TSO_Security)*In_MVA*Thousand/In_FX -> 18786.659 | F52: =In_HCSSZ_Date -> 47126 | I52: =SUM(J52:ET52) -> -18786.659 | J52: =-$E52*N(AND(J$3<=$F52,J$4>=$F52)) -> 0 | K52: =-$E52*N(AND(K$3<=$F52,K$4>=$F52)) -> 0 | L52: =-$E52*N(AND(L$3<=$F52,L$4>=$F52)) -> 0 | M52: =-$E52*N(AND(M$3<=$F52,M$4>=$F52)) -> 0 | N52: =-$E52*N(AND(N$3<=$F52,N$4>=$F52)) -> 0 | O52: =-$E52*N(AND(O$3<=$F52,O$4>=$F52)) -> 0 | P52: =-$E52*N(AND(P$3<=$F52,P$4>=$F52)) -> 0 | Q52: =-$E52*N(AND(Q$3<=$F52,Q$4>=$F52)) -> 0 | ... ET52: =-$E52*N(AND(ET$3<=$F52,ET$4>=$F52)) -> 0
C53: Connection fees | D53: EUR k | I53: =SUM(J53:ET53) -> -20179.387 | J53: =J51+J52 -> 0 | K53: =K51+K52 -> 0 | L53: =L51+L52 -> 0 | M53: =M51+M52 -> 0 | N53: =N51+N52 -> 0 | O53: =O51+O52 -> 0 | P53: =P51+P52 -> 0 | Q53: =Q51+Q52 -> 0 | ... ET53: =ET51+ET52 -> 0
C54: Devex (FEP-borne) | D54: EUR k | I54: =SUM(J54:ET54) -> -2404.8306 | J54: =-SUMIFS(Devex_Keur,Devex_Date,">="&J$3,Devex_Date,"<="&J$4,Devex_Land,0) -> 0 | K54: =-SUMIFS(Devex_Keur,Devex_Date,">="&K$3,Devex_Date,"<="&K$4,Devex_Land,0) -> -178.52055 | L54: =-SUMIFS(Devex_Keur,Devex_Date,">="&L$3,Devex_Date,"<="&L$4,Devex_Land,0) -> -407.86301 | M54: =-SUMIFS(Devex_Keur,Devex_Date,">="&M$3,Devex_Date,"<="&M$4,Devex_Land,0) -> -43.835616 | N54: =-SUMIFS(Devex_Keur,Devex_Date,">="&N$3,Devex_Date,"<="&N$4,Devex_Land,0) -> -43.835616 | O54: =-SUMIFS(Devex_Keur,Devex_Date,">="&O$3,Devex_Date,"<="&O$4,Devex_Land,0) -> -184.36164 | P54: =-SUMIFS(Devex_Keur,Devex_Date,">="&P$3,Devex_Date,"<="&P$4,Devex_Land,0) -> -1290.0418 | Q54: =-SUMIFS(Devex_Keur,Devex_Date,">="&Q$3,Devex_Date,"<="&Q$4,Devex_Land,0) -> -4.609589 | ... ET54: =-SUMIFS(Devex_Keur,Devex_Date,">="&ET$3,Devex_Date,"<="&ET$4,Devex_Land,0) -> 0
C55: Land (E: paid to the exit) | D55: EUR k | E55: =-SUMIF($J$4:$ET$4,"<="&$E12,$J55:$ET55) -> 430.44452 | I55: =SUM(J55:ET55) -> -430.44452 | J55: =-SUMIFS(Devex_Keur,Devex_Date,">="&J$3,Devex_Date,"<="&J$4,Devex_Land,1) -> 0 | K55: =-SUMIFS(Devex_Keur,Devex_Date,">="&K$3,Devex_Date,"<="&K$4,Devex_Land,1) -> 0 | L55: =-SUMIFS(Devex_Keur,Devex_Date,">="&L$3,Devex_Date,"<="&L$4,Devex_Land,1) -> -180.58151 | M55: =-SUMIFS(Devex_Keur,Devex_Date,">="&M$3,Devex_Date,"<="&M$4,Devex_Land,1) -> 0 | N55: =-SUMIFS(Devex_Keur,Devex_Date,">="&N$3,Devex_Date,"<="&N$4,Devex_Land,1) -> 0 | O55: =-SUMIFS(Devex_Keur,Devex_Date,">="&O$3,Devex_Date,"<="&O$4,Devex_Land,1) -> 0 | P55: =-SUMIFS(Devex_Keur,Devex_Date,">="&P$3,Devex_Date,"<="&P$4,Devex_Land,1) -> 0 | Q55: =-SUMIFS(Devex_Keur,Devex_Date,">="&Q$3,Devex_Date,"<="&Q$4,Devex_Land,1) -> 0 | ... ET55: =-SUMIFS(Devex_Keur,Devex_Date,">="&ET$3,Devex_Date,"<="&ET$4,Devex_Land,1) -> 0
C56: Devex contingency | D56: EUR k | E56: =In_Devex_Contingency*(SUM(Devex_Keur)+$E47) -> 284.34943 | F56: =In_Contingency_Date -> 47118 | I56: =SUM(J56:ET56) -> -284.34943 | J56: =-$E56*N(AND(J$3<=$F56,J$4>=$F56)) -> 0 | K56: =-$E56*N(AND(K$3<=$F56,K$4>=$F56)) -> 0 | L56: =-$E56*N(AND(L$3<=$F56,L$4>=$F56)) -> 0 | M56: =-$E56*N(AND(M$3<=$F56,M$4>=$F56)) -> 0 | N56: =-$E56*N(AND(N$3<=$F56,N$4>=$F56)) -> 0 | O56: =-$E56*N(AND(O$3<=$F56,O$4>=$F56)) -> 0 | P56: =-$E56*N(AND(P$3<=$F56,P$4>=$F56)) -> 0 | Q56: =-$E56*N(AND(Q$3<=$F56,Q$4>=$F56)) -> 0 | ... ET56: =-$E56*N(AND(ET$3<=$F56,ET$4>=$F56)) -> 0
C57: Devex, land and contingency (E: to the exit, F: to COD) | D57: EUR k | E57: =-SUMIF($J$4:$ET$4,"<="&$E12,$J57:$ET57) -> 3119.6245 | F57: =-SUMIF($J$4:$ET$4,"<="&In_COD,$J57:$ET57) -> 3119.6245 | I57: =SUM(J57:ET57) -> -3119.6245 | J57: =J54+J55+J56 -> 0 | K57: =K54+K55+K56 -> -178.52055 | L57: =L54+L55+L56 -> -588.44452 | M57: =M54+M55+M56 -> -43.835616 | N57: =N54+N55+N56 -> -43.835616 | O57: =O54+O55+O56 -> -184.36164 | P57: =P54+P55+P56 -> -1290.0418 | Q57: =Q54+Q55+Q56 -> -4.609589 | ... ET57: =ET54+ET55+ET56 -> 0
C58: Guarantee fees (E: to the exit, F: to COD) | D58: EUR k | E58: =SUMIF($J$4:$ET$4,"<="&$E12,$J58:$ET58) -> -1112.0921 | F58: =SUMIF($J$4:$ET$4,"<="&In_COD,$J58:$ET58) -> -1750.2597 | I58: =SUM(J58:ET58) -> -2298.4037 | J58: =-(J48+J49)*In_Guarantee_Fee*J$5/Days_In_Year -> 0 | K58: =-(K48+K49)*In_Guarantee_Fee*K$5/Days_In_Year -> -15.804151 | L58: =-(L48+L49)*In_Guarantee_Fee*L$5/Days_In_Year -> -90.023644 | M58: =-(M48+M49)*In_Guarantee_Fee*M$5/Days_In_Year -> -91.023907 | N58: =-(N48+N49)*In_Guarantee_Fee*N$5/Days_In_Year -> -92.02417 | O58: =-(O48+O49)*In_Guarantee_Fee*O$5/Days_In_Year -> -92.02417 | P58: =-(P48+P49)*In_Guarantee_Fee*P$5/Days_In_Year -> -91.023907 | Q58: =-(Q48+Q49)*In_Guarantee_Fee*Q$5/Days_In_Year -> -91.023907 | ... ET58: =-(ET48+ET49)*In_Guarantee_Fee*ET$5/Days_In_Year -> 0
C59: Development cash flow (excl. connection fees) | D59: EUR k | I59: =SUM(J59:ET59) -> -7059.1241 | J59: =J46+J47+J50+J57+J58 -> -400 | K59: =K46+K47+K50+K57+K58 -> -1435.4206 | L59: =L46+L47+L50+L57+L58 -> -678.46816 | M59: =M46+M47+M50+M57+M58 -> -134.85952 | N59: =N46+N47+N50+N57+N58 -> -135.85979 | O59: =O46+O47+O50+O57+O58 -> -276.38581 | P59: =P46+P47+P50+P57+P58 -> -1381.0657 | Q59: =Q46+Q47+Q50+Q57+Q58 -> -95.633496 | ... ET59: =ET46+ET47+ET50+ET57+ET58 -> 0
C60: Cash posted incl. land, cumulative (E: at the exit) | D60: EUR k | E60: =SUMIF($J$4:$ET$4,$E12,$J60:$ET60) -> 21850.928 | J60: =I60-J47-J50-J53-J55 -> 0 | K60: =J60-K47-K50-K53-K55 -> 1241.0959 | L60: =K60-L47-L50-L53-L55 -> 1421.6774 | M60: =L60-M47-M50-M53-M55 -> 1421.6774 | N60: =M60-N47-N50-N53-N55 -> 1421.6774 | O60: =N60-O47-O50-O53-O55 -> 1421.6774 | P60: =O60-P47-P50-P53-P55 -> 1421.6774 | Q60: =P60-Q47-Q50-Q53-Q55 -> 1421.6774 | ... ET60: =ES60-ET47-ET50-ET53-ET55 -> 21850.928
A62: x | C62: FEP claims, devex-file method, accrued to COD (E: to the exit, F: to COD)
C63: Cash 12 %: participation fee, TSO security, connection fees
C64: New principal (E: recoverable, to the exit) | D64: EUR k | E64: =SUMIF($J$4:$ET$4,"<="&$E12,$J64:$ET64)+$I47 -> 21412.264 | I64: =SUM(J64:ET64) -> 21420.483 | J64: =-(J47+J50+J53) -> 0 | K64: =-(K47+K50+K53) -> 1241.0959 | L64: =-(L47+L50+L53) -> 0 | M64: =-(M47+M50+M53) -> 0 | N64: =-(N47+N50+N53) -> 0 | O64: =-(O47+O50+O53) -> 0 | P64: =-(P47+P50+P53) -> 0 | Q64: =-(Q47+Q50+Q53) -> 0 | ... ET64: =-(ET47+ET50+ET53) -> 0
C65: Date-weighted new principal | D65: # | J65: =-(J47*$F47+J50*$F50+J51*$F51+J52*$F52) -> 0 | K65: =-(K47*$F47+K50*$F50+K51*$F51+K52*$F52) -> 57568973 | L65: =-(L47*$F47+L50*$F50+L51*$F51+L52*$F52) -> 0 | M65: =-(M47*$F47+M50*$F50+M51*$F51+M52*$F52) -> 0 | N65: =-(N47*$F47+N50*$F50+N51*$F51+N52*$F52) -> 0 | O65: =-(O47*$F47+O50*$F50+O51*$F51+O52*$F52) -> 0 | P65: =-(P47*$F47+P50*$F50+P51*$F51+P52*$F52) -> 0 | Q65: =-(Q47*$F47+Q50*$F50+Q51*$F51+Q52*$F52) -> 0 | ... ET65: =-(ET47*$F47+ET50*$F50+ET51*$F51+ET52*$F52) -> 0
C66: Opening balance | D66: EUR k | J66: =I69 -> 0 | K66: =J69 -> 0 | L66: =K69 -> 1242.0768 | M66: =L69 -> 1242.0768 | N66: =M69 -> 1242.0768 | O66: =N69 -> 1242.0768 | P66: =O69 -> 1391.126 | Q66: =P69 -> 1391.126 | ... ET66: =ES69 -> 28053.765
C67: Return accrued | D67: EUR k | E67: =SUMIF($J$4:$ET$4,"<="&$E12,$J67:$ET67) -> 1564.5366 | F67: =SUMIF($J$4:$ET$4,"<="&In_COD,$J67:$ET67) -> 6633.2814 | I67: =SUM(J67:ET67) -> 6633.2814 | J67: =In_Cash_Rate/Days_In_Year*(1-J19)*(J66*J$5+(J$4+1)*J64-J65)*(J$4<=In_COD) -> 0 | K67: =In_Cash_Rate/Days_In_Year*(1-K19)*(K66*K$5+(K$4+1)*K64-K65)*(K$4<=In_COD) -> 0.98089698 | L67: =In_Cash_Rate/Days_In_Year*(1-L19)*(L66*L$5+(L$4+1)*L64-L65)*(L$4<=In_COD) -> 36.751861 | M67: =In_Cash_Rate/Days_In_Year*(1-M19)*(M66*M$5+(M$4+1)*M64-M65)*(M$4<=In_COD) -> 37.160215 | N67: =In_Cash_Rate/Days_In_Year*(1-N19)*(N66*N$5+(N$4+1)*N64-N65)*(N$4<=In_COD) -> 37.568569 | O67: =In_Cash_Rate/Days_In_Year*(1-O19)*(O66*O$5+(O$4+1)*O64-O65)*(O$4<=In_COD) -> 37.568569 | P67: =In_Cash_Rate/Days_In_Year*(1-P19)*(P66*P$5+(P$4+1)*P64-P65)*(P$4<=In_COD) -> 41.619441 | Q67: =In_Cash_Rate/Days_In_Year*(1-Q19)*(Q66*Q$5+(Q$4+1)*Q64-Q65)*(Q$4<=In_COD) -> 41.619441 | ... ET67: =In_Cash_Rate/Days_In_Year*(1-ET19)*(ET66*ET$5+(ET$4+1)*ET64-ET65)*(ET$4<=In_COD) -> 0
C68: Capitalised at 31-Dec | D68: EUR k | I68: =SUM(J68:ET68) -> 6633.2814 | J68: =J20*SUMIF($J$7:J$7,J$7,$J67:J67) -> 0 | K68: =K20*SUMIF($J$7:K$7,K$7,$J67:K67) -> 0.98089698 | L68: =L20*SUMIF($J$7:L$7,L$7,$J67:L67) -> 0 | M68: =M20*SUMIF($J$7:M$7,M$7,$J67:M67) -> 0 | N68: =N20*SUMIF($J$7:N$7,N$7,$J67:N67) -> 0 | O68: =O20*SUMIF($J$7:O$7,O$7,$J67:O67) -> 149.04921 | P68: =P20*SUMIF($J$7:P$7,P$7,$J67:P67) -> 0 | Q68: =Q20*SUMIF($J$7:Q$7,Q$7,$J67:Q67) -> 0 | ... ET68: =ET20*SUMIF($J$7:ET$7,ET$7,$J67:ET67) -> 0
C69: Closing balance | D69: EUR k | J69: =J66+J64+J68 -> 0 | K69: =K66+K64+K68 -> 1242.0768 | L69: =L66+L64+L68 -> 1242.0768 | M69: =M66+M64+M68 -> 1242.0768 | N69: =N66+N64+N68 -> 1242.0768 | O69: =O66+O64+O68 -> 1391.126 | P69: =P66+P64+P68 -> 1391.126 | Q69: =Q66+Q64+Q68 -> 1391.126 | ... ET69: =ET66+ET64+ET68 -> 28053.765
C70: Guarantee 6 %: bid security and performance security face value
C71: Opening capitalised return | D71: EUR k | J71: =I74 -> 0 | K71: =J74 -> 0 | L71: =K74 -> 15.804151 | M71: =L74 -> 15.804151 | N71: =M74 -> 15.804151 | O71: =N74 -> 15.804151 | P71: =O74 -> 381.84829 | Q71: =P74 -> 381.84829 | ... ET71: =ES74 -> 1734.3247
C72: Return accrued | D72: EUR k | E72: =SUMIF($J$4:$ET$4,"<="&$E12,$J72:$ET72) -> 974.90312 | F72: =SUMIF($J$4:$ET$4,"<="&In_COD,$J72:$ET72) -> 1734.3247 | I72: =SUM(J72:ET72) -> 1734.3247 | J72: =In_Guar_Credit*(1-J19)*(J71+J48+J49)*J$5/Days_In_Year*(J$4<=In_COD) -> 0 | K72: =In_Guar_Credit*(1-K19)*(K71+K48+K49)*K$5/Days_In_Year*(K$4<=In_COD) -> 15.804151 | L72: =In_Guar_Credit*(1-L19)*(L71+L48+L49)*L$5/Days_In_Year*(L$4<=In_COD) -> 90.257459 | M72: =In_Guar_Credit*(1-M19)*(M71+M48+M49)*M$5/Days_In_Year*(M$4<=In_COD) -> 91.26032 | N72: =In_Guar_Credit*(1-N19)*(N71+N48+N49)*N$5/Days_In_Year*(N$4<=In_COD) -> 92.26318 | O72: =In_Guar_Credit*(1-O19)*(O71+O48+O49)*O$5/Days_In_Year*(O$4<=In_COD) -> 92.26318 | P72: =In_Guar_Credit*(1-P19)*(P71+P48+P49)*P$5/Days_In_Year*(P$4<=In_COD) -> 96.735939 | Q72: =In_Guar_Credit*(1-Q19)*(Q71+Q48+Q49)*Q$5/Days_In_Year*(Q$4<=In_COD) -> 96.735939 | ... ET72: =In_Guar_Credit*(1-ET19)*(ET71+ET48+ET49)*ET$5/Days_In_Year*(ET$4<=In_COD) -> 0
C73: Capitalised at 31-Dec | D73: EUR k | I73: =SUM(J73:ET73) -> 1734.3247 | J73: =J20*SUMIF($J$7:J$7,J$7,$J72:J72) -> 0 | K73: =K20*SUMIF($J$7:K$7,K$7,$J72:K72) -> 15.804151 | L73: =L20*SUMIF($J$7:L$7,L$7,$J72:L72) -> 0 | M73: =M20*SUMIF($J$7:M$7,M$7,$J72:M72) -> 0 | N73: =N20*SUMIF($J$7:N$7,N$7,$J72:N72) -> 0 | O73: =O20*SUMIF($J$7:O$7,O$7,$J72:O72) -> 366.04414 | P73: =P20*SUMIF($J$7:P$7,P$7,$J72:P72) -> 0 | Q73: =Q20*SUMIF($J$7:Q$7,Q$7,$J72:Q72) -> 0 | ... ET73: =ET20*SUMIF($J$7:ET$7,ET$7,$J72:ET72) -> 0
C74: Closing capitalised return | D74: EUR k | J74: =J71+J73 -> 0 | K74: =K71+K73 -> 15.804151 | L74: =L71+L73 -> 15.804151 | M74: =M71+M73 -> 15.804151 | N74: =N71+N73 -> 15.804151 | O74: =O71+O73 -> 381.84829 | P74: =P71+P73 -> 381.84829 | Q74: =Q71+Q73 -> 381.84829 | ... ET74: =ET71+ET73 -> 1734.3247
C75: At risk 20 % with 2x floor: devex, land, contingency
C76: Date-weighted new principal | D76: # | J76: =SUMPRODUCT(Devex_Keur*Devex_Date*(Devex_Date>=J$3)*(Devex_Date<=J$4))-J56*$F56 -> 0 | K76: =SUMPRODUCT(Devex_Keur*Devex_Date*(Devex_Date>=K$3)*(Devex_Date<=K$4))-K56*$F56 -> 8264787.3 | L76: =SUMPRODUCT(Devex_Keur*Devex_Date*(Devex_Date>=L$3)*(Devex_Date<=L$4))-L56*$F56 -> 27328011 | M76: =SUMPRODUCT(Devex_Keur*Devex_Date*(Devex_Date>=M$3)*(Devex_Date<=M$4))-M56*$F56 -> 2041249.3 | N76: =SUMPRODUCT(Devex_Keur*Devex_Date*(Devex_Date>=N$3)*(Devex_Date<=N$4))-N56*$F56 -> 2042564.4 | O76: =SUMPRODUCT(Devex_Keur*Devex_Date*(Devex_Date>=O$3)*(Devex_Date<=O$4))-O56*$F56 -> 8617904.1 | P76: =SUMPRODUCT(Devex_Keur*Devex_Date*(Devex_Date>=P$3)*(Devex_Date<=P$4))-P56*$F56 -> 60359660 | Q76: =SUMPRODUCT(Devex_Keur*Devex_Date*(Devex_Date>=Q$3)*(Devex_Date<=Q$4))-Q56*$F56 -> 216330.55 | ... ET76: =SUMPRODUCT(Devex_Keur*Devex_Date*(Devex_Date>=ET$3)*(Devex_Date<=ET$4))-ET56*$F56 -> 0
C77: Opening balance | D77: EUR k | J77: =I80 -> 0 | K77: =J80 -> 0 | L77: =K80 -> 187.51994 | M77: =L80 -> 775.96446 | N77: =M80 -> 819.80008 | O77: =N80 -> 863.63569 | P77: =O80 -> 1195.1838 | Q77: =P80 -> 2485.2256 | ... ET77: =ES80 -> 5690.5611
C78: Return accrued (E, F: with the floor) | D78: EUR k | E78: =MAX(SUMIF($J$4:$ET$4,"<="&$E12,$J78:$ET78),(In_Min_Multiple-1)*$E57) -> 3119.6245 | F78: =MAX(SUMIF($J$4:$ET$4,"<="&In_COD,$J78:$ET78),(In_Min_Multiple-1)*$F57) -> 3119.6245 | I78: =SUM(J78:ET78) -> 2570.9366 | J78: =In_AtRisk_Rate/Days_In_Year*(1-J19)*(J77*J$5-(J$4+1)*J57-J76)*(J$4<=In_COD) -> 0 | K78: =In_AtRisk_Rate/Days_In_Year*(1-K19)*(K77*K$5-(K$4+1)*K57-K76)*(K$4<=In_COD) -> 8.999392 | L78: =In_AtRisk_Rate/Days_In_Year*(1-L19)*(L77*L$5-(L$4+1)*L57-L76)*(L$4<=In_COD) -> 21.145094 | M78: =In_AtRisk_Rate/Days_In_Year*(1-M19)*(M77*M$5-(M$4+1)*M57-M76)*(M$4<=In_COD) -> 38.763985 | N78: =In_AtRisk_Rate/Days_In_Year*(1-N19)*(N77*N$5-(N$4+1)*N57-N76)*(N$4<=In_COD) -> 42.888177 | O78: =In_AtRisk_Rate/Days_In_Year*(1-O19)*(O77*O$5-(O$4+1)*O57-O76)*(O$4<=In_COD) -> 44.389222 | P78: =In_AtRisk_Rate/Days_In_Year*(1-P19)*(P77*P$5-(P$4+1)*P57-P76)*(P$4<=In_COD) -> 98.531352 | Q78: =In_AtRisk_Rate/Days_In_Year*(1-Q19)*(Q77*Q$5-(Q$4+1)*Q57-Q76)*(Q$4<=In_COD) -> 123.93208 | ... ET78: =In_AtRisk_Rate/Days_In_Year*(1-ET19)*(ET77*ET$5-(ET$4+1)*ET57-ET76)*(ET$4<=In_COD) -> 0
C79: Capitalised at 31-Dec | D79: EUR k | I79: =SUM(J79:ET79) -> 2570.9366 | J79: =J20*SUMIF($J$7:J$7,J$7,$J78:J78) -> 0 | K79: =K20*SUMIF($J$7:K$7,K$7,$J78:K78) -> 8.999392 | L79: =L20*SUMIF($J$7:L$7,L$7,$J78:L78) -> 0 | M79: =M20*SUMIF($J$7:M$7,M$7,$J78:M78) -> 0 | N79: =N20*SUMIF($J$7:N$7,N$7,$J78:N78) -> 0 | O79: =O20*SUMIF($J$7:O$7,O$7,$J78:O78) -> 147.18648 | P79: =P20*SUMIF($J$7:P$7,P$7,$J78:P78) -> 0 | Q79: =Q20*SUMIF($J$7:Q$7,Q$7,$J78:Q78) -> 0 | ... ET79: =ET20*SUMIF($J$7:ET$7,ET$7,$J78:ET78) -> 0
C80: Closing balance | D80: EUR k | J80: =J77-J57+J79 -> 0 | K80: =K77-K57+K79 -> 187.51994 | L80: =L77-L57+L79 -> 775.96446 | M80: =M77-M57+M79 -> 819.80008 | N80: =N77-N57+N79 -> 863.63569 | O80: =O77-O57+O79 -> 1195.1838 | P80: =P77-P57+P79 -> 2485.2256 | Q80: =Q77-Q57+Q79 -> 2489.8352 | ... ET80: =ET77-ET57+ET79 -> 5690.5611
A82: x | C82: Overbuild and BESS sanction (E: wind / pro rata, F: BESS / full call)
C83: Build shortfall share | D83: % | E83: =1-$F24/$E24 -> 0.28571429 | F83: =(1-In_BESS_Built)*($E25>0) -> 0
C84: Performance security by technology | D84: EUR k | E84: =$E49*$E24*In_Bench_Wind/$E45 -> 3893.1507 | F84: =$E49-$E84 -> 2191.7808
C85: Sanction amount | D85: EUR k | E85: =($E83>In_Tolerance_Cap)*$E83*$E84+($F83>In_Tolerance_Cap)*$F83*$F84 -> 1112.3288 | F85: =($E83+$F83>0)*$E49 -> 6084.9315
C86: Sanction paid, selected regime (E: date) | D86: EUR k | E86: =EDATE(In_COD,In_Sanction_Lag) -> 48303 | I86: =SUM(J86:ET86) -> -1112.3288 | J86: =-CHOOSE(In_Sanction_Regime,$E85,$F85)*N(AND(J$3<=$E86,J$4>=$E86)) -> 0 | K86: =-CHOOSE(In_Sanction_Regime,$E85,$F85)*N(AND(K$3<=$E86,K$4>=$E86)) -> 0 | L86: =-CHOOSE(In_Sanction_Regime,$E85,$F85)*N(AND(L$3<=$E86,L$4>=$E86)) -> 0 | M86: =-CHOOSE(In_Sanction_Regime,$E85,$F85)*N(AND(M$3<=$E86,M$4>=$E86)) -> 0 | N86: =-CHOOSE(In_Sanction_Regime,$E85,$F85)*N(AND(N$3<=$E86,N$4>=$E86)) -> 0 | O86: =-CHOOSE(In_Sanction_Regime,$E85,$F85)*N(AND(O$3<=$E86,O$4>=$E86)) -> 0 | P86: =-CHOOSE(In_Sanction_Regime,$E85,$F85)*N(AND(P$3<=$E86,P$4>=$E86)) -> 0 | Q86: =-CHOOSE(In_Sanction_Regime,$E85,$F85)*N(AND(Q$3<=$E86,Q$4>=$E86)) -> 0 | ... ET86: =-CHOOSE(In_Sanction_Regime,$E85,$F85)*N(AND(ET$3<=$E86,ET$4>=$E86)) -> 0
C87: Connection capacity lost pro rata | D87: MVA | E87: =($E83>In_Tolerance_Cap)*$E83*In_MVA -> 28.571429
C88: 3-year group exclusion possible (if the PB loss counts as a call) | D88: flag | E88: =N($I86<0) -> 1
A90: x | C90: Build and debt
C91: Turbine supply, live route | D91: EUR k/MW | E91: =IF(In_CN_Turbine=1,In_Turbine_CN,In_Turbine) -> 600
C92: Substation and 132 kV bay, live route | D92: EUR k | E92: =IF(In_CN_Turbine=1,In_Substation_CN,In_Substation) -> 12000
C93: Capex on built MW (E: total) | D93: EUR k | E93: =(($E91+In_Other_Wind)*$F24+$E92)*(1+In_Capex_Contingency)+In_BESS_Capex*$F25 -> 122475 | I93: =SUM(J93:ET93) -> -122475 | J93: =-$E93*J13 -> 0 | K93: =-$E93*K13 -> 0 | L93: =-$E93*L13 -> 0 | M93: =-$E93*M13 -> 0 | N93: =-$E93*N13 -> 0 | O93: =-$E93*O13 -> 0 | P93: =-$E93*P13 -> 0 | Q93: =-$E93*Q13 -> 0 | ... ET93: =-$E93*ET13 -> 0
C94: Municipal one-off at COD | D94: EUR k | E94: =$E30*In_MVA -> 5000 | I94: =SUM(J94:ET94) -> -5000 | J94: =-$E94*J14 -> 0 | K94: =-$E94*K14 -> 0 | L94: =-$E94*L14 -> 0 | M94: =-$E94*M14 -> 0 | N94: =-$E94*N14 -> 0 | O94: =-$E94*O14 -> 0 | P94: =-$E94*P14 -> 0 | Q94: =-$E94*Q14 -> 0 | ... ET94: =-$E94*ET14 -> 0
C95: Senior debt
C96: Opening balance | D96: EUR k | J96: =I100 -> 0 | K96: =J100 -> 0 | L96: =K100 -> 0 | M96: =L100 -> 0 | N96: =M100 -> 0 | O96: =N100 -> 0 | P96: =O100 -> 0 | Q96: =P100 -> 0 | ... ET96: =ES100 -> 0
C97: Drawdown (E: debt size) | D97: EUR k | E97: =-IF(In_CN_Turbine=1,In_Gearing_CN,In_Gearing)*($I93+$I53+$I94) -> 88592.632 | I97: =SUM(J97:ET97) -> 88592.632 | J97: =$E97*J13 -> 0 | K97: =$E97*K13 -> 0 | L97: =$E97*L13 -> 0 | M97: =$E97*M13 -> 0 | N97: =$E97*N13 -> 0 | O97: =$E97*O13 -> 0 | P97: =$E97*P13 -> 0 | Q97: =$E97*Q13 -> 0 | ... ET97: =$E97*ET13 -> 0
C98: Interest capitalised (F: rate per period) | D98: EUR k | F98: =In_Debt_Rate*Months_Per_Period/Months_In_Year -> 0.0125 | I98: =SUM(J98:ET98) -> 3972.8387 | J98: =J96*$F98*(J$4<=In_COD) -> 0 | K98: =K96*$F98*(K$4<=In_COD) -> 0 | L98: =L96*$F98*(L$4<=In_COD) -> 0 | M98: =M96*$F98*(M$4<=In_COD) -> 0 | N98: =N96*$F98*(N$4<=In_COD) -> 0 | O98: =O96*$F98*(O$4<=In_COD) -> 0 | P98: =P96*$F98*(P$4<=In_COD) -> 0 | Q98: =Q96*$F98*(Q$4<=In_COD) -> 0 | ... ET98: =ET96*$F98*(ET$4<=In_COD) -> 0
C99: Repayment (level annuity) | D99: EUR k | I99: =SUM(J99:ET99) -> -92565.471 | J99: =PPMT($F98,1,In_Debt_Tenor*Months_In_Year/Months_Per_Period-SUM($J17:J17)+1,J96)*J17 -> 0 | K99: =PPMT($F98,1,In_Debt_Tenor*Months_In_Year/Months_Per_Period-SUM($J17:K17)+1,K96)*K17 -> 0 | L99: =PPMT($F98,1,In_Debt_Tenor*Months_In_Year/Months_Per_Period-SUM($J17:L17)+1,L96)*L17 -> 0 | M99: =PPMT($F98,1,In_Debt_Tenor*Months_In_Year/Months_Per_Period-SUM($J17:M17)+1,M96)*M17 -> 0 | N99: =PPMT($F98,1,In_Debt_Tenor*Months_In_Year/Months_Per_Period-SUM($J17:N17)+1,N96)*N17 -> 0 | O99: =PPMT($F98,1,In_Debt_Tenor*Months_In_Year/Months_Per_Period-SUM($J17:O17)+1,O96)*O17 -> 0 | P99: =PPMT($F98,1,In_Debt_Tenor*Months_In_Year/Months_Per_Period-SUM($J17:P17)+1,P96)*P17 -> 0 | Q99: =PPMT($F98,1,In_Debt_Tenor*Months_In_Year/Months_Per_Period-SUM($J17:Q17)+1,Q96)*Q17 -> 0 | ... ET99: =PPMT($F98,1,In_Debt_Tenor*Months_In_Year/Months_Per_Period-SUM($J17:ET17)+1,ET96)*ET17 -> 0
C100: Closing balance | D100: EUR k | J100: =SUM(J96:J99) -> 0 | K100: =SUM(K96:K99) -> 0 | L100: =SUM(L96:L99) -> 0 | M100: =SUM(M96:M99) -> 0 | N100: =SUM(N96:N99) -> 0 | O100: =SUM(O96:O99) -> 0 | P100: =SUM(P96:P99) -> 0 | Q100: =SUM(Q96:Q99) -> 0 | ... ET100: =SUM(ET96:ET99) -> 0
C101: Interest paid | D101: EUR k | I101: =SUM(J101:ET101) -> -25627.358 | J101: =-J96*$F98*(J$4>In_COD) -> 0 | K101: =-K96*$F98*(K$4>In_COD) -> 0 | L101: =-L96*$F98*(L$4>In_COD) -> 0 | M101: =-M96*$F98*(M$4>In_COD) -> 0 | N101: =-N96*$F98*(N$4>In_COD) -> 0 | O101: =-O96*$F98*(O$4>In_COD) -> 0 | P101: =-P96*$F98*(P$4>In_COD) -> 0 | Q101: =-Q96*$F98*(Q$4>In_COD) -> 0 | ... ET101: =-ET96*$F98*(ET$4>In_COD) -> 0
C102: Upfront fee | D102: EUR k | I102: =SUM(J102:ET102) -> -1550.3711 | J102: =-In_Upfront_Fee*$E97*(J96=0)*(J97>0) -> 0 | K102: =-In_Upfront_Fee*$E97*(K96=0)*(K97>0) -> 0 | L102: =-In_Upfront_Fee*$E97*(L96=0)*(L97>0) -> 0 | M102: =-In_Upfront_Fee*$E97*(M96=0)*(M97>0) -> 0 | N102: =-In_Upfront_Fee*$E97*(N96=0)*(N97>0) -> 0 | O102: =-In_Upfront_Fee*$E97*(O96=0)*(O97>0) -> 0 | P102: =-In_Upfront_Fee*$E97*(P96=0)*(P97>0) -> 0 | Q102: =-In_Upfront_Fee*$E97*(Q96=0)*(Q97>0) -> 0 | ... ET102: =-In_Upfront_Fee*$E97*(ET96=0)*(ET97>0) -> 0
C103: Commitment fee | D103: EUR k | I103: =SUM(J103:ET103) -> -897.00863 | J103: =-In_Commitment_Fee*($E97-SUM($J97:J97)+J97)*J$6*(J13>0) -> 0 | K103: =-In_Commitment_Fee*($E97-SUM($J97:K97)+K97)*K$6*(K13>0) -> 0 | L103: =-In_Commitment_Fee*($E97-SUM($J97:L97)+L97)*L$6*(L13>0) -> 0 | M103: =-In_Commitment_Fee*($E97-SUM($J97:M97)+M97)*M$6*(M13>0) -> 0 | N103: =-In_Commitment_Fee*($E97-SUM($J97:N97)+N97)*N$6*(N13>0) -> 0 | O103: =-In_Commitment_Fee*($E97-SUM($J97:O97)+O97)*O$6*(O13>0) -> 0 | P103: =-In_Commitment_Fee*($E97-SUM($J97:P97)+P97)*P$6*(P13>0) -> 0 | Q103: =-In_Commitment_Fee*($E97-SUM($J97:Q97)+Q97)*Q$6*(Q13>0) -> 0 | ... ET103: =-In_Commitment_Fee*($E97-SUM($J97:ET97)+ET97)*ET$6*(ET13>0) -> 0
C104: Build cost (capex, connection, municipal, debt fees) | D104: EUR k | I104: =SUM(J104:ET104) -> -150101.77 | J104: =J93+J53+J94+J102+J103 -> 0 | K104: =K93+K53+K94+K102+K103 -> 0 | L104: =L93+L53+L94+L102+L103 -> 0 | M104: =M93+M53+M94+M102+M103 -> 0 | N104: =N93+N53+N94+N102+N103 -> 0 | O104: =O93+O53+O94+O102+O103 -> 0 | P104: =P93+P53+P94+P102+P103 -> 0 | Q104: =Q93+Q53+Q94+Q102+Q103 -> 0 | ... ET104: =ET93+ET53+ET94+ET102+ET103 -> 0
A106: x | C106: Operations
C107: Operating year | D107: # | J107: =ROUNDUP(YEARFRAC(In_COD,J$4),0)*(J$4>In_COD) -> 0 | K107: =ROUNDUP(YEARFRAC(In_COD,K$4),0)*(K$4>In_COD) -> 0 | L107: =ROUNDUP(YEARFRAC(In_COD,L$4),0)*(L$4>In_COD) -> 0 | M107: =ROUNDUP(YEARFRAC(In_COD,M$4),0)*(M$4>In_COD) -> 0 | N107: =ROUNDUP(YEARFRAC(In_COD,N$4),0)*(N$4>In_COD) -> 0 | O107: =ROUNDUP(YEARFRAC(In_COD,O$4),0)*(O$4>In_COD) -> 0 | P107: =ROUNDUP(YEARFRAC(In_COD,P$4),0)*(P$4>In_COD) -> 0 | Q107: =ROUNDUP(YEARFRAC(In_COD,Q$4),0)*(Q$4>In_COD) -> 0 | ... ET107: =ROUNDUP(YEARFRAC(In_COD,ET$4),0)*(ET$4>In_COD) -> 30
C108: Opex escalation index | D108: factor | J108: =(1+In_Opex_Esc)^(J$7-YEAR(In_COD)) -> 0.88385429 | K108: =(1+In_Opex_Esc)^(K$7-YEAR(In_COD)) -> 0.88385429 | L108: =(1+In_Opex_Esc)^(L$7-YEAR(In_COD)) -> 0.90595064 | M108: =(1+In_Opex_Esc)^(M$7-YEAR(In_COD)) -> 0.90595064 | N108: =(1+In_Opex_Esc)^(N$7-YEAR(In_COD)) -> 0.90595064 | O108: =(1+In_Opex_Esc)^(O$7-YEAR(In_COD)) -> 0.90595064 | P108: =(1+In_Opex_Esc)^(P$7-YEAR(In_COD)) -> 0.92859941 | Q108: =(1+In_Opex_Esc)^(Q$7-YEAR(In_COD)) -> 0.92859941 | ... ET108: =(1+In_Opex_Esc)^(ET$7-YEAR(In_COD)) -> 2.0975676
C109: PPA price | D109: EUR/MWh | J109: =In_PPA_Price*(1+In_PPA_Esc)^(J$7-YEAR(In_COD)) -> 85.631912 | K109: =In_PPA_Price*(1+In_PPA_Esc)^(K$7-YEAR(In_COD)) -> 85.631912 | L109: =In_PPA_Price*(1+In_PPA_Esc)^(L$7-YEAR(In_COD)) -> 86.488231 | M109: =In_PPA_Price*(1+In_PPA_Esc)^(M$7-YEAR(In_COD)) -> 86.488231 | N109: =In_PPA_Price*(1+In_PPA_Esc)^(N$7-YEAR(In_COD)) -> 86.488231 | O109: =In_PPA_Price*(1+In_PPA_Esc)^(O$7-YEAR(In_COD)) -> 86.488231 | P109: =In_PPA_Price*(1+In_PPA_Esc)^(P$7-YEAR(In_COD)) -> 87.353113 | Q109: =In_PPA_Price*(1+In_PPA_Esc)^(Q$7-YEAR(In_COD)) -> 87.353113 | ... ET109: =In_PPA_Price*(1+In_PPA_Esc)^(ET$7-YEAR(In_COD)) -> 121.3064
...

Sheet Checks
B2: =Dashboard!$C$3&" – Checks" -> Project Bora – Checks
C4: Period end | J4: =Calc_1!J$4 -> 46295 | K4: =Calc_1!K$4 -> 46387 | L4: =Calc_1!L$4 -> 46477 | M4: =Calc_1!M$4 -> 46568 | N4: =Calc_1!N$4 -> 46660 | O4: =Calc_1!O$4 -> 46752 | P4: =Calc_1!P$4 -> 46843 | Q4: =Calc_1!Q$4 -> 46934 | ... ET4: =Calc_1!ET$4 -> 59079
E9: Status | F9: Fails
A11: x | C11: Checks (0 = OK)
C12: Levers within the tender rules – Calc_1 | D12: flag | E12: =IF(F12=0,"OK","CHECK") -> OK | F12: =N(Calc_1!$E42+Calc_1!$F42>0) -> 0
C13: Levers within the tender rules – Calc_2 | D13: flag | E13: =IF(F13=0,"OK","CHECK") -> OK | F13: =N(Calc_2!$E42+Calc_2!$F42>0) -> 0
C14: Exit and COD fall on a quarter end – Calc_1 | D14: flag | E14: =IF(F14=0,"OK","CHECK") -> OK | F14: =N(COUNTIF(Calc_1!$J$4:$ET$4,Calc_1!$E12)=0)+N(COUNTIF(Calc_1!$J$4:$ET$4,In_COD)=0) -> 0
C15: Exit and COD fall on a quarter end – Calc_2 | D15: flag | E15: =IF(F15=0,"OK","CHECK") -> OK | F15: =N(COUNTIF(Calc_2!$J$4:$ET$4,Calc_2!$E12)=0)+N(COUNTIF(Calc_2!$J$4:$ET$4,In_COD)=0) -> 0
C16: Cash posted to the exit = buyer reimbursement + participation fee – Calc_1 | D16: flag | E16: =IF(F16=0,"OK","CHECK") -> OK | F16: =N(ABS(Calc_1!$E60-Calc_1!$E132-Calc_1!$E47)>Tolerance) -> 0
C17: Cash posted to the exit = buyer reimbursement + participation fee – Calc_2 | D17: flag | E17: =IF(F17=0,"OK","CHECK") -> OK | F17: =N(ABS(Calc_2!$E60-Calc_2!$E132-Calc_2!$E47)>Tolerance) -> 0
C18: RtB waterfall: paid + distributable = cash available – Calc_1 | D18: flag | E18: =IF(F18=0,"OK","CHECK") -> OK | F18: =N(ABS(Calc_1!$F141+Calc_1!$F142+Calc_1!$F133-Calc_1!$F132)>Tolerance) -> 0
C19: RtB waterfall: paid + distributable = cash available – Calc_2 | D19: flag | E19: =IF(F19=0,"OK","CHECK") -> OK | F19: =N(ABS(Calc_2!$F141+Calc_2!$F142+Calc_2!$F133-Calc_2!$F132)>Tolerance) -> 0
C20: FEP RtB build-up adds up to the profit – Calc_1 | D20: flag | E20: =IF(F20=0,"OK","CHECK") -> OK | F20: =N(ABS(Calc_1!$F141+Calc_1!$E147+Calc_1!$E58+Calc_1!$E150-Calc_1!$I151)>Tolerance) -> 0
C21: FEP RtB build-up adds up to the profit – Calc_2 | D21: flag | E21: =IF(F21=0,"OK","CHECK") -> OK | F21: =N(ABS(Calc_2!$F141+Calc_2!$E147+Calc_2!$E58+Calc_2!$E150-Calc_2!$I151)>Tolerance) -> 0
C22: RtB waterfall: no step paid above its amount due – Calc_1 | D22: flag | E22: =IF(F22=0,"OK","CHECK") -> OK | F22: =N(SUMPRODUCT(--(Calc_1!$F133:$F139>Calc_1!$E133:$E139+Tolerance))>0) -> 0
C23: RtB waterfall: no step paid above its amount due – Calc_2 | D23: flag | E23: =IF(F23=0,"OK","CHECK") -> OK | F23: =N(SUMPRODUCT(--(Calc_2!$F133:$F139>Calc_2!$E133:$E139+Tolerance))>0) -> 0
C24: COD waterfall: distributable not negative, paid within cash available – Calc_1 | D24: flag | E24: =IF(F24=0,"OK","CHECK") -> OK | F24: =N(Calc_1!$F166<-Tolerance)+N(SUM(Calc_1!$F162:$F165)>Calc_1!$F161+Tolerance) -> 0
C25: COD waterfall: distributable not negative, paid within cash available – Calc_2 | D25: flag | E25: =IF(F25=0,"OK","CHECK") -> OK | F25: =N(Calc_2!$F166<-Tolerance)+N(SUM(Calc_2!$F162:$F165)>Calc_2!$F161+Tolerance) -> 0
C26: Sources = uses to COD (equity + debt vs all-in cost lines) – Calc_1 | D26: flag | E26: =IF(F26=0,"OK","CHECK") -> OK | F26: =N(ABS(Calc_1!$E179-Calc_1!$F179)>Tolerance) -> 0
C27: Sources = uses to COD (equity + debt vs all-in cost lines) – Calc_2 | D27: flag | E27: =IF(F27=0,"OK","CHECK") -> OK | F27: =N(ABS(Calc_2!$E179-Calc_2!$F179)>Tolerance) -> 0
C28: Debt repaid by the end of the tenor – Calc_1 | D28: flag | E28: =IF(F28=0,"OK","CHECK") -> OK | F28: =SUM(J28:ET28) -> 0 | J28: =N((Calc_1!J$4>=Calc_1!$F17)*ABS(Calc_1!J100)>Tolerance) -> 0 | K28: =N((Calc_1!K$4>=Calc_1!$F17)*ABS(Calc_1!K100)>Tolerance) -> 0 | L28: =N((Calc_1!L$4>=Calc_1!$F17)*ABS(Calc_1!L100)>Tolerance) -> 0 | M28: =N((Calc_1!M$4>=Calc_1!$F17)*ABS(Calc_1!M100)>Tolerance) -> 0 | N28: =N((Calc_1!N$4>=Calc_1!$F17)*ABS(Calc_1!N100)>Tolerance) -> 0 | O28: =N((Calc_1!O$4>=Calc_1!$F17)*ABS(Calc_1!O100)>Tolerance) -> 0 | P28: =N((Calc_1!P$4>=Calc_1!$F17)*ABS(Calc_1!P100)>Tolerance) -> 0 | Q28: =N((Calc_1!Q$4>=Calc_1!$F17)*ABS(Calc_1!Q100)>Tolerance) -> 0 | ... ET28: =N((Calc_1!ET$4>=Calc_1!$F17)*ABS(Calc_1!ET100)>Tolerance) -> 0
C29: Debt repaid by the end of the tenor – Calc_2 | D29: flag | E29: =IF(F29=0,"OK","CHECK") -> OK | F29: =SUM(J29:ET29) -> 0 | J29: =N((Calc_2!J$4>=Calc_2!$F17)*ABS(Calc_2!J100)>Tolerance) -> 0 | K29: =N((Calc_2!K$4>=Calc_2!$F17)*ABS(Calc_2!K100)>Tolerance) -> 0 | L29: =N((Calc_2!L$4>=Calc_2!$F17)*ABS(Calc_2!L100)>Tolerance) -> 0 | M29: =N((Calc_2!M$4>=Calc_2!$F17)*ABS(Calc_2!M100)>Tolerance) -> 0 | N29: =N((Calc_2!N$4>=Calc_2!$F17)*ABS(Calc_2!N100)>Tolerance) -> 0 | O29: =N((Calc_2!O$4>=Calc_2!$F17)*ABS(Calc_2!O100)>Tolerance) -> 0 | P29: =N((Calc_2!P$4>=Calc_2!$F17)*ABS(Calc_2!P100)>Tolerance) -> 0 | Q29: =N((Calc_2!Q$4>=Calc_2!$F17)*ABS(Calc_2!Q100)>Tolerance) -> 0 | ... ET29: =N((Calc_2!ET$4>=Calc_2!$F17)*ABS(Calc_2!ET100)>Tolerance) -> 0
C30: XIRR returned a number on every route – Calc_1 | D30: flag | E30: =IF(F30=0,"OK","CHECK") -> OK | F30: =N(ISTEXT(Calc_1!$E152))+N(ISERROR(Calc_1!$E184))+N(ISERROR(Calc_1!$E169)) -> 0
C31: XIRR returned a number on every route – Calc_2 | D31: flag | E31: =IF(F31=0,"OK","CHECK") -> OK | F31: =N(ISTEXT(Calc_2!$E152))+N(ISERROR(Calc_2!$E184))+N(ISERROR(Calc_2!$E169)) -> 0
C32: Stored zero bid + Δ = live, base set – bid 1 | D32: flag | E32: =IF(F32=0,"OK","CHECK") -> OK | F32: =(Scenario_Selected=1)*(SUMPRODUCT(ABS(ZB_Live_1-ZB_Zero_Stored-ZB_Delta_1_Stored))>Tolerance) -> 0
C33: Stored zero bid + Δ = live, base set – bid 2 | D33: flag | E33: =IF(F33=0,"OK","CHECK") -> OK | F33: =(Scenario_Selected=1)*(SUMPRODUCT(ABS(ZB_Live_2-ZB_Zero_Stored-ZB_Delta_2_Stored))>Tolerance) -> 0
C34: Stored results = live case | D34: flag | E34: =IF(F34=0,"OK","CHECK") -> OK | F34: =--(SUMPRODUCT(ABS(Stored_Results-Live_Results)*(Scenario_Names=Scenario_Name))>Tolerance) -> 0
C36: Master check | E36: =IF(F36=0,"OK","CHECK") -> OK | F36: =SUMPRODUCT(ABS(F12:F34)) -> 0
C38: ***END***
