Workbook

Sheet Cover
B2: Project ARES – BORA onshore wind (Hungary)
B3: Bora IC model v4 – FEP returns: RtB sale, sale at COD, hold to maturity; RtB tender strategies S0–S4 (11-Oct-2026)
B5: Sheet | C5: Purpose | D5: Status
B6: Control Panel | C6: Route and tender-strategy selectors, the five tender strategies S0–S4 with their points, the offerable ranges and point bands (section g), every business input (one source) and the scenario comparison of all routes (Excel data table). | D6: Live – edit here
B7: Dashboard | C7: Results only: headline returns side by side (sell at RTB vs HTM build & operate), Case A/B bridges, FEP-file tie-out, sensitivities, turbine-case comparison (section 11, live). | D7: Live
B8: Inputs | C8: Every static input, per case (10 case columns), fed from the Control Panel; sections per topic. Yellow = estimates. | D8: Live – edit here (yellow = estimates)
B9: Curves | C9: EURIBOR forward curves and the open Aurora Hungary wind capture-price block (amber – paste in, then set Inputs E166 = 1). | D9: EURIBOR live; Aurora awaiting paste
B10: Deposits | C10: Schedule of MEKH tender securities and grid-connection fee: gross, netting, payable, grid month, k€, cash vs guarantee, recovery %, reconciliation to the 280 MW source table. | D10: Live
B11: MOIC | C11: Sell-at-RTB monthly grid (months 0-60), 14 numbered blocks. No inputs. | D11: Live
B12: HTM | C12: Annual hold-to-maturity engine 2026–2061 (30-year life from COD), 15 blocks: development phase (from MOIC/Deposits), capex, generation, revenue, opex, debt, tax, cash flows, results incl. NPV/Equity, sensitivities, buyer returns (block 14) and gearing sensitivity (block 15). | D12: Live – on estimates
B13: Open_Items | C13: Every open assumption, its interim treatment and owner. | D13: Working sheet – hidden for IC (right-click a tab → Unhide)
B14: Change_Log | C14: Full audit trail of every build phase, defect and fix. | D14: Working sheet – hidden for IC (right-click a tab → Unhide)
B15: Tender | C15: Tender strategies S0–S4 for Bora (set on the Control Panel) – GYIK rules; offerable ranges and band points (Control Panel section g); promise price effect on the RtB and COD exit vs the current bid; group caps and community purchase right (sections 8–9); live 5 × 5 returns matrix. | D15: Live – scenarios set on the Control Panel
B18: Conventions
B19: Blue text on cream fill = hard-coded input; black = formula; green = link from another sheet.
B20: Yellow fill = key assumption to confirm with the deal team; amber fill = awaiting data.
B21: Units are stated in column D of every sheet. EUR k unless stated; mHUF = HUF million; FX at Inputs E11.
B22: Sign convention on MOIC cash-flow blocks: positive = inflow to the party, negative = outflow.
B23: Month 0 = investment date (Inputs E23). Column G on MOIC holds row totals or scalar results.
B24: The IC paper of 27-Jul-26 was used for context only; no IC-deck number was typed into the model.
B26: Headline – active case
B27: Case | C27: =Inputs!E7 -> FEP base case
B28: FEP net profit (post-tax), k€ | C28: =MOIC!G182 -> 15173.724
B29: MOIC | C29: =MOIC!G186 -> 1.3121055
B30: IRR (post-tax) | C30: =MOIC!G187 -> 0.20894449
B31: Integrity checks | C31: =MOIC!G270 -> ALL OK
B32: HTM – project IRR (unlevered, post-tax) | C32: =HTM!G135 -> 0.108862
B33: HTM – equity IRR (levered, post-tax) | C33: =HTM!G139 -> 0.11965554
B34: HTM – FEP net cash over life, k€ | C34: =HTM!G144 -> 1303176.7
B35: HTM – LCOE, EUR/MWh | C35: =HTM!G156 -> 102.14704
B36: HTM integrity checks | C36: =HTM!G172 -> ALL OK
B37: FEP NPV / Equity – sell at RTB (HTM: see Dashboard) | C37: =MOIC!G194 -> 0.17787568
B38: Update note
B39: 06-Sep-26: final MEKH tender terms (30-Aug-26) reflected – see Inputs section Q, Open_Items 31–35 (item 31: no 400 kV node offered) and Change_Log entries 57–60 (rows 61–64). Figures from press coverage of the kiírás; verify against the MEKH document before the IC.
B40: 25-Sep-26: review comments reflected – 30-year life, COD-year operating fraction fix, land lease from NTP, devex in tax losses, debt 1.75% fee / 10-yr tenor, NPV/Equity, buyer IRR, gearing sensitivity; v3 archive tabs deleted. See Change_Log #63–#72.
B41: 02-Oct-26: open items #1–#15, #54–#55 closed; control panel moved to its own sheet; FEP exit-waterfall interest aligned to BORA Devex 01-Oct-26 (frozen 30/06/2029); single 8% discount rate; commitment fee and bid-offer inputs added; land lease 3 k€/MW/yr.
B42: IC version: working sheets Open_Items, Change_Log, Devex_FEP, BORA_Devex and Run_Map are hidden (not deleted) – unhide via right-click on any tab. No macro in this file.
B43: 08-Oct-26: 90 €/MWh PPA (10 yrs) applied to all turbine and sale-at-COD cases incl. Chinese; Tender sheet added (MEKH tender score, tender scenarios, promise price effect, returns matrix); sale at COD (cases 7 / 8). Chinese cases: no EU transformer points, substation capex −10%. HTM = hold to maturity.
B44: 10-Oct-26: Bora IC model v2 – one Control Panel (route / tender-scenario selectors, tender scenarios 0 / A / B / C with their points, every business input, scenario comparison of all routes via an Excel data table, buyer IRR at our COD price); no macro.
B45: 11-Oct-26 (v4): strategy S0 zero bid added (every commitment at its minimum, 0 points, valid – GYIK 17); price-effect reference stays S1 (current bid), so S0 shows a positive price effect; offerable ranges and band points on the Control Panel (section g); ÖSZ-9a points only with the EU-turbine commitment.

Sheet Control Panel
C2: Bora – Control Panel (IC model v4: RtB tender strategies S0–S4; RtB sale, sale at COD, hold to maturity)
C3: Blue cells on cream are the inputs – the model's input cells link here (one source). Everything else is a formula; Excel recalculates the whole workbook, including the scenario comparison (Excel data table, section f). No macro.
C4: If recalculation feels slow: File › Options › Formulas › 'Automatic except for data tables'; F9 then refreshes sections d and e. Other model inputs (rates, deposits, curves): blue cells on the Inputs and Tender sheets.
C6: a. Selection
C7: Item | D7: Unit | E7: Selection | F7: Code | G7: Name | O7: Model cell
C8: Active route | D8: route | E8: RtB sale (case 1) | F8: =INDEX($D$14:$D$18,MATCH($E$8,$C$14:$C$18,0)) -> 1 | O8: → Inputs E6 (model case) – while the data-table driver E10 = 0
C9: Active tender strategy (S0 zero bid … S4 maximum score) | D9: scenario | E9: S1 | F9: =MATCH($E$9&"",{"S1","S2","S3","S4","S0"},0)-1 -> 0 | G9: =INDEX(Tender!$E$11:$I$11,1,$F$9+1) -> S1 – Current bid | O9: → Tender E5 (0 … 4, F9) – while E10 = 0
C10: Data-table driver – leave 0 (input cell of the data table, section f) | D10: # | E10: 0 | O10: → Inputs E6 and Tender E5 take the run's case / scenario while Excel fills the table
C11: Model in use: case (Inputs E6) / tender scenario (Tender E5) | D11: check | E11: =Inputs!$E$6 -> 1 | F11: =Tender!$E$5 -> 0 | G11: =IF(AND(Inputs!$E$6=$F$8,Tender!$E$5=$F$9,$E$10=0),"OK","FAIL – set E10 back to 0") -> OK
C13: Route (list for E8) | D13: Case | E13: Exit | G13: Turbine | O13: Note
C14: RtB sale (case 1) | D14: 1 | E14: Sale of the project rights at RtB | G14: Scenario's turbine (row 22) | O14: RtB: no construction; buyer pays the RtB premium (± price effect of the promises)
C15: Sale at COD – European turbine (case 7) | D15: 7 | E15: Sale of 100 % of the SPV at COD | G15: European | O15: Cases 7 / 8: build, sell 100 % of the SPV at COD (price per installed MW)
C16: Sale at COD – Chinese turbine (case 8) | D16: 8 | E16: Sale of 100 % of the SPV at COD | G16: Chinese
C17: Hold to maturity – European turbine (case 2) | D17: 2 | E17: Build, operate, hold | G17: European | O17: Cases 2 / 3: build and operate for the full life (FEP JV share)
C18: Hold to maturity – Chinese turbine (case 3) | D18: 3 | E18: Build, operate, hold | G18: Chinese
C20: b. Tender strategies S0–S4 (ÖSZ commitments) – edit columns E:I; price-effect reference = S1 current bid
C21: Commitment | D21: Unit | E21: S0 – zero bid | F21: S1 – current bid | G21: S2 – free points | H21: S3 – ≈70 points | I21: S4 – max. score | J21: Active (Tender J) | O21: Tender row (columns E:I link here) / rule | P21: Link check
C22: Scenario name | D22: text | E22: S0 – Zero bid | F22: S1 – Current bid | G22: S2 – Free points | H22: S3 – Cost-efficient (≈70 points) | I22: S4 – Maximum score | J22: =Tender!$J$11 -> S1 – Current bid | O22: Tender E11:I11 | P22: =IF(AND((Tender!$E$11&"")=($F$22&""),(Tender!$F$11&"")=($G$22&""),(Tender!$G$11&"")=($H$22&""),(Tender!$H$11&"")=($I$22&""),(Tender!$I$11&"")=($E$22&"")),"OK","FAIL") -> OK
C23: ÖSZ-1 one-off municipal contribution | D23: k€/MW | E23: 0 | F23: 20 | G23: 20 | H23: 50 | I23: 50 | J23: =Tender!$J$12 -> 20 | O23: Tender E12:I12 | P23: =IF(AND(ABS(N(Tender!$E$12)-N($F$23))<=Tender!$E$32,ABS(N(Tender!$F$12)-N($G$23))<=Tender!$E$32,ABS(N(Tender!$G$12)-N($H$23))<=Tender!$E$32,ABS(N(Tender!$H$12)-N($I$23))<=Tender!$E$32,ABS(N(Tender!$I$12)-N($E$23))<=Tender!$E$32),"OK","FAIL") -> OK
C24: ÖSZ-2 annual community contribution on energy fed in | D24: €/MWh | E24: 0 | F24: 2 | G24: 2 | H24: 2 | I24: 3 | J24: =Tender!$J$13 -> 2 | O24: Tender E13:I13 | P24: =IF(AND(ABS(N(Tender!$E$13)-N($F$24))<=Tender!$E$32,ABS(N(Tender!$F$13)-N($G$24))<=Tender!$E$32,ABS(N(Tender!$G$13)-N($H$24))<=Tender!$E$32,ABS(N(Tender!$H$13)-N($I$24))<=Tender!$E$32,ABS(N(Tender!$I$13)-N($E$24))<=Tender!$E$32),"OK","FAIL") -> OK
C25: ÖSZ-3 overbuild – installed wind above the net connection capacity | D25: % | E25: 0 | F25: 0.305 | G25: 0.4 | H25: 0.4 | I25: 0.54 | J25: =Tender!$J$14 -> 0.305 | O25: Tender E14:I14 | P25: =IF(AND(ABS(N(Tender!$E$14)-N($F$25))<=Tender!$E$32,ABS(N(Tender!$F$14)-N($G$25))<=Tender!$E$32,ABS(N(Tender!$G$14)-N($H$25))<=Tender!$E$32,ABS(N(Tender!$H$14)-N($I$25))<=Tender!$E$32,ABS(N(Tender!$I$14)-N($E$25))<=Tender!$E$32),"OK","FAIL") -> OK
C26: ÖSZ-4 BESS power as % of the ratio basis (row below) | D26: % | E26: 0 | F26: 0.34482759 | G26: 0.45 | H26: 0.45 | I26: 0.51 | J26: =Tender!$J$15 -> 0.34482759 | O26: Tender E15:I15 | P26: =IF(AND(ABS(N(Tender!$E$15)-N($F$26))<=Tender!$E$32,ABS(N(Tender!$F$15)-N($G$26))<=Tender!$E$32,ABS(N(Tender!$G$15)-N($H$26))<=Tender!$E$32,ABS(N(Tender!$H$15)-N($I$26))<=Tender!$E$32,ABS(N(Tender!$I$15)-N($E$26))<=Tender!$E$32),"OK","FAIL") -> OK
C27: ÖSZ-4 BESS ratio basis (1 = installed wind, GYIK 20; 0 = net MVA) | D27: 1 / 0 | E27: 1 | F27: 1 | G27: 0 | H27: 0 | I27: 1 | J27: =Tender!$J$25 -> 1 | O27: Tender E25:I25 | P27: =IF(AND(ABS(N(Tender!$E$25)-N($F$27))<=Tender!$E$32,ABS(N(Tender!$F$25)-N($G$27))<=Tender!$E$32,ABS(N(Tender!$G$25)-N($H$27))<=Tender!$E$32,ABS(N(Tender!$H$25)-N($I$27))<=Tender!$E$32,ABS(N(Tender!$I$25)-N($E$27))<=Tender!$E$32),"OK","FAIL") -> OK
C28: ÖSZ-4 BESS duration | D28: h | E28: 4 | F28: 4 | G28: 4 | H28: 4 | I28: 4 | J28: =Tender!$J$16 -> 4 | O28: Tender E16:I16 | P28: =IF(AND(ABS(N(Tender!$E$16)-N($F$28))<=Tender!$E$32,ABS(N(Tender!$F$16)-N($G$28))<=Tender!$E$32,ABS(N(Tender!$G$16)-N($H$28))<=Tender!$E$32,ABS(N(Tender!$H$16)-N($I$28))<=Tender!$E$32,ABS(N(Tender!$I$16)-N($E$28))<=Tender!$E$32),"OK","FAIL") -> OK
C29: ÖSZ-6 performance security (% of the tender minimum) | D29: % | E29: 1 | F29: 1.5 | G29: 1.6 | H29: 2 | I29: 2.1 | J29: =Tender!$J$17 -> 1.5 | O29: Tender E17:I17 | P29: =IF(AND(ABS(N(Tender!$E$17)-N($F$29))<=Tender!$E$32,ABS(N(Tender!$F$17)-N($G$29))<=Tender!$E$32,ABS(N(Tender!$G$17)-N($H$29))<=Tender!$E$32,ABS(N(Tender!$H$17)-N($I$29))<=Tender!$E$32,ABS(N(Tender!$I$17)-N($E$29))<=Tender!$E$32),"OK","FAIL") -> OK
C30: ÖSZ-5 accept partial award (1 = yes) | D30: 1 / 0 | E30: 0 | F30: 0 | G30: 1 | H30: 1 | I30: 1 | J30: =Tender!$J$18 -> 0 | O30: Tender E18:I18 | P30: =IF(AND(ABS(N(Tender!$E$18)-N($F$30))<=Tender!$E$32,ABS(N(Tender!$F$18)-N($G$30))<=Tender!$E$32,ABS(N(Tender!$G$18)-N($H$30))<=Tender!$E$32,ABS(N(Tender!$H$18)-N($I$30))<=Tender!$E$32,ABS(N(Tender!$I$18)-N($E$30))<=Tender!$E$32),"OK","FAIL") -> OK
C31: ÖSZ-7 brownfield site ≥ 70 % (1 = yes) | D31: 1 / 0 | E31: 0 | F31: 0 | G31: 0 | H31: 0 | I31: 0 | J31: =Tender!$J$19 -> 0 | O31: Tender E19:I19 | P31: =IF(AND(ABS(N(Tender!$E$19)-N($F$31))<=Tender!$E$32,ABS(N(Tender!$F$19)-N($G$31))<=Tender!$E$32,ABS(N(Tender!$G$19)-N($H$31))<=Tender!$E$32,ABS(N(Tender!$H$19)-N($I$31))<=Tender!$E$32,ABS(N(Tender!$I$19)-N($E$31))<=Tender!$E$32),"OK","FAIL") -> OK
C32: ÖSZ-8 shared connection point and line (1 = yes) | D32: 1 / 0 | E32: 0 | F32: 0 | G32: 1 | H32: 1 | I32: 1 | J32: =Tender!$J$20 -> 0 | O32: Tender E20:I20 | P32: =IF(AND(ABS(N(Tender!$E$20)-N($F$32))<=Tender!$E$32,ABS(N(Tender!$F$20)-N($G$32))<=Tender!$E$32,ABS(N(Tender!$G$20)-N($H$32))<=Tender!$E$32,ABS(N(Tender!$H$20)-N($I$32))<=Tender!$E$32,ABS(N(Tender!$I$20)-N($E$32))<=Tender!$E$32),"OK","FAIL") -> OK
C33: ÖSZ-9a turbine of the scenario (1 = EU, 0 = CN) – RtB route and headline score | D33: 1 / 0 | E33: 0 | F33: 1 | G33: 1 | H33: 1 | I33: 1 | J33: =Tender!$J$22 -> 1 | O33: Tender E22:I22 | P33: =IF(AND(ABS(N(Tender!$E$22)-N($F$33))<=Tender!$E$32,ABS(N(Tender!$F$22)-N($G$33))<=Tender!$E$32,ABS(N(Tender!$G$22)-N($H$33))<=Tender!$E$32,ABS(N(Tender!$H$22)-N($I$33))<=Tender!$E$32,ABS(N(Tender!$I$22)-N($E$33))<=Tender!$E$32),"OK","FAIL") -> OK
C34: ÖSZ-9b EU-made generator transformer (1 = yes; European-turbine routes only) | D34: 1 / 0 | E34: 0 | F34: 0 | G34: 1 | H34: 1 | I34: 1 | J34: =Tender!$J$21 -> 0 | O34: Tender E21:I21 | P34: =IF(AND(ABS(N(Tender!$E$21)-N($F$34))<=Tender!$E$32,ABS(N(Tender!$F$21)-N($G$34))<=Tender!$E$32,ABS(N(Tender!$G$21)-N($H$34))<=Tender!$E$32,ABS(N(Tender!$H$21)-N($I$34))<=Tender!$E$32,ABS(N(Tender!$I$21)-N($E$34))<=Tender!$E$32),"OK","FAIL") -> OK
C35: Derived per scenario (Tender rows 40–45, live)
C36: Gross installed wind = net MVA × (1 + overbuild) | D36: MW | E36: =Tender!I$40 -> 200 | F36: =Tender!E$40 -> 261 | G36: =Tender!F$40 -> 280 | H36: =Tender!G$40 -> 280 | I36: =Tender!H$40 -> 308 | J36: =Tender!$J$40 -> 261 | O36: Tender E40:I40
C37: BESS power = ratio × basis MW | D37: MW | E37: =Tender!I$41 -> 0 | F37: =Tender!E$41 -> 90 | G37: =Tender!F$41 -> 90 | H37: =Tender!G$41 -> 90 | I37: =Tender!H$41 -> 157.08 | J37: =Tender!$J$41 -> 90 | O37: Tender E41:I41
C38: BESS energy (power × duration) | D38: MWh | E38: =Tender!I$42 -> 0 | F38: =Tender!E$42 -> 360 | G38: =Tender!F$42 -> 360 | H38: =Tender!G$42 -> 360 | I38: =Tender!H$42 -> 628.32 | J38: =Tender!$J$42 -> 360 | O38: Tender E42:I42
C39: BESS ratio of installed wind (ÖSZ-4 x, GYIK 20) | D39: % | E39: =Tender!I$44 -> 0 | F39: =Tender!E$44 -> 0.34482759 | G39: =Tender!F$44 -> 0.32142857 | H39: =Tender!G$44 -> 0.32142857 | I39: =Tender!H$44 -> 0.51 | J39: =Tender!$J$44 -> 0.34482759 | O39: Tender E44:I44
C40: Clipping loss at the connection capacity (L20 estimate) | D40: % | E40: =Tender!I$45 -> 0 | F40: =Tender!E$45 -> 0.0465125 | G40: =Tender!F$45 -> 0.08 | H40: =Tender!G$45 -> 0.08 | I40: =Tender!H$45 -> 0.1458 | J40: =Tender!$J$45 -> 0.0465125 | O40: Tender E45:I45
C41: Points – Annex 3 weight × Annex 4 inner points, GYIK rules (Tender rows 51–88, live)
C42: ÖSZ-1 municipal contribution | D42: pts | E42: =Tender!I$55 -> 0 | F42: =Tender!E$55 -> 4 | G42: =Tender!F$55 -> 4 | H42: =Tender!G$55 -> 20 | I42: =Tender!H$55 -> 20 | O42: Tender E55:I55
C43: ÖSZ-2 community contribution | D43: pts | E43: =Tender!I$60 -> 0 | F43: =Tender!E$60 -> 0 | G43: =Tender!F$60 -> 0 | H43: =Tender!G$60 -> 0 | I43: =Tender!H$60 -> 15 | O43: Tender E60:I60
C44: ÖSZ-3 overbuild | D44: pts | E44: =Tender!I$65 -> 0 | F44: =Tender!E$65 -> 7 | G44: =Tender!F$65 -> 9 | H44: =Tender!G$65 -> 9 | I44: =Tender!H$65 -> 10 | O44: Tender E65:I65
C45: ÖSZ-4 BESS (ratio of installed wind) | D45: pts | E45: =Tender!I$70 -> 0 | F45: =Tender!E$70 -> 10.5 | G45: =Tender!F$70 -> 10.5 | H45: =Tender!G$70 -> 10.5 | I45: =Tender!H$70 -> 15 | O45: Tender E70:I70
C46: ÖSZ-5 partial award | D46: pts | E46: =Tender!I$72 -> 0 | F46: =Tender!E$72 -> 0 | G46: =Tender!F$72 -> 5 | H46: =Tender!G$72 -> 5 | I46: =Tender!H$72 -> 5 | O46: Tender E72:I72
C47: ÖSZ-6 performance security | D47: pts | E47: =Tender!I$76 -> 0 | F47: =Tender!E$76 -> 2.5 | G47: =Tender!F$76 -> 3 | H47: =Tender!G$76 -> 5 | I47: =Tender!H$76 -> 5 | O47: Tender E76:I76
C48: ÖSZ-7 brownfield site | D48: pts | E48: =Tender!I$78 -> 0 | F48: =Tender!E$78 -> 0 | G48: =Tender!F$78 -> 0 | H48: =Tender!G$78 -> 0 | I48: =Tender!H$78 -> 0 | O48: Tender E78:I78
C49: ÖSZ-8 shared connection | D49: pts | E49: =Tender!I$80 -> 0 | F49: =Tender!E$80 -> 0 | G49: =Tender!F$80 -> 5 | H49: =Tender!G$80 -> 5 | I49: =Tender!H$80 -> 5 | O49: Tender E80:I80
C50: ÖSZ-9 EU-made equipment (European-turbine routes only) | D50: pts | E50: =Tender!I$82 -> 0 | F50: =Tender!E$82 -> 12 | G50: =Tender!F$82 -> 15 | H50: =Tender!G$82 -> 15 | I50: =Tender!H$82 -> 15 | O50: Tender E82:I82
C51: Σ ÖSZ-1 … ÖSZ-8 | D51: pts | E51: =Tender!I$83 -> 0 | F51: =Tender!E$83 -> 24 | G51: =Tender!F$83 -> 36.5 | H51: =Tender!G$83 -> 54.5 | I51: =Tender!H$83 -> 75 | O51: Tender E83:I83
C52: TOTAL SCORE – European-turbine routes (RtB with EU turbine, cases 2 / 7) | D52: pts | E52: =Tender!I$84 -> 0 | F52: =Tender!E$84 -> 36 | G52: =Tender!F$84 -> 51.5 | H52: =Tender!G$84 -> 69.5 | I52: =Tender!H$84 -> 90 | J52: =Tender!$J$84 -> 36 | O52: Tender E84:I84
C53: TOTAL SCORE – Chinese-turbine routes (cases 3 / 8) | D53: pts | E53: =Tender!I$85 -> 0 | F53: =Tender!E$85 -> 24 | G53: =Tender!F$85 -> 36.5 | H53: =Tender!G$85 -> 54.5 | I53: =Tender!H$85 -> 75 | J53: =Tender!$J$85 -> 24 | O53: Tender E85:I85
C54: Score of the scenario (its own turbine, row 22) | D54: pts | E54: =Tender!I$86 -> 0 | F54: =Tender!E$86 -> 36 | G54: =Tender!F$86 -> 51.5 | H54: =Tender!G$86 -> 69.5 | I54: =Tender!H$86 -> 90 | J54: =Tender!$J$86 -> 36 | O54: Tender E86:I86
C55: Bid validity – scoring rules (node cap: see row 65) | D55: status | E55: =Tender!I$87 -> Valid | F55: =Tender!E$87 -> Valid | G55: =Tender!F$87 -> Valid | H55: =Tender!G$87 -> Valid | I55: =Tender!H$87 -> Valid | O55: Tender E87:I87 (installed wind ≥ net MVA, VII.16)
C56: GYIK eligibility of the scored items (1 = points awarded; 0 = below the minimum / not eligible)
C57: ÖSZ-1 eligible (10 000 ≤ x ≤ 50 000 €/MW; below → 0 points, GYIK 17) | D57: 1 / 0 | E57: =Tender!I$52 -> 0 | F57: =Tender!E$52 -> 1 | G57: =Tender!F$52 -> 1 | H57: =Tender!G$52 -> 1 | I57: =Tender!H$52 -> 1 | O57: Tender E52:I52
C58: ÖSZ-2 eligible (2 ≤ x ≤ 3 €/MWh; below → 0 points, GYIK 17) | D58: 1 / 0 | E58: =Tender!I$57 -> 0 | F58: =Tender!E$57 -> 1 | G58: =Tender!F$57 -> 1 | H58: =Tender!G$57 -> 1 | I58: =Tender!H$57 -> 1 | O58: Tender E57:I57
C59: ÖSZ-3 eligible (installed wind ≥ net MVA) | D59: 1 / 0 | E59: =Tender!I$62 -> 1 | F59: =Tender!E$62 -> 1 | G59: =Tender!F$62 -> 1 | H59: =Tender!G$62 -> 1 | I59: =Tender!H$62 -> 1 | O59: Tender E62:I62
C60: ÖSZ-4 eligible (ratio ≥ 5 % of installed wind, ≥ 4 h, BESS MW ≤ wind MW) | D60: 1 / 0 | E60: =Tender!I$67 -> 0 | F60: =Tender!E$67 -> 1 | G60: =Tender!F$67 -> 1 | H60: =Tender!G$67 -> 1 | I60: =Tender!H$67 -> 1 | O60: Tender E67:I67
C61: Company-group caps – eligibility flag only (not an integrity check; Tender section 8)
C62: Same company group (1 = Bora's SPV bids within a company group) | D62: 1 / 0 | E62: 1 | O62: → Tender E348 | P62: =IF(AND(ABS(N(Tender!$E$348)-N($E$62))<=Tender!$E$32),"OK","FAIL") -> OK
C63: Other bids by the same group at this node | D63: MVA | E63: 0 | O63: → Tender F351 | P63: =IF(AND(ABS(N(Tender!$F$351)-N($E$63))<=Tender!$E$32),"OK","FAIL") -> OK
C64: Other bids by the same group in total (all nodes) | D64: MVA | E64: 0 | O64: → Tender G351 | P64: =IF(AND(ABS(N(Tender!$G$351)-N($E$64))<=Tender!$E$32),"OK","FAIL") -> OK
C65: Node cap (100 MVA per node, V.7 / VII.36): Bora + other bids at the node | D65: flag | E65: =Tender!$I$353 -> FLAG – eligibility: 200 MVA > 100 MVA node cap (V.7 / VII.36) | O65: Tender I353
C66: Group total cap (200 MVA, V.6) | D66: flag | E66: =Tender!$E$355 -> OK | O66: Tender E355
C67: Group caps – status | D67: flag | E67: =Tender!$E$356 -> FLAG – 1 group-cap issue(s), rows 353 / 355 | O67: Tender E356
C69: c. Business inputs – single source (the model's input cells link here)
C70: Input | D70: Unit | E70: Base / RtB (case 1) | F70: European (cases 2, 7) | G70: Chinese (cases 3, 8) | O70: Model cell (→) / note | P70: Link check
C71: European / Chinese columns left blank = same as Base. Rows without a European / Chinese cell apply to every route.
C72: Project and deal
C73: Grid node (Annex 1) | D73: name | E73: Szombathely OVIT (SZHO B 132.00) | O73: → Inputs G280 | P73: =IF(AND((Inputs!$G$280&"")=($E$73&"")),"OK","FAIL") -> OK
C74: Net grid connection capacity – requested MVA (premium basis, grid fees, TSO bond) | D74: MVA | E74: 200 | O74: → Inputs G16 / G281, Tender E37 | P74: =IF(AND(ABS(N(Inputs!$G$16)-N($E$74))<=Tender!$E$32,ABS(N(Inputs!$G$281)-N($E$74))<=Tender!$E$32,ABS(N(Tender!$E$37)-N($E$74))<=Tender!$E$32),"OK","FAIL") -> OK
C75: Signing fee / purchase price to the current owners | D75: k€ | E75: 250 | O75: → Inputs G24 / G283 | P75: =IF(AND(ABS(N(Inputs!$G$24)-N($E$75))<=Tender!$E$32,ABS(N(Inputs!$G$283)-N($E$75))<=Tender!$E$32),"OK","FAIL") -> OK
C76: JV structure live (1 = 70/30 JV with A.RES, 0 = FEP 100 %) | D76: 1 / 0 | E76: 1 | O76: → Inputs G31 / G284 | P76: =IF(AND(ABS(N(Inputs!$G$31)-N($E$76))<=Tender!$E$32,ABS(N(Inputs!$G$284)-N($E$76))<=Tender!$E$32),"OK","FAIL") -> OK
C77: FEP share of the net proceeds if JV | D77: % | E77: 0.7 | O77: → Inputs G32 / G285 | P77: =IF(AND(ABS(N(Inputs!$G$32)-N($E$77))<=Tender!$E$32,ABS(N(Inputs!$G$285)-N($E$77))<=Tender!$E$32),"OK","FAIL") -> OK
C78: Developer success fee (DSA) live | D78: 1 / 0 | E78: 1 | O78: → Inputs G286 | P78: =IF(AND(ABS(N(Inputs!$G$286)-N($E$78))<=Tender!$E$32),"OK","FAIL") -> OK
C79: DSA basis = installed wind MW (FLAG – BORA_Devex V37, user 09-Oct-26) | D79: MW | E79: =Inputs!$E$29 -> 261 | O79: DSA = 2.5 k€/MW × installed wind MW (cap Inputs E37 per MW)
C80: Number of tender bids (participation fee per bid) | D80: # | E80: 2 | O80: → Inputs G82 / G287 | P80: =IF(AND(ABS(N(Inputs!$G$82)-N($E$80))<=Tender!$E$32,ABS(N(Inputs!$G$287)-N($E$80))<=Tender!$E$32),"OK","FAIL") -> OK
C81: Indirect connection fee (Annex 1) | D81: Ft/MVA | E81: 73071306 | O81: → Inputs G85 / G288 | P81: =IF(AND(ABS(N(Inputs!$G$288)-N($E$81))<=Tender!$E$32,ABS(Inputs!$G$85-$E$81/1000000)<=Tender!$E$32),"OK","FAIL") -> OK
C82: Direct connection investment (Annex 1, per connection point) | D82: Ft | E82: 508345804 | O82: → Inputs G84 / G289 | P82: =IF(AND(ABS(N(Inputs!$G$289)-N($E$82))<=Tender!$E$32,ABS(Inputs!$G$84-$E$82/1000000/$E$74)<=Tender!$E$32),"OK","FAIL") -> OK
C83: Devex – total incl. contingency (BORA_Devex line items) | D83: k€ | E83: =Inputs!$E$292 -> 3137.8459 | O83: Inputs G292 (formula)
C84: RtB exit
C85: RtB exit premium (sale price) | D85: k€/MW | E85: 150 | O85: → Inputs G141:I141 | P85: =IF(AND(ABS(N(Inputs!$G$141)-N($E$85))<=Tender!$E$32,ABS(N(Inputs!$H$141)-N($F$85))<=Tender!$E$32,ABS(N(Inputs!$I$141)-N($G$85))<=Tender!$E$32),"OK","FAIL") -> OK
C86: RtB premium MW basis (0 = net MVA, 1 = installed wind – FLAG) | D86: 1 / 0 | E86: 0 | O86: → Inputs G149 (E149 / E150) | P86: =IF(AND(ABS(N(Inputs!$G$149)-N($E$86))<=Tender!$E$32),"OK","FAIL") -> OK
C87: Premium basis MW (Inputs E150) | D87: MW | E87: =Inputs!$E$150 -> 200 | O87: Inputs E150
C88: Lag from RtB to the RtB sale | D88: months | E88: 9 | O88: → Inputs G28:I28 | P88: =IF(AND(ABS(N(Inputs!$G$28)-N($E$88))<=Tender!$E$32,ABS(N(Inputs!$H$28)-N($F$88))<=Tender!$E$32,ABS(N(Inputs!$I$28)-N($G$88))<=Tender!$E$32),"OK","FAIL") -> OK
C89: Pass-through of the promises' PV into the exit price (RtB and sale at COD) | D89: % | E89: 1 | O89: → Tender E30 | P89: =IF(AND(ABS(N(Tender!$E$30)-N($E$89))<=Tender!$E$32),"OK","FAIL") -> OK
C90: Timing
C91: COD (month end) – the timeline moves with it (RtB, RtB sale, NTP) | D91: date | E91: 48121 | O91: → Inputs G298 (E55 back-solves the months to RtB) | P91: =IF(AND(ABS(N(Inputs!$G$298)-N($E$91))<=Tender!$E$32),"OK","FAIL") -> OK
C92: Construction (NTP → COD) | D92: months | E92: 24 | O92: → Inputs G153:I153 | P92: =IF(AND(ABS(N(Inputs!$G$153)-N($E$92))<=Tender!$E$32,ABS(N(Inputs!$H$153)-N($F$92))<=Tender!$E$32,ABS(N(Inputs!$I$153)-N($G$92))<=Tender!$E$32),"OK","FAIL") -> OK
C93: NTP / FID lag after RtB | D93: months | E93: 3 | O93: → Inputs G152 | P93: =IF(AND(ABS(N(Inputs!$G$152)-N($E$93))<=Tender!$E$32),"OK","FAIL") -> OK
C94: Operating life | D94: years | E94: 30 | O94: → Inputs G157:I157 | P94: =IF(AND(ABS(N(Inputs!$G$157)-N($E$94))<=Tender!$E$32,ABS(N(Inputs!$H$157)-N($F$94))<=Tender!$E$32,ABS(N(Inputs!$I$157)-N($G$94))<=Tender!$E$32),"OK","FAIL") -> OK
C95: Valid COD window – earliest | D95: date | E95: =MAX(Inputs!$E$237,EOMONTH(Inputs!$E$27,MAX(Devex_FEP!$I$5:$I$38)-Inputs!$E$28+Inputs!$E$152+Inputs!$E$153),EOMONTH(Inputs!$E$27,Inputs!$E$152+Inputs!$E$153)) -> 47756 | O95: Earliest grid connection (Inputs E237); RtB sale after the last devex payment; months to RtB ≥ 0
C96: Valid COD window – latest | D96: date | E96: =MIN(Inputs!$E$238,DATE(HTM!$AQ$5-Inputs!$E$157,12,31),EOMONTH(Inputs!$E$27,MOIC!$BP$4-Inputs!$E$28+Inputs!$E$152+Inputs!$E$153)) -> 48213 | O96: COD deadline (Inputs E238); life inside the HTM horizon; RtB sale inside the MOIC grid
C97: Timeline validity | D97: status | E97: =IF(AND(Inputs!$E$155>=$E$95,Inputs!$E$155<=$E$96),"OK","FLAG – COD outside the valid window – see MOIC G270 / HTM G172") -> OK | O97: Inputs E155 vs the two rows above
C98: RtB date / RtB sale date | D98: date | E98: =Inputs!$E$56 -> 47299 | F98: =Inputs!$E$58 -> 47573 | O98: Inputs E56 / E58
C99: NTP / COD | D99: date | E99: =Inputs!$E$154 -> 47391 | F99: =Inputs!$E$155 -> 48121 | O99: Inputs E154 / E155
C100: Capex
C101: Turbine supply incl. transport | D101: k€/MW | E101: 950 | F101: 950 | G101: 500 | O101: → Inputs G162:I162 | P101: =IF(AND(ABS(N(Inputs!$G$162)-N($E$101))<=Tender!$E$32,ABS(N(Inputs!$H$162)-N($F$101))<=Tender!$E$32,ABS(N(Inputs!$I$162)-N($G$101))<=Tender!$E$32),"OK","FAIL") -> OK
C102: Turbine installation and erection | D102: k€/MW | E102: 80 | O102: → Inputs G163:I163 | P102: =IF(AND(ABS(N(Inputs!$G$163)-N($E$102))<=Tender!$E$32,ABS(N(Inputs!$H$163)-N($F$102))<=Tender!$E$32,ABS(N(Inputs!$I$163)-N($G$102))<=Tender!$E$32),"OK","FAIL") -> OK
C103: Foundations | D103: k€/MW | E103: 90 | O103: → Inputs G164:I164 | P103: =IF(AND(ABS(N(Inputs!$G$164)-N($E$103))<=Tender!$E$32,ABS(N(Inputs!$H$164)-N($F$103))<=Tender!$E$32,ABS(N(Inputs!$I$164)-N($G$103))<=Tender!$E$32),"OK","FAIL") -> OK
C104: Balance of plant – civil | D104: k€/MW | E104: 70 | O104: → Inputs G165:I165 | P104: =IF(AND(ABS(N(Inputs!$G$165)-N($E$104))<=Tender!$E$32,ABS(N(Inputs!$H$165)-N($F$104))<=Tender!$E$32,ABS(N(Inputs!$I$165)-N($G$104))<=Tender!$E$32),"OK","FAIL") -> OK
C105: Balance of plant – electrical | D105: k€/MW | E105: 60 | O105: → Inputs G166:I166 | P105: =IF(AND(ABS(N(Inputs!$G$166)-N($E$105))<=Tender!$E$32,ABS(N(Inputs!$H$166)-N($F$105))<=Tender!$E$32,ABS(N(Inputs!$I$166)-N($G$105))<=Tender!$E$32),"OK","FAIL") -> OK
...

Sheet Tender
C2: Tender – MEKH capacity tender 2026 for Bora: tender strategies S0–S4 (columns E:I; E = S1 current bid = price-effect reference, I = S0 zero bid; J = active), points (GYIK rules), price effect of the promises and the returns matrix
C3: Column J = the active strategy (E5, set on the Control Panel) → Inputs G20 / G21 / G90 / G233 / G234 / G297 / M230 / N230, HTM E36 and row 340. Strategy columns E:I link to the Control Panel (one source). Blue = input, green = link, black = formula. Section 5 is live (Control Panel data table); section 7 holds the checks (→ MOIC G271, HTM G173).
C5: Active tender strategy (0 = S1, 1 = S2, 2 = S3, 3 = S4, 4 = S0) – set on the Control Panel (E9; data-table runs: E10) | D5: # | E5: =IF('Control Panel'!$E$10=0,'Control Panel'!$F$9,INDEX('Control Panel'!$D$306:$D$330,'Control Panel'!$E$10)) -> 0 | F5: =$J$11 -> S1 – Current bid
C7: Active case (set on the Control Panel → Inputs E6) | D7: # | E7: =Inputs!$E$6 -> 1 | F7: =Inputs!$E$7 -> FEP base case
C9: 1. Tender strategies – columns E:I = S1 / S2 / S3 / S4 / S0 (links to the Control Panel, section b), column J = active strategy; price-effect reference = S1 (column E)
C10: Item | D10: Unit | E10: S1 – current bid (reference) | F10: S2 – free points | G10: S3 – ≈70 points | H10: S4 – maximum score | I10: S0 – zero bid | J10: Active | K10: Feeds / note
C11: Scenario name | D11: Text | E11: ='Control Panel'!$F$22 -> S1 – Current bid | F11: ='Control Panel'!$G$22 -> S2 – Free points | G11: ='Control Panel'!$H$22 -> S3 – Cost-efficient (≈70 points) | H11: ='Control Panel'!$I$22 -> S4 – Maximum score | I11: ='Control Panel'!$E$22 -> S0 – Zero bid | J11: =INDEX($E11:$I11,1,$E$5+1) -> S1 – Current bid | K11: Selector E5 (Control Panel E9)
C12: ÖSZ-1 One-off municipal contribution | D12: k€/MW | E12: ='Control Panel'!$F$23 -> 20 | F12: ='Control Panel'!$G$23 -> 20 | G12: ='Control Panel'!$H$23 -> 50 | H12: ='Control Panel'!$I$23 -> 50 | I12: ='Control Panel'!$E$23 -> 0 | J12: =INDEX($E12:$I12,1,$E$5+1) -> 20 | K12: → Inputs G233 (paid in the COD year on net MW, HTM row 29)
C13: ÖSZ-2 Annual community contribution on energy fed in | D13: €/MWh | E13: ='Control Panel'!$F$24 -> 2 | F13: ='Control Panel'!$G$24 -> 2 | G13: ='Control Panel'!$H$24 -> 2 | H13: ='Control Panel'!$I$24 -> 3 | I13: ='Control Panel'!$E$24 -> 0 | J13: =INDEX($E13:$I13,1,$E$5+1) -> 2 | K13: → Inputs G234 (every operating year, HTM row 59)
C14: ÖSZ-3 Overbuild – gross wind above net MVA | D14: % | E14: ='Control Panel'!$F$25 -> 0.305 | F14: ='Control Panel'!$G$25 -> 0.4 | G14: ='Control Panel'!$H$25 -> 0.4 | H14: ='Control Panel'!$I$25 -> 0.54 | I14: ='Control Panel'!$E$25 -> 0 | J14: =INDEX($E14:$I14,1,$E$5+1) -> 0.305 | K14: Gross installed wind = net MVA × (1 + overbuild), row 40 per strategy (S1: 30.5 % → 261 MW, Munka1: Bora1 151 + Bora2 110; S2 / S3: 40 % → 280 MW; S4: 54 % → 308 MW; S0: 0 % → 200 MW)
C15: ÖSZ-4 BESS power ratio (basis: row 25 – installed wind or net MVA) | D15: % | E15: ='Control Panel'!$F$26 -> 0.34482759 | F15: ='Control Panel'!$G$26 -> 0.45 | G15: ='Control Panel'!$H$26 -> 0.45 | H15: ='Control Panel'!$I$26 -> 0.51 | I15: ='Control Panel'!$E$26 -> 0 | J15: =INDEX($E15:$I15,1,$E$5+1) -> 0.34482759 | K15: BESS = ratio × basis (row 25), row 41 per strategy. S1: 90 MW = 34.48 % of the 261 MW installed wind (Munka1: Bora 70 + 20 MW); S2 / S3: 45 % of the net MVA = 90 MW; S4: 51 % of installed wind (GYIK 20); S0: no BESS
C16: ÖSZ-4 BESS duration | D16: h | E16: ='Control Panel'!$F$28 -> 4 | F16: ='Control Panel'!$G$28 -> 4 | G16: ='Control Panel'!$H$28 -> 4 | H16: ='Control Panel'!$I$28 -> 4 | I16: ='Control Panel'!$E$28 -> 4 | J16: =INDEX($E16:$I16,1,$E$5+1) -> 4 | K16: → Inputs G21 (≥ 4 h needed for ÖSZ-4 points)
C17: ÖSZ-6 Performance security as % of the tender minimum | D17: % | E17: ='Control Panel'!$F$29 -> 1.5 | F17: ='Control Panel'!$G$29 -> 1.6 | G17: ='Control Panel'!$H$29 -> 2 | H17: ='Control Panel'!$I$29 -> 2.1 | I17: ='Control Panel'!$E$29 -> 1 | J17: =INDEX($E17:$I17,1,$E$5+1) -> 1.5 | K17: → Inputs G90 performance bond uplift (Deposits row 10)
C18: ÖSZ-5 Accept partial award | D18: 1 / 0 | E18: ='Control Panel'!$F$30 -> 0 | F18: ='Control Panel'!$G$30 -> 1 | G18: ='Control Panel'!$H$30 -> 1 | H18: ='Control Panel'!$I$30 -> 1 | I18: ='Control Panel'!$E$30 -> 0 | J18: =INDEX($E18:$I18,1,$E$5+1) -> 0 | K18: Scored; no cost modelled
C19: ÖSZ-7 Brownfield site (≥ 70 %) | D19: 1 / 0 | E19: ='Control Panel'!$F$31 -> 0 | F19: ='Control Panel'!$G$31 -> 0 | G19: ='Control Panel'!$H$31 -> 0 | H19: ='Control Panel'!$I$31 -> 0 | I19: ='Control Panel'!$E$31 -> 0 | J19: =INDEX($E19:$I19,1,$E$5+1) -> 0 | K19: Not available at Bora's node – no points in any scenario
C20: ÖSZ-8 Shared connection point and line | D20: 1 / 0 | E20: ='Control Panel'!$F$32 -> 0 | F20: ='Control Panel'!$G$32 -> 1 | G20: ='Control Panel'!$H$32 -> 1 | H20: ='Control Panel'!$I$32 -> 1 | I20: ='Control Panel'!$E$32 -> 0 | J20: =INDEX($E20:$I20,1,$E$5+1) -> 0 | K20: Scored; no cost modelled
C21: ÖSZ-9b EU-made generator transformer (European-turbine routes only) | D21: 1 / 0 | E21: ='Control Panel'!$F$34 -> 0 | F21: ='Control Panel'!$G$34 -> 1 | G21: ='Control Panel'!$H$34 -> 1 | H21: ='Control Panel'!$I$34 -> 1 | I21: ='Control Panel'!$E$34 -> 0 | J21: =INDEX($E21:$I21,1,$E$5+1) -> 0 | K21: Chinese routes: non-EU transformer, substation capex reduced by Tender E29 (Inputs I167 / N167)
C22: Turbine of the scenario (1 = European, 0 = Chinese) | D22: 1 / 0 | E22: ='Control Panel'!$F$33 -> 1 | F22: ='Control Panel'!$G$33 -> 1 | G22: ='Control Panel'!$H$33 -> 1 | H22: ='Control Panel'!$I$33 -> 1 | I22: ='Control Panel'!$E$33 -> 0 | J22: =INDEX($E22:$I22,1,$E$5+1) -> 1 | K22: Headline score of the scenario and the score of its RtB route; ÖSZ-9a turbine points only for European
C23: Sale at COD price – European turbine, before clipping | D23: k€/gross MW | E23: ='Control Panel'!$E$133 -> 2450 | F23: ='Control Panel'!$E$133 -> 2450 | G23: ='Control Panel'!$E$133 -> 2450 | H23: ='Control Panel'!$E$133 -> 2450 | I23: ='Control Panel'!$E$133 -> 2450 | J23: =INDEX($E23:$I23,1,$E$5+1) -> 2450 | K23: One price for all scenarios (Control Panel section c); × (1 − clip) per scenario (row 46) → Inputs M230 (case 7)
C24: Sale at COD price – Chinese turbine, before clipping | D24: k€/gross MW | E24: ='Control Panel'!$E$134 -> 2100 | F24: ='Control Panel'!$E$134 -> 2100 | G24: ='Control Panel'!$E$134 -> 2100 | H24: ='Control Panel'!$E$134 -> 2100 | I24: ='Control Panel'!$E$134 -> 2100 | J24: =INDEX($E24:$I24,1,$E$5+1) -> 2100 | K24: One price for all scenarios (Control Panel section c); × (1 − clip) per scenario (row 47) → Inputs N230 (case 8)
C25: ÖSZ-4 BESS ratio basis (1 = % of installed gross wind, GYIK 20; 0 = % of net MVA) | D25: 1 / 0 | E25: ='Control Panel'!$F$27 -> 1 | F25: ='Control Panel'!$G$27 -> 0 | G25: ='Control Panel'!$H$27 -> 0 | H25: ='Control Panel'!$I$27 -> 1 | I25: ='Control Panel'!$E$27 -> 1 | J25: =INDEX($E25:$I25,1,$E$5+1) -> 1 | K25: Round 5 (GYIK 20): ÖSZ-4 is scored on BESS MW ÷ installed wind MW (BT1)
C26: 1b. Common inputs (one value for all scenarios) | D26: Unit | E26: Value | F26: Note
C27: Reference overbuild of the L20 clipping estimate | D27: % | E27: 0.2 | F27: clip(x) = L20 × (x ÷ 20 %)² – estimate, replace with an 8,760 h export-cap study
C28: Clipping loss at the reference overbuild (L20) – ESTIMATE, all scenarios incl. 0 | D28: % | E28: ='Control Panel'!$E$113 -> 0.02 | F28: Physical effect of the overbuild (row 43), so it applies in every scenario; set on the Control Panel
C29: Chinese routes: substation and 132 kV bay capex reduction (non-EU transformer) | D29: % | E29: 0.1 | F29: → Inputs I167 / N167 (cases 3 / 8)
C30: Pass-through of the promises' PV into the exit price (RtB and sale at COD) | D30: % | E30: ='Control Panel'!$E$89 -> 1 | F30: 100 % = the buyer deducts the full PV of the promises relative to the S1 current-bid reference (promises below it, e.g. S0, add to the price); set on the Control Panel
C31: Performance security held after COD (buyer's guarantee fee, RtB price effect) | D31: months | E31: 6 | F31: Tender XII.2 – security returned 6 months after COD (as v5)
C32: Check tolerance – absolute | D32: k€ / mHUF | E32: 0.01 | F32: Used by the check rows (section 7, Deposits)
C33: Check tolerance – relative | D33: x | E33: 1e-06 | F33: Live vs data-table tie-out (section 6)
C35: 2. Strategy block – each tender strategy applied to Bora (columns E:I = S1 / S2 / S3 / S4 / S0; column J = active strategy → Inputs / HTM)
C36: Item | D36: Unit | E36: S1 | F36: S2 | G36: S3 | H36: S4 | I36: S0 | J36: Active scenario | K36: Note
C37: Net grid connection capacity (Annex 1) | D37: MVA | E37: ='Control Panel'!$E$74 -> 200 | F37: =$E37 -> 200 | G37: =$E37 -> 200 | H37: =$E37 -> 200 | I37: =$E37 -> 200 | J37: =$E37 -> 200 | K37: Control Panel section c – RtB premium (default basis), grid fees, TSO bond
C38: S1 current bid (column E) – gross installed wind (reference of the price effect = column E row 40) | D38: MW | E38: =$E$40 -> 261 | J38: =$E38 -> 261 | K38: Munka1: Bora1 151 + Bora2 110 = 261 MW
C39: S1 current bid (column E) – BESS power (reference of the price effect = column E row 41) | D39: MW | E39: =$E$41 -> 90 | J39: =$E39 -> 90 | K39: Munka1: Bora 70 + 20 MW
C40: Gross installed wind = net MVA × (1 + overbuild) | D40: MW | E40: =ROUND($E37*(1+E$14),6) -> 261 | F40: =ROUND($E37*(1+F$14),6) -> 280 | G40: =ROUND($E37*(1+G$14),6) -> 280 | H40: =ROUND($E37*(1+H$14),6) -> 308 | I40: =ROUND($E37*(1+I$14),6) -> 200 | J40: =INDEX($E40:$I40,1,$E$5+1) -> 261 | K40: Active (column I) → Inputs G297 (installed wind)
C41: BESS power = ratio × basis MW (row 25) | D41: MW | E41: =ROUND(E$15*CHOOSE(E$25+1,$E37,E40),6) -> 90 | F41: =ROUND(F$15*CHOOSE(F$25+1,$E37,F40),6) -> 90 | G41: =ROUND(G$15*CHOOSE(G$25+1,$E37,G40),6) -> 90 | H41: =ROUND(H$15*CHOOSE(H$25+1,$E37,H40),6) -> 157.08 | I41: =ROUND(I$15*CHOOSE(I$25+1,$E37,I40),6) -> 0 | J41: =INDEX($E41:$I41,1,$E$5+1) -> 90 | K41: Active → Inputs G20 / G282; ratio × installed wind (row 25 = 1) or × net MVA
C42: BESS energy (power × duration) | D42: MWh | E42: =E41*E$16 -> 360 | F42: =F41*F$16 -> 360 | G42: =G41*G$16 -> 360 | H42: =H41*H$16 -> 628.32 | I42: =I41*I$16 -> 0 | J42: =INDEX($E42:$I42,1,$E$5+1) -> 360
C43: Overbuild (gross wind ÷ net MVA − 1) | D43: % | E43: =E40/E37-1 -> 0.305 | F43: =F40/F37-1 -> 0.4 | G43: =G40/G37-1 -> 0.4 | H43: =H40/H37-1 -> 0.54 | I43: =I40/I37-1 -> 0 | J43: =INDEX($E43:$I43,1,$E$5+1) -> 0.305 | K43: ÖSZ-3 commitment
C44: BESS ratio (BESS MW ÷ installed gross wind MW – GYIK 20, BT1) | D44: % | E44: =E41/E40 -> 0.34482759 | F44: =F41/F40 -> 0.32142857 | G44: =G41/G40 -> 0.32142857 | H44: =H41/H40 -> 0.51 | I44: =I41/I40 -> 0 | J44: =INDEX($E44:$I44,1,$E$5+1) -> 0.34482759 | K44: ÖSZ-4 commitment (round 5: was ÷ net MVA)
C45: Clipping loss at the connection capacity (L20 × (overbuild ÷ reference)²) | D45: % | E45: =$E$28*(MAX(0,E43)/$E$27)^2 -> 0.0465125 | F45: =$E$28*(MAX(0,F43)/$E$27)^2 -> 0.08 | G45: =$E$28*(MAX(0,G43)/$E$27)^2 -> 0.08 | H45: =$E$28*(MAX(0,H43)/$E$27)^2 -> 0.1458 | I45: =$E$28*(MAX(0,I43)/$E$27)^2 -> 0 | J45: =INDEX($E45:$I45,1,$E$5+1) -> 0.0465125 | K45: Active → HTM E36 (generation × (1 − clip)), applied once
C46: Sale at COD price – European, after clipping | D46: k€/gross MW | E46: =E$23*(1-E45) -> 2336.0444 | F46: =F$23*(1-F45) -> 2254 | G46: =G$23*(1-G45) -> 2254 | H46: =H$23*(1-H45) -> 2092.79 | I46: =I$23*(1-I45) -> 2450 | J46: =INDEX($E46:$I46,1,$E$5+1) -> 2336.0444 | K46: Active → Inputs M230 (case 7)
C47: Sale at COD price – Chinese, after clipping | D47: k€/gross MW | E47: =E$24*(1-E45) -> 2002.3238 | F47: =F$24*(1-F45) -> 1932 | G47: =G$24*(1-G45) -> 1932 | H47: =H$24*(1-H45) -> 1793.82 | I47: =I$24*(1-I45) -> 2100 | J47: =INDEX($E47:$I47,1,$E$5+1) -> 2002.3238 | K47: Active → Inputs N230 (case 8)
C48: RtB exit route available (1 = yes) | D48: 1 / 0 | E48: 1 | F48: =$E48 -> 1 | G48: =$E48 -> 1 | H48: =$E48 -> 1 | I48: =$E48 -> 1 | J48: =INDEX($E48:$I48,1,$E$5+1) -> 1 | K48: RtB exit available for Bora
C50: Points – Annex 3 weight × Annex 4 inner points (tables and parameters in section 3) | D50: Unit | E50: S1 | F50: S2 | G50: S3 | H50: S4 | I50: S0 | J50: Active scenario | K50: Rule
C51: ÖSZ-1 commitment x (6 dp) | D51: EUR/MW | E51: =ROUND(E$12*1000,6) -> 20000 | F51: =ROUND(F$12*1000,6) -> 20000 | G51: =ROUND(G$12*1000,6) -> 50000 | H51: =ROUND(H$12*1000,6) -> 50000 | I51: =ROUND(I$12*1000,6) -> 0 | J51: =INDEX($E51:$I51,1,$E$5+1) -> 20000 | K51: x = active ÖSZ-1 × 1000
C52: ÖSZ-1 eligible (min ≤ x ≤ max) | D52: 1 / 0 | E52: =AND(E51>=$E$162,E51<=$E$163)*1 -> 1 | F52: =AND(F51>=$E$162,F51<=$E$163)*1 -> 1 | G52: =AND(G51>=$E$162,G51<=$E$163)*1 -> 1 | H52: =AND(H51>=$E$162,H51<=$E$163)*1 -> 1 | I52: =AND(I51>=$E$162,I51<=$E$163)*1 -> 0 | J52: =INDEX($E52:$I52,1,$E$5+1) -> 1
C53: ÖSZ-1 band number (lookup) | D53: band | E53: =SUMPRODUCT(($D$93:$D$101<E51)+($D$93:$D$101=E51)*$E$93:$E$101) -> 2 | F53: =SUMPRODUCT(($D$93:$D$101<F51)+($D$93:$D$101=F51)*$E$93:$E$101) -> 2 | G53: =SUMPRODUCT(($D$93:$D$101<G51)+($D$93:$D$101=G51)*$E$93:$E$101) -> 9 | H53: =SUMPRODUCT(($D$93:$D$101<H51)+($D$93:$D$101=H51)*$E$93:$E$101) -> 9 | I53: =SUMPRODUCT(($D$93:$D$101<I51)+($D$93:$D$101=I51)*$E$93:$E$101) -> 0 | J53: =INDEX($E53:$I53,1,$E$5+1) -> 2 | K53: Σ (lower < x) + (lower = x) × included
C54: ÖSZ-1 inner points | D54: 0–100 | E54: =INDEX($F$92:$F$101,E53+1)*E52 -> 20 | F54: =INDEX($F$92:$F$101,F53+1)*F52 -> 20 | G54: =INDEX($F$92:$F$101,G53+1)*G52 -> 100 | H54: =INDEX($F$92:$F$101,H53+1)*H52 -> 100 | I54: =INDEX($F$92:$F$101,I53+1)*I52 -> 0 | J54: =INDEX($E54:$I54,1,$E$5+1) -> 20 | K54: INDEX(points incl. row 0, band + 1) × eligible
C55: ÖSZ-1 weighted points | D55: pts | E55: =E54*$E$153/100 -> 4 | F55: =F54*$E$153/100 -> 4 | G55: =G54*$E$153/100 -> 20 | H55: =H54*$E$153/100 -> 20 | I55: =I54*$E$153/100 -> 0 | J55: =INDEX($E55:$I55,1,$E$5+1) -> 4 | K55: inner × weight ÷ 100
C56: ÖSZ-2 commitment x (6 dp) | D56: EUR/MWh | E56: =ROUND(E$13,6) -> 2 | F56: =ROUND(F$13,6) -> 2 | G56: =ROUND(G$13,6) -> 2 | H56: =ROUND(H$13,6) -> 3 | I56: =ROUND(I$13,6) -> 0 | J56: =INDEX($E56:$I56,1,$E$5+1) -> 2
C57: ÖSZ-2 eligible (min ≤ x ≤ max) | D57: 1 / 0 | E57: =AND(E56>=$E$164,E56<=$E$165)*1 -> 1 | F57: =AND(F56>=$E$164,F56<=$E$165)*1 -> 1 | G57: =AND(G56>=$E$164,G56<=$E$165)*1 -> 1 | H57: =AND(H56>=$E$164,H56<=$E$165)*1 -> 1 | I57: =AND(I56>=$E$164,I56<=$E$165)*1 -> 0 | J57: =INDEX($E57:$I57,1,$E$5+1) -> 1
C58: ÖSZ-2 band number (lookup) | D58: band | E58: =SUMPRODUCT(($D$104:$D$114<E56)+($D$104:$D$114=E56)*$E$104:$E$114) -> 0 | F58: =SUMPRODUCT(($D$104:$D$114<F56)+($D$104:$D$114=F56)*$E$104:$E$114) -> 0 | G58: =SUMPRODUCT(($D$104:$D$114<G56)+($D$104:$D$114=G56)*$E$104:$E$114) -> 0 | H58: =SUMPRODUCT(($D$104:$D$114<H56)+($D$104:$D$114=H56)*$E$104:$E$114) -> 11 | I58: =SUMPRODUCT(($D$104:$D$114<I56)+($D$104:$D$114=I56)*$E$104:$E$114) -> 0 | J58: =INDEX($E58:$I58,1,$E$5+1) -> 0
C59: ÖSZ-2 inner points | D59: 0–100 | E59: =INDEX($F$103:$F$114,E58+1)*E57 -> 0 | F59: =INDEX($F$103:$F$114,F58+1)*F57 -> 0 | G59: =INDEX($F$103:$F$114,G58+1)*G57 -> 0 | H59: =INDEX($F$103:$F$114,H58+1)*H57 -> 100 | I59: =INDEX($F$103:$F$114,I58+1)*I57 -> 0 | J59: =INDEX($E59:$I59,1,$E$5+1) -> 0
C60: ÖSZ-2 weighted points | D60: pts | E60: =E59*$E$154/100 -> 0 | F60: =F59*$E$154/100 -> 0 | G60: =G59*$E$154/100 -> 0 | H60: =H59*$E$154/100 -> 15 | I60: =I59*$E$154/100 -> 0 | J60: =INDEX($E60:$I60,1,$E$5+1) -> 0
C61: ÖSZ-3 overbuild x (6 dp) | D61: % | E61: =ROUND(E43*100,6) -> 30.5 | F61: =ROUND(F43*100,6) -> 40 | G61: =ROUND(G43*100,6) -> 40 | H61: =ROUND(H43*100,6) -> 54 | I61: =ROUND(I43*100,6) -> 0 | J61: =INDEX($E61:$I61,1,$E$5+1) -> 30.5
C62: ÖSZ-3 eligible (gross wind ≥ net MVA, VII.16) | D62: 1 / 0 | E62: =(E61>=0)*1 -> 1 | F62: =(F61>=0)*1 -> 1 | G62: =(G61>=0)*1 -> 1 | H62: =(H61>=0)*1 -> 1 | I62: =(I61>=0)*1 -> 1 | J62: =INDEX($E62:$I62,1,$E$5+1) -> 1
C63: ÖSZ-3 band number (lookup) | D63: band | E63: =SUMPRODUCT(($D$117:$D$126<E61)+($D$117:$D$126=E61)*$E$117:$E$126) -> 7 | F63: =SUMPRODUCT(($D$117:$D$126<F61)+($D$117:$D$126=F61)*$E$117:$E$126) -> 9 | G63: =SUMPRODUCT(($D$117:$D$126<G61)+($D$117:$D$126=G61)*$E$117:$E$126) -> 9 | H63: =SUMPRODUCT(($D$117:$D$126<H61)+($D$117:$D$126=H61)*$E$117:$E$126) -> 10 | I63: =SUMPRODUCT(($D$117:$D$126<I61)+($D$117:$D$126=I61)*$E$117:$E$126) -> 0 | J63: =INDEX($E63:$I63,1,$E$5+1) -> 7
C64: ÖSZ-3 inner points | D64: 0–100 | E64: =INDEX($F$116:$F$126,E63+1)*E62 -> 70 | F64: =INDEX($F$116:$F$126,F63+1)*F62 -> 90 | G64: =INDEX($F$116:$F$126,G63+1)*G62 -> 90 | H64: =INDEX($F$116:$F$126,H63+1)*H62 -> 100 | I64: =INDEX($F$116:$F$126,I63+1)*I62 -> 0 | J64: =INDEX($E64:$I64,1,$E$5+1) -> 70
C65: ÖSZ-3 weighted points | D65: pts | E65: =E64*$E$155/100 -> 7 | F65: =F64*$E$155/100 -> 9 | G65: =G64*$E$155/100 -> 9 | H65: =H64*$E$155/100 -> 10 | I65: =I64*$E$155/100 -> 0 | J65: =INDEX($E65:$I65,1,$E$5+1) -> 7
C66: ÖSZ-4 BESS ratio x (6 dp) | D66: % | E66: =ROUND(E44*100,6) -> 34.482759 | F66: =ROUND(F44*100,6) -> 32.142857 | G66: =ROUND(G44*100,6) -> 32.142857 | H66: =ROUND(H44*100,6) -> 51 | I66: =ROUND(I44*100,6) -> 0 | J66: =INDEX($E66:$I66,1,$E$5+1) -> 34.482759
C67: ÖSZ-4 eligible (ratio ≥ min on installed wind, duration ≥ min, BESS MW ≤ wind MW) | D67: 1 / 0 | E67: =AND(E66>=$E$166,E$16>=$E$167,ROUND(E41,6)<=ROUND(E40,6))*1 -> 1 | F67: =AND(F66>=$E$166,F$16>=$E$167,ROUND(F41,6)<=ROUND(F40,6))*1 -> 1 | G67: =AND(G66>=$E$166,G$16>=$E$167,ROUND(G41,6)<=ROUND(G40,6))*1 -> 1 | H67: =AND(H66>=$E$166,H$16>=$E$167,ROUND(H41,6)<=ROUND(H40,6))*1 -> 1 | I67: =AND(I66>=$E$166,I$16>=$E$167,ROUND(I41,6)<=ROUND(I40,6))*1 -> 0 | J67: =INDEX($E67:$I67,1,$E$5+1) -> 1 | K67: ratio ≥ 5 % of installed wind (GYIK 20), duration ≥ 4 h, BESS MW ≤ gross wind MW (VII.13)
C68: ÖSZ-4 band number (lookup; GYIK 20: 40 ≤ x ≤ 50 → 90) | D68: band | E68: =SUMPRODUCT(($D$129:$D$138<E66)+($D$129:$D$138=E66)*$E$129:$E$138) -> 7 | F68: =SUMPRODUCT(($D$129:$D$138<F66)+($D$129:$D$138=F66)*$E$129:$E$138) -> 7 | G68: =SUMPRODUCT(($D$129:$D$138<G66)+($D$129:$D$138=G66)*$E$129:$E$138) -> 7 | H68: =SUMPRODUCT(($D$129:$D$138<H66)+($D$129:$D$138=H66)*$E$129:$E$138) -> 10 | I68: =SUMPRODUCT(($D$129:$D$138<I66)+($D$129:$D$138=I66)*$E$129:$E$138) -> 0 | J68: =INDEX($E68:$I68,1,$E$5+1) -> 7
C69: ÖSZ-4 inner points | D69: 0–100 | E69: =INDEX($F$128:$F$138,E68+1)*E67 -> 70 | F69: =INDEX($F$128:$F$138,F68+1)*F67 -> 70 | G69: =INDEX($F$128:$F$138,G68+1)*G67 -> 70 | H69: =INDEX($F$128:$F$138,H68+1)*H67 -> 100 | I69: =INDEX($F$128:$F$138,I68+1)*I67 -> 0 | J69: =INDEX($E69:$I69,1,$E$5+1) -> 70
C70: ÖSZ-4 weighted points | D70: pts | E70: =E69*$E$156/100 -> 10.5 | F70: =F69*$E$156/100 -> 10.5 | G70: =G69*$E$156/100 -> 10.5 | H70: =H69*$E$156/100 -> 15 | I70: =I69*$E$156/100 -> 0 | J70: =INDEX($E70:$I70,1,$E$5+1) -> 10.5
C71: ÖSZ-5 partial award accepted | D71: 1 / 0 | E71: =E$18 -> 0 | F71: =F$18 -> 1 | G71: =G$18 -> 1 | H71: =H$18 -> 1 | I71: =I$18 -> 0 | J71: =INDEX($E71:$I71,1,$E$5+1) -> 0
C72: ÖSZ-5 weighted points | D72: pts | E72: =E71*$E$168*$E$157/100 -> 0 | F72: =F71*$E$168*$E$157/100 -> 5 | G72: =G71*$E$168*$E$157/100 -> 5 | H72: =H71*$E$168*$E$157/100 -> 5 | I72: =I71*$E$168*$E$157/100 -> 0 | J72: =INDEX($E72:$I72,1,$E$5+1) -> 0
C73: ÖSZ-6 performance security x (6 dp) | D73: % of min | E73: =ROUND(E$17*100,6) -> 150 | F73: =ROUND(F$17*100,6) -> 160 | G73: =ROUND(G$17*100,6) -> 200 | H73: =ROUND(H$17*100,6) -> 210 | I73: =ROUND(I$17*100,6) -> 100 | J73: =INDEX($E73:$I73,1,$E$5+1) -> 150
C74: ÖSZ-6 band number (lookup; GYIK 34: 200 ≤ x → 100) | D74: band | E74: =SUMPRODUCT(($D$141:$D$150<E73)+($D$141:$D$150=E73)*$E$141:$E$150) -> 5 | F74: =SUMPRODUCT(($D$141:$D$150<F73)+($D$141:$D$150=F73)*$E$141:$E$150) -> 6 | G74: =SUMPRODUCT(($D$141:$D$150<G73)+($D$141:$D$150=G73)*$E$141:$E$150) -> 10 | H74: =SUMPRODUCT(($D$141:$D$150<H73)+($D$141:$D$150=H73)*$E$141:$E$150) -> 10 | I74: =SUMPRODUCT(($D$141:$D$150<I73)+($D$141:$D$150=I73)*$E$141:$E$150) -> 0 | J74: =INDEX($E74:$I74,1,$E$5+1) -> 5
C75: ÖSZ-6 inner points | D75: 0–100 | E75: =INDEX($F$140:$F$150,E74+1) -> 50 | F75: =INDEX($F$140:$F$150,F74+1) -> 60 | G75: =INDEX($F$140:$F$150,G74+1) -> 100 | H75: =INDEX($F$140:$F$150,H74+1) -> 100 | I75: =INDEX($F$140:$F$150,I74+1) -> 0 | J75: =INDEX($E75:$I75,1,$E$5+1) -> 50
C76: ÖSZ-6 weighted points | D76: pts | E76: =E75*$E$158/100 -> 2.5 | F76: =F75*$E$158/100 -> 3 | G76: =G75*$E$158/100 -> 5 | H76: =H75*$E$158/100 -> 5 | I76: =I75*$E$158/100 -> 0 | J76: =INDEX($E76:$I76,1,$E$5+1) -> 2.5
C77: ÖSZ-7 brownfield site | D77: 1 / 0 | E77: =E$19 -> 0 | F77: =F$19 -> 0 | G77: =G$19 -> 0 | H77: =H$19 -> 0 | I77: =I$19 -> 0 | J77: =INDEX($E77:$I77,1,$E$5+1) -> 0
C78: ÖSZ-7 weighted points | D78: pts | E78: =E77*$E$169*$E$159/100 -> 0 | F78: =F77*$E$169*$E$159/100 -> 0 | G78: =G77*$E$169*$E$159/100 -> 0 | H78: =H77*$E$169*$E$159/100 -> 0 | I78: =I77*$E$169*$E$159/100 -> 0 | J78: =INDEX($E78:$I78,1,$E$5+1) -> 0
C79: ÖSZ-8 shared connection point and line | D79: 1 / 0 | E79: =E$20 -> 0 | F79: =F$20 -> 1 | G79: =G$20 -> 1 | H79: =H$20 -> 1 | I79: =I$20 -> 0 | J79: =INDEX($E79:$I79,1,$E$5+1) -> 0
C80: ÖSZ-8 weighted points | D80: pts | E80: =E79*$E$170*$E$160/100 -> 0 | F80: =F79*$E$170*$E$160/100 -> 5 | G80: =G79*$E$170*$E$160/100 -> 5 | H80: =H79*$E$170*$E$160/100 -> 5 | I80: =I79*$E$170*$E$160/100 -> 0 | J80: =INDEX($E80:$I80,1,$E$5+1) -> 0
C81: ÖSZ-9 inner points – EU turbine (only with the EU-turbine commitment, row 22) + EU transformer (row 21) | D81: 0–100 | E81: =$E$171*E$22+$E$172*E$21 -> 80 | F81: =$E$171*F$22+$E$172*F$21 -> 100 | G81: =$E$171*G$22+$E$172*G$21 -> 100 | H81: =$E$171*H$22+$E$172*H$21 -> 100 | I81: =$E$171*I$22+$E$172*I$21 -> 0 | J81: =INDEX($E81:$I81,1,$E$5+1) -> 80
C82: ÖSZ-9 weighted points – European-turbine routes only | D82: pts EU | E82: =E81*$E$161/100 -> 12 | F82: =F81*$E$161/100 -> 15 | G82: =G81*$E$161/100 -> 15 | H82: =H81*$E$161/100 -> 15 | I82: =I81*$E$161/100 -> 0 | J82: =INDEX($E82:$I82,1,$E$5+1) -> 12 | K82: excluded from Σ (unit 'pts EU'); Chinese routes score 0 on ÖSZ-9
C83: Σ weighted points ÖSZ-1 … ÖSZ-8 (rows with unit 'pts') | D83: pts Σ | E83: =SUMIF($D$51:$D$82,"pts",E51:E82) -> 24 | F83: =SUMIF($D$51:$D$82,"pts",F51:F82) -> 36.5 | G83: =SUMIF($D$51:$D$82,"pts",G51:G82) -> 54.5 | H83: =SUMIF($D$51:$D$82,"pts",H51:H82) -> 75 | I83: =SUMIF($D$51:$D$82,"pts",I51:I82) -> 0 | J83: =INDEX($E83:$I83,1,$E$5+1) -> 24 | K83: SUMIF on the unit column
C84: TOTAL SCORE – European-turbine routes (RtB, cases 2 / 7), rounded to 2 dp | D84: points | E84: =ROUND(E83+E82,2) -> 36 | F84: =ROUND(F83+F82,2) -> 51.5 | G84: =ROUND(G83+G82,2) -> 69.5 | H84: =ROUND(H83+H82,2) -> 90 | I84: =ROUND(I83+I82,2) -> 0 | J84: =INDEX($E84:$I84,1,$E$5+1) -> 36 | K84: Σ + ÖSZ-9 weighted, ROUND 2 (X.1)
C85: TOTAL SCORE – Chinese-turbine routes (cases 3 / 8), rounded to 2 dp | D85: points | E85: =ROUND(E83,2) -> 24 | F85: =ROUND(F83,2) -> 36.5 | G85: =ROUND(G83,2) -> 54.5 | H85: =ROUND(H83,2) -> 75 | I85: =ROUND(I83,2) -> 0 | J85: =INDEX($E85:$I85,1,$E$5+1) -> 24 | K85: Σ only (no EU turbine, non-EU transformer)
C86: Score of the scenario (its turbine, row 22) | D86: points | E86: =IF(E$22=1,E84,E85) -> 36 | F86: =IF(F$22=1,F84,F85) -> 51.5 | G86: =IF(G$22=1,G84,G85) -> 69.5 | H86: =IF(H$22=1,H84,H85) -> 90 | I86: =IF(I$22=1,I84,I85) -> 0 | J86: =INDEX($E86:$I86,1,$E$5+1) -> 36
C87: Bid validity (gross wind ≥ net MVA, VII.16; ÖSZ-1 / ÖSZ-2 below the minimum → 0 points, not invalid – GYIK 17) | D87: Status | E87: =IF(E61>=0,"Valid","INVALID") -> Valid | F87: =IF(F61>=0,"Valid","INVALID") -> Valid | G87: =IF(G61>=0,"Valid","INVALID") -> Valid | H87: =IF(H61>=0,"Valid","INVALID") -> Valid | I87: =IF(I61>=0,"Valid","INVALID") -> Valid | J87: =INDEX($E87:$I87,1,$E$5+1) -> Valid
C88: Check path: EU total = Σ inner points × weight ÷ 100 (rounded, K3) | D88: points | E88: =ROUND((E54*$E$153+E59*$E$154+E64*$E$155+E69*$E$156+E71*$E$168*$E$157+E75*$E$158+E77*$E$169*$E$159+E79*$E$170*$E$160+E81*$E$161)/100,2) -> 36 | F88: =ROUND((F54*$E$153+F59*$E$154+F64*$E$155+F69*$E$156+F71*$E$168*$E$157+F75*$E$158+F77*$E$169*$E$159+F79*$E$170*$E$160+F81*$E$161)/100,2) -> 51.5 | G88: =ROUND((G54*$E$153+G59*$E$154+G64*$E$155+G69*$E$156+G71*$E$168*$E$157+G75*$E$158+G77*$E$169*$E$159+G79*$E$170*$E$160+G81*$E$161)/100,2) -> 69.5 | H88: =ROUND((H54*$E$153+H59*$E$154+H64*$E$155+H69*$E$156+H71*$E$168*$E$157+H75*$E$158+H77*$E$169*$E$159+H79*$E$170*$E$160+H81*$E$161)/100,2) -> 90 | I88: =ROUND((I54*$E$153+I59*$E$154+I64*$E$155+I69*$E$156+I71*$E$168*$E$157+I75*$E$158+I77*$E$169*$E$159+I79*$E$170*$E$160+I81*$E$161)/100,2) -> 0 | J88: =INDEX($E88:$I88,1,$E$5+1) -> 36
C90: 3. Annex 4 band tables (lookup – no nested IFs) and Annex 3 / X.4 parameters – MEKH Kapacitás pályázati kiírás 2026 (30-Aug-26), PDF pages in column G
C91: ÖSZ-1 municipal one-off – EUR/MW | D91: Lower bound | E91: Included 1/0 | F91: Inner points | G91: PDF page | H91: =IF(SUMPRODUCT(--(D94:D101<=D93:D100))=0,"OK","FAIL") -> OK
C92: below the lowest band (or not eligible) | F92: 0
C93: =IF(E93=1,"x ≥ ","x > ")&D93 -> x > 10000 | D93: 10000 | E93: 0 | F93: 10 | G93: 36–37
C94: =IF(E94=1,"x ≥ ","x > ")&D94 -> x > 15000 | D94: 15000 | E94: 0 | F94: 20 | G94: 36–37
C95: =IF(E95=1,"x ≥ ","x > ")&D95 -> x > 20000 | D95: 20000 | E95: 0 | F95: 30 | G95: 36–37
C96: =IF(E96=1,"x ≥ ","x > ")&D96 -> x > 25000 | D96: 25000 | E96: 0 | F96: 40 | G96: 36–37
C97: =IF(E97=1,"x ≥ ","x > ")&D97 -> x > 30000 | D97: 30000 | E97: 0 | F97: 55 | G97: 36–37
C98: =IF(E98=1,"x ≥ ","x > ")&D98 -> x > 35000 | D98: 35000 | E98: 0 | F98: 70 | G98: 36–37
C99: =IF(E99=1,"x ≥ ","x > ")&D99 -> x > 40000 | D99: 40000 | E99: 0 | F99: 80 | G99: 36–37
C100: =IF(E100=1,"x ≥ ","x > ")&D100 -> x > 45000 | D100: 45000 | E100: 0 | F100: 90 | G100: 36–37
C101: =IF(E101=1,"x ≥ ","x > ")&D101 -> x ≥ 50000 | D101: 50000 | E101: 1 | F101: 100 | G101: 36–37
C102: ÖSZ-2 annual community contribution – EUR/MWh | D102: Lower bound | E102: Included 1/0 | F102: Inner points | G102: PDF page | H102: =IF(SUMPRODUCT(--(D105:D114<=D104:D113))=0,"OK","FAIL") -> OK
C103: below the lowest band (or not eligible) | F103: 0
C104: =IF(E104=1,"x ≥ ","x > ")&D104 -> x > 2 | D104: 2 | E104: 0 | F104: 5 | G104: 37–38
C105: =IF(E105=1,"x ≥ ","x > ")&D105 -> x > 2.1 | D105: 2.1 | E105: 0 | F105: 10 | G105: 37–38
C106: =IF(E106=1,"x ≥ ","x > ")&D106 -> x > 2.2 | D106: 2.2 | E106: 0 | F106: 20 | G106: 37–38
C107: =IF(E107=1,"x ≥ ","x > ")&D107 -> x > 2.3 | D107: 2.3 | E107: 0 | F107: 30 | G107: 37–38
...

Sheet Dashboard
B1: HUN Onshore Wind – MOIC model v5
C2: Dashboard – results only. All inputs and the route / tender-scenario selectors are on the Control Panel; sections 1 onwards show results.
C3: Live: case / tender scenario (set on the Control Panel) → | E3: =Inputs!$E$7 -> FEP base case | F3: =Tender!$J$11 -> S1 – Current bid
C6: 1. Headline returns – sell at RTB (active case) vs hold-to-maturity with European / Chinese turbine | E6: Sell at RTB | F6: HTM – European turbine | G6: HTM – Chinese turbine
C7: Active case | D7: Name | E7: ="Case "&Inputs!$E$6&" – "&Inputs!E7 -> Case 1 – FEP base case | F7: ="Case 2 – "&Inputs!H7 -> Case 2 – European turbine | G7: ="Case 3 – "&Inputs!I7 -> Case 3 – Chinese turbine
C8: Case description | D8: Text | E8: =FIXED(Inputs!E141,0)&" k€/MW RTB premium × "&FIXED(Inputs!E150,0)&IF(Inputs!E149=1," MW installed wind (FLAG)"," MVA net")&", sale "&Inputs!E28&" months after RTB" -> 150 k€/MW RTB premium × 200 MVA net, sale 9 months after RTB | F8: =FIXED(IF(Inputs!H162="",Inputs!$G162,Inputs!H162),0)&" k€/MW, "&FIXED(IF(Inputs!H217="",Inputs!$G217,Inputs!H217)*100,0)&"% debt, PPA "&FIXED(IF(Inputs!H191="",Inputs!$G191,Inputs!H191),0)&" €/MWh" -> 950 k€/MW, 60% debt, PPA 90 €/MWh | G8: =FIXED(IF(Inputs!I162="",Inputs!$G162,Inputs!I162),0)&" k€/MW, "&FIXED(IF(Inputs!I217="",Inputs!$G217,Inputs!I217)*100,0)&"% debt, PPA "&FIXED(IF(Inputs!I191="",Inputs!$G191,Inputs!I191),0)&" €/MWh" -> 500 k€/MW, 50% debt, PPA 90 €/MWh
C9: Successful capacity – net grid / gross wind | D9: MW | E9: =TEXT(Inputs!E18,"0")&" / "&TEXT(Inputs!E29,"0") -> 200 / 261 | F9: =TEXT(Inputs!$E$18,"0")&" / "&TEXT(Inputs!$E$29,"0") -> 200 / 261 | G9: =TEXT(Inputs!$E$18,"0")&" / "&TEXT(Inputs!$E$29,"0") -> 200 / 261
C10: Exit / price basis | D10: k€/MW | €/MWh | E10: =Inputs!E141 -> 150 | F10: =E218 -> 136.7236 | G10: =F218 -> 136.7236
C11: Gross proceeds / lifetime revenue | D11: k€ | E11: =MOIC!G171 -> 64143.615 | F11: =E219 -> 2358431.6 | G11: =F219 -> 2358431.6
C12: FEP net profit (pre-tax) – MOIC basis (after signing fee, DD, guarantee fees; before cost of capital) | D12: k€ / mHUF | E12: =FIXED(MOIC!$G$172,0)&" / "&FIXED(MOIC!$G$172*Inputs!$E$11/1000,0) -> 15,526 / 5,667 | F12: =FIXED(E223,0)&" / "&FIXED(E223*Inputs!$E$11/1000,0) -> 1,254,061 / 457,732 | G12: =FIXED(F223,0)&" / "&FIXED(F223*Inputs!$E$11/1000,0) -> 1,431,277 / 522,416
C13: FEP net profit (pre-tax) – Case B: with cost of capital | D13: k€ / mHUF | E13: =FIXED($L$40,0)&" / "&FIXED(($L$40)*Inputs!$E$11/1000,0) -> 10,273 / 3,750 | F13: - | G13: -
C14: FEP net profit (post-tax) – MOIC basis (MOIC G182; basis of headline MOIC / IRR) | D14: k€ / mHUF | E14: =FIXED(MOIC!$G$182,0)&" / "&FIXED(MOIC!$G$182*Inputs!$E$11/1000,0) -> 15,174 / 5,538 | F14: =FIXED(E224,0)&" / "&FIXED(E224*Inputs!$E$11/1000,0) -> 1,137,959 / 415,355 | G14: =FIXED(F224,0)&" / "&FIXED(F224*Inputs!$E$11/1000,0) -> 1,299,225 / 474,217
C15: FEP net profit (post-tax) – Case B: with cost of capital | D15: k€ / mHUF | E15: =FIXED($L$42,0)&" / "&FIXED(($L$42)*Inputs!$E$11/1000,0) -> 9,921 / 3,621 | F15: - | G15: -
C16: FEP MOIC | D16: x | E16: =MOIC!G186 -> 1.3121055 | F16: =E228 -> 6.133291 | G16: =F228 -> 7.7915901
C17: FEP IRR (post-tax) | D17: % | E17: =MOIC!G187 -> 0.20894449 | F17: =E225 -> 0.09991356 | G17: =F225 -> 0.13111233
C18: FEP NPV (post-tax) at NPV / Equity rate (Inputs E253) | D18: k€ | E18: =MOIC!G192 -> 7253.3564 | F18: =E226 -> 62081.307 | G18: =F226 -> 139279.29
C19: FEP NPV / Equity (NPV ÷ PV of equity invested) | D19: x | E19: =MOIC!G194 -> 0.17787568 | F19: =E227 -> 0.37667365 | G19: =F227 -> 0.97347376
C20: Project IRR – unlevered, post-tax | D20: % | E20: n/a | F20: =E233 -> 0.091701924 | G20: =F233 -> 0.12109681
C21: FEP peak cumulative exposure | D21: k€ | E21: =MOIC!G188 -> 48525.878 | F21: =E229 -> 221682.18 | G21: =F229 -> 191299.15
C22: FEP peak cumulative exposure | D22: mHUF | E22: =MOIC!G189 -> 17711.945 | F22: =F21*Inputs!$E$11/1000 -> 80913.997 | G22: =G21*Inputs!$E$11/1000 -> 69824.188
C23: Economic profit (RTB) / project NPV (HTM) | D23: k€ | E23: =MOIC!G190 -> 9943.1039 | F23: =E234 -> 47524.011 | G23: =F234 -> 133488.73
C24: Timeline | D24: Text | E24: =CHOOSE(MONTH(Inputs!E27),"Jan","Feb","Mar","Apr","May","Jun","Jul","Aug","Sep","Oct","Nov","Dec")&"-"&RIGHT(YEAR(Inputs!E27),2)&" → RTB "&CHOOSE(MONTH(Inputs!E56),"Jan","Feb","Mar","Apr","May","Jun","Jul","Aug","Sep","Oct","Nov","Dec")&"-"&RIGHT(YEAR(Inputs!E56),2)&" → sale "&CHOOSE(MONTH(Inputs!E58),"Jan","Feb","Mar","Apr","May","Jun","Jul","Aug","Sep","Oct","Nov","Dec")&"-"&RIGHT(YEAR(Inputs!E58),2) -> Jul-26 → RTB Jun-29 → sale Mar-30 | F24: ="COD "&CHOOSE(MONTH(Inputs!$E$155),"Jan","Feb","Mar","Apr","May","Jun","Jul","Aug","Sep","Oct","Nov","Dec")&"-"&RIGHT(YEAR(Inputs!$E$155),2)&" → capex "&FIXED(E212,0)&" k€/MW → payback "&E230 -> COD Sep-31 → capex 2,156 k€/MW → payback 2044 | G24: ="COD "&CHOOSE(MONTH(Inputs!$E$155),"Jan","Feb","Mar","Apr","May","Jun","Jul","Aug","Sep","Oct","Nov","Dec")&"-"&RIGHT(YEAR(Inputs!$E$155),2)&" → capex "&FIXED(F212,0)&" k€/MW → payback "&F230 -> COD Sep-31 → capex 1,533 k€/MW → payback 2041
C25: Integrity checks | D25: Status | E25: =MOIC!G270 -> ALL OK | F25: =E240 -> ALL OK | G25: =F240 -> ALL OK
C26: Sell-at-RTB column follows the active case (Inputs E6). European / Chinese columns (F–G) link to section 11 (live – Control Panel data table, active tender scenario). Tender local-benefit commitments (20 k€/MW one-off at COD, 2 €/MWh on generation) sit in HTM only; a buyer at RTB inherits them, so read the RTB premium as gross of the 20 k€/MW.
C27: 2. FEP sources & uses to exit (cash actually funded by FEP; k€ and mHUF at Inputs FX) | H27: ="FEP profit – two cases (sale "&DAY(Inputs!E58)&"/"&TEXT(MONTH(Inputs!E58),"00")&"/"&YEAR(Inputs!E58)&"; "&LEFT(Inputs!$F$64,FIND(":",Inputs!$F$64)-1)&")" -> FEP profit – two cases (sale 31/03/2030; Interest pause 30/06/2029 – 01/01/2030) | K27: Case A: profit bridge – before deal costs, guarantee fees and cost of capital (not a headline) | L27: Case B: with cost of capital
C28: Uses | E28: k€ | F28: mHUF | H28: Interest on recoverable loan (12 % per line to the RtB sale, interest pause excluded: cash TSO bond, connection fees, participation fee) | J28: k€ | K28: =Deposits!$Y$23+Deposits!$Y$24 -> 4370.0331 | L28: =K28 -> 4370.0331
C29: DD and transaction costs | D29: k€ | E29: =-MOIC!G159 -> 150 | F29: =E29*Inputs!$E$11/1000 -> 54.75 | H29: Interest on at-risk loan (20%) | J29: k€ | K29: =MOIC!G126 -> 0 | L29: =K29 -> 0
C30: Signing fee | D30: k€ | E30: =-MOIC!G158 -> 250 | F30: =E30*Inputs!$E$11/1000 -> 91.25 | H30: Return on at-risk devex and land: MAX(20 % to the RtB sale excl. the pause, 2×) – principal × 1 | J30: k€ | K30: =MOIC!G131 -> 3087.8459 | L30: =K30 -> 3087.8459
C31: Devex (FEP-funded share, incl. land costs reimbursed by buyer at RtB exit) | D31: k€ | E31: =-MOIC!G162 -> 3087.8459 | F31: =E31*Inputs!$E$11/1000 -> 1127.0638 | H31: Interest on bank-guaranteed securities (6%) | J31: k€ | K31: =MOIC!G169 -> 3219.9262 | L31: =K31 -> 3219.9262
C32: Securities and connection fee – cash posted, net of pre-sale refunds (FEP share) | D32: k€ | E32: =-(MOIC!G160+MOIC!G161) -> 41448.238 | F32: =E32*Inputs!$E$11/1000 -> 15128.607 | H32: Total interest earned by FEP | J32: k€ | K32: =SUM(K28:K31) -> 10677.805 | L32: =SUM(L28:L31) -> 10677.805
C33: Bank guarantee fees | D33: k€ | E33: =-MOIC!G163 -> 3681.2145 | F33: =E33*Inputs!$E$11/1000 -> 1343.6433 | H33: FEP 70% share of distributable proceeds | J33: k€ | K33: =MOIC!G170 -> 11608.63 | L33: =K33 -> 11608.63
C34: Total uses | D34: k€ | E34: =SUM(E29:E33) -> 48617.299 | F34: =E34*Inputs!$E$11/1000 -> 17745.314 | H34: Less: devex and participation fee carried by FEP (not repaid; land costs repaid by buyer at RtB exit added back) | J34: k€ | K34: =MOIC!G162+MOIC!G161+MOIC!G167 -> -2678.9045 | L34: =K34 -> -2678.9045
H35: FEP profit before costs of capital and deal costs | J35: k€ | K35: =K32+K33+K34 -> 19607.531 | L35: =L32+L33+L34 -> 19607.531
C36: Sources | E36: k€ | F36: mHUF | H36: Less: signing fee | J36: k€ | K36: 0 | L36: =MOIC!G158 -> -250
C37: FEP equity (signing fee + transaction costs) | D37: k€ | E37: =-(MOIC!G158+MOIC!G159) -> 400 | F37: =E37*Inputs!$E$11/1000 -> 146 | H37: Less: DD and transaction costs | J37: k€ | K37: 0 | L37: =MOIC!G159 -> -150
C38: FEP shareholder loan – recoverable (refunded if the project fails) | D38: k€ | E38: =-MOIC!G160 -> 41431.8 | F38: =E38*Inputs!$E$11/1000 -> 15122.607 | H38: Less: bank guarantee fees (guarantee price on guaranteed securities) | J38: k€ | K38: 0 | L38: =MOIC!G163 -> -3681.2145
C39: FEP shareholder loan – at-risk (devex and land costs; all deposits and grid bonds are refunded on failure) | D39: k€ | E39: =-(MOIC!G161+MOIC!G162) -> 3104.2843 | F39: =E39*Inputs!$E$11/1000 -> 1133.0638 | H39: Less: cost of capital on cash-funded items (Inputs E72) | J39: k€ | K39: 0 | L39: =-MOIC!G200 -> -5253.0928
C40: FEP direct funding of guarantee fees | D40: k€ | E40: =-MOIC!G163 -> 3681.2145 | F40: =E40*Inputs!$E$11/1000 -> 1343.6433 | H40: FEP net profit (pre-tax) | J40: k€ | K40: =SUM(K35:K39) -> 19607.531 | L40: =SUM(L35:L39) -> 10273.223
C41: Total sources | D41: k€ | E41: =SUM(E37:E40) -> 48617.299 | F41: =E41*Inputs!$E$11/1000 -> 17745.314 | H41: Less: corporate income tax – actual tax per MOIC G174 (70% share gain exempt under participation exemption, Inputs E14; interest and top-up taxable) | J41: k€ | K41: =MOIC!$G$174 -> -352.59175 | L41: =MOIC!G174 -> -352.59175
C42: Sources = Uses | D42: Check | E42: =IF(ABS(E34-E41)<0.01,"OK","FAIL") -> OK | H42: FEP net profit (post-tax) | J42: k€ | K42: =K40+K41 -> 19254.939 | L42: =L40+L41 -> 9920.6317
C43: Memo: expected buyer reimbursement of securities and connection fee at exit | D43: k€ | E43: =MOIC!G144 -> 41857.18 | F43: =E43*Inputs!$E$11/1000 -> 15277.871 | H43: Check: Case B excl. cost of capital ties to MOIC net cash flow (G172 / G182, before the community purchase right, MOIC G284:G286) | J43: Check | L43: =IF(AND(ABS(L40-L39-MOIC!G172+SUM(MOIC!G284:G286))<Tender!$E$32,ABS(L42-L39-MOIC!G182+SUM(MOIC!G284:G286))<Tender!$E$32),"OK","ERROR") -> OK
C44: Memo: at-risk spend to RTB (total uses less reimbursable securities) | D44: k€ | E44: =E34-E43 -> 6760.1191 | F44: =E44*Inputs!$E$11/1000 -> 2467.4435
C45: Memo: contingent exposure if every bank guarantee is called (cash invested + guarantee-backed securities) | D45: k€ | E45: =E34+Deposits!$E$27 -> 66901.477 | F45: =E45*Inputs!$E$11/1000 -> 24419.039
H46: Tie-out vs BORA Devex file 01-Oct-26 (HISTORIC snapshot: column J typed from that file – freeze 30/06/2029, exit 31/12/2029). Current reconciliation vs BORA_Devex_20261002_BG: CHECKS §14
C47: 3. Exit proceeds waterfall (€k) – active case | E47: k€ | F47: mHUF | H47: Bucket | J47: Devex file 01-Oct-26 (historic, typed) | K47: Our model | L47: Difference
C48: RTB premium proceeds | D48: k€ | E48: =MOIC!G143 -> 30000 | F48: =E48*Inputs!$E$11/1000 -> 10950 | H48: Devex principal incl. contingency and participation fee (carried by FEP; land excluded – reimbursed by buyer) | J48: 2678.6602 | K48: =Devex_FEP!$H$39+MOIC!G44 -> 2678.9045 | L48: =K48-J48 -> 0.24435394
C49: Recovery of securities and connection fee (buyer reimbursement) | D49: k€ | E49: =MOIC!G144 -> 41857.18 | F49: =E49*Inputs!$E$11/1000 -> 15277.871 | H49: 12% interest – cash TSO bond + connection fees + participation fee | J49: 3012.0184 | K49: =Deposits!$Y$23+Deposits!$Y$24 -> 4370.0331 | L49: =K49-J49 -> 1358.0148
C50: Total proceeds | D50: k€ | E50: =MOIC!G145 -> 71857.18 | F50: =E50*Inputs!$E$11/1000 -> 26227.871 | H50: 6% interest – bank-guaranteed securities | J50: 2464.1755 | K50: =Deposits!$Y$22 -> 3219.9262 | L50: =K50-J50 -> 755.75066
C51: Less: sale costs | D51: k€ | E51: =MOIC!G146 -> -500 | F51: =E51*Inputs!$E$11/1000 -> -182.5 | H51: 20% at-risk devex and land – minimum 2× (return on principal) | J51: 3087.8237 | K51: =MOIC!G131 -> 3087.8459 | L51: =K51-J51 -> 0.022213995
C52: Less: repayment of recoverable loans | D52: k€ | E52: =MOIC!G147 -> -45795.312 | F52: =E52*Inputs!$E$11/1000 -> -16715.289 | H52: Total FEP interest | J52: =SUM(J49:J51) -> 8564.0176 | K52: =SUM(K49:K51) -> 10677.805 | L52: =K52-J52 -> 2113.7876
C53: Less: repayment of unrecoverable loans | D53: k€ | E53: =MOIC!G148 -> -425.37973 | F53: =E53*Inputs!$E$11/1000 -> -155.2636 | H53: DSA / developer success fee | J53: 1590.2778 | K53: =-MOIC!G151 -> 2238.4375 | L53: =K53-J53 -> 648.15972
C54: Less: minimum-return top-up | D54: k€ | E54: =MOIC!G149 -> -3094.3672 | F54: =E54*Inputs!$E$11/1000 -> -1129.444 | H54: Sale costs | J54: 500 | K54: =-MOIC!G146 -> 500 | L54: =K54-J54 -> 0
C55: Less: interest on bank-guaranteed securities (FEP + Developer) | D55: k€ | E55: =MOIC!G150 -> -3219.9262 | F55: =E55*Inputs!$E$11/1000 -> -1175.2731 | H55: Distributable proceeds (premium − sale costs − interest − DSA) | J55: 19345.707 | K55: =MOIC!G152 -> 16583.757 | L55: =K55-J55 -> -2761.9502
C56: Less: developer success fee | D56: k€ | E56: =MOIC!G151 -> -2238.4375 | F56: =E56*Inputs!$E$11/1000 -> -817.02969 | H56: FEP 70% share | J56: 13541.995 | K56: =MOIC!G153 -> 11608.63 | L56: =K56-J56 -> -1933.3652
C57: Distributable proceeds | D57: k€ | E57: =MOIC!G152 -> 16583.757 | F57: =E57*Inputs!$E$11/1000 -> 6053.0714 | H57: FEP profit, interest + share − devex (Case A) | J57: 19427.35 | K57: =K35 -> 19607.531 | L57: =K57-J57 -> 180.18099
C58: To FEP | D58: k€ | E58: =MOIC!G153 -> 11608.63 | F58: =E58*Inputs!$E$11/1000 -> 4237.15 | H58: Case B deductions: signing, DD, guarantee fees, cost of capital (not in Devex file – our figures applied to both columns) | J58: =K58 -> -9334.3073 | K58: =SUM(L36:L39) -> -9334.3073 | L58: =K58-J58 -> 0
C59: To Developer | D59: k€ | E59: =MOIC!G154 -> 4975.1272 | F59: =E59*Inputs!$E$11/1000 -> 1815.9214 | H59: FEP net profit pre-tax (Devex = Case A; ours = Case B) | J59: =J57+J58 -> 10093.042 | K59: =L40 -> 10273.223 | L59: =K59-J59 -> 180.18099
H60: Column J is a typed snapshot of the BORA Devex file of 01-Oct-26 (historic). The model has moved since (COD Sep-2031 → sale 31/03/2030, interest pause to 01/01/2030, BORA_Devex waterfall), so the differences are not errors. At the inputs of BORA_Devex_20261002_BG the model reproduces that file exactly (tools/devex_recon.py, CHECKS §14).
C61: 4. FEP returns sensitised to RTB sale premium (all other inputs at the active case)
C62: RTB sale premium | D62: k€/MW | E62: =MOIC!H225 -> 50 | F62: =MOIC!I225 -> 75 | G62: =MOIC!J225 -> 100 | H62: =MOIC!K225 -> 125 | I62: =MOIC!L225 -> 150 | J62: =MOIC!M225 -> 175 | K62: =MOIC!N225 -> 200
C63: FEP net profit | D63: k€ | E63: =MOIC!H238 -> 1173.7245 | F63: =MOIC!I238 -> 4673.7245 | G63: =MOIC!J238 -> 8173.7245 | H63: =MOIC!K238 -> 11673.724 | I63: =MOIC!L238 -> 15173.724 | J63: =MOIC!M238 -> 18673.724 | K63: =MOIC!N238 -> 22173.724
C64: FEP net profit | D64: mHUF | E64: =MOIC!H239 -> 428.40944 | F64: =MOIC!I239 -> 1705.9094 | G64: =MOIC!J239 -> 2983.4094 | H64: =MOIC!K239 -> 4260.9094 | I64: =MOIC!L239 -> 5538.4094 | J64: =MOIC!M239 -> 6815.9094 | K64: =MOIC!N239 -> 8093.4094
C65: MOIC | D65: x | E65: =MOIC!H240 -> 1.0241421 | F65: =MOIC!I240 -> 1.096133 | G65: =MOIC!J240 -> 1.1681238 | H65: =MOIC!K240 -> 1.2401146 | I65: =MOIC!L240 -> 1.3121055 | J65: =MOIC!M240 -> 1.3840963 | K65: =MOIC!N240 -> 1.4560871
C66: IRR (post-tax) | D66: % | E66: =MOIC!H241 -> 0.017274138 | F66: =MOIC!I241 -> 0.067606586 | G66: =MOIC!J241 -> 0.11626122 | H66: =MOIC!K241 -> 0.16334204 | I66: =MOIC!L241 -> 0.20894449 | J66: =MOIC!M241 -> 0.25315638 | K66: =MOIC!N241 -> 0.29605859
C67: FEP NPV / Equity | D67: x | E67: =MOIC!H243 -> -0.080999713 | F67: =MOIC!I243 -> -0.016280866 | G67: =MOIC!J243 -> 0.048437982 | H67: =MOIC!K243 -> 0.11315683 | I67: =MOIC!L243 -> 0.17787568 | J67: =MOIC!M243 -> 0.24259453 | K67: =MOIC!N243 -> 0.30731337
C68: Sense check: buyer unlevered post-tax IRR at this price (HTM 14b) | D68: % | E68: =HTM!F227 -> 0.11601918 | F68: =HTM!F228 -> 0.11468946 | G68: =HTM!F229 -> 0.11338497 | H68: =HTM!F230 -> 0.11210491 | I68: =HTM!F231 -> 0.11084851 | J68: =HTM!F232 -> 0.10961501 | K68: =HTM!F233 -> 0.1084037
C69: Sense check: buyer levered equity IRR at this price (HTM 14c) | D69: % | E69: =HTM!F237 -> 0.13048531 | F69: =HTM!F238 -> 0.12847171 | G69: =HTM!F239 -> 0.12651969 | H69: =HTM!F240 -> 0.12462596 | I69: =HTM!F241 -> 0.12278745 | J69: =HTM!F242 -> 0.1210013 | K69: =HTM!F243 -> 0.1192649
C70: Active case marker | E70: =IF(E62=Inputs!$E$141,"◄ active","") | F70: =IF(F62=Inputs!$E$141,"◄ active","") | G70: =IF(G62=Inputs!$E$141,"◄ active","") | H70: =IF(H62=Inputs!$E$141,"◄ active","") | I70: =IF(I62=Inputs!$E$141,"◄ active","") -> ◄ active | J70: =IF(J62=Inputs!$E$141,"◄ active","") | K70: =IF(K62=Inputs!$E$141,"◄ active","")
C71: Only exit proceeds move across the columns; devex, deposits, loans and timing are held at the active case. Recovery of securities is assumed identical in every column.
C74: 5. Tender securities and grid connection – summary (Deposits sheet)
C75: Gross securities and fees – model capacity | D75: mHUF | E75: =Deposits!E22 -> 23592.162
C76: Actually payable after netting – model capacity | D76: mHUF | E76: =Deposits!E23 -> 21802.332
C77: Actually payable – model capacity | D77: k€ | E77: =Deposits!E24 -> 59732.416
C78: Included in FEP cash flows (pre-sale instalments) | D78: k€ | E78: =Deposits!E25 -> 59732.416
C79: Of which cash-settled | D79: k€ | E79: =Deposits!E26 -> 41448.238
C80: Of which guarantee-backed | D80: k€ | E80: =Deposits!E27 -> 18284.178
C81: Reconciliation to source table at 280 MW | D81: Status | E81: =Deposits!E34 -> n/a – inputs differ from BORA_Devex source
C84: 6. Integrity checks (from MOIC block 14)
C85: =MOIC!C254 -> Deposits schedule reconciles to source table at reference capacity | E85: =MOIC!G254 -> n/a – inputs differ from BORA_Devex source
C86: =MOIC!C255 -> FEP recoverable loan closes to nil | E86: =MOIC!G255 -> OK
C87: =MOIC!C256 -> FEP unrecoverable loan closes to nil | E87: =MOIC!G256 -> OK
C88: =MOIC!C257 -> Developer loans close to nil | E88: =MOIC!G257 -> OK
C89: =MOIC!C258 -> Guarantee balance nil at end of grid | E89: =MOIC!G258 -> OK
C90: =MOIC!C259 -> Proceeds conserved through the cash flows: FEP inflows (rows 166–170) + developer inflows (rows 209–213) + sale costs = total proceeds G145 | E90: =MOIC!G259 -> OK
C91: =MOIC!C260 -> Developer's take through its cash flows (rows 212 + 213) = MAX(0, success fee + distributable × Inputs E34) – BORA_Devex V44 with the floor | E91: =MOIC!G260 -> OK
C92: =MOIC!C261 -> Devex spent equals Devex_FEP total (BORA Devex line items) | E92: =MOIC!G261 -> OK
C93: =MOIC!C262 -> Success fee within cap (Inputs E37 × installed wind MW Inputs E29) | E93: =MOIC!G262 -> OK
C94: =MOIC!C263 -> Sale month inside the grid | E94: =MOIC!G263 -> OK
C95: =MOIC!C264 -> All included deposit payments fall inside the grid | E95: =MOIC!G264 -> OK
C96: =MOIC!C265 -> Key outputs are numeric | E96: =MOIC!G265 -> OK
... C101: =MOIC!C270 -> OVERALL STATUS (rows 254–269 and the Tender checks in row 271; no WARNING state since round 5 – the economic outcome is an info line: MOIC G156, HTM G380, Run_Map row 54) | E101: =MOIC!G270 -> ALL OK
C104: 7. HTM (build & operate) returns – active case, nominal k€ (HTM sheet; estimates in yellow on Inputs sections I–P)
C105: Price source in use | D105: Text | E105: =IF(Inputs!E186=1,"Aurora curve (Curves)","Flat estimate (Inputs L)") -> Aurora curve (Curves)
C106: Capex incl. connection fee | D106: k€ | E106: =HTM!G149 -> 431201.3 | F106: =E106*Inputs!$E$11/1000 -> 157388.47 | G106: mHUF
C107: Capex per MW (all-in) | D107: k€/MW | E107: =HTM!G150 -> 2156.0065
C108: 7a. Capex breakdown – all construction capex items, per MW and total (Inputs J, Deposits, Inputs Q)
C109: Item | D109: Basis | E109: k€/MW | F109: Total k€ | G109: % of total
C110: Turbine supply incl. transport | D110: per MW | E110: =F110/Inputs!$E$18 -> 1239.75 | F110: =Inputs!$E$162*Inputs!$E$29 -> 247950 | G110: =F110/$F$127 -> 0.57502146
C111: Turbine installation and erection | D111: per MW | E111: =F111/Inputs!$E$18 -> 104.4 | F111: =Inputs!$E$163*Inputs!$E$29 -> 20880 | G111: =F111/$F$127 -> 0.04842286
C112: Turbines (WTG) subtotal | E112: =F112/Inputs!$E$18 -> 1344.15 | F112: =SUM(F110:F111) -> 268830 | G112: =F112/$F$127 -> 0.62344432
...

Sheet Bora
B1: =Inputs!G279&" – "&TEXT(Inputs!G281,"0")&" MW net grid / "&TEXT(Inputs!G297,"0")&" MW gross onshore wind, grid node "&Inputs!G280 -> Bora – 200 MW net grid / 261 MW gross onshore wind, grid node Szombathely OVIT (SZHO B 132.00)
B2: Project model view – sell at RTB, hold to maturity and sale at COD, each with European / Chinese turbine. Section A: live inputs; section B: all routes of the active tender scenario (live – Control Panel data table).
B4: A. Project inputs (live – Inputs block M)
B5: Input | C5: Unit | D5: Value | G5: Source / note
B6: Grid node (hálózati csomópont) | C6: Name | D6: =Inputs!G280 -> Szombathely OVIT (SZHO B 132.00) | G6: MEKH/MAVIR Kapacitás pályázati kiírás 2026, Annex 1
B7: Net grid connection capacity | C7: MW | D7: =Inputs!G281 -> 200 | G7: Annex 1 (1 MVA = 1 MW) – RTB premium (default basis, Inputs E149), grid fees, TSO bond; the success fee (DSA) is on the installed wind MW (row 18)
B8: BESS connection capacity / storage | C8: MW | D8: =Inputs!G282 -> 90 | G8: 4-hour duration (Inputs E21)
B9: Signing fee to current owners | C9: k€ | D9: =Inputs!G283 -> 250
B10: FEP share of RTB proceeds | C10: % | D10: =IF(Inputs!G284=1,Inputs!G285,1) -> 0.7 | G10: 70/30 JV with developer
B11: Number of tender bids | C11: # | D11: =Inputs!G287 -> 2 | G11: Participation fee per bid
B12: Indirect connection fee | C12: Ft/MVA | D12: =Inputs!G288 -> 73071306 | G12: Annex 1 – fajlagos várható közvetett csatlakozási díj
B13: Direct connection investment | C13: Ft | D13: =Inputs!G289 -> 508345804 | G13: Annex 1 – per connection point (TMÁ)
B14: Indirect / direct connection fee per MW | C14: mHUF/MW | D14: =FIXED(Inputs!G290,3)&" / "&FIXED(Inputs!G291,3) -> 73.071 / 2.542
B15: Devex – total incl. contingency (target) | C15: k€ | D15: =Inputs!G292 -> 3137.8459 | G15: Devex_FEP line items × scaling factor
B16: Devex scaling factor vs BORA Devex | C16: x | D16: =Inputs!G294 -> 1
B17: RTB exit premium | C17: k€/MW | D17: =Inputs!$E$141 -> 150 | G17: RtB premium (Control Panel section c)
B18: Gross installed wind capacity (overbuild) | C18: MW | D18: =Inputs!G297 -> 261 | G18: Munka1 – bid / performance bonds, turbine & BOP capex, generation, opex
B19: B. Returns – all routes of the active tender scenario (live, Control Panel data table): Sell at RTB | Hold-to-maturity European | Hold-to-maturity Chinese | Sale at COD European | Sale at COD Chinese
B20: Metric | C20: Unit | D20: Sell at RTB | E20: HTM – European | F20: HTM – Chinese | G20: Sale at COD – European | H20: Sale at COD – Chinese | I20: Note
B21: FEP headline returns
B22: FEP net profit (pre-tax) | C22: k€ | D22: =INDEX('Control Panel'!$G$306:$G$330,Tender!$E$5*5+1) -> 15526.316 | E22: =INDEX('Control Panel'!$G$306:$G$330,Tender!$E$5*5+4) -> 1254061.3 | F22: =INDEX('Control Panel'!$G$306:$G$330,Tender!$E$5*5+5) -> 1431276.9 | G22: =INDEX('Control Panel'!$G$306:$G$330,Tender!$E$5*5+2) -> 103211.98 | H22: =INDEX('Control Panel'!$G$306:$G$330,Tender!$E$5*5+3) -> 135331.94 | I22: RTB: MOIC basis (G172 / G182) – after deal costs and guarantee fees, before cost of capital
B23: FEP net profit (post-tax) | C23: k€ | D23: =INDEX('Control Panel'!$H$306:$H$330,Tender!$E$5*5+1) -> 15173.724 | E23: =INDEX('Control Panel'!$H$306:$H$330,Tender!$E$5*5+4) -> 1137959.2 | F23: =INDEX('Control Panel'!$H$306:$H$330,Tender!$E$5*5+5) -> 1299225.4 | G23: =INDEX('Control Panel'!$H$306:$H$330,Tender!$E$5*5+2) -> 103211.98 | H23: =INDEX('Control Panel'!$H$306:$H$330,Tender!$E$5*5+3) -> 135331.94
B24: FEP IRR (post-tax) | C24: % | D24: =INDEX('Control Panel'!$I$306:$I$330,Tender!$E$5*5+1) -> 0.20894449 | E24: =INDEX('Control Panel'!$I$306:$I$330,Tender!$E$5*5+4) -> 0.09991356 | F24: =INDEX('Control Panel'!$I$306:$I$330,Tender!$E$5*5+5) -> 0.13111233 | G24: =INDEX('Control Panel'!$I$306:$I$330,Tender!$E$5*5+2) -> 0.31364238 | H24: =INDEX('Control Panel'!$I$306:$I$330,Tender!$E$5*5+3) -> 0.42123413 | I24: RTB: all cash
B25: FEP NPV (post-tax, Inputs E253 rate) | C25: k€ | D25: =INDEX('Control Panel'!$J$306:$J$330,Tender!$E$5*5+1) -> 7253.3564 | E25: =INDEX('Control Panel'!$J$306:$J$330,Tender!$E$5*5+4) -> 62081.307 | F25: =INDEX('Control Panel'!$J$306:$J$330,Tender!$E$5*5+5) -> 139279.29 | G25: =INDEX('Control Panel'!$J$306:$J$330,Tender!$E$5*5+2) -> 57524.989 | H25: =INDEX('Control Panel'!$J$306:$J$330,Tender!$E$5*5+3) -> 80447.169
B26: FEP NPV / Equity | C26: x | D26: =INDEX('Control Panel'!$K$306:$K$330,Tender!$E$5*5+1) -> 0.17787568 | E26: =INDEX('Control Panel'!$K$306:$K$330,Tender!$E$5*5+4) -> 0.37667365 | F26: =INDEX('Control Panel'!$K$306:$K$330,Tender!$E$5*5+5) -> 0.97347376 | G26: =INDEX('Control Panel'!$K$306:$K$330,Tender!$E$5*5+2) -> 0.4009341 | H26: =INDEX('Control Panel'!$K$306:$K$330,Tender!$E$5*5+3) -> 0.6310593
B27: FEP MOIC | C27: x | D27: =INDEX('Control Panel'!$L$306:$L$330,Tender!$E$5*5+1) -> 1.3121055 | E27: =INDEX('Control Panel'!$L$306:$L$330,Tender!$E$5*5+4) -> 6.133291 | F27: =INDEX('Control Panel'!$L$306:$L$330,Tender!$E$5*5+5) -> 7.7915901 | G27: =INDEX('Control Panel'!$L$306:$L$330,Tender!$E$5*5+2) -> 1.5372084 | H27: =INDEX('Control Panel'!$L$306:$L$330,Tender!$E$5*5+3) -> 1.7952252 | I27: RTB: all cash
B28: FEP peak cumulative exposure | C28: k€ | D28: =INDEX('Control Panel'!$M$306:$M$330,Tender!$E$5*5+1) -> 48525.878 | E28: =INDEX('Control Panel'!$M$306:$M$330,Tender!$E$5*5+4) -> 221682.18 | F28: =INDEX('Control Panel'!$M$306:$M$330,Tender!$E$5*5+5) -> 191299.15 | G28: =INDEX('Control Panel'!$M$306:$M$330,Tender!$E$5*5+2) -> 192126.5 | H28: =INDEX('Control Panel'!$M$306:$M$330,Tender!$E$5*5+3) -> 170180.66
B29: Economic profit (RTB) / project NPV (HTM) | C29: k€ | D29: =INDEX('Control Panel'!$N$306:$N$330,Tender!$E$5*5+1) -> 9943.1039 | E29: =INDEX('Control Panel'!$N$306:$N$330,Tender!$E$5*5+4) -> 47524.011 | F29: =INDEX('Control Panel'!$N$306:$N$330,Tender!$E$5*5+5) -> 133488.73 | G29: =INDEX('Control Panel'!$N$306:$N$330,Tender!$E$5*5+2) -> 57524.989 | H29: =INDEX('Control Panel'!$N$306:$N$330,Tender!$E$5*5+3) -> 80447.169
B30: Integrity checks | C30: Status | D30: =INDEX('Control Panel'!$O$306:$O$330,Tender!$E$5*5+1) -> ALL OK | E30: =INDEX('Control Panel'!$O$306:$O$330,Tender!$E$5*5+4) -> ALL OK | F30: =INDEX('Control Panel'!$O$306:$O$330,Tender!$E$5*5+5) -> ALL OK | G30: =INDEX('Control Panel'!$O$306:$O$330,Tender!$E$5*5+2) -> ALL OK / OK | H30: =INDEX('Control Panel'!$O$306:$O$330,Tender!$E$5*5+3) -> ALL OK / OK
B31: Sell at RTB – detail
B32: RTB date → sale date | C32: Date | D32: =INDEX('Control Panel'!$P$306:$P$330,Tender!$E$5*5+1) -> Jun-29 → Mar-30 | E32: =INDEX('Control Panel'!$P$306:$P$330,Tender!$E$5*5+4) -> – | F32: =INDEX('Control Panel'!$P$306:$P$330,Tender!$E$5*5+5) -> – | G32: =INDEX('Control Panel'!$P$306:$P$330,Tender!$E$5*5+2) -> COD Sep-31 → sale at COD | H32: =INDEX('Control Panel'!$P$306:$P$330,Tender!$E$5*5+3) -> COD Sep-31 → sale at COD
B33: Gross RTB proceeds (premium + buyer reimbursement) | C33: k€ | D33: =INDEX('Control Panel'!$Q$306:$Q$330,Tender!$E$5*5+1) -> 64143.615 | E33: =INDEX('Control Panel'!$Q$306:$Q$330,Tender!$E$5*5+4) -> – | F33: =INDEX('Control Panel'!$Q$306:$Q$330,Tender!$E$5*5+5) -> – | G33: =INDEX('Control Panel'!$Q$306:$Q$330,Tender!$E$5*5+2) -> 609707.58 | H33: =INDEX('Control Panel'!$Q$306:$Q$330,Tender!$E$5*5+3) -> 522606.5
B34: FEP net profit pre-tax – Case B (signing fee, DD, guarantee fees, cost of capital) | C34: k€ | D34: =INDEX('Control Panel'!$R$306:$R$330,Tender!$E$5*5+1) -> 10273.223 | E34: =INDEX('Control Panel'!$R$306:$R$330,Tender!$E$5*5+4) -> – | F34: =INDEX('Control Panel'!$R$306:$R$330,Tender!$E$5*5+5) -> – | G34: =INDEX('Control Panel'!$R$306:$R$330,Tender!$E$5*5+2) -> 272537.82 | H34: =INDEX('Control Panel'!$R$306:$R$330,Tender!$E$5*5+3) -> 161496.92
B35: FEP net profit post-tax – Case B | C35: k€ | D35: =INDEX('Control Panel'!$S$306:$S$330,Tender!$E$5*5+1) -> 9920.6317 | E35: =INDEX('Control Panel'!$S$306:$S$330,Tender!$E$5*5+4) -> – | F35: =INDEX('Control Panel'!$S$306:$S$330,Tender!$E$5*5+5) -> – | G35: =INDEX('Control Panel'!$S$306:$S$330,Tender!$E$5*5+2) -> 336669.76 | H35: =INDEX('Control Panel'!$S$306:$S$330,Tender!$E$5*5+3) -> 360609.58
B36: Gearing (senior debt / total capex) | C36: % | D36: =INDEX('Control Panel'!$T$306:$T$330,Tender!$E$5*5+1) -> – | E36: =INDEX('Control Panel'!$T$306:$T$330,Tender!$E$5*5+4) -> – | F36: =INDEX('Control Panel'!$T$306:$T$330,Tender!$E$5*5+5) -> – | G36: =INDEX('Control Panel'!$T$306:$T$330,Tender!$E$5*5+2) -> 0.6 | H36: =INDEX('Control Panel'!$T$306:$T$330,Tender!$E$5*5+3) -> 0.5
B37: Sale at COD price per installed MW (after clipping) | C37: k€/MW | D37: =INDEX('Control Panel'!$U$306:$U$330,Tender!$E$5*5+1) -> – | E37: =INDEX('Control Panel'!$U$306:$U$330,Tender!$E$5*5+4) -> – | F37: =INDEX('Control Panel'!$U$306:$U$330,Tender!$E$5*5+5) -> – | G37: =INDEX('Control Panel'!$U$306:$U$330,Tender!$E$5*5+2) -> 2336.0444 | H37: =INDEX('Control Panel'!$U$306:$U$330,Tender!$E$5*5+3) -> 2002.3238
B38: Grid connection fee – indirect / direct | C38: mHUF | D38: =INDEX('Control Panel'!$V$306:$V$330,Tender!$E$5*5+1) -> 14,614 / 508 | E38: =INDEX('Control Panel'!$V$306:$V$330,Tender!$E$5*5+4) -> – | F38: =INDEX('Control Panel'!$V$306:$V$330,Tender!$E$5*5+5) -> – | G38: =INDEX('Control Panel'!$V$306:$V$330,Tender!$E$5*5+2) -> 14,614 / 508 | H38: =INDEX('Control Panel'!$V$306:$V$330,Tender!$E$5*5+3) -> 14,614 / 508
B39: Total tender securities and grid fees (gross) | C39: mHUF | D39: =INDEX('Control Panel'!$W$306:$W$330,Tender!$E$5*5+1) -> 23592.162 | E39: =INDEX('Control Panel'!$W$306:$W$330,Tender!$E$5*5+4) -> – | F39: =INDEX('Control Panel'!$W$306:$W$330,Tender!$E$5*5+5) -> – | G39: =INDEX('Control Panel'!$W$306:$W$330,Tender!$E$5*5+2) -> 23592.162 | H39: =INDEX('Control Panel'!$W$306:$W$330,Tender!$E$5*5+3) -> 23592.162
B40: Devex – total incl. contingency | C40: k€ | D40: =INDEX('Control Panel'!$X$306:$X$330,Tender!$E$5*5+1) -> 3137.8459 | E40: =INDEX('Control Panel'!$X$306:$X$330,Tender!$E$5*5+4) -> – | F40: =INDEX('Control Panel'!$X$306:$X$330,Tender!$E$5*5+5) -> – | G40: =INDEX('Control Panel'!$X$306:$X$330,Tender!$E$5*5+2) -> 3137.8459 | H40: =INDEX('Control Panel'!$X$306:$X$330,Tender!$E$5*5+3) -> 3137.8459
B41: Hold-to-maturity – detail
B42: Capex per MW (all-in incl. grid connection fee) | C42: k€/MW | D42: =INDEX('Control Panel'!$Y$306:$Y$330,Tender!$E$5*5+1) -> – | E42: =INDEX('Control Panel'!$Y$306:$Y$330,Tender!$E$5*5+4) -> 2156.0065 | F42: =INDEX('Control Panel'!$Y$306:$Y$330,Tender!$E$5*5+5) -> 1533.094 | G42: =INDEX('Control Panel'!$Y$306:$Y$330,Tender!$E$5*5+2) -> 2156.0065 | H42: =INDEX('Control Panel'!$Y$306:$Y$330,Tender!$E$5*5+3) -> 1533.094
B43: Total capex | C43: k€ | D43: =INDEX('Control Panel'!$Z$306:$Z$330,Tender!$E$5*5+1) -> – | E43: =INDEX('Control Panel'!$Z$306:$Z$330,Tender!$E$5*5+4) -> 431201.3 | F43: =INDEX('Control Panel'!$Z$306:$Z$330,Tender!$E$5*5+5) -> 306618.8 | G43: =INDEX('Control Panel'!$Z$306:$Z$330,Tender!$E$5*5+2) -> 431201.3 | H43: =INDEX('Control Panel'!$Z$306:$Z$330,Tender!$E$5*5+3) -> 306618.8
B44: Gearing / senior debt at COD | C44: k€ | D44: =INDEX('Control Panel'!$AA$306:$AA$330,Tender!$E$5*5+1) -> – | E44: =INDEX('Control Panel'!$AA$306:$AA$330,Tender!$E$5*5+4) -> 272537.82 | F44: =INDEX('Control Panel'!$AA$306:$AA$330,Tender!$E$5*5+5) -> 161496.92 | G44: =INDEX('Control Panel'!$AA$306:$AA$330,Tender!$E$5*5+2) -> 272537.82 | H44: =INDEX('Control Panel'!$AA$306:$AA$330,Tender!$E$5*5+3) -> 161496.92 | I44: RtB: no debt. HTM and sale at COD: EU 60% / CN 50% gearing (Control Panel section c)
B45: Lifetime net generation | C45: GWh | D45: =INDEX('Control Panel'!$AB$306:$AB$330,Tender!$E$5*5+1) -> – | E45: =INDEX('Control Panel'!$AB$306:$AB$330,Tender!$E$5*5+4) -> 17249.631 | F45: =INDEX('Control Panel'!$AB$306:$AB$330,Tender!$E$5*5+5) -> 17249.631 | G45: =INDEX('Control Panel'!$AB$306:$AB$330,Tender!$E$5*5+2) -> – | H45: =INDEX('Control Panel'!$AB$306:$AB$330,Tender!$E$5*5+3) -> –
B46: Average achieved price (lifetime) | C46: €/MWh | D46: =INDEX('Control Panel'!$AC$306:$AC$330,Tender!$E$5*5+1) -> – | E46: =INDEX('Control Panel'!$AC$306:$AC$330,Tender!$E$5*5+4) -> 136.7236 | F46: =INDEX('Control Panel'!$AC$306:$AC$330,Tender!$E$5*5+5) -> 136.7236 | G46: =INDEX('Control Panel'!$AC$306:$AC$330,Tender!$E$5*5+2) -> – | H46: =INDEX('Control Panel'!$AC$306:$AC$330,Tender!$E$5*5+3) -> – | I46: HTM: 90 €/MWh PPA 10 yrs then Aurora Central – European and Chinese (08-Oct-26)
B47: Lifetime revenue | C47: k€ | D47: =INDEX('Control Panel'!$AD$306:$AD$330,Tender!$E$5*5+1) -> – | E47: =INDEX('Control Panel'!$AD$306:$AD$330,Tender!$E$5*5+4) -> 2358431.6 | F47: =INDEX('Control Panel'!$AD$306:$AD$330,Tender!$E$5*5+5) -> 2358431.6 | G47: =INDEX('Control Panel'!$AD$306:$AD$330,Tender!$E$5*5+2) -> – | H47: =INDEX('Control Panel'!$AD$306:$AD$330,Tender!$E$5*5+3) -> –
B48: LCOE | C48: €/MWh | D48: =INDEX('Control Panel'!$AE$306:$AE$330,Tender!$E$5*5+1) -> – | E48: =INDEX('Control Panel'!$AE$306:$AE$330,Tender!$E$5*5+4) -> 101.81218 | F48: =INDEX('Control Panel'!$AE$306:$AE$330,Tender!$E$5*5+5) -> 82.108321 | G48: =INDEX('Control Panel'!$AE$306:$AE$330,Tender!$E$5*5+2) -> – | H48: =INDEX('Control Panel'!$AE$306:$AE$330,Tender!$E$5*5+3) -> –
B49: Project IRR – unlevered, post-tax | C49: % | D49: =INDEX('Control Panel'!$AF$306:$AF$330,Tender!$E$5*5+1) -> – | E49: =INDEX('Control Panel'!$AF$306:$AF$330,Tender!$E$5*5+4) -> 0.091701924 | F49: =INDEX('Control Panel'!$AF$306:$AF$330,Tender!$E$5*5+5) -> 0.12109681 | G49: =INDEX('Control Panel'!$AF$306:$AF$330,Tender!$E$5*5+2) -> – | H49: =INDEX('Control Panel'!$AF$306:$AF$330,Tender!$E$5*5+3) -> –
B50: Equity IRR – levered, post-tax (100%) | C50: % | D50: =INDEX('Control Panel'!$AG$306:$AG$330,Tender!$E$5*5+1) -> – | E50: =INDEX('Control Panel'!$AG$306:$AG$330,Tender!$E$5*5+4) -> 0.09991356 | F50: =INDEX('Control Panel'!$AG$306:$AG$330,Tender!$E$5*5+5) -> 0.13111233 | G50: =INDEX('Control Panel'!$AG$306:$AG$330,Tender!$E$5*5+2) -> 0.49320293 | H50: =INDEX('Control Panel'!$AG$306:$AG$330,Tender!$E$5*5+3) -> 0.63972784
B51: Payback year | C51: Year | D51: =INDEX('Control Panel'!$AH$306:$AH$330,Tender!$E$5*5+1) -> – | E51: =INDEX('Control Panel'!$AH$306:$AH$330,Tender!$E$5*5+4) -> 2044 | F51: =INDEX('Control Panel'!$AH$306:$AH$330,Tender!$E$5*5+5) -> 2041 | G51: =INDEX('Control Panel'!$AH$306:$AH$330,Tender!$E$5*5+2) -> – | H51: =INDEX('Control Panel'!$AH$306:$AH$330,Tender!$E$5*5+3) -> –
B52: Minimum DSCR | C52: x | D52: =INDEX('Control Panel'!$AI$306:$AI$330,Tender!$E$5*5+1) -> – | E52: =INDEX('Control Panel'!$AI$306:$AI$330,Tender!$E$5*5+4) -> 1.1631739 | F52: =INDEX('Control Panel'!$AI$306:$AI$330,Tender!$E$5*5+5) -> 1.9196059 | G52: =INDEX('Control Panel'!$AI$306:$AI$330,Tender!$E$5*5+2) -> – | H52: =INDEX('Control Panel'!$AI$306:$AI$330,Tender!$E$5*5+3) -> –
B54: Live check vs the model (the route active in Inputs E6) | C54: Status | D54: =CHOOSE(1+(Inputs!$E$6=1)*(1+IFERROR(ABS(MOIC!$G$187-D24)<=Tender!$E$33,0)),"n/a","STALE – data table not recalculated (F9)","OK") -> OK | E54: =CHOOSE(1+(Inputs!$E$6=2)*(1+IFERROR(ABS(HTM!$G$139-E24)<=Tender!$E$33,0)),"n/a","STALE – data table not recalculated (F9)","OK") -> n/a | F54: =CHOOSE(1+(Inputs!$E$6=3)*(1+IFERROR(ABS(HTM!$G$139-F24)<=Tender!$E$33,0)),"n/a","STALE – data table not recalculated (F9)","OK") -> n/a | G54: =CHOOSE(1+(Inputs!$E$6=7)*(1+IFERROR(ABS(HTM!$G$352-G24)<=Tender!$E$33,0)),"n/a","STALE – data table not recalculated (F9)","OK") -> n/a | H54: =CHOOSE(1+(Inputs!$E$6=8)*(1+IFERROR(ABS(HTM!$G$352-H24)<=Tender!$E$33,0)),"n/a","STALE – data table not recalculated (F9)","OK") -> n/a

Sheet Inputs
A1: HUN Onshore Wind – MOIC model v5
A2: Inputs – all static inputs. Column E = active case (picks case column G:P; falls back to case 1 if the selected case cell is blank).
A3: Blue on cream = input. Black = calculated. Green = link from another sheet. Yellow fill = key assumption to confirm. Amber fill = awaiting input.
C5: Input | D5: Unit | E5: Active case | F5: Note | G5: Case 1 | H5: Case 2 | I5: Case 3 | J5: Case 4 | K5: Case 5 | L5: Case 6 | M5: Case 7 | N5: Case 8 | O5: Case 9 | P5: Case 10
C6: Case # | D6: # | E6: =IF('Control Panel'!$E$10=0,'Control Panel'!$F$8,INDEX('Control Panel'!$E$306:$E$330,'Control Panel'!$E$10)) -> 1 | F6: Set on the Control Panel (E8 route; data-table driver E10) | G6: 1 | H6: =G6+1 -> 2 | I6: =H6+1 -> 3 | J6: =I6+1 -> 4 | K6: =J6+1 -> 5 | L6: =K6+1 -> 6 | M6: =L6+1 -> 7 | N6: =M6+1 -> 8 | O6: =N6+1 -> 9 | P6: =O6+1 -> 10
C7: Case name | D7: Name | E7: {=INDEX($G7:$P7,$E$6)} -> FEP base case | G7: FEP base case | H7: European turbine | I7: Chinese turbine | J7: No deposit recovery at exit | K7: IC deck basis (280 MW, 70/30 JV) | L7: All deposits cash-settled | M7: Sale at COD, European turbine | N7: Sale at COD, Chinese turbine | O7: Spare | P7: Spare
C8: Case description | D8: Text | E8: {=INDEX($G8:$P8,$E$6)} -> FEP funds 100%, 70/30 JV on proceeds, 200 MW, aligned to BORA Devex 29/09/2026 | G8: FEP funds 100%, 70/30 JV on proceeds, 200 MW, aligned to BORA Devex 29/09/2026 | H8: Turbine supply 950 k€/MW, 60% gearing, 100% of output under a 90 €/MWh PPA (10 yrs, 1% p.a. indexation), Aurora Central merchant tail | I8: Turbine supply 500 k€/MW, 50% gearing, 100% of output under a 90 €/MWh PPA (10 yrs, 1% p.a. indexation), Aurora Central merchant tail | J8: As case 1 but buyer does not reimburse securities / connection fee | K8: Portfolio 280 MW, JV 70/30 live, success fee live | L8: As case 1 but no bank guarantees | M8: No RTB exit. Build with European turbine (as case 2), 60% gearing, 90 €/MWh PPA; sell 100% of the SPV at the project's COD (Bora: Sep-2031 override) at the Tender price per gross MW net of clipping and of the post-COD promise costs (enterprise value; senior debt repaid from proceeds). | N8: No RTB exit. Build with Chinese turbine (as case 3), 50% gearing, 90 €/MWh PPA; sell 100% of the SPV at the project's COD (Bora: Sep-2031 override) at the Tender price per gross MW net of clipping and of the post-COD promise costs (enterprise value; senior debt repaid from proceeds).
B10: x | C10: A. Macro
C11: EUR / HUF | D11: HUF/EUR | E11: {=IF(INDEX($G11:$P11,$E$6)="",$G11,INDEX($G11:$P11,$E$6))} -> 365 | F11: Single FX for the whole model (also used for mHUF reporting outputs). | G11: 365
C12: Hungary corporate income tax | D12: % | E12: {=IF(INDEX($G12:$P12,$E$6)="",$G12,INDEX($G12:$P12,$E$6))} -> 0.09 | F12: Applied to positive cumulative profit at sale, less any gain exempted by the participation exemption (E14). | G12: 0.09
C13: Cost of capital for economic profit | D13: % | E13: {=IF(INDEX($G13:$P13,$E$6)="",$G13,INDEX($G13:$P13,$E$6))} -> 0.08 | F13: Monthly charge on the negative cumulative equity position. Linked to the single discount rate (Inputs row 253 ← Control Panel section c), per decision 02-Oct-26 (Open_Items #10). Previously 8.9% typed. | G13: =G$253 -> 0.08 | H13: =H$253 | I13: =I$253 | M13: =H13 | N13: =I13
C14: Participation exemption on RtB share sale (1 = gain on shares exempt) | D14: Switch | E14: {=IF(INDEX($G14:$P14,$E$6)="",$G14,INDEX($G14:$P14,$E$6))} -> 1 | F14: 1 = the share of distributable proceeds (gain on the SPV/JV shares) is exempt from CIT under the Hungarian participation exemption (bejelentett részesedés): shareholding notified to NAV within 75 days of acquisition and held ≥ 1 year before sale (investment date E27 to sale ≈ 3 years). Interest, 2× top-up and loan returns stay taxable at E12. 0 = flat E12 on all profit at sale. | G14: 1
B15: x | C15: B. Capacity, acquisition and exit timing
C16: Gross capacity entered in tender | D16: MW | E16: {=IF(INDEX($G16:$P16,$E$6)="",$G16,INDEX($G16:$P16,$E$6))} -> 200 | F16: Bid-stage items (participation fee, bid bond) scale with this. | G16: ='Control Panel'!$E$74 -> 200 | K16: 280
C17: Conversion rate (capacity awarded and taken to RTB) | D17: % | E17: {=IF(INDEX($G17:$P17,$E$6)="",$G17,INDEX($G17:$P17,$E$6))} -> 1 | F17: Post-award items and exit proceeds scale with successful capacity. | G17: 1
C18: Successful capacity | D18: MW | E18: =E16*E17 -> 200
C19: Failed capacity | D19: MW | E19: =E16-E18 -> 0 | F19: Devex on failed capacity is still spent; its bid bond is refunded at award if the switch below is on.
C20: BESS connection capacity (gross) | D20: MW | E20: {=IF(INDEX($G20:$P20,$E$6)="",$G20,INDEX($G20:$P20,$E$6))} -> 90 | F20: BESS power rating entered in the tender. FEP workbook assumes 100 MW (50% of wind). | G20: =Tender!$J$41 -> 90
C21: BESS duration | D21: Hours | E21: {=IF(INDEX($G21:$P21,$E$6)="",$G21,INDEX($G21:$P21,$E$6))} -> 4 | F21: Storage hours at rated power – linked to Tender J16 (active tender strategy; 4 h in every strategy, Munka1 0.25C) | G21: =Tender!$J$16 -> 4
C22: BESS storage capacity (gross) | D22: MWh | E22: =E20*E21 -> 360 | F22: Drives the BESS leg of the security base at the bid stage.
C23: BESS storage capacity (successful) | D23: MWh | E23: =E22*E17 -> 360 | F23: Post-award BESS base; scales with the same conversion rate as wind.
C24: Signing fee to current owners | D24: k€ | E24: {=IF(INDEX($G24:$P24,$E$6)="",$G24,INDEX($G24:$P24,$E$6))} -> 250 | F24: Paid at month 0. | G24: ='Control Panel'!$E$75 -> 250 | K24: 295
C25: Transaction / DD costs to FEP | D25: k€ | E25: {=IF(INDEX($G25:$P25,$E$6)="",$G25,INDEX($G25:$P25,$E$6))} -> 150 | F25: Paid at month 0. | G25: 150
C26: Sale costs at exit | D26: k€ | E26: {=IF(INDEX($G26:$P26,$E$6)="",$G26,INDEX($G26:$P26,$E$6))} -> 500 | F26: Deducted from proceeds in the waterfall. | G26: 500
C27: Investment date (month 0) | D27: Date | E27: {=IF(INDEX($G27:$P27,$E$6)="",$G27,INDEX($G27:$P27,$E$6))} -> 46234 | F27: Start of the monthly grid; every month steps by EOMONTH. | G27: 46234
C28: Lag from RTB to sale | D28: Months | E28: {=IF(INDEX($G28:$P28,$E$6)="",$G28,INDEX($G28:$P28,$E$6))} -> 9 | F28: ="RTB + "&E28&" months = RtB sale (BORA Devex proposal; was 3). RTB "&DAY(E56)&"/"&TEXT(MONTH(E56),"00")&"/"&YEAR(E56)&" → sale "&DAY(E58)&"/"&TEXT(MONTH(E58),"00")&"/"&YEAR(E58) -> RTB + 9 months = RtB sale (BORA Devex proposal; was 3). RTB 30/06/2029 → sale 31/03/2030 | G28: ='Control Panel'!$E$88 -> 9 | H28: =IF('Control Panel'!$F$88="","",'Control Panel'!$F$88) | I28: =IF('Control Panel'!$G$88="","",'Control Panel'!$G$88) | M28: =H28 | N28: =I28
C29: Gross installed wind capacity – successful (overbuild) | D29: MW | E29: =IF(E281=0,E18,E18*E297/E281) -> 261 | F29: Net successful MW (E18) × gross / net ratio of the project (row 297 ÷ row 281). Drives bid / performance bonds, turbine & BOP capex, generation, opex, decommissioning, the COD sale price and the developer success fee (DSA, DSA on installed MW per BORA_Devex – user 09-Oct-26). Grid fees, TSO bond and the RTB premium stay on net MW (E18; premium: switch row 149).
B30: x | C30: C. Ownership and developer economics
C31: JV structure live (1 = 70/30 JV, 0 = FEP 100%) | D31: Switch | E31: {=IF(INDEX($G31:$P31,$E$6)="",$G31,INDEX($G31:$P31,$E$6))} -> 1 | F31: Master switch. Also drives Assumptions!E8 on the HTM side. | G31: ='Control Panel'!$E$76 -> 1 | K31: 1
C32: FEP share of net proceeds if JV | D32: % | E32: {=IF(INDEX($G32:$P32,$E$6)="",$G32,INDEX($G32:$P32,$E$6))} -> 0.7 | G32: ='Control Panel'!$E$77 -> 0.7
C33: FEP effective share of distributable proceeds | D33: % | E33: =IF(E31=1,E32,1) -> 0.7
C34: Developer effective share | D34: % | E34: =1-E33 -> 0.3
C35: Developer funds pro rata (1 = yes) | D35: Switch | E35: {=IF(INDEX($G35:$P35,$E$6)="",$G35,INDEX($G35:$P35,$E$6))} -> 0 | F35: If on, the developer funds its share of both shareholder loans on the same terms. | G35: 0
C36: Developer success fee p.a. | D36: k€/MW | E36: {=IF(INDEX($G36:$P36,$E$6)="",$G36,INDEX($G36:$P36,$E$6))} -> 2.5 | F36: DSA on installed MW per BORA_Devex – user 09-Oct-26: accrues pro rata to the sale on the installed wind MW (E29, BORA_Devex V37 = 2 500 €/MW × V6); settled at exit from proceeds (not funded to RTB). Cap E37 per the same MW. | G36: 2.5
C37: Success fee cap | D37: k€/MW | E37: {=IF(INDEX($G37:$P37,$E$6)="",$G37,INDEX($G37:$P37,$E$6))} -> 10 | G37: 10
C38: Success fee live | D38: Switch | E38: =E31 -> 1 | F38: Fee only exists in the JV case.
B40: x | C40: D. Milestone timing (drives RTB and sale dates). Milestone devex amounts (rows 41–48) are NO LONGER USED – devex comes from the BORA_Devex sheet via Devex_FEP.
C41: Milestone 1 devex | D41: k€/MW | E41: {=IF(INDEX($G41:$P41,$E$6)="",$G41,INDEX($G41:$P41,$E$6))} -> 0 | F41: NOT USED since 29-Sep-2026 – kept for reference only (grouped). Devex = BORA Devex line items with their own payment dates (Devex_FEP / BORA_Devex).
C42: Milestone 2 devex | D42: k€/MW | E42: {=IF(INDEX($G42:$P42,$E$6)="",$G42,INDEX($G42:$P42,$E$6))} -> 0
C43: Milestone 3 devex | D43: k€/MW | E43: {=IF(INDEX($G43:$P43,$E$6)="",$G43,INDEX($G43:$P43,$E$6))} -> 0
C44: Milestone 4 devex | D44: k€/MW | E44: {=IF(INDEX($G44:$P44,$E$6)="",$G44,INDEX($G44:$P44,$E$6))} -> 0
C45: Milestone 5 devex | D45: k€/MW | E45: {=IF(INDEX($G45:$P45,$E$6)="",$G45,INDEX($G45:$P45,$E$6))} -> 0
C46: Milestone 6 devex | D46: k€/MW | E46: {=IF(INDEX($G46:$P46,$E$6)="",$G46,INDEX($G46:$P46,$E$6))} -> 0
C47: Total devex | D47: k€/MW | E47: =SUM(E41:E46) -> 0
C48: Total devex on gross capacity | D48: k€ | E48: =E47*E16 -> 0 | F48: Spent on successful and failed capacity alike.
C49: Milestone 1 timing (months after previous) | D49: Months | E49: {=IF(INDEX($G49:$P49,$E$6)="",$G49,INDEX($G49:$P49,$E$6))} -> 0 | F49: Months to RTB now 32 (E55), RTB 31/03/2029 (E56); spread evenly across the six milestones. | G49: 0
C50: Milestone 2 timing (months after previous) | D50: Months | E50: {=IF(INDEX($G50:$P50,$E$6)="",$G50,INDEX($G50:$P50,$E$6))} -> 6 | G50: 6
C51: Milestone 3 timing (months after previous) | D51: Months | E51: {=IF(INDEX($G51:$P51,$E$6)="",$G51,INDEX($G51:$P51,$E$6))} -> 6 | G51: 6
C52: Milestone 4 timing (months after previous) | D52: Months | E52: {=IF(INDEX($G52:$P52,$E$6)="",$G52,INDEX($G52:$P52,$E$6))} -> 6 | G52: 6
C53: Milestone 5 timing (months after previous) | D53: Months | E53: {=IF(INDEX($G53:$P53,$E$6)="",$G53,INDEX($G53:$P53,$E$6))} -> 7 | G53: 7
C54: Milestone 6 timing (months after previous) | D54: Months | E54: {=IF(INDEX($G54:$P54,$E$6)="",$G54,INDEX($G54:$P54,$E$6))} -> 7 | G54: 7
C55: Months from investment to RTB | D55: Months | E55: =IF(E298="",SUM(E49:E54),(YEAR(E298)-YEAR(E27))*12+MONTH(E298)-MONTH(E27)-E152-E153) -> 35 | F55: Milestone sum, or derived from the COD override (Inputs row 298 ← Control Panel section c; Bora Sep-2031)
C56: RTB date | D56: Date | E56: =EOMONTH(E27,E55) -> 47299
C57: Sale month (grid index) | D57: Months | E57: =E55+E28 -> 44
C58: Sale date | D58: Date | E58: =EOMONTH(E27,E57) -> 47573
B60: x | C60: E. FEP shareholder loans to HoldCo
C61: Recoverable loan interest (refundable securities) | D61: % p.a. | E61: {=IF(INDEX($G61:$P61,$E$6)="",$G61,INDEX($G61:$P61,$E$6))} -> 0.12 | F61: Compounded monthly on the drawn balance. | G61: 0.12
C62: Unrecoverable (at-risk) loan interest | D62: % p.a. | E62: {=IF(INDEX($G62:$P62,$E$6)="",$G62,INDEX($G62:$P62,$E$6))} -> 0.2 | F62: Compounded monthly. | G62: 0.2
C63: Minimum return on unrecoverable loan | D63: x | E63: {=IF(INDEX($G63:$P63,$E$6)="",$G63,INDEX($G63:$P63,$E$6))} -> 2 | F63: Top-up paid from proceeds so the at-risk loan returns at least this multiple of principal. | G63: 2
C64: Interest pause start (no accrual after this date until the pause end, row 73) | D64: Date | E64: {=IF(INDEX($G64:$P64,$E$6)="",$G64,INDEX($G64:$P64,$E$6))} -> 47299 | F64: ="Interest pause "&TEXT(DAY(E64),"00")&"/"&TEXT(MONTH(E64),"00")&"/"&YEAR(E64)&" – "&TEXT(DAY(E73),"00")&"/"&TEXT(MONTH(E73),"00")&"/"&YEAR(E73)&": no accrual in between (user 09-Oct-26)" -> Interest pause 30/06/2029 – 01/01/2030: no accrual in between (user 09-Oct-26) | G64: =DATE(2029,6,30) -> 47299
C65: Interest on bank-guaranteed securities (credited to FEP) | D65: % p.a. | E65: {=IF(INDEX($G65:$P65,$E$6)="",$G65,INDEX($G65:$P65,$E$6))} -> 0.06 | F65: Accrues monthly-compounded on the guarantee-backed securities outstanding; paid to FEP (and Developer pro rata) from sale proceeds, like loan interest. | G65: 0.06
C66: At-risk loan return = flat multiple of principal (1) or 20% compounding with minimum (0) | D66: Switch | E66: {=IF(INDEX($G66:$P66,$E$6)="",$G66,INDEX($G66:$P66,$E$6))} -> 1 | F66: 1 = flat 2× principal in the memo loan schedule (rows 126 / 130); 0 = 20 % compounding topped up to 2×. The waterfall claim (MOIC G131 / G280) always follows BORA_Devex column P: MAX(20 % growth to the exit excl. the pause, 2×) – 2× while the growth is below 2×. | G66: 1
C67: Devex basis – retired switch, keep at 1 (BORA Devex line items via Devex_FEP) | D67: Switch | E67: {=IF(INDEX($G67:$P67,$E$6)="",$G67,INDEX($G67:$P67,$E$6))} -> 1 | F67: 1 = devex from the Devex_FEP sheet (BORA_Devex_20260925.xlsx FEP view, updated 29/09/2026). Land reservation fee and land purchase price (Devex rows 14–15) are paid by FEP and earn the 2× at-risk return; their principal is reimbursed by the buyer at RtB exit (not refunded if the project fails) – Devex_FEP J:K, MOIC row 20. RtB land (row 48), financial costs and G&A excluded. | G67: 1
C68: Contingency on FEP-borne devex (line-item basis) | D68: % | E68: {=IF(INDEX($G68:$P68,$E$6)="",$G68,INDEX($G68:$P68,$E$6))} -> 0.1 | F68: Applied to FEP-borne devex on Devex_FEP. Devex file Y52: €2.65m including contingency. | G68: 0.1
C69: Interest compounding: annual, BORA Devex convention (1) or monthly (0) | D69: Switch | E69: {=IF(INDEX($G69:$P69,$E$6)="",$G69,INDEX($G69:$P69,$E$6))} -> 1 | F69: 1 = effective monthly rate (1+r)^(1/12)−1, equivalent to annual compounding as in the Devex file. 0 = nominal r/12. | G69: 1
C70: DSA / developer success fee accrual start (signing) | D70: Date | E70: {=IF(INDEX($G70:$P70,$E$6)="",$G70,INDEX($G70:$P70,$E$6))} -> 46321 | F70: Signing 26/10/2026. Fee accrues pro rata (30/360) from here to the sale date at E36, capped at E37. | G70: =DATE(2026,10,26) -> 46321
C71: At-risk loan principal (devex) repaid from sale proceeds (1) or carried by FEP (0) | D71: Switch | E71: {=IF(INDEX($G71:$P71,$E$6)="",$G71,INDEX($G71:$P71,$E$6))} -> 0 | F71: 0 = FEP carries its devex (only the 2× return is paid from proceeds), as in the Devex file. | G71: 0
C72: Standard cost of capital on FEP cash-funded items (Case B) | D72: % p.a. | E72: {=IF(INDEX($G72:$P72,$E$6)="",$G72,INDEX($G72:$P72,$E$6))} -> 0.08 | F72: Linked to the model's standard cost of capital (Inputs E13, 8.9%). Opportunity cost on cash FEP funds (cash securities, connection fee, participation fee, devex), compounded to the sale date. Guarantee-backed items use the guarantee fee instead. | G72: =$E$13 -> 0.08
C73: Interest pause end (accrual resumes on this date; user 09-Oct-26) | D73: Date | E73: =IF(INDEX($G73:$P73,$E$6)="",$G73,INDEX($G73:$P73,$E$6)) -> 47484 | F73: Every interest / return accrual (securities 6 % / 12 %, participation fee, devex and land 20 % with the 2× minimum, shareholder-loan and guarantee interest) pauses from row 64 to here, then runs on to the exit date (RtB sale E58; COD sale E155). Not paused: success fee (BORA_Devex X37 = V37), bank guarantee fees. Exact while the pause ends on 1 January (each year keeps one stub); a pause ending mid-year splits that year into two simple stubs – cross-term r²·a·b/365², ≈ +0.8 % on a 20 % line for half a year each side – so a zero-length pause is not exactly the continuous accrual. | G73: =DATE(2030,1,1) -> 47484
B74: x | C74: F. Tender securities and grid connection – unit rates (source: Bora_csatlakozási_biztosítékok_díjak.xlsx)
C75: Benchmark CAPEX – wind (csatlakozási díj alapdíj) | D75: mHUF/MW | E75: {=IF(INDEX($G75:$P75,$E$6)="",$G75,INDEX($G75:$P75,$E$6))} -> 406 | F75: Wind leg of the %-driven security base. Matches the FEP workbook's 406 mHUF/MW. | G75: 406
C76: Bid bond rate (ajánlati biztosíték) | D76: % of base | E76: {=IF(INDEX($G76:$P76,$E$6)="",$G76,INDEX($G76:$P76,$E$6))} -> 0.005 | F76: 0.5% of the bid-stage base (E91), no uplift – matches BORA Devex I6 (606 mHUF). | G76: 0.005
C77: Performance bond rate (teljesítési biztosíték) | D77: % of base | E77: {=IF(INDEX($G77:$P77,$E$6)="",$G77,INDEX($G77:$P77,$E$6))} -> 0.025 | G77: 0.025
C78: Supplementary security total rate (kiegészítő biztosíték) | D78: % of base | E78: {=IF(INDEX($G78:$P78,$E$6)="",$G78,INDEX($G78:$P78,$E$6))} -> 0 | F78: 0 – no supplementary security (kiegészítő biztosíték) in this procedure: GYIK 70 (user 09-Oct-26; removed 07-Oct-26, was 5 %). Deposits rows 13–17 stay at 0; the Bora reconciliation excludes the source's supplementary lines (Deposits E50). | G78: 0
C79: Supplementary – 1st instalment share | D79: % | E79: {=IF(INDEX($G79:$P79,$E$6)="",$G79,INDEX($G79:$P79,$E$6))} -> 0.4 | F79: 2030 COD: first annual instalment is double. | G79: 0.4
C80: Supplementary – instalments 2–4 share (each) | D80: % | E80: {=IF(INDEX($G80:$P80,$E$6)="",$G80,INDEX($G80:$P80,$E$6))} -> 0.2 | G80: 0.2
C81: Participation fee (részvételi díj) | D81: mHUF per bid | E81: {=IF(INDEX($G81:$P81,$E$6)="",$G81,INDEX($G81:$P81,$E$6))} -> 3 | F81: Final tender: HUF 3.0m per bid (draft was 2.0m). Source: MEKH kiírás 30-Aug-26 via palyazatok.org, https://palyazatok.org/szeleromu-palyazat/ | G81: 3
C82: Number of separate bids (fee is per bid) | D82: # | E82: {=IF(INDEX($G82:$P82,$E$6)="",$G82,INDEX($G82:$P82,$E$6))} -> 2 | F82: IC paper: BORA = 6 SPVs (5 × 50 MW + 1 × 30 MW). Case 1 keeps 6 bids at 200 MW as a conservative fee count. | G82: ='Control Panel'!$E$80 -> 2
C83: Connection request security (igénybejelentési biztosíték) | D83: mHUF/MW | E83: {=IF(INDEX($G83:$P83,$E$6)="",$G83,INDEX($G83:$P83,$E$6))} -> 4.5 | F83: Cash only – the TSO bond cannot be posted as a bank guarantee; credited against the indirect connection fee. | G83: 4.5
C84: Connection fee – direct (csatlakozási díj – közvetlen) | D84: mHUF/MW | E84: {=IF(INDEX($G84:$P84,$E$6)="",$G84,INDEX($G84:$P84,$E$6))} -> 2.541729 | F84: BORA_Devex_20261002_BG row 19 (unchanged since 25-Sep): direct connection fee 508,345,804 HUF (k€ 1,374 at 370 HUF/EUR in the example); expressed per MW so it scales with capacity. Paid on the connection fee date. | G84: ='Control Panel'!$E$82/1000000/'Control Panel'!$E$74 -> 2.541729
C85: Connection fee estimate (csatlakozási díj) | D85: mHUF/MW | E85: {=IF(INDEX($G85:$P85,$E$6)="",$G85,INDEX($G85:$P85,$E$6))} -> 73.071306 | F85: BORA_Devex_20261002_BG row 18: 73,071,306 HUF/MW (unchanged), booked net of the TSO bond. The example applies it to its 260 MW wind capacity (V6; k€ 48,915); the model to the net MVA (Inputs E18) – Bora 200 MVA: k€ 37,573 at 365 HUF/EUR. | G85: ='Control Panel'!$E$81/1000000 -> 73.071306
C86: Reference capacity of source table | D86: MW | E86: {=IF(INDEX($G86:$P86,$E$6)="",$G86,INDEX($G86:$P86,$E$6))} -> 200 | F86: Used only for the reconciliation check on Deposits. | G86: 200
C87: Source gross total at reference capacity | D87: mHUF | E87: {=IF(INDEX($G87:$P87,$E$6)="",$G87,INDEX($G87:$P87,$E$6))} -> 22797.61 | F87: From source table. | G87: 22797.61
C88: Source actually-payable total at reference capacity | D88: mHUF | E88: {=IF(INDEX($G88:$P88,$E$6)="",$G88,INDEX($G88:$P88,$E$6))} -> 21291.61 | F88: From source table. | G88: 21291.61
C89: Benchmark CAPEX – BESS | D89: mHUF/MWh | E89: {=IF(INDEX($G89:$P89,$E$6)="",$G89,INDEX($G89:$P89,$E$6))} -> 200 | F89: BESS leg of the %-driven security base. | G89: 200
C90: Performance bond uplift | D90: x | E90: {=IF(INDEX($G90:$P90,$E$6)="",$G90,INDEX($G90:$P90,$E$6))} -> 1.5 | F90: Applies to the performance bond only, as in the BORA Devex file (I7 = 2.5% × base × uplift − bid bond). Linked to Tender J17 (ÖSZ-6 of the active strategy: S0 100% / S1 150% / S2 160% / S3 200% / S4 210%). The bid bond stays at 0.5% of the base and is credited against the performance bond. | G90: =Tender!$J$17 -> 1.5
C91: Security base – bid stage (gross) | D91: mHUF | E91: =E16*IF(E18=0,1,E29/E18)*E75+E22*E89 -> 177966 | F91: Gross (overbuild) wind MW × benchmark CAPEX + BESS gross MWh × benchmark (wind leg on gross MW since 07-Oct-26)
C92: Security base – post-award (successful) | D92: mHUF | E92: =E29*E75+E23*E89 -> 177966 | F92: Performance bond applies to this. Supplementary bonds stay on the wind leg only, per the FEP build.
B94: x | C94: G. Tender and grid milestone dates
C95: Bid submission (pályázat benyújtása) | D95: Date | E95: {=IF(INDEX($G95:$P95,$E$6)="",$G95,INDEX($G95:$P95,$E$6))} -> 46325 | F95: Final tender: window 4 Sep – 30 Oct 2026 (draft was 1–18 Sep). Source: MEKH kiírás 30-Aug-26 via Világgazdaság/Portfolio, https://www.portfolio.hu/gazdasag/20260831/meg-csak-most-irtak-ki-a-szeltendert-de-maris-bearnyekolja-a-hazai-szelenergia-celokat-859412 | G95: =DATE(2026,10,30) -> 46325
C96: Award (eredményhirdetés) | D96: Date | E96: {=IF(INDEX($G96:$P96,$E$6)="",$G96,INDEX($G96:$P96,$E$6))} -> 46369 | F96: Final tender: results by 13 Dec 2026 (draft was 2 Dec). Same source as above. | G96: =DATE(2026,12,13) -> 46369
C97: Connection request (igénybejelentés) | D97: Date | E97: {=IF(INDEX($G97:$P97,$E$6)="",$G97,INDEX($G97:$P97,$E$6))} -> 46386 | F97: Within 15 days of award (linked: award + 14 days). | G97: =DATE(2026,12,30) -> 46386
C98: MGT acceptance | D98: Date | E98: {=IF(INDEX($G98:$P98,$E$6)="",$G98,INDEX($G98:$P98,$E$6))} -> 46478 | G98: 46478
C99: HCsSz signature (connection agreement) | D99: Date | E99: {=IF(INDEX($G99:$P99,$E$6)="",$G99,INDEX($G99:$P99,$E$6))} -> 47126 | F99: Connection fee paid here. | G99: =DATE(2029,1,8) -> 47126
C100: Building permit obtained (építési engedély) | D100: Date | E100: {=IF(INDEX($G100:$P100,$E$6)="",$G100,INDEX($G100:$P100,$E$6))} -> 46825 | F100: Drives the 50% supplementary refund and the step-down of later instalments. | G100: 46825
C101: COD – target (tender application) | D101: Date | E101: {=IF(INDEX($G101:$P101,$E$6)="",$G101,INDEX($G101:$P101,$E$6))} -> 47848 | F101: TARGET, not a deadline. The binding dates are the earliest connection date (E237) and the COD deadline (E238), checked on E240 and E241. Slipping past this target is not a breach. | G101: 47848
C102: Performance bond payment deadline after award | D102: Days | E102: {=IF(INDEX($G102:$P102,$E$6)="",$G102,INDEX($G102:$P102,$E$6))} -> 17 | G102: 17
C103: Supplementary security April payment day | D103: Day | E103: {=IF(INDEX($G103:$P103,$E$6)="",$G103,INDEX($G103:$P103,$E$6))} -> 23 | G103: 23
C104: First April payment after MGT acceptance (dates the supplementary instalments – nil, GYIK 70) | D104: Date | E104: =IF(DATE(YEAR(E98),4,E103)>=E98,DATE(YEAR(E98),4,E103),DATE(YEAR(E98)+1,4,E103)) -> 46500
B106: x | C106: H. Deposit mechanics
...

Sheet Curves
A1: Bora Onshore Wind – MOIC model v5
A2: Curves – time-series inputs: EURIBOR curves (monthly, aligned to the MOIC grid) and the Aurora Hungarian wind capture price placeholder (annual).
B4: x | C4: 1. EURIBOR curves (monthly) – select the curve in use on Inputs!E112
C5: Month index | G5: → | H5: =MOIC!H4 -> 0 | I5: =MOIC!I4 -> 1 | J5: =MOIC!J4 -> 2 | K5: =MOIC!K4 -> 3 | L5: =MOIC!L4 -> 4 | M5: =MOIC!M4 -> 5 | N5: =MOIC!N4 -> 6 | O5: =MOIC!O4 -> 7 | ... BP5: =MOIC!BP4 -> 60
C6: Period end date | D6: Date | H6: =MOIC!H5 -> 46234 | I6: =MOIC!I5 -> 46265 | J6: =MOIC!J5 -> 46295 | K6: =MOIC!K5 -> 46326 | L6: =MOIC!L5 -> 46356 | M6: =MOIC!M5 -> 46387 | N6: =MOIC!N5 -> 46418 | O6: =MOIC!O5 -> 46446 | ... BP6: =MOIC!BP5 -> 48060
C7: Curve in use (selected) | D7: % p.a. | E7: =Inputs!E112 -> 1M EURIBOR Jul-26 | H7: =INDEX(H$9:H$11,MATCH($E$7,$C$9:$C$11,0)) -> 0.02204 | I7: =INDEX(I$9:I$11,MATCH($E$7,$C$9:$C$11,0)) -> 0.0230337 | J7: =INDEX(J$9:J$11,MATCH($E$7,$C$9:$C$11,0)) -> 0.0239429 | K7: =INDEX(K$9:K$11,MATCH($E$7,$C$9:$C$11,0)) -> 0.0248091 | L7: =INDEX(L$9:L$11,MATCH($E$7,$C$9:$C$11,0)) -> 0.0256369 | M7: =INDEX(M$9:M$11,MATCH($E$7,$C$9:$C$11,0)) -> 0.0263515 | N7: =INDEX(N$9:N$11,MATCH($E$7,$C$9:$C$11,0)) -> 0.0270143 | O7: =INDEX(O$9:O$11,MATCH($E$7,$C$9:$C$11,0)) -> 0.0274756 | ... BP7: =INDEX(BP$9:BP$11,MATCH($E$7,$C$9:$C$11,0)) -> 0.0278735
C8: Available curves | D8: Unit | E8: Source | F8: Note
C9: 1M EURIBOR Aug-25 | D9: % p.a. | E9: Source: Chatham financial, 28/8/25 | F9: Monthly 1M EURIBOR forward; held flat after the last quoted month. | H9: 0.019 | I9: 0.0188 | J9: 0.0186 | K9: 0.0184 | L9: 0.0182 | M9: 0.0181 | N9: 0.018 | O9: 0.018 | P9: 0.018 | Q9: 0.018 | R9: 0.018 | S9: 0.0181 | T9: 0.0182 | U9: 0.0183 | V9: 0.0185 | W9: 0.0186 | X9: 0.0188 | Y9: 0.019 | Z9: 0.0192 | AA9: 0.0192 | AB9: 0.0192 | AC9: 0.0192 | AD9: 0.0192 | AE9: 0.0192 | AF9: 0.0192 | AG9: 0.0192 | AH9: 0.0192 | AI9: 0.0192 | AJ9: 0.0192 | AK9: 0.0192 | AL9: 0.0192 | AM9: 0.0192 | AN9: 0.0192 | AO9: 0.0192 | AP9: 0.0192 | AQ9: 0.0192 | AR9: 0.0192 | AS9: 0.0192 | AT9: 0.0192 | AU9: 0.0192 | AV9: 0.0192 | AW9: 0.0192 | AX9: 0.0192 | AY9: 0.0192 | AZ9: 0.0192 | BA9: 0.0192 | BB9: 0.0192 | BC9: 0.0192 | BD9: 0.0192 | BE9: 0.0192 | BF9: 0.0192 | BG9: 0.0192 | BH9: 0.0192 | BI9: 0.0192 | BJ9: 0.0192 | BK9: =BJ9 -> 0.0192 | BL9: =BK9 -> 0.0192 | BM9: =BL9 -> 0.0192 | BN9: =BM9 -> 0.0192 | BO9: =BN9 -> 0.0192 | BP9: =BO9 -> 0.0192
C10: 1M EURIBOR Nov-25 | D10: % p.a. | E10: Source: Chatham financial, 10/11/25 | F10: Monthly 1M EURIBOR forward; held flat after the last quoted month. | H10: 0.01891 | I10: 0.0188532 | J10: 0.0187946 | K10: 0.0187431 | L10: 0.0186996 | M10: 0.0186559 | N10: 0.0186267 | O10: 0.0186046 | P10: 0.0185936 | Q10: 0.0185946 | R10: 0.0186079 | S10: 0.0186343 | T10: 0.018673 | U10: 0.018725 | V10: 0.0187935 | W10: 0.0188776 | X10: 0.0189673 | Y10: 0.0190866 | Z10: 0.0192105 | AA10: 0.0192105 | AB10: 0.0192105 | AC10: 0.0192105 | AD10: 0.0192105 | AE10: 0.0192105 | AF10: 0.0192105 | AG10: 0.0192105 | AH10: 0.0192105 | AI10: 0.0192105 | AJ10: 0.0192105 | AK10: 0.0192105 | AL10: 0.0192105 | AM10: 0.0192105 | AN10: 0.0192105 | AO10: 0.0192105 | AP10: 0.0192105 | AQ10: 0.0192105 | AR10: 0.0192105 | AS10: 0.0192105 | AT10: 0.0192105 | AU10: 0.0192105 | AV10: 0.0192105 | AW10: 0.0192105 | AX10: 0.0192105 | AY10: 0.0192105 | AZ10: 0.0192105 | BA10: 0.0192105 | BB10: 0.0192105 | BC10: 0.0192105 | BD10: 0.0192105 | BE10: 0.0192105 | BF10: 0.0192105 | BG10: 0.0192105 | BH10: 0.0192105 | BI10: 0.0192105 | BJ10: 0.0192105 | BK10: =BJ10 -> 0.0192105 | BL10: =BK10 -> 0.0192105 | BM10: =BL10 -> 0.0192105 | BN10: =BM10 -> 0.0192105 | BO10: =BN10 -> 0.0192105 | BP10: =BO10 -> 0.0192105
C11: 1M EURIBOR Jul-26 | D11: % p.a. | E11: Source: Chatham financial, 22/07/26 | F11: Monthly 1M EURIBOR forward; held flat after the last quoted month. | H11: 0.02204 | I11: 0.0230337 | J11: 0.0239429 | K11: 0.0248091 | L11: 0.0256369 | M11: 0.0263515 | N11: 0.0270143 | O11: 0.0274756 | P11: 0.0278202 | Q11: 0.0280983 | R11: 0.0282812 | S11: 0.0283804 | T11: 0.0284156 | U11: 0.0283978 | V11: 0.0283387 | W11: 0.0282487 | X11: 0.0281543 | Y11: 0.028056 | Z11: 0.0279639 | AA11: 0.0278951 | AB11: 0.0278436 | AC11: 0.0278026 | AD11: 0.0277784 | AE11: 0.027765 | AF11: 0.0277628 | AG11: 0.0277702 | AH11: 0.0277875 | AI11: 0.0278085 | AJ11: 0.0278372 | AK11: 0.0278735 | AL11: 0.0278735 | AM11: 0.0278735 | AN11: 0.0278735 | AO11: 0.0278735 | AP11: 0.0278735 | AQ11: 0.0278735 | AR11: 0.0278735 | AS11: 0.0278735 | AT11: 0.0278735 | AU11: 0.0278735 | AV11: 0.0278735 | AW11: 0.0278735 | AX11: 0.0278735 | AY11: 0.0278735 | AZ11: 0.0278735 | BA11: 0.0278735 | BB11: 0.0278735 | BC11: 0.0278735 | BD11: 0.0278735 | BE11: 0.0278735 | BF11: 0.0278735 | BG11: 0.0278735 | BH11: 0.0278735 | BI11: 0.0278735 | BJ11: 0.0278735 | BK11: =BJ11 -> 0.0278735 | BL11: =BK11 -> 0.0278735 | BM11: =BL11 -> 0.0278735 | BN11: =BM11 -> 0.0278735 | BO11: =BN11 -> 0.0278735 | BP11: =BO11 -> 0.0278735
B14: x | C14: 2. Aurora – Hungarian onshore wind capture prices (Aurora Q2 2026, real 2025 €/MWh, calendar-year averages, 2026–2060)
C15: Aurora Q2 2026 HUN Power & Renewables Market Forecast, pasted from the shared file hungary_wind_capture_price_aurora_q2_2026.json (2027–2060; the 2026 value is not needed and 2061+ is beyond the Aurora horizon – blank). Columns D:I are the source series in real 2025 €/MWh; wind capture = 'uncurtailed capture price'. Scenario selector in E16 picks Low / Central / High. Columns J:K convert the selected series to nominal using E19/G19 so they are consistent with the nominal HTM opex; HTM reads column K by year (Inputs E166 = 1). M:R are informational (curtailment %, capture curtailed below zero). The MOIC (sell-at-RTB) model does not use prices.
C16: Scenario in use (1 = Low, 2 = Central, 3 = High) | D16: Switch | E16: =Inputs!E199 -> 2 | F16: Aurora scenarios: 1 = Low, 2 = Central (base case), 3 = High.
C17: Price basis (Real 20xx / Nominal) | D17: Text | E17: Real 2025 | F17: Aurora basis: real 2025 €/MWh (calendar-year averages).
C18: Aurora release / vintage | D18: Text | E18: Aurora Q2 2026 HUN Power & Renewables Market Forecast | F18: Aurora Q2 2026 HUN Power & Renewables Market Forecast Data (Aurora_Q2_26_HUN_Power_Renewables_Market_Forecast_Data.xlsx).
C19: Inflation to convert Aurora real-2025 prices to nominal (HTM opex is nominal) | D19: % p.a. | E19: 0.02 | F19: ESTIMATE – set to 0% to run in real terms. Base year of the real series → | G19: 2025
C20: Year | D20: Baseload HUPX – Low | E20: Baseload HUPX – Central | F20: Baseload HUPX – High | G20: Wind capture – Low | H20: Wind capture – Central | I20: Wind capture – High | J20: Selected baseload (nominal) | K20: Selected wind capture (nominal) | L20: Implied capture rate | M20: Wind curtailment – Low | N20: Wind curtailment – Central | O20: Wind curtailment – High | P20: Wind capture curtailed <0 – Low | Q20: Wind capture curtailed <0 – Central | R20: Wind capture curtailed <0 – High
D21: EUR/MWh | E21: EUR/MWh | F21: EUR/MWh | G21: EUR/MWh | H21: EUR/MWh | I21: EUR/MWh | J21: EUR/MWh nominal | K21: EUR/MWh nominal | L21: % | M21: % (info) | N21: % (info) | O21: % (info) | P21: EUR/MWh (info) | Q21: EUR/MWh (info) | R21: EUR/MWh (info)
C22: 2027 | D22: 73.88 | E22: 119.34 | F22: 184.66 | G22: 76.68 | H22: 124.38 | I22: 190.39 | J22: {=IF(INDEX(D22:F22,$E$16)="","",INDEX(D22:F22,$E$16)*(1+$E$19)^($C22-$G$19))} -> 124.16134 | K22: {=IF(INDEX(G22:I22,$E$16)="","",INDEX(G22:I22,$E$16)*(1+$E$19)^($C22-$G$19))} -> 129.40495 | L22: =IF(OR(J22="",K22="",J22=0),"",K22/J22) -> 1.0422323 | M22: 0.048 | N22: 0.039 | O22: 0.015 | P22: 80.72 | Q22: 129.58 | R22: 193.34
C23: 2028 | D23: 70.4 | E23: 110 | F23: 160.02 | G23: 75.08 | H23: 114.23 | I23: 164.62 | J23: {=IF(INDEX(D23:F23,$E$16)="","",INDEX(D23:F23,$E$16)*(1+$E$19)^($C23-$G$19))} -> 116.73288 | K23: {=IF(INDEX(G23:I23,$E$16)="","",INDEX(G23:I23,$E$16)*(1+$E$19)^($C23-$G$19))} -> 121.22179 | L23: =IF(OR(J23="",K23="",J23=0),"",K23/J23) -> 1.0384545 | M23: 0.035 | N23: 0.034 | O23: 0.014 | P23: 78 | Q23: 118.43 | R23: 166.96
C24: 2029 | D24: 67.2 | E24: 103.08 | F24: 147.54 | G24: 69.52 | H24: 105.66 | I24: 150.51 | J24: {=IF(INDEX(D24:F24,$E$16)="","",INDEX(D24:F24,$E$16)*(1+$E$19)^($C24-$G$19))} -> 111.57711 | K24: {=IF(INDEX(G24:I24,$E$16)="","",INDEX(G24:I24,$E$16)*(1+$E$19)^($C24-$G$19))} -> 114.36978 | L24: =IF(OR(J24="",K24="",J24=0),"",K24/J24) -> 1.0250291 | M24: 0.03 | N24: 0.032 | O24: 0.01 | P24: 71.91 | Q24: 109.41 | R24: 152.07
C25: 2030 | D25: 67.66 | E25: 94.89 | F25: 131.78 | G25: 69.45 | H25: 97.72 | I25: 135.02 | J25: {=IF(INDEX(D25:F25,$E$16)="","",INDEX(D25:F25,$E$16)*(1+$E$19)^($C25-$G$19))} -> 104.76623 | K25: {=IF(INDEX(G25:I25,$E$16)="","",INDEX(G25:I25,$E$16)*(1+$E$19)^($C25-$G$19))} -> 107.89078 | L25: =IF(OR(J25="",K25="",J25=0),"",K25/J25) -> 1.029824 | M25: 0.027 | N25: 0.021 | O25: 0.006 | P25: 71.57 | Q25: 99.99 | R25: 135.96
C26: 2031 | D26: 68.83 | E26: 98.51 | F26: 132.57 | G26: 71.22 | H26: 102.77 | I26: 135.86 | J26: {=IF(INDEX(D26:F26,$E$16)="","",INDEX(D26:F26,$E$16)*(1+$E$19)^($C26-$G$19))} -> 110.93826 | K26: {=IF(INDEX(G26:I26,$E$16)="","",INDEX(G26:I26,$E$16)*(1+$E$19)^($C26-$G$19))} -> 115.73571 | L26: =IF(OR(J26="",K26="",J26=0),"",K26/J26) -> 1.0432443 | M26: 0.015 | N26: 0.026 | O26: 0.005 | P26: 72.37 | Q26: 105.75 | R26: 136.51
C27: 2032 | D27: 66.42 | E27: 96.1 | F27: 123.49 | G27: 68.56 | H27: 99.64 | I27: 126.56 | J27: {=IF(INDEX(D27:F27,$E$16)="","",INDEX(D27:F27,$E$16)*(1+$E$19)^($C27-$G$19))} -> 110.38869 | K27: {=IF(INDEX(G27:I27,$E$16)="","",INDEX(G27:I27,$E$16)*(1+$E$19)^($C27-$G$19))} -> 114.45504 | L27: =IF(OR(J27="",K27="",J27=0),"",K27/J27) -> 1.0368366 | M27: 0.005 | N27: 0.014 | O27: 0.005 | P27: 68.92 | Q27: 101.17 | R27: 127.15
C28: 2033 | D28: 66.19 | E28: 96.72 | F28: 122.89 | G28: 68.19 | H28: 100.09 | I28: 126.03 | J28: {=IF(INDEX(D28:F28,$E$16)="","",INDEX(D28:F28,$E$16)*(1+$E$19)^($C28-$G$19))} -> 113.3229 | K28: {=IF(INDEX(G28:I28,$E$16)="","",INDEX(G28:I28,$E$16)*(1+$E$19)^($C28-$G$19))} -> 117.27139 | L28: =IF(OR(J28="",K28="",J28=0),"",K28/J28) -> 1.0348428 | M28: 0.004 | N28: 0.017 | O28: 0.002 | P28: 68.45 | Q28: 101.91 | R28: 126.36
C29: 2034 | D29: 62.4 | E29: 93.13 | F29: 116.85 | G29: 64.51 | H29: 96.3 | I29: 119.86 | J29: {=IF(INDEX(D29:F29,$E$16)="","",INDEX(D29:F29,$E$16)*(1+$E$19)^($C29-$G$19))} -> 111.29897 | K29: {=IF(INDEX(G29:I29,$E$16)="","",INDEX(G29:I29,$E$16)*(1+$E$19)^($C29-$G$19))} -> 115.08741 | L29: =IF(OR(J29="",K29="",J29=0),"",K29/J29) -> 1.0340384 | M29: 0.002 | N29: 0.004 | O29: 0.001 | P29: 64.65 | Q29: 96.69 | R29: 119.95
C30: 2035 | D30: 61.87 | E30: 92.97 | F30: 115.61 | G30: 63.86 | H30: 96.08 | I30: 118.57 | J30: {=IF(INDEX(D30:F30,$E$16)="","",INDEX(D30:F30,$E$16)*(1+$E$19)^($C30-$G$19))} -> 113.32991 | K30: {=IF(INDEX(G30:I30,$E$16)="","",INDEX(G30:I30,$E$16)*(1+$E$19)^($C30-$G$19))} -> 117.12098 | L30: =IF(OR(J30="",K30="",J30=0),"",K30/J30) -> 1.0334517 | M30: 0.003 | N30: 0.001 | O30: 0.001 | P30: 64.06 | Q30: 96.21 | R30: 118.67
C31: 2036 | D31: 62.29 | E31: 93.04 | F31: 116.98 | G31: 64.21 | H31: 96.19 | I31: 120.17 | J31: {=IF(INDEX(D31:F31,$E$16)="","",INDEX(D31:F31,$E$16)*(1+$E$19)^($C31-$G$19))} -> 115.68355 | K31: {=IF(INDEX(G31:I31,$E$16)="","",INDEX(G31:I31,$E$16)*(1+$E$19)^($C31-$G$19))} -> 119.60017 | L31: =IF(OR(J31="",K31="",J31=0),"",K31/J31) -> 1.0338564 | M31: 0 | N31: 0.001 | O31: 0 | P31: 64.21 | Q31: 96.26 | R31: 120.17
C32: 2037 | D32: 64.78 | E32: 96.63 | F32: 121.54 | G32: 66.78 | H32: 99.52 | I32: 124.51 | J32: {=IF(INDEX(D32:F32,$E$16)="","",INDEX(D32:F32,$E$16)*(1+$E$19)^($C32-$G$19))} -> 122.5502 | K32: {=IF(INDEX(G32:I32,$E$16)="","",INDEX(G32:I32,$E$16)*(1+$E$19)^($C32-$G$19))} -> 126.21542 | L32: =IF(OR(J32="",K32="",J32=0),"",K32/J32) -> 1.0299079 | M32: 0 | N32: 0.001 | O32: 0 | P32: 66.78 | Q32: 99.59 | R32: 124.51
C33: 2038 | D33: 64.13 | E33: 95.76 | F33: 121.06 | G33: 66.1 | H33: 98.19 | I33: 123.84 | J33: {=IF(INDEX(D33:F33,$E$16)="","",INDEX(D33:F33,$E$16)*(1+$E$19)^($C33-$G$19))} -> 123.87577 | K33: {=IF(INDEX(G33:I33,$E$16)="","",INDEX(G33:I33,$E$16)*(1+$E$19)^($C33-$G$19))} -> 127.01924 | L33: =IF(OR(J33="",K33="",J33=0),"",K33/J33) -> 1.0253759 | M33: 0 | N33: 0 | O33: 0 | P33: 66.1 | Q33: 98.22 | R33: 123.84
... C55: 2060 | D55: 57.56 | E55: 92.71 | F55: 111.08 | G55: 58.1 | H55: 93.36 | I55: 103 | J55: {=IF(INDEX(D55:F55,$E$16)="","",INDEX(D55:F55,$E$16)*(1+$E$19)^($C55-$G$19))} -> 185.40976 | K55: {=IF(INDEX(G55:I55,$E$16)="","",INDEX(G55:I55,$E$16)*(1+$E$19)^($C55-$G$19))} -> 186.70969 | L55: =IF(OR(J55="",K55="",J55=0),"",K55/J55) -> 1.0070111 | M55: 0 | N55: 0 | O55: 0 | P55: 58.1 | Q55: 93.36 | R55: 103
C56: 2061 | J56: {=IF(INDEX(D56:F56,$E$16)="","",INDEX(D56:F56,$E$16)*(1+$E$19)^($C56-$G$19))} | K56: {=IF(INDEX(G56:I56,$E$16)="","",INDEX(G56:I56,$E$16)*(1+$E$19)^($C56-$G$19))} | L56: =IF(OR(J56="",K56="",J56=0),"",K56/J56)
C57: 2062 | J57: {=IF(INDEX(D57:F57,$E$16)="","",INDEX(D57:F57,$E$16)*(1+$E$19)^($C57-$G$19))} | K57: {=IF(INDEX(G57:I57,$E$16)="","",INDEX(G57:I57,$E$16)*(1+$E$19)^($C57-$G$19))} | L57: =IF(OR(J57="",K57="",J57=0),"",K57/J57)
C58: 2063 | J58: {=IF(INDEX(D58:F58,$E$16)="","",INDEX(D58:F58,$E$16)*(1+$E$19)^($C58-$G$19))} | K58: {=IF(INDEX(G58:I58,$E$16)="","",INDEX(G58:I58,$E$16)*(1+$E$19)^($C58-$G$19))} | L58: =IF(OR(J58="",K58="",J58=0),"",K58/J58)
C59: 2064 | J59: {=IF(INDEX(D59:F59,$E$16)="","",INDEX(D59:F59,$E$16)*(1+$E$19)^($C59-$G$19))} | K59: {=IF(INDEX(G59:I59,$E$16)="","",INDEX(G59:I59,$E$16)*(1+$E$19)^($C59-$G$19))} | L59: =IF(OR(J59="",K59="",J59=0),"",K59/J59)
C60: 2065 | J60: {=IF(INDEX(D60:F60,$E$16)="","",INDEX(D60:F60,$E$16)*(1+$E$19)^($C60-$G$19))} | K60: {=IF(INDEX(G60:I60,$E$16)="","",INDEX(G60:I60,$E$16)*(1+$E$19)^($C60-$G$19))} | L60: =IF(OR(J60="",K60="",J60=0),"",K60/J60)
C61: 2066 | J61: {=IF(INDEX(D61:F61,$E$16)="","",INDEX(D61:F61,$E$16)*(1+$E$19)^($C61-$G$19))} | K61: {=IF(INDEX(G61:I61,$E$16)="","",INDEX(G61:I61,$E$16)*(1+$E$19)^($C61-$G$19))} | L61: =IF(OR(J61="",K61="",J61=0),"",K61/J61)
C62: 2067 | J62: {=IF(INDEX(D62:F62,$E$16)="","",INDEX(D62:F62,$E$16)*(1+$E$19)^($C62-$G$19))} | K62: {=IF(INDEX(G62:I62,$E$16)="","",INDEX(G62:I62,$E$16)*(1+$E$19)^($C62-$G$19))} | L62: =IF(OR(J62="",K62="",J62=0),"",K62/J62)
C63: 2068 | J63: {=IF(INDEX(D63:F63,$E$16)="","",INDEX(D63:F63,$E$16)*(1+$E$19)^($C63-$G$19))} | K63: {=IF(INDEX(G63:I63,$E$16)="","",INDEX(G63:I63,$E$16)*(1+$E$19)^($C63-$G$19))} | L63: =IF(OR(J63="",K63="",J63=0),"",K63/J63)
C64: 2069 | J64: {=IF(INDEX(D64:F64,$E$16)="","",INDEX(D64:F64,$E$16)*(1+$E$19)^($C64-$G$19))} | K64: {=IF(INDEX(G64:I64,$E$16)="","",INDEX(G64:I64,$E$16)*(1+$E$19)^($C64-$G$19))} | L64: =IF(OR(J64="",K64="",J64=0),"",K64/J64)
C65: 2070 | J65: {=IF(INDEX(D65:F65,$E$16)="","",INDEX(D65:F65,$E$16)*(1+$E$19)^($C65-$G$19))} | K65: {=IF(INDEX(G65:I65,$E$16)="","",INDEX(G65:I65,$E$16)*(1+$E$19)^($C65-$G$19))} | L65: =IF(OR(J65="",K65="",J65=0),"",K65/J65)
C66: 2071 | J66: {=IF(INDEX(D66:F66,$E$16)="","",INDEX(D66:F66,$E$16)*(1+$E$19)^($C66-$G$19))} | K66: {=IF(INDEX(G66:I66,$E$16)="","",INDEX(G66:I66,$E$16)*(1+$E$19)^($C66-$G$19))} | L66: =IF(OR(J66="",K66="",J66=0),"",K66/J66)
C68: Derived (informational – HTM reads column K directly)
C69: First operating year (COD year + 1, from Inputs!E155) | D69: Year | E69: =YEAR(Inputs!E101)+1 -> 2031
C70: Selected baseload price in first operating year | D70: EUR/MWh | E70: =IFERROR(IF(INDEX($J$22:$J$66,MATCH(E69,$C$22:$C$66,0))="","",INDEX($J$22:$J$66,MATCH(E69,$C$22:$C$66,0))),"") -> 110.93826
C71: Selected wind capture price in first operating year | D71: EUR/MWh | E71: =IFERROR(IF(INDEX($K$22:$K$66,MATCH(E69,$C$22:$C$66,0))="","",INDEX($K$22:$K$66,MATCH(E69,$C$22:$C$66,0))),"") -> 115.73571
C72: Average capture rate over populated years | D72: % | E72: =IF(COUNT($L$22:$L$66)=0,"",AVERAGE($L$22:$L$66)) -> 1.0247019
C73: Implied baseload escalation (CAGR over populated years) | D73: % p.a. | E73: {=IF(COUNT($J$22:$J$66)<2,"",(LOOKUP(9.99E+307,$J$22:$J$66)/INDEX($J$22:$J$66,MATCH(TRUE,INDEX($J$22:$J$66<>"",0),0)))^(1/(COUNT($J$22:$J$66)-1))-1)} -> 0.01222523

Sheet Deposits
A1: Bora Onshore Wind – MOIC model v5
A2: Deposits – tender securities and grid connection schedule. Gross = unit rate × capacity basis; Netting applies the source rules (bid bond credited into the performance bond, 50% supplementary refund at building permit with later instalments stepped down, ÁSZ securities credited against the connection fee). Payable = Gross + Netting. Positive = cash out, negative = cash in.
A3: No inputs on this sheet – every value derives from Inputs. Hungarian item names are kept so the schedule ties back to Bora_csatlakozási_biztosítékok_díjak.xlsx.
C5: Item (HU) | D5: Item (EN) | E5: Basis | F5: Unit rate | G5: Capacity basis | H5: Gross | I5: Netting / adjustment | J5: Payable | K5: Payment date | L5: Grid month | M5: Payable | N5: After sale? | O5: Included in FEP cash flows | P5: Cash (1) / guarantee (0) | Q5: Recovered at exit | R5: Type | S5: Gross – FEP basis | T5: Payable – FEP basis | U5: Funded at 12% (recoverable / agreed) | W5: FEP rate (12% cash / 6% guarantee) | X5: FEP accrual factor to the RtB sale, pause excluded (= Z × AB) | Y5: FEP-convention interest to the RtB sale (pause excluded) | Z5: Segment 1 to the RtB sale: payment → MIN(sale, pause start) (row 6) | AA5: Segment 2 start = MAX(payment, pause end) (row 6 = Inputs E73) | AB5: Segment 2 to the RtB sale (row 6 = Inputs E58) | AC5: Segment 1 to the COD sale: payment → MIN(COD, pause start) | AD5: Segment 2 to the COD sale (row 6 = Inputs E155) | AE5: FEP accrual factor to the COD sale (= AC × AD) | AF5: FEP-convention interest to the COD sale (HTM row 367) | AG5: Memo: accrual days to the RtB sale excl. the pause (both ends counted, as the Devex stubs) | AH5: Memo: accrual days to the COD sale excl. the pause
F6: mHUF/MW or mHUF | G6: MW | H6: mHUF | I6: mHUF | J6: mHUF | K6: Date | L6: # | M6: k€ | N6: Flag | O6: k€ | P6: Switch | Q6: % | S6: mHUF | T6: mHUF | U6: % | W6: % | X6: x | Y6: k€ | Z6: =MIN(Inputs!$E$58,Inputs!$E$64) -> 47299 | AA6: =Inputs!$E$73 -> 47484 | AB6: =Inputs!$E$58 -> 47573 | AC6: =MIN(Inputs!$E$155,Inputs!$E$64) -> 47299 | AD6: =Inputs!$E$155 -> 48121 | AE6: x | AF6: k€ | AG6: days | AH6: days
C7: Részvételi díj | D7: Participation fee | E7: per bid × bids | F7: =Inputs!$E$81 -> 3 | G7: =Inputs!$E$82 -> 2 | H7: =F7*G7 -> 6 | I7: 0 | J7: =H7+I7 -> 6 | K7: =Inputs!$E$95 -> 46325 | L7: =IF(K7="","",(YEAR(K7)-YEAR(Inputs!$E$27))*12+MONTH(K7)-MONTH(Inputs!$E$27)) -> 3 | M7: =J7*1000/Inputs!$E$11 -> 16.438356 | N7: =IF(L7="",0,IF(L7>Inputs!$E$57,1,0)) -> 0 | O7: =M7*IF(N7=1,Inputs!$E$109,1) -> 16.438356 | P7: =Inputs!$E$117 -> 1 | Q7: =Inputs!$E$129 -> 0 | R7: Fee | S7: 0 | T7: 0 | U7: =Inputs!$E$256 -> 0 | W7: =IF(P7=1,Inputs!$E$61,Inputs!$E$65) -> 0.12 | X7: =Z7*AB7 -> 1.3967127 | Y7: =O7*(X7-1) -> 6.5213048 | Z7: =IF($K7>Z$6,1,(1+$W7*(DATE(YEAR($K7),12,31)-$K7+1)/365)*(1+$W7)^(YEAR(Z$6)-YEAR($K7)-1)*(1+$W7*(Z$6-DATE(YEAR(Z$6),1,1)+1)/365)) -> 1.356573 | AA7: =MAX($K7,AA$6) -> 47484 | AB7: =IF(AB$6<$AA7,1,(1+$W7*(DATE(YEAR($AA7),12,31)-$AA7+1)/365)*(1+$W7)^(YEAR(AB$6)-YEAR($AA7)-1)*(1+$W7*(AB$6-DATE(YEAR(AB$6),1,1)+1)/365)) -> 1.029589 | AC7: =IF($K7>AC$6,1,(1+$W7*(DATE(YEAR($K7),12,31)-$K7+1)/365)*(1+$W7)^(YEAR(AC$6)-YEAR($K7)-1)*(1+$W7*(AC$6-DATE(YEAR(AC$6),1,1)+1)/365)) -> 1.356573 | AD7: =IF(AD$6<$AA7,1,(1+$W7*(DATE(YEAR($AA7),12,31)-$AA7+1)/365)*(1+$W7)^(YEAR(AD$6)-YEAR($AA7)-1)*(1+$W7*(AD$6-DATE(YEAR(AD$6),1,1)+1)/365)) -> 1.2205238 | AE7: =AC7*AD7 -> 1.6557297 | AF7: =O7*(AE7-1) -> 10.779118 | AG7: =MAX(0,Z$6-$K7+1)+MAX(0,AB$6-AA7+1) -> 1065 | AH7: =MAX(0,AC$6-$K7+1)+MAX(0,AD$6-AA7+1) -> 1613
C8: Ajánlati biztosíték | D8: Bid bond | E8: % of combined benchmark CAPEX (wind + BESS), gross | F8: =Inputs!$E$76 -> 0.005 | G8: =Inputs!$E$91 -> 177966 | H8: =F8*G8 -> 889.83 | I8: 0 | J8: =H8+I8 -> 889.83 | K8: =Inputs!$E$95 -> 46325 | L8: =IF(K8="","",(YEAR(K8)-YEAR(Inputs!$E$27))*12+MONTH(K8)-MONTH(Inputs!$E$27)) -> 3 | M8: =J8*1000/Inputs!$E$11 -> 2437.8904 | N8: =IF(L8="",0,IF(L8>Inputs!$E$57,1,0)) -> 0 | O8: =M8*IF(N8=1,Inputs!$E$109,1) -> 2437.8904 | P8: =Inputs!$E$118 -> 0 | Q8: =Inputs!$E$130 -> 1 | R8: Security | S8: =J8 -> 889.83 | T8: =J8 -> 889.83 | U8: =Inputs!$E$257 -> 0 | W8: =IF(P8=1,Inputs!$E$61,Inputs!$E$65) -> 0.06 | X8: =Z8*AB8 -> 1.1863083 | Y8: =O8*(X8-1) -> 454.19932 | Z8: =IF($K8>Z$6,1,(1+$W8*(DATE(YEAR($K8),12,31)-$K8+1)/365)*(1+$W8)^(YEAR(Z$6)-YEAR($K8)-1)*(1+$W8*(Z$6-DATE(YEAR(Z$6),1,1)+1)/365)) -> 1.1690134 | AA8: =MAX($K8,AA$6) -> 47484 | AB8: =IF(AB$6<$AA8,1,(1+$W8*(DATE(YEAR($AA8),12,31)-$AA8+1)/365)*(1+$W8)^(YEAR(AB$6)-YEAR($AA8)-1)*(1+$W8*(AB$6-DATE(YEAR(AB$6),1,1)+1)/365)) -> 1.0147945 | AC8: =IF($K8>AC$6,1,(1+$W8*(DATE(YEAR($K8),12,31)-$K8+1)/365)*(1+$W8)^(YEAR(AC$6)-YEAR($K8)-1)*(1+$W8*(AC$6-DATE(YEAR(AC$6),1,1)+1)/365)) -> 1.1690134 | AD8: =IF(AD$6<$AA8,1,(1+$W8*(DATE(YEAR($AA8),12,31)-$AA8+1)/365)*(1+$W8)^(YEAR(AD$6)-YEAR($AA8)-1)*(1+$W8*(AD$6-DATE(YEAR(AD$6),1,1)+1)/365)) -> 1.1075693 | AE8: =AC8*AD8 -> 1.2947633 | AF8: =O8*(AE8-1) -> 718.60066 | AG8: =MAX(0,Z$6-$K8+1)+MAX(0,AB$6-AA8+1) -> 1065 | AH8: =MAX(0,AC$6-$K8+1)+MAX(0,AD$6-AA8+1) -> 1613
C9: Ajánlati biztosíték visszatérítés – sikertelen kapacitás | D9: Bid bond refund on failed capacity | E9: % of benchmark CAPEX on failed wind capacity | F9: =F8 -> 0.005 | G9: =Inputs!$E$19*Inputs!$E$75*IF(Inputs!$E$18=0,1,Inputs!$E$29/Inputs!$E$18) -> 0 | H9: =-F9*G9*Inputs!$E$110 -> 0 | I9: 0 | J9: =H9+I9 -> 0 | K9: =Inputs!$E$96 -> 46369 | L9: =IF(K9="","",(YEAR(K9)-YEAR(Inputs!$E$27))*12+MONTH(K9)-MONTH(Inputs!$E$27)) -> 5 | M9: =J9*1000/Inputs!$E$11 -> 0 | N9: =IF(L9="",0,IF(L9>Inputs!$E$57,1,0)) -> 0 | O9: =M9*IF(N9=1,Inputs!$E$109,1) -> 0 | P9: =P8 -> 0 | Q9: =Q8 -> 1 | R9: Refund | S9: =J9 -> 0 | T9: =J9 -> 0 | U9: =U8 -> 0 | W9: =IF(P9=1,Inputs!$E$61,Inputs!$E$65) -> 0.06 | X9: =Z9*AB9 -> 1.1778159 | Y9: =O9*(X9-1) -> 0 | Z9: =IF($K9>Z$6,1,(1+$W9*(DATE(YEAR($K9),12,31)-$K9+1)/365)*(1+$W9)^(YEAR(Z$6)-YEAR($K9)-1)*(1+$W9*(Z$6-DATE(YEAR(Z$6),1,1)+1)/365)) -> 1.1606447 | AA9: =MAX($K9,AA$6) -> 47484 | AB9: =IF(AB$6<$AA9,1,(1+$W9*(DATE(YEAR($AA9),12,31)-$AA9+1)/365)*(1+$W9)^(YEAR(AB$6)-YEAR($AA9)-1)*(1+$W9*(AB$6-DATE(YEAR(AB$6),1,1)+1)/365)) -> 1.0147945 | AC9: =IF($K9>AC$6,1,(1+$W9*(DATE(YEAR($K9),12,31)-$K9+1)/365)*(1+$W9)^(YEAR(AC$6)-YEAR($K9)-1)*(1+$W9*(AC$6-DATE(YEAR(AC$6),1,1)+1)/365)) -> 1.1606447 | AD9: =IF(AD$6<$AA9,1,(1+$W9*(DATE(YEAR($AA9),12,31)-$AA9+1)/365)*(1+$W9)^(YEAR(AD$6)-YEAR($AA9)-1)*(1+$W9*(AD$6-DATE(YEAR(AD$6),1,1)+1)/365)) -> 1.1075693 | AE9: =AC9*AD9 -> 1.2854944 | AF9: =O9*(AE9-1) -> 0 | AG9: =MAX(0,Z$6-$K9+1)+MAX(0,AB$6-AA9+1) -> 1021 | AH9: =MAX(0,AC$6-$K9+1)+MAX(0,AD$6-AA9+1) -> 1569
C10: Teljesítési biztosíték | D10: Performance bond | E10: % of combined benchmark CAPEX (wind + BESS), post-award, x uplift | F10: =Inputs!$E$77*Inputs!$E$90 -> 0.0375 | G10: =Inputs!$E$92 -> 177966 | H10: =F10*G10 -> 6673.725 | I10: =-$H$8*Inputs!$E$107 -> -889.83 | J10: =H10+I10 -> 5783.895 | K10: =Inputs!$E$96+Inputs!$E$102 -> 46386 | L10: =IF(K10="","",(YEAR(K10)-YEAR(Inputs!$E$27))*12+MONTH(K10)-MONTH(Inputs!$E$27)) -> 5 | M10: =J10*1000/Inputs!$E$11 -> 15846.288 | N10: =IF(L10="",0,IF(L10>Inputs!$E$57,1,0)) -> 0 | O10: =M10*IF(N10=1,Inputs!$E$109,1) -> 15846.288 | P10: =Inputs!$E$119 -> 0 | Q10: =Inputs!$E$131 -> 1 | R10: Security | S10: =J10+J8 -> 6673.725 | T10: =J10 -> 5783.895 | U10: =Inputs!$E$258 -> 0 | W10: =IF(P10=1,Inputs!$E$61,Inputs!$E$65) -> 0.06 | X10: =Z10*AB10 -> 1.1745347 | Y10: =O10*(X10-1) -> 2765.7269 | Z10: =IF($K10>Z$6,1,(1+$W10*(DATE(YEAR($K10),12,31)-$K10+1)/365)*(1+$W10)^(YEAR(Z$6)-YEAR($K10)-1)*(1+$W10*(Z$6-DATE(YEAR(Z$6),1,1)+1)/365)) -> 1.1574113 | AA10: =MAX($K10,AA$6) -> 47484 | AB10: =IF(AB$6<$AA10,1,(1+$W10*(DATE(YEAR($AA10),12,31)-$AA10+1)/365)*(1+$W10)^(YEAR(AB$6)-YEAR($AA10)-1)*(1+$W10*(AB$6-DATE(YEAR(AB$6),1,1)+1)/365)) -> 1.0147945 | AC10: =IF($K10>AC$6,1,(1+$W10*(DATE(YEAR($K10),12,31)-$K10+1)/365)*(1+$W10)^(YEAR(AC$6)-YEAR($K10)-1)*(1+$W10*(AC$6-DATE(YEAR(AC$6),1,1)+1)/365)) -> 1.1574113 | AD10: =IF(AD$6<$AA10,1,(1+$W10*(DATE(YEAR($AA10),12,31)-$AA10+1)/365)*(1+$W10)^(YEAR(AD$6)-YEAR($AA10)-1)*(1+$W10*(AD$6-DATE(YEAR(AD$6),1,1)+1)/365)) -> 1.1075693 | AE10: =AC10*AD10 -> 1.2819133 | AF10: =O10*(AE10-1) -> 4467.279 | AG10: =MAX(0,Z$6-$K10+1)+MAX(0,AB$6-AA10+1) -> 1004 | AH10: =MAX(0,AC$6-$K10+1)+MAX(0,AD$6-AA10+1) -> 1552
C11: Igénybejelentési biztosíték | D11: Connection request security | E11: per MW (successful capacity) | F11: =Inputs!$E$83 -> 4.5 | G11: =Inputs!$E$18 -> 200 | H11: =F11*G11 -> 900 | I11: 0 | J11: =H11+I11 -> 900 | K11: =Inputs!$E$97 -> 46386 | L11: =IF(K11="","",(YEAR(K11)-YEAR(Inputs!$E$27))*12+MONTH(K11)-MONTH(Inputs!$E$27)) -> 5 | M11: =J11*1000/Inputs!$E$11 -> 2465.7534 | N11: =IF(L11="",0,IF(L11>Inputs!$E$57,1,0)) -> 0 | O11: =M11*IF(N11=1,Inputs!$E$109,1) -> 2465.7534 | P11: =Inputs!$E$120 -> 1 | Q11: =Inputs!$E$132 -> 1 | R11: Security | S11: =J11 -> 900 | T11: =J11 -> 900 | U11: =Inputs!$E$259 -> 1 | W11: =IF(P11=1,Inputs!$E$61,Inputs!$E$65) -> 0.12 | X11: =Z11*AB11 -> 1.3692703 | Y11: =O11*(X11-1) -> 910.52956 | Z11: =IF($K11>Z$6,1,(1+$W11*(DATE(YEAR($K11),12,31)-$K11+1)/365)*(1+$W11)^(YEAR(Z$6)-YEAR($K11)-1)*(1+$W11*(Z$6-DATE(YEAR(Z$6),1,1)+1)/365)) -> 1.3299193 | AA11: =MAX($K11,AA$6) -> 47484 | AB11: =IF(AB$6<$AA11,1,(1+$W11*(DATE(YEAR($AA11),12,31)-$AA11+1)/365)*(1+$W11)^(YEAR(AB$6)-YEAR($AA11)-1)*(1+$W11*(AB$6-DATE(YEAR(AB$6),1,1)+1)/365)) -> 1.029589 | AC11: =IF($K11>AC$6,1,(1+$W11*(DATE(YEAR($K11),12,31)-$K11+1)/365)*(1+$W11)^(YEAR(AC$6)-YEAR($K11)-1)*(1+$W11*(AC$6-DATE(YEAR(AC$6),1,1)+1)/365)) -> 1.3299193 | AD11: =IF(AD$6<$AA11,1,(1+$W11*(DATE(YEAR($AA11),12,31)-$AA11+1)/365)*(1+$W11)^(YEAR(AD$6)-YEAR($AA11)-1)*(1+$W11*(AD$6-DATE(YEAR(AD$6),1,1)+1)/365)) -> 1.2205238 | AE11: =AC11*AD11 -> 1.6231982 | AF11: =O11*(AE11-1) -> 1536.6531 | AG11: =MAX(0,Z$6-$K11+1)+MAX(0,AB$6-AA11+1) -> 1004 | AH11: =MAX(0,AC$6-$K11+1)+MAX(0,AD$6-AA11+1) -> 1552
C12: Csatlakozási díj – közvetlen | D12: Grid connection fee – direct | E12: lump sum, per MW (successful capacity) | F12: =Inputs!$E$84 -> 2.541729 | G12: =Inputs!$E$18 -> 200 | H12: =F12*G12 -> 508.3458 | I12: 0 | J12: =H12+I12 -> 508.3458 | K12: =Inputs!$E$99 -> 47126 | L12: =IF(K12="","",(YEAR(K12)-YEAR(Inputs!$E$27))*12+MONTH(K12)-MONTH(Inputs!$E$27)) -> 30 | M12: =J12*1000/Inputs!$E$11 -> 1392.7282 | N12: =IF(L12="",0,IF(L12>Inputs!$E$57,1,0)) -> 0 | O12: =M12*IF(N12=1,Inputs!$E$109,1) -> 1392.7282 | P12: =Inputs!$E$121 -> 1 | Q12: =Inputs!$E$133 -> 1 | R12: Connection fee | S12: =J12 -> 508.3458 | T12: =J12 -> 508.3458 | U12: =Inputs!$E$260 -> 1 | W12: =IF(P12=1,Inputs!$E$61,Inputs!$E$65) -> 0.12 | X12: =Z12*AB12 -> 1.0886152 | Y12: =O12*(X12-1) -> 123.41683 | Z12: =IF($K12>Z$6,1,(1+$W12*(DATE(YEAR($K12),12,31)-$K12+1)/365)*(1+$W12)^(YEAR(Z$6)-YEAR($K12)-1)*(1+$W12*(Z$6-DATE(YEAR(Z$6),1,1)+1)/365)) -> 1.0573298 | AA12: =MAX($K12,AA$6) -> 47484 | AB12: =IF(AB$6<$AA12,1,(1+$W12*(DATE(YEAR($AA12),12,31)-$AA12+1)/365)*(1+$W12)^(YEAR(AB$6)-YEAR($AA12)-1)*(1+$W12*(AB$6-DATE(YEAR(AB$6),1,1)+1)/365)) -> 1.029589 | AC12: =IF($K12>AC$6,1,(1+$W12*(DATE(YEAR($K12),12,31)-$K12+1)/365)*(1+$W12)^(YEAR(AC$6)-YEAR($K12)-1)*(1+$W12*(AC$6-DATE(YEAR(AC$6),1,1)+1)/365)) -> 1.0573298 | AD12: =IF(AD$6<$AA12,1,(1+$W12*(DATE(YEAR($AA12),12,31)-$AA12+1)/365)*(1+$W12)^(YEAR(AD$6)-YEAR($AA12)-1)*(1+$W12*(AD$6-DATE(YEAR(AD$6),1,1)+1)/365)) -> 1.2205238 | AE12: =AC12*AD12 -> 1.2904962 | AF12: =O12*(AE12-1) -> 404.58226 | AG12: =MAX(0,Z$6-$K12+1)+MAX(0,AB$6-AA12+1) -> 264 | AH12: =MAX(0,AC$6-$K12+1)+MAX(0,AD$6-AA12+1) -> 812
C13: Kiegészítő biztosíték 1. részlet | D13: Supplementary security – instalment 1 | E13: per MW (successful capacity) | F13: =Inputs!$E$75*Inputs!$E$78*Inputs!$E$79 -> 0 | G13: =Inputs!$E$29 -> 261 | H13: =F13*G13 -> 0 | I13: =-H13*Inputs!$E$108*(K13>Inputs!$E$100) -> 0 | J13: =H13+I13 -> 0 | K13: =Inputs!$E$104 -> 46500 | L13: =IF(K13="","",(YEAR(K13)-YEAR(Inputs!$E$27))*12+MONTH(K13)-MONTH(Inputs!$E$27)) -> 9 | M13: =J13*1000/Inputs!$E$11 -> 0 | N13: =IF(L13="",0,IF(L13>Inputs!$E$57,1,0)) -> 0 | O13: =M13*IF(N13=1,Inputs!$E$109,1) -> 0 | P13: =Inputs!$E$122 -> 0 | Q13: =Inputs!$E$134 -> 1 | R13: Security | S13: =J13 -> 0 | T13: =J13 -> 0 | U13: =Inputs!$E$261 -> 1 | W13: =IF(P13=1,Inputs!$E$61,Inputs!$E$65) -> 0.06 | X13: =Z13*AB13 -> 1.1537551 | Y13: =O13*(X13-1) -> 0 | Z13: =IF($K13>Z$6,1,(1+$W13*(DATE(YEAR($K13),12,31)-$K13+1)/365)*(1+$W13)^(YEAR(Z$6)-YEAR($K13)-1)*(1+$W13*(Z$6-DATE(YEAR(Z$6),1,1)+1)/365)) -> 1.1369347 | AA13: =MAX($K13,AA$6) -> 47484 | AB13: =IF(AB$6<$AA13,1,(1+$W13*(DATE(YEAR($AA13),12,31)-$AA13+1)/365)*(1+$W13)^(YEAR(AB$6)-YEAR($AA13)-1)*(1+$W13*(AB$6-DATE(YEAR(AB$6),1,1)+1)/365)) -> 1.0147945 | AC13: =IF($K13>AC$6,1,(1+$W13*(DATE(YEAR($K13),12,31)-$K13+1)/365)*(1+$W13)^(YEAR(AC$6)-YEAR($K13)-1)*(1+$W13*(AC$6-DATE(YEAR(AC$6),1,1)+1)/365)) -> 1.1369347 | AD13: =IF(AD$6<$AA13,1,(1+$W13*(DATE(YEAR($AA13),12,31)-$AA13+1)/365)*(1+$W13)^(YEAR(AD$6)-YEAR($AA13)-1)*(1+$W13*(AD$6-DATE(YEAR(AD$6),1,1)+1)/365)) -> 1.1075693 | AE13: =AC13*AD13 -> 1.259234 | AF13: =O13*(AE13-1) -> 0 | AG13: =MAX(0,Z$6-$K13+1)+MAX(0,AB$6-AA13+1) -> 890 | AH13: =MAX(0,AC$6-$K13+1)+MAX(0,AD$6-AA13+1) -> 1438
C14: Kiegészítő biztosíték 2. részlet | D14: Supplementary security – instalment 2 | E14: per MW (successful capacity) | F14: =Inputs!$E$75*Inputs!$E$78*Inputs!$E$80 -> 0 | G14: =Inputs!$E$29 -> 261 | H14: =F14*G14 -> 0 | I14: =-H14*Inputs!$E$108*(K14>Inputs!$E$100) -> 0 | J14: =H14+I14 -> 0 | K14: =EDATE(Inputs!$E$104,12) -> 46866 | L14: =IF(K14="","",(YEAR(K14)-YEAR(Inputs!$E$27))*12+MONTH(K14)-MONTH(Inputs!$E$27)) -> 21 | M14: =J14*1000/Inputs!$E$11 -> 0 | N14: =IF(L14="",0,IF(L14>Inputs!$E$57,1,0)) -> 0 | O14: =M14*IF(N14=1,Inputs!$E$109,1) -> 0 | P14: =Inputs!$E$123 -> 0 | Q14: =Inputs!$E$135 -> 1 | R14: Security | S14: =J14 -> 0 | T14: =J14 -> 0 | U14: =Inputs!$E$262 -> 1 | W14: =IF(P14=1,Inputs!$E$61,Inputs!$E$65) -> 0.06 | X14: =Z14*AB14 -> 1.0884482 | Y14: =O14*(X14-1) -> 0 | Z14: =IF($K14>Z$6,1,(1+$W14*(DATE(YEAR($K14),12,31)-$K14+1)/365)*(1+$W14)^(YEAR(Z$6)-YEAR($K14)-1)*(1+$W14*(Z$6-DATE(YEAR(Z$6),1,1)+1)/365)) -> 1.0725799 | AA14: =MAX($K14,AA$6) -> 47484 | AB14: =IF(AB$6<$AA14,1,(1+$W14*(DATE(YEAR($AA14),12,31)-$AA14+1)/365)*(1+$W14)^(YEAR(AB$6)-YEAR($AA14)-1)*(1+$W14*(AB$6-DATE(YEAR(AB$6),1,1)+1)/365)) -> 1.0147945 | AC14: =IF($K14>AC$6,1,(1+$W14*(DATE(YEAR($K14),12,31)-$K14+1)/365)*(1+$W14)^(YEAR(AC$6)-YEAR($K14)-1)*(1+$W14*(AC$6-DATE(YEAR(AC$6),1,1)+1)/365)) -> 1.0725799 | AD14: =IF(AD$6<$AA14,1,(1+$W14*(DATE(YEAR($AA14),12,31)-$AA14+1)/365)*(1+$W14)^(YEAR(AD$6)-YEAR($AA14)-1)*(1+$W14*(AD$6-DATE(YEAR(AD$6),1,1)+1)/365)) -> 1.1075693 | AE14: =AC14*AD14 -> 1.1879566 | AF14: =O14*(AE14-1) -> 0 | AG14: =MAX(0,Z$6-$K14+1)+MAX(0,AB$6-AA14+1) -> 524 | AH14: =MAX(0,AC$6-$K14+1)+MAX(0,AD$6-AA14+1) -> 1072
C15: Kiegészítő biztosíték visszautalás építési engedély megszerzésekor | D15: Supplementary security refund on building permit | E15: % of instalments paid before permit | H15: 0 | I15: =-Inputs!$E$108*((K13<=Inputs!$E$100)*J13+(K14<=Inputs!$E$100)*J14+(K16<=Inputs!$E$100)*J16+(K17<=Inputs!$E$100)*J17) -> 0 | J15: =H15+I15 -> 0 | K15: =Inputs!$E$100 -> 46825 | L15: =IF(K15="","",(YEAR(K15)-YEAR(Inputs!$E$27))*12+MONTH(K15)-MONTH(Inputs!$E$27)) -> 20 | M15: =J15*1000/Inputs!$E$11 -> 0 | N15: =IF(L15="",0,IF(L15>Inputs!$E$57,1,0)) -> 0 | O15: =M15*IF(N15=1,Inputs!$E$109,1) -> 0 | P15: =P13 -> 0 | Q15: =Q13 -> 1 | R15: Refund | S15: =J15 -> 0 | T15: =J15 -> 0 | U15: =U13 -> 1 | W15: =IF(P15=1,Inputs!$E$61,Inputs!$E$65) -> 0.06 | X15: =Z15*AB15 -> 1.0954911 | Y15: =O15*(X15-1) -> 0 | Z15: =IF($K15>Z$6,1,(1+$W15*(DATE(YEAR($K15),12,31)-$K15+1)/365)*(1+$W15)^(YEAR(Z$6)-YEAR($K15)-1)*(1+$W15*(Z$6-DATE(YEAR(Z$6),1,1)+1)/365)) -> 1.0795201 | AA15: =MAX($K15,AA$6) -> 47484 | AB15: =IF(AB$6<$AA15,1,(1+$W15*(DATE(YEAR($AA15),12,31)-$AA15+1)/365)*(1+$W15)^(YEAR(AB$6)-YEAR($AA15)-1)*(1+$W15*(AB$6-DATE(YEAR(AB$6),1,1)+1)/365)) -> 1.0147945 | AC15: =IF($K15>AC$6,1,(1+$W15*(DATE(YEAR($K15),12,31)-$K15+1)/365)*(1+$W15)^(YEAR(AC$6)-YEAR($K15)-1)*(1+$W15*(AC$6-DATE(YEAR(AC$6),1,1)+1)/365)) -> 1.0795201 | AD15: =IF(AD$6<$AA15,1,(1+$W15*(DATE(YEAR($AA15),12,31)-$AA15+1)/365)*(1+$W15)^(YEAR(AD$6)-YEAR($AA15)-1)*(1+$W15*(AD$6-DATE(YEAR(AD$6),1,1)+1)/365)) -> 1.1075693 | AE15: =AC15*AD15 -> 1.1956434 | AF15: =O15*(AE15-1) -> 0 | AG15: =MAX(0,Z$6-$K15+1)+MAX(0,AB$6-AA15+1) -> 565 | AH15: =MAX(0,AC$6-$K15+1)+MAX(0,AD$6-AA15+1) -> 1113
C16: Kiegészítő biztosíték 3. részlet | D16: Supplementary security – instalment 3 | E16: per MW (successful capacity) | F16: =Inputs!$E$75*Inputs!$E$78*Inputs!$E$80 -> 0 | G16: =Inputs!$E$29 -> 261 | H16: =F16*G16 -> 0 | I16: =-H16*Inputs!$E$108*(K16>Inputs!$E$100) -> 0 | J16: =H16+I16 -> 0 | K16: =EDATE(Inputs!$E$104,24) -> 47231 | L16: =IF(K16="","",(YEAR(K16)-YEAR(Inputs!$E$27))*12+MONTH(K16)-MONTH(Inputs!$E$27)) -> 33 | M16: =J16*1000/Inputs!$E$11 -> 0 | N16: =IF(L16="",0,IF(L16>Inputs!$E$57,1,0)) -> 0 | O16: =M16*IF(N16=1,Inputs!$E$109,1) -> 0 | P16: =Inputs!$E$124 -> 0 | Q16: =Inputs!$E$136 -> 1 | R16: Security | S16: =J16 -> 0 | T16: =J16 -> 0 | U16: =Inputs!$E$263 -> 1 | W16: =IF(P16=1,Inputs!$E$61,Inputs!$E$65) -> 0.06 | X16: =Z16*AB16 -> 1.0268379 | Y16: =O16*(X16-1) -> 0 | Z16: =IF($K16>Z$6,1,(1+$W16*(DATE(YEAR($K16),12,31)-$K16+1)/365)*(1+$W16)^(YEAR(Z$6)-YEAR($K16)-1)*(1+$W16*(Z$6-DATE(YEAR(Z$6),1,1)+1)/365)) -> 1.0118678 | AA16: =MAX($K16,AA$6) -> 47484 | AB16: =IF(AB$6<$AA16,1,(1+$W16*(DATE(YEAR($AA16),12,31)-$AA16+1)/365)*(1+$W16)^(YEAR(AB$6)-YEAR($AA16)-1)*(1+$W16*(AB$6-DATE(YEAR(AB$6),1,1)+1)/365)) -> 1.0147945 | AC16: =IF($K16>AC$6,1,(1+$W16*(DATE(YEAR($K16),12,31)-$K16+1)/365)*(1+$W16)^(YEAR(AC$6)-YEAR($K16)-1)*(1+$W16*(AC$6-DATE(YEAR(AC$6),1,1)+1)/365)) -> 1.0118678 | AD16: =IF(AD$6<$AA16,1,(1+$W16*(DATE(YEAR($AA16),12,31)-$AA16+1)/365)*(1+$W16)^(YEAR(AD$6)-YEAR($AA16)-1)*(1+$W16*(AD$6-DATE(YEAR(AD$6),1,1)+1)/365)) -> 1.1075693 | AE16: =AC16*AD16 -> 1.1207137 | AF16: =O16*(AE16-1) -> 0 | AG16: =MAX(0,Z$6-$K16+1)+MAX(0,AB$6-AA16+1) -> 159 | AH16: =MAX(0,AC$6-$K16+1)+MAX(0,AD$6-AA16+1) -> 707
C17: Kiegészítő biztosíték 4. részlet | D17: Supplementary security – instalment 4 | E17: per MW (successful capacity) | F17: =Inputs!$E$75*Inputs!$E$78*Inputs!$E$80 -> 0 | G17: =Inputs!$E$29 -> 261 | H17: =F17*G17 -> 0 | I17: =-H17*Inputs!$E$108*(K17>Inputs!$E$100) -> 0 | J17: =H17+I17 -> 0 | K17: =EDATE(Inputs!$E$104,36) -> 47596 | L17: =IF(K17="","",(YEAR(K17)-YEAR(Inputs!$E$27))*12+MONTH(K17)-MONTH(Inputs!$E$27)) -> 45 | M17: =J17*1000/Inputs!$E$11 -> 0 | N17: =IF(L17="",0,IF(L17>Inputs!$E$57,1,0)) -> 1 | O17: =M17*IF(N17=1,Inputs!$E$109,1) -> 0 | P17: =Inputs!$E$125 -> 0 | Q17: =Inputs!$E$137 -> 1 | R17: Security | S17: 0 | T17: 0 | U17: =Inputs!$E$264 -> 1 | W17: =IF(P17=1,Inputs!$E$61,Inputs!$E$65) -> 0.06 | X17: =Z17*AB17 -> 1 | Y17: =O17*(X17-1) -> 0 | Z17: =IF($K17>Z$6,1,(1+$W17*(DATE(YEAR($K17),12,31)-$K17+1)/365)*(1+$W17)^(YEAR(Z$6)-YEAR($K17)-1)*(1+$W17*(Z$6-DATE(YEAR(Z$6),1,1)+1)/365)) -> 1 | AA17: =MAX($K17,AA$6) -> 47596 | AB17: =IF(AB$6<$AA17,1,(1+$W17*(DATE(YEAR($AA17),12,31)-$AA17+1)/365)*(1+$W17)^(YEAR(AB$6)-YEAR($AA17)-1)*(1+$W17*(AB$6-DATE(YEAR(AB$6),1,1)+1)/365)) -> 1 | AC17: =IF($K17>AC$6,1,(1+$W17*(DATE(YEAR($K17),12,31)-$K17+1)/365)*(1+$W17)^(YEAR(AC$6)-YEAR($K17)-1)*(1+$W17*(AC$6-DATE(YEAR(AC$6),1,1)+1)/365)) -> 1 | AD17: =IF(AD$6<$AA17,1,(1+$W17*(DATE(YEAR($AA17),12,31)-$AA17+1)/365)*(1+$W17)^(YEAR(AD$6)-YEAR($AA17)-1)*(1+$W17*(AD$6-DATE(YEAR(AD$6),1,1)+1)/365)) -> 1.0883321 | AE17: =AC17*AD17 -> 1.0883321 | AF17: =O17*(AE17-1) -> 0 | AG17: =MAX(0,Z$6-$K17+1)+MAX(0,AB$6-AA17+1) -> 0 | AH17: =MAX(0,AC$6-$K17+1)+MAX(0,AD$6-AA17+1) -> 526
C18: Csatlakozási díj – becsült összeg | D18: Grid connection fee (estimate) | E18: per MW (successful capacity) | F18: =Inputs!$E$85 -> 73.071306 | G18: =Inputs!$E$18 -> 200 | H18: =F18*G18 -> 14614.261 | I18: =-J11 -> -900 | J18: =H18+I18 -> 13714.261 | K18: =Inputs!$E$99 -> 47126 | L18: =IF(K18="","",(YEAR(K18)-YEAR(Inputs!$E$27))*12+MONTH(K18)-MONTH(Inputs!$E$27)) -> 30 | M18: =J18*1000/Inputs!$E$11 -> 37573.318 | N18: =IF(L18="",0,IF(L18>Inputs!$E$57,1,0)) -> 0 | O18: =M18*IF(N18=1,Inputs!$E$109,1) -> 37573.318 | P18: =Inputs!$E$126 -> 1 | Q18: =Inputs!$E$138 -> 1 | R18: Connection fee | S18: =J18+J11 -> 14614.261 | T18: =J18 -> 13714.261 | U18: =Inputs!$E$265 -> 1 | W18: =IF(P18=1,Inputs!$E$61,Inputs!$E$65) -> 0.12 | X18: =Z18*AB18 -> 1.0886152 | Y18: =O18*(X18-1) -> 3329.5654 | Z18: =IF($K18>Z$6,1,(1+$W18*(DATE(YEAR($K18),12,31)-$K18+1)/365)*(1+$W18)^(YEAR(Z$6)-YEAR($K18)-1)*(1+$W18*(Z$6-DATE(YEAR(Z$6),1,1)+1)/365)) -> 1.0573298 | AA18: =MAX($K18,AA$6) -> 47484 | AB18: =IF(AB$6<$AA18,1,(1+$W18*(DATE(YEAR($AA18),12,31)-$AA18+1)/365)*(1+$W18)^(YEAR(AB$6)-YEAR($AA18)-1)*(1+$W18*(AB$6-DATE(YEAR(AB$6),1,1)+1)/365)) -> 1.029589 | AC18: =IF($K18>AC$6,1,(1+$W18*(DATE(YEAR($K18),12,31)-$K18+1)/365)*(1+$W18)^(YEAR(AC$6)-YEAR($K18)-1)*(1+$W18*(AC$6-DATE(YEAR(AC$6),1,1)+1)/365)) -> 1.0573298 | AD18: =IF(AD$6<$AA18,1,(1+$W18*(DATE(YEAR($AA18),12,31)-$AA18+1)/365)*(1+$W18)^(YEAR(AD$6)-YEAR($AA18)-1)*(1+$W18*(AD$6-DATE(YEAR(AD$6),1,1)+1)/365)) -> 1.2205238 | AE18: =AC18*AD18 -> 1.2904962 | AF18: =O18*(AE18-1) -> 10914.906 | AG18: =MAX(0,Z$6-$K18+1)+MAX(0,AB$6-AA18+1) -> 264 | AH18: =MAX(0,AC$6-$K18+1)+MAX(0,AD$6-AA18+1) -> 812
C19: Total | H19: =SUM(H7:H18) -> 23592.162 | I19: =SUM(I7:I18) -> -1789.83 | J19: =SUM(J7:J18) -> 21802.332 | M19: =SUM(M7:M18) -> 59732.416 | O19: =SUM(O7:O18) -> 59732.416 | S19: =SUM(S7:S18) -> 23586.162 | T19: =SUM(T7:T18) -> 21796.332 | Y19: =SUM(Y7:Y18) -> 7589.9593
B21: x | C21: Summary and reconciliation to source table | W21: FEP-convention interest by type (BORA Devex method; to the exit date, interest pause excluded) – column Y to the RtB sale, column AF to the COD sale | AF21: To the COD sale
C22: Gross securities and fees – model capacity | D22: mHUF | E22: =H19 -> 23592.162 | W22: Bank-guarantee securities (6%, net of refunds) | Y22: =SUMIFS(Y7:Y18,P7:P18,0) -> 3219.9262 | AF22: =SUMIFS(AF7:AF18,P7:P18,0) -> 5185.8797
C23: Actually payable – model capacity | D23: mHUF | E23: =J19 -> 21802.332 | W23: Cash deposits and connection fees (12%) | Y23: =SUMIFS(Y7:Y18,P7:P18,1,R7:R18,"<>Fee") -> 4363.5118 | AF23: =SUMIFS(AF7:AF18,P7:P18,1,R7:R18,"<>Fee") -> 12856.141
C24: Actually payable – model capacity | D24: k€ | E24: =M19 -> 59732.416 | W24: Participation fee (12%, no 2× minimum) | Y24: =SUMIFS(Y7:Y18,R7:R18,"Fee") -> 6.5213048 | AF24: =SUMIFS(AF7:AF18,R7:R18,"Fee") -> 10.779118
C25: Of which included in FEP cash flows (pre-sale, or all if Inputs!E92 = 1) | D25: k€ | E25: =O19 -> 59732.416
C26: Of which cash-settled (included) | D26: k€ | E26: =SUMPRODUCT(O7:O18,P7:P18) -> 41448.238
C27: Of which guarantee-backed (included) | D27: k€ | E27: {=SUMPRODUCT(O7:O18,1-P7:P18)} -> 18284.178
C28: Gross – FEP basis (excl. application fee and 2030 instalment) | D28: mHUF | E28: =S19 -> 23586.162
C29: Source gross total (excl. the source's supplementary security, row 50 – GYIK 70) | D29: mHUF | E29: =Inputs!$E$87-$E$50 -> 21173.61
C30: Difference – gross | D30: mHUF | E30: =E28-E29 -> 2412.552
C31: Payable – FEP basis (excl. application fee and 2030 instalment) | D31: mHUF | E31: =T19 -> 21796.332
C32: Source payable total (excl. the source's supplementary security, row 50 – GYIK 70) | D32: mHUF | E32: =Inputs!$E$88-$E$50 -> 19667.61
C33: Difference – payable | D33: mHUF | E33: =E31-E32 -> 2128.722
C34: Reconciliation check | D34: Status | E34: =IF(E47>0,"n/a – inputs differ from BORA_Devex source",E48) -> n/a – inputs differ from BORA_Devex source
C35: Reconciliation columns S:T restate the schedule on the BORA_Devex_20260921_FEP.xlsx basis: application fee and the 2030 supplementary instalment excluded (the FEP file zeroes the 2030 instalment as a new-owner cost; this model keeps it for the hold-to-maturity case only), gross shown before the MEKH and TSO nettings and after the supplementary refund.
C37: Bora source-driver test – Deposits E34 reads n/a when a Bora driver differs from the BORA_Devex source (1 = differs)
C38: Tender capacity (Inputs E16) vs source reference capacity (E86) | D38: 1 / 0 | E38: =IF(Inputs!$E$16<>Inputs!$E$86,1,0) -> 0
C39: Successful net capacity (Inputs E18) vs reference capacity (E86) | D39: 1 / 0 | E39: =IF(Inputs!$E$18<>Inputs!$E$86,1,0) -> 0
C40: Gross installed wind (Inputs E29) vs reference capacity (E86) – the source has no overbuild | D40: 1 / 0 | E40: =IF(Inputs!$E$29<>Inputs!$E$86,1,0) -> 1
C41: BESS MW (Inputs E20) vs BORA_Devex AF9 | D41: 1 / 0 | E41: =IF(Inputs!$E$20<>BORA_Devex!$AF$9,1,0) -> 1
C42: BESS MWh (Inputs E22) vs BORA_Devex AF10 | D42: 1 / 0 | E42: =IF(Inputs!$E$22<>BORA_Devex!$AF$10,1,0) -> 1
C43: Performance bond uplift (F10 / F8) vs source (I6 + I7) / I6 | D43: 1 / 0 | E43: =IF(ABS(F10/F8-(BORA_Devex!$I$6+BORA_Devex!$I$7)/BORA_Devex!$I$6)>Tender!$E$33,1,0) -> 0
C44: Direct connection fee (H12) vs source I19 (HUF → mHUF) | D44: 1 / 0 | E44: =IF(ABS(H12-BORA_Devex!$I$19/10^6)>Tender!$E$32,1,0) -> 0
C45: Indirect fee + TSO bond (H18) vs source (I8 + I18) (HUF → mHUF) | D45: 1 / 0 | E45: =IF(ABS(H18-(BORA_Devex!$I$8+BORA_Devex!$I$18)/10^6)>Tender!$E$32,1,0) -> 0
C46: Supplementary security in the model (H13:H17) – none in this procedure (GYIK 70); source totals restated without it (row 50) | D46: 1 / 0 | E46: =IF(SUMPRODUCT(ABS(H13:H17))>Tender!$E$32,1,0) -> 0
C47: Bora drivers differing from the BORA_Devex source | D47: # | E47: =SUM(E38:E46) -> 3
C48: Reconciliation test – gross and payable differences (E30, E33) within the tolerance | D48: Status | E48: =IF(AND(ABS(E30)<Tender!$E$32,ABS(E33)<Tender!$E$32),"OK","FAIL") -> FAIL
C50: Source supplementary security (BORA_Devex I9:I13; Bora only) – void in this procedure (GYIK 70), excluded from the source totals E29 / E32 | D50: mHUF | E50: =SUM(BORA_Devex!$I$9:$I$13)/10^6 -> 1624

Sheet MOIC
A1: =Inputs!A1 -> HUN Onshore Wind – MOIC model v5
A2: MOIC – monthly calculation grid (month 0 = investment date). No inputs on this sheet. Column G holds row totals or scalar results. Sign convention in cash-flow blocks: + = inflow to the party, − = outflow.
A3: Block 13 (sensitivity) reuses columns H:N as scenarios, not months – labelled on the block header.
C4: Month index | D4: # | H4: 0 | I4: =H4+1 -> 1 | J4: =I4+1 -> 2 | K4: =J4+1 -> 3 | L4: =K4+1 -> 4 | M4: =L4+1 -> 5 | N4: =M4+1 -> 6 | O4: =N4+1 -> 7 | P4: =O4+1 -> 8 | ... BP4: =BO4+1 -> 60
C5: Period end date | D5: Date | H5: =Inputs!$E$27 -> 46234 | I5: =EOMONTH(H5,1) -> 46265 | J5: =EOMONTH(I5,1) -> 46295 | K5: =EOMONTH(J5,1) -> 46326 | L5: =EOMONTH(K5,1) -> 46356 | M5: =EOMONTH(L5,1) -> 46387 | N5: =EOMONTH(M5,1) -> 46418 | O5: =EOMONTH(N5,1) -> 46446 | P5: =EOMONTH(O5,1) -> 46477 | ... BP5: =EOMONTH(BO5,1) -> 48060
C6: RTB flag | D6: Flag | H6: =N(H$4=Inputs!$E$55) -> 0 | I6: =N(I$4=Inputs!$E$55) -> 0 | J6: =N(J$4=Inputs!$E$55) -> 0 | K6: =N(K$4=Inputs!$E$55) -> 0 | L6: =N(L$4=Inputs!$E$55) -> 0 | M6: =N(M$4=Inputs!$E$55) -> 0 | N6: =N(N$4=Inputs!$E$55) -> 0 | O6: =N(O$4=Inputs!$E$55) -> 0 | ... BP6: =N(BP$4=Inputs!$E$55) -> 0
C7: Sale flag | D7: Flag | H7: =N(H$4=Inputs!$E$57) -> 0 | I7: =N(I$4=Inputs!$E$57) -> 0 | J7: =N(J$4=Inputs!$E$57) -> 0 | K7: =N(K$4=Inputs!$E$57) -> 0 | L7: =N(L$4=Inputs!$E$57) -> 0 | M7: =N(M$4=Inputs!$E$57) -> 0 | N7: =N(N$4=Inputs!$E$57) -> 0 | O7: =N(O$4=Inputs!$E$57) -> 0 | ... BP7: =N(BP$4=Inputs!$E$57) -> 0
C8: Development period flag (month ≤ RTB) | D8: Flag | H8: =N(H$4<=Inputs!$E$55) -> 1 | I8: =N(I$4<=Inputs!$E$55) -> 1 | J8: =N(J$4<=Inputs!$E$55) -> 1 | K8: =N(K$4<=Inputs!$E$55) -> 1 | L8: =N(L$4<=Inputs!$E$55) -> 1 | M8: =N(M$4<=Inputs!$E$55) -> 1 | N8: =N(N$4<=Inputs!$E$55) -> 1 | O8: =N(O$4<=Inputs!$E$55) -> 1 | ... BP8: =N(BP$4<=Inputs!$E$55) -> 0
C9: Pre-sale flag (month ≤ sale) | D9: Flag | H9: =N(H$4<=Inputs!$E$57) -> 1 | I9: =N(I$4<=Inputs!$E$57) -> 1 | J9: =N(J$4<=Inputs!$E$57) -> 1 | K9: =N(K$4<=Inputs!$E$57) -> 1 | L9: =N(L$4<=Inputs!$E$57) -> 1 | M9: =N(M$4<=Inputs!$E$57) -> 1 | N9: =N(N$4<=Inputs!$E$57) -> 1 | O9: =N(O$4<=Inputs!$E$57) -> 1 | ... BP9: =N(BP$4<=Inputs!$E$57) -> 0
C10: Interest accrual flag (month ≤ pause start Inputs E64, or after the pause end E73) | D10: Flag | H10: =N(OR(H$5<=Inputs!$E$64,H$5>Inputs!$E$73)) -> 1 | I10: =N(OR(I$5<=Inputs!$E$64,I$5>Inputs!$E$73)) -> 1 | J10: =N(OR(J$5<=Inputs!$E$64,J$5>Inputs!$E$73)) -> 1 | K10: =N(OR(K$5<=Inputs!$E$64,K$5>Inputs!$E$73)) -> 1 | L10: =N(OR(L$5<=Inputs!$E$64,L$5>Inputs!$E$73)) -> 1 | M10: =N(OR(M$5<=Inputs!$E$64,M$5>Inputs!$E$73)) -> 1 | N10: =N(OR(N$5<=Inputs!$E$64,N$5>Inputs!$E$73)) -> 1 | O10: =N(OR(O$5<=Inputs!$E$64,O$5>Inputs!$E$73)) -> 1 | ... BP10: =N(OR(BP$5<=Inputs!$E$64,BP$5>Inputs!$E$73)) -> 1
C11: 1. Development costs (devex) – BORA Devex line items (row 18). Milestone rows 12–17 are memo only, not used (grouped). | E11: Cum. month | F11: k€ total | G11: Total
C12: =Inputs!C41 -> Milestone 1 devex | D12: k€ | E12: =Inputs!E49 -> 0 | F12: =Inputs!E41*Inputs!$E$16 -> 0 | G12: =SUM(H12:BP12) -> 0 | H12: =IF(H$4=$E12,$F12,0) -> 0 | I12: =IF(I$4=$E12,$F12,0) -> 0 | J12: =IF(J$4=$E12,$F12,0) -> 0 | K12: =IF(K$4=$E12,$F12,0) -> 0 | L12: =IF(L$4=$E12,$F12,0) -> 0 | M12: =IF(M$4=$E12,$F12,0) -> 0 | N12: =IF(N$4=$E12,$F12,0) -> 0 | O12: =IF(O$4=$E12,$F12,0) -> 0 | ... BP12: =IF(BP$4=$E12,$F12,0) -> 0
C13: =Inputs!C42 -> Milestone 2 devex | D13: k€ | E13: =E12+Inputs!E50 -> 6 | F13: =Inputs!E42*Inputs!$E$16 -> 0 | G13: =SUM(H13:BP13) -> 0 | H13: =IF(H$4=$E13,$F13,0) -> 0 | I13: =IF(I$4=$E13,$F13,0) -> 0 | J13: =IF(J$4=$E13,$F13,0) -> 0 | K13: =IF(K$4=$E13,$F13,0) -> 0 | L13: =IF(L$4=$E13,$F13,0) -> 0 | M13: =IF(M$4=$E13,$F13,0) -> 0 | N13: =IF(N$4=$E13,$F13,0) -> 0 | O13: =IF(O$4=$E13,$F13,0) -> 0 | ... BP13: =IF(BP$4=$E13,$F13,0) -> 0
C14: =Inputs!C43 -> Milestone 3 devex | D14: k€ | E14: =E13+Inputs!E51 -> 12 | F14: =Inputs!E43*Inputs!$E$16 -> 0 | G14: =SUM(H14:BP14) -> 0 | H14: =IF(H$4=$E14,$F14,0) -> 0 | I14: =IF(I$4=$E14,$F14,0) -> 0 | J14: =IF(J$4=$E14,$F14,0) -> 0 | K14: =IF(K$4=$E14,$F14,0) -> 0 | L14: =IF(L$4=$E14,$F14,0) -> 0 | M14: =IF(M$4=$E14,$F14,0) -> 0 | N14: =IF(N$4=$E14,$F14,0) -> 0 | O14: =IF(O$4=$E14,$F14,0) -> 0 | ... BP14: =IF(BP$4=$E14,$F14,0) -> 0
C15: =Inputs!C44 -> Milestone 4 devex | D15: k€ | E15: =E14+Inputs!E52 -> 18 | F15: =Inputs!E44*Inputs!$E$16 -> 0 | G15: =SUM(H15:BP15) -> 0 | H15: =IF(H$4=$E15,$F15,0) -> 0 | I15: =IF(I$4=$E15,$F15,0) -> 0 | J15: =IF(J$4=$E15,$F15,0) -> 0 | K15: =IF(K$4=$E15,$F15,0) -> 0 | L15: =IF(L$4=$E15,$F15,0) -> 0 | M15: =IF(M$4=$E15,$F15,0) -> 0 | N15: =IF(N$4=$E15,$F15,0) -> 0 | O15: =IF(O$4=$E15,$F15,0) -> 0 | ... BP15: =IF(BP$4=$E15,$F15,0) -> 0
C16: =Inputs!C45 -> Milestone 5 devex | D16: k€ | E16: =E15+Inputs!E53 -> 25 | F16: =Inputs!E45*Inputs!$E$16 -> 0 | G16: =SUM(H16:BP16) -> 0 | H16: =IF(H$4=$E16,$F16,0) -> 0 | I16: =IF(I$4=$E16,$F16,0) -> 0 | J16: =IF(J$4=$E16,$F16,0) -> 0 | K16: =IF(K$4=$E16,$F16,0) -> 0 | L16: =IF(L$4=$E16,$F16,0) -> 0 | M16: =IF(M$4=$E16,$F16,0) -> 0 | N16: =IF(N$4=$E16,$F16,0) -> 0 | O16: =IF(O$4=$E16,$F16,0) -> 0 | ... BP16: =IF(BP$4=$E16,$F16,0) -> 0
C17: =Inputs!C46 -> Milestone 6 devex | D17: k€ | E17: =E16+Inputs!E54 -> 32 | F17: =Inputs!E46*Inputs!$E$16 -> 0 | G17: =SUM(H17:BP17) -> 0 | H17: =IF(H$4=$E17,$F17,0) -> 0 | I17: =IF(I$4=$E17,$F17,0) -> 0 | J17: =IF(J$4=$E17,$F17,0) -> 0 | K17: =IF(K$4=$E17,$F17,0) -> 0 | L17: =IF(L$4=$E17,$F17,0) -> 0 | M17: =IF(M$4=$E17,$F17,0) -> 0 | N17: =IF(N$4=$E17,$F17,0) -> 0 | O17: =IF(O$4=$E17,$F17,0) -> 0 | ... BP17: =IF(BP$4=$E17,$F17,0) -> 0
C18: Total devex (BORA Devex line items via Devex_FEP) | D18: k€ | G18: =SUM(H18:BP18) -> 2662.4662 | H18: =SUMIFS(Devex_FEP!$H$5:$H$38,Devex_FEP!$I$5:$I$38,H$4) -> 0 | I18: =SUMIFS(Devex_FEP!$H$5:$H$38,Devex_FEP!$I$5:$I$38,I$4) -> 0 | J18: =SUMIFS(Devex_FEP!$H$5:$H$38,Devex_FEP!$I$5:$I$38,J$4) -> 0 | K18: =SUMIFS(Devex_FEP!$H$5:$H$38,Devex_FEP!$I$5:$I$38,K$4) -> 177.24324 | L18: =SUMIFS(Devex_FEP!$H$5:$H$38,Devex_FEP!$I$5:$I$38,L$4) -> 0 | M18: =SUMIFS(Devex_FEP!$H$5:$H$38,Devex_FEP!$I$5:$I$38,M$4) -> 0 | N18: =SUMIFS(Devex_FEP!$H$5:$H$38,Devex_FEP!$I$5:$I$38,N$4) -> 9.7297297 | O18: =SUMIFS(Devex_FEP!$H$5:$H$38,Devex_FEP!$I$5:$I$38,O$4) -> 0 | ... BP18: =SUMIFS(Devex_FEP!$H$5:$H$38,Devex_FEP!$I$5:$I$38,BP$4) -> 0
C19: Cumulative devex | D19: k€ | H19: =H18 -> 0 | I19: =H19+I18 -> 0 | J19: =I19+J18 -> 0 | K19: =J19+K18 -> 177.24324 | L19: =K19+L18 -> 177.24324 | M19: =L19+M18 -> 177.24324 | N19: =M19+N18 -> 186.97297 | O19: =N19+O18 -> 186.97297 | P19: =O19+P18 -> 584.97297 | ... BP19: =BO19+BP18 -> 2662.4662
C20: Land costs paid by FEP – reimbursed by buyer at RtB exit (not refunded if project fails) | D20: k€ | G20: =SUM(H20:BP20) -> 425.37973 | H20: =IF(Inputs!$E$67=1,SUMIFS(Devex_FEP!$K$5:$K$38,Devex_FEP!$I$5:$I$38,H$4),0) -> 0 | I20: =IF(Inputs!$E$67=1,SUMIFS(Devex_FEP!$K$5:$K$38,Devex_FEP!$I$5:$I$38,I$4),0) -> 0 | J20: =IF(Inputs!$E$67=1,SUMIFS(Devex_FEP!$K$5:$K$38,Devex_FEP!$I$5:$I$38,J$4),0) -> 0 | K20: =IF(Inputs!$E$67=1,SUMIFS(Devex_FEP!$K$5:$K$38,Devex_FEP!$I$5:$I$38,K$4),0) -> 0 | L20: =IF(Inputs!$E$67=1,SUMIFS(Devex_FEP!$K$5:$K$38,Devex_FEP!$I$5:$I$38,L$4),0) -> 0 | M20: =IF(Inputs!$E$67=1,SUMIFS(Devex_FEP!$K$5:$K$38,Devex_FEP!$I$5:$I$38,M$4),0) -> 0 | N20: =IF(Inputs!$E$67=1,SUMIFS(Devex_FEP!$K$5:$K$38,Devex_FEP!$I$5:$I$38,N$4),0) -> 0 | O20: =IF(Inputs!$E$67=1,SUMIFS(Devex_FEP!$K$5:$K$38,Devex_FEP!$I$5:$I$38,O$4),0) -> 178.89324 | ... BP20: =IF(Inputs!$E$67=1,SUMIFS(Devex_FEP!$K$5:$K$38,Devex_FEP!$I$5:$I$38,BP$4),0) -> 0
C21: 2. Developer success fee / DSA – 2.5 k€/MW p.a. pro rata (30/360) from signing (Inputs E70) to sale, capped at Inputs E37, × installed wind MW (Inputs E29) – DSA on installed MW per BORA_Devex – user 09-Oct-26
C22: Opening balance | D22: k€/MW | H22: 0 | I22: =H24 -> 0 | J22: =I24 -> 0 | K22: =J24 -> 0 | L22: =K24 -> 0.034722222 | M22: =L24 -> 0.23611111 | N22: =M24 -> 0.45138889 | O22: =N24 -> 0.65972222 | P22: =O24 -> 0.84722222 | ... BP22: =BO24 -> 8.5763889
C23: Accrual | D23: k€/MW | H23: =Inputs!$E$38*MAX(0,MIN(Inputs!$E$37,Inputs!$E$36*N(H$5>=Inputs!$E$70)*YEARFRAC(Inputs!$E$70,MIN(H$5,Inputs!$E$58)))-H22) -> 0 | I23: =Inputs!$E$38*MAX(0,MIN(Inputs!$E$37,Inputs!$E$36*N(I$5>=Inputs!$E$70)*YEARFRAC(Inputs!$E$70,MIN(I$5,Inputs!$E$58)))-I22) -> 0 | J23: =Inputs!$E$38*MAX(0,MIN(Inputs!$E$37,Inputs!$E$36*N(J$5>=Inputs!$E$70)*YEARFRAC(Inputs!$E$70,MIN(J$5,Inputs!$E$58)))-J22) -> 0 | K23: =Inputs!$E$38*MAX(0,MIN(Inputs!$E$37,Inputs!$E$36*N(K$5>=Inputs!$E$70)*YEARFRAC(Inputs!$E$70,MIN(K$5,Inputs!$E$58)))-K22) -> 0.034722222 | L23: =Inputs!$E$38*MAX(0,MIN(Inputs!$E$37,Inputs!$E$36*N(L$5>=Inputs!$E$70)*YEARFRAC(Inputs!$E$70,MIN(L$5,Inputs!$E$58)))-L22) -> 0.20138889 | M23: =Inputs!$E$38*MAX(0,MIN(Inputs!$E$37,Inputs!$E$36*N(M$5>=Inputs!$E$70)*YEARFRAC(Inputs!$E$70,MIN(M$5,Inputs!$E$58)))-M22) -> 0.21527778 | N23: =Inputs!$E$38*MAX(0,MIN(Inputs!$E$37,Inputs!$E$36*N(N$5>=Inputs!$E$70)*YEARFRAC(Inputs!$E$70,MIN(N$5,Inputs!$E$58)))-N22) -> 0.20833333 | O23: =Inputs!$E$38*MAX(0,MIN(Inputs!$E$37,Inputs!$E$36*N(O$5>=Inputs!$E$70)*YEARFRAC(Inputs!$E$70,MIN(O$5,Inputs!$E$58)))-O22) -> 0.1875 | ... BP23: =Inputs!$E$38*MAX(0,MIN(Inputs!$E$37,Inputs!$E$36*N(BP$5>=Inputs!$E$70)*YEARFRAC(Inputs!$E$70,MIN(BP$5,Inputs!$E$58)))-BP22) -> 0
C24: Closing balance | D24: k€/MW | H24: =H22+H23 -> 0 | I24: =I22+I23 -> 0 | J24: =J22+J23 -> 0 | K24: =K22+K23 -> 0.034722222 | L24: =L22+L23 -> 0.23611111 | M24: =M22+M23 -> 0.45138889 | N24: =N22+N23 -> 0.65972222 | O24: =O22+O23 -> 0.84722222 | ... BP24: =BP22+BP23 -> 8.5763889
C25: Success fee payable at sale | D25: k€ | G25: =SUM(H25:BP25) -> 2238.4375 | H25: =H$7*H24*Inputs!$E$29 -> 0 | I25: =I$7*I24*Inputs!$E$29 -> 0 | J25: =J$7*J24*Inputs!$E$29 -> 0 | K25: =K$7*K24*Inputs!$E$29 -> 0 | L25: =L$7*L24*Inputs!$E$29 -> 0 | M25: =M$7*M24*Inputs!$E$29 -> 0 | N25: =N$7*N24*Inputs!$E$29 -> 0 | O25: =O$7*O24*Inputs!$E$29 -> 0 | ... BP25: =BP$7*BP24*Inputs!$E$29 -> 0
C27: 3. Securities and connection fee – payable flows (€k; + = paid, − = refunded). Source: Deposits
C28: =Deposits!C7 -> Részvételi díj | D28: k€ | G28: =SUM(H28:BP28) -> 16.438356 | H28: =IF(H$4=Deposits!$L$7,Deposits!$O$7,0) -> 0 | I28: =IF(I$4=Deposits!$L$7,Deposits!$O$7,0) -> 0 | J28: =IF(J$4=Deposits!$L$7,Deposits!$O$7,0) -> 0 | K28: =IF(K$4=Deposits!$L$7,Deposits!$O$7,0) -> 16.438356 | L28: =IF(L$4=Deposits!$L$7,Deposits!$O$7,0) -> 0 | M28: =IF(M$4=Deposits!$L$7,Deposits!$O$7,0) -> 0 | N28: =IF(N$4=Deposits!$L$7,Deposits!$O$7,0) -> 0 | O28: =IF(O$4=Deposits!$L$7,Deposits!$O$7,0) -> 0 | ... BP28: =IF(BP$4=Deposits!$L$7,Deposits!$O$7,0) -> 0
C29: =Deposits!C8 -> Ajánlati biztosíték | D29: k€ | G29: =SUM(H29:BP29) -> 2437.8904 | H29: =IF(H$4=Deposits!$L$8,Deposits!$O$8,0) -> 0 | I29: =IF(I$4=Deposits!$L$8,Deposits!$O$8,0) -> 0 | J29: =IF(J$4=Deposits!$L$8,Deposits!$O$8,0) -> 0 | K29: =IF(K$4=Deposits!$L$8,Deposits!$O$8,0) -> 2437.8904 | L29: =IF(L$4=Deposits!$L$8,Deposits!$O$8,0) -> 0 | M29: =IF(M$4=Deposits!$L$8,Deposits!$O$8,0) -> 0 | N29: =IF(N$4=Deposits!$L$8,Deposits!$O$8,0) -> 0 | O29: =IF(O$4=Deposits!$L$8,Deposits!$O$8,0) -> 0 | ... BP29: =IF(BP$4=Deposits!$L$8,Deposits!$O$8,0) -> 0
C30: =Deposits!C9 -> Ajánlati biztosíték visszatérítés – sikertelen kapacitás | D30: k€ | G30: =SUM(H30:BP30) -> 0 | H30: =IF(H$4=Deposits!$L$9,Deposits!$O$9,0) -> 0 | I30: =IF(I$4=Deposits!$L$9,Deposits!$O$9,0) -> 0 | J30: =IF(J$4=Deposits!$L$9,Deposits!$O$9,0) -> 0 | K30: =IF(K$4=Deposits!$L$9,Deposits!$O$9,0) -> 0 | L30: =IF(L$4=Deposits!$L$9,Deposits!$O$9,0) -> 0 | M30: =IF(M$4=Deposits!$L$9,Deposits!$O$9,0) -> 0 | N30: =IF(N$4=Deposits!$L$9,Deposits!$O$9,0) -> 0 | O30: =IF(O$4=Deposits!$L$9,Deposits!$O$9,0) -> 0 | ... BP30: =IF(BP$4=Deposits!$L$9,Deposits!$O$9,0) -> 0
C31: =Deposits!C10 -> Teljesítési biztosíték | D31: k€ | G31: =SUM(H31:BP31) -> 15846.288 | H31: =IF(H$4=Deposits!$L$10,Deposits!$O$10,0) -> 0 | I31: =IF(I$4=Deposits!$L$10,Deposits!$O$10,0) -> 0 | J31: =IF(J$4=Deposits!$L$10,Deposits!$O$10,0) -> 0 | K31: =IF(K$4=Deposits!$L$10,Deposits!$O$10,0) -> 0 | L31: =IF(L$4=Deposits!$L$10,Deposits!$O$10,0) -> 0 | M31: =IF(M$4=Deposits!$L$10,Deposits!$O$10,0) -> 15846.288 | N31: =IF(N$4=Deposits!$L$10,Deposits!$O$10,0) -> 0 | O31: =IF(O$4=Deposits!$L$10,Deposits!$O$10,0) -> 0 | ... BP31: =IF(BP$4=Deposits!$L$10,Deposits!$O$10,0) -> 0
C32: =Deposits!C11 -> Igénybejelentési biztosíték | D32: k€ | G32: =SUM(H32:BP32) -> 2465.7534 | H32: =IF(H$4=Deposits!$L$11,Deposits!$O$11,0) -> 0 | I32: =IF(I$4=Deposits!$L$11,Deposits!$O$11,0) -> 0 | J32: =IF(J$4=Deposits!$L$11,Deposits!$O$11,0) -> 0 | K32: =IF(K$4=Deposits!$L$11,Deposits!$O$11,0) -> 0 | L32: =IF(L$4=Deposits!$L$11,Deposits!$O$11,0) -> 0 | M32: =IF(M$4=Deposits!$L$11,Deposits!$O$11,0) -> 2465.7534 | N32: =IF(N$4=Deposits!$L$11,Deposits!$O$11,0) -> 0 | O32: =IF(O$4=Deposits!$L$11,Deposits!$O$11,0) -> 0 | ... BP32: =IF(BP$4=Deposits!$L$11,Deposits!$O$11,0) -> 0
C33: =Deposits!C12 -> Csatlakozási díj – közvetlen | D33: k€ | G33: =SUM(H33:BP33) -> 1392.7282 | H33: =IF(H$4=Deposits!$L$12,Deposits!$O$12,0) -> 0 | I33: =IF(I$4=Deposits!$L$12,Deposits!$O$12,0) -> 0 | J33: =IF(J$4=Deposits!$L$12,Deposits!$O$12,0) -> 0 | K33: =IF(K$4=Deposits!$L$12,Deposits!$O$12,0) -> 0 | L33: =IF(L$4=Deposits!$L$12,Deposits!$O$12,0) -> 0 | M33: =IF(M$4=Deposits!$L$12,Deposits!$O$12,0) -> 0 | N33: =IF(N$4=Deposits!$L$12,Deposits!$O$12,0) -> 0 | O33: =IF(O$4=Deposits!$L$12,Deposits!$O$12,0) -> 0 | ... BP33: =IF(BP$4=Deposits!$L$12,Deposits!$O$12,0) -> 0
C34: =Deposits!C13 -> Kiegészítő biztosíték 1. részlet | D34: k€ | G34: =SUM(H34:BP34) -> 0 | H34: =IF(H$4=Deposits!$L$13,Deposits!$O$13,0) -> 0 | I34: =IF(I$4=Deposits!$L$13,Deposits!$O$13,0) -> 0 | J34: =IF(J$4=Deposits!$L$13,Deposits!$O$13,0) -> 0 | K34: =IF(K$4=Deposits!$L$13,Deposits!$O$13,0) -> 0 | L34: =IF(L$4=Deposits!$L$13,Deposits!$O$13,0) -> 0 | M34: =IF(M$4=Deposits!$L$13,Deposits!$O$13,0) -> 0 | N34: =IF(N$4=Deposits!$L$13,Deposits!$O$13,0) -> 0 | O34: =IF(O$4=Deposits!$L$13,Deposits!$O$13,0) -> 0 | ... BP34: =IF(BP$4=Deposits!$L$13,Deposits!$O$13,0) -> 0
C35: =Deposits!C14 -> Kiegészítő biztosíték 2. részlet | D35: k€ | G35: =SUM(H35:BP35) -> 0 | H35: =IF(H$4=Deposits!$L$14,Deposits!$O$14,0) -> 0 | I35: =IF(I$4=Deposits!$L$14,Deposits!$O$14,0) -> 0 | J35: =IF(J$4=Deposits!$L$14,Deposits!$O$14,0) -> 0 | K35: =IF(K$4=Deposits!$L$14,Deposits!$O$14,0) -> 0 | L35: =IF(L$4=Deposits!$L$14,Deposits!$O$14,0) -> 0 | M35: =IF(M$4=Deposits!$L$14,Deposits!$O$14,0) -> 0 | N35: =IF(N$4=Deposits!$L$14,Deposits!$O$14,0) -> 0 | O35: =IF(O$4=Deposits!$L$14,Deposits!$O$14,0) -> 0 | ... BP35: =IF(BP$4=Deposits!$L$14,Deposits!$O$14,0) -> 0
C36: =Deposits!C15 -> Kiegészítő biztosíték visszautalás építési engedély megszerzésekor | D36: k€ | G36: =SUM(H36:BP36) -> 0 | H36: =IF(H$4=Deposits!$L$15,Deposits!$O$15,0) -> 0 | I36: =IF(I$4=Deposits!$L$15,Deposits!$O$15,0) -> 0 | J36: =IF(J$4=Deposits!$L$15,Deposits!$O$15,0) -> 0 | K36: =IF(K$4=Deposits!$L$15,Deposits!$O$15,0) -> 0 | L36: =IF(L$4=Deposits!$L$15,Deposits!$O$15,0) -> 0 | M36: =IF(M$4=Deposits!$L$15,Deposits!$O$15,0) -> 0 | N36: =IF(N$4=Deposits!$L$15,Deposits!$O$15,0) -> 0 | O36: =IF(O$4=Deposits!$L$15,Deposits!$O$15,0) -> 0 | ... BP36: =IF(BP$4=Deposits!$L$15,Deposits!$O$15,0) -> 0
C37: =Deposits!C16 -> Kiegészítő biztosíték 3. részlet | D37: k€ | G37: =SUM(H37:BP37) -> 0 | H37: =IF(H$4=Deposits!$L$16,Deposits!$O$16,0) -> 0 | I37: =IF(I$4=Deposits!$L$16,Deposits!$O$16,0) -> 0 | J37: =IF(J$4=Deposits!$L$16,Deposits!$O$16,0) -> 0 | K37: =IF(K$4=Deposits!$L$16,Deposits!$O$16,0) -> 0 | L37: =IF(L$4=Deposits!$L$16,Deposits!$O$16,0) -> 0 | M37: =IF(M$4=Deposits!$L$16,Deposits!$O$16,0) -> 0 | N37: =IF(N$4=Deposits!$L$16,Deposits!$O$16,0) -> 0 | O37: =IF(O$4=Deposits!$L$16,Deposits!$O$16,0) -> 0 | ... BP37: =IF(BP$4=Deposits!$L$16,Deposits!$O$16,0) -> 0
C38: =Deposits!C17 -> Kiegészítő biztosíték 4. részlet | D38: k€ | G38: =SUM(H38:BP38) -> 0 | H38: =IF(H$4=Deposits!$L$17,Deposits!$O$17,0) -> 0 | I38: =IF(I$4=Deposits!$L$17,Deposits!$O$17,0) -> 0 | J38: =IF(J$4=Deposits!$L$17,Deposits!$O$17,0) -> 0 | K38: =IF(K$4=Deposits!$L$17,Deposits!$O$17,0) -> 0 | L38: =IF(L$4=Deposits!$L$17,Deposits!$O$17,0) -> 0 | M38: =IF(M$4=Deposits!$L$17,Deposits!$O$17,0) -> 0 | N38: =IF(N$4=Deposits!$L$17,Deposits!$O$17,0) -> 0 | O38: =IF(O$4=Deposits!$L$17,Deposits!$O$17,0) -> 0 | ... BP38: =IF(BP$4=Deposits!$L$17,Deposits!$O$17,0) -> 0
C39: =Deposits!C18 -> Csatlakozási díj – becsült összeg | D39: k€ | G39: =SUM(H39:BP39) -> 37573.318 | H39: =IF(H$4=Deposits!$L$18,Deposits!$O$18,0) -> 0 | I39: =IF(I$4=Deposits!$L$18,Deposits!$O$18,0) -> 0 | J39: =IF(J$4=Deposits!$L$18,Deposits!$O$18,0) -> 0 | K39: =IF(K$4=Deposits!$L$18,Deposits!$O$18,0) -> 0 | L39: =IF(L$4=Deposits!$L$18,Deposits!$O$18,0) -> 0 | M39: =IF(M$4=Deposits!$L$18,Deposits!$O$18,0) -> 0 | N39: =IF(N$4=Deposits!$L$18,Deposits!$O$18,0) -> 0 | O39: =IF(O$4=Deposits!$L$18,Deposits!$O$18,0) -> 0 | ... BP39: =IF(BP$4=Deposits!$L$18,Deposits!$O$18,0) -> 0
C40: Total payable flows | D40: k€ | G40: =SUM(H40:BP40) -> 59732.416 | H40: =SUM(H28:H39) -> 0 | I40: =SUM(I28:I39) -> 0 | J40: =SUM(J28:J39) -> 0 | K40: =SUM(K28:K39) -> 2454.3288 | L40: =SUM(L28:L39) -> 0 | M40: =SUM(M28:M39) -> 18312.041 | N40: =SUM(N28:N39) -> 0 | O40: =SUM(O28:O39) -> 0 | ... BP40: =SUM(BP28:BP39) -> 0
C41: Cumulative | D41: k€ | H41: =H40 -> 0 | I41: =H41+I40 -> 0 | J41: =I41+J40 -> 0 | K41: =J41+K40 -> 2454.3288 | L41: =K41+L40 -> 2454.3288 | M41: =L41+M40 -> 20766.37 | N41: =M41+N40 -> 20766.37 | O41: =N41+O40 -> 20766.37 | P41: =O41+P40 -> 20766.37 | ... BP41: =BO41+BP40 -> 59732.416
C43: 4. Cash-settled deposits (line × cash switch)
C44: =C28 -> Részvételi díj | D44: k€ | G44: =SUM(H44:BP44) -> 16.438356 | H44: =H28*Deposits!$P$7 -> 0 | I44: =I28*Deposits!$P$7 -> 0 | J44: =J28*Deposits!$P$7 -> 0 | K44: =K28*Deposits!$P$7 -> 16.438356 | L44: =L28*Deposits!$P$7 -> 0 | M44: =M28*Deposits!$P$7 -> 0 | N44: =N28*Deposits!$P$7 -> 0 | O44: =O28*Deposits!$P$7 -> 0 | ... BP44: =BP28*Deposits!$P$7 -> 0
C45: =C29 -> Ajánlati biztosíték | D45: k€ | G45: =SUM(H45:BP45) -> 0 | H45: =H29*Deposits!$P$8 -> 0 | I45: =I29*Deposits!$P$8 -> 0 | J45: =J29*Deposits!$P$8 -> 0 | K45: =K29*Deposits!$P$8 -> 0 | L45: =L29*Deposits!$P$8 -> 0 | M45: =M29*Deposits!$P$8 -> 0 | N45: =N29*Deposits!$P$8 -> 0 | O45: =O29*Deposits!$P$8 -> 0 | ... BP45: =BP29*Deposits!$P$8 -> 0
C46: =C30 -> Ajánlati biztosíték visszatérítés – sikertelen kapacitás | D46: k€ | G46: =SUM(H46:BP46) -> 0 | H46: =H30*Deposits!$P$9 -> 0 | I46: =I30*Deposits!$P$9 -> 0 | J46: =J30*Deposits!$P$9 -> 0 | K46: =K30*Deposits!$P$9 -> 0 | L46: =L30*Deposits!$P$9 -> 0 | M46: =M30*Deposits!$P$9 -> 0 | N46: =N30*Deposits!$P$9 -> 0 | O46: =O30*Deposits!$P$9 -> 0 | ... BP46: =BP30*Deposits!$P$9 -> 0
C47: =C31 -> Teljesítési biztosíték | D47: k€ | G47: =SUM(H47:BP47) -> 0 | H47: =H31*Deposits!$P$10 -> 0 | I47: =I31*Deposits!$P$10 -> 0 | J47: =J31*Deposits!$P$10 -> 0 | K47: =K31*Deposits!$P$10 -> 0 | L47: =L31*Deposits!$P$10 -> 0 | M47: =M31*Deposits!$P$10 -> 0 | N47: =N31*Deposits!$P$10 -> 0 | O47: =O31*Deposits!$P$10 -> 0 | ... BP47: =BP31*Deposits!$P$10 -> 0
C48: =C32 -> Igénybejelentési biztosíték | D48: k€ | G48: =SUM(H48:BP48) -> 2465.7534 | H48: =H32*Deposits!$P$11 -> 0 | I48: =I32*Deposits!$P$11 -> 0 | J48: =J32*Deposits!$P$11 -> 0 | K48: =K32*Deposits!$P$11 -> 0 | L48: =L32*Deposits!$P$11 -> 0 | M48: =M32*Deposits!$P$11 -> 2465.7534 | N48: =N32*Deposits!$P$11 -> 0 | O48: =O32*Deposits!$P$11 -> 0 | ... BP48: =BP32*Deposits!$P$11 -> 0
C49: =C33 -> Csatlakozási díj – közvetlen | D49: k€ | G49: =SUM(H49:BP49) -> 1392.7282 | H49: =H33*Deposits!$P$12 -> 0 | I49: =I33*Deposits!$P$12 -> 0 | J49: =J33*Deposits!$P$12 -> 0 | K49: =K33*Deposits!$P$12 -> 0 | L49: =L33*Deposits!$P$12 -> 0 | M49: =M33*Deposits!$P$12 -> 0 | N49: =N33*Deposits!$P$12 -> 0 | O49: =O33*Deposits!$P$12 -> 0 | ... BP49: =BP33*Deposits!$P$12 -> 0
C50: =C34 -> Kiegészítő biztosíték 1. részlet | D50: k€ | G50: =SUM(H50:BP50) -> 0 | H50: =H34*Deposits!$P$13 -> 0 | I50: =I34*Deposits!$P$13 -> 0 | J50: =J34*Deposits!$P$13 -> 0 | K50: =K34*Deposits!$P$13 -> 0 | L50: =L34*Deposits!$P$13 -> 0 | M50: =M34*Deposits!$P$13 -> 0 | N50: =N34*Deposits!$P$13 -> 0 | O50: =O34*Deposits!$P$13 -> 0 | ... BP50: =BP34*Deposits!$P$13 -> 0
C51: =C35 -> Kiegészítő biztosíték 2. részlet | D51: k€ | G51: =SUM(H51:BP51) -> 0 | H51: =H35*Deposits!$P$14 -> 0 | I51: =I35*Deposits!$P$14 -> 0 | J51: =J35*Deposits!$P$14 -> 0 | K51: =K35*Deposits!$P$14 -> 0 | L51: =L35*Deposits!$P$14 -> 0 | M51: =M35*Deposits!$P$14 -> 0 | N51: =N35*Deposits!$P$14 -> 0 | O51: =O35*Deposits!$P$14 -> 0 | ... BP51: =BP35*Deposits!$P$14 -> 0
C52: =C36 -> Kiegészítő biztosíték visszautalás építési engedély megszerzésekor | D52: k€ | G52: =SUM(H52:BP52) -> 0 | H52: =H36*Deposits!$P$15 -> 0 | I52: =I36*Deposits!$P$15 -> 0 | J52: =J36*Deposits!$P$15 -> 0 | K52: =K36*Deposits!$P$15 -> 0 | L52: =L36*Deposits!$P$15 -> 0 | M52: =M36*Deposits!$P$15 -> 0 | N52: =N36*Deposits!$P$15 -> 0 | O52: =O36*Deposits!$P$15 -> 0 | ... BP52: =BP36*Deposits!$P$15 -> 0
C53: =C37 -> Kiegészítő biztosíték 3. részlet | D53: k€ | G53: =SUM(H53:BP53) -> 0 | H53: =H37*Deposits!$P$16 -> 0 | I53: =I37*Deposits!$P$16 -> 0 | J53: =J37*Deposits!$P$16 -> 0 | K53: =K37*Deposits!$P$16 -> 0 | L53: =L37*Deposits!$P$16 -> 0 | M53: =M37*Deposits!$P$16 -> 0 | N53: =N37*Deposits!$P$16 -> 0 | O53: =O37*Deposits!$P$16 -> 0 | ... BP53: =BP37*Deposits!$P$16 -> 0
C54: =C38 -> Kiegészítő biztosíték 4. részlet | D54: k€ | G54: =SUM(H54:BP54) -> 0 | H54: =H38*Deposits!$P$17 -> 0 | I54: =I38*Deposits!$P$17 -> 0 | J54: =J38*Deposits!$P$17 -> 0 | K54: =K38*Deposits!$P$17 -> 0 | L54: =L38*Deposits!$P$17 -> 0 | M54: =M38*Deposits!$P$17 -> 0 | N54: =N38*Deposits!$P$17 -> 0 | O54: =O38*Deposits!$P$17 -> 0 | ... BP54: =BP38*Deposits!$P$17 -> 0
C55: =C39 -> Csatlakozási díj – becsült összeg | D55: k€ | G55: =SUM(H55:BP55) -> 37573.318 | H55: =H39*Deposits!$P$18 -> 0 | I55: =I39*Deposits!$P$18 -> 0 | J55: =J39*Deposits!$P$18 -> 0 | K55: =K39*Deposits!$P$18 -> 0 | L55: =L39*Deposits!$P$18 -> 0 | M55: =M39*Deposits!$P$18 -> 0 | N55: =N39*Deposits!$P$18 -> 0 | O55: =O39*Deposits!$P$18 -> 0 | ... BP55: =BP39*Deposits!$P$18 -> 0
C56: Total cash deposits paid / (refunded) | D56: k€ | G56: =SUM(H56:BP56) -> 41448.238 | H56: =SUM(H44:H55) -> 0 | I56: =SUM(I44:I55) -> 0 | J56: =SUM(J44:J55) -> 0 | K56: =SUM(K44:K55) -> 16.438356 | L56: =SUM(L44:L55) -> 0 | M56: =SUM(M44:M55) -> 2465.7534 | N56: =SUM(N44:N55) -> 0 | O56: =SUM(O44:O55) -> 0 | ... BP56: =SUM(BP44:BP55) -> 0
C57: Cash posted with counterparties (cumulative) | D57: k€ | G57: =MAX(H57:BP57) -> 41448.238 | H57: =H56 -> 0 | I57: =H57+I56 -> 0 | J57: =I57+J56 -> 0 | K57: =J57+K56 -> 16.438356 | L57: =K57+L56 -> 16.438356 | M57: =L57+M56 -> 2482.1918 | N57: =M57+N56 -> 2482.1918 | O57: =N57+O56 -> 2482.1918 | P57: =O57+P56 -> 2482.1918 | ... BP57: =BO57+BP56 -> 41448.238
C59: 5. Guarantee-backed securities and guarantee fee (line × (1 − cash switch))
C60: =C28 -> Részvételi díj | D60: k€ | G60: =SUM(H60:BP60) -> 0 | H60: =H28*(1-Deposits!$P$7) -> 0 | I60: =I28*(1-Deposits!$P$7) -> 0 | J60: =J28*(1-Deposits!$P$7) -> 0 | K60: =K28*(1-Deposits!$P$7) -> 0 | L60: =L28*(1-Deposits!$P$7) -> 0 | M60: =M28*(1-Deposits!$P$7) -> 0 | N60: =N28*(1-Deposits!$P$7) -> 0 | O60: =O28*(1-Deposits!$P$7) -> 0 | ... BP60: =BP28*(1-Deposits!$P$7) -> 0
C61: =C29 -> Ajánlati biztosíték | D61: k€ | G61: =SUM(H61:BP61) -> 2437.8904 | H61: =H29*(1-Deposits!$P$8) -> 0 | I61: =I29*(1-Deposits!$P$8) -> 0 | J61: =J29*(1-Deposits!$P$8) -> 0 | K61: =K29*(1-Deposits!$P$8) -> 2437.8904 | L61: =L29*(1-Deposits!$P$8) -> 0 | M61: =M29*(1-Deposits!$P$8) -> 0 | N61: =N29*(1-Deposits!$P$8) -> 0 | O61: =O29*(1-Deposits!$P$8) -> 0 | ... BP61: =BP29*(1-Deposits!$P$8) -> 0
C62: =C30 -> Ajánlati biztosíték visszatérítés – sikertelen kapacitás | D62: k€ | G62: =SUM(H62:BP62) -> 0 | H62: =H30*(1-Deposits!$P$9) -> 0 | I62: =I30*(1-Deposits!$P$9) -> 0 | J62: =J30*(1-Deposits!$P$9) -> 0 | K62: =K30*(1-Deposits!$P$9) -> 0 | L62: =L30*(1-Deposits!$P$9) -> 0 | M62: =M30*(1-Deposits!$P$9) -> 0 | N62: =N30*(1-Deposits!$P$9) -> 0 | O62: =O30*(1-Deposits!$P$9) -> 0 | ... BP62: =BP30*(1-Deposits!$P$9) -> 0
C63: =C31 -> Teljesítési biztosíték | D63: k€ | G63: =SUM(H63:BP63) -> 15846.288 | H63: =H31*(1-Deposits!$P$10) -> 0 | I63: =I31*(1-Deposits!$P$10) -> 0 | J63: =J31*(1-Deposits!$P$10) -> 0 | K63: =K31*(1-Deposits!$P$10) -> 0 | L63: =L31*(1-Deposits!$P$10) -> 0 | M63: =M31*(1-Deposits!$P$10) -> 15846.288 | N63: =N31*(1-Deposits!$P$10) -> 0 | O63: =O31*(1-Deposits!$P$10) -> 0 | ... BP63: =BP31*(1-Deposits!$P$10) -> 0
C64: =C32 -> Igénybejelentési biztosíték | D64: k€ | G64: =SUM(H64:BP64) -> 0 | H64: =H32*(1-Deposits!$P$11) -> 0 | I64: =I32*(1-Deposits!$P$11) -> 0 | J64: =J32*(1-Deposits!$P$11) -> 0 | K64: =K32*(1-Deposits!$P$11) -> 0 | L64: =L32*(1-Deposits!$P$11) -> 0 | M64: =M32*(1-Deposits!$P$11) -> 0 | N64: =N32*(1-Deposits!$P$11) -> 0 | O64: =O32*(1-Deposits!$P$11) -> 0 | ... BP64: =BP32*(1-Deposits!$P$11) -> 0
C65: =C33 -> Csatlakozási díj – közvetlen | D65: k€ | G65: =SUM(H65:BP65) -> 0 | H65: =H33*(1-Deposits!$P$12) -> 0 | I65: =I33*(1-Deposits!$P$12) -> 0 | J65: =J33*(1-Deposits!$P$12) -> 0 | K65: =K33*(1-Deposits!$P$12) -> 0 | L65: =L33*(1-Deposits!$P$12) -> 0 | M65: =M33*(1-Deposits!$P$12) -> 0 | N65: =N33*(1-Deposits!$P$12) -> 0 | O65: =O33*(1-Deposits!$P$12) -> 0 | ... BP65: =BP33*(1-Deposits!$P$12) -> 0
C66: =C34 -> Kiegészítő biztosíték 1. részlet | D66: k€ | G66: =SUM(H66:BP66) -> 0 | H66: =H34*(1-Deposits!$P$13) -> 0 | I66: =I34*(1-Deposits!$P$13) -> 0 | J66: =J34*(1-Deposits!$P$13) -> 0 | K66: =K34*(1-Deposits!$P$13) -> 0 | L66: =L34*(1-Deposits!$P$13) -> 0 | M66: =M34*(1-Deposits!$P$13) -> 0 | N66: =N34*(1-Deposits!$P$13) -> 0 | O66: =O34*(1-Deposits!$P$13) -> 0 | ... BP66: =BP34*(1-Deposits!$P$13) -> 0
C67: =C35 -> Kiegészítő biztosíték 2. részlet | D67: k€ | G67: =SUM(H67:BP67) -> 0 | H67: =H35*(1-Deposits!$P$14) -> 0 | I67: =I35*(1-Deposits!$P$14) -> 0 | J67: =J35*(1-Deposits!$P$14) -> 0 | K67: =K35*(1-Deposits!$P$14) -> 0 | L67: =L35*(1-Deposits!$P$14) -> 0 | M67: =M35*(1-Deposits!$P$14) -> 0 | N67: =N35*(1-Deposits!$P$14) -> 0 | O67: =O35*(1-Deposits!$P$14) -> 0 | ... BP67: =BP35*(1-Deposits!$P$14) -> 0
C68: =C36 -> Kiegészítő biztosíték visszautalás építési engedély megszerzésekor | D68: k€ | G68: =SUM(H68:BP68) -> 0 | H68: =H36*(1-Deposits!$P$15) -> 0 | I68: =I36*(1-Deposits!$P$15) -> 0 | J68: =J36*(1-Deposits!$P$15) -> 0 | K68: =K36*(1-Deposits!$P$15) -> 0 | L68: =L36*(1-Deposits!$P$15) -> 0 | M68: =M36*(1-Deposits!$P$15) -> 0 | N68: =N36*(1-Deposits!$P$15) -> 0 | O68: =O36*(1-Deposits!$P$15) -> 0 | ... BP68: =BP36*(1-Deposits!$P$15) -> 0
C69: =C37 -> Kiegészítő biztosíték 3. részlet | D69: k€ | G69: =SUM(H69:BP69) -> 0 | H69: =H37*(1-Deposits!$P$16) -> 0 | I69: =I37*(1-Deposits!$P$16) -> 0 | J69: =J37*(1-Deposits!$P$16) -> 0 | K69: =K37*(1-Deposits!$P$16) -> 0 | L69: =L37*(1-Deposits!$P$16) -> 0 | M69: =M37*(1-Deposits!$P$16) -> 0 | N69: =N37*(1-Deposits!$P$16) -> 0 | O69: =O37*(1-Deposits!$P$16) -> 0 | ... BP69: =BP37*(1-Deposits!$P$16) -> 0
C70: =C38 -> Kiegészítő biztosíték 4. részlet | D70: k€ | G70: =SUM(H70:BP70) -> 0 | H70: =H38*(1-Deposits!$P$17) -> 0 | I70: =I38*(1-Deposits!$P$17) -> 0 | J70: =J38*(1-Deposits!$P$17) -> 0 | K70: =K38*(1-Deposits!$P$17) -> 0 | L70: =L38*(1-Deposits!$P$17) -> 0 | M70: =M38*(1-Deposits!$P$17) -> 0 | N70: =N38*(1-Deposits!$P$17) -> 0 | O70: =O38*(1-Deposits!$P$17) -> 0 | ... BP70: =BP38*(1-Deposits!$P$17) -> 0
C71: =C39 -> Csatlakozási díj – becsült összeg | D71: k€ | G71: =SUM(H71:BP71) -> 0 | H71: =H39*(1-Deposits!$P$18) -> 0 | I71: =I39*(1-Deposits!$P$18) -> 0 | J71: =J39*(1-Deposits!$P$18) -> 0 | K71: =K39*(1-Deposits!$P$18) -> 0 | L71: =L39*(1-Deposits!$P$18) -> 0 | M71: =M39*(1-Deposits!$P$18) -> 0 | N71: =N39*(1-Deposits!$P$18) -> 0 | O71: =O39*(1-Deposits!$P$18) -> 0 | ... BP71: =BP39*(1-Deposits!$P$18) -> 0
C72: Total guarantee movements | D72: k€ | G72: =SUM(H72:BP72) -> 18284.178 | H72: =SUM(H60:H71) -> 0 | I72: =SUM(I60:I71) -> 0 | J72: =SUM(J60:J71) -> 0 | K72: =SUM(K60:K71) -> 2437.8904 | L72: =SUM(L60:L71) -> 0 | M72: =SUM(M60:M71) -> 15846.288 | N72: =SUM(N60:N71) -> 0 | O72: =SUM(O60:O71) -> 0 | ... BP72: =SUM(BP60:BP71) -> 0
C73: Opening guarantee balance | D73: k€ | H73: 0 | I73: =H76 -> 0 | J73: =I76 -> 0 | K73: =J76 -> 0 | L73: =K76 -> 2437.8904 | M73: =L76 -> 2437.8904 | N73: =M76 -> 18284.178 | O73: =N76 -> 18284.178 | P73: =O76 -> 18284.178 | ... BP73: =BO76 -> 0
C74: Guarantees issued / (reduced) | D74: k€ | H74: =H72 -> 0 | I74: =I72 -> 0 | J74: =J72 -> 0 | K74: =K72 -> 2437.8904 | L74: =L72 -> 0 | M74: =M72 -> 15846.288 | N74: =N72 -> 0 | O74: =O72 -> 0 | ... BP74: =BP72 -> 0
C75: Release at sale | D75: k€ | G75: =SUM(H75:BP75) -> -18284.178 | H75: =-H$7*(H73+H74) -> 0 | I75: =-I$7*(I73+I74) -> 0 | J75: =-J$7*(J73+J74) -> 0 | K75: =-K$7*(K73+K74) -> 0 | L75: =-L$7*(L73+L74) -> 0 | M75: =-M$7*(M73+M74) -> 0 | N75: =-N$7*(N73+N74) -> 0 | O75: =-O$7*(O73+O74) -> 0 | ... BP75: =-BP$7*(BP73+BP74) -> 0
C76: Closing guarantee balance | D76: k€ | G76: =MAX(H76:BP76) -> 18284.178 | H76: =H73+H74+H75 -> 0 | I76: =I73+I74+I75 -> 0 | J76: =J73+J74+J75 -> 0 | K76: =K73+K74+K75 -> 2437.8904 | L76: =L73+L74+L75 -> 2437.8904 | M76: =M73+M74+M75 -> 18284.178 | N76: =N73+N74+N75 -> 18284.178 | O76: =O73+O74+O75 -> 18284.178 | ... BP76: =BP73+BP74+BP75 -> 0
C77: EURIBOR (Curves, selected) | D77: % p.a. | H77: =Curves!H7 -> 0.02204 | I77: =Curves!I7 -> 0.0230337 | J77: =Curves!J7 -> 0.0239429 | K77: =Curves!K7 -> 0.0248091 | L77: =Curves!L7 -> 0.0256369 | M77: =Curves!M7 -> 0.0263515 | N77: =Curves!N7 -> 0.0270143 | O77: =Curves!O7 -> 0.0274756 | ... BP77: =Curves!BP7 -> 0.0278735
C78: All-in guarantee rate (assumed flat if Inputs E97 = 1, else EURIBOR + margin) | D78: % p.a. | H78: =IF(Inputs!$E$114=1,Inputs!$E$113,H77+Inputs!$E$111) -> 0.06 | I78: =IF(Inputs!$E$114=1,Inputs!$E$113,I77+Inputs!$E$111) -> 0.06 | J78: =IF(Inputs!$E$114=1,Inputs!$E$113,J77+Inputs!$E$111) -> 0.06 | K78: =IF(Inputs!$E$114=1,Inputs!$E$113,K77+Inputs!$E$111) -> 0.06 | L78: =IF(Inputs!$E$114=1,Inputs!$E$113,L77+Inputs!$E$111) -> 0.06 | M78: =IF(Inputs!$E$114=1,Inputs!$E$113,M77+Inputs!$E$111) -> 0.06 | N78: =IF(Inputs!$E$114=1,Inputs!$E$113,N77+Inputs!$E$111) -> 0.06 | O78: =IF(Inputs!$E$114=1,Inputs!$E$113,O77+Inputs!$E$111) -> 0.06 | ... BP78: =IF(Inputs!$E$114=1,Inputs!$E$113,BP77+Inputs!$E$111) -> 0.06
C79: Guarantee fee | D79: k€ | G79: =SUM(H79:BP79) -> 3681.2145 | H79: =(H73+H74)*H78/12 -> 0 | I79: =(I73+I74)*I78/12 -> 0 | J79: =(J73+J74)*J78/12 -> 0 | K79: =(K73+K74)*K78/12 -> 12.189452 | L79: =(L73+L74)*L78/12 -> 12.189452 | M79: =(M73+M74)*M78/12 -> 91.42089 | N79: =(N73+N74)*N78/12 -> 91.42089 | O79: =(O73+O74)*O78/12 -> 91.42089 | ... BP79: =(BP73+BP74)*BP78/12 -> 0
C80: Interest on guarantee-backed securities (credited to lenders) | D80: % p.a. | E80: =Inputs!$E$65 -> 0.06
C81: Opening accrued guarantee interest | D81: k€ | H81: 0 | I81: =H84 -> 0 | J81: =I84 -> 0 | K81: =J84 -> 0 | L81: =K84 -> 11.866555 | M81: =L84 -> 23.790871 | N81: =M84 -> 112.90584 | O81: =N84 -> 202.45457 | P81: =O84 -> 292.43919 | ... BP81: =BO84 -> 0
C82: Guarantee interest accrual (memo; accrual flag row 10 – interest pause excluded) | D82: k€ | G82: =SUM(H82:BP82) -> 3310.1711 | H82: =IF(Inputs!$E$69=1,(1+$E$80)^(1/12)-1,$E$80/12)*(H73+H74+H81)*H$10 -> 0 | I82: =IF(Inputs!$E$69=1,(1+$E$80)^(1/12)-1,$E$80/12)*(I73+I74+I81)*I$10 -> 0 | J82: =IF(Inputs!$E$69=1,(1+$E$80)^(1/12)-1,$E$80/12)*(J73+J74+J81)*J$10 -> 0 | K82: =IF(Inputs!$E$69=1,(1+$E$80)^(1/12)-1,$E$80/12)*(K73+K74+K81)*K$10 -> 11.866555 | L82: =IF(Inputs!$E$69=1,(1+$E$80)^(1/12)-1,$E$80/12)*(L73+L74+L81)*L$10 -> 11.924316 | M82: =IF(Inputs!$E$69=1,(1+$E$80)^(1/12)-1,$E$80/12)*(M73+M74+M81)*M$10 -> 89.114965 | N82: =IF(Inputs!$E$69=1,(1+$E$80)^(1/12)-1,$E$80/12)*(N73+N74+N81)*N$10 -> 89.548736 | O82: =IF(Inputs!$E$69=1,(1+$E$80)^(1/12)-1,$E$80/12)*(O73+O74+O81)*O$10 -> 89.984619 | ... BP82: =IF(Inputs!$E$69=1,(1+$E$80)^(1/12)-1,$E$80/12)*(BP73+BP74+BP81)*BP$10 -> 0
C83: Paid from proceeds at sale | D83: k€ | G83: =SUM(H83:BP83) -> -3310.1711 | H83: =-H$7*(H81+H82) -> 0 | I83: =-I$7*(I81+I82) -> 0 | J83: =-J$7*(J81+J82) -> 0 | K83: =-K$7*(K81+K82) -> 0 | L83: =-L$7*(L81+L82) -> 0 | M83: =-M$7*(M81+M82) -> 0 | N83: =-N$7*(N81+N82) -> 0 | O83: =-O$7*(O81+O82) -> 0 | ... BP83: =-BP$7*(BP81+BP82) -> 0
C84: Closing accrued guarantee interest | D84: k€ | H84: =SUM(H81:H83) -> 0 | I84: =SUM(I81:I83) -> 0 | J84: =SUM(J81:J83) -> 0 | K84: =SUM(K81:K83) -> 11.866555 | L84: =SUM(L81:L83) -> 23.790871 | M84: =SUM(M81:M83) -> 112.90584 | N84: =SUM(N81:N83) -> 202.45457 | O84: =SUM(O81:O83) -> 292.43919 | ... BP84: =SUM(BP81:BP83) -> 0
C86: 6. Recovery of securities at exit – buyer reimburses cash posted, per line % (Inputs J)
C87: =C28 -> Részvételi díj | D87: k€ | G87: =SUM(H87:BP87) -> 0 | H87: =H$7*SUM($H44:H44)*Deposits!$Q$7 -> 0 | I87: =I$7*SUM($H44:I44)*Deposits!$Q$7 -> 0 | J87: =J$7*SUM($H44:J44)*Deposits!$Q$7 -> 0 | K87: =K$7*SUM($H44:K44)*Deposits!$Q$7 -> 0 | L87: =L$7*SUM($H44:L44)*Deposits!$Q$7 -> 0 | M87: =M$7*SUM($H44:M44)*Deposits!$Q$7 -> 0 | N87: =N$7*SUM($H44:N44)*Deposits!$Q$7 -> 0 | O87: =O$7*SUM($H44:O44)*Deposits!$Q$7 -> 0 | ... BP87: =BP$7*SUM($H44:BP44)*Deposits!$Q$7 -> 0
C88: =C29 -> Ajánlati biztosíték | D88: k€ | G88: =SUM(H88:BP88) -> 0 | H88: =H$7*SUM($H45:H45)*Deposits!$Q$8 -> 0 | I88: =I$7*SUM($H45:I45)*Deposits!$Q$8 -> 0 | J88: =J$7*SUM($H45:J45)*Deposits!$Q$8 -> 0 | K88: =K$7*SUM($H45:K45)*Deposits!$Q$8 -> 0 | L88: =L$7*SUM($H45:L45)*Deposits!$Q$8 -> 0 | M88: =M$7*SUM($H45:M45)*Deposits!$Q$8 -> 0 | N88: =N$7*SUM($H45:N45)*Deposits!$Q$8 -> 0 | O88: =O$7*SUM($H45:O45)*Deposits!$Q$8 -> 0 | ... BP88: =BP$7*SUM($H45:BP45)*Deposits!$Q$8 -> 0
C89: =C30 -> Ajánlati biztosíték visszatérítés – sikertelen kapacitás | D89: k€ | G89: =SUM(H89:BP89) -> 0 | H89: =H$7*SUM($H46:H46)*Deposits!$Q$9 -> 0 | I89: =I$7*SUM($H46:I46)*Deposits!$Q$9 -> 0 | J89: =J$7*SUM($H46:J46)*Deposits!$Q$9 -> 0 | K89: =K$7*SUM($H46:K46)*Deposits!$Q$9 -> 0 | L89: =L$7*SUM($H46:L46)*Deposits!$Q$9 -> 0 | M89: =M$7*SUM($H46:M46)*Deposits!$Q$9 -> 0 | N89: =N$7*SUM($H46:N46)*Deposits!$Q$9 -> 0 | O89: =O$7*SUM($H46:O46)*Deposits!$Q$9 -> 0 | ... BP89: =BP$7*SUM($H46:BP46)*Deposits!$Q$9 -> 0
C90: =C31 -> Teljesítési biztosíték | D90: k€ | G90: =SUM(H90:BP90) -> 0 | H90: =H$7*SUM($H47:H47)*Deposits!$Q$10 -> 0 | I90: =I$7*SUM($H47:I47)*Deposits!$Q$10 -> 0 | J90: =J$7*SUM($H47:J47)*Deposits!$Q$10 -> 0 | K90: =K$7*SUM($H47:K47)*Deposits!$Q$10 -> 0 | L90: =L$7*SUM($H47:L47)*Deposits!$Q$10 -> 0 | M90: =M$7*SUM($H47:M47)*Deposits!$Q$10 -> 0 | N90: =N$7*SUM($H47:N47)*Deposits!$Q$10 -> 0 | O90: =O$7*SUM($H47:O47)*Deposits!$Q$10 -> 0 | ... BP90: =BP$7*SUM($H47:BP47)*Deposits!$Q$10 -> 0
C91: =C32 -> Igénybejelentési biztosíték | D91: k€ | G91: =SUM(H91:BP91) -> 2465.7534 | H91: =H$7*SUM($H48:H48)*Deposits!$Q$11 -> 0 | I91: =I$7*SUM($H48:I48)*Deposits!$Q$11 -> 0 | J91: =J$7*SUM($H48:J48)*Deposits!$Q$11 -> 0 | K91: =K$7*SUM($H48:K48)*Deposits!$Q$11 -> 0 | L91: =L$7*SUM($H48:L48)*Deposits!$Q$11 -> 0 | M91: =M$7*SUM($H48:M48)*Deposits!$Q$11 -> 0 | N91: =N$7*SUM($H48:N48)*Deposits!$Q$11 -> 0 | O91: =O$7*SUM($H48:O48)*Deposits!$Q$11 -> 0 | ... BP91: =BP$7*SUM($H48:BP48)*Deposits!$Q$11 -> 0
C92: =C33 -> Csatlakozási díj – közvetlen | D92: k€ | G92: =SUM(H92:BP92) -> 1392.7282 | H92: =H$7*SUM($H49:H49)*Deposits!$Q$12 -> 0 | I92: =I$7*SUM($H49:I49)*Deposits!$Q$12 -> 0 | J92: =J$7*SUM($H49:J49)*Deposits!$Q$12 -> 0 | K92: =K$7*SUM($H49:K49)*Deposits!$Q$12 -> 0 | L92: =L$7*SUM($H49:L49)*Deposits!$Q$12 -> 0 | M92: =M$7*SUM($H49:M49)*Deposits!$Q$12 -> 0 | N92: =N$7*SUM($H49:N49)*Deposits!$Q$12 -> 0 | O92: =O$7*SUM($H49:O49)*Deposits!$Q$12 -> 0 | ... BP92: =BP$7*SUM($H49:BP49)*Deposits!$Q$12 -> 0
C93: =C34 -> Kiegészítő biztosíték 1. részlet | D93: k€ | G93: =SUM(H93:BP93) -> 0 | H93: =H$7*SUM($H50:H50)*Deposits!$Q$13 -> 0 | I93: =I$7*SUM($H50:I50)*Deposits!$Q$13 -> 0 | J93: =J$7*SUM($H50:J50)*Deposits!$Q$13 -> 0 | K93: =K$7*SUM($H50:K50)*Deposits!$Q$13 -> 0 | L93: =L$7*SUM($H50:L50)*Deposits!$Q$13 -> 0 | M93: =M$7*SUM($H50:M50)*Deposits!$Q$13 -> 0 | N93: =N$7*SUM($H50:N50)*Deposits!$Q$13 -> 0 | O93: =O$7*SUM($H50:O50)*Deposits!$Q$13 -> 0 | ... BP93: =BP$7*SUM($H50:BP50)*Deposits!$Q$13 -> 0
C94: =C35 -> Kiegészítő biztosíték 2. részlet | D94: k€ | G94: =SUM(H94:BP94) -> 0 | H94: =H$7*SUM($H51:H51)*Deposits!$Q$14 -> 0 | I94: =I$7*SUM($H51:I51)*Deposits!$Q$14 -> 0 | J94: =J$7*SUM($H51:J51)*Deposits!$Q$14 -> 0 | K94: =K$7*SUM($H51:K51)*Deposits!$Q$14 -> 0 | L94: =L$7*SUM($H51:L51)*Deposits!$Q$14 -> 0 | M94: =M$7*SUM($H51:M51)*Deposits!$Q$14 -> 0 | N94: =N$7*SUM($H51:N51)*Deposits!$Q$14 -> 0 | O94: =O$7*SUM($H51:O51)*Deposits!$Q$14 -> 0 | ... BP94: =BP$7*SUM($H51:BP51)*Deposits!$Q$14 -> 0
C95: =C36 -> Kiegészítő biztosíték visszautalás építési engedély megszerzésekor | D95: k€ | G95: =SUM(H95:BP95) -> 0 | H95: =H$7*SUM($H52:H52)*Deposits!$Q$15 -> 0 | I95: =I$7*SUM($H52:I52)*Deposits!$Q$15 -> 0 | J95: =J$7*SUM($H52:J52)*Deposits!$Q$15 -> 0 | K95: =K$7*SUM($H52:K52)*Deposits!$Q$15 -> 0 | L95: =L$7*SUM($H52:L52)*Deposits!$Q$15 -> 0 | M95: =M$7*SUM($H52:M52)*Deposits!$Q$15 -> 0 | N95: =N$7*SUM($H52:N52)*Deposits!$Q$15 -> 0 | O95: =O$7*SUM($H52:O52)*Deposits!$Q$15 -> 0 | ... BP95: =BP$7*SUM($H52:BP52)*Deposits!$Q$15 -> 0
C96: =C37 -> Kiegészítő biztosíték 3. részlet | D96: k€ | G96: =SUM(H96:BP96) -> 0 | H96: =H$7*SUM($H53:H53)*Deposits!$Q$16 -> 0 | I96: =I$7*SUM($H53:I53)*Deposits!$Q$16 -> 0 | J96: =J$7*SUM($H53:J53)*Deposits!$Q$16 -> 0 | K96: =K$7*SUM($H53:K53)*Deposits!$Q$16 -> 0 | L96: =L$7*SUM($H53:L53)*Deposits!$Q$16 -> 0 | M96: =M$7*SUM($H53:M53)*Deposits!$Q$16 -> 0 | N96: =N$7*SUM($H53:N53)*Deposits!$Q$16 -> 0 | O96: =O$7*SUM($H53:O53)*Deposits!$Q$16 -> 0 | ... BP96: =BP$7*SUM($H53:BP53)*Deposits!$Q$16 -> 0
C97: =C38 -> Kiegészítő biztosíték 4. részlet | D97: k€ | G97: =SUM(H97:BP97) -> 0 | H97: =H$7*SUM($H54:H54)*Deposits!$Q$17 -> 0 | I97: =I$7*SUM($H54:I54)*Deposits!$Q$17 -> 0 | J97: =J$7*SUM($H54:J54)*Deposits!$Q$17 -> 0 | K97: =K$7*SUM($H54:K54)*Deposits!$Q$17 -> 0 | L97: =L$7*SUM($H54:L54)*Deposits!$Q$17 -> 0 | M97: =M$7*SUM($H54:M54)*Deposits!$Q$17 -> 0 | N97: =N$7*SUM($H54:N54)*Deposits!$Q$17 -> 0 | O97: =O$7*SUM($H54:O54)*Deposits!$Q$17 -> 0 | ... BP97: =BP$7*SUM($H54:BP54)*Deposits!$Q$17 -> 0
C98: =C39 -> Csatlakozási díj – becsült összeg | D98: k€ | G98: =SUM(H98:BP98) -> 37573.318 | H98: =H$7*SUM($H55:H55)*Deposits!$Q$18 -> 0 | I98: =I$7*SUM($H55:I55)*Deposits!$Q$18 -> 0 | J98: =J$7*SUM($H55:J55)*Deposits!$Q$18 -> 0 | K98: =K$7*SUM($H55:K55)*Deposits!$Q$18 -> 0 | L98: =L$7*SUM($H55:L55)*Deposits!$Q$18 -> 0 | M98: =M$7*SUM($H55:M55)*Deposits!$Q$18 -> 0 | N98: =N$7*SUM($H55:N55)*Deposits!$Q$18 -> 0 | O98: =O$7*SUM($H55:O55)*Deposits!$Q$18 -> 0 | ... BP98: =BP$7*SUM($H55:BP55)*Deposits!$Q$18 -> 0
C99: Total recovered at exit | D99: k€ | G99: =SUM(H99:BP99) -> 41431.8 | H99: =SUM(H87:H98) -> 0 | I99: =SUM(I87:I98) -> 0 | J99: =SUM(J87:J98) -> 0 | K99: =SUM(K87:K98) -> 0 | L99: =SUM(L87:L98) -> 0 | M99: =SUM(M87:M98) -> 0 | N99: =SUM(N87:N98) -> 0 | O99: =SUM(O87:O98) -> 0 | ... BP99: =SUM(BP87:BP98) -> 0
C101: 7. Funding split of cash deposits between the two shareholder loans – 'recoverable' = refunded if the project FAILS (Deposits U / Inputs S)
C102: Funded by recoverable loan (refundable share of each line; participation fee per Inputs E256 / Deposits U7) | D102: k€ | G102: =SUM(H102:BP102) -> 41431.8 | H102: =SUMPRODUCT(H44:H55,Deposits!$U$7:$U$18) -> 0 | I102: =SUMPRODUCT(I44:I55,Deposits!$U$7:$U$18) -> 0 | J102: =SUMPRODUCT(J44:J55,Deposits!$U$7:$U$18) -> 0 | K102: =SUMPRODUCT(K44:K55,Deposits!$U$7:$U$18) -> 0 | L102: =SUMPRODUCT(L44:L55,Deposits!$U$7:$U$18) -> 0 | M102: =SUMPRODUCT(M44:M55,Deposits!$U$7:$U$18) -> 2465.7534 | N102: =SUMPRODUCT(N44:N55,Deposits!$U$7:$U$18) -> 0 | O102: =SUMPRODUCT(O44:O55,Deposits!$U$7:$U$18) -> 0 | ... BP102: =SUMPRODUCT(BP44:BP55,Deposits!$U$7:$U$18) -> 0
C103: Funded by unrecoverable (at-risk) loan (balance – forfeited on failure) | D103: k€ | G103: =SUM(H103:BP103) -> 16.438356 | H103: =H56-H102 -> 0 | I103: =I56-I102 -> 0 | J103: =J56-J102 -> 0 | K103: =K56-K102 -> 16.438356 | L103: =L56-L102 -> 0 | M103: =M56-M102 -> 0 | N103: =N56-N102 -> 0 | O103: =O56-O102 -> 0 | ... BP103: =BP56-BP102 -> 0
C105: 8. Shareholder loans (monthly compounding; repaid from proceeds at sale)
C106: FEP share of loan funding | D106: % | E106: =IF(Inputs!$E$35=1,Inputs!$E$33,1) -> 1
...

Sheet HTM
A1: =Inputs!A1 -> HUN Onshore Wind – MOIC model v5
A2: HTM (build & operate) – annual calculation grid 2026-2060, nominal k€. No inputs on this sheet. Column E = scalar parameter, column G = row total or result. Sign: + inflow, − outflow.
A3: Development-phase flows are pulled from MOIC / Deposits (Stage 1); everything from NTP onwards is driven by Inputs sections I–P.
C4: Timeline | H4: =H5-YEAR(Inputs!$E$27) -> 0 | I4: =I5-YEAR(Inputs!$E$27) -> 1 | J4: =J5-YEAR(Inputs!$E$27) -> 2 | K4: =K5-YEAR(Inputs!$E$27) -> 3 | L4: =L5-YEAR(Inputs!$E$27) -> 4 | M4: =M5-YEAR(Inputs!$E$27) -> 5 | N4: =N5-YEAR(Inputs!$E$27) -> 6 | O4: =O5-YEAR(Inputs!$E$27) -> 7 | ... AQ4: =AQ5-YEAR(Inputs!$E$27) -> 35
C5: Year | D5: Year | H5: =YEAR(Inputs!$E$27) -> 2026 | I5: =H5+1 -> 2027 | J5: =I5+1 -> 2028 | K5: =J5+1 -> 2029 | L5: =K5+1 -> 2030 | M5: =L5+1 -> 2031 | N5: =M5+1 -> 2032 | O5: =N5+1 -> 2033 | P5: =O5+1 -> 2034 | ... AQ5: =AP5+1 -> 2061
C6: Development-phase flag (investment year → NTP year) | D6: Flag | H6: =IF(AND(H5>=YEAR(Inputs!$E$27),H5<=YEAR(Inputs!$E$154)),1,0) -> 1 | I6: =IF(AND(I5>=YEAR(Inputs!$E$27),I5<=YEAR(Inputs!$E$154)),1,0) -> 1 | J6: =IF(AND(J5>=YEAR(Inputs!$E$27),J5<=YEAR(Inputs!$E$154)),1,0) -> 1 | K6: =IF(AND(K5>=YEAR(Inputs!$E$27),K5<=YEAR(Inputs!$E$154)),1,0) -> 1 | L6: =IF(AND(L5>=YEAR(Inputs!$E$27),L5<=YEAR(Inputs!$E$154)),1,0) -> 0 | M6: =IF(AND(M5>=YEAR(Inputs!$E$27),M5<=YEAR(Inputs!$E$154)),1,0) -> 0 | N6: =IF(AND(N5>=YEAR(Inputs!$E$27),N5<=YEAR(Inputs!$E$154)),1,0) -> 0 | O6: =IF(AND(O5>=YEAR(Inputs!$E$27),O5<=YEAR(Inputs!$E$154)),1,0) -> 0 | ... AQ6: =IF(AND(AQ5>=YEAR(Inputs!$E$27),AQ5<=YEAR(Inputs!$E$154)),1,0) -> 0
C7: Construction share of the year (by days NTP → COD) | D7: % | G7: =SUM(H7:AQ7) -> 1 | H7: =MAX(0,MIN(DATE(H5,12,31),Inputs!$E$155)-MAX(DATE(H5,1,1)-1,Inputs!$E$154))/(Inputs!$E$155-Inputs!$E$154) -> 0 | I7: =MAX(0,MIN(DATE(I5,12,31),Inputs!$E$155)-MAX(DATE(I5,1,1)-1,Inputs!$E$154))/(Inputs!$E$155-Inputs!$E$154) -> 0 | J7: =MAX(0,MIN(DATE(J5,12,31),Inputs!$E$155)-MAX(DATE(J5,1,1)-1,Inputs!$E$154))/(Inputs!$E$155-Inputs!$E$154) -> 0 | K7: =MAX(0,MIN(DATE(K5,12,31),Inputs!$E$155)-MAX(DATE(K5,1,1)-1,Inputs!$E$154))/(Inputs!$E$155-Inputs!$E$154) -> 0.1260274 | L7: =MAX(0,MIN(DATE(L5,12,31),Inputs!$E$155)-MAX(DATE(L5,1,1)-1,Inputs!$E$154))/(Inputs!$E$155-Inputs!$E$154) -> 0.5 | M7: =MAX(0,MIN(DATE(M5,12,31),Inputs!$E$155)-MAX(DATE(M5,1,1)-1,Inputs!$E$154))/(Inputs!$E$155-Inputs!$E$154) -> 0.3739726 | N7: =MAX(0,MIN(DATE(N5,12,31),Inputs!$E$155)-MAX(DATE(N5,1,1)-1,Inputs!$E$154))/(Inputs!$E$155-Inputs!$E$154) -> 0 | O7: =MAX(0,MIN(DATE(O5,12,31),Inputs!$E$155)-MAX(DATE(O5,1,1)-1,Inputs!$E$154))/(Inputs!$E$155-Inputs!$E$154) -> 0 | ... AQ7: =MAX(0,MIN(DATE(AQ5,12,31),Inputs!$E$155)-MAX(DATE(AQ5,1,1)-1,Inputs!$E$154))/(Inputs!$E$155-Inputs!$E$154) -> 0
C8: Full operating-year flag (operating fraction = 100%) | D8: Flag | G8: =SUM(H8:AQ8) -> 29 | H8: =IF(H10>=1,1,0) -> 0 | I8: =IF(I10>=1,1,0) -> 0 | J8: =IF(J10>=1,1,0) -> 0 | K8: =IF(K10>=1,1,0) -> 0 | L8: =IF(L10>=1,1,0) -> 0 | M8: =IF(M10>=1,1,0) -> 0 | N8: =IF(N10>=1,1,0) -> 1 | O8: =IF(O10>=1,1,0) -> 1 | ... AQ8: =IF(AQ10>=1,1,0) -> 0
C9: Operating year index (1 = first full calendar year after COD; COD year = 0) | D9: # | H9: =IF(AND(H10>0,H$5>=Inputs!$E$156),H$5-Inputs!$E$156+1,0) -> 0 | I9: =IF(AND(I10>0,I$5>=Inputs!$E$156),I$5-Inputs!$E$156+1,0) -> 0 | J9: =IF(AND(J10>0,J$5>=Inputs!$E$156),J$5-Inputs!$E$156+1,0) -> 0 | K9: =IF(AND(K10>0,K$5>=Inputs!$E$156),K$5-Inputs!$E$156+1,0) -> 0 | L9: =IF(AND(L10>0,L$5>=Inputs!$E$156),L$5-Inputs!$E$156+1,0) -> 0 | M9: =IF(AND(M10>0,M$5>=Inputs!$E$156),M$5-Inputs!$E$156+1,0) -> 0 | N9: =IF(AND(N10>0,N$5>=Inputs!$E$156),N$5-Inputs!$E$156+1,0) -> 1 | O9: =IF(AND(O10>0,O$5>=Inputs!$E$156),O$5-Inputs!$E$156+1,0) -> 2 | ... AQ9: =IF(AND(AQ10>0,AQ$5>=Inputs!$E$156),AQ$5-Inputs!$E$156+1,0) -> 30
