Workbook
Name Balancing: Inputs!$E$69
Name Bench_BESS: Inputs!$E$8
Name Bench_Wind: Inputs!$E$7
Name BESS_Capex: Inputs!$E$56
Name Bid_Sec_Rate: Inputs!$E$9
Name Capex_Civil: Inputs!$E$49
Name Capex_Cont: Inputs!$E$55
Name Capex_Elec: Inputs!$E$50
Name Capex_Fdn: Inputs!$E$48
Name Capex_Install: Inputs!$E$47
Name Capex_Land: Inputs!$E$52
Name Capex_Owner: Inputs!$E$51
Name Case_CN: Dashboard!$H$25
Name Case_EU: Dashboard!$H$24
Name Case_OM: Dashboard!$H$28
Name Case_P50: Dashboard!$H$27
Name Case_PPA: Dashboard!$H$26
Name CIT_Rate: Inputs!$E$45
Name Clipping: Inputs!$E$59
Name Curtailment: Inputs!$E$58
Name Dash_BESS_Share: Dashboard!$E$8:$G$8
Name Dash_Brownfield: Dashboard!$E$15:$G$15
Name Dash_Case: Dashboard!$H$23
Name Dash_Case_CN: Dashboard!$E$25:$G$25
Name Dash_Case_EU: Dashboard!$E$24:$G$24
Name Dash_Case_OM: Dashboard!$E$28:$G$28
Name Dash_Case_P50: Dashboard!$E$27:$G$27
Name Dash_Case_PPA: Dashboard!$E$26:$G$26
Name Dash_Community: Dashboard!$E$12:$G$12
Name Dash_DSA: Dashboard!$E$20:$G$20
Name Dash_FEP_Share: Dashboard!$E$19:$G$19
Name Dash_Hours: Dashboard!$E$9:$G$9
Name Dash_Municipal: Dashboard!$E$11:$G$11
Name Dash_MVA: Dashboard!$E$6:$G$6
Name Dash_Overbuild: Dashboard!$E$7:$G$7
Name Dash_Partial: Dashboard!$E$13:$G$13
Name Dash_PB_Mult: Dashboard!$E$14:$G$14
Name Dash_Premium: Dashboard!$E$18:$G$18
Name Dash_Shared: Dashboard!$E$16:$G$16
Name Dash_Shortfall: Dashboard!$E$10:$G$10
Name Dash_Turbine: Dashboard!$E$17:$G$17
Name Days_In_Year: Inputs!$E$80
Name Degradation: Inputs!$E$60
Name Devex_Floor: Inputs!$E$39
Name Discount_Rate: Inputs!$E$77
Name DSA_Cap: Inputs!$E$44
Name DSA_Rate: Inputs!$E$43
Name First_Year: Inputs!$E$78
Name Freeze_Date: Inputs!$E$40
Name FX: Inputs!$E$6
Name Grid_Charges: Inputs!$E$70
Name HIPA_Rate: Inputs!$E$72
Name Life: Inputs!$E$76
Name Lump_Basis: Inputs!$E$54
Name Master_Check: Dashboard!$H$356
Name MEKH_Fee: Inputs!$E$71
Name Months_In_Year: Inputs!$E$81
Name Opex_Admin: Inputs!$E$68
Name Opex_BoP: Inputs!$E$63
Name Opex_Cont: Inputs!$E$73

Sheet Dashboard
C2: HU wind projects
C3: Master check (0 = OK; checks at the end of the detail) | D3: flag | H3: =Master_Check -> 0
B5: x | C5: Key inputs: the bids | E5: Bora | F5: Iváncsa | G5: Dunaújváros | H5: Total
C6: Net connection capacity | D6: MVA | E6: 50 | F6: 50 | G6: 50 | H6: =SUM(E6:G6) -> 150
C7: Overbuild (ÖSZ-3) | D7: % | E7: 0.2 | F7: 0.4 | G7: 0.4
C8: BESS power, share of MVA (ÖSZ-4) | D8: % | E8: 0.1 | F8: 0.2 | G8: 0.2
C9: BESS duration | D9: h | E9: 4 | F9: 4 | G9: 4
C10: Wind built below the bid | D10: % | E10: 0.1 | F10: 0.1 | G10: 0.1
C11: Municipal one-off (ÖSZ-1), at COD | D11: EUR k/MVA | E11: 20 | F11: 50 | G11: 50
C12: Community contribution (ÖSZ-2) | D12: EUR/MWh | E12: 0 | F12: 3 | G12: 3
C13: Partial award accepted (ÖSZ-5) | D13: flag | E13: 1 | F13: 0 | G13: 0
C14: Performance security multiple (ÖSZ-6) | D14: x | E14: 1 | F14: 1 | G14: 1
C15: Brownfield site (ÖSZ-7) | D15: flag | E15: 0 | F15: 0 | G15: 0
C16: Shared connection (ÖSZ-8) | D16: flag | E16: 1 | F16: 0 | G16: 0
C17: Turbine route (EU or CN; EU scores ÖSZ-9) | D17: text | E17: CN | F17: CN | G17: CN
C18: RtB premium | D18: EUR k/MVA | E18: 150 | F18: 150 | G18: 150
C19: FEP share of distributable proceeds | D19: % | E19: 0.7 | F19: 1 | G19: 1
C20: Developer success fee (DSA) on | D20: flag | E20: 1 | F20: 0 | G20: 0
B22: x | C22: Case: turbine price, PPA, yield, O&M | E22: Base | F22: Low | G22: High | H22: Live
C23: Case selected (Base, Low or High) | D23: case | H23: Base
C24: Turbine supply incl. transport, EU route | D24: EUR k/MW | E24: 850 | F24: 950 | G24: 800 | H24: =INDEX(E24:G24,MATCH(Dash_Case,$E$22:$G$22,0)) -> 850 | J24: Bora Dashboard H8 / Inputs G162
C25: Turbine supply incl. transport, CN route | D25: EUR k/MW | E25: 500 | F25: 600 | G25: 480 | H25: =INDEX(E25:G25,MATCH(Dash_Case,$E$22:$G$22,0)) -> 500 | J25: Bora Inputs H162
C26: PPA price in the COD year | D26: EUR/MWh | E26: 90 | F26: 90 | G26: 100 | H26: =INDEX(E26:G26,MATCH(Dash_Case,$E$22:$G$22,0)) -> 90 | J26: Bora Dashboard H9
C27: Net P50 hours | D27: h/yr | E27: 2500 | F27: 2460 | G27: 2600 | H27: =INDEX(E27:G27,MATCH(Dash_Case,$E$22:$G$22,0)) -> 2500 | J27: Bora Dashboard H10
C28: O&M full-service contract | D28: EUR k/MW/yr | E28: 12 | F28: 12 | G28: 10 | H28: =INDEX(E28:G28,MATCH(Dash_Case,$E$22:$G$22,0)) -> 12 | J28: Bora Dashboard H11
B30: x | C30: Bid points and capacity | E30: Bora | F30: Iváncsa | G30: Dunaújváros | H30: Total
C31: Points – municipal one-off | D31: points | E31: =INDEX(Osz1_Pts,1+SUMPRODUCT((Osz1_LB<E11)+(Osz1_LB=E11)*Osz1_Incl))*Osz1_W -> 4 | F31: =INDEX(Osz1_Pts,1+SUMPRODUCT((Osz1_LB<F11)+(Osz1_LB=F11)*Osz1_Incl))*Osz1_W -> 20 | G31: =INDEX(Osz1_Pts,1+SUMPRODUCT((Osz1_LB<G11)+(Osz1_LB=G11)*Osz1_Incl))*Osz1_W -> 20
C32: Points – community contribution | D32: points | E32: =INDEX(Osz2_Pts,1+SUMPRODUCT((Osz2_LB<E12)+(Osz2_LB=E12)*Osz2_Incl))*Osz2_W -> 0 | F32: =INDEX(Osz2_Pts,1+SUMPRODUCT((Osz2_LB<F12)+(Osz2_LB=F12)*Osz2_Incl))*Osz2_W -> 15 | G32: =INDEX(Osz2_Pts,1+SUMPRODUCT((Osz2_LB<G12)+(Osz2_LB=G12)*Osz2_Incl))*Osz2_W -> 15
C33: Points – overbuild | D33: points | E33: =INDEX(Osz3_Pts,1+SUMPRODUCT((Osz3_LB<E7)+(Osz3_LB=E7)*Osz3_Incl))*Osz3_W -> 5 | F33: =INDEX(Osz3_Pts,1+SUMPRODUCT((Osz3_LB<F7)+(Osz3_LB=F7)*Osz3_Incl))*Osz3_W -> 9 | G33: =INDEX(Osz3_Pts,1+SUMPRODUCT((Osz3_LB<G7)+(Osz3_LB=G7)*Osz3_Incl))*Osz3_W -> 9
C34: Points – BESS | D34: points | E34: =INDEX(Osz3_Pts,1+SUMPRODUCT((Osz3_LB<E8)+(Osz3_LB=E8)*Osz3_Incl))*Osz4_W -> 4.5 | F34: =INDEX(Osz3_Pts,1+SUMPRODUCT((Osz3_LB<F8)+(Osz3_LB=F8)*Osz3_Incl))*Osz4_W -> 7.5 | G34: =INDEX(Osz3_Pts,1+SUMPRODUCT((Osz3_LB<G8)+(Osz3_LB=G8)*Osz3_Incl))*Osz4_W -> 7.5
C35: Points – partial award | D35: points | E35: =E13*Osz5_Pts*Osz5_W -> 5 | F35: =F13*Osz5_Pts*Osz5_W -> 0 | G35: =G13*Osz5_Pts*Osz5_W -> 0
C36: Points – performance security | D36: points | E36: =INDEX(Osz6_Pts,1+SUMPRODUCT((Osz6_LB<E14)+(Osz6_LB=E14)*Osz6_Incl))*Osz6_W -> 0 | F36: =INDEX(Osz6_Pts,1+SUMPRODUCT((Osz6_LB<F14)+(Osz6_LB=F14)*Osz6_Incl))*Osz6_W -> 0 | G36: =INDEX(Osz6_Pts,1+SUMPRODUCT((Osz6_LB<G14)+(Osz6_LB=G14)*Osz6_Incl))*Osz6_W -> 0
C37: Points – brownfield | D37: points | E37: =E15*Osz7_Pts*Osz7_W -> 0 | F37: =F15*Osz7_Pts*Osz7_W -> 0 | G37: =G15*Osz7_Pts*Osz7_W -> 0
C38: Points – shared connection | D38: points | E38: =E16*Osz8_Pts*Osz8_W -> 5 | F38: =F16*Osz8_Pts*Osz8_W -> 0 | G38: =G16*Osz8_Pts*Osz8_W -> 0
C39: Points – EU turbines | D39: points | E39: =N(E17="EU")*Osz9a_Pts*Osz9_W -> 0 | F39: =N(F17="EU")*Osz9a_Pts*Osz9_W -> 0 | G39: =N(G17="EU")*Osz9a_Pts*Osz9_W -> 0
C40: Points – EU transformers | D40: points | E40: =Inputs!E$25*Osz9b_Pts*Osz9_W -> 0 | F40: =Inputs!F$25*Osz9b_Pts*Osz9_W -> 0 | G40: =Inputs!G$25*Osz9b_Pts*Osz9_W -> 0
C41: Points total | D41: points | E41: =SUM(E31:E40) -> 23.5 | F41: =SUM(F31:F40) -> 51.5 | G41: =SUM(G31:G40) -> 51.5
C42: Wind committed in the bid | D42: MW | E42: =E6*(1+E7) -> 60 | F42: =F6*(1+F7) -> 70 | G42: =G6*(1+G7) -> 70 | H42: =SUM(E42:G42) -> 200
C43: BESS energy | D43: MWh | E43: =E6*E8*E9 -> 20 | F43: =F6*F8*F9 -> 40 | G43: =G6*G8*G9 -> 40 | H43: =SUM(E43:G43) -> 100
C44: Wind built (committed less the build shortfall) | D44: MW | E44: =E42*(1-E10) -> 54 | F44: =F42*(1-F10) -> 63 | G44: =G42*(1-G10) -> 63 | H44: =SUM(E44:G44) -> 180
B46: x | C46: Guarantees, securities and connection fees, DEVEX (HUF) | E46: Bora | F46: Iváncsa | G46: Dunaújváros | H46: Total | J46: Date
C47: Participation fee | D47: HUF | E47: =Part_Fee -> 3000000 | F47: =Part_Fee -> 3000000 | G47: =Part_Fee -> 3000000 | H47: =SUM(E47:G47) -> 9000000 | J47: =Inputs!E$27 -> 46325
C48: Bid security | D48: HUF | E48: =Bid_Sec_Rate*(E42*Bench_Wind+E43*Bench_BESS) -> 141800000 | F48: =Bid_Sec_Rate*(F42*Bench_Wind+F43*Bench_BESS) -> 182100000 | G48: =Bid_Sec_Rate*(G42*Bench_Wind+G43*Bench_BESS) -> 182100000 | H48: =SUM(E48:G48) -> 506000000 | J48: =Inputs!E$27 -> 46325
C49: Performance security payable (bid security deducted) | D49: HUF | E49: =PB_Rate*E14*(E42*Bench_Wind+E43*Bench_BESS)-E48 -> 567200000 | F49: =PB_Rate*F14*(F42*Bench_Wind+F43*Bench_BESS)-F48 -> 728400000 | G49: =PB_Rate*G14*(G42*Bench_Wind+G43*Bench_BESS)-G48 -> 728400000 | H49: =SUM(E49:G49) -> 2024000000 | J49: =Inputs!E$28 -> 46402
C50: TSO connection-request security | D50: HUF | E50: =TSO_Rate*E6 -> 225000000 | F50: =TSO_Rate*F6 -> 225000000 | G50: =TSO_Rate*G6 -> 225000000 | H50: =SUM(E50:G50) -> 675000000 | J50: =Inputs!E$29 -> 46402
C51: Direct connection fee (per point ÷ bids sharing it) | D51: HUF | E51: =Inputs!E$15/Inputs!E$16 -> 254172902 | F51: =Inputs!F$15/Inputs!F$16 -> 460000000 | G51: =Inputs!G$15/Inputs!G$16 -> 460000000 | H51: =SUM(E51:G51) -> 1174172902 | J51: =Inputs!E$30 -> 47027
C52: Indirect connection fee, payable (TSO security deducted) | D52: HUF | E52: =Inputs!E$14*E6-E50 -> 3428565300 | F52: =Inputs!F$14*F6-F50 -> 766334000 | G52: =Inputs!G$14*G6-G50 -> 766334000 | H52: =SUM(E52:G52) -> 4961233300 | J52: =Inputs!E$30 -> 47027
C53: DEVEX | D53: HUF | E53: =SUM(Inputs!E$18:E$23)*FX*Thousand -> 286331550 | F53: =SUM(Inputs!F$18:F$23)*FX*Thousand -> 3.65e+08 | G53: =SUM(Inputs!G$18:G$23)*FX*Thousand -> 3.65e+08 | H53: =SUM(E53:G53) -> 1016331550 | J53: =Inputs!E$31 -> 46752
C54: Signing fee and DD | D54: HUF | E54: =Inputs!E$17*FX*Thousand -> 36500000 | F54: =Inputs!F$17*FX*Thousand -> 54750000 | G54: =Inputs!G$17*FX*Thousand -> 54750000 | H54: =SUM(E54:G54) -> 146000000 | J54: =Inputs!E$26 -> 46234
C55: Total cash to RtB (incl. signing and DD) | D55: HUF | E55: =SUM(E47:E54) -> 4942569752 | F55: =SUM(F47:F54) -> 2784584000 | G55: =SUM(G47:G54) -> 2784584000 | H55: =SUM(E55:G55) -> 10511737752
B57: x | C57: Guarantees, securities and connection fees, DEVEX (EUR k) | E57: Bora | F57: Iváncsa | G57: Dunaújváros | H57: Total | J57: Date
C58: Participation fee | D58: EUR k | E58: =E47/FX/Thousand -> 8.2191781 | F58: =F47/FX/Thousand -> 8.2191781 | G58: =G47/FX/Thousand -> 8.2191781 | H58: =SUM(E58:G58) -> 24.657534 | J58: =Inputs!E$27 -> 46325
C59: Bid security | D59: EUR k | E59: =E48/FX/Thousand -> 388.49315 | F59: =F48/FX/Thousand -> 498.90411 | G59: =G48/FX/Thousand -> 498.90411 | H59: =SUM(E59:G59) -> 1386.3014 | J59: =Inputs!E$27 -> 46325
C60: Performance security payable (bid security deducted) | D60: EUR k | E60: =E49/FX/Thousand -> 1553.9726 | F60: =F49/FX/Thousand -> 1995.6164 | G60: =G49/FX/Thousand -> 1995.6164 | H60: =SUM(E60:G60) -> 5545.2055 | J60: =Inputs!E$28 -> 46402
C61: TSO connection-request security | D61: EUR k | E61: =E50/FX/Thousand -> 616.43836 | F61: =F50/FX/Thousand -> 616.43836 | G61: =G50/FX/Thousand -> 616.43836 | H61: =SUM(E61:G61) -> 1849.3151 | J61: =Inputs!E$29 -> 46402
C62: Direct connection fee (per point ÷ bids sharing it) | D62: EUR k | E62: =E51/FX/Thousand -> 696.36412 | F62: =F51/FX/Thousand -> 1260.274 | G62: =G51/FX/Thousand -> 1260.274 | H62: =SUM(E62:G62) -> 3216.9121 | J62: =Inputs!E$30 -> 47027
C63: Indirect connection fee, payable (TSO security deducted) | D63: EUR k | E63: =E52/FX/Thousand -> 9393.3296 | F63: =F52/FX/Thousand -> 2099.5452 | G63: =G52/FX/Thousand -> 2099.5452 | H63: =SUM(E63:G63) -> 13592.42 | J63: =Inputs!E$30 -> 47027
C64: DEVEX | D64: EUR k | E64: =E53/FX/Thousand -> 784.47 | F64: =F53/FX/Thousand -> 1000 | G64: =G53/FX/Thousand -> 1000 | H64: =SUM(E64:G64) -> 2784.47 | J64: =Inputs!E$31 -> 46752
C65: Signing fee and DD | D65: EUR k | E65: =Inputs!E$17 -> 100 | F65: =Inputs!F$17 -> 150 | G65: =Inputs!G$17 -> 150 | H65: =SUM(E65:G65) -> 400 | J65: =Inputs!E$26 -> 46234
C66: Total cash to RtB (incl. signing and DD) | D66: EUR k | E66: =SUM(E58:E65) -> 13541.287 | F66: =SUM(F58:F65) -> 7628.9973 | G66: =SUM(G58:G65) -> 7628.9973 | H66: =SUM(E66:G66) -> 28799.282
B68: x | C68: Cash to RtB by nature: sunk, returned, or borne by the buyer (EUR k) | E68: Bora | F68: Iváncsa | G68: Dunaújváros | H68: Total | J68: Who bears it
C69: Sunk fees and devex (signing and DD, participation fee, devex) | D69: EUR k | E69: =E58+E64+E65 -> 892.68918 | F69: =F58+F64+F65 -> 1158.2192 | G69: =G58+G64+G65 -> 1158.2192 | H69: =SUM(E69:G69) -> 3209.1275 | J69: FEP – sunk; recovered only via the claims at the sale
C70: Securities, returned (bid, performance, TSO connection request) | D70: EUR k | E70: =SUM(E59:E61) -> 2558.9041 | F70: =SUM(F59:F61) -> 3110.9589 | G70: =SUM(G59:G61) -> 3110.9589 | H70: =SUM(E70:G70) -> 8780.8219 | J70: FEP – cash out, returned or reimbursed at the sale
C71: Grid connection fees (direct + indirect, payable at HCSSZ) | D71: EUR k | E71: =E62+E63 -> 10089.694 | F71: =F62+F63 -> 3359.8192 | G71: =G62+G63 -> 3359.8192 | H71: =SUM(E71:G71) -> 16809.332 | J71: Buyer at RtB; FEP pays only if no buyer is found
C72: Total cash to RtB (= total above) | D72: EUR k | E72: =SUM(E69:E71) -> 13541.287 | F72: =SUM(F69:F71) -> 7628.9973 | G72: =SUM(G69:G71) -> 7628.9973 | H72: =SUM(E72:G72) -> 28799.282 | J72: Case A: FEP pre-funds everything
C73: Grid connection fees, share of the total | D73: % | E73: =E71/E72 -> 0.74510596 | F73: =F71/F72 -> 0.44040115 | G73: =G71/G72 -> 0.44040115 | H73: =H71/H72 -> 0.58367192
C74: FEP exposure if the buyer pays the grid connection fees | D74: EUR k | E74: =E72-E71 -> 3451.5933 | F74: =F72-F71 -> 4269.1781 | G74: =G72-G71 -> 4269.1781 | H74: =SUM(E74:G74) -> 11989.949 | J74: Case B: FEP funds sunk fees, devex and securities only
B76: x | C76: Capex breakdown to COD | E76: Bora | F76: Iváncsa | G76: Dunaújváros | H76: Total
C77: Turbines (route price, live case) | D77: EUR k | E77: =IF(E17="EU",Case_EU,Case_CN)*E44 -> 27000 | F77: =IF(F17="EU",Case_EU,Case_CN)*F44 -> 31500 | G77: =IF(G17="EU",Case_EU,Case_CN)*G44 -> 31500 | H77: =SUM(E77:G77) -> 90000
C78: Installation and erection | D78: EUR k | E78: =Capex_Install*E44 -> 4320 | F78: =Capex_Install*F44 -> 5040 | G78: =Capex_Install*G44 -> 5040 | H78: =SUM(E78:G78) -> 14400
C79: Foundations | D79: EUR k | E79: =Capex_Fdn*E44 -> 4860 | F79: =Capex_Fdn*F44 -> 5670 | G79: =Capex_Fdn*G44 -> 5670 | H79: =SUM(E79:G79) -> 16200
C80: Balance of plant – civil | D80: EUR k | E80: =Capex_Civil*E44 -> 3780 | F80: =Capex_Civil*F44 -> 4410 | G80: =Capex_Civil*G44 -> 4410 | H80: =SUM(E80:G80) -> 12600
C81: Balance of plant – electrical | D81: EUR k | E81: =Capex_Elec*E44 -> 3240 | F81: =Capex_Elec*F44 -> 3780 | G81: =Capex_Elec*G44 -> 3780 | H81: =SUM(E81:G81) -> 10800
C82: Owner's costs, engineering, PM, construction insurance | D82: EUR k | E82: =Capex_Owner*E44 -> 2160 | F82: =Capex_Owner*F44 -> 2520 | G82: =Capex_Owner*G44 -> 2520 | H82: =SUM(E82:G82) -> 7200
C83: Land purchase and easements | D83: EUR k | E83: =Capex_Land*E44 -> 810 | F83: =Capex_Land*F44 -> 945 | G83: =Capex_Land*G44 -> 945 | H83: =SUM(E83:G83) -> 2700
C84: Substation and 132 kV bay (scaled by MVA) | D84: EUR k | E84: =Subs_Lump*E6/Lump_Basis -> 3000 | F84: =Subs_Lump*F6/Lump_Basis -> 3000 | G84: =Subs_Lump*G6/Lump_Basis -> 3000 | H84: =SUM(E84:G84) -> 9000
C85: Contingency (not on BESS) | D85: EUR k | E85: =SUM(E77:E84)*Capex_Cont -> 2458.5 | F85: =SUM(F77:F84)*Capex_Cont -> 2843.25 | G85: =SUM(G77:G84)*Capex_Cont -> 2843.25 | H85: =SUM(E85:G85) -> 8145
C86: BESS (on BESS energy) | D86: EUR k | E86: =BESS_Capex*E43 -> 2000 | F86: =BESS_Capex*F43 -> 4000 | G86: =BESS_Capex*G43 -> 4000 | H86: =SUM(E86:G86) -> 10000
C87: Construction capex | D87: EUR k | E87: =SUM(E77:E86) -> 53628.5 | F87: =SUM(F77:F86) -> 63708.25 | G87: =SUM(G77:G86) -> 63708.25 | H87: =SUM(E87:G87) -> 181045
C88: Connection fees (TSO security, direct, indirect) | D88: EUR k | E88: =E61+E62+E63 -> 10706.132 | F88: =F61+F62+F63 -> 3976.2575 | G88: =G61+G62+G63 -> 3976.2575 | H88: =SUM(E88:G88) -> 18658.647
C89: Municipal one-off | D89: EUR k | E89: =E11*E6 -> 1000 | F89: =F11*F6 -> 2500 | G89: =G11*G6 -> 2500 | H89: =SUM(E89:G89) -> 6000
C90: Development (participation fee, devex, signing and DD) | D90: EUR k | E90: =E58+E64+E65 -> 892.68918 | F90: =F58+F64+F65 -> 1158.2192 | G90: =G58+G64+G65 -> 1158.2192 | H90: =SUM(E90:G90) -> 3209.1275
C91: All-in cost to COD (securities excluded: returned) | D91: EUR k | E91: =E87+SUM(E88:E90) -> 66227.321 | F91: =F87+SUM(F88:F90) -> 71342.727 | G91: =G87+SUM(G88:G90) -> 71342.727 | H91: =SUM(E91:G91) -> 208912.77
C92: All-in cost per MW built | D92: EUR k/MW | E92: =E91/E44 -> 1226.4319 | F92: =F91/F44 -> 1132.4242 | G92: =G91/G44 -> 1132.4242 | H92: =H91/H44 -> 1160.6265
C93: All-in cost per MVA | D93: EUR k/MVA | E93: =E91/E6 -> 1324.5464 | F93: =F91/F6 -> 1426.8545 | G93: =G91/G6 -> 1426.8545 | H93: =H91/H6 -> 1392.7518
B95: x | C95: Devex breakdown (Bora: devex-file categories; tender fee and securities: above) | E95: Bora | F95: Iváncsa | G95: Dunaújváros | H95: Total
C96: Grid connection plan and agreement | D96: EUR k | E96: =Inputs!E$18 -> 40.47 | F96: =Inputs!F$18 -> 51.588971 | G96: =Inputs!G$18 -> 51.588971 | H96: =SUM(E96:G96) -> 143.64794
C97: Land (reservation, purchase, contracting) | D97: EUR k | E97: =Inputs!E$19 -> 150.66 | F97: =Inputs!F$19 -> 192.05323 | G97: =Inputs!G$19 -> 192.05323 | H97: =SUM(E97:G97) -> 534.76647
C98: Permits, zoning, cable rights | D98: EUR k | E98: =Inputs!E$20 -> 333.93 | F98: =Inputs!F$20 -> 425.67593 | G98: =Inputs!G$20 -> 425.67593 | H98: =SUM(E98:G98) -> 1185.2819
C99: Studies (wind, environment, ground) | D99: EUR k | E99: =Inputs!E$21 -> 151.36 | F99: =Inputs!F$21 -> 192.94556 | G99: =Inputs!G$21 -> 192.94556 | H99: =SUM(E99:G99) -> 537.25111
C100: Legal, financial and other | D100: EUR k | E100: =Inputs!E$22 -> 37.5 | F100: =Inputs!F$22 -> 47.802975 | G100: =Inputs!G$22 -> 47.802975 | H100: =SUM(E100:G100) -> 133.10595
C101: Contingency | D101: EUR k | E101: =Inputs!E$23 -> 70.55 | F101: =Inputs!F$23 -> 89.933331 | G101: =Inputs!G$23 -> 89.933331 | H101: =SUM(E101:G101) -> 250.41666
C102: Devex total (= DEVEX line above) | D102: EUR k | E102: =SUM(E96:E101) -> 784.47 | F102: =SUM(F96:F101) -> 1000 | G102: =SUM(G96:G101) -> 1000 | H102: =SUM(E102:G102) -> 2784.47
B104: x | C104: Returns RTB COD HTM | E104: Bora | F104: Iváncsa | G104: Dunaújváros | H104: Total
C105: RTB exit, Case A: buyer pays the grid connection fees (FEP does not pre-fund)
C106: Grid connection fees paid by the buyer (not FEP cash) | D106: EUR k | E106: =E216 -> 10089.694 | F106: =F216 -> 3359.8192 | G106: =G216 -> 3359.8192 | H106: =SUM(E106:G106) -> 16809.332
C107: Total FEP cash out to RtB (peak exposure) | D107: EUR k | E107: =E217 -> 3451.5933 | F107: =F217 -> 4269.1781 | G107: =G217 -> 4269.1781 | H107: =SUM(E107:G107) -> 11989.949
C108: Total proceeds to FEP at the sale | D108: EUR k | E108: =E238 -> 7816.125 | F108: =F238 -> 10360.959 | G108: =G238 -> 10360.959 | H108: =SUM(E108:G108) -> 28538.043
C109: FEP profit, pre-tax | D109: EUR k | E109: =E239 -> 4364.5317 | F109: =F239 -> 6091.7808 | G109: =G239 -> 6091.7808 | H109: =SUM(E109:G109) -> 16548.093
C110: FEP profit, post-tax | D110: EUR k | E110: =E241 -> 3971.7238 | F110: =F241 -> 5543.5205 | G110: =G241 -> 5543.5205 | H110: =SUM(E110:G110) -> 15058.765
...

Sheet Inputs
C2: HU wind bids – other inputs (blue) with sources
B4: x | C4: Inputs | E4: Bora | F4: Iváncsa | G4: Dunaújváros | H4: Source
C5: Tender and grid (all projects; value in column E)
C6: FX rate | D6: HUF/EUR | E6: 365 | H6: Bora Inputs E11; Bid_Cash E45
C7: Security base: benchmark investment, wind | D7: HUF/MW | E7: 406000000 | H7: Bora Inputs E75; Bid_Cash E46
C8: Security base: benchmark investment, BESS | D8: HUF/MWh | E8: 200000000 | H8: Bora Inputs E89; Bid_Cash E47
C9: Bid security, share of base | D9: % | E9: 0.005 | H9: Bora Inputs E76; Bid_Cash E49
C10: Performance security, minimum share of base | D10: % | E10: 0.025 | H10: Bora Inputs E77; Bid_Cash E50
C11: Participation fee per bid | D11: HUF | E11: 3000000 | H11: Bora Inputs E81; Bid_Cash E48
C12: TSO connection-request security | D12: HUF/MVA | E12: 4500000 | H12: Bora Inputs E83; Bid_Cash E51
C13: Per project: fees, devex, dates
C14: Indirect connection fee | D14: HUF/MVA | E14: 73071306 | F14: 19826680 | G14: 19826680 | H14: Bora Inputs G290; Bid_Cash E52
C15: Direct connection fee per connection point | D15: HUF | E15: 508345804 | F15: 460000000 | G15: 460000000 | H15: Bora Inputs G291; Bid_Cash E53
C16: Bids sharing the connection point | D16: count | E16: 2 | F16: 1 | G16: 1 | H16: Bora: 2 bids per point (SPEC §22.2)
C17: Signing fee and DD | D17: EUR k | E17: 100 | F17: 150 | G17: 150 | H17: Bora E24+E25: 400 × 50/200; Bid_Cash E55
C18: Devex: grid connection plan and agreement | D18: EUR k | E18: 40.47 | F18: =$E18/SUM($E$18:$E$23)*F$24 -> 51.588971 | G18: =$E18/SUM($E$18:$E$23)*G$24 -> 51.588971 | H18: Bora share × F25/G25 (Iváncsa, Dunaújváros); Bora: Devex_FEP × 50/100 MVA
C19: Devex: land (reservation, purchase, contracting) | D19: EUR k | E19: 150.66 | F19: =$E19/SUM($E$18:$E$23)*F$24 -> 192.05323 | G19: =$E19/SUM($E$18:$E$23)*G$24 -> 192.05323 | H19: Bora share × F25/G25 (Iváncsa, Dunaújváros); Bora: Devex_FEP × 50/100 MVA
C20: Devex: permits, zoning, cable rights | D20: EUR k | E20: 333.93 | F20: =$E20/SUM($E$18:$E$23)*F$24 -> 425.67593 | G20: =$E20/SUM($E$18:$E$23)*G$24 -> 425.67593 | H20: Bora share × F25/G25 (Iváncsa, Dunaújváros); Bora: Devex_FEP × 50/100 MVA
C21: Devex: studies (wind, environment, ground) | D21: EUR k | E21: 151.36 | F21: =$E21/SUM($E$18:$E$23)*F$24 -> 192.94556 | G21: =$E21/SUM($E$18:$E$23)*G$24 -> 192.94556 | H21: Bora share × F25/G25 (Iváncsa, Dunaújváros); Bora: Devex_FEP × 50/100 MVA
C22: Devex: legal, financial and other | D22: EUR k | E22: 37.5 | F22: =$E22/SUM($E$18:$E$23)*F$24 -> 47.802975 | G22: =$E22/SUM($E$18:$E$23)*G$24 -> 47.802975 | H22: Bora share × F25/G25 (Iváncsa, Dunaújváros); Bora: Devex_FEP × 50/100 MVA
C23: Devex: contingency | D23: EUR k | E23: 70.55 | F23: =$E23/SUM($E$18:$E$23)*F$24 -> 89.933331 | G23: =$E23/SUM($E$18:$E$23)*G$24 -> 89.933331 | H23: Bora share × F25/G25 (Iváncsa, Dunaújváros); Bora: Devex_FEP × 50/100 MVA
C24: Devex total, Iváncsa and Dunaújváros (allocated pro rata to Bora's categories) | D24: EUR k | F24: 1000 | G24: 1000 | H24: User, 27-Oct-26: EUR 1m per project, split as Bora
C25: EU transformers ≥ 80 % (ÖSZ-9) | D25: flag | E25: 0 | F25: 0 | G25: 0 | H25: Bid_Cash E16; SPEC §23.1
C26: Signing fee and DD paid | D26: date | E26: 46234 | F26: 46234 | G26: 46234 | H26: Bora Inputs E27; Bid_Cash E34
C27: Bid submission: fee paid, bid security posted | D27: date | E27: 46325 | F27: 46325 | G27: 46325 | H27: Bora Inputs E95; Bid_Cash E35
C28: Performance security posted | D28: date | E28: 46402 | F28: 46402 | G28: 46402 | H28: Bora Deposits K10 (E96 + 17 d); Bid_Cash E36
C29: TSO security paid | D29: date | E29: 46402 | F29: 46402 | G29: 46402 | H29: Bora Inputs E97; Bid_Cash E37
C30: Connection agreement (HCSSZ): fees paid | D30: date | E30: 47027 | F30: 47027 | G30: 47027 | H30: Bora Inputs E99; Bid_Cash E39
C31: Devex average payment date | D31: date | E31: 46752 | F31: 46752 | G31: 46752 | H31: Bora Devex_FEP, amount-weighted; Bid_Cash 'continuous'
C32: Notice to proceed | D32: date | E32: 47299 | F32: 47299 | G32: 47299 | H32: Bora Inputs E154; Bid_Cash E40
C33: COD | D33: date | E33: 48029 | F33: 48029 | G33: 48029 | H33: Bora Inputs E155; Bid_Cash E41
C34: Performance security released | D34: date | E34: 48669 | F34: 48669 | G34: 48669 | H34: Bid_Cash E42 (Kiírás XII.13, estimate)
C35: DSA accrual start | D35: date | E35: 46325 | F35: 46325 | G35: 46325 | H35: Bora Inputs E70; others: signing (DSA off)
C36: RtB exit terms (all projects; value in column E)
C37: Claim rate, cash lines (incl. cash-posted securities) | D37: % | E37: 0.12 | H37: Devex file V18; SPEC §21.1
C38: Claim rate, devex | D38: % | E38: 0.2 | H38: Devex file V19
C39: Devex minimum return multiple | D39: x | E39: 2 | H39: Devex file V20
C40: Interest freeze date | D40: date | E40: 47299 | H40: Devex file V24
C41: Sale date (RtB exit) | D41: date | E41: 47391 | H41: Bora Inputs E58; SPEC §21.1
C42: Sale costs per project | D42: EUR k | E42: 250 | H42: SPEC §21.1
C43: Developer success fee (on committed MW, 30/360) | D43: EUR k/MW/yr | E43: 2.5 | H43: Bora Inputs E36
C44: Developer success fee cap | D44: EUR k/MW | E44: 10 | H44: Bora Inputs E37
C45: Corporate income tax on exit gains | D45: % | E45: 0.09 | H45: SPEC §22.2 (exit gains only)
C46: Capex (per MW of wind built unless stated; turbines: case table on the Dashboard)
C47: Turbine installation and erection | D47: EUR k/MW | E47: 80 | H47: Bora Inputs G163
C48: Foundations | D48: EUR k/MW | E48: 90 | H48: Bora Inputs G164
C49: Balance of plant – civil | D49: EUR k/MW | E49: 70 | H49: Bora Inputs G165
C50: Balance of plant – electrical | D50: EUR k/MW | E50: 60 | H50: Bora Inputs G166
C51: Owner's costs, engineering, PM, construction insurance | D51: EUR k/MW | E51: 40 | H51: Bora Inputs G169
C52: Land purchase and easements | D52: EUR k/MW | E52: 15 | H52: Bora Inputs G170
C53: On-site substation and 132 kV bay (lump sum) | D53: EUR k | E53: 12000 | H53: Bora Inputs G167
C54: Source basis of the lump sums | D54: MVA | E54: 200 | H54: Bora Inputs E305
C55: Capex contingency (not on BESS) | D55: % | E55: 0.05 | H55: Bora Inputs G173
C56: BESS capex | D56: EUR k/MWh | E56: 100 | H56: CLAUDE.md standing assumption, 15-Oct-26
C57: Generation (hours and PPA price: case table on the Dashboard)
C58: Curtailment | D58: % | E58: 0.02 | H58: Bora Inputs G183
C59: Clipping | D59: % | E59: 0.04 | H59: Bora Dash_Clip_Override (user, 26-Oct-26)
C60: Degradation | D60: % p.a. | E60: 0.003 | H60: Bora Inputs G184
C61: PPA escalation | D61: % p.a. | E61: 0.01 | H61: Bora Inputs G194
C62: Opex (COD-year prices; O&M contract: case table on the Dashboard)
C63: Balance of plant maintenance | D63: EUR k/MW/yr | E63: 3 | H63: Bora Inputs G204
C64: Land lease | D64: EUR k/MW/yr | E64: 3 | H64: Bora Inputs G205
C65: Operational insurance | D65: EUR k/MW/yr | E65: 2.5 | H65: Bora Inputs G206
C66: Asset and commercial management | D66: EUR k/MW/yr | E66: 1.5 | H66: Bora Inputs G207
C67: Property tax | D67: EUR k/MW/yr | E67: 3 | H67: Bora Inputs G208
C68: Administration, audit, compliance (at the source basis) | D68: EUR k/yr | E68: 150 | H68: Bora Inputs G209
C69: Balancing cost | D69: EUR/MWh | E69: 4 | H69: Bora Inputs G196
C70: Grid use-of-system charges | D70: EUR/MWh | E70: 1 | H70: Bora Inputs G197
C71: MEKH supervisory fee | D71: % of rev. | E71: 0.001 | H71: Bora Inputs G198
C72: HIPA local business tax | D72: % of rev. | E72: 0.02 | H72: Bora Inputs G212
C73: Opex contingency (not on community, HIPA) | D73: % | E73: 0.05 | H73: Bora Inputs G210
C74: Opex escalation | D74: % p.a. | E74: 0.025 | H74: Bora Inputs G211
C75: Valuation, timeline and constants
C76: Operating life from COD | D76: years | E76: 30 | H76: Bora Inputs G157
C77: Discount rate (buyer's pre-tax return at COD) | D77: % | E77: 0.08 | H77: Bora Inputs G226
C78: First year of the annual timeline | D78: year | E78: 2026 | H78: Year of the first signing
C79: Thousand | D79: x | E79: 1000 | H79: Constant
C80: Days in a year (act/365) | D80: days | E80: 365 | H80: Constant
C81: Months in a year | D81: months | E81: 12 | H81: Constant
C82: Check tolerance | D82: EUR k | E82: 0.001 | H82: Constant
B84: x | C84: Band tables for the points (ÖSZ, Kiírás Annex 4) – expand the group | E84: Values →
C85: Osz1_LB | E85: 10 | F85: 15 | G85: 20 | H85: 25 | I85: 30 | J85: 35 | K85: 40 | L85: 45 | M85: 50
C86: Osz1_Incl | E86: 0 | F86: 0 | G86: 0 | H86: 0 | I86: 0 | J86: 0 | K86: 0 | L86: 0 | M86: 1
C87: Osz1_Pts | E87: 0 | F87: 10 | G87: 20 | H87: 30 | I87: 40 | J87: 55 | K87: 70 | L87: 80 | M87: 90 | N87: 100
C88: Osz2_LB | E88: 2 | F88: 2.1 | G88: 2.2 | H88: 2.3 | I88: 2.4 | J88: 2.5 | K88: 2.6 | L88: 2.7 | M88: 2.8 | N88: 2.9 | O88: 3
C89: Osz2_Incl | E89: 0 | F89: 0 | G89: 0 | H89: 0 | I89: 0 | J89: 0 | K89: 0 | L89: 0 | M89: 0 | N89: 0 | O89: 1
C90: Osz2_Pts | E90: 0 | F90: 5 | G90: 10 | H90: 20 | I90: 30 | J90: 40 | K90: 50 | L90: 60 | M90: 70 | N90: 80 | O90: 90 | P90: 100
C91: Osz3_LB | E91: 0.02 | F91: 0.05 | G91: 0.1 | H91: 0.15 | I91: 0.2 | J91: 0.25 | K91: 0.3 | L91: 0.35 | M91: 0.4 | N91: 0.5
C92: Osz3_Incl | E92: 0 | F92: 1 | G92: 1 | H92: 1 | I92: 1 | J92: 1 | K92: 1 | L92: 1 | M92: 1 | N92: 0
C93: Osz3_Pts | E93: 0 | F93: 10 | G93: 20 | H93: 30 | I93: 40 | J93: 50 | K93: 60 | L93: 70 | M93: 80 | N93: 90 | O93: 100
C94: Osz6_LB | E94: 1 | F94: 1.2 | G94: 1.3 | H94: 1.4 | I94: 1.5 | J94: 1.6 | K94: 1.7 | L94: 1.8 | M94: 1.9 | N94: 2
C95: Osz6_Incl | E95: 0 | F95: 1 | G95: 1 | H95: 1 | I95: 1 | J95: 1 | K95: 1 | L95: 1 | M95: 1 | N95: 1
C96: Osz6_Pts | E96: 0 | F96: 10 | G96: 20 | H96: 30 | I96: 40 | J96: 50 | K96: 60 | L96: 70 | M96: 80 | N96: 90 | O96: 100
C97: Osz5_Pts | E97: 100
C98: Osz7_Pts | E98: 100
C99: Osz8_Pts | E99: 100
C100: Osz9a_Pts | E100: 80
C101: Osz9b_Pts | E101: 20
C102: Osz1_W | E102: 0.2
C103: Osz2_W | E103: 0.15
...
