Workbook
Name Balancing: Inputs!$E$64
Name Bench_BESS: Inputs!$E$8
Name Bench_Wind: Inputs!$E$7
Name BESS_Capex: Inputs!$E$51
Name Bid_Sec_Rate: Inputs!$E$9
Name Capex_Civil: Inputs!$E$44
Name Capex_Cont: Inputs!$E$50
Name Capex_Elec: Inputs!$E$45
Name Capex_Fdn: Inputs!$E$43
Name Capex_Install: Inputs!$E$42
Name Capex_Land: Inputs!$E$47
Name Capex_Owner: Inputs!$E$46
Name Case_CN: Dashboard!$H$27
Name Case_EU: Dashboard!$H$26
Name Case_OM: Dashboard!$H$30
Name Case_P50: Dashboard!$H$29
Name Case_PPA: Dashboard!$H$28
Name CIT_Rate: Inputs!$E$39
Name Clipping: Inputs!$E$54
Name Curtailment: Inputs!$E$53
Name Dash_BESS_Share: Dashboard!$E$8:$G$8
Name Dash_Brownfield: Dashboard!$E$15:$G$15
Name Dash_Case: Dashboard!$H$25
Name Dash_Case_CN: Dashboard!$E$27:$G$27
Name Dash_Case_EU: Dashboard!$E$26:$G$26
Name Dash_Case_OM: Dashboard!$E$30:$G$30
Name Dash_Case_P50: Dashboard!$E$29:$G$29
Name Dash_Case_PPA: Dashboard!$E$28:$G$28
Name Dash_Community: Dashboard!$E$12:$G$12
Name Dash_DSA: Dashboard!$E$20:$G$20
Name Dash_FEP_Share: Dashboard!$E$19:$G$19
Name Dash_Hours: Dashboard!$E$9:$G$9
Name Dash_JV: Dashboard!$E$21:$G$21
Name Dash_Municipal: Dashboard!$E$11:$G$11
Name Dash_MVA: Dashboard!$E$6:$G$6
Name Dash_Overbuild: Dashboard!$E$7:$G$7
Name Dash_P50: Dashboard!$E$22:$G$22
Name Dash_Partial: Dashboard!$E$13:$G$13
Name Dash_PB_Mult: Dashboard!$E$14:$G$14
Name Dash_Premium: Dashboard!$E$18:$G$18
Name Dash_Shared: Dashboard!$E$16:$G$16
Name Dash_Shortfall: Dashboard!$E$10:$G$10
Name Dash_Turbine: Dashboard!$E$17:$G$17
Name Days_In_Year: Inputs!$E$75
Name Degradation: Inputs!$E$55
Name Devex_Class: Inputs!$G$80:$G$112
Name Devex_Date: Inputs!$F$80:$F$112
Name Devex_Floor: Inputs!$E$32
Name Devex_HUF: Inputs!$E$80:$E$112
Name Discount_Rate: Inputs!$E$72
Name DSA_Cap: Inputs!$E$38
Name DSA_Rate: Inputs!$E$37
Name First_Year: Inputs!$E$73
Name Freeze_Date: Inputs!$E$33
Name FX: Inputs!$E$6
Name Grid_Charges: Inputs!$E$65
Name HIPA_Rate: Inputs!$E$67
Name Life: Inputs!$E$71
Name Lump_Basis: Inputs!$E$49
Name Master_Check: Dashboard!$H$442

Sheet Dashboard
C2: HU wind projects
C3: Master check (0 = OK; checks at the end of the detail) | D3: flag | H3: =Master_Check -> 0
B5: x | C5: Key inputs: the bids | E5: Bora | F5: Iváncsa | G5: Dunaújváros | H5: Total
C6: Net connection capacity | D6: MVA | E6: 50 | F6: 50 | G6: 50 | H6: =SUM(E6:G6) -> 150
C7: Overbuild (ÖSZ-3) | D7: % | E7: 0.2 | F7: 0.4 | G7: 0.4
C8: BESS power, share of MVA (ÖSZ-4) | D8: % | E8: 0.1 | F8: 0.2 | G8: 0.2
C9: BESS duration | D9: h | E9: 4 | F9: 4 | G9: 4
C10: Wind built below the bid | D10: % | E10: 0.1 | F10: 0.1 | G10: 0.1
C11: Municipal one-off (ÖSZ-1), at COD | D11: EUR k/MVA | E11: 20 | F11: 50 | G11: 50
C12: Community contribution (ÖSZ-2) | D12: EUR/MWh | E12: 0 | F12: 3 | G12: 3
C13: Partial award accepted (ÖSZ-5) | D13: flag | E13: 1 | F13: 1 | G13: 1
C14: Performance security multiple (ÖSZ-6) | D14: x | E14: 1 | F14: 1 | G14: 1
C15: Brownfield site (ÖSZ-7) | D15: flag | E15: 0 | F15: 0 | G15: 0
C16: Shared connection (ÖSZ-8) | D16: flag | E16: 1 | F16: 1 | G16: 1
C17: Turbine route (EU or CN; EU scores ÖSZ-9) | D17: text | E17: CN | F17: CN | G17: CN
C18: RtB premium | D18: EUR k/MVA | E18: 150 | F18: 150 | G18: 150
C19: FEP share of distributable proceeds | D19: % | E19: 0.7 | F19: 1 | G19: 1
C20: Developer success fee (DSA) on | D20: flag | E20: 1 | F20: 0 | G20: 0
C21: JV with a developer (1 = yes; claims and DSA apply) | D21: flag | E21: 1 | F21: 0 | G21: 0
C22: Net P50 hours (project wind study) | D22: h/yr | E22: 2500 | F22: 2500 | G22: 2500
B24: x | C24: Case: turbine price, PPA, yield, O&M | E24: Base | F24: Low | G24: High | H24: Live
C25: Case selected (Base, Low or High) | D25: case | H25: Base
C26: Turbine supply incl. transport, EU route | D26: EUR k/MW | E26: 850 | F26: 950 | G26: 800 | H26: =INDEX(E26:G26,MATCH(Dash_Case,$E$24:$G$24,0)) -> 850 | J26: Bora Dashboard H8 / Inputs G162
C27: Turbine supply incl. transport, CN route | D27: EUR k/MW | E27: 500 | F27: 600 | G27: 480 | H27: =INDEX(E27:G27,MATCH(Dash_Case,$E$24:$G$24,0)) -> 500 | J27: Bora Inputs H162
C28: PPA price in the COD year | D28: EUR/MWh | E28: 90 | F28: 90 | G28: 100 | H28: =INDEX(E28:G28,MATCH(Dash_Case,$E$24:$G$24,0)) -> 90 | J28: Bora Dashboard H9
C29: Net P50 hours (not used: project P50 in row 22) | D29: h/yr | E29: 2400 | F29: 2350 | G29: 2500 | H29: =INDEX(E29:G29,MATCH(Dash_Case,$E$24:$G$24,0)) -> 2400 | J29: Bora Dashboard H10
C30: O&M full-service contract | D30: EUR k/MW/yr | E30: 12 | F30: 12 | G30: 10 | H30: =INDEX(E30:G30,MATCH(Dash_Case,$E$24:$G$24,0)) -> 12 | J30: Bora Dashboard H11
B32: x | C32: Bid points and capacity | E32: Bora | F32: Iváncsa | G32: Dunaújváros | H32: Total
C33: Points – municipal one-off | D33: points | E33: =INDEX(Osz1_Pts,1+SUMPRODUCT((Osz1_LB<E11)+(Osz1_LB=E11)*Osz1_Incl))*Osz1_W -> 4 | F33: =INDEX(Osz1_Pts,1+SUMPRODUCT((Osz1_LB<F11)+(Osz1_LB=F11)*Osz1_Incl))*Osz1_W -> 20 | G33: =INDEX(Osz1_Pts,1+SUMPRODUCT((Osz1_LB<G11)+(Osz1_LB=G11)*Osz1_Incl))*Osz1_W -> 20
C34: Points – community contribution | D34: points | E34: =INDEX(Osz2_Pts,1+SUMPRODUCT((Osz2_LB<E12)+(Osz2_LB=E12)*Osz2_Incl))*Osz2_W -> 0 | F34: =INDEX(Osz2_Pts,1+SUMPRODUCT((Osz2_LB<F12)+(Osz2_LB=F12)*Osz2_Incl))*Osz2_W -> 15 | G34: =INDEX(Osz2_Pts,1+SUMPRODUCT((Osz2_LB<G12)+(Osz2_LB=G12)*Osz2_Incl))*Osz2_W -> 15
C35: Points – overbuild | D35: points | E35: =INDEX(Osz3_Pts,1+SUMPRODUCT((Osz3_LB<E7)+(Osz3_LB=E7)*Osz3_Incl))*Osz3_W -> 5 | F35: =INDEX(Osz3_Pts,1+SUMPRODUCT((Osz3_LB<F7)+(Osz3_LB=F7)*Osz3_Incl))*Osz3_W -> 9 | G35: =INDEX(Osz3_Pts,1+SUMPRODUCT((Osz3_LB<G7)+(Osz3_LB=G7)*Osz3_Incl))*Osz3_W -> 9
C36: Points – BESS | D36: points | E36: {=INDEX(Osz4_Pts,1+SUMPRODUCT((Osz4_LB<E8)+(Osz4_LB=E8)*Osz4_Incl))*Osz4_W} -> 4.5 | F36: {=INDEX(Osz4_Pts,1+SUMPRODUCT((Osz4_LB<F8)+(Osz4_LB=F8)*Osz4_Incl))*Osz4_W} -> 7.5 | G36: {=INDEX(Osz4_Pts,1+SUMPRODUCT((Osz4_LB<G8)+(Osz4_LB=G8)*Osz4_Incl))*Osz4_W} -> 7.5
C37: Points – partial award | D37: points | E37: =E13*Osz5_Pts*Osz5_W -> 5 | F37: =F13*Osz5_Pts*Osz5_W -> 5 | G37: =G13*Osz5_Pts*Osz5_W -> 5
C38: Points – performance security | D38: points | E38: =INDEX(Osz6_Pts,1+SUMPRODUCT((Osz6_LB<E14)+(Osz6_LB=E14)*Osz6_Incl))*Osz6_W -> 0 | F38: =INDEX(Osz6_Pts,1+SUMPRODUCT((Osz6_LB<F14)+(Osz6_LB=F14)*Osz6_Incl))*Osz6_W -> 0 | G38: =INDEX(Osz6_Pts,1+SUMPRODUCT((Osz6_LB<G14)+(Osz6_LB=G14)*Osz6_Incl))*Osz6_W -> 0
C39: Points – brownfield | D39: points | E39: =E15*Osz7_Pts*Osz7_W -> 0 | F39: =F15*Osz7_Pts*Osz7_W -> 0 | G39: =G15*Osz7_Pts*Osz7_W -> 0
C40: Points – shared connection | D40: points | E40: =E16*Osz8_Pts*Osz8_W -> 5 | F40: =F16*Osz8_Pts*Osz8_W -> 5 | G40: =G16*Osz8_Pts*Osz8_W -> 5
C41: Points – EU turbines | D41: points | E41: =N(E17="EU")*Osz9a_Pts*Osz9_W -> 0 | F41: =N(F17="EU")*Osz9a_Pts*Osz9_W -> 0 | G41: =N(G17="EU")*Osz9a_Pts*Osz9_W -> 0
C42: Points – EU transformers | D42: points | E42: =Inputs!E$19*Osz9b_Pts*Osz9_W -> 0 | F42: =Inputs!F$19*Osz9b_Pts*Osz9_W -> 0 | G42: =Inputs!G$19*Osz9b_Pts*Osz9_W -> 0
C43: Points total | D43: points | E43: =SUM(E33:E42) -> 23.5 | F43: =SUM(F33:F42) -> 61.5 | G43: =SUM(G33:G42) -> 61.5
C44: Wind committed in the bid | D44: MW | E44: =E6*(1+E7) -> 60 | F44: =F6*(1+F7) -> 70 | G44: =G6*(1+G7) -> 70 | H44: =SUM(E44:G44) -> 200
C45: BESS energy | D45: MWh | E45: =E6*E8*E9 -> 20 | F45: =F6*F8*F9 -> 40 | G45: =G6*G8*G9 -> 40 | H45: =SUM(E45:G45) -> 100
C46: Wind built (committed less the build shortfall) | D46: MW | E46: =E44*(1-E10) -> 54 | F46: =F44*(1-F10) -> 63 | G46: =G44*(1-G10) -> 63 | H46: =SUM(E46:G46) -> 180
B48: x | C48: Guarantees, securities and connection fees, DEVEX (HUF) | E48: Bora | F48: Iváncsa | G48: Dunaújváros | H48: Total | J48: Date
C49: Participation fee | D49: HUF | E49: =Part_Fee -> 3000000 | F49: =Part_Fee -> 3000000 | G49: =Part_Fee -> 3000000 | H49: =SUM(E49:G49) -> 9000000 | J49: =Inputs!E$21 -> 46325
C50: Bid security | D50: HUF | E50: =Bid_Sec_Rate*(E44*Bench_Wind+E45*Bench_BESS) -> 141800000 | F50: =Bid_Sec_Rate*(F44*Bench_Wind+F45*Bench_BESS) -> 182100000 | G50: =Bid_Sec_Rate*(G44*Bench_Wind+G45*Bench_BESS) -> 182100000 | H50: =SUM(E50:G50) -> 506000000 | J50: =Inputs!E$21 -> 46325
C51: Performance security payable (bid security deducted) | D51: HUF | E51: =PB_Rate*E14*(E44*Bench_Wind+E45*Bench_BESS)-E50 -> 567200000 | F51: =PB_Rate*F14*(F44*Bench_Wind+F45*Bench_BESS)-F50 -> 728400000 | G51: =PB_Rate*G14*(G44*Bench_Wind+G45*Bench_BESS)-G50 -> 728400000 | H51: =SUM(E51:G51) -> 2024000000 | J51: =Inputs!E$22 -> 46402
C52: TSO connection-request security | D52: HUF | E52: =TSO_Rate*E6 -> 225000000 | F52: =TSO_Rate*F6 -> 225000000 | G52: =TSO_Rate*G6 -> 225000000 | H52: =SUM(E52:G52) -> 675000000 | J52: =Inputs!E$23 -> 46402
C53: Direct connection fee (per point ÷ bids sharing it) | D53: HUF | E53: =Inputs!E$15/Inputs!E$16 -> 254172902 | F53: =Inputs!F$15/Inputs!F$16 -> 460000000 | G53: =Inputs!G$15/Inputs!G$16 -> 460000000 | H53: =SUM(E53:G53) -> 1174172902 | J53: =Inputs!E$24 -> 47027
C54: Indirect connection fee, payable (TSO security deducted) | D54: HUF | E54: =Inputs!E$14*E6-E52 -> 3428565300 | F54: =Inputs!F$14*F6-F52 -> 766334000 | G54: =Inputs!G$14*G6-G52 -> 766334000 | H54: =SUM(E54:G54) -> 4961233300 | J54: =Inputs!E$24 -> 47027
C55: DEVEX – development (devex items excl. land) | D55: HUF | E55: =SUMIF(Devex_Class,"Devex",Devex_HUF)*Inputs!E$18 -> 2.5590107e+08 | F55: =SUMIF(Devex_Class,"Devex",Devex_HUF)*Inputs!F$18 -> 2.5590107e+08 | G55: =SUMIF(Devex_Class,"Devex",Devex_HUF)*Inputs!G$18 -> 2.5590107e+08 | H55: =SUM(E55:G55) -> 7.677032e+08 | J55: =SUMPRODUCT((Devex_Class="Devex")*Devex_HUF,Devex_Date)/SUMIF(Devex_Class,"Devex",Devex_HUF) -> 46714.124
C56: DEVEX – land (reservation and purchase) | D56: HUF | E56: =SUMIF(Devex_Class,"Land",Devex_HUF)*Inputs!E$18 -> 39347625 | F56: =SUMIF(Devex_Class,"Land",Devex_HUF)*Inputs!F$18 -> 39347625 | G56: =SUMIF(Devex_Class,"Land",Devex_HUF)*Inputs!G$18 -> 39347625 | H56: =SUM(E56:G56) -> 118042875 | J56: =SUMPRODUCT((Devex_Class="Land")*Devex_HUF,Devex_Date)/SUMIF(Devex_Class,"Land",Devex_HUF) -> 46877.177
C57: Signing fee and DD | D57: HUF | E57: =Inputs!E$17*FX*Thousand -> 36500000 | F57: =Inputs!F$17*FX*Thousand -> 54750000 | G57: =Inputs!G$17*FX*Thousand -> 54750000 | H57: =SUM(E57:G57) -> 146000000 | J57: =Inputs!E$20 -> 46234
C58: Total cash to RtB (incl. signing and DD) | D58: HUF | E58: =SUM(E49:E57) -> 4.9514869e+09 | F58: =SUM(F49:F57) -> 2.7148327e+09 | G58: =SUM(G49:G57) -> 2.7148327e+09 | H58: =SUM(E58:G58) -> 1.0381152e+10
B60: x | C60: Guarantees, securities and connection fees, DEVEX (EUR k) | E60: Bora | F60: Iváncsa | G60: Dunaújváros | H60: Total | J60: Date
C61: Participation fee | D61: EUR k | E61: =E49/FX/Thousand -> 8.2191781 | F61: =F49/FX/Thousand -> 8.2191781 | G61: =G49/FX/Thousand -> 8.2191781 | H61: =SUM(E61:G61) -> 24.657534 | J61: =Inputs!E$21 -> 46325
C62: Bid security | D62: EUR k | E62: =E50/FX/Thousand -> 388.49315 | F62: =F50/FX/Thousand -> 498.90411 | G62: =G50/FX/Thousand -> 498.90411 | H62: =SUM(E62:G62) -> 1386.3014 | J62: =Inputs!E$21 -> 46325
C63: Performance security payable (bid security deducted) | D63: EUR k | E63: =E51/FX/Thousand -> 1553.9726 | F63: =F51/FX/Thousand -> 1995.6164 | G63: =G51/FX/Thousand -> 1995.6164 | H63: =SUM(E63:G63) -> 5545.2055 | J63: =Inputs!E$22 -> 46402
C64: TSO connection-request security | D64: EUR k | E64: =E52/FX/Thousand -> 616.43836 | F64: =F52/FX/Thousand -> 616.43836 | G64: =G52/FX/Thousand -> 616.43836 | H64: =SUM(E64:G64) -> 1849.3151 | J64: =Inputs!E$23 -> 46402
C65: Direct connection fee (per point ÷ bids sharing it) | D65: EUR k | E65: =E53/FX/Thousand -> 696.36412 | F65: =F53/FX/Thousand -> 1260.274 | G65: =G53/FX/Thousand -> 1260.274 | H65: =SUM(E65:G65) -> 3216.9121 | J65: =Inputs!E$24 -> 47027
C66: Indirect connection fee, payable (TSO security deducted) | D66: EUR k | E66: =E54/FX/Thousand -> 9393.3296 | F66: =F54/FX/Thousand -> 2099.5452 | G66: =G54/FX/Thousand -> 2099.5452 | H66: =SUM(E66:G66) -> 13592.42 | J66: =Inputs!E$24 -> 47027
C67: DEVEX – development (devex items excl. land) | D67: EUR k | E67: =E55/FX/Thousand -> 701.09882 | F67: =F55/FX/Thousand -> 701.09882 | G67: =G55/FX/Thousand -> 701.09882 | H67: =SUM(E67:G67) -> 2103.2964 | J67: =J55 -> 46714.124
C68: DEVEX – land (reservation and purchase) | D68: EUR k | E68: =E56/FX/Thousand -> 107.80171 | F68: =F56/FX/Thousand -> 107.80171 | G68: =G56/FX/Thousand -> 107.80171 | H68: =SUM(E68:G68) -> 323.40514 | J68: =J56 -> 46877.177
C69: Signing fee and DD | D69: EUR k | E69: =E57/FX/Thousand -> 100 | F69: =F57/FX/Thousand -> 150 | G69: =G57/FX/Thousand -> 150 | H69: =SUM(E69:G69) -> 400 | J69: =Inputs!E$20 -> 46234
C70: Total cash to RtB (incl. signing and DD) | D70: EUR k | E70: =SUM(E61:E69) -> 13565.718 | F70: =SUM(F61:F69) -> 7437.8978 | G70: =SUM(G61:G69) -> 7437.8978 | H70: =SUM(E70:G70) -> 28441.513
B72: x | C72: Cash to RtB by nature: sunk, returned, or borne by the buyer (EUR k) | E72: Bora | F72: Iváncsa | G72: Dunaújváros | H72: Total | J72: Who bears it
C73: Sunk fees and devex (signing and DD, participation fee, land, development devex) | D73: EUR k | E73: =E61+SUM(E67:E69) -> 917.11971 | F73: =F61+SUM(F67:F69) -> 967.11971 | G73: =G61+SUM(G67:G69) -> 967.11971 | H73: =SUM(E73:G73) -> 2851.3591 | J73: FEP – sunk; recovered only via the claims at the sale
C74: Securities, returned (bid, performance, TSO connection request) | D74: EUR k | E74: =SUM(E62:E64) -> 2558.9041 | F74: =SUM(F62:F64) -> 3110.9589 | G74: =SUM(G62:G64) -> 3110.9589 | H74: =SUM(E74:G74) -> 8780.8219 | J74: FEP – cash out, returned or reimbursed at the sale
C75: Grid connection fees (direct + indirect, payable at HCSSZ) | D75: EUR k | E75: =E65+E66 -> 10089.694 | F75: =F65+F66 -> 3359.8192 | G75: =G65+G66 -> 3359.8192 | H75: =SUM(E75:G75) -> 16809.332 | J75: Buyer at RtB; FEP pays only if no buyer is found
C76: Total cash to RtB (= total above) | D76: EUR k | E76: =SUM(E73:E75) -> 13565.718 | F76: =SUM(F73:F75) -> 7437.8978 | G76: =SUM(G73:G75) -> 7437.8978 | H76: =SUM(E76:G76) -> 28441.513 | J76: Case A: FEP pre-funds everything
C77: Grid connection fees, share of the total | D77: % | E77: =E75/E76 -> 0.7437641 | F77: =F75/F76 -> 0.45171623 | G77: =G75/G76 -> 0.45171623 | H77: =H75/H76 -> 0.59101399
C78: FEP exposure if the buyer pays the grid connection fees | D78: EUR k | E78: =E76-E75 -> 3476.0238 | F78: =F76-F75 -> 4078.0786 | G78: =G76-G75 -> 4078.0786 | H78: =SUM(E78:G78) -> 11632.181 | J78: Case B: FEP funds sunk fees, devex and securities only
B80: x | C80: Capex breakdown to COD | E80: Bora | F80: Iváncsa | G80: Dunaújváros | H80: Total
C81: Turbines (route price, live case) | D81: EUR k | E81: =IF(E17="EU",Case_EU,Case_CN)*E46 -> 27000 | F81: =IF(F17="EU",Case_EU,Case_CN)*F46 -> 31500 | G81: =IF(G17="EU",Case_EU,Case_CN)*G46 -> 31500 | H81: =SUM(E81:G81) -> 90000
C82: Installation and erection | D82: EUR k | E82: =Capex_Install*E46 -> 4320 | F82: =Capex_Install*F46 -> 5040 | G82: =Capex_Install*G46 -> 5040 | H82: =SUM(E82:G82) -> 14400
C83: Foundations | D83: EUR k | E83: =Capex_Fdn*E46 -> 4860 | F83: =Capex_Fdn*F46 -> 5670 | G83: =Capex_Fdn*G46 -> 5670 | H83: =SUM(E83:G83) -> 16200
C84: Balance of plant – civil | D84: EUR k | E84: =Capex_Civil*E46 -> 3780 | F84: =Capex_Civil*F46 -> 4410 | G84: =Capex_Civil*G46 -> 4410 | H84: =SUM(E84:G84) -> 12600
C85: Balance of plant – electrical | D85: EUR k | E85: =Capex_Elec*E46 -> 3240 | F85: =Capex_Elec*F46 -> 3780 | G85: =Capex_Elec*G46 -> 3780 | H85: =SUM(E85:G85) -> 10800
C86: Owner's costs, engineering, PM, construction insurance | D86: EUR k | E86: =Capex_Owner*E46 -> 2160 | F86: =Capex_Owner*F46 -> 2520 | G86: =Capex_Owner*G46 -> 2520 | H86: =SUM(E86:G86) -> 7200
C87: Land purchase and easements | D87: EUR k | E87: =Capex_Land*E46 -> 0 | F87: =Capex_Land*F46 -> 0 | G87: =Capex_Land*G46 -> 0 | H87: =SUM(E87:G87) -> 0
C88: Substation and 132 kV bay (scaled by MVA) | D88: EUR k | E88: =Subs_Lump*E6/Lump_Basis -> 3000 | F88: =Subs_Lump*F6/Lump_Basis -> 3000 | G88: =Subs_Lump*G6/Lump_Basis -> 3000 | H88: =SUM(E88:G88) -> 9000
C89: Contingency (not on BESS) | D89: EUR k | E89: =SUM(E81:E88)*Capex_Cont -> 2418 | F89: =SUM(F81:F88)*Capex_Cont -> 2796 | G89: =SUM(G81:G88)*Capex_Cont -> 2796 | H89: =SUM(E89:G89) -> 8010
C90: BESS (on BESS energy) | D90: EUR k | E90: =BESS_Capex*E45 -> 2000 | F90: =BESS_Capex*F45 -> 4000 | G90: =BESS_Capex*G45 -> 4000 | H90: =SUM(E90:G90) -> 10000
C91: Construction capex | D91: EUR k | E91: =SUM(E81:E90) -> 52778 | F91: =SUM(F81:F90) -> 62716 | G91: =SUM(G81:G90) -> 62716 | H91: =SUM(E91:G91) -> 178210
C92: Connection fees (TSO security, direct, indirect) | D92: EUR k | E92: =E64+E65+E66 -> 10706.132 | F92: =F64+F65+F66 -> 3976.2575 | G92: =G64+G65+G66 -> 3976.2575 | H92: =SUM(E92:G92) -> 18658.647
C93: TSO connection-request security (returned) | D93: EUR k | E93: =0 -> 0 | F93: =0 -> 0 | G93: =0 -> 0 | H93: =SUM(E93:G93) -> 0
C94: Bid security (returned) | D94: EUR k | E94: =0 -> 0 | F94: =0 -> 0 | G94: =0 -> 0 | H94: =SUM(E94:G94) -> 0
C95: Performance security: 0 (returned) | D95: EUR k | E95: =0 -> 0 | F95: =0 -> 0 | G95: =0 -> 0 | H95: =SUM(E95:G95) -> 0
C96: Municipal one-off | D96: EUR k | E96: =E11*E6 -> 1000 | F96: =F11*F6 -> 2500 | G96: =G11*G6 -> 2500 | H96: =SUM(E96:G96) -> 6000
C97: Land | D97: EUR k | E97: =E68 -> 107.80171 | F97: =F68 -> 107.80171 | G97: =G68 -> 107.80171 | H97: =SUM(E97:G97) -> 323.40514
C98: Developer premium paid for the RtB project (150 k€/MVA × MVA; replaces FEP's devex, which the buyer does not bear) | D98: EUR k | E98: =E18*E6 -> 7500 | F98: =F18*F6 -> 7500 | G98: =G18*G6 -> 7500 | H98: =SUM(E98:G98) -> 22500
C99: All-in cost to COD for a buyer (securities excluded: returned) | D99: EUR k | E99: =E91+SUM(E92:E98) -> 72091.934 | F99: =F91+SUM(F92:F98) -> 76800.059 | G99: =G91+SUM(G92:G98) -> 76800.059 | H99: =SUM(E99:G99) -> 225692.05
C100: All-in cost per MW built | D100: EUR k/MW | E100: =E99/E46 -> 1335.0358 | F100: =F99/F46 -> 1219.0486 | G100: =G99/G46 -> 1219.0486 | H100: =H99/H46 -> 1253.8447
C101: All-in cost per MVA | D101: EUR k/MVA | E101: =E99/E6 -> 1441.8387 | F101: =F99/F6 -> 1536.0012 | G101: =G99/G6 -> 1536.0012 | H101: =H99/H6 -> 1504.6137
B103: x | C103: Devex breakdown (BORA_Devex 02-Oct-26 items × the scale; tender fee and securities above) | E103: Bora | F103: Iváncsa | G103: Dunaújváros | H103: Total
C104: Land | D104: EUR k | E104: =E68 -> 107.80171 | F104: =F68 -> 107.80171 | G104: =G68 -> 107.80171 | H104: =SUM(E104:G104) -> 323.40514
C105: Development devex (incl. contingency) | D105: EUR k | E105: =E67 -> 701.09882 | F105: =F67 -> 701.09882 | G105: =G67 -> 701.09882 | H105: =SUM(E105:G105) -> 2103.2964
C106: Devex total (= DEVEX lines above; devex items × scale) | D106: EUR k | E106: =SUM(E104:E105) -> 808.90053 | F106: =SUM(F104:F105) -> 808.90053 | G106: =SUM(G104:G105) -> 808.90053 | H106: =SUM(E106:G106) -> 2426.7016
B108: x | C108: Returns RTB COD HTM | E108: Bora | F108: Iváncsa | G108: Dunaújváros | H108: Total
C109: RTB exit, Case A: buyer pays the grid connection fees (FEP does not pre-fund)
C110: Grid connection fees paid by the buyer (not FEP cash) | D110: EUR k | E110: =E202 -> 10089.694 | F110: =F202 -> 3359.8192 | G110: =G202 -> 3359.8192 | H110: =SUM(E110:G110) -> 16809.332
...

Sheet Inputs
C2: HU wind bids – other inputs (blue) with sources
B4: x | C4: Inputs | E4: Bora | F4: Iváncsa | G4: Dunaújváros | H4: Source
C5: Tender and grid (all projects; value in column E)
C6: FX rate | D6: HUF/EUR | E6: 365 | H6: Bora Inputs E11; Bid_Cash E45
C7: Security base: benchmark investment, wind | D7: HUF/MW | E7: 406000000 | H7: Bora Inputs E75; Bid_Cash E46
C8: Security base: benchmark investment, BESS | D8: HUF/MWh | E8: 200000000 | H8: Bora Inputs E89; Bid_Cash E47
C9: Bid security, share of base | D9: % | E9: 0.005 | H9: Bora Inputs E76; Bid_Cash E49
C10: Performance security, minimum share of base | D10: % | E10: 0.025 | H10: Bora Inputs E77; Bid_Cash E50
C11: Participation fee per bid | D11: HUF | E11: 3000000 | H11: Bora Inputs E81; Bid_Cash E48
C12: TSO connection-request security | D12: HUF/MVA | E12: 4500000 | H12: Bora Inputs E83; Bid_Cash E51
C13: Per project: fees, devex, dates
C14: Indirect connection fee | D14: HUF/MVA | E14: 73071306 | F14: 19826680 | G14: 19826680 | H14: Bora Inputs G290; Bid_Cash E52
C15: Direct connection fee per connection point | D15: HUF | E15: 508345804 | F15: 460000000 | G15: 460000000 | H15: Bora Inputs G291; Bid_Cash E53
C16: Bids sharing the connection point | D16: count | E16: 2 | F16: 1 | G16: 1 | H16: Bora: 2 bids per point (SPEC §22.2)
C17: Signing fee and DD | D17: EUR k | E17: 100 | F17: 150 | G17: 150 | H17: Bora E24+E25: 400 × 50/200; Bid_Cash E55
C18: Devex scale (bid MVA ÷ 200 MVA of the devex file) | D18: x | E18: 0.25 | F18: 0.25 | G18: 0.25 | H18: SPEC §26.2: 50/200; 1 = the full devex file
C19: EU transformers ≥ 80 % (ÖSZ-9) | D19: flag | E19: 0 | F19: 0 | G19: 0 | H19: Bid_Cash E16; SPEC §23.1
C20: Signing fee and DD paid | D20: date | E20: 46234 | F20: 46234 | G20: 46234 | H20: Bora Inputs E27; Bid_Cash E34
C21: Bid submission: fee paid, bid security posted | D21: date | E21: 46325 | F21: 46325 | G21: 46325 | H21: Bora Inputs E95; Bid_Cash E35
C22: Performance security posted | D22: date | E22: 46402 | F22: 46402 | G22: 46402 | H22: Bora Deposits K10 (E96 + 17 d); Bid_Cash E36
C23: TSO security paid | D23: date | E23: 46402 | F23: 46402 | G23: 46402 | H23: Bora Inputs E97; Bid_Cash E37
C24: Connection agreement (HCSSZ): fees paid | D24: date | E24: 47027 | F24: 47027 | G24: 47027 | H24: Bora Inputs E99; Bid_Cash E39
C25: Notice to proceed | D25: date | E25: 47299 | F25: 47299 | G25: 47299 | H25: Bora Inputs E154; Bid_Cash E40
... C28: DSA accrual start | D28: date | E28: 46325 | F28: 46325 | G28: 46325 | H28: Bora Inputs E70; others: signing (DSA off)
C29: RtB exit terms (all projects; value in column E)
C30: Claim rate, cash lines (incl. cash-posted securities) | D30: % | E30: 0.12 | H30: Devex file V18; SPEC §21.1
C31: Claim rate, devex | D31: % | E31: 0.2 | H31: Devex file V19
C32: Devex minimum return multiple | D32: x | E32: 2 | H32: Devex file V20
C33: Interest freeze date | D33: date | E33: 47299 | H33: Devex file V24
C34: Sale date, Case B (RtB exit after HCSSZ) | D34: date | E34: 47391 | H34: Bora Inputs E58; SPEC §21.1
C35: Sale date, Case A (before HCSSZ) | D35: date | E35: 47026 | H35: SPEC §25.2 (user, 28-Oct-2026)
C36: Sale costs per project | D36: EUR k | E36: 250 | H36: SPEC §21.1
C37: Developer success fee (on committed MW, 30/360) | D37: EUR k/MW/yr | E37: 2.5 | H37: Bora Inputs E36
C38: Developer success fee cap | D38: EUR k/MW | E38: 10 | H38: Bora Inputs E37
C39: Corporate income tax on exit gains | D39: % | E39: 0.15 | H39: SPEC §22.2 (exit gains only)
C40: Share deal, participation exemption on the share gain (1 = on); claims taxed as interest | D40: flag | E40: 1
C41: Capex (per MW of wind built unless stated; turbines: case table on the Dashboard)
C42: Turbine installation and erection | D42: EUR k/MW | E42: 80 | H42: Bora Inputs G163
C43: Foundations | D43: EUR k/MW | E43: 90 | H43: Bora Inputs G164
C44: Balance of plant – civil | D44: EUR k/MW | E44: 70 | H44: Bora Inputs G165
C45: Balance of plant – electrical | D45: EUR k/MW | E45: 60 | H45: Bora Inputs G166
C46: Owner's costs, engineering, PM, construction insurance | D46: EUR k/MW | E46: 40 | H46: Bora Inputs G169
C47: Land purchase and easements | D47: EUR k/MW | E47: 0 | H47: Land is in the devex (Inputs rows 80, 81, 110) and bought by the buyer at cost; 0 so it is not counted twice (v3)
C48: On-site substation and 132 kV bay (lump sum) | D48: EUR k | E48: 12000 | H48: Bora Inputs G167
C49: Source basis of the lump sums | D49: MVA | E49: 200 | H49: Bora Inputs E305
C50: Capex contingency (not on BESS) | D50: % | E50: 0.05 | H50: Bora Inputs G173
C51: BESS capex | D51: EUR k/MWh | E51: 100 | H51: CLAUDE.md standing assumption, 15-Oct-26
C52: Generation (hours and PPA price: case table on the Dashboard)
C53: Curtailment | D53: % | E53: 0.02 | H53: Bora Inputs G183
C54: Clipping | D54: % | E54: 0.04 | H54: Bora Dash_Clip_Override (user, 26-Oct-26)
C55: Degradation | D55: % p.a. | E55: 0.003 | H55: Bora Inputs G184
C56: PPA escalation | D56: % p.a. | E56: 0.01 | H56: Bora Inputs G194
C57: Opex (COD-year prices; O&M contract: case table on the Dashboard)
C58: Balance of plant maintenance | D58: EUR k/MW/yr | E58: 3 | H58: Bora Inputs G204
C59: Land lease | D59: EUR k/MW/yr | E59: 3 | H59: Bora Inputs G205
C60: Operational insurance | D60: EUR k/MW/yr | E60: 2.5 | H60: Bora Inputs G206
C61: Asset and commercial management | D61: EUR k/MW/yr | E61: 1.5 | H61: Bora Inputs G207
C62: Property tax | D62: EUR k/MW/yr | E62: 3 | H62: Bora Inputs G208
C63: Administration, audit, compliance (at the source basis) | D63: EUR k/yr | E63: 150 | H63: Bora Inputs G209
C64: Balancing cost | D64: EUR/MWh | E64: 4 | H64: Bora Inputs G196
C65: Grid use-of-system charges | D65: EUR/MWh | E65: 1 | H65: Bora Inputs G197
C66: MEKH supervisory fee | D66: % of rev. | E66: 0.001 | H66: Bora Inputs G198
C67: HIPA local business tax | D67: % of rev. | E67: 0.02 | H67: Bora Inputs G212
C68: Opex contingency (not on community, HIPA) | D68: % | E68: 0.05 | H68: Bora Inputs G210
C69: Opex escalation | D69: % p.a. | E69: 0.025 | H69: Bora Inputs G211
C70: Valuation, timeline and constants
C71: Operating life from COD | D71: years | E71: 30 | H71: Bora Inputs G157
C72: Discount rate (buyer's pre-tax return at COD) | D72: % | E72: 0.08 | H72: Bora Inputs G226
C73: First year of the annual timeline | D73: year | E73: 2026 | H73: Year of the first signing
C74: Thousand | D74: x | E74: 1000 | H74: Constant
C75: Days in a year (act/365) | D75: days | E75: 365 | H75: Constant
C76: Months in a year | D76: months | E76: 12 | H76: Constant
C77: Check tolerance | D77: EUR k | E77: 0.001 | H77: Constant
C79: Devex items (BORA_Devex 02-Oct-26; all projects × the scale): HUF | date | class
C80: Capacity allocation process - Awarding – Land reservation fee | D80: HUF | E80: 20590500 | F80: 46431 | G80: Land | H80: BORA_Devex 02-Oct-26 row 14
C81: Capacity allocation process - Awarding – Land purchase price | D81: HUF | E81: 45600000 | F81: 46431 | G81: Land | H81: BORA_Devex 02-Oct-26 row 15
C82: Grid connection plan – Design fee | D82: HUF | E82: 59142857 | F82: 46976 | G82: Devex | H82: BORA_Devex 02-Oct-26 row 16
C83: Grid connection plan – Administrative fee | D83: HUF | E83: 750544 | F83: 46976 | G83: Devex | H83: BORA_Devex 02-Oct-26 row 17
C84: Land contracting (additional land) – Legal fee, agent fee | D84: HUF | E84: 65580000 | F84: 46296 | G84: Devex | H84: BORA_Devex 02-Oct-26 row 20
C85: Wind measurement – Met Masts | D85: HUF | E85: 147260000 | F85: 46447 | G85: Devex | H85: BORA_Devex 02-Oct-26 row 21
C86: Wind measurement – Design fee | D86: HUF | E86: 3600000 | F86: 46388 | G86: Devex | H86: BORA_Devex 02-Oct-26 row 22
C87: Wind measurement – EYA | D87: HUF | E87: 1665000 | F87: 46932 | G87: Devex | H87: BORA_Devex 02-Oct-26 row 23
C88: Land reclassification – Administrative fee | D88: HUF | E88: 960000 | F88: 46746 | G88: Devex | H88: BORA_Devex 02-Oct-26 row 24
C89: Land reclassification – Report fee | D89: HUF | E89: 8000000 | F89: 46596 | G89: Devex | H89: BORA_Devex 02-Oct-26 row 25
C90: Zoning plan modification – Design fee | D90: HUF | E90: 50000000 | F90: 46806 | G90: Devex | H90: BORA_Devex 02-Oct-26 row 26
C91: Municipality donation – Donation | D91: HUF | E91: 35000000 | F91: 46806 | G91: Devex | H91: BORA_Devex 02-Oct-26 row 27
... C112: Contingency – Contingency | D112: HUF | E112: 1.0790862e+08 | F112: 46752 | G112: Devex | H112: BORA_Devex 02-Oct-26 row 48; continuous: 31-Dec-27
B114: x | C114: Band tables for the points (ÖSZ, Kiírás Annex 4) – expand the group | E114: Values →
C115: Osz1_LB | E115: 10 | F115: 15 | G115: 20 | H115: 25 | I115: 30 | J115: 35 | K115: 40 | L115: 45 | M115: 50
C116: Osz1_Incl | E116: 0 | F116: 0 | G116: 0 | H116: 0 | I116: 0 | J116: 0 | K116: 0 | L116: 0 | M116: 1
C117: Osz1_Pts | E117: 0 | F117: 10 | G117: 20 | H117: 30 | I117: 40 | J117: 55 | K117: 70 | L117: 80 | M117: 90 | N117: 100
C118: Osz2_LB | E118: 2 | F118: 2.1 | G118: 2.2 | H118: 2.3 | I118: 2.4 | J118: 2.5 | K118: 2.6 | L118: 2.7 | M118: 2.8 | N118: 2.9 | O118: 3
C119: Osz2_Incl | E119: 0 | F119: 0 | G119: 0 | H119: 0 | I119: 0 | J119: 0 | K119: 0 | L119: 0 | M119: 0 | N119: 0 | O119: 1
C120: Osz2_Pts | E120: 0 | F120: 5 | G120: 10 | H120: 20 | I120: 30 | J120: 40 | K120: 50 | L120: 60 | M120: 70 | N120: 80 | O120: 90 | P120: 100
C121: Osz3_LB | E121: 0.02 | F121: 0.05 | G121: 0.1 | H121: 0.15 | I121: 0.2 | J121: 0.25 | K121: 0.3 | L121: 0.35 | M121: 0.4 | N121: 0.5
C122: Osz3_Incl | E122: 0 | F122: 1 | G122: 1 | H122: 1 | I122: 1 | J122: 1 | K122: 1 | L122: 1 | M122: 1 | N122: 0
C123: Osz3_Pts | E123: 0 | F123: 10 | G123: 20 | H123: 30 | I123: 40 | J123: 50 | K123: 60 | L123: 70 | M123: 80 | N123: 90 | O123: 100
B124: Osz4_LB | E124: 0.02 | F124: 0.05 | G124: 0.1 | H124: 0.15 | I124: 0.2 | J124: 0.25 | K124: 0.3 | L124: 0.35 | M124: 0.4 | N124: 0.5
B125: Osz4_Incl | E125: 0 | F125: 1 | G125: 1 | H125: 1 | I125: 1 | J125: 1 | K125: 1 | L125: 1 | M125: 1 | N125: 0
B126: Osz4_Pts | E126: 0 | F126: 10 | G126: 20 | H126: 30 | I126: 40 | J126: 50 | K126: 60 | L126: 70 | M126: 80 | N126: 90 | O126: 100 | P126: Kiírás Annex 4, ÖSZ-4: 2<x<5:10 … 40≤x<50:90, 50<x:100 (x = 50 % not defined; scored 90)
...
