Workbook

Sheet Dashboard
C2: HU wind projects
C3: Master check (0 = OK; checks at the end of the detail) | D3: flag | H3: =Master_Check -> 0
B5: x | C5: Key inputs: the bids | E5: Bora | F5: Iváncsa | G5: Dunaújváros | H5: Total
C6: Net connection capacity | D6: MVA | E6: 50 | F6: 50 | G6: 50 | H6: =SUM(E6:G6) -> 150
C7: Overbuild (ÖSZ-3) | D7: % | E7: 0 | F7: 0.4 | G7: 0.4
C8: BESS power, share of MVA (ÖSZ-4) | D8: % | E8: 0 | F8: 0.2 | G8: 0.2
C9: BESS duration | D9: h | E9: 4 | F9: 4 | G9: 4
C10: Wind built below the bid | D10: % | E10: 0 | F10: 0 | G10: 0
C11: Municipal one-off (ÖSZ-1), at COD | D11: EUR k/MVA | E11: 20 | F11: 50 | G11: 50
C12: Community contribution (ÖSZ-2) | D12: EUR/MWh | E12: 0 | F12: 3 | G12: 3
C13: Partial award accepted (ÖSZ-5) | D13: flag | E13: 1 | F13: 1 | G13: 1
C14: Performance security multiple (ÖSZ-6) | D14: x | E14: 1 | F14: 1 | G14: 1
C15: Brownfield site (ÖSZ-7) | D15: flag | E15: 0 | F15: 0 | G15: 0
C16: Shared connection (ÖSZ-8) | D16: flag | E16: 1 | F16: 1 | G16: 1
C17: Turbine route (EU or CN; EU scores ÖSZ-9) | D17: text | E17: CN | F17: CN | G17: CN
C18: RtB premium | D18: EUR k/MVA | E18: 150 | F18: 150 | G18: 150
C19: FEP share of distributable proceeds | D19: % | E19: 0.7 | F19: 1 | G19: 1
C20: Developer success fee (DSA) on | D20: flag | E20: 1 | F20: 0 | G20: 0
C21: JV with a developer (1 = yes; claims and DSA apply) | D21: flag | E21: 1 | F21: 0 | G21: 0
C22: Net P50 hours (project wind study) | D22: h/yr | E22: 2500 | F22: 2500 | G22: 2500
B24: x | C24: Case: turbine price, PPA, yield, O&M | E24: Base | F24: Low | G24: High | H24: Live
C25: Case selected (Base, Low or High) | D25: case | H25: Base
C26: Turbine supply incl. transport, EU route | D26: EUR k/MW | E26: 850 | F26: 950 | G26: 800 | H26: =INDEX(E26:G26,MATCH(Dash_Case,$E$24:$G$24,0)) -> 850 | J26: Bora Dashboard H8 / Inputs G162
C27: Turbine supply incl. transport, CN route | D27: EUR k/MW | E27: 500 | F27: 600 | G27: 480 | H27: =INDEX(E27:G27,MATCH(Dash_Case,$E$24:$G$24,0)) -> 500 | J27: Bora Inputs H162
C28: PPA price in the COD year | D28: EUR/MWh | E28: 90 | F28: 90 | G28: 100 | H28: =INDEX(E28:G28,MATCH(Dash_Case,$E$24:$G$24,0)) -> 90 | J28: Bora Dashboard H9
C29: Net P50 hours (not used: project P50 in row 21) | D29: h/yr | E29: 2500 | F29: 2460 | G29: 2600 | H29: =INDEX(E29:G29,MATCH(Dash_Case,$E$24:$G$24,0)) -> 2500 | J29: Bora Dashboard H10
C30: O&M full-service contract | D30: EUR k/MW/yr | E30: 12 | F30: 12 | G30: 10 | H30: =INDEX(E30:G30,MATCH(Dash_Case,$E$24:$G$24,0)) -> 12 | J30: Bora Dashboard H11
B32: x | C32: Bid points and capacity | E32: Bora | F32: Iváncsa | G32: Dunaújváros | H32: Total
C33: Points – municipal one-off | D33: points | E33: =INDEX(Osz1_Pts,1+SUMPRODUCT((Osz1_LB<E11)+(Osz1_LB=E11)*Osz1_Incl))*Osz1_W -> 4 | F33: =INDEX(Osz1_Pts,1+SUMPRODUCT((Osz1_LB<F11)+(Osz1_LB=F11)*Osz1_Incl))*Osz1_W -> 20 | G33: =INDEX(Osz1_Pts,1+SUMPRODUCT((Osz1_LB<G11)+(Osz1_LB=G11)*Osz1_Incl))*Osz1_W -> 20
C34: Points – community contribution | D34: points | E34: =INDEX(Osz2_Pts,1+SUMPRODUCT((Osz2_LB<E12)+(Osz2_LB=E12)*Osz2_Incl))*Osz2_W -> 0 | F34: =INDEX(Osz2_Pts,1+SUMPRODUCT((Osz2_LB<F12)+(Osz2_LB=F12)*Osz2_Incl))*Osz2_W -> 15 | G34: =INDEX(Osz2_Pts,1+SUMPRODUCT((Osz2_LB<G12)+(Osz2_LB=G12)*Osz2_Incl))*Osz2_W -> 15
C35: Points – overbuild | D35: points | E35: =INDEX(Osz3_Pts,1+SUMPRODUCT((Osz3_LB<E7)+(Osz3_LB=E7)*Osz3_Incl))*Osz3_W -> 0 | F35: =INDEX(Osz3_Pts,1+SUMPRODUCT((Osz3_LB<F7)+(Osz3_LB=F7)*Osz3_Incl))*Osz3_W -> 9 | G35: =INDEX(Osz3_Pts,1+SUMPRODUCT((Osz3_LB<G7)+(Osz3_LB=G7)*Osz3_Incl))*Osz3_W -> 9
C36: Points – BESS | D36: points | E36: =INDEX(Osz3_Pts,1+SUMPRODUCT((Osz3_LB<E8)+(Osz3_LB=E8)*Osz3_Incl))*Osz4_W -> 0 | F36: =INDEX(Osz3_Pts,1+SUMPRODUCT((Osz3_LB<F8)+(Osz3_LB=F8)*Osz3_Incl))*Osz4_W -> 7.5 | G36: =INDEX(Osz3_Pts,1+SUMPRODUCT((Osz3_LB<G8)+(Osz3_LB=G8)*Osz3_Incl))*Osz4_W -> 7.5
C37: Points – partial award | D37: points | E37: =E13*Osz5_Pts*Osz5_W -> 5 | F37: =F13*Osz5_Pts*Osz5_W -> 5 | G37: =G13*Osz5_Pts*Osz5_W -> 5
C38: Points – performance security | D38: points | E38: =INDEX(Osz6_Pts,1+SUMPRODUCT((Osz6_LB<E14)+(Osz6_LB=E14)*Osz6_Incl))*Osz6_W -> 0 | F38: =INDEX(Osz6_Pts,1+SUMPRODUCT((Osz6_LB<F14)+(Osz6_LB=F14)*Osz6_Incl))*Osz6_W -> 0 | G38: =INDEX(Osz6_Pts,1+SUMPRODUCT((Osz6_LB<G14)+(Osz6_LB=G14)*Osz6_Incl))*Osz6_W -> 0
C39: Points – brownfield | D39: points | E39: =E15*Osz7_Pts*Osz7_W -> 0 | F39: =F15*Osz7_Pts*Osz7_W -> 0 | G39: =G15*Osz7_Pts*Osz7_W -> 0
C40: Points – shared connection | D40: points | E40: =E16*Osz8_Pts*Osz8_W -> 5 | F40: =F16*Osz8_Pts*Osz8_W -> 5 | G40: =G16*Osz8_Pts*Osz8_W -> 5
C41: Points – EU turbines | D41: points | E41: =N(E17="EU")*Osz9a_Pts*Osz9_W -> 0 | F41: =N(F17="EU")*Osz9a_Pts*Osz9_W -> 0 | G41: =N(G17="EU")*Osz9a_Pts*Osz9_W -> 0
C42: Points – EU transformers | D42: points | E42: =Inputs!E$25*Osz9b_Pts*Osz9_W -> 0 | F42: =Inputs!F$25*Osz9b_Pts*Osz9_W -> 0 | G42: =Inputs!G$25*Osz9b_Pts*Osz9_W -> 0
C43: Points total | D43: points | E43: =SUM(E33:E42) -> 14 | F43: =SUM(F33:F42) -> 61.5 | G43: =SUM(G33:G42) -> 61.5
C44: Wind committed in the bid | D44: MW | E44: =E6*(1+E7) -> 50 | F44: =F6*(1+F7) -> 70 | G44: =G6*(1+G7) -> 70 | H44: =SUM(E44:G44) -> 190
C45: BESS energy | D45: MWh | E45: =E6*E8*E9 -> 0 | F45: =F6*F8*F9 -> 40 | G45: =G6*G8*G9 -> 40 | H45: =SUM(E45:G45) -> 80
C46: Wind built (committed less the build shortfall) | D46: MW | E46: =E44*(1-E10) -> 50 | F46: =F44*(1-F10) -> 70 | G46: =G44*(1-G10) -> 70 | H46: =SUM(E46:G46) -> 190
B48: x | C48: Guarantees, securities and connection fees, DEVEX (HUF) | E48: Bora | F48: Iváncsa | G48: Dunaújváros | H48: Total | J48: Date
C49: Participation fee | D49: HUF | E49: =Part_Fee -> 3000000 | F49: =Part_Fee -> 3000000 | G49: =Part_Fee -> 3000000 | H49: =SUM(E49:G49) -> 9000000 | J49: =Inputs!E$27 -> 46325
C50: Bid security | D50: HUF | E50: =Bid_Sec_Rate*(E44*Bench_Wind+E45*Bench_BESS) -> 101500000 | F50: =Bid_Sec_Rate*(F44*Bench_Wind+F45*Bench_BESS) -> 182100000 | G50: =Bid_Sec_Rate*(G44*Bench_Wind+G45*Bench_BESS) -> 182100000 | H50: =SUM(E50:G50) -> 465700000 | J50: =Inputs!E$27 -> 46325
C51: Performance security payable (bid security deducted) | D51: HUF | E51: =PB_Rate*E14*(E44*Bench_Wind+E45*Bench_BESS)-E50 -> 406000000 | F51: =PB_Rate*F14*(F44*Bench_Wind+F45*Bench_BESS)-F50 -> 728400000 | G51: =PB_Rate*G14*(G44*Bench_Wind+G45*Bench_BESS)-G50 -> 728400000 | H51: =SUM(E51:G51) -> 1862800000 | J51: =Inputs!E$28 -> 46402
C52: TSO connection-request security | D52: HUF | E52: =TSO_Rate*E6 -> 225000000 | F52: =TSO_Rate*F6 -> 225000000 | G52: =TSO_Rate*G6 -> 225000000 | H52: =SUM(E52:G52) -> 675000000 | J52: =Inputs!E$29 -> 46402
C53: Direct connection fee (per point ÷ bids sharing it) | D53: HUF | E53: =Inputs!E$15/Inputs!E$16 -> 254172902 | F53: =Inputs!F$15/Inputs!F$16 -> 460000000 | G53: =Inputs!G$15/Inputs!G$16 -> 460000000 | H53: =SUM(E53:G53) -> 1174172902 | J53: =Inputs!E$30 -> 47027
C54: Indirect connection fee, payable (TSO security deducted) | D54: HUF | E54: =Inputs!E$14*E6-E52 -> 3428565300 | F54: =Inputs!F$14*F6-F52 -> 766334000 | G54: =Inputs!G$14*G6-G52 -> 766334000 | H54: =SUM(E54:G54) -> 4961233300 | J54: =Inputs!E$30 -> 47027
C55: DEVEX | D55: HUF | E55: =SUM(Inputs!E$18:E$23)*FX*Thousand -> 286331550 | F55: =SUM(Inputs!F$18:F$23)*FX*Thousand -> 365000000 | G55: =SUM(Inputs!G$18:G$23)*FX*Thousand -> 365000000 | H55: =SUM(E55:G55) -> 1016331550 | J55: =Inputs!E$31 -> 46752
C56: Signing fee and DD | D56: HUF | E56: =Inputs!E$17*FX*Thousand -> 36500000 | F56: =Inputs!F$17*FX*Thousand -> 54750000 | G56: =Inputs!G$17*FX*Thousand -> 54750000 | H56: =SUM(E56:G56) -> 146000000 | J56: =Inputs!E$26 -> 46234
C57: Total cash to RtB (incl. signing and DD) | D57: HUF | E57: =SUM(E49:E56) -> 4741069752 | F57: =SUM(F49:F56) -> 2784584000 | G57: =SUM(G49:G56) -> 2784584000 | H57: =SUM(E57:G57) -> 10310237752
B59: x | C59: Guarantees, securities and connection fees, DEVEX (EUR k) | E59: Bora | F59: Iváncsa | G59: Dunaújváros | H59: Total | J59: Date
C60: Participation fee | D60: EUR k | E60: =E49/FX/Thousand -> 8.2191781 | F60: =F49/FX/Thousand -> 8.2191781 | G60: =G49/FX/Thousand -> 8.2191781 | H60: =SUM(E60:G60) -> 24.657534 | J60: =Inputs!E$27 -> 46325
C61: Bid security | D61: EUR k | E61: =E50/FX/Thousand -> 278.08219 | F61: =F50/FX/Thousand -> 498.90411 | G61: =G50/FX/Thousand -> 498.90411 | H61: =SUM(E61:G61) -> 1275.8904 | J61: =Inputs!E$27 -> 46325
C62: Performance security payable (bid security deducted) | D62: EUR k | E62: =E51/FX/Thousand -> 1112.3288 | F62: =F51/FX/Thousand -> 1995.6164 | G62: =G51/FX/Thousand -> 1995.6164 | H62: =SUM(E62:G62) -> 5103.5616 | J62: =Inputs!E$28 -> 46402
C63: TSO connection-request security | D63: EUR k | E63: =E52/FX/Thousand -> 616.43836 | F63: =F52/FX/Thousand -> 616.43836 | G63: =G52/FX/Thousand -> 616.43836 | H63: =SUM(E63:G63) -> 1849.3151 | J63: =Inputs!E$29 -> 46402
C64: Direct connection fee (per point ÷ bids sharing it) | D64: EUR k | E64: =E53/FX/Thousand -> 696.36412 | F64: =F53/FX/Thousand -> 1260.274 | G64: =G53/FX/Thousand -> 1260.274 | H64: =SUM(E64:G64) -> 3216.9121 | J64: =Inputs!E$30 -> 47027
C65: Indirect connection fee, payable (TSO security deducted) | D65: EUR k | E65: =E54/FX/Thousand -> 9393.3296 | F65: =F54/FX/Thousand -> 2099.5452 | G65: =G54/FX/Thousand -> 2099.5452 | H65: =SUM(E65:G65) -> 13592.42 | J65: =Inputs!E$30 -> 47027
C66: DEVEX | D66: EUR k | E66: =E55/FX/Thousand -> 784.47 | F66: =F55/FX/Thousand -> 1000 | G66: =G55/FX/Thousand -> 1000 | H66: =SUM(E66:G66) -> 2784.47 | J66: =Inputs!E$31 -> 46752
C67: Signing fee and DD | D67: EUR k | E67: =Inputs!E$17 -> 100 | F67: =Inputs!F$17 -> 150 | G67: =Inputs!G$17 -> 150 | H67: =SUM(E67:G67) -> 400 | J67: =Inputs!E$26 -> 46234
C68: Total cash to RtB (incl. signing and DD) | D68: EUR k | E68: =SUM(E60:E67) -> 12989.232 | F68: =SUM(F60:F67) -> 7628.9973 | G68: =SUM(G60:G67) -> 7628.9973 | H68: =SUM(E68:G68) -> 28247.227
B70: x | C70: Cash to RtB by nature: sunk, returned, or borne by the buyer (EUR k) | E70: Bora | F70: Iváncsa | G70: Dunaújváros | H70: Total | J70: Who bears it
C71: Sunk fees and devex (signing and DD, participation fee, devex) | D71: EUR k | E71: =E60+E66+E67 -> 892.68918 | F71: =F60+F66+F67 -> 1158.2192 | G71: =G60+G66+G67 -> 1158.2192 | H71: =SUM(E71:G71) -> 3209.1275 | J71: FEP – sunk; recovered only via the claims at the sale
C72: Securities, returned (bid, performance, TSO connection request) | D72: EUR k | E72: =SUM(E61:E63) -> 2006.8493 | F72: =SUM(F61:F63) -> 3110.9589 | G72: =SUM(G61:G63) -> 3110.9589 | H72: =SUM(E72:G72) -> 8228.7671 | J72: FEP – cash out, returned or reimbursed at the sale
C73: Grid connection fees (direct + indirect, payable at HCSSZ) | D73: EUR k | E73: =E64+E65 -> 10089.694 | F73: =F64+F65 -> 3359.8192 | G73: =G64+G65 -> 3359.8192 | H73: =SUM(E73:G73) -> 16809.332 | J73: Buyer at RtB; FEP pays only if no buyer is found
C74: Total cash to RtB (= total above) | D74: EUR k | E74: =SUM(E71:E73) -> 12989.232 | F74: =SUM(F71:F73) -> 7628.9973 | G74: =SUM(G71:G73) -> 7628.9973 | H74: =SUM(E74:G74) -> 28247.227 | J74: Case A: FEP pre-funds everything
C75: Grid connection fees, share of the total | D75: % | E75: =E73/E74 -> 0.77677368 | F75: =F73/F74 -> 0.44040115 | G75: =G73/G74 -> 0.44040115 | H75: =H73/H74 -> 0.59507902
C76: FEP exposure if the buyer pays the grid connection fees | D76: EUR k | E76: =E74-E73 -> 2899.5385 | F76: =F74-F73 -> 4269.1781 | G76: =G74-G73 -> 4269.1781 | H76: =SUM(E76:G76) -> 11437.895 | J76: Case B: FEP funds sunk fees, devex and securities only
B78: x | C78: Capex breakdown to COD | E78: Bora | F78: Iváncsa | G78: Dunaújváros | H78: Total
C79: Turbines (route price, live case) | D79: EUR k | E79: =IF(E17="EU",Case_EU,Case_CN)*E46 -> 25000 | F79: =IF(F17="EU",Case_EU,Case_CN)*F46 -> 35000 | G79: =IF(G17="EU",Case_EU,Case_CN)*G46 -> 35000 | H79: =SUM(E79:G79) -> 95000
C80: Installation and erection | D80: EUR k | E80: =Capex_Install*E46 -> 4000 | F80: =Capex_Install*F46 -> 5600 | G80: =Capex_Install*G46 -> 5600 | H80: =SUM(E80:G80) -> 15200
C81: Foundations | D81: EUR k | E81: =Capex_Fdn*E46 -> 4500 | F81: =Capex_Fdn*F46 -> 6300 | G81: =Capex_Fdn*G46 -> 6300 | H81: =SUM(E81:G81) -> 17100
C82: Balance of plant – civil | D82: EUR k | E82: =Capex_Civil*E46 -> 3500 | F82: =Capex_Civil*F46 -> 4900 | G82: =Capex_Civil*G46 -> 4900 | H82: =SUM(E82:G82) -> 13300
C83: Balance of plant – electrical | D83: EUR k | E83: =Capex_Elec*E46 -> 3000 | F83: =Capex_Elec*F46 -> 4200 | G83: =Capex_Elec*G46 -> 4200 | H83: =SUM(E83:G83) -> 11400
C84: Owner's costs, engineering, PM, construction insurance | D84: EUR k | E84: =Capex_Owner*E46 -> 2000 | F84: =Capex_Owner*F46 -> 2800 | G84: =Capex_Owner*G46 -> 2800 | H84: =SUM(E84:G84) -> 7600
C85: Land purchase and easements | D85: EUR k | E85: =Capex_Land*E46 -> 750 | F85: =Capex_Land*F46 -> 1050 | G85: =Capex_Land*G46 -> 1050 | H85: =SUM(E85:G85) -> 2850
C86: Substation and 132 kV bay (scaled by MVA) | D86: EUR k | E86: =Subs_Lump*E6/Lump_Basis -> 3000 | F86: =Subs_Lump*F6/Lump_Basis -> 3000 | G86: =Subs_Lump*G6/Lump_Basis -> 3000 | H86: =SUM(E86:G86) -> 9000
C87: Contingency (not on BESS) | D87: EUR k | E87: =SUM(E79:E86)*Capex_Cont -> 2287.5 | F87: =SUM(F79:F86)*Capex_Cont -> 3142.5 | G87: =SUM(G79:G86)*Capex_Cont -> 3142.5 | H87: =SUM(E87:G87) -> 8572.5
C88: BESS (on BESS energy) | D88: EUR k | E88: =BESS_Capex*E45 -> 0 | F88: =BESS_Capex*F45 -> 4000 | G88: =BESS_Capex*G45 -> 4000 | H88: =SUM(E88:G88) -> 8000
C89: Construction capex | D89: EUR k | E89: =SUM(E79:E88) -> 48037.5 | F89: =SUM(F79:F88) -> 69992.5 | G89: =SUM(G79:G88) -> 69992.5 | H89: =SUM(E89:G89) -> 188022.5
C90: Connection fees (TSO security, direct, indirect) | D90: EUR k | E90: =E63+E64+E65 -> 10706.132 | F90: =F63+F64+F65 -> 3976.2575 | G90: =G63+G64+G65 -> 3976.2575 | H90: =SUM(E90:G90) -> 18658.647
C91: Municipal one-off | D91: EUR k | E91: =E11*E6 -> 1000 | F91: =F11*F6 -> 2500 | G91: =G11*G6 -> 2500 | H91: =SUM(E91:G91) -> 6000
C92: Development (participation fee, devex, signing and DD) | D92: EUR k | E92: =E60+E66+E67 -> 892.68918 | F92: =F60+F66+F67 -> 1158.2192 | G92: =G60+G66+G67 -> 1158.2192 | H92: =SUM(E92:G92) -> 3209.1275
C93: All-in cost to COD (securities excluded: returned) | D93: EUR k | E93: =E89+SUM(E90:E92) -> 60636.321 | F93: =F89+SUM(F90:F92) -> 77626.977 | G93: =G89+SUM(G90:G92) -> 77626.977 | H93: =SUM(E93:G93) -> 215890.27
C94: All-in cost per MW built | D94: EUR k/MW | E94: =E93/E46 -> 1212.7264 | F94: =F93/F46 -> 1108.9568 | G94: =G93/G46 -> 1108.9568 | H94: =H93/H46 -> 1136.2646
C95: All-in cost per MVA | D95: EUR k/MVA | E95: =E93/E6 -> 1212.7264 | F95: =F93/F6 -> 1552.5395 | G95: =G93/G6 -> 1552.5395 | H95: =H93/H6 -> 1439.2685
B97: x | C97: Devex breakdown (Bora: devex-file categories; tender fee and securities: above) | E97: Bora | F97: Iváncsa | G97: Dunaújváros | H97: Total
C98: Grid connection plan and agreement | D98: EUR k | E98: =Inputs!E$18 -> 40.47 | F98: =Inputs!F$18 -> 51.588971 | G98: =Inputs!G$18 -> 51.588971 | H98: =SUM(E98:G98) -> 143.64794
C99: Land (reservation, purchase, contracting) | D99: EUR k | E99: =Inputs!E$19 -> 150.66 | F99: =Inputs!F$19 -> 192.05323 | G99: =Inputs!G$19 -> 192.05323 | H99: =SUM(E99:G99) -> 534.76647
C100: Permits, zoning, cable rights | D100: EUR k | E100: =Inputs!E$20 -> 333.93 | F100: =Inputs!F$20 -> 425.67593 | G100: =Inputs!G$20 -> 425.67593 | H100: =SUM(E100:G100) -> 1185.2819
C101: Studies (wind, environment, ground) | D101: EUR k | E101: =Inputs!E$21 -> 151.36 | F101: =Inputs!F$21 -> 192.94556 | G101: =Inputs!G$21 -> 192.94556 | H101: =SUM(E101:G101) -> 537.25111
C102: Legal, financial and other | D102: EUR k | E102: =Inputs!E$22 -> 37.5 | F102: =Inputs!F$22 -> 47.802975 | G102: =Inputs!G$22 -> 47.802975 | H102: =SUM(E102:G102) -> 133.10595
C103: Contingency | D103: EUR k | E103: =Inputs!E$23 -> 70.55 | F103: =Inputs!F$23 -> 89.933331 | G103: =Inputs!G$23 -> 89.933331 | H103: =SUM(E103:G103) -> 250.41666
C104: Devex total (= DEVEX line above) | D104: EUR k | E104: =SUM(E98:E103) -> 784.47 | F104: =SUM(F98:F103) -> 1000 | G104: =SUM(G98:G103) -> 1000 | H104: =SUM(E104:G104) -> 2784.47
B106: x | C106: Returns RTB COD HTM | E106: Bora | F106: Iváncsa | G106: Dunaújváros | H106: Total
C107: RTB exit, Case A: buyer pays the grid connection fees (FEP does not pre-fund)
C108: Grid connection fees paid by the buyer (not FEP cash) | D108: EUR k | E108: =E223 -> 10089.694 | F108: =F223 -> 3359.8192 | G108: =G223 -> 3359.8192 | H108: =SUM(E108:G108) -> 16809.332
C109: Total FEP cash out to RtB (peak exposure) | D109: EUR k | E109: =E224 -> 2899.5385 | F109: =F224 -> 4269.1781 | G109: =G224 -> 4269.1781 | H109: =SUM(E109:G109) -> 11437.895
C110: Total proceeds to FEP at the sale | D110: EUR k | E110: =E262 -> 7282.5856 | F110: =F262 -> 10360.959 | G110: =G262 -> 10360.959 | H110: =SUM(E110:G110) -> 28004.503
...

Sheet Inputs
C2: HU wind bids – other inputs (blue) with sources
B4: x | C4: Inputs | E4: Bora | F4: Iváncsa | G4: Dunaújváros | H4: Source
C5: Tender and grid (all projects; value in column E)
C6: FX rate | D6: HUF/EUR | E6: 365 | H6: Bora Inputs E11; Bid_Cash E45
C7: Security base: benchmark investment, wind | D7: HUF/MW | E7: 406000000 | H7: Bora Inputs E75; Bid_Cash E46
C8: Security base: benchmark investment, BESS | D8: HUF/MWh | E8: 200000000 | H8: Bora Inputs E89; Bid_Cash E47
C9: Bid security, share of base | D9: % | E9: 0.005 | H9: Bora Inputs E76; Bid_Cash E49
C10: Performance security, minimum share of base | D10: % | E10: 0.025 | H10: Bora Inputs E77; Bid_Cash E50
C11: Participation fee per bid | D11: HUF | E11: 3000000 | H11: Bora Inputs E81; Bid_Cash E48
C12: TSO connection-request security | D12: HUF/MVA | E12: 4500000 | H12: Bora Inputs E83; Bid_Cash E51
C13: Per project: fees, devex, dates
C14: Indirect connection fee | D14: HUF/MVA | E14: 73071306 | F14: 19826680 | G14: 19826680 | H14: Bora Inputs G290; Bid_Cash E52
C15: Direct connection fee per connection point | D15: HUF | E15: 508345804 | F15: 460000000 | G15: 460000000 | H15: Bora Inputs G291; Bid_Cash E53
C16: Bids sharing the connection point | D16: count | E16: 2 | F16: 1 | G16: 1 | H16: Bora: 2 bids per point (SPEC §22.2)
C17: Signing fee and DD | D17: EUR k | E17: 100 | F17: 150 | G17: 150 | H17: Bora E24+E25: 400 × 50/200; Bid_Cash E55
C18: Devex: grid connection plan and agreement | D18: EUR k | E18: 40.47 | F18: =$E18/SUM($E$18:$E$23)*F$24 -> 51.588971 | G18: =$E18/SUM($E$18:$E$23)*G$24 -> 51.588971 | H18: Bora share × F25/G25 (Iváncsa, Dunaújváros); Bora: Devex_FEP × 50/100 MVA
C19: Devex: land (reservation, purchase, contracting) | D19: EUR k | E19: 150.66 | F19: =$E19/SUM($E$18:$E$23)*F$24 -> 192.05323 | G19: =$E19/SUM($E$18:$E$23)*G$24 -> 192.05323 | H19: Bora share × F25/G25 (Iváncsa, Dunaújváros); Bora: Devex_FEP × 50/100 MVA
C20: Devex: permits, zoning, cable rights | D20: EUR k | E20: 333.93 | F20: =$E20/SUM($E$18:$E$23)*F$24 -> 425.67593 | G20: =$E20/SUM($E$18:$E$23)*G$24 -> 425.67593 | H20: Bora share × F25/G25 (Iváncsa, Dunaújváros); Bora: Devex_FEP × 50/100 MVA
C21: Devex: studies (wind, environment, ground) | D21: EUR k | E21: 151.36 | F21: =$E21/SUM($E$18:$E$23)*F$24 -> 192.94556 | G21: =$E21/SUM($E$18:$E$23)*G$24 -> 192.94556 | H21: Bora share × F25/G25 (Iváncsa, Dunaújváros); Bora: Devex_FEP × 50/100 MVA
C22: Devex: legal, financial and other | D22: EUR k | E22: 37.5 | F22: =$E22/SUM($E$18:$E$23)*F$24 -> 47.802975 | G22: =$E22/SUM($E$18:$E$23)*G$24 -> 47.802975 | H22: Bora share × F25/G25 (Iváncsa, Dunaújváros); Bora: Devex_FEP × 50/100 MVA
C23: Devex: contingency | D23: EUR k | E23: 70.55 | F23: =$E23/SUM($E$18:$E$23)*F$24 -> 89.933331 | G23: =$E23/SUM($E$18:$E$23)*G$24 -> 89.933331 | H23: Bora share × F25/G25 (Iváncsa, Dunaújváros); Bora: Devex_FEP × 50/100 MVA
C24: Devex total, Iváncsa and Dunaújváros (allocated pro rata to Bora's categories) | D24: EUR k | F24: 1000 | G24: 1000 | H24: User, 27-Oct-26: EUR 1m per project, split as Bora
C25: EU transformers ≥ 80 % (ÖSZ-9) | D25: flag | E25: 0 | F25: 0 | G25: 0 | H25: Bid_Cash E16; SPEC §23.1
C26: Signing fee and DD paid | D26: date | E26: 46234 | F26: 46234 | G26: 46234 | H26: Bora Inputs E27; Bid_Cash E34
C27: Bid submission: fee paid, bid security posted | D27: date | E27: 46325 | F27: 46325 | G27: 46325 | H27: Bora Inputs E95; Bid_Cash E35
C28: Performance security posted | D28: date | E28: 46402 | F28: 46402 | G28: 46402 | H28: Bora Deposits K10 (E96 + 17 d); Bid_Cash E36
C29: TSO security paid | D29: date | E29: 46402 | F29: 46402 | G29: 46402 | H29: Bora Inputs E97; Bid_Cash E37
C30: Connection agreement (HCSSZ): fees paid | D30: date | E30: 47027 | F30: 47027 | G30: 47027 | H30: Bora Inputs E99; Bid_Cash E39
C31: Devex average payment date | D31: date | E31: 46752 | F31: 46752 | G31: 46752 | H31: Bora Devex_FEP, amount-weighted; Bid_Cash 'continuous'
C32: Notice to proceed | D32: date | E32: 47299 | F32: 47299 | G32: 47299 | H32: Bora Inputs E154; Bid_Cash E40
C33: COD | D33: date | E33: 48029 | F33: 48029 | G33: 48029 | H33: Bora Inputs E155; Bid_Cash E41
C34: Performance security released | D34: date | E34: 48669 | F34: 48669 | G34: 48669 | H34: Bid_Cash E42 (Kiírás XII.13, estimate)
C35: DSA accrual start | D35: date | E35: 46325 | F35: 46325 | G35: 46325 | H35: Bora Inputs E70; others: signing (DSA off)
C36: RtB exit terms (all projects; value in column E)
C37: Claim rate, cash lines (incl. cash-posted securities) | D37: % | E37: 0.12 | H37: Devex file V18; SPEC §21.1
C38: Claim rate, devex | D38: % | E38: 0.2 | H38: Devex file V19
C39: Devex minimum return multiple | D39: x | E39: 2 | H39: Devex file V20
C40: Interest freeze date | D40: date | E40: 47299 | H40: Devex file V24
C41: Sale date, Case B (RtB exit after HCSSZ) | D41: date | E41: 47391 | H41: Bora Inputs E58; SPEC §21.1
C42: Sale date, Case A (before HCSSZ) | D42: date | E42: 47026 | H42: SPEC §25.2 (user, 28-Oct-2026)
C43: Sale costs per project | D43: EUR k | E43: 250 | H43: SPEC §21.1
C44: Developer success fee (on committed MW, 30/360) | D44: EUR k/MW/yr | E44: 2.5 | H44: Bora Inputs E36
C45: Developer success fee cap | D45: EUR k/MW | E45: 10 | H45: Bora Inputs E37
C46: Corporate income tax on exit gains and on operating profit | D46: % | E46: 0.15 | H46: SPEC §24.1 / §25.3 (15 %)
C47: Share deal, participation exemption on the share gain (1 = on); claims taxed as interest | D47: flag | E47: 1
C48: Tax depreciation period (straight line from the COD year) | D48: years | E48: 20 | H48: Bora model Inputs G215
C49: Gearing (debt ÷ all-in cost to COD) | D49: % | E49: 0.6 | H49: Bora model Inputs G219
C50: Debt interest rate | D50: % | E50: 0.05 | H50: Bora model Inputs G220
C51: Debt tenor (annuity from the first full year) | D51: years | E51: 15 | H51: Bora model Inputs G222
C52: Capex (per MW of wind built unless stated; turbines: case table on the Dashboard)
C53: Turbine installation and erection | D53: EUR k/MW | E53: 80 | H53: Bora Inputs G163
C54: Foundations | D54: EUR k/MW | E54: 90 | H54: Bora Inputs G164
C55: Balance of plant – civil | D55: EUR k/MW | E55: 70 | H55: Bora Inputs G165
C56: Balance of plant – electrical | D56: EUR k/MW | E56: 60 | H56: Bora Inputs G166
C57: Owner's costs, engineering, PM, construction insurance | D57: EUR k/MW | E57: 40 | H57: Bora Inputs G169
C58: Land purchase and easements | D58: EUR k/MW | E58: 15 | H58: Bora Inputs G170
C59: On-site substation and 132 kV bay (lump sum) | D59: EUR k | E59: 12000 | H59: Bora Inputs G167
C60: Source basis of the lump sums | D60: MVA | E60: 200 | H60: Bora Inputs E305
C61: Capex contingency (not on BESS) | D61: % | E61: 0.05 | H61: Bora Inputs G173
C62: BESS capex | D62: EUR k/MWh | E62: 100 | H62: CLAUDE.md standing assumption, 15-Oct-26
C63: Generation (hours and PPA price: case table on the Dashboard)
C64: Curtailment | D64: % | E64: 0.02 | H64: Bora Inputs G183
C65: Clipping | D65: % | E65: 0.04 | H65: Bora Dash_Clip_Override (user, 26-Oct-26)
C66: Degradation | D66: % p.a. | E66: 0.003 | H66: Bora Inputs G184
C67: PPA escalation | D67: % p.a. | E67: 0.01 | H67: Bora Inputs G194
C68: Opex (COD-year prices; O&M contract: case table on the Dashboard)
C69: Balance of plant maintenance | D69: EUR k/MW/yr | E69: 3 | H69: Bora Inputs G204
C70: Land lease | D70: EUR k/MW/yr | E70: 3 | H70: Bora Inputs G205
C71: Operational insurance | D71: EUR k/MW/yr | E71: 2.5 | H71: Bora Inputs G206
C72: Asset and commercial management | D72: EUR k/MW/yr | E72: 1.5 | H72: Bora Inputs G207
C73: Property tax | D73: EUR k/MW/yr | E73: 3 | H73: Bora Inputs G208
C74: Administration, audit, compliance (at the source basis) | D74: EUR k/yr | E74: 150 | H74: Bora Inputs G209
C75: Balancing cost | D75: EUR/MWh | E75: 4 | H75: Bora Inputs G196
C76: Grid use-of-system charges | D76: EUR/MWh | E76: 1 | H76: Bora Inputs G197
C77: MEKH supervisory fee | D77: % of rev. | E77: 0.001 | H77: Bora Inputs G198
C78: HIPA local business tax | D78: % of rev. | E78: 0.02 | H78: Bora Inputs G212
C79: Opex contingency (not on community, HIPA) | D79: % | E79: 0.05 | H79: Bora Inputs G210
C80: Opex escalation | D80: % p.a. | E80: 0.025 | H80: Bora Inputs G211
C81: Valuation, timeline and constants
C82: Operating life from COD | D82: years | E82: 30 | H82: Bora Inputs G157
C83: Discount rate (buyer's pre-tax return at COD) | D83: % | E83: 0.08 | H83: Bora Inputs G226
C84: First year of the annual timeline | D84: year | E84: 2026 | H84: Year of the first signing
C85: Thousand | D85: x | E85: 1000 | H85: Constant
C86: Days in a year (act/365) | D86: days | E86: 365 | H86: Constant
C87: Months in a year | D87: months | E87: 12 | H87: Constant
C88: Check tolerance | D88: EUR k | E88: 0.001 | H88: Constant
B90: x | C90: Band tables for the points (ÖSZ, Kiírás Annex 4) – expand the group | E90: Values →
C91: Osz1_LB | E91: 10 | F91: 15 | G91: 20 | H91: 25 | I91: 30 | J91: 35 | K91: 40 | L91: 45 | M91: 50
C92: Osz1_Incl | E92: 0 | F92: 0 | G92: 0 | H92: 0 | I92: 0 | J92: 0 | K92: 0 | L92: 0 | M92: 1
C93: Osz1_Pts | E93: 0 | F93: 10 | G93: 20 | H93: 30 | I93: 40 | J93: 55 | K93: 70 | L93: 80 | M93: 90 | N93: 100
C94: Osz2_LB | E94: 2 | F94: 2.1 | G94: 2.2 | H94: 2.3 | I94: 2.4 | J94: 2.5 | K94: 2.6 | L94: 2.7 | M94: 2.8 | N94: 2.9 | O94: 3
C95: Osz2_Incl | E95: 0 | F95: 0 | G95: 0 | H95: 0 | I95: 0 | J95: 0 | K95: 0 | L95: 0 | M95: 0 | N95: 0 | O95: 1
C96: Osz2_Pts | E96: 0 | F96: 5 | G96: 10 | H96: 20 | I96: 30 | J96: 40 | K96: 50 | L96: 60 | M96: 70 | N96: 80 | O96: 90 | P96: 100
C97: Osz3_LB | E97: 0.02 | F97: 0.05 | G97: 0.1 | H97: 0.15 | I97: 0.2 | J97: 0.25 | K97: 0.3 | L97: 0.35 | M97: 0.4 | N97: 0.5
C98: Osz3_Incl | E98: 0 | F98: 1 | G98: 1 | H98: 1 | I98: 1 | J98: 1 | K98: 1 | L98: 1 | M98: 1 | N98: 0
C99: Osz3_Pts | E99: 0 | F99: 10 | G99: 20 | H99: 30 | I99: 40 | J99: 50 | K99: 60 | L99: 70 | M99: 80 | N99: 90 | O99: 100
C100: Osz6_LB | E100: 1 | F100: 1.2 | G100: 1.3 | H100: 1.4 | I100: 1.5 | J100: 1.6 | K100: 1.7 | L100: 1.8 | M100: 1.9 | N100: 2
C101: Osz6_Incl | E101: 0 | F101: 1 | G101: 1 | H101: 1 | I101: 1 | J101: 1 | K101: 1 | L101: 1 | M101: 1 | N101: 1
C102: Osz6_Pts | E102: 0 | F102: 10 | G102: 20 | H102: 30 | I102: 40 | J102: 50 | K102: 60 | L102: 70 | M102: 80 | N102: 90 | O102: 100
C103: Osz5_Pts | E103: 100
...
