Workbook

Sheet Stat_Inp
B2: Outputs
B3: Project IRR | C3: % | F3: =Model!D37 -> 0.093844097
B4: Buyer Unlevered IRR | C4: % | F4: =Model!D44 -> 0.079572534
B6: Buyer IRR Sensitivities
B8: Purchase price vs CAPEX | J8: Purchase price vs Capture price | S8: Purchase price vs Yield
D9: Buyer purchase price, €k/MW | M9: Buyer purchase price, €k/MW | U9: Buyer purchase price, €k/MW
C10: =F4 -> 0.079572534 | D10: =E10-10 -> 60 | E10: =F10-10 -> 70 | F10: 80 | G10: =F10+10 -> 90 | H10: =G10+10 -> 100 | L10: =$F$4 -> 0.079572534 | M10: =N10-10 -> 60 | N10: =O10-10 -> 70 | O10: 80 | P10: =O10+10 -> 90 | Q10: =P10+10 -> 100 | T10: =$F$4 -> 0.079572534 | U10: =V10-10 -> 60 | V10: =W10-10 -> 70 | W10: 80 | X10: =W10+10 -> 90 | Y10: =X10+10 -> 100
B11: CAPEX, €k/MW | C11: =C12+10 -> 535 | J11: Capture price, €/MWh | L11: =L12 + 5 -> 55 | T11: =T12+25 -> 1300
C12: =C13+10 -> 525 | L12: =L13 + 5 -> 50 | T12: =T13+25 -> 1275
C13: 515 | L13: 45 | T13: 1250
C14: =C13 - 10 -> 505 | L14: =L13-5 -> 40 | T14: =T13-25 -> 1225
C15: =C14 - 10 -> 495 | L15: =L14-5 -> 35 | T15: =T14-25 -> 1200
C16: =C15 - 10 -> 485 | L16: =L15-5 -> 30 | T16: =T15-25 -> 1175
B18: Scenarios
B19: 1
B21: Inputs | C21: Unit | F21: Live | H21: 1 | I21: =H21+1 -> 2 | J21: =I21+1 -> 3 | K21: =J21+1 -> 4 | L21: =K21+1 -> 5 | M21: =L21+1 -> 6 | N21: =M21+1 -> 7
B22: Macro | H22: PV (N-S) | I22: PV (N-S) + BESS | J22: PV (E-W) | K22: PV (E-W) + BESS | L22: PV (E-W) | M22: PV (E-W) | N22: PV (E-W)
B23: Inflation profile | C23: Selection
B24: Quarter of inflation step-up | C24: Quarter | F24: {=IF(ISBLANK(INDEX(H24:O24, B$19)), H24, INDEX(H24:O24, B$19))} -> 1 | H24: 1
B25: Acquisition date | C25: Date | F25: {=IF(ISBLANK(INDEX(H25:O25, B$19)), H25, INDEX(H25:O25, B$19))} -> 46173 | H25: =H29 -> 46173
B26: Equity premium | C26: €k/MW | F26: {=IF(ISBLANK(INDEX(H26:O26, B$19)), H26, INDEX(H26:O26, B$19))} -> 90 | H26: 90
B28: Construction
B29: Construction start | C29: Date | F29: {=IF(ISBLANK(INDEX(H29:O29, B$19)), H29, INDEX(H29:O29, B$19))} -> 46173 | H29: 46173
B30: Construction timeline | C30: Months | F30: {=IF(ISBLANK(INDEX(H30:O30, B$19)), H30, INDEX(H30:O30, B$19))} -> 18 | H30: 18
B31: Construction End | C31: Date | F31: =EOMONTH(F29,F30) -> 46721
B33: PV
B34: CAPEX | C34: €k/MW | F34: {=IF(ISBLANK(INDEX(H34:O34, B$19)), H34, INDEX(H34:O34, B$19))} -> 515 | H34: 515
B35: PV useful life | C35: Years | F35: {=IF(ISBLANK(INDEX(H35:O35, B$19)), H35, INDEX(H35:O35, B$19))} -> 35 | H35: 35
B37: BESS
B38: BESS CAPEX | C38: €k/MW | F38: {=IF(ISBLANK(INDEX(H38:O38, B$19)), H38, INDEX(H38:O38, B$19))} -> 220 | H38: 220
B39: BESS CAPEX - refresh | C39: €k/MW | F39: {=IF(ISBLANK(INDEX(H39:O39, B$19)), H39, INDEX(H39:O39, B$19))} -> 110 | H39: 110
B40: BESS useful life | C40: Years | F40: {=IF(ISBLANK(INDEX(H40:O40, B$19)), H40, INDEX(H40:O40, B$19))} -> 17 | H40: 17
B42: Operations start | C42: Date | F42: =F31+1 -> 46722
B43: Asset hold period | C43: Years | F43: =F35 -> 35
B44: Operations end | C44: Date | F44: =EOMONTH(F42, (F43*12)) -> 59536
B45: BESS useful life | C45: Years | F45: =F40 -> 17
B46: BESS refresh period | C46: Date | F46: =EOMONTH(F42, (F45*12)) -> 52962
B48: Generation
B49: PV
B50: Capacity | C50: MW | F50: {=IF(ISBLANK(INDEX(H50:O50, B$19)), H50, INDEX(H50:O50, B$19))} -> 61 | H50: 61
B51: Base Yield | C51: MWh / MWp | F51: {=IF(ISBLANK(INDEX(H51:O51, B$19)), H51, INDEX(H51:O51, B$19))} -> 1250 | H51: 1250
B52: Yield sensitivity | F52: {=IF(ISBLANK(INDEX(H52:O52, B$19)), H52, INDEX(H52:O52, B$19))} -> 0 | H52: 0
B53: Yield in use | F53: =F51 * (1 + F52) -> 1250
B54: Availability | C54: % | F54: {=IF(ISBLANK(INDEX(H54:O54, B$19)), H54, INDEX(H54:O54, B$19))} -> 0.995 | H54: 0.995
B55: Degradation | C55: % p.a. | F55: {=IF(ISBLANK(INDEX(H55:O55, B$19)), H55, INDEX(H55:O55, B$19))} -> 0.003 | H55: 0.003
B57: BESS
B58: Capacity | C58: MW | F58: {=IF(ISBLANK(INDEX(H58:O58, B$19)), H58, INDEX(H58:O58, B$19))} -> 50 | H58: 50
B59: Duration | C59: Hours | F59: {=IF(ISBLANK(INDEX(H59:O59, B$19)), H59, INDEX(H59:O59, B$19))} -> 2 | H59: 2
B60: Cycles / day | C60: # | F60: {=IF(ISBLANK(INDEX(H60:O60, B$19)), H60, INDEX(H60:O60, B$19))} -> 1.5 | H60: 1.5
B61: Degradation / cycle | C61: % | F61: {=IF(ISBLANK(INDEX(H61:O61, B$19)), H61, INDEX(H61:O61, B$19))} -> 4.99e-05 | H61: 4.99e-05
B62: Availability | C62: % | F62: {=IF(ISBLANK(INDEX(H62:O62, B$19)), H62, INDEX(H62:O62, B$19))} -> 0.99 | H62: 0.99
B64: Revenue
B65: PV
A66: Replace w curve | B66: Capture price | C66: €/MWh | F66: {=IF(ISBLANK(INDEX(H66:O66, B$19)), H66, INDEX(H66:O66, B$19))} -> 45 | H66: 45
B67: GoOs | C67: €/MWh | F67: {=IF(ISBLANK(INDEX(H67:O67, B$19)), H67, INDEX(H67:O67, B$19))} -> 1.75 | H67: 1.75
B69: BESS
A70: Curve | B70: Revenue curve | C70: Selection
B71: Revenue degradation (% of physical degradation) | C71: % | F71: {=IF(ISBLANK(INDEX(H71:O71, B$19)), H71, INDEX(H71:O71, B$19))} -> 0.66666667 | H71: =2/3 -> 0.66666667
B73: Active capacity for revenue (1=degraded, 0=non-dgraded)
B74: Energy trading
B75: Ancillary services
B77: RTM commission on revenues | C77: % | F77: {=IF(ISBLANK(INDEX(H77:O77, B$19)), H77, INDEX(H77:O77, B$19))} -> 0.05 | H77: 0.05
B79: OPEX
B80: PV
B81: OPEX excl. balancing, land lease | C81: €k / MW p.a. | F81: {=IF(ISBLANK(INDEX(H81:O81, B$19)), H81, INDEX(H81:O81, B$19))} -> 14.96 | H81: 14.96 | P81: Source: Finnish PV
B82: Balancing | C82: €/MWh | F82: {=IF(ISBLANK(INDEX(H82:O82, B$19)), H82, INDEX(H82:O82, B$19))} -> 5 | H82: 5
B83: Land lease | C83: €k p.a. | F83: {=IF(ISBLANK(INDEX(H83:O83, B$19)), H83, INDEX(H83:O83, B$19))} -> 96 | H83: 96
B85: BESS
A86: Timing | B86: Waranty cost | C86: €/MW | F86: {=IF(ISBLANK(INDEX(H86:O86, B$19)), H86, INDEX(H86:O86, B$19))} -> 5543 | H86: 5543
A87: Timing | B87: Maintenance cost | C87: €/MW | F87: {=IF(ISBLANK(INDEX(H87:O87, B$19)), H87, INDEX(H87:O87, B$19))} -> 5543 | H87: 5543
B88: Other OPEX (BoP maintenance, insurance, legal etc) | C88: €/MW
B89: Land lease | C89: €/MW
B91: NWC
B92: Days payable | C92: Days | F92: {=IF(ISBLANK(INDEX(H92:O92, B$19)), H92, INDEX(H92:O92, B$19))} -> 30 | H92: 30
B93: Days receivable | C93: Days | F93: {=IF(ISBLANK(INDEX(H93:O93, B$19)), H93, INDEX(H93:O93, B$19))} -> 30 | H93: 30
B95: Tax
B96: Depreciation period | C96: Years | F96: {=IF(ISBLANK(INDEX(H96:O96, B$19)), H96, INDEX(H96:O96, B$19))} -> 30 | H96: 30
B97: CIT | C97: % | F97: {=IF(ISBLANK(INDEX(H97:O97, B$19)), H97, INDEX(H97:O97, B$19))} -> 0.09 | H97: 0.09
A99: End of sheet

Sheet Dyn_Inp
B2: Dynamic Inputs
B4: Month of construction | E4: 1 | F4: =E4+1 -> 2 | G4: =F4+1 -> 3 | H4: =G4+1 -> 4 | I4: =H4+1 -> 5 | J4: =I4+1 -> 6 | K4: =J4+1 -> 7 | L4: =K4+1 -> 8 | M4: =L4+1 -> 9 | ... AB4: =AA4+1 -> 24
B5: CAPEX timetable | C5: Source: Finland model | E5: 0.1 | F5: 0.0625 | G5: 0.0625 | H5: 0.0625 | I5: 0.0625 | J5: 0.0625 | K5: 0.0625 | L5: 0.0625 | M5: 0.0625 | N5: 0.066666667 | O5: 0.066666667 | P5: 0.066666667 | Q5: 0.03 | R5: 0.03 | S5: 0.03 | T5: 0.03 | U5: 0.03 | V5: 0.05 | W5: 0 | X5: 0 | Y5: 0 | Z5: 0 | AA5: 0 | AB5: 0
B7: Year | E7: 2025 | F7: =E7+1 -> 2026 | G7: =F7+1 -> 2027 | H7: =G7+1 -> 2028 | I7: =H7+1 -> 2029 | J7: =I7+1 -> 2030 | K7: =J7+1 -> 2031 | L7: =K7+1 -> 2032 | M7: =L7+1 -> 2033 | ... AS7: =AR7+1 -> 2065
B8: Inflation | C8: Source: IMF | E8: 0.049 | F8: 0.036 | G8: 0.032 | H8: 0.03 | I8: 0.03 | J8: 0.025 | K8: 0.025 | L8: 0.025 | M8: 0.025 | N8: 0.025 | O8: 0.025 | P8: 0.025 | Q8: 0.025 | R8: 0.025 | S8: 0.025 | T8: 0.025 | U8: 0.025 | V8: 0.025 | W8: 0.025 | X8: 0.025 | Y8: 0.025 | Z8: 0.025 | AA8: 0.025 | AB8: 0.025 | AC8: 0.025 | AD8: 0.025 | AE8: 0.025 | AF8: 0.025 | AG8: 0.025 | AH8: 0.025 | AI8: 0.025 | AJ8: 0.025 | AK8: 0.025 | AL8: 0.025 | AM8: 0.025 | AN8: 0.025 | AO8: 0.025 | AP8: 0.025 | AQ8: 0.025 | AR8: 0.025 | AS8: 0.025

Sheet Model
B2: Timing | H2: Sum
B3: Period start | I3: 45931 | J3: =I4+1 -> 46023 | K3: =J4+1 -> 46113 | L3: =K4+1 -> 46204 | M3: =L4+1 -> 46296 | N3: =M4+1 -> 46388 | O3: =N4+1 -> 46478 | P3: =O4+1 -> 46569 | Q3: =P4+1 -> 46661 | ... FM3: =FL4+1 -> 60541
B4: Period end | I4: =EOMONTH(I3,2) -> 46022 | J4: =EOMONTH(J3,2) -> 46112 | K4: =EOMONTH(K3,2) -> 46203 | L4: =EOMONTH(L3,2) -> 46295 | M4: =EOMONTH(M3,2) -> 46387 | N4: =EOMONTH(N3,2) -> 46477 | O4: =EOMONTH(O3,2) -> 46568 | P4: =EOMONTH(P3,2) -> 46660 | ... FM4: =EOMONTH(FM3,2) -> 60632
B5: Days in period | I5: =I4 - I3 + 1 -> 92 | J5: =J4 - J3 + 1 -> 90 | K5: =K4 - K3 + 1 -> 91 | L5: =L4 - L3 + 1 -> 92 | M5: =M4 - M3 + 1 -> 92 | N5: =N4 - N3 + 1 -> 90 | O5: =O4 - O3 + 1 -> 91 | P5: =P4 - P3 + 1 -> 92 | ... FM5: =FM4 - FM3 + 1 -> 92
B6: Days in year | I6: =DATE(I9, 12, 31) - DATE(I9, 1, 1) +1 -> 365 | J6: =DATE(J9, 12, 31) - DATE(J9, 1, 1) +1 -> 365 | K6: =DATE(K9, 12, 31) - DATE(K9, 1, 1) +1 -> 365 | L6: =DATE(L9, 12, 31) - DATE(L9, 1, 1) +1 -> 365 | M6: =DATE(M9, 12, 31) - DATE(M9, 1, 1) +1 -> 365 | N6: =DATE(N9, 12, 31) - DATE(N9, 1, 1) +1 -> 365 | O6: =DATE(O9, 12, 31) - DATE(O9, 1, 1) +1 -> 365 | P6: =DATE(P9, 12, 31) - DATE(P9, 1, 1) +1 -> 365 | ... FM6: =DATE(FM9, 12, 31) - DATE(FM9, 1, 1) +1 -> 365
B7: Fraction of year | I7: =I5/I6 -> 0.25205479 | J7: =J5/J6 -> 0.24657534 | K7: =K5/K6 -> 0.24931507 | L7: =L5/L6 -> 0.25205479 | M7: =M5/M6 -> 0.25205479 | N7: =N5/N6 -> 0.24657534 | O7: =O5/O6 -> 0.24931507 | P7: =P5/P6 -> 0.25205479 | ... FM7: =FM5/FM6 -> 0.25205479
B8: Quarter | I8: =MONTH(I4) / 3 -> 4 | J8: =MONTH(J4) / 3 -> 1 | K8: =MONTH(K4) / 3 -> 2 | L8: =MONTH(L4) / 3 -> 3 | M8: =MONTH(M4) / 3 -> 4 | N8: =MONTH(N4) / 3 -> 1 | O8: =MONTH(O4) / 3 -> 2 | P8: =MONTH(P4) / 3 -> 3 | ... FM8: =MONTH(FM4) / 3 -> 4
B9: Year | I9: =YEAR(I4) -> 2025 | J9: =YEAR(J4) -> 2026 | K9: =YEAR(K4) -> 2026 | L9: =YEAR(L4) -> 2026 | M9: =YEAR(M4) -> 2026 | N9: =YEAR(N4) -> 2027 | O9: =YEAR(O4) -> 2027 | P9: =YEAR(P4) -> 2027 | ... FM9: =YEAR(FM4) -> 2065
B11: Flags
B12: Construction | C12: % | D12: =Stat_Inp!F29 -> 46173 | E12: =Stat_Inp!F31 -> 46721 | I12: =MAX(0,(MIN($E12,I$4)-MAX($D12,I$3)+1)/I$5)+((($D12-$E12+1)/I$5)*($D12>I$3)*($E12<I$4)) -> 0 | J12: =MAX(0,(MIN($E12,J$4)-MAX($D12,J$3)+1)/J$5)+((($D12-$E12+1)/J$5)*($D12>J$3)*($E12<J$4)) -> 0 | K12: =MAX(0,(MIN($E12,K$4)-MAX($D12,K$3)+1)/K$5)+((($D12-$E12+1)/K$5)*($D12>K$3)*($E12<K$4)) -> 0.34065934 | L12: =MAX(0,(MIN($E12,L$4)-MAX($D12,L$3)+1)/L$5)+((($D12-$E12+1)/L$5)*($D12>L$3)*($E12<L$4)) -> 1 | M12: =MAX(0,(MIN($E12,M$4)-MAX($D12,M$3)+1)/M$5)+((($D12-$E12+1)/M$5)*($D12>M$3)*($E12<M$4)) -> 1 | N12: =MAX(0,(MIN($E12,N$4)-MAX($D12,N$3)+1)/N$5)+((($D12-$E12+1)/N$5)*($D12>N$3)*($E12<N$4)) -> 1 | O12: =MAX(0,(MIN($E12,O$4)-MAX($D12,O$3)+1)/O$5)+((($D12-$E12+1)/O$5)*($D12>O$3)*($E12<O$4)) -> 1 | P12: =MAX(0,(MIN($E12,P$4)-MAX($D12,P$3)+1)/P$5)+((($D12-$E12+1)/P$5)*($D12>P$3)*($E12<P$4)) -> 1 | ... FM12: =MAX(0,(MIN($E12,FM$4)-MAX($D12,FM$3)+1)/FM$5)+((($D12-$E12+1)/FM$5)*($D12>FM$3)*($E12<FM$4)) -> 0
B13: Construction month | C13: Month | H13: 0 | I13: =IF(I12, H13 + ROUND( I12 * (MONTH(I4) - MONTH(I3) +1), 0), 0) -> 0 | J13: =IF(J12, I13 + ROUND( J12 * (MONTH(J4) - MONTH(J3) +1), 0), 0) -> 0 | K13: =IF(K12, J13 + ROUND( K12 * (MONTH(K4) - MONTH(K3) +1), 0), 0) -> 1 | L13: =IF(L12, K13 + ROUND( L12 * (MONTH(L4) - MONTH(L3) +1), 0), 0) -> 4 | M13: =IF(M12, L13 + ROUND( M12 * (MONTH(M4) - MONTH(M3) +1), 0), 0) -> 7 | N13: =IF(N12, M13 + ROUND( N12 * (MONTH(N4) - MONTH(N3) +1), 0), 0) -> 10 | O13: =IF(O12, N13 + ROUND( O12 * (MONTH(O4) - MONTH(O3) +1), 0), 0) -> 13 | P13: =IF(P12, O13 + ROUND( P12 * (MONTH(P4) - MONTH(P3) +1), 0), 0) -> 16 | ... FM13: =IF(FM12, FL13 + ROUND( FM12 * (MONTH(FM4) - MONTH(FM3) +1), 0), 0) -> 0
B14: Operations | C14: % | D14: =Stat_Inp!F42 -> 46722 | E14: =Stat_Inp!F44 -> 59536 | H14: 0 | I14: =MAX(0,(MIN($E14,I$4)-MAX($D14,I$3)+1)/I$5)+((($D14-$E14+1)/I$5)*($D14>I$3)*($E14<I$4)) -> 0 | J14: =MAX(0,(MIN($E14,J$4)-MAX($D14,J$3)+1)/J$5)+((($D14-$E14+1)/J$5)*($D14>J$3)*($E14<J$4)) -> 0 | K14: =MAX(0,(MIN($E14,K$4)-MAX($D14,K$3)+1)/K$5)+((($D14-$E14+1)/K$5)*($D14>K$3)*($E14<K$4)) -> 0 | L14: =MAX(0,(MIN($E14,L$4)-MAX($D14,L$3)+1)/L$5)+((($D14-$E14+1)/L$5)*($D14>L$3)*($E14<L$4)) -> 0 | M14: =MAX(0,(MIN($E14,M$4)-MAX($D14,M$3)+1)/M$5)+((($D14-$E14+1)/M$5)*($D14>M$3)*($E14<M$4)) -> 0 | N14: =MAX(0,(MIN($E14,N$4)-MAX($D14,N$3)+1)/N$5)+((($D14-$E14+1)/N$5)*($D14>N$3)*($E14<N$4)) -> 0 | O14: =MAX(0,(MIN($E14,O$4)-MAX($D14,O$3)+1)/O$5)+((($D14-$E14+1)/O$5)*($D14>O$3)*($E14<O$4)) -> 0 | P14: =MAX(0,(MIN($E14,P$4)-MAX($D14,P$3)+1)/P$5)+((($D14-$E14+1)/P$5)*($D14>P$3)*($E14<P$4)) -> 0 | ... FM14: =MAX(0,(MIN($E14,FM$4)-MAX($D14,FM$3)+1)/FM$5)+((($D14-$E14+1)/FM$5)*($D14>FM$3)*($E14<FM$4)) -> 0
B15: First operating period | C15: Flag | I15: =N(AND(H14=0,I14>0)) -> 0 | J15: =N(AND(I14=0,J14>0)) -> 0 | K15: =N(AND(J14=0,K14>0)) -> 0 | L15: =N(AND(K14=0,L14>0)) -> 0 | M15: =N(AND(L14=0,M14>0)) -> 0 | N15: =N(AND(M14=0,N14>0)) -> 0 | O15: =N(AND(N14=0,O14>0)) -> 0 | P15: =N(AND(O14=0,P14>0)) -> 0 | ... FM15: =N(AND(FL14=0,FM14>0)) -> 0
B16: Last operating period | C16: Flag | I16: =N(AND(I14>0,J14=0)) -> 0 | J16: =N(AND(J14>0,K14=0)) -> 0 | K16: =N(AND(K14>0,L14=0)) -> 0 | L16: =N(AND(L14>0,M14=0)) -> 0 | M16: =N(AND(M14>0,N14=0)) -> 0 | N16: =N(AND(N14>0,O14=0)) -> 0 | O16: =N(AND(O14>0,P14=0)) -> 0 | P16: =N(AND(P14>0,Q14=0)) -> 0 | ... FM16: =N(AND(FM14>0,FN14=0)) -> 0
B17: Operations year | C17: Count | I17: =IF(I14, I9 - YEAR($D14) +1, 0) -> 0 | J17: =IF(J14, J9 - YEAR($D14) +1, 0) -> 0 | K17: =IF(K14, K9 - YEAR($D14) +1, 0) -> 0 | L17: =IF(L14, L9 - YEAR($D14) +1, 0) -> 0 | M17: =IF(M14, M9 - YEAR($D14) +1, 0) -> 0 | N17: =IF(N14, N9 - YEAR($D14) +1, 0) -> 0 | O17: =IF(O14, O9 - YEAR($D14) +1, 0) -> 0 | P17: =IF(P14, P9 - YEAR($D14) +1, 0) -> 0 | ... FM17: =IF(FM14, FM9 - YEAR($D14) +1, 0) -> 0
B19: Inflation
B20: Annual inflation | C20: % | I20: =SUMIFS(Dyn_Inp!$E$8:$AS$8, Dyn_Inp!$E$7:$AS$7, I$9) -> 0.049 | J20: =SUMIFS(Dyn_Inp!$E$8:$AS$8, Dyn_Inp!$E$7:$AS$7, J$9) -> 0.036 | K20: =SUMIFS(Dyn_Inp!$E$8:$AS$8, Dyn_Inp!$E$7:$AS$7, K$9) -> 0.036 | L20: =SUMIFS(Dyn_Inp!$E$8:$AS$8, Dyn_Inp!$E$7:$AS$7, L$9) -> 0.036 | M20: =SUMIFS(Dyn_Inp!$E$8:$AS$8, Dyn_Inp!$E$7:$AS$7, M$9) -> 0.036 | N20: =SUMIFS(Dyn_Inp!$E$8:$AS$8, Dyn_Inp!$E$7:$AS$7, N$9) -> 0.032 | O20: =SUMIFS(Dyn_Inp!$E$8:$AS$8, Dyn_Inp!$E$7:$AS$7, O$9) -> 0.032 | P20: =SUMIFS(Dyn_Inp!$E$8:$AS$8, Dyn_Inp!$E$7:$AS$7, P$9) -> 0.032 | ... FM20: =SUMIFS(Dyn_Inp!$E$8:$AS$8, Dyn_Inp!$E$7:$AS$7, FM$9) -> 0.025
B21: Step-up flag | C21: Flag | D21: =Stat_Inp!F24 -> 1 | I21: =N($D21 = I8) -> 0 | J21: =N($D21 = J8) -> 1 | K21: =N($D21 = K8) -> 0 | L21: =N($D21 = L8) -> 0 | M21: =N($D21 = M8) -> 0 | N21: =N($D21 = N8) -> 1 | O21: =N($D21 = O8) -> 0 | P21: =N($D21 = P8) -> 0 | ... FM21: =N($D21 = FM8) -> 0
B22: Inflation in period | C22: % | I22: =I20 * I21 -> 0 | J22: =J20 * J21 -> 0.036 | K22: =K20 * K21 -> 0 | L22: =L20 * L21 -> 0 | M22: =M20 * M21 -> 0 | N22: =N20 * N21 -> 0.032 | O22: =O20 * O21 -> 0 | P22: =P20 * P21 -> 0 | ... FM22: =FM20 * FM21 -> 0
B23: Inflation index (all items) | C23: Index | H23: 1 | I23: =H23 * (1 + I22) -> 1 | J23: =I23 * (1 + J22) -> 1.036 | K23: =J23 * (1 + K22) -> 1.036 | L23: =K23 * (1 + L22) -> 1.036 | M23: =L23 * (1 + M22) -> 1.036 | N23: =M23 * (1 + N22) -> 1.069152 | O23: =N23 * (1 + O22) -> 1.069152 | P23: =O23 * (1 + P22) -> 1.069152 | ... FM23: =FL23 * (1 + FM22) -> 2.7591357
B25: Valuation
B27: Construction flag | C27: Flag | H27: =SUM(I27:FM27) -> 1 | I27: =N(AND(I$3<=$D12,I$4>=$D12)) -> 0 | J27: =N(AND(J3<=$D12,J4>=$D12)) -> 0 | K27: =N(AND(K3<=$D12,K4>=$D12)) -> 1 | L27: =N(AND(L3<=$D12,L4>=$D12)) -> 0 | M27: =N(AND(M3<=$D12,M4>=$D12)) -> 0 | N27: =N(AND(N3<=$D12,N4>=$D12)) -> 0 | O27: =N(AND(O3<=$D12,O4>=$D12)) -> 0 | P27: =N(AND(P3<=$D12,P4>=$D12)) -> 0 | Q27: =N(AND(Q3<=$D12,Q4>=$D12)) -> 0 | ... FM27: =N(AND(FM3<=$D12,FM4>=$D12)) -> 0
B28: Acquisition flag | C28: Flag | D28: =Stat_Inp!F25 -> 46173 | H28: =SUM(I28:FM28) -> 1 | I28: =N(AND(I$3<=$D28,I$4>=$D28)) -> 0 | J28: =N(AND(J$3<=$D28,J$4>=$D28)) -> 0 | K28: =N(AND(K$3<=$D28,K$4>=$D28)) -> 1 | L28: =N(AND(L$3<=$D28,L$4>=$D28)) -> 0 | M28: =N(AND(M$3<=$D28,M$4>=$D28)) -> 0 | N28: =N(AND(N$3<=$D28,N$4>=$D28)) -> 0 | O28: =N(AND(O$3<=$D28,O$4>=$D28)) -> 0 | P28: =N(AND(P$3<=$D28,P$4>=$D28)) -> 0 | ... FM28: =N(AND(FM$3<=$D28,FM$4>=$D28)) -> 0
B29: Ownership flag | C29: Flag | H29: =SUM(I29:FM29) -> 159 | I29: =SUM($I28:I28) -> 0 | J29: =SUM($I28:J28) -> 0 | K29: =SUM($I28:K28) -> 1 | L29: =SUM($I28:L28) -> 1 | M29: =SUM($I28:M28) -> 1 | N29: =SUM($I28:N28) -> 1 | O29: =SUM($I28:O28) -> 1 | P29: =SUM($I28:P28) -> 1 | ... FM29: =SUM($I28:FM28) -> 1
B31: EBITDA | C31: €k | H31: =SUM(I31:FM31) -> 128735.67 | I31: =I50 -> 0 | J31: =J50 -> 0 | K31: =K50 -> -8.4469479 | L31: =L50 -> -25.068362 | M31: =M50 -> -25.068362 | N31: =N50 -> -25.308146 | O31: =O50 -> -25.589348 | P31: =P50 -> -25.870549 | ... FM31: =FM50 -> 0
B32: Cash taxes | C32: €k | H32: =SUM(I32:FM32) -> 8758.8599 | I32: =I118 -> 0 | J32: =J118 -> 0 | K32: =K118 -> 0 | L32: =L118 -> 0 | M32: =M118 -> 0 | N32: =N118 -> 0 | O32: =O118 -> 0 | P32: =P118 -> 0 | ... FM32: =FM118 -> 0
B33: ∆ NWC | C33: €k | H33: =SUM(I33:FM33) -> 0 | I33: =I99 -> 0 | J33: =J99 -> 0 | K33: =K99 -> 2.7847081 | L33: =L99 -> 5.3897576 | M33: =M99 -> 0 | N33: =N99 -> 0.2615829 | O33: =O99 -> 0 | P33: =P99 -> 0 | ... FM33: =FM99 -> 0
B34: CAPEX | C34: €k | H34: =SUM(I34:FM34) -> -31415 | I34: =-1 * I71 -> 0 | J34: =-1 * J71 -> 0 | K34: =-1 * K71 -> -3141.5 | L34: =-1 * L71 -> -5890.3125 | M34: =-1 * M71 -> -5890.3125 | N34: =-1 * N71 -> -6021.2083 | O34: =-1 * O71 -> -5131.1167 | P34: =-1 * P71 -> -2827.35 | ... FM34: =-1 * FM71 -> 0
B35: Free cash flow to the firm | C35: €k | H35: =SUM(I35:FM35) -> 106079.53 | I35: =SUM(I31:I34) -> 0 | J35: =SUM(J31:J34) -> 0 | K35: =SUM(K31:K34) -> -3147.1622 | L35: =SUM(L31:L34) -> -5909.9911 | M35: =SUM(M31:M34) -> -5915.3809 | N35: =SUM(N31:N34) -> -6046.2549 | O35: =SUM(O31:O34) -> -5156.706 | P35: =SUM(P31:P34) -> -2853.2205 | ... FM35: =SUM(FM31:FM34) -> 0
B37: Project IRR | C37: % | D37: =SUM(I37:FM37) -> 0.093844097 | I37: =IFERROR(I$27 * XIRR(I35:$FM35, I$4:$FM$4,0), 0) -> 0 | J37: =IFERROR(J$27 * XIRR(J35:$FM35, J$4:$FM$4,0), 0) -> 0 | K37: =IFERROR(K$27 * XIRR(K35:$FM35, K$4:$FM$4,0), 0) -> 0.093844097 | L37: =IFERROR(L$27 * XIRR(L35:$FM35, L$4:$FM$4,0), 0) -> 0 | M37: =IFERROR(M$27 * XIRR(M35:$FM35, M$4:$FM$4,0), 0) -> 0 | N37: =IFERROR(N$27 * XIRR(N35:$FM35, N$4:$FM$4,0), 0) -> 0 | O37: =IFERROR(O$27 * XIRR(O35:$FM35, O$4:$FM$4,0), 0) -> 0 | P37: =IFERROR(P$27 * XIRR(P35:$FM35, P$4:$FM$4,0), 0) -> 0 | ... FM37: =IFERROR(FM$27 * XIRR(FM35:$FM35, FM$4:$FM$4,0), 0) -> 0
B39: Buyer return
B40: Purchase price | C40: €k | D40: =Stat_Inp!F26 -> 90 | H40: =SUM(I40:FM40) -> -5490 | I40: =-1 * $D40 * $D61 * I28 -> 0 | J40: =-1 * $D40 * $D61 * J28 -> 0 | K40: =-1 * $D40 * $D61 * K28 -> -5490 | L40: =-1 * $D40 * $D61 * L28 -> 0 | M40: =-1 * $D40 * $D61 * M28 -> 0 | N40: =-1 * $D40 * $D61 * N28 -> 0 | O40: =-1 * $D40 * $D61 * O28 -> 0 | P40: =-1 * $D40 * $D61 * P28 -> 0 | ... FM40: =-1 * $D40 * $D61 * FM28 -> 0
B41: Post-purchase cash flows | C41: €k | H41: =SUM(I41:FM41) -> 106079.53 | I41: =I29 * I35 -> 0 | J41: =J29 * J35 -> 0 | K41: =K29 * K35 -> -3147.1622 | L41: =L29 * L35 -> -5909.9911 | M41: =M29 * M35 -> -5915.3809 | N41: =N29 * N35 -> -6046.2549 | O41: =O29 * O35 -> -5156.706 | P41: =P29 * P35 -> -2853.2205 | ... FM41: =FM29 * FM35 -> 0
B42: Net cash flows | C42: €k | H42: =SUM(I42:FM42) -> 100589.53 | I42: =SUM(I40:I41) -> 0 | J42: =SUM(J40:J41) -> 0 | K42: =SUM(K40:K41) -> -8637.1622 | L42: =SUM(L40:L41) -> -5909.9911 | M42: =SUM(M40:M41) -> -5915.3809 | N42: =SUM(N40:N41) -> -6046.2549 | O42: =SUM(O40:O41) -> -5156.706 | P42: =SUM(P40:P41) -> -2853.2205 | ... FM42: =SUM(FM40:FM41) -> 0
B44: Buyer IRR | C44: % | D44: =SUM(I44:FM44) -> 0.079572534 | I44: =IFERROR(I$27 * XIRR(I42:$FM42, I$4:$FM$4,0), 0) -> 0 | J44: =IFERROR(J$27 * XIRR(J42:$FM42, J$4:$FM$4,0), 0) -> 0 | K44: =IFERROR(K$27 * XIRR(K42:$FM42, K$4:$FM$4,0), 0) -> 0.079572534 | L44: =IFERROR(L$27 * XIRR(L42:$FM42, L$4:$FM$4,0), 0) -> 0 | M44: =IFERROR(M$27 * XIRR(M42:$FM42, M$4:$FM$4,0), 0) -> 0 | N44: =IFERROR(N$27 * XIRR(N42:$FM42, N$4:$FM$4,0), 0) -> 0 | O44: =IFERROR(O$27 * XIRR(O42:$FM42, O$4:$FM$4,0), 0) -> 0 | P44: =IFERROR(P$27 * XIRR(P42:$FM42, P$4:$FM$4,0), 0) -> 0 | ... FM44: =IFERROR(FM$27 * XIRR(FM42:$FM42, FM$4:$FM$4,0), 0) -> 0
B47: Income statement
B48: Revenue | C48: €k | H48: =SUM(I48:FM48) -> 202885.33 | I48: =I87 -> 0 | J48: =J87 -> 0 | K48: =K87 -> 0 | L48: =L87 -> 0 | M48: =M87 -> 0 | N48: =N87 -> 0 | O48: =O87 -> 0 | P48: =P87 -> 0 | ... FM48: =FM87 -> 0
B49: Operating costs | C49: €k | H49: =SUM(I49:FM49) -> -74149.668 | I49: =-1 * I93 -> 0 | J49: =-1 * J93 -> 0 | K49: =-1 * K93 -> -8.4469479 | L49: =-1 * L93 -> -25.068362 | M49: =-1 * M93 -> -25.068362 | N49: =-1 * N93 -> -25.308146 | O49: =-1 * O93 -> -25.589348 | P49: =-1 * P93 -> -25.870549 | ... FM49: =-1 * FM93 -> 0
B50: EBITDA | C50: €k | H50: =SUM(I50:FM50) -> 128735.67 | I50: =SUM(I48:I49) -> 0 | J50: =SUM(J48:J49) -> 0 | K50: =SUM(K48:K49) -> -8.4469479 | L50: =SUM(L48:L49) -> -25.068362 | M50: =SUM(M48:M49) -> -25.068362 | N50: =SUM(N48:N49) -> -25.308146 | O50: =SUM(O48:O49) -> -25.589348 | P50: =SUM(P48:P49) -> -25.870549 | ... FM50: =SUM(FM48:FM49) -> 0
B51: EBITDA margin | C51: % | I51: =IFERROR(I50 / I48, 0) -> 0 | J51: =IFERROR(J50 / J48, 0) -> 0 | K51: =IFERROR(K50 / K48, 0) -> 0 | L51: =IFERROR(L50 / L48, 0) -> 0 | M51: =IFERROR(M50 / M48, 0) -> 0 | N51: =IFERROR(N50 / N48, 0) -> 0 | O51: =IFERROR(O50 / O48, 0) -> 0 | P51: =IFERROR(P50 / P48, 0) -> 0 | ... FM51: =IFERROR(FM50 / FM48, 0) -> 0
B53: Depreciation | C53: €k | H53: =SUM(I53:FM53) -> -31415 | I53: =I105 -> 0 | J53: =J105 -> 0 | K53: =K105 -> 0 | L53: =L105 -> 0 | M53: =M105 -> 0 | N53: =N105 -> 0 | O53: =O105 -> 0 | P53: =P105 -> 0 | ... FM53: =FM105 -> 0
B54: EBT | C54: €k | H54: =SUM(I54:FM54) -> 97320.666 | I54: =SUM(I50,I53) -> 0 | J54: =SUM(J50,J53) -> 0 | K54: =SUM(K50,K53) -> -8.4469479 | L54: =SUM(L50,L53) -> -25.068362 | M54: =SUM(M50,M53) -> -25.068362 | N54: =SUM(N50,N53) -> -25.308146 | O54: =SUM(O50,O53) -> -25.589348 | P54: =SUM(P50,P53) -> -25.870549 | ... FM54: =SUM(FM50,FM53) -> 0
B56: Tax | C56: €k | H56: =SUM(I56:FM56) -> -8771.0416 | I56: =-1 * MAX(I110, 0) -> 0 | J56: =-1 * MAX(J110, 0) -> 0 | K56: =-1 * MAX(K110, 0) -> 0 | L56: =-1 * MAX(L110, 0) -> 0 | M56: =-1 * MAX(M110, 0) -> 0 | N56: =-1 * MAX(N110, 0) -> 0 | O56: =-1 * MAX(O110, 0) -> 0 | P56: =-1 * MAX(P110, 0) -> 0 | ... FM56: =-1 * MAX(FM110, 0) -> 0
B57: Net income | C57: €k | H57: =SUM(I57:FM57) -> 88549.624 | I57: =SUM(I54,I56) -> 0 | J57: =SUM(J54,J56) -> 0 | K57: =SUM(K54,K56) -> -8.4469479 | L57: =SUM(L54,L56) -> -25.068362 | M57: =SUM(M54,M56) -> -25.068362 | N57: =SUM(N54,N56) -> -25.308146 | O57: =SUM(O54,O56) -> -25.589348 | P57: =SUM(P54,P56) -> -25.870549 | ... FM57: =SUM(FM54,FM56) -> 0
B59: Capacity & generation
B60: Capacity build-out flag | C60: Flag | I60: =N(AND(SUM($I15:I15)=1,SUM($H16:H16)=0)) -> 0 | J60: =N(AND(SUM($I15:J15)=1,SUM($H16:I16)=0)) -> 0 | K60: =N(AND(SUM($I15:K15)=1,SUM($H16:J16)=0)) -> 0 | L60: =N(AND(SUM($I15:L15)=1,SUM($H16:K16)=0)) -> 0 | M60: =N(AND(SUM($I15:M15)=1,SUM($H16:L16)=0)) -> 0 | N60: =N(AND(SUM($I15:N15)=1,SUM($H16:M16)=0)) -> 0 | O60: =N(AND(SUM($I15:O15)=1,SUM($H16:N16)=0)) -> 0 | P60: =N(AND(SUM($I15:P15)=1,SUM($H16:O16)=0)) -> 0 | ... FM60: =N(AND(SUM($I15:FM15)=1,SUM($H16:FL16)=0)) -> 0
B61: Capacity build-out | C61: MWp | D61: =Stat_Inp!F50 -> 61 | I61: =$D61 * I60 -> 0 | J61: =$D61 * J60 -> 0 | K61: =$D61 * K60 -> 0 | L61: =$D61 * L60 -> 0 | M61: =$D61 * M60 -> 0 | N61: =$D61 * N60 -> 0 | O61: =$D61 * O60 -> 0 | P61: =$D61 * P60 -> 0 | ... FM61: =$D61 * FM60 -> 0
B63: Generation pre-availability, degradation | C63: MWh | D63: =Stat_Inp!F51 -> 1250 | I63: =$D63 * I7 * I14 * I61 -> 0 | J63: =$D63 * J7 * J14 * J61 -> 0 | K63: =$D63 * K7 * K14 * K61 -> 0 | L63: =$D63 * L7 * L14 * L61 -> 0 | M63: =$D63 * M7 * M14 * M61 -> 0 | N63: =$D63 * N7 * N14 * N61 -> 0 | O63: =$D63 * O7 * O14 * O61 -> 0 | P63: =$D63 * P7 * P14 * P61 -> 0 | ... FM63: =$D63 * FM7 * FM14 * FM61 -> 0
B64: Availability factor | C64: % | D64: =Stat_Inp!F54 -> 0.995 | I64: =$D64 -> 0.995 | J64: =$D64 -> 0.995 | K64: =$D64 -> 0.995 | L64: =$D64 -> 0.995 | M64: =$D64 -> 0.995 | N64: =$D64 -> 0.995 | O64: =$D64 -> 0.995 | P64: =$D64 -> 0.995 | ... FM64: =$D64 -> 0.995
B65: Degradation factor | C65: % | D65: =Stat_Inp!F55 -> 0.003 | I65: =IF(I14, IF(I15, 1, H65 - ($D65 * I7 * I14)), 0) -> 0 | J65: =IF(J14, IF(J15, 1, I65 - ($D65 * J7 * J14)), 0) -> 0 | K65: =IF(K14, IF(K15, 1, J65 - ($D65 * K7 * K14)), 0) -> 0 | L65: =IF(L14, IF(L15, 1, K65 - ($D65 * L7 * L14)), 0) -> 0 | M65: =IF(M14, IF(M15, 1, L65 - ($D65 * M7 * M14)), 0) -> 0 | N65: =IF(N14, IF(N15, 1, M65 - ($D65 * N7 * N14)), 0) -> 0 | O65: =IF(O14, IF(O15, 1, N65 - ($D65 * O7 * O14)), 0) -> 0 | P65: =IF(P14, IF(P15, 1, O65 - ($D65 * P7 * P14)), 0) -> 0 | ... FM65: =IF(FM14, IF(FM15, 1, FL65 - ($D65 * FM7 * FM14)), 0) -> 0
B66: Net generation | C66: MWh | H66: =SUM(I66:FM66) -> 2521445.2 | I66: =PRODUCT(I63:I65) -> 0 | J66: =PRODUCT(J63:J65) -> 0 | K66: =PRODUCT(K63:K65) -> 0 | L66: =PRODUCT(L63:L65) -> 0 | M66: =PRODUCT(M63:M65) -> 0 | N66: =PRODUCT(N63:N65) -> 0 | O66: =PRODUCT(O63:O65) -> 0 | P66: =PRODUCT(P63:P65) -> 0 | ... FM66: =PRODUCT(FM63:FM65) -> 0
B68: Construction (not indexed)
B69: Construction timetable | C69: % | H69: =SUM(I69:FM69) -> 1 | I69: {=SUMPRODUCT(Dyn_Inp!$E$5:$AB$5, (Dyn_Inp!$E$4:$AB$4 <=I13) * (Dyn_Inp!$E$4:$AB$4 > H13))} -> 0 | J69: {=SUMPRODUCT(Dyn_Inp!$E$5:$AB$5, (Dyn_Inp!$E$4:$AB$4 <=J13) * (Dyn_Inp!$E$4:$AB$4 > I13))} -> 0 | K69: {=SUMPRODUCT(Dyn_Inp!$E$5:$AB$5, (Dyn_Inp!$E$4:$AB$4 <=K13) * (Dyn_Inp!$E$4:$AB$4 > J13))} -> 0.1 | L69: {=SUMPRODUCT(Dyn_Inp!$E$5:$AB$5, (Dyn_Inp!$E$4:$AB$4 <=L13) * (Dyn_Inp!$E$4:$AB$4 > K13))} -> 0.1875 | M69: {=SUMPRODUCT(Dyn_Inp!$E$5:$AB$5, (Dyn_Inp!$E$4:$AB$4 <=M13) * (Dyn_Inp!$E$4:$AB$4 > L13))} -> 0.1875 | N69: {=SUMPRODUCT(Dyn_Inp!$E$5:$AB$5, (Dyn_Inp!$E$4:$AB$4 <=N13) * (Dyn_Inp!$E$4:$AB$4 > M13))} -> 0.19166667 | O69: {=SUMPRODUCT(Dyn_Inp!$E$5:$AB$5, (Dyn_Inp!$E$4:$AB$4 <=O13) * (Dyn_Inp!$E$4:$AB$4 > N13))} -> 0.16333333 | P69: {=SUMPRODUCT(Dyn_Inp!$E$5:$AB$5, (Dyn_Inp!$E$4:$AB$4 <=P13) * (Dyn_Inp!$E$4:$AB$4 > O13))} -> 0.09 | ... FM69: {=SUMPRODUCT(Dyn_Inp!$E$5:$AB$5, (Dyn_Inp!$E$4:$AB$4 <=FM13) * (Dyn_Inp!$E$4:$AB$4 > FL13))} -> 0
B71: CAPEX | C71: €k | D71: =Stat_Inp!F34 -> 515 | H71: =SUM(I71:FM71) -> 31415 | I71: =$D71 * $D61 * I69 -> 0 | J71: =$D71 * $D61 * J69 -> 0 | K71: =$D71 * $D61 * K69 -> 3141.5 | L71: =$D71 * $D61 * L69 -> 5890.3125 | M71: =$D71 * $D61 * M69 -> 5890.3125 | N71: =$D71 * $D61 * N69 -> 6021.2083 | O71: =$D71 * $D61 * O69 -> 5131.1167 | P71: =$D71 * $D61 * P69 -> 2827.35 | ... FM71: =$D71 * $D61 * FM69 -> 0
B73: Revenue
B74: Volume | C74: MWh | H74: =SUM(I74:FM74) -> 2521445.2 | I74: =I66 -> 0 | J74: =J66 -> 0 | K74: =K66 -> 0 | L74: =L66 -> 0 | M74: =M66 -> 0 | N74: =N66 -> 0 | O74: =O66 -> 0 | P74: =P66 -> 0 | ... FM74: =FM66 -> 0
B76: Real prices
B77: Merchant price | C77: €/MWh | D77: =Stat_Inp!F66 -> 45 | I77: =$D77 -> 45 | J77: =$D77 -> 45 | K77: =$D77 -> 45 | L77: =$D77 -> 45 | M77: =$D77 -> 45 | N77: =$D77 -> 45 | O77: =$D77 -> 45 | P77: =$D77 -> 45 | ... FM77: =$D77 -> 45
B78: GoO price | C78: €/MWh | D78: =Stat_Inp!F67 -> 1.75 | I78: =$D78 -> 1.75 | J78: =$D78 -> 1.75 | K78: =$D78 -> 1.75 | L78: =$D78 -> 1.75 | M78: =$D78 -> 1.75 | N78: =$D78 -> 1.75 | O78: =$D78 -> 1.75 | P78: =$D78 -> 1.75 | ... FM78: =$D78 -> 1.75
B80: Nominal prices
B81: =B77 -> Merchant price | C81: €/MWh | I81: =I77 * I$23 -> 45 | J81: =J77 * J$23 -> 46.62 | K81: =K77 * K$23 -> 46.62 | L81: =L77 * L$23 -> 46.62 | M81: =M77 * M$23 -> 46.62 | N81: =N77 * N$23 -> 48.11184 | O81: =O77 * O$23 -> 48.11184 | P81: =P77 * P$23 -> 48.11184 | ... FM81: =FM77 * FM$23 -> 124.16111
B82: =B78 -> GoO price | C82: €/MWh | I82: =I78 * I$23 -> 1.75 | J82: =J78 * J$23 -> 1.813 | K82: =K78 * K$23 -> 1.813 | L82: =L78 * L$23 -> 1.813 | M82: =M78 * M$23 -> 1.813 | N82: =N78 * N$23 -> 1.871016 | O82: =O78 * O$23 -> 1.871016 | P82: =P78 * P$23 -> 1.871016 | ... FM82: =FM78 * FM$23 -> 4.8284874
B84: Gross revenue
B85: =B77 -> Merchant price | C85: €k | H85: =SUM(I85:FM85) -> 195290.7 | I85: =I$74 * I81 / 1000 -> 0 | J85: =J$74 * J81 / 1000 -> 0 | K85: =K$74 * K81 / 1000 -> 0 | L85: =L$74 * L81 / 1000 -> 0 | M85: =M$74 * M81 / 1000 -> 0 | N85: =N$74 * N81 / 1000 -> 0 | O85: =O$74 * O81 / 1000 -> 0 | P85: =P$74 * P81 / 1000 -> 0 | ... FM85: =FM$74 * FM81 / 1000 -> 0
B86: =B78 -> GoO price | C86: €k | H86: =SUM(I86:FM86) -> 7594.6382 | I86: =I$74 * I82 / 1000 -> 0 | J86: =J$74 * J82 / 1000 -> 0 | K86: =K$74 * K82 / 1000 -> 0 | L86: =L$74 * L82 / 1000 -> 0 | M86: =M$74 * M82 / 1000 -> 0 | N86: =N$74 * N82 / 1000 -> 0 | O86: =O$74 * O82 / 1000 -> 0 | P86: =P$74 * P82 / 1000 -> 0 | ... FM86: =FM$74 * FM82 / 1000 -> 0
B87: Total gross revenue | C87: €k | H87: =SUM(I87:FM87) -> 202885.33 | I87: =SUM(I85:I86) -> 0 | J87: =SUM(J85:J86) -> 0 | K87: =SUM(K85:K86) -> 0 | L87: =SUM(L85:L86) -> 0 | M87: =SUM(M85:M86) -> 0 | N87: =SUM(N85:N86) -> 0 | O87: =SUM(O85:O86) -> 0 | P87: =SUM(P85:P86) -> 0 | ... FM87: =SUM(FM85:FM86) -> 0
B89: OPEX
B90: =Stat_Inp!B81 -> OPEX excl. balancing, land lease | C90: €k | D90: =Stat_Inp!F81 -> 14.96 | E90: €k / MW p.a. | F90: Inflated | H90: =SUM(I90:FM90) -> 55546.523 | I90: =$D90 * I7 * I14 * I61 * I23 -> 0 | J90: =$D90 * J7 * J14 * J61 * J23 -> 0 | K90: =$D90 * K7 * K14 * K61 * K23 -> 0 | L90: =$D90 * L7 * L14 * L61 * L23 -> 0 | M90: =$D90 * M7 * M14 * M61 * M23 -> 0 | N90: =$D90 * N7 * N14 * N61 * N23 -> 0 | O90: =$D90 * O7 * O14 * O61 * O23 -> 0 | P90: =$D90 * P7 * P14 * P61 * P23 -> 0 | ... FM90: =$D90 * FM7 * FM14 * FM61 * FM23 -> 0
B91: Balancing | C91: €k | D91: =Stat_Inp!F82 -> 5 | E91: €/MWh | F91: Not inflated | H91: =SUM(I91:FM91) -> 12607.226 | I91: =$D91 * I74 / 1000 -> 0 | J91: =$D91 * J74 / 1000 -> 0 | K91: =$D91 * K74 / 1000 -> 0 | L91: =$D91 * L74 / 1000 -> 0 | M91: =$D91 * M74 / 1000 -> 0 | N91: =$D91 * N74 / 1000 -> 0 | O91: =$D91 * O74 / 1000 -> 0 | P91: =$D91 * P74 / 1000 -> 0 | ... FM91: =$D91 * FM74 / 1000 -> 0
B92: Land lease | C92: €k | D92: =Stat_Inp!F83 -> 96 | E92: €k p.a. | F92: Inflated | H92: =SUM(I92:FM92) -> 5995.9193 | I92: =I7 * SUM(I12,I14) * $D92 * I23 -> 0 | J92: =J7 * SUM(J12,J14) * $D92 * J23 -> 0 | K92: =K7 * SUM(K12,K14) * $D92 * K23 -> 8.4469479 | L92: =L7 * SUM(L12,L14) * $D92 * L23 -> 25.068362 | M92: =M7 * SUM(M12,M14) * $D92 * M23 -> 25.068362 | N92: =N7 * SUM(N12,N14) * $D92 * N23 -> 25.308146 | O92: =O7 * SUM(O12,O14) * $D92 * O23 -> 25.589348 | P92: =P7 * SUM(P12,P14) * $D92 * P23 -> 25.870549 | ... FM92: =FM7 * SUM(FM12,FM14) * $D92 * FM23 -> 0
B93: Total OPEX | C93: €k | H93: =SUM(I93:FM93) -> 74149.668 | I93: =SUM(I90:I92) -> 0 | J93: =SUM(J90:J92) -> 0 | K93: =SUM(K90:K92) -> 8.4469479 | L93: =SUM(L90:L92) -> 25.068362 | M93: =SUM(M90:M92) -> 25.068362 | N93: =SUM(N90:N92) -> 25.308146 | O93: =SUM(O90:O92) -> 25.589348 | P93: =SUM(P90:P92) -> 25.870549 | ... FM93: =SUM(FM90:FM92) -> 0
B95: Working capital | D95: Days outstanding
B96: Trade receivables | C96: €k | D96: =Stat_Inp!F92 -> 30 | I96: =I87*($D96/I5) -> 0 | J96: =J87*($D96/J5) -> 0 | K96: =K87*($D96/K5) -> 0 | L96: =L87*($D96/L5) -> 0 | M96: =M87*($D96/M5) -> 0 | N96: =N87*($D96/N5) -> 0 | O96: =O87*($D96/O5) -> 0 | P96: =P87*($D96/P5) -> 0 | ... FM96: =FM87*($D96/FM5) -> 0
B97: Trade payables | C97: €k | D97: =Stat_Inp!F93 -> 30 | I97: =-1 * I93*($D97/I5) -> 0 | J97: =-1 * J93*($D97/J5) -> 0 | K97: =-1 * K93*($D97/K5) -> -2.7847081 | L97: =-1 * L93*($D97/L5) -> -8.1744658 | M97: =-1 * M93*($D97/M5) -> -8.1744658 | N97: =-1 * N93*($D97/N5) -> -8.4360487 | O97: =-1 * O93*($D97/O5) -> -8.4360487 | P97: =-1 * P93*($D97/P5) -> -8.4360487 | ... FM97: =-1 * FM93*($D97/FM5) -> 0
B98: Net working capital | C98: €k | I98: =SUM(I96:I97) -> 0 | J98: =SUM(J96:J97) -> 0 | K98: =SUM(K96:K97) -> -2.7847081 | L98: =SUM(L96:L97) -> -8.1744658 | M98: =SUM(M96:M97) -> -8.1744658 | N98: =SUM(N96:N97) -> -8.4360487 | O98: =SUM(O96:O97) -> -8.4360487 | P98: =SUM(P96:P97) -> -8.4360487 | ... FM98: =SUM(FM96:FM97) -> 0
B99: ∆ NWC | C99: €k | H99: =SUM(I99:FM99) -> 0 | I99: =H98-I98 -> 0 | J99: =I98-J98 -> 0 | K99: =J98-K98 -> 2.7847081 | L99: =K98-L98 -> 5.3897576 | M99: =L98-M98 -> 0 | N99: =M98-N98 -> 0.2615829 | O99: =N98-O98 -> 0 | P99: =O98-P98 -> 0 | ... FM99: =FL98-FM98 -> 0
B101: Taxes
B102: Depreciation
B103: Opening balance | C103: €k | I103: =H106 -> 0 | J103: =I106 -> 0 | K103: =J106 -> 0 | L103: =K106 -> 3141.5 | M103: =L106 -> 9031.8125 | N103: =M106 -> 14922.125 | O103: =N106 -> 20943.333 | P103: =O106 -> 26074.45 | ... FM103: =FL106 -> 0
B104: CAPEX addition | C104: €k | D104: Depreciation period | H104: =SUM(I104:FM104) -> 31415 | I104: =I71 -> 0 | J104: =J71 -> 0 | K104: =K71 -> 3141.5 | L104: =L71 -> 5890.3125 | M104: =M71 -> 5890.3125 | N104: =N71 -> 6021.2083 | O104: =O71 -> 5131.1167 | P104: =P71 -> 2827.35 | ... FM104: =FM71 -> 0
B105: Depreciation | C105: €k | D105: =Stat_Inp!F96 -> 30 | H105: =SUM(I105:FM105) -> -31415 | I105: =-1*MIN(($H104/$D105)*I7*I14,SUM(I103:I104)) -> 0 | J105: =-1*MIN(($H104/$D105)*J7*J14,SUM(J103:J104)) -> 0 | K105: =-1*MIN(($H104/$D105)*K7*K14,SUM(K103:K104)) -> 0 | L105: =-1*MIN(($H104/$D105)*L7*L14,SUM(L103:L104)) -> 0 | M105: =-1*MIN(($H104/$D105)*M7*M14,SUM(M103:M104)) -> 0 | N105: =-1*MIN(($H104/$D105)*N7*N14,SUM(N103:N104)) -> 0 | O105: =-1*MIN(($H104/$D105)*O7*O14,SUM(O103:O104)) -> 0 | P105: =-1*MIN(($H104/$D105)*P7*P14,SUM(P103:P104)) -> 0 | ... FM105: =-1*MIN(($H104/$D105)*FM7*FM14,SUM(FM103:FM104)) -> 0
B106: Closing balance | C106: €k | I106: =SUM(I103:I105) -> 0 | J106: =SUM(J103:J105) -> 0 | K106: =SUM(K103:K105) -> 3141.5 | L106: =SUM(L103:L105) -> 9031.8125 | M106: =SUM(M103:M105) -> 14922.125 | N106: =SUM(N103:N105) -> 20943.333 | O106: =SUM(O103:O105) -> 26074.45 | P106: =SUM(P103:P105) -> 28901.8 | ... FM106: =SUM(FM103:FM105) -> 0
B108: Tax calculation
B109: EBT | C109: €k | D109: CIT | H109: =SUM(I109:FM109) -> 97320.666 | I109: =I54 -> 0 | J109: =J54 -> 0 | K109: =K54 -> -8.4469479 | L109: =L54 -> -25.068362 | M109: =M54 -> -25.068362 | N109: =N54 -> -25.308146 | O109: =O54 -> -25.589348 | P109: =P54 -> -25.870549 | ... FM109: =FM54 -> 0
B110: Tax | C110: €k | D110: =Stat_Inp!F97 -> 0.09 | H110: =SUM(I110:FM110) -> 8758.8599 | I110: =$D110 * I109 -> 0 | J110: =$D110 * J109 -> 0 | K110: =$D110 * K109 -> -0.76022532 | L110: =$D110 * L109 -> -2.2561525 | M110: =$D110 * M109 -> -2.2561525 | N110: =$D110 * N109 -> -2.2777331 | O110: =$D110 * O109 -> -2.3030413 | P110: =$D110 * P109 -> -2.3283494 | ... FM110: =$D110 * FM109 -> 0
B112: Tax loss carryforward
B113: Opening balance | I113: =H116 -> 0 | J113: =I116 -> 0 | K113: =J116 -> 0 | L113: =K116 -> 0.76022532 | M113: =L116 -> 3.0163779 | N113: =M116 -> 5.2725304 | O113: =N116 -> 7.5502635 | P113: =O116 -> 9.8533048 | ... FM113: =FL116 -> 0
B114: Additions (negative tax) | H114: =SUM(I114:FM114) -> 12.181654 | I114: =-1 * MIN(I110, 0) -> 0 | J114: =-1 * MIN(J110, 0) -> 0 | K114: =-1 * MIN(K110, 0) -> 0.76022532 | L114: =-1 * MIN(L110, 0) -> 2.2561525 | M114: =-1 * MIN(M110, 0) -> 2.2561525 | N114: =-1 * MIN(N110, 0) -> 2.2777331 | O114: =-1 * MIN(O110, 0) -> 2.3030413 | P114: =-1 * MIN(P110, 0) -> 2.3283494 | ... FM114: =-1 * MIN(FM110, 0) -> 0
B115: Use (positive tax) | H115: =SUM(I115:FM115) -> -12.181654 | I115: =-1 * MIN( MAX(I110, 0), SUM(I113:I114)) -> 0 | J115: =-1 * MIN( MAX(J110, 0), SUM(J113:J114)) -> 0 | K115: =-1 * MIN( MAX(K110, 0), SUM(K113:K114)) -> 0 | L115: =-1 * MIN( MAX(L110, 0), SUM(L113:L114)) -> 0 | M115: =-1 * MIN( MAX(M110, 0), SUM(M113:M114)) -> 0 | N115: =-1 * MIN( MAX(N110, 0), SUM(N113:N114)) -> 0 | O115: =-1 * MIN( MAX(O110, 0), SUM(O113:O114)) -> 0 | P115: =-1 * MIN( MAX(P110, 0), SUM(P113:P114)) -> 0 | ... FM115: =-1 * MIN( MAX(FM110, 0), SUM(FM113:FM114)) -> 0
B116: Closing balance | I116: =SUM(I113:I115) -> 0 | J116: =SUM(J113:J115) -> 0 | K116: =SUM(K113:K115) -> 0.76022532 | L116: =SUM(L113:L115) -> 3.0163779 | M116: =SUM(M113:M115) -> 5.2725304 | N116: =SUM(N113:N115) -> 7.5502635 | O116: =SUM(O113:O115) -> 9.8533048 | P116: =SUM(P113:P115) -> 12.181654 | ... FM116: =SUM(FM113:FM115) -> 0
B118: Cash taxes paid | I118: =MAX(SUM(I110, I115), 0) -> 0 | J118: =MAX(SUM(J110, J115), 0) -> 0 | K118: =MAX(SUM(K110, K115), 0) -> 0 | L118: =MAX(SUM(L110, L115), 0) -> 0 | M118: =MAX(SUM(M110, M115), 0) -> 0 | N118: =MAX(SUM(N110, N115), 0) -> 0 | O118: =MAX(SUM(O110, O115), 0) -> 0 | P118: =MAX(SUM(P110, P115), 0) -> 0 | ... FM118: =MAX(SUM(FM110, FM115), 0) -> 0
A120: End of sheet
