Workbook

Sheet Dashboard
B2: =C3&" – Dashboard" -> Project Zalahaláp – Dashboard
C3: Project Zalahaláp
C4: 63 MWp PV + 50 MW / 200 MWh BESS – sale at RtB, sale at COD or hold
C5: Version | E5: v1
C6: Model date | E6: 46317
C7: Key-assumption set | E7: =Scenario_Name -> Base
C8: Master check | E8: =IF(Master_Check=0,"OK","CHECK") -> OK
C9: Item | D9: Unit | E9: A Original | F9: B Aurora | G9: C Offer | AB9: Key assumptions | AC9: Unit | AD9: Live
A11: x | C11: Levers (case per sheet; other inputs on Inputs, by set) | E11: A Original | F11: B Aurora | G11: C Offer | AB11: Key-assumption set
C12: Revenue case (A, B or C) | D12: text | E12: A | F12: B | G12: C | AB12: Key-assumption set | AC12: text | AD12: Base
C13: Case name | D13: text | E13: =INDEX(Case_Labels,1,Calc_1!$F12) -> v3 reconstruction | F13: =INDEX(Case_Labels,1,Calc_2!$F12) -> Aurora merchant | G13: =INDEX(Case_Labels,1,Calc_3!$F12) -> Offer + merchant tail
C14: PV price curve, direct export | D14: text | E14: =Calc_1!$E42 -> v3 capture | F14: =Calc_2!$E42 -> DC 4h direct | G14: =Calc_3!$E42 -> DC 4h direct | AB14: Key assumptions (live)
C15: PV price curve, energy sent to the BESS | D15: text | E15: =Calc_1!$E43 -> v3 capture | F15: =Calc_2!$E43 -> DC 4h transfer | G15: =Calc_3!$E43 -> DC 4h transfer | AB15: RtB price (0 = implied) | AC15: EUR k/MWp | AD15: =In_RtB_Price -> 90
C16: BESS revenue curve (Aurora block) | D16: text | E16: =Calc_1!$E47 -> DC 4h | F16: =Calc_2!$E47 -> DC 4h | G16: =Calc_3!$E47 -> DC 4h | AB16: COD price (0 = implied) | AC16: EUR k/MWp | AD16: =In_COD_Price -> 0
C17: Offers in case C: PV / BESS | D17: text | E17: =IF(Calc_1!$E57=1,In_Offer_PV&" / "&In_Offer_BESS,"–") -> – | F17: =IF(Calc_2!$E57=1,In_Offer_PV&" / "&In_Offer_BESS,"–") -> – | G17: =IF(Calc_3!$E57=1,In_Offer_PV&" / "&In_Offer_BESS,"–") -> C2a / C2c | AB17: Buyer target IRR, RtB | AC17: % | AD17: =In_Buyer_IRR_RtB -> 0.08
C18: BESS offer duration ≠ built (1 = yes) | D18: flag | E18: =Calc_1!$E65 -> 0 | F18: =Calc_2!$E65 -> 0 | G18: =Calc_3!$E65 -> 1 | AB18: Buyer target IRR, COD | AC18: % | AD18: =In_Buyer_IRR_COD -> 0.08
C19: BESS built | D19: MW | E19: =Calc_1!$E18 -> 50 | F19: =Calc_2!$E18 -> 50 | G19: =Calc_3!$E18 -> 50 | AB19: Asset deal (1 = FEP gain taxed) | AC19: flag | AD19: =In_Sale_Form -> 0
C20: BESS energy | D20: MWh | E20: =Calc_1!$F18 -> 200 | F20: =Calc_2!$F18 -> 200 | G20: =Calc_3!$F18 -> 200 | AB20: PV merchant price change | AC20: % | AD20: =In_PV_Price_Adj -> 0
C21: Grid import allowed for charging | D21: MW | E21: =In_Grid_Import_MW -> 0 | F21: =In_Grid_Import_MW -> 0 | G21: =In_Grid_Import_MW -> 0 | AB21: Yield, cases B and C | AC21: MWh/MWp | AD21: =In_Yield -> 1265
C22: Stack kept without grid charging, year 1 | D22: % | E22: =AVERAGEIF(Calc_1!$J$7:$FH$7,YEAR(Calc_1!$F16)+1,Calc_1!$J50:$FH50) -> 0.87953311 | F22: =AVERAGEIF(Calc_2!$J$7:$FH$7,YEAR(Calc_2!$F16)+1,Calc_2!$J50:$FH50) -> 0.87953311 | G22: =AVERAGEIF(Calc_3!$J$7:$FH$7,YEAR(Calc_3!$F16)+1,Calc_3!$J50:$FH50) -> 0.87953311 | AB22: BESS power | AC22: MW | AD22: =In_BESS_MW -> 50
C23: Buyer target IRR (unlevered, after tax) | D23: % | E23: =In_Buyer_IRR_RtB -> 0.08 | F23: =In_Buyer_IRR_RtB -> 0.08 | G23: =In_Buyer_IRR_RtB -> 0.08 | AB23: BESS duration | AC23: h | AD23: =In_BESS_Hours -> 4
C24: Futureal share at the RtB exit | D24: % | E24: =Calc_1!$E227 -> 0.6 | F24: =Calc_2!$E227 -> 0.6 | G24: =Calc_3!$E227 -> 0.6 | AB24: BESS built | AC24: flag | AD24: =In_BESS_On -> 1
C25: Futureal share at a COD sale | D25: % | E25: =Calc_1!$E255 -> 0.6 | F25: =Calc_2!$E255 -> 0.6 | G25: =Calc_3!$E255 -> 0.6 | AB25: BESS repowered | AC25: flag | AD25: =In_Repower -> 1
AB26: BESS capex | AC26: EUR k/MWh | AD26: =In_BESS_Capex -> 110
A27: x | C27: Returns at a glance | E27: A Original | F27: B Aurora | G27: C Offer | AB27: BESS haircut | AC27: % | AD27: =In_BESS_Haircut -> 0
C28: Sale at RtB | E28: A Original | F28: B Aurora | G28: C Offer | AB28: Grid import for charging | AC28: MW | AD28: =In_Grid_Import_MW -> 0
C29: Development costs (100 %) | D29: EUR m | E29: =Calc_1!$E185/Thousand -> 5.631 | F29: =Calc_2!$E185/Thousand -> 5.661 | G29: =Calc_3!$E185/Thousand -> 5.661 | AB29: PV offer (case C) | AC29: text | AD29: =In_Offer_PV -> C2a
C30: Construction capex (paid by the buyer) | D30: EUR m | E30: =Calc_1!$E180/Thousand -> 56.385 | F30: =Calc_2!$E180/Thousand -> 57.085 | G30: =Calc_3!$E180/Thousand -> 57.085 | AB30: BESS offer (case C) | AC30: text | AD30: =In_Offer_BESS -> C2c
C31: RtB price used | D31: EUR k/MWp | E31: =Calc_1!$E194 -> 90 | F31: =Calc_2!$E194 -> 90 | G31: =Calc_3!$E194 -> 90 | AB31: Gearing cap | AC31: % | AD31: =In_Gearing -> 0.55
C32: Implied RtB price at the buyer target IRR | D32: EUR k/MWp | E32: =Calc_1!$E192 -> 270.4537 | F32: =Calc_2!$E192 -> 34.005711 | G32: =Calc_3!$E192 -> 0 | AB32: Debt rate | AC32: % | AD32: =In_Debt_Rate -> 0.05
C33: Implied price below zero (floored, 1 = yes) | D33: flag | E33: =N(Calc_1!$F192<0) -> 0 | F33: =N(Calc_2!$F192<0) -> 0 | G33: =N(Calc_3!$F192<0) -> 1 | AB33: DSCR merchant | AC33: x | AD33: =In_DSCR_Merchant -> 1.35
C34: All-in implied price incl. reimbursements | D34: EUR k/MWp | E34: =Calc_1!$F193 -> 344.7078 | F34: =Calc_2!$F193 -> 105.90254 | G34: =Calc_3!$F193 -> 71.896825 | AB34: CIT | AC34: % | AD34: =In_CIT -> 0.09
C35: Buyer all-in price at our price | D35: EUR k/MWp | E35: =Calc_1!$E194+Calc_1!$E193 -> 164.2541 | F35: =Calc_2!$E194+Calc_2!$E193 -> 161.89683 | G35: =Calc_3!$E194+Calc_3!$E193 -> 161.89683 | AB35: Discount rate | AC35: % | AD35: =In_Discount_Rate -> 0.08
C36: Buyer IRR at our price, unlevered, after tax | D36: % | E36: =Calc_1!$E196 -> 0.09758288 | F36: =Calc_2!$E196 -> 0.073727777 | G36: =Calc_3!$E196 -> 0.057439932 | AB36: FX | AC36: HUF/EUR | AD36: =In_FX -> 400
C37: Buyer IRR at our price, before tax | D37: % | E37: =Calc_1!$E198 -> 0.10481234 | F37: =Calc_2!$E198 -> 0.079772257 | G37: =Calc_3!$E198 -> 0.061743371 | AB37: COD, cases B and C | AC37: date | AD37: =In_COD -> 46843
C38: Buyer IRR at our price, levered | D38: % | E38: =Calc_1!$E200 -> 0.11506981 | F38: =Calc_2!$E200 -> 0.081662433 | G38: =Calc_3!$E200 -> 0.057608148 | AB38: RtB exit, cases B and C | AC38: date | AD38: =In_RtB_Exit -> 46477
C39: Buyer equity (price, reimbursements, to COD) | D39: EUR m | E39: =Calc_1!$E199/Thousand -> 37.096749 | F39: =Calc_2!$E199/Thousand -> 37.564449 | G39: =Calc_3!$E199/Thousand -> 53.102847 | AB39: Share rule (1 step, 0 v3) | AC39: flag | AD39: =In_Share_Rule -> 1
C40: FEP equity contributed | D40: EUR m | E40: =(-Calc_1!$I241)/Thousand -> 7.434864 | F40: =(-Calc_2!$I241)/Thousand -> 7.4720874 | G40: =(-Calc_3!$I241)/Thousand -> 7.4720874 | AB40: Early works lines in development | AC40: # | AD40: =In_Milestones_Scope -> 4
C41: FEP proceeds | D41: EUR m | E41: =Calc_1!$I242/Thousand -> 9.7280213 | F41: =Calc_2!$I242/Thousand -> 9.8725721 | G41: =Calc_3!$I242/Thousand -> 9.8725721
C42: FEP profit | D42: EUR m | E42: =Calc_1!$I245/Thousand -> 2.2719959 | F42: =Calc_2!$I245/Thousand -> 2.3744495 | G42: =Calc_3!$I245/Thousand -> 2.3744495 | AB42: Not re-optimised in Excel
C43: FEP IRR, after tax (no debt before NTP) | D43: % | E43: =Calc_1!$E246 -> 0.84734558 | F43: =Calc_2!$E246 -> 0.62577947 | G43: =Calc_3!$E246 -> 0.62577947 | AB43: Aurora's BESS revenue is a fixed annual series per MW
C44: FEP IRR, before tax | D44: % | E44: =Calc_1!$E247 -> 0.8552917 | F44: =Calc_2!$E247 -> 0.63244879 | G44: =Calc_3!$E247 -> 0.63244879 | AB44: for one duration, cycle cap, RTE 0.86, availability
C45: FEP MOIC | D45: x | E45: =Calc_1!$E248 -> 1.3055867 | F45: =Calc_2!$E248 -> 1.3177759 | G45: =Calc_3!$E248 -> 1.3177759 | AB45: 0.98, DC co-location 1:1:1 and entry year. MW
C46: FEP NPV | D46: EUR m | E46: =Calc_1!$E249/Thousand -> 1.9033517 | F46: =Calc_2!$E249/Thousand -> 1.8882344 | G46: =Calc_3!$E249/Thousand -> 1.8882344 | AB46: scales it; hours/cycles switch blocks; grid import,
C47: PSH profit | D47: EUR m | E47: =Calc_1!$I250/Thousand -> 1.3553537 | F47: =Calc_2!$I250/Thousand -> 1.3908029 | G47: =Calc_3!$I250/Thousand -> 1.3908029 | AB47: RTE or charging rules act only via the PV-only factor,
C48: PSH share of the exit proceeds | D48: % | E48: =Calc_1!$F239/(Calc_1!$F238+Calc_1!$F239) -> 0.27419922 | F48: =Calc_2!$F239/(Calc_2!$F238+Calc_2!$F239) -> 0.27174655 | G48: =Calc_3!$F239/(Calc_3!$F238+Calc_3!$F239) -> 0.27174655 | AB48: haircut, availability and augmentation inputs.
C49: Memo: PSH IRR (150 k€ in-kind apport) | D49: % | E49: =Calc_1!$E251 -> 9.0356915 | F49: =Calc_2!$E251 -> 5.4795983 | G49: =Calc_3!$E251 -> 5.4795983 | AB49: Curve codes: see Curves (repower table, Aurora names).
C50: Sale at COD | E50: A Original | F50: B Aurora | G50: C Offer
C51: Development costs (100 %) | D51: EUR m | E51: =Calc_1!$E185/Thousand -> 5.631 | F51: =Calc_2!$E185/Thousand -> 5.661 | G51: =Calc_3!$E185/Thousand -> 5.661
C52: Construction capex (100 %) | D52: EUR m | E52: =Calc_1!$E180/Thousand -> 56.385 | F52: =Calc_2!$E180/Thousand -> 57.085 | G52: =Calc_3!$E180/Thousand -> 57.085
C53: COD price used (enterprise value per MWp) | D53: EUR k/MWp | E53: =Calc_1!$E204 -> 1322.6731 | F53: =Calc_2!$E204 -> 1030.3204 | G53: =Calc_3!$E204 -> 844.06215
C54: Implied COD price at the buyer target IRR | D54: EUR k/MWp | E54: =Calc_1!$E203 -> 1322.6731 | F54: =Calc_2!$E203 -> 1030.3204 | G54: =Calc_3!$E203 -> 844.06215
C55: Implied price below zero (floored, 1 = yes) | D55: flag | E55: =N(Calc_1!$F203<0) -> 0 | F55: =N(Calc_2!$F203<0) -> 0 | G55: =N(Calc_3!$F203<0) -> 0
C56: Buyer IRR at our price, unlevered, after tax | D56: % | E56: =Calc_1!$E206 -> 0.08 | F56: =Calc_2!$E206 -> 0.08 | G56: =Calc_3!$E206 -> 0.08
C57: Buyer IRR at our price, before tax | D57: % | E57: =Calc_1!$E208 -> 0.086819863 | F57: =Calc_2!$E208 -> 0.086576728 | G57: =Calc_3!$E208 -> 0.084903399
C58: Buyer IRR at our price, levered | D58: % | E58: =Calc_1!$E210 -> 0.088795717 | F58: =Calc_2!$E210 -> 0.093977531 | G58: =Calc_3!$E210 -> 0.084720441
C59: Buyer equity (price − debt + DSRA) | D59: EUR m | E59: =Calc_1!$E209/Thousand -> 50.576257 | F59: =Calc_2!$E209/Thousand -> 34.620942 | G59: =Calc_3!$E209/Thousand -> 39.011917
C60: FEP equity contributed | D60: EUR m | E60: =(-Calc_1!$I256)/Thousand -> 33.860738 | F60: =(-Calc_2!$I256)/Thousand -> 34.185662 | G60: =(-Calc_3!$I256)/Thousand -> 49.724059
C61: FEP proceeds (incl. deposits back) | D61: EUR m | E61: =(Calc_1!$F264+Calc_1!$I112)/Thousand -> 44.702543 | F61: =(Calc_2!$F264+Calc_2!$I112)/Thousand -> 35.183442 | G61: =(Calc_3!$F264+Calc_3!$I112)/Thousand -> 39.574417
C62: FEP profit | D62: EUR m | E62: =Calc_1!$I268/Thousand -> 10.785557 | F62: =Calc_2!$I268/Thousand -> 0.95860532 | G62: =Calc_3!$I268/Thousand -> -10.149642
C63: FEP IRR, levered, after tax (n/a < −99 %) | D63: % | E63: =Calc_1!$E270 -> 0.49548249 | F63: =Calc_2!$E270 -> 0.055841403 | G63: =Calc_3!$E270 -> -0.47488235
C64: FEP IRR, levered, before tax | D64: % | E64: =Calc_1!$E271 -> 0.49790312 | F64: =Calc_2!$E271 -> 0.058107754 | G64: =Calc_3!$E271 -> -0.47488235
C65: FEP MOIC | D65: x | E65: =Calc_1!$E269 -> 1.4024559 | F65: =Calc_2!$E269 -> 1.0382397 | G65: =Calc_3!$E269 -> 0.71778111
C66: FEP NPV | D66: EUR m | E66: =Calc_1!$E272/Thousand -> 7.680267 | F66: =Calc_2!$E272/Thousand -> -0.35216781 | G66: =Calc_3!$E272/Thousand -> -9.961467
C67: JV IRR (100 %), unlevered, after tax | D67: % | E67: =Calc_1!$E274 -> 0.57762163 | F67: =Calc_2!$E274 -> 0.08514801 | G67: =Calc_3!$E274 -> -0.38131516
C68: JV IRR (100 %), unlevered, before tax | D68: % | E68: =Calc_1!$E276 -> 0.57762163 | F68: =Calc_2!$E276 -> 0.08514801 | G68: =Calc_3!$E276 -> -0.38131516
C69: PSH profit | D69: EUR m | E69: =Calc_1!$I277/Thousand -> 6.2862131 | F69: =Calc_2!$I277/Thousand -> -0.15 | G69: =Calc_3!$I277/Thousand -> -0.15
C70: PSH share of the COD proceeds | D70: % | E70: =Calc_1!$F265/(Calc_1!$F264+Calc_1!$F265) -> 0.1272576 | F70: =Calc_2!$F265/(Calc_2!$F264+Calc_2!$F265) -> 0 | G70: =Calc_3!$F265/(Calc_3!$F264+Calc_3!$F265) -> 0
C71: Memo: PSH IRR (150 k€ in-kind apport) | D71: % | E71: =Calc_1!$E278 -> 4.318558 | F71: =Calc_2!$E278 -> n/a | G71: =Calc_3!$E278 -> n/a
C72: Hold to maturity | E72: A Original | F72: B Aurora | G72: C Offer
C73: Development costs (100 %) | D73: EUR m | E73: =Calc_1!$E185/Thousand -> 5.631 | F73: =Calc_2!$E185/Thousand -> 5.661 | G73: =Calc_3!$E185/Thousand -> 5.661
C74: Construction capex (100 %) | D74: EUR m | E74: =Calc_1!$E180/Thousand -> 56.385 | F74: =Calc_2!$E180/Thousand -> 57.085 | G74: =Calc_3!$E180/Thousand -> 57.085
C75: FEP equity contributed (incl. 2048 repower) | D75: EUR m | E75: =Calc_1!$E289/Thousand -> 68.495703 | F75: =Calc_2!$E289/Thousand -> 69.440991 | G75: =Calc_3!$E289/Thousand -> 84.97955
C76: FEP distributions (all inflows) | D76: EUR m | E76: =(SUMIF(Calc_1!$J283:$FH283,">0"))/Thousand -> 229.07619 | F76: =(SUMIF(Calc_2!$J283:$FH283,">0"))/Thousand -> 167.04045 | G76: =(SUMIF(Calc_3!$J283:$FH283,">0"))/Thousand -> 176.43158
C77: FEP profit | D77: EUR m | E77: =Calc_1!$I283/Thousand -> 160.58049 | F77: =Calc_2!$I283/Thousand -> 97.599456 | G77: =Calc_3!$I283/Thousand -> 91.452027
C78: FEP IRR, levered, after tax | D78: % | E78: =Calc_1!$E284 -> 0.12189198 | F78: =Calc_2!$E284 -> 0.087428309 | G78: =Calc_3!$E284 -> 0.060776331
C79: FEP IRR, levered, before tax | D79: % | E79: =Calc_1!$E286 -> 0.13046037 | F79: =Calc_2!$E286 -> 0.094090931 | G79: =Calc_3!$E286 -> 0.065313695
C80: FEP MOIC | D80: x | E80: =Calc_1!$E287 -> 3.3443877 | F80: =Calc_2!$E287 -> 2.4055021 | G80: =Calc_3!$E287 -> 2.0761651
C81: FEP NPV | D81: EUR m | E81: =Calc_1!$E288/Thousand -> 15.947397 | F81: =Calc_2!$E288/Thousand -> 2.4985444 | G81: =Calc_3!$E288/Thousand -> -9.5715348
C82: Project IRR, unlevered, after tax | D82: % | E82: =Calc_1!$E174 -> 0.10459681 | F82: =Calc_2!$E174 -> 0.080220471 | G82: =Calc_3!$E174 -> 0.062349053
C83: Project IRR, unlevered, before tax | D83: % | E83: =Calc_1!$E175 -> 0.1121315 | F83: =Calc_2!$E175 -> 0.086513015 | G83: =Calc_3!$E175 -> 0.066738609
C84: PSH buy-out: RtB entitlement at px_rtb | D84: EUR m | E84: =Calc_1!$F281/Thousand -> 1.5053537 | F84: =Calc_2!$F281/Thousand -> 1.5408029 | G84: =Calc_3!$F281/Thousand -> 1.5408029
C85: PSH profit (bought out at the exit) | D85: EUR m | E85: =Calc_1!$I290/Thousand -> 1.3553537 | F85: =Calc_2!$I290/Thousand -> 1.3908029 | G85: =Calc_3!$I290/Thousand -> 1.3908029
C86: Memo: PSH IRR (150 k€ in-kind apport) | D86: % | E86: =Calc_1!$E291 -> 9.0356915 | F86: =Calc_2!$E291 -> 5.4795983 | G86: =Calc_3!$E291 -> 5.4795983
A88: x | C88: Revenue cases compared (live: A | B | C) | E88: A Original | F88: B Aurora | G88: C Offer
C89: PV generation, first full year | D89: GWh | E89: =Calc_1!$E77/Thousand -> 75.611992 | F89: =Calc_2!$E77/Thousand -> 79.028166 | G89: =Calc_3!$E77/Thousand -> 79.028166
C90: PV price received, lifetime average | D90: EUR/MWh | E90: =Calc_1!$I90*Thousand/(Calc_1!$I77+Calc_1!$I78) -> 92.19943 | F90: =Calc_2!$I90*Thousand/(Calc_2!$I77+Calc_2!$I78) -> 60.976698 | G90: =Calc_3!$I90*Thousand/(Calc_3!$I77+Calc_3!$I78) -> 59.406915
C91: PV revenue, first full year | D91: EUR m | E91: =Calc_1!$E90/Thousand -> 5.3770417 | F91: =Calc_2!$E90/Thousand -> 4.7594522 | G91: =Calc_3!$E90/Thousand -> 3.222185
C92: BESS revenue, first full year | D92: EUR m | E92: =Calc_1!$E92/Thousand -> 6.0105746 | F92: =Calc_2!$E92/Thousand -> 6.0105746 | G92: =Calc_3!$E92/Thousand -> 2.485
C93: Revenue, first full year | D93: EUR m | E93: =Calc_1!$E93/Thousand -> 11.528057 | F93: =Calc_2!$E93/Thousand -> 10.919808 | G93: =Calc_3!$E93/Thousand -> 5.8569667
C94: EBITDA, first full year | D94: EUR m | E94: =Calc_1!$E101/Thousand -> 7.7711724 | F94: =Calc_2!$E101/Thousand -> 7.106991 | G94: =Calc_3!$E101/Thousand -> 2.1605946
C95: Lifetime revenue | D95: EUR m | E95: =Calc_1!$I93/Thousand -> 471.96053 | F95: =Calc_2!$I93/Thousand -> 405.22485 | G95: =Calc_3!$I93/Thousand -> 390.76222
C96: Lifetime EBITDA | D96: EUR m | E96: =Calc_1!$I101/Thousand -> 289.98368 | F96: =Calc_2!$I101/Thousand -> 221.40491 | G96: =Calc_3!$I101/Thousand -> 207.27492
C97: Project IRR, unlevered, after tax | D97: % | E97: =Calc_1!$E174 -> 0.10459681 | F97: =Calc_2!$E174 -> 0.080220471 | G97: =Calc_3!$E174 -> 0.062349053
C98: FEP IRR – hold to maturity | D98: % | E98: =Calc_1!$E284 -> 0.12189198 | F98: =Calc_2!$E284 -> 0.087428309 | G98: =Calc_3!$E284 -> 0.060776331
C99: Implied RtB price | D99: EUR k/MWp | E99: =Calc_1!$E192 -> 270.4537 | F99: =Calc_2!$E192 -> 34.005711 | G99: =Calc_3!$E192 -> 0
A101: x | C101: Capacity and energy | E101: A Original | F101: B Aurora | G101: C Offer
C102: PV capacity | D102: MWp | E102: =Calc_1!$E13 -> 61 | F102: =Calc_2!$E13 -> 63 | G102: =Calc_3!$E13 -> 63
C103: Grid export capacity | D103: MVA | E103: =Calc_1!$F13 -> 50 | F103: =Calc_2!$F13 -> 49.9 | G103: =Calc_3!$F13 -> 49.9
C104: PV clipped, lifetime | D104: GWh | E104: =(-Calc_1!$I78)/Thousand -> 50.460014 | F104: =(-Calc_2!$I78)/Thousand -> 0 | G104: =(-Calc_3!$I78)/Thousand -> 0
...

Sheet Inputs
B2: =Dashboard!$C$3&" – Inputs and scenarios" -> Project Zalahaláp – Inputs and scenarios
B4: Scenario selected | D4: Set on the Dashboard | F4: =Scenario_Name -> Base
B5: Scenario number | F5: =MATCH(Scenario_Name,Scenario_Names,0) -> 1
B7: Input | C7: Unit | D7: Source / note | F7: Live | H7: Base | I7: Reconciliation (v3 rules) | J7: PV price −10% | K7: PV yield −10% | L7: BESS revenue −20% | M7: Capex +10% | N7: Buyer IRR +1 pp | O7: RtB and COD price −10% | P7: RtB price = implied | Q7: Gearing −10 pp | R7: COD +12 months | S7: BESS 2 h | T7: No BESS | U7: BESS capex 200 k€/MWh | V7: No BESS repower | W7: PV and BESS prices −20% | X7: C: E.ON PPA + option B | Y7: C: MVM 45 + MET floor
A10: x | C10: Constants
B11: Thousand | C11: # | D11: Scale | F11: 1000
B12: Million | C12: # | D12: Scale | F12: 1000000
B13: Days In Year | C13: days | D13: Day count for year fractions and XIRR | F13: 365
B14: Months In Year | C14: months | D14: Calendar | F14: 12
B15: Months Per Period | C15: months | D15: Timeline periodicity (quarterly) | F15: 3
B16: Tolerance | C16: # | D16: Check and solver tolerance | F16: 1e-06
A18: x | C18: Timing
B19: Model start date | C19: date | D19: Timeline start | F19: =IF(INDEX($H19:$Y19,1,Scenario_Selected)="",$H19,INDEX($H19:$Y19,1,Scenario_Selected)) -> 45931 | H19: 45931
B20: Sensitivity step (price, yield, capex, opex sets) | C20: % | D20: SPEC §10 | F20: 0.1
B21: Large sensitivity step (BESS revenue, downside sets) | C21: % | D21: SPEC §10 | F21: 0.2
B22: Rate step (buyer IRR, debt rate sets) | C22: % | D22: SPEC §10 | F22: 0.01
B23: Hours in a day | C23: h | D23: Grid export limit | F23: 24
B24: Key-assumption set of the reconciliation | C24: # | D24: SPEC §10 set 2 | F24: 2
B25: Acquisition, JV start, deposits paid | C25: date | D25: ZHLP v3 Stat_inp E39 | F25: =IF(INDEX($H25:$Y25,1,Scenario_Selected)="",$H25,INDEX($H25:$Y25,1,Scenario_Selected)) -> 45991 | H25: 45991
B26: Ready to build (cases B, C) | C26: date | D26: Teaser p6; placeholder – pending user (SPEC §16 Q5) | F26: =IF(INDEX($H26:$Y26,1,Scenario_Selected)="",$H26,INDEX($H26:$Y26,1,Scenario_Selected)) -> 46387 | H26: 46387
B27: RtB sale closing (exit), cases B, C | C27: date | D27: placeholder – pending user (SPEC §16 Q5) | F27: =IF(INDEX($H27:$Y27,1,Scenario_Selected)="",$H27,INDEX($H27:$Y27,1,Scenario_Selected)) -> 46477 | H27: 46477
B28: Notice to proceed (cases B, C) | C28: date | D28: placeholder – pending user (SPEC §16 Q5) | F28: =IF(INDEX($H28:$Y28,1,Scenario_Selected)="",$H28,INDEX($H28:$Y28,1,Scenario_Selected)) -> 46568 | H28: 46568
B29: Commercial operation, PV and BESS (cases B, C) | C29: date | D29: Teaser p6; placeholder – pending user (SPEC §16 Q5) | F29: =IF(INDEX($H29:$Y29,1,Scenario_Selected)="",$H29,INDEX($H29:$Y29,1,Scenario_Selected)) -> 46843 | H29: 46843
B30: COD delay (construction longer) | C30: months | D30: SPEC §10 | F30: =IF(INDEX($H30:$Y30,1,Scenario_Selected)="",$H30,INDEX($H30:$Y30,1,Scenario_Selected)) -> 0 | H30: 0 | R30: 12
B31: Operating life | C31: years | D31: ZHLP v3 Control D30 | F31: =IF(INDEX($H31:$Y31,1,Scenario_Selected)="",$H31,INDEX($H31:$Y31,1,Scenario_Selected)) -> 35 | H31: 35
B32: Pre-RtB development costs: first month | C32: date | D32: ZHLP v3 Control D116 | F32: =IF(INDEX($H32:$Y32,1,Scenario_Selected)="",$H32,INDEX($H32:$Y32,1,Scenario_Selected)) -> 46326 | H32: 46326
B33: Pre-RtB development costs: last month | C33: date | D33: ZHLP v3 Control D117 | F33: =IF(INDEX($H33:$Y33,1,Scenario_Selected)="",$H33,INDEX($H33:$Y33,1,Scenario_Selected)) -> 46477 | H33: 46477
A35: x | C35: PV and grid (cases B, C; case A on Curves)
B36: PV capacity | C36: MWp | D36: Teaser p1 | F36: =IF(INDEX($H36:$Y36,1,Scenario_Selected)="",$H36,INDEX($H36:$Y36,1,Scenario_Selected)) -> 63 | H36: 63
B37: Grid export capacity | C37: MVA | D37: Teaser p1 | F37: =IF(INDEX($H37:$Y37,1,Scenario_Selected)="",$H37,INDEX($H37:$Y37,1,Scenario_Selected)) -> 49.9 | H37: 49.9
B38: Specific yield | C38: MWh/MWp | D38: Teaser p1 (v3: 1,250) | F38: =IF(INDEX($H38:$Y38,1,Scenario_Selected)="",$H38,INDEX($H38:$Y38,1,Scenario_Selected)) -> 1265 | H38: 1265
B39: Yield change (P90 proxy) | C39: % | D39: SPEC §10 | F39: =IF(INDEX($H39:$Y39,1,Scenario_Selected)="",$H39,INDEX($H39:$Y39,1,Scenario_Selected)) -> 0 | H39: 0 | K39: =-Sens_Step -> -0.1
B40: PV availability | C40: % | D40: ZHLP v3 Control D56 | F40: =IF(INDEX($H40:$Y40,1,Scenario_Selected)="",$H40,INDEX($H40:$Y40,1,Scenario_Selected)) -> 0.995 | H40: 0.995
B41: PV degradation per year | C41: % | D41: ZHLP v3 Control D57 | F41: =IF(INDEX($H41:$Y41,1,Scenario_Selected)="",$H41,INDEX($H41:$Y41,1,Scenario_Selected)) -> 0.003 | H41: 0.003
B42: Clipping, case A (v3 + fix 5), share of DC energy | C42: % | D42: placeholder – pending user (SPEC §16 Q13) | F42: =IF(INDEX($H42:$Y42,1,Scenario_Selected)="",$H42,INDEX($H42:$Y42,1,Scenario_Selected)) -> 0.02 | H42: 0.02
B43: Clipping, cases B, C (DC-coupled BESS) | C43: % | D43: Aurora s+29 = 0; placeholder – pending user (SPEC §16 Q13) | F43: =IF(INDEX($H43:$Y43,1,Scenario_Selected)="",$H43,INDEX($H43:$Y43,1,Scenario_Selected)) -> 0 | H43: 0
B44: Grid import allowed for BESS charging | C44: MW | D44: confirmed by user, 22-Oct-2026 (no grid charging) | F44: =IF(INDEX($H44:$Y44,1,Scenario_Selected)="",$H44,INDEX($H44:$Y44,1,Scenario_Selected)) -> 0 | H44: 0
B45: aFRR-down/FCR capacity deliverable from PV charge | C45: % | D45: placeholder – aFRR-down/FCR share deliverable from PV SoC | F45: =IF(INDEX($H45:$Y45,1,Scenario_Selected)="",$H45,INDEX($H45:$Y45,1,Scenario_Selected)) -> 0 | H45: 0
A47: x | C47: BESS
B48: BESS built (1 = yes) | C48: flag | D48: Teaser p1; SPEC §10 | F48: =IF(INDEX($H48:$Y48,1,Scenario_Selected)="",$H48,INDEX($H48:$Y48,1,Scenario_Selected)) -> 1 | H48: 1 | T48: 0
B49: BESS power | C49: MW | D49: Teaser p1; ZHLP v3 Control D91 | F49: =IF(INDEX($H49:$Y49,1,Scenario_Selected)="",$H49,INDEX($H49:$Y49,1,Scenario_Selected)) -> 50 | H49: 50
B50: BESS duration | C50: h | D50: Teaser; placeholder – pending user (SPEC §16 Q6) | F50: =IF(INDEX($H50:$Y50,1,Scenario_Selected)="",$H50,INDEX($H50:$Y50,1,Scenario_Selected)) -> 4 | H50: 4 | S50: 2
B51: Aurora battery block (Degraded batteries) | C51: text | D51: Aurora Q2-26; placeholder – pending user (SPEC §16 Q6) | F51: =IF(INDEX($H51:$Y51,1,Scenario_Selected)="",$H51,INDEX($H51:$Y51,1,Scenario_Selected)) -> DC 4h | H51: DC 4h | S51: DC 2h
B52: Round-trip efficiency (energy check only) | C52: % | D52: Aurora Q2-26 Inputs C17 | F52: =IF(INDEX($H52:$Y52,1,Scenario_Selected)="",$H52,INDEX($H52:$Y52,1,Scenario_Selected)) -> 0.86 | H52: 0.86
B53: Haircut on merchant BESS revenue | C53: % | D53: SPEC §6.2, §10 | F53: =IF(INDEX($H53:$Y53,1,Scenario_Selected)="",$H53,INDEX($H53:$Y53,1,Scenario_Selected)) -> 0 | H53: 0 | L53: =Sens_Step_Large -> 0.2 | W53: =Sens_Step_Large -> 0.2
B54: Grid charge on charging, offers that deduct it | C54: EUR k/MW | D54: placeholder – pending user (SPEC §16 Q12) | F54: =IF(INDEX($H54:$Y54,1,Scenario_Selected)="",$H54,INDEX($H54:$Y54,1,Scenario_Selected)) -> 0 | H54: 0
B55: BESS capex | C55: EUR k/MWh | D55: v3 Control D94; placeholder – pending user (SPEC §16 Q6) | F55: =IF(INDEX($H55:$Y55,1,Scenario_Selected)="",$H55,INDEX($H55:$Y55,1,Scenario_Selected)) -> 110 | H55: 110 | U55: 200
B56: BESS augmentation cost | C56: EUR k/MWh | D56: v3 Control D100; placeholder – pending user (SPEC §16 Q6) | F56: =IF(INDEX($H56:$Y56,1,Scenario_Selected)="",$H56,INDEX($H56:$Y56,1,Scenario_Selected)) -> 110 | H56: 110
B57: Augmentation year (0 = Aurora block repower year) | C57: year | D57: SPEC §6.2 | F57: =IF(INDEX($H57:$Y57,1,Scenario_Selected)="",$H57,INDEX($H57:$Y57,1,Scenario_Selected)) -> 0 | H57: 0
B58: BESS repowered (0 = retired at the repower year) | C58: flag | D58: Aurora repower s+1; placeholder – pending user (SPEC §16 Q6) | F58: =IF(INDEX($H58:$Y58,1,Scenario_Selected)="",$H58,INDEX($H58:$Y58,1,Scenario_Selected)) -> 1 | H58: 1 | V58: 0
B59: Augmentation year, v3 rule (fix 7 off) | C59: year | D59: ZHLP v3 Control D101 | F59: =IF(INDEX($H59:$Y59,1,Scenario_Selected)="",$H59,INDEX($H59:$Y59,1,Scenario_Selected)) -> 2048 | H59: 2048
B60: BESS fixed opex | C60: EUR k/MW | D60: ZHLP v3 Control D96 | F60: =IF(INDEX($H60:$Y60,1,Scenario_Selected)="",$H60,INDEX($H60:$Y60,1,Scenario_Selected)) -> 30.8 | H60: 30.8
A62: x | C62: Prices and offers
B63: PV price, direct export (Curves, real 2025) | C63: text | D63: SPEC §0.2, §6.2; fix round 1 M2 | F63: =IF(INDEX($H63:$Y63,1,Scenario_Selected)="",$H63,INDEX($H63:$Y63,1,Scenario_Selected)) -> DC 4h direct | H63: DC 4h direct | S63: DC 2h direct
B64: PV price, energy sent to the BESS | C64: text | D64: Aurora s+36/s+32; fix round 1 M2 | F64: =IF(INDEX($H64:$Y64,1,Scenario_Selected)="",$H64,INDEX($H64:$Y64,1,Scenario_Selected)) -> DC 4h transfer | H64: DC 4h transfer | S64: DC 2h transfer
B65: PV merchant price change | C65: % | D65: SPEC §10 | F65: =IF(INDEX($H65:$Y65,1,Scenario_Selected)="",$H65,INDEX($H65:$Y65,1,Scenario_Selected)) -> 0 | H65: 0 | J65: =-Sens_Step -> -0.1 | W65: =-Sens_Step_Large -> -0.2
B66: Guarantee of origin price, real 2025 | C66: EUR/MWh | D66: v3 Control D58; placeholder – pending user (SPEC §16 Q12) | F66: =IF(INDEX($H66:$Y66,1,Scenario_Selected)="",$H66,INDEX($H66:$Y66,1,Scenario_Selected)) -> 1.75 | H66: 1.75
B67: PV offer in case C (C1, C2a, C2b, C3) | C67: text | D67: SPEC §6.3; placeholder – pending user (SPEC §16 Q12) | F67: =IF(INDEX($H67:$Y67,1,Scenario_Selected)="",$H67,INDEX($H67:$Y67,1,Scenario_Selected)) -> C2a | H67: C2a | X67: C1 | Y67: C3
B68: BESS offer in case C (C1A, C1B, C2c, C2d, none) | C68: text | D68: SPEC §6.3; placeholder – pending user (SPEC §16 Q12) | F68: =IF(INDEX($H68:$Y68,1,Scenario_Selected)="",$H68,INDEX($H68:$Y68,1,Scenario_Selected)) -> C2c | H68: C2c | X68: C1B | Y68: C2d
A70: x | C70: Capex
B71: PV equipment and balance of plant | C71: EUR k/MWp | D71: ZHLP v3 Control D82:D83 | F71: =IF(INDEX($H71:$Y71,1,Scenario_Selected)="",$H71,INDEX($H71:$Y71,1,Scenario_Selected)) -> 350 | H71: 350
B72: MV cable to the grid connection point | C72: EUR k | D72: v3 Control D104; placeholder – pending user (SPEC §16 Q13) | F72: =IF(INDEX($H72:$Y72,1,Scenario_Selected)="",$H72,INDEX($H72:$Y72,1,Scenario_Selected)) -> 3700 | H72: 3700
B73: HV substation | C73: EUR k | D73: v3 Control D105; placeholder – pending user (SPEC §16 Q13) | F73: =IF(INDEX($H73:$Y73,1,Scenario_Selected)="",$H73,INDEX($H73:$Y73,1,Scenario_Selected)) -> 9500 | H73: 9500
B74: Land to COD (not depreciated) | C74: EUR k | D74: ZHLP v3 Control D106 | F74: =IF(INDEX($H74:$Y74,1,Scenario_Selected)="",$H74,INDEX($H74:$Y74,1,Scenario_Selected)) -> 620 | H74: 620
B75: Capex change | C75: % | D75: SPEC §10 | F75: =IF(INDEX($H75:$Y75,1,Scenario_Selected)="",$H75,INDEX($H75:$Y75,1,Scenario_Selected)) -> 0 | H75: 0 | M75: =Sens_Step -> 0.1
B76: Pre-RtB development costs | C76: EUR k | D76: ZHLP v3 Control D115 | F76: =IF(INDEX($H76:$Y76,1,Scenario_Selected)="",$H76,INDEX($H76:$Y76,1,Scenario_Selected)) -> 3182 | H76: 3182
B77: Buyer reimburses pre-RtB costs (1 = yes) | C77: flag | D77: ZHLP v3 Control D118 | F77: =IF(INDEX($H77:$Y77,1,Scenario_Selected)="",$H77,INDEX($H77:$Y77,1,Scenario_Selected)) -> 1 | H77: 1
A79: x | C79: Early works (provisional – to be revisited)
B80: Early-works lines paid in development (4 or 6) | C80: # | D80: provisional – early works to be revisited (user 22-Oct-26) | F80: =IF(INDEX($H80:$Y80,1,Scenario_Selected)="",$H80,INDEX($H80:$Y80,1,Scenario_Selected)) -> 4 | H80: 4 | I80: 6
B81: Lines outside the scope paid at NTP (1 = yes) | C81: flag | D81: provisional – early works to be revisited (user 22-Oct-26) | F81: =IF(INDEX($H81:$Y81,1,Scenario_Selected)="",$H81,INDEX($H81:$Y81,1,Scenario_Selected)) -> 1 | H81: 1
B82: Buyer reimburses early works at the exit (1 = yes) | C82: flag | D82: provisional – early works to be revisited (user 22-Oct-26) | F82: =IF(INDEX($H82:$Y82,1,Scenario_Selected)="",$H82,INDEX($H82:$Y82,1,Scenario_Selected)) -> 1 | H82: 1
B83: Early works earn the FEP return (1 = yes) | C83: flag | D83: provisional – early works to be revisited (user 22-Oct-26) | F83: =IF(INDEX($H83:$Y83,1,Scenario_Selected)="",$H83,INDEX($H83:$Y83,1,Scenario_Selected)) -> 1 | H83: 1
B84: Early works are PSH milestone income (v3) | C84: flag | D84: ZHLP v3 Calculation F221 | F84: =IF(INDEX($H84:$Y84,1,Scenario_Selected)="",$H84,INDEX($H84:$Y84,1,Scenario_Selected)) -> 0 | H84: 0 | I84: 1
A86: x | C86: Opex and levies (real 2025, Aurora euro index)
B87: O&M and fixed opex | C87: EUR k/MWp | D87: ZHLP v3 Control D59 | F87: =IF(INDEX($H87:$Y87,1,Scenario_Selected)="",$H87,INDEX($H87:$Y87,1,Scenario_Selected)) -> 14.96 | H87: 14.96
B88: MV cable O&M | C88: EUR k/MWp | D88: ZHLP v3 Control D62 | F88: =IF(INDEX($H88:$Y88,1,Scenario_Selected)="",$H88,INDEX($H88:$Y88,1,Scenario_Selected)) -> 5 | H88: 5
B89: Balancing cost | C89: EUR/MWh | D89: ZHLP v3 Control D60 | F89: =IF(INDEX($H89:$Y89,1,Scenario_Selected)="",$H89,INDEX($H89:$Y89,1,Scenario_Selected)) -> 5 | H89: 5
B90: Land lease from COD | C90: EUR k | D90: ZHLP v3 Control D61 | F90: =IF(INDEX($H90:$Y90,1,Scenario_Selected)="",$H90,INDEX($H90:$Y90,1,Scenario_Selected)) -> 96 | H90: 96
B91: Route-to-market fee on PV revenue | C91: % | D91: ZHLP v3 Control D77 | F91: =IF(INDEX($H91:$Y91,1,Scenario_Selected)="",$H91,INDEX($H91:$Y91,1,Scenario_Selected)) -> 0 | H91: 0
B92: Opex change | C92: % | D92: SPEC §10 (no set) | F92: =IF(INDEX($H92:$Y92,1,Scenario_Selected)="",$H92,INDEX($H92:$Y92,1,Scenario_Selected)) -> 0 | H92: 0
B93: Local business tax (HIPA), on revenue | C93: % | D93: Bana; placeholder – pending user (SPEC §16 Q10) | F93: =IF(INDEX($H93:$Y93,1,Scenario_Selected)="",$H93,INDEX($H93:$Y93,1,Scenario_Selected)) -> 0.02 | H93: 0.02 | I93: 0
B94: Innovation contribution, on revenue | C94: % | D94: Act LXXVI/2014; placeholder – pending user (SPEC §16 Q10) | F94: =IF(INDEX($H94:$Y94,1,Scenario_Selected)="",$H94,INDEX($H94:$Y94,1,Scenario_Selected)) -> 0.003 | H94: 0.003 | I94: 0
A96: x | C96: Deposits and guarantees
B97: FX rate | C97: HUF/EUR | D97: ZHLP v3 Stat_inp E23 (Aurora 397.77) | F97: =IF(INDEX($H97:$Y97,1,Scenario_Selected)="",$H97,INDEX($H97:$Y97,1,Scenario_Selected)) -> 400 | H97: 400
B98: Bank guarantee base rate (1M EURIBOR) | C98: % | D98: ZHLP v3 Dyn_Inp G50:Y50 average | F98: =IF(INDEX($H98:$Y98,1,Scenario_Selected)="",$H98,INDEX($H98:$Y98,1,Scenario_Selected)) -> 0.0187 | H98: 0.0187
B99: Bank guarantee margin | C99: % | D99: ZHLP v3 Stat_inp E110 | F99: =IF(INDEX($H99:$Y99,1,Scenario_Selected)="",$H99,INDEX($H99:$Y99,1,Scenario_Selected)) -> 0.0175 | H99: 0.0175
A101: x | C101: JV, RtB exit and COD sale
B102: RtB price (0 = implied at the buyer target IRR) | C102: EUR k/MWp | D102: v3 Stat_inp E24; placeholder – pending user (SPEC §16 Q3) | F102: =IF(INDEX($H102:$Y102,1,Scenario_Selected)="",$H102,INDEX($H102:$Y102,1,Scenario_Selected)) -> 90 | H102: 90 | P102: 0
B103: COD price (0 = implied at the buyer target IRR) | C103: EUR k/MWp | D103: placeholder – pending user (SPEC §16 Q8) | F103: =IF(INDEX($H103:$Y103,1,Scenario_Selected)="",$H103,INDEX($H103:$Y103,1,Scenario_Selected)) -> 0 | H103: 0
B104: RtB and COD price change | C104: % | D104: SPEC §10 | F104: =IF(INDEX($H104:$Y104,1,Scenario_Selected)="",$H104,INDEX($H104:$Y104,1,Scenario_Selected)) -> 0 | H104: 0 | O104: =-Sens_Step -> -0.1
B105: Share rule (1 = step, 0 = v3 slide) | C105: flag | D105: SPEC §0.1; set 2 = v3 | F105: =IF(INDEX($H105:$Y105,1,Scenario_Selected)="",$H105,INDEX($H105:$Y105,1,Scenario_Selected)) -> 1 | H105: 1 | I105: 0
B106: Futureal share at or below the threshold | C106: % | D106: User 22-Oct-26 (SPEC §0.1) | F106: =IF(INDEX($H106:$Y106,1,Scenario_Selected)="",$H106,INDEX($H106:$Y106,1,Scenario_Selected)) -> 0.6 | H106: 0.6
B107: Futureal share above the threshold | C107: % | D107: User 22-Oct-26 (SPEC §0.1) | F107: =IF(INDEX($H107:$Y107,1,Scenario_Selected)="",$H107,INDEX($H107:$Y107,1,Scenario_Selected)) -> 0.5 | H107: 0.5
B108: Share threshold (60 % at or below) | C108: EUR k/MWp | D108: User 22-Oct-26: 60 % at 90 | F108: =IF(INDEX($H108:$Y108,1,Scenario_Selected)="",$H108,INDEX($H108:$Y108,1,Scenario_Selected)) -> 90 | H108: 90
B109: v3 slide: 50 % reached at | C109: EUR k/MWp | D109: ZHLP v3 Stat_inp J36 | F109: =IF(INDEX($H109:$Y109,1,Scenario_Selected)="",$H109,INDEX($H109:$Y109,1,Scenario_Selected)) -> 100 | H109: 100
B110: Transaction costs (FEP) | C110: EUR k | D110: ZHLP v3 Stat_inp E37 | F110: =IF(INDEX($H110:$Y110,1,Scenario_Selected)="",$H110,INDEX($H110:$Y110,1,Scenario_Selected)) -> 200 | H110: 200
B111: FEP SPV acquisition price | C111: EUR k | D111: JV sheet G19; placeholder – pending user (SPEC §16 Q3) | F111: =IF(INDEX($H111:$Y111,1,Scenario_Selected)="",$H111,INDEX($H111:$Y111,1,Scenario_Selected)) -> 549 | H111: 549 | I111: 150
B112: SPV price earns the FEP return (1 = yes) | C112: flag | D112: ZHLP v3 Stat_inp E66 | F112: =IF(INDEX($H112:$Y112,1,Scenario_Selected)="",$H112,INDEX($H112:$Y112,1,Scenario_Selected)) -> 0 | H112: 0 | I112: 1
B113: DSA loan to PSH | C113: EUR k/MWp | D113: JV sheet F55; placeholder – pending user (SPEC §16 Q3) | F113: =IF(INDEX($H113:$Y113,1,Scenario_Selected)="",$H113,INDEX($H113:$Y113,1,Scenario_Selected)) -> 15 | H113: 15 | I113: 0
B114: FEP return on loans and costs | C114: % | D114: JV sheet G30; v3 Stat_inp E69 | F114: =IF(INDEX($H114:$Y114,1,Scenario_Selected)="",$H114,INDEX($H114:$Y114,1,Scenario_Selected)) -> 0.12 | H114: 0.12
...

Sheet Curves
B2: =Dashboard!$C$3&" – Time-series inputs" -> Project Zalahaláp – Time-series inputs
A5: x | C5: Notes
C6: Aurora battery revenue blocks (Degraded batteries) are fixed dispatch outputs of Aurora's model: they do NOT re-optimise when inputs change.
C7: BESS MW scales them linearly; hours and cycles switch blocks. RTE, degradation, grid cap, PV:BESS ratio and charging rules act only through the haircut, PV-only factor and augmentation inputs. Aurora's 98 % availability is inside the blocks.
C8: No grid charging (user, 22-Oct-2026): the stack keeps DA/ID discharge at the share PV can charge, the PV transfer cost and aFRR-up capacity (PV-only factor); aFRR energy and aFRR-down/FCR capacity are lost (the deliverable share of the latter is In_AFRR_Down_Share).
C9: Network charges apply to grid-drawn energy only (Hungarian RHD); none with no import.
C10: The hourly export and charging limits live inside Aurora's dispatch (1 MW PV : 1 MW storage : 1 MW grid); Excel only checks the annual energy balance.
C11: Aurora data: data/aurora_extract.py → data/aurora_curves.csv (source rows cited per curve). Case A curves: data/old_engine/old_curves.csv (ZHLP v3 Aurora_Curve).
A13: x | C13: Revenue-case table (one column per case; Calc picks the case on the Dashboard) | E13: SPEC §6.4
C14: Item | J14: A | K14: B | L14: C
C15: Case | D15: text | J15: A | K15: B | L15: C
C16: Case name | D16: text | J16: v3 reconstruction | K16: Aurora merchant | L16: Offer + merchant tail
C17: PV price curve, direct export | D17: text | E17: ZHLP v3 Control D15:D29 | J17: v3 capture | K17: =In_PV_Curve -> DC 4h direct | L17: =In_PV_Curve -> DC 4h direct
C18: PV price curve, energy sent to the BESS | D18: text | E18: ZHLP v3 Control D15:D29 | J18: v3 capture | K18: =In_PV_Transfer_Curve -> DC 4h transfer | L18: =In_PV_Transfer_Curve -> DC 4h transfer
C19: Clipping, share of DC energy | D19: % | E19: ZHLP v3 Control D15:D29 | J19: =In_Clip_Loss*In_Fix_Clip -> 0.02 | K19: =In_Clip_Loss_DC -> 0 | L19: =In_Clip_Loss_DC -> 0
C20: BESS revenue curve | D20: text | E20: ZHLP v3 Control D15:D29 | J20: =IF(In_Fix_BESS=1,In_BESS_Block,"v3 BESS") -> DC 4h | K20: =In_BESS_Block -> DC 4h | L20: =In_BESS_Block -> DC 4h
C21: Offtake offer applies (1 = yes) | D21: flag | J21: 0 | K21: 0 | L21: 1
C22: PV capacity (MWp) | D22: MWp | E22: ZHLP v3 Control D15:D29 | J22: 61 | K22: =In_MWp -> 63 | L22: =In_MWp -> 63
C23: Grid export capacity (MVA) | D23: MVA | E23: ZHLP v3 Control D15:D29 | J23: 50 | K23: =In_Grid_MVA -> 49.9 | L23: =In_Grid_MVA -> 49.9
C24: Specific yield (MWh/MWp) | D24: MWh/MWp | E24: ZHLP v3 Control D15:D29 | J24: 1250 | K24: =In_Yield -> 1265 | L24: =In_Yield -> 1265
C25: Ready to build | D25: date | E25: ZHLP v3 Control D15:D29 | J25: 46234 | K25: =In_RtB -> 46387 | L25: =In_RtB -> 46387
C26: RtB sale closing (exit) | D26: date | E26: ZHLP v3 Control D15:D29 | J26: 46326 | K26: =In_RtB_Exit -> 46477 | L26: =In_RtB_Exit -> 46477
C27: NTP (construction start − 1 day) | D27: date | E27: ZHLP v3 Control D15:D29 | J27: 46477 | K27: =In_NTP -> 46568 | L27: =In_NTP -> 46568
C28: COD (operations from the next day) | D28: date | E28: ZHLP v3 Control D15:D29 | J28: 46843 | K28: =In_COD -> 46843 | L28: =In_COD -> 46843
A30: x | C30: PV prices, real 2025: <block> direct = (s+34+s+35)/s+31, transfer = s+36/s+32; v3 Low/High = ∓ 15 % | E30: v3 Aurora_Curve L; Aurora s+34:s+37 over s+31, s+32 (aurora_curves.csv)
C31: Year | J31: 2025 | K31: 2026 | L31: 2027 | M31: 2028 | N31: 2029 | O31: 2030 | P31: 2031 | Q31: 2032 | R31: 2033 | S31: 2034 | T31: 2035 | U31: 2036 | V31: 2037 | W31: 2038 | X31: 2039 | Y31: 2040 | Z31: 2041 | AA31: 2042 | AB31: 2043 | AC31: 2044 | AD31: 2045 | AE31: 2046 | AF31: 2047 | AG31: 2048 | AH31: 2049 | AI31: 2050 | AJ31: 2051 | AK31: 2052 | AL31: 2053 | AM31: 2054 | AN31: 2055 | AO31: 2056 | AP31: 2057 | AQ31: 2058 | AR31: 2059 | AS31: 2060 | AT31: 2061 | AU31: 2062 | AV31: 2063 | AW31: 2064
C32: v3 capture | D32: EUR/MWh | J32: 0 | K32: 78.3445 | L32: 77.571 | M32: 71.5 | N32: 67.002 | O32: 61.6785 | P32: 64.0315 | Q32: 62.465 | R32: 62.868 | S32: 60.5345 | T32: 60.4305 | U32: 60.476 | V32: 62.8095 | W32: 62.244 | X32: 61.919 | Y32: 61.061 | Z32: 60.3135 | AA32: 60.853 | AB32: 61.0545 | AC32: 60.554 | AD32: 61.7435 | AE32: 61.9905 | AF32: 61.8735 | AG32: 60.645 | AH32: 60.7815 | AI32: 60.047 | AJ32: 59.4425 | AK32: 58.305 | AL32: 58.9615 | AM32: 58.7405 | AN32: 58.552 | AO32: 57.8305 | AP32: 58.4285 | AQ32: 59.8845 | AR32: 60.9245 | AS32: 60.2615 | AT32: 60.2615 | AU32: 60.2615 | AV32: 60.2615 | AW32: 60.2615
C33: v3 capture Low | D33: EUR/MWh | J33: 0 | K33: 66.592825 | L33: 65.93535 | M33: 60.775 | N33: 56.9517 | O33: 52.426725 | P33: 54.426775 | Q33: 53.09525 | R33: 53.4378 | S33: 51.454325 | T33: 51.365925 | U33: 51.4046 | V33: 53.388075 | W33: 52.9074 | X33: 52.63115 | Y33: 51.90185 | Z33: 51.266475 | AA33: 51.72505 | AB33: 51.896325 | AC33: 51.4709 | AD33: 52.481975 | AE33: 52.691925 | AF33: 52.592475 | AG33: 51.54825 | AH33: 51.664275 | AI33: 51.03995 | AJ33: 50.526125 | AK33: 49.55925 | AL33: 50.117275 | AM33: 49.929425 | AN33: 49.7692 | AO33: 49.155925 | AP33: 49.664225 | AQ33: 50.901825 | AR33: 51.785825 | AS33: 51.222275 | AT33: 51.222275 | AU33: 51.222275 | AV33: 51.222275 | AW33: 51.222275
C34: v3 capture High | D34: EUR/MWh | J34: 0 | K34: 90.096175 | L34: 89.20665 | M34: 82.225 | N34: 77.0523 | O34: 70.930275 | P34: 73.636225 | Q34: 71.83475 | R34: 72.2982 | S34: 69.614675 | T34: 69.495075 | U34: 69.5474 | V34: 72.230925 | W34: 71.5806 | X34: 71.20685 | Y34: 70.22015 | Z34: 69.360525 | AA34: 69.98095 | AB34: 70.212675 | AC34: 69.6371 | AD34: 71.005025 | AE34: 71.289075 | AF34: 71.154525 | AG34: 69.74175 | AH34: 69.898725 | AI34: 69.05405 | AJ34: 68.358875 | AK34: 67.05075 | AL34: 67.805725 | AM34: 67.551575 | AN34: 67.3348 | AO34: 66.505075 | AP34: 67.192775 | AQ34: 68.867175 | AR34: 70.063175 | AS34: 69.300725 | AT34: 69.300725 | AU34: 69.300725 | AV34: 69.300725 | AW34: 69.300725
C35: DC 4h direct | D35: EUR/MWh | J35: 0 | K35: 0 | L35: 107.45398 | M35: 97.385579 | N35: 90.576086 | O35: 82.517914 | P35: 82.820586 | Q35: 77.089947 | R35: 76.043866 | S35: 71.106742 | T35: 69.435847 | U35: 68.220039 | V35: 70.386891 | W35: 69.78564 | X35: 68.102419 | Y35: 65.251077 | Z35: 62.520992 | AA35: 62.657367 | AB35: 62.263383 | AC35: 61.00633 | AD35: 62.575628 | AE35: 62.378225 | AF35: 62.020215 | AG35: 59.242295 | AH35: 70.826934 | AI35: 68.089247 | AJ35: 66.577524 | AK35: 64.569189 | AL35: 63.525124 | AM35: 62.203209 | AN35: 61.14484 | AO35: 59.041048 | AP35: 58.877107 | AQ35: 57.914745 | AR35: 57.8271 | AS35: 56.585236 | AT35: 56.585236 | AU35: 56.585236 | AV35: 56.585236 | AW35: 56.585236
C36: DC 2h direct | D36: EUR/MWh | J36: 0 | K36: 0 | L36: 83.416853 | M36: 74.7685 | N36: 70.386499 | O36: 62.214056 | P36: 63.421937 | Q36: 58.828288 | R36: 59.096765 | S36: 54.400285 | T36: 53.286899 | U36: 53.253133 | V36: 56.079909 | W36: 56.213238 | X36: 54.97995 | Y36: 52.88098 | Z36: 50.684825 | AA36: 50.938819 | AB36: 50.58768 | AC36: 49.753263 | AD36: 51.490997 | AE36: 51.887551 | AF36: 51.818932 | AG36: 52.680134 | AH36: 51.949949 | AI36: 50.701172 | AJ36: 50.225707 | AK36: 48.931741 | AL36: 48.634119 | AM36: 47.837442 | AN36: 47.325811 | AO36: 46.079868 | AP36: 46.140978 | AQ36: 45.754272 | AR36: 46.240982 | AS36: 45.587123 | AT36: 45.587123 | AU36: 45.587123 | AV36: 45.587123 | AW36: 45.587123
C37: DC 2h 1.5cy direct | D37: EUR/MWh | J37: 0 | K37: 0 | L37: 82.694231 | M37: 73.787131 | N37: 69.853057 | O37: 61.389308 | P37: 62.25282 | Q37: 57.135993 | R37: 56.975302 | S37: 51.818739 | T37: 50.294247 | U37: 49.478048 | V37: 52.956021 | W37: 52.817266 | X37: 51.658425 | Y37: 49.200642 | Z37: 47.132255 | AA37: 47.57186 | AB37: 46.977152 | AC37: 46.199864 | AD37: 48.687544 | AE37: 48.828746 | AF37: 49.555441 | AG37: 48.006782 | AH37: 47.7335 | AI37: 46.960386 | AJ37: 46.834548 | AK37: 46.048238 | AL37: 45.338632 | AM37: 44.787254 | AN37: 44.384792 | AO37: 43.547221 | AP37: 43.422912 | AQ37: 42.66133 | AR37: 42.863504 | AS37: 42.429673 | AT37: 42.429673 | AU37: 42.429673 | AV37: 42.429673 | AW37: 42.429673
C38: DC 4h 2030 direct | D38: EUR/MWh | J38: 0 | K38: 0 | L38: 0 | M38: 0 | N38: 0 | O38: 85.849206 | P38: 86.031328 | Q38: 79.676919 | R38: 78.411918 | S38: 73.225545 | T38: 71.350014 | U38: 69.795642 | V38: 71.870425 | W38: 71.398089 | X38: 69.789439 | Y38: 66.836711 | Z38: 63.824837 | AA38: 64.113335 | AB38: 63.587594 | AC38: 62.296139 | AD38: 63.883592 | AE38: 63.582671 | AF38: 63.204832 | AG38: 60.458234 | AH38: 59.579516 | AI38: 58.004895 | AJ38: 57.171326 | AK38: 67.724636 | AL38: 66.181738 | AM38: 64.516444 | AN38: 62.969981 | AO38: 60.862872 | AP38: 60.407526 | AQ38: 59.433835 | AR38: 59.066951 | AS38: 57.981814 | AT38: 57.981814 | AU38: 57.981814 | AV38: 57.981814 | AW38: 57.981814
C39: DC 2h 1.5cy 2030 direct | D39: EUR/MWh | J39: 0 | K39: 0 | L39: 0 | M39: 0 | N39: 0 | O39: 62.693931 | P39: 63.279601 | Q39: 57.920576 | R39: 57.487356 | S39: 52.198963 | T39: 50.688957 | U39: 49.649229 | V39: 53.274742 | W39: 52.839031 | X39: 51.730359 | Y39: 49.502394 | Z39: 47.256307 | AA39: 47.868696 | AB39: 47.3048 | AC39: 46.677679 | AD39: 48.555079 | AE39: 48.661643 | AF39: 49.449238 | AG39: 48.399821 | AH39: 47.878595 | AI39: 46.972557 | AJ39: 46.860056 | AK39: 46.262424 | AL39: 45.597747 | AM39: 45.039769 | AN39: 44.52662 | AO39: 43.769958 | AP39: 43.626343 | AQ39: 42.875757 | AR39: 42.868088 | AS39: 42.366441 | AT39: 42.366441 | AU39: 42.366441 | AV39: 42.366441 | AW39: 42.366441
C40: DC 4h transfer | D40: EUR/MWh | J40: 0 | K40: 0 | L40: 36.551423 | M40: 36.097357 | N40: 35.996376 | O40: 29.77703 | P40: 31.636148 | Q40: 27.42858 | R40: 30.352489 | S40: 26.813027 | T40: 26.596533 | U40: 26.460903 | V40: 28.163462 | W40: 29.492749 | X40: 28.037109 | Y40: 27.233291 | Z40: 25.066688 | AA40: 24.191368 | AB40: 24.216529 | AC40: 22.625349 | AD40: 23.382458 | AE40: 24.462475 | AF40: 22.629013 | AG40: 18.91539 | AH40: 22.466774 | AI40: 20.973221 | AJ40: 20.34225 | AK40: 18.850295 | AL40: 19.550285 | AM40: 19.055435 | AN40: 18.401118 | AO40: 17.800007 | AP40: 18.265574 | AQ40: 19.412634 | AR40: 20.635924 | AS40: 20.340431 | AT40: 20.340431 | AU40: 20.340431 | AV40: 20.340431 | AW40: 20.340431
C41: DC 2h transfer | D41: EUR/MWh | J41: 0 | K41: 0 | L41: 33.023974 | M41: 33.141213 | N41: 33.466048 | O41: 31.04554 | P41: 33.172509 | Q41: 28.591635 | R41: 31.553597 | S41: 28.861867 | T41: 29.065848 | U41: 27.355375 | V41: 29.102814 | W41: 29.159744 | X41: 28.653022 | Y41: 26.564583 | Z41: 24.28655 | AA41: 22.537967 | AB41: 23.462371 | AC41: 21.41509 | AD41: 22.214485 | AE41: 22.970048 | AF41: 21.394321 | AG41: 18.472763 | AH41: 19.249735 | AI41: 17.754987 | AJ41: 16.631675 | AK41: 15.769368 | AL41: 16.723233 | AM41: 16.19841 | AN41: 15.440636 | AO41: 15.045102 | AP41: 16.026328 | AQ41: 17.181861 | AR41: 19.048647 | AS41: 19.173193 | AT41: 19.173193 | AU41: 19.173193 | AV41: 19.173193 | AW41: 19.173193
C42: DC 2h 1.5cy transfer | D42: EUR/MWh | J42: 0 | K42: 0 | L42: 44.617385 | M42: 43.899406 | N42: 41.982546 | O42: 37.05035 | P42: 40.470618 | Q42: 37.242679 | R42: 41.092166 | S42: 38.587058 | T42: 39.572829 | U42: 40.743539 | V42: 41.396338 | W42: 42.326672 | X42: 41.683712 | Y42: 40.920411 | Z42: 38.679266 | AA42: 37.627564 | AB42: 38.906648 | AC42: 40.758918 | AD42: 40.874471 | AE42: 41.966451 | AF42: 39.175537 | AG42: 33.634636 | AH42: 33.639209 | AI42: 32.205861 | AJ42: 30.708781 | AK42: 28.685588 | AL42: 30.501997 | AM42: 29.298482 | AN42: 28.744962 | AO42: 27.011886 | AP42: 28.057637 | AQ42: 30.731584 | AR42: 33.203539 | AS42: 32.244968 | AT42: 32.244968 | AU42: 32.244968 | AV42: 32.244968 | AW42: 32.244968
C43: DC 4h 2030 transfer | D43: EUR/MWh | J43: 0 | K43: 0 | L43: 0 | M43: 0 | N43: 0 | O43: 30.315776 | P43: 31.849777 | Q43: 27.7096 | R43: 30.282906 | S43: 26.735758 | T43: 26.618476 | U43: 27.086578 | V43: 28.814559 | W43: 29.775652 | X43: 28.066023 | Y43: 27.107955 | Z43: 25.243238 | AA43: 24.12802 | AB43: 24.229836 | AC43: 22.697181 | AD43: 23.539019 | AE43: 24.718921 | AF43: 23.026195 | AG43: 18.778533 | AH43: 19.542868 | AI43: 18.779579 | AJ43: 18.675949 | AK43: 19.933274 | AL43: 20.072103 | AM43: 19.599791 | AN43: 18.859533 | AO43: 17.956064 | AP43: 18.978811 | AQ43: 19.640276 | AR43: 21.161142 | AS43: 20.772434 | AT43: 20.772434 | AU43: 20.772434 | AV43: 20.772434 | AW43: 20.772434
... C45: Baseload (info) | D45: EUR/MWh | J45: 0 | K45: 120.53 | L45: 119.34 | M45: 110 | N45: 103.08 | O45: 94.89 | P45: 98.51 | Q45: 96.1 | R45: 96.72 | S45: 93.13 | T45: 92.97 | U45: 93.04 | V45: 96.63 | W45: 95.76 | X45: 95.26 | Y45: 93.94 | Z45: 92.79 | AA45: 93.62 | AB45: 93.93 | AC45: 93.16 | AD45: 94.99 | AE45: 95.37 | AF45: 95.19 | AG45: 93.3 | AH45: 93.51 | AI45: 92.38 | AJ45: 91.45 | AK45: 89.7 | AL45: 90.71 | AM45: 90.37 | AN45: 90.08 | AO45: 88.97 | AP45: 89.89 | AQ45: 92.13 | AR45: 93.73 | AS45: 92.71 | AT45: 92.71 | AU45: 92.71 | AV45: 92.71 | AW45: 92.71
D46: EUR/MWh
D47: EUR/MWh
C48: Aurora euro inflation index (2025 = 1; +2 % a year after 2060) | D48: index | E48: Aurora Common Assumptions row 14 | J48: 1 | K48: 1.01897 | L48: 1.040399 | M48: 1.061363 | N48: 1.083026 | O48: 1.105173 | P48: 1.127276 | Q48: 1.149822 | R48: 1.172818 | S48: 1.196275 | T48: 1.2202 | U48: 1.244604 | V48: 1.269496 | W48: 1.294886 | X48: 1.320784 | Y48: 1.3472 | Z48: 1.374144 | AA48: 1.401627 | AB48: 1.429659 | AC48: 1.458252 | AD48: 1.487417 | AE48: 1.517166 | AF48: 1.547509 | AG48: 1.578459 | AH48: 1.610028 | AI48: 1.642229 | AJ48: 1.675074 | AK48: 1.708575 | AL48: 1.742746 | AM48: 1.777601 | AN48: 1.813153 | AO48: 1.849417 | AP48: 1.886405 | AQ48: 1.924133 | AR48: 1.962616 | AS48: 2.001868 | AT48: 2.0419054 | AU48: 2.0827435 | AV48: 2.1243983 | AW48: 2.1668863
A50: x | C50: BESS storage total cashflow, real 2025 (Aurora block row s+27; v3: Aurora_Curve AB) | E50: Fixed Aurora dispatch: no re-optimisation
C51: Year | J51: 2025 | K51: 2026 | L51: 2027 | M51: 2028 | N51: 2029 | O51: 2030 | P51: 2031 | Q51: 2032 | R51: 2033 | S51: 2034 | T51: 2035 | U51: 2036 | V51: 2037 | W51: 2038 | X51: 2039 | Y51: 2040 | Z51: 2041 | AA51: 2042 | AB51: 2043 | AC51: 2044 | AD51: 2045 | AE51: 2046 | AF51: 2047 | AG51: 2048 | AH51: 2049 | AI51: 2050 | AJ51: 2051 | AK51: 2052 | AL51: 2053 | AM51: 2054 | AN51: 2055 | AO51: 2056 | AP51: 2057 | AQ51: 2058 | AR51: 2059 | AS51: 2060 | AT51: 2061 | AU51: 2062 | AV51: 2063 | AW51: 2064
C52: v3 BESS | D52: EUR k/MW | J52: 0 | K52: 0 | L52: 93.389022 | M52: 78.518855 | N52: 59.435142 | O52: 51.3737 | P52: 50.188142 | Q52: 52.538761 | R52: 46.66525 | S52: 42.664567 | T52: 42.566214 | U52: 39.641929 | V52: 40.853887 | W52: 39.21916 | X52: 39.025938 | Y52: 38.051382 | Z52: 35.722098 | AA52: 37.425267 | AB52: 36.870159 | AC52: 36.753016 | AD52: 36.591657 | AE52: 36.371979 | AF52: 37.200855 | AG52: 37.771523 | AH52: 45.424028 | AI52: 43.532867 | AJ52: 42.698641 | AK52: 42.5168 | AL52: 40.722544 | AM52: 39.725125 | AN52: 39.399921 | AO52: 40.353172 | AP52: 38.680711 | AQ52: 38.30918 | AR52: 37.975954 | AS52: 37.048555 | AT52: 37.048555 | AU52: 37.048555 | AV52: 37.048555 | AW52: 37.048555
C53: DC 4h | D53: EUR k/MW | J53: 0 | K53: 0 | L53: 186.97508 | M53: 163.09638 | N53: 126.19871 | O53: 110.60632 | P53: 109.76518 | Q53: 116.90163 | R53: 104.55695 | S53: 100.30601 | T53: 101.68627 | U53: 93.19838 | V53: 90.141566 | W53: 87.480792 | X53: 86.930013 | Y53: 89.101476 | Z53: 87.471327 | AA53: 86.695136 | AB53: 83.156189 | AC53: 80.857169 | AD53: 80.251742 | AE53: 82.595328 | AF53: 80.491717 | AG53: 81.954988 | AH53: 102.85961 | AI53: 101.83491 | AJ53: 100.55645 | AK53: 98.644736 | AL53: 98.913931 | AM53: 96.605269 | AN53: 96.595125 | AO53: 96.879634 | AP53: 92.897333 | AQ53: 94.085507 | AR53: 94.292553 | AS53: 91.148957 | AT53: 91.148957 | AU53: 91.148957 | AV53: 91.148957 | AW53: 91.148957
C54: DC 2h | D54: EUR k/MW | J54: 0 | K54: 0 | L54: 140.43076 | M54: 118.15523 | N54: 88.966994 | O54: 78.630159 | P54: 75.433148 | Q54: 80.146939 | R54: 71.389492 | S54: 68.816524 | T54: 69.657684 | U54: 63.149384 | V54: 61.105696 | W54: 59.18947 | X54: 59.451133 | Y54: 60.469608 | Z54: 59.115767 | AA54: 58.31418 | AB54: 56.064396 | AC54: 54.196884 | AD54: 53.116375 | AE54: 54.959463 | AF54: 54.040223 | AG54: 73.110529 | AH54: 71.16618 | AI54: 69.269448 | AJ54: 68.622599 | AK54: 67.230398 | AL54: 66.680016 | AM54: 65.353202 | AN54: 64.438004 | AO54: 64.081652 | AP54: 62.372566 | AQ54: 62.892224 | AR54: 63.230441 | AS54: 61.750194 | AT54: 61.750194 | AU54: 61.750194 | AV54: 61.750194 | AW54: 61.750194
C55: DC 2h 1.5cy | D55: EUR k/MW | J55: 0 | K55: 0 | L55: 146.22803 | M55: 120.92954 | N55: 89.610144 | O55: 74.559655 | P55: 71.666501 | Q55: 77.99007 | R55: 68.329502 | S55: 64.026952 | T55: 64.566261 | U55: 58.39811 | V55: 56.745521 | W55: 54.200613 | X55: 54.737791 | Y55: 55.321488 | Z55: 53.878505 | AA55: 52.728275 | AB55: 50.254385 | AC55: 66.518121 | AD55: 64.232588 | AE55: 65.981601 | AF55: 64.483605 | AG55: 64.950266 | AH55: 63.231413 | AI55: 62.139068 | AJ55: 61.569631 | AK55: 60.568633 | AL55: 59.925765 | AM55: 57.939806 | AN55: 57.705096 | AO55: 57.857965 | AP55: 54.88809 | AQ55: 54.969774 | AR55: 54.887275 | AS55: 53.099911 | AT55: 53.099911 | AU55: 53.099911 | AV55: 53.099911 | AW55: 53.099911
C56: Standalone 2h | D56: EUR k/MW | J56: 0 | K56: 0 | L56: 118.42575 | M56: 98.062815 | N56: 68.671355 | O56: 53.179736 | P56: 51.993307 | Q56: 58.888903 | R56: 49.589672 | S56: 46.314257 | T56: 47.761074 | U56: 40.672482 | V56: 40.24227 | W56: 38.517618 | X56: 40.286784 | Y56: 41.840577 | Z56: 40.351325 | AA56: 40.706267 | AB56: 37.288096 | AC56: 36.421801 | AD56: 36.375291 | AE56: 38.701097 | AF56: 38.157452 | AG56: 50.082597 | AH56: 49.181816 | AI56: 49.518508 | AJ56: 49.779418 | AK56: 50.188528 | AL56: 49.531838 | AM56: 47.804481 | AN56: 48.016719 | AO56: 48.436934 | AP56: 45.520902 | AQ56: 46.390906 | AR56: 46.877834 | AS56: 45.161947 | AT56: 45.161947 | AU56: 45.161947 | AV56: 45.161947 | AW56: 45.161947
C57: DC 4h 2030 | D57: EUR k/MW | J57: 0 | K57: 0 | L57: 0 | M57: 0 | N57: 0 | O57: 114.67249 | P57: 113.88472 | Q57: 120.59803 | R57: 108.52193 | S57: 104.0115 | T57: 105.11977 | U57: 96.455983 | V57: 93.647428 | W57: 90.500833 | X57: 90.236883 | Y57: 92.038904 | Z57: 90.557988 | AA57: 89.370901 | AB57: 85.961704 | AC57: 83.569122 | AD57: 82.777312 | AE57: 85.221742 | AF57: 83.064611 | AG57: 84.801151 | AH57: 84.106049 | AI57: 83.930061 | AJ57: 83.391003 | AK57: 102.91098 | AL57: 102.4465 | AM57: 100.1236 | AN57: 99.724659 | AO57: 99.944973 | AP57: 96.466085 | AQ57: 97.321934 | AR57: 97.156936 | AS57: 94.139924 | AT57: 94.139924 | AU57: 94.139924 | AV57: 94.139924 | AW57: 94.139924
C58: DC 2h 1.5cy 2030 | D58: EUR k/MW | J58: 0 | K58: 0 | L58: 0 | M58: 0 | N58: 0 | O58: 79.380515 | P58: 75.625851 | Q58: 82.040255 | R58: 71.510519 | S58: 67.392554 | T58: 67.855831 | U58: 61.406921 | V58: 59.799191 | W58: 57.014381 | X58: 57.456263 | Y58: 58.074289 | Z58: 56.600936 | AA58: 55.482088 | AB58: 52.832524 | AC58: 51.287255 | AD58: 50.493639 | AE58: 52.198911 | AF58: 69.041372 | AG58: 69.067029 | AH58: 66.682617 | AI58: 65.901129 | AJ58: 64.39371 | AK58: 63.424377 | AL58: 62.72778 | AM58: 60.645877 | AN58: 60.129583 | AO58: 60.31489 | AP58: 57.307844 | AQ58: 57.587057 | AR58: 57.420315 | AS58: 55.566206 | AT58: 55.566206 | AU58: 55.566206 | AV58: 55.566206 | AW58: 55.566206
D59: EUR k/MW
D60: EUR k/MW
A62: x | C62: BESS discharge volume (s+11; v3: U) | E62: Aurora Q2-26 Degraded batteries
C63: Year | J63: 2025 | K63: 2026 | L63: 2027 | M63: 2028 | N63: 2029 | O63: 2030 | P63: 2031 | Q63: 2032 | R63: 2033 | S63: 2034 | T63: 2035 | U63: 2036 | V63: 2037 | W63: 2038 | X63: 2039 | Y63: 2040 | Z63: 2041 | AA63: 2042 | AB63: 2043 | AC63: 2044 | AD63: 2045 | AE63: 2046 | AF63: 2047 | AG63: 2048 | AH63: 2049 | AI63: 2050 | AJ63: 2051 | AK63: 2052 | AL63: 2053 | AM63: 2054 | AN63: 2055 | AO63: 2056 | AP63: 2057 | AQ63: 2058 | AR63: 2059 | AS63: 2060 | AT63: 2061 | AU63: 2062 | AV63: 2063 | AW63: 2064
C64: v3 BESS | D64: MWh/MW | J64: 0 | K64: 0 | L64: 848.18621 | M64: 818.63997 | N64: 792.487 | O64: 776.06455 | P64: 761.75845 | Q64: 746.22864 | R64: 731.7511 | S64: 724.65717 | T64: 713.11771 | U64: 700.9989 | V64: 686.90562 | W64: 678.33378 | X64: 670.02206 | Y64: 664.40603 | Z64: 645.77854 | AA64: 642.52715 | AB64: 637.43134 | AC64: 625.12337 | AD64: 613.41838 | AE64: 604.41499 | AF64: 594.1347 | AG64: 594.28249 | AH64: 850.60406 | AI64: 817.59362 | AJ64: 791.66529 | AK64: 780.93571 | AL64: 760.60568 | AM64: 748.56964 | AN64: 736.75233 | AO64: 724.11921 | AP64: 711.40334 | AQ64: 697.96033 | AR64: 687.8101 | AS64: 680.99992 | AT64: 680.99992 | AU64: 680.99992 | AV64: 680.99992 | AW64: 680.99992
C65: DC 4h | D65: MWh/MW | J65: 0 | K65: 0 | L65: 1434.7848 | M65: 1384.8003 | N65: 1340.5561 | O65: 1312.7766 | P65: 1288.5815 | Q65: 1262.3118 | R65: 1237.8223 | S65: 1225.8242 | T65: 1206.3021 | U65: 1185.803 | V65: 1161.9555 | W65: 1147.4598 | X65: 1133.4 | Y65: 1123.9041 | Z65: 1092.3891 | AA65: 1086.8921 | AB65: 1078.267 | AC65: 1057.4522 | AD65: 1037.6458 | AE65: 1022.4241 | AF65: 1005.0335 | AG65: 1005.285 | AH65: 1438.8674 | AI65: 1383.0321 | AJ65: 1339.1729 | AK65: 1321.0198 | AL65: 1286.6306 | AM65: 1266.273 | AN65: 1246.2818 | AO65: 1224.9121 | AP65: 1203.4042 | AQ65: 1180.6573 | AR65: 1163.4895 | AS65: 1151.9674 | AT65: 1151.9674 | AU65: 1151.9674 | AV65: 1151.9674 | AW65: 1151.9674
C66: DC 2h | D66: MWh/MW | J66: 0 | K66: 0 | L66: 712.3509 | M66: 688.69816 | N66: 665.70296 | O66: 653.26519 | P66: 639.39988 | Q66: 629.51611 | R66: 616.22558 | S66: 605.25129 | T66: 595.5071 | U66: 579.5399 | V66: 578.70225 | W66: 561.00059 | X66: 555.77798 | Y66: 541.52266 | Z66: 538.20885 | AA66: 523.30606 | AB66: 514.09401 | AC66: 509.7306 | AD66: 500.79607 | AE66: 490.27415 | AF66: 480.16792 | AG66: 710.0536 | AH66: 685.1107 | AI66: 665.26126 | AJ66: 650.52353 | AK66: 637.33117 | AL66: 624.26843 | AM66: 614.56091 | AN66: 603.92325 | AO66: 594.89564 | AP66: 585.43579 | AQ66: 571.67911 | AR66: 560.95278 | AS66: 554.21737 | AT66: 554.21737 | AU66: 554.21737 | AV66: 554.21737 | AW66: 554.21737
C67: DC 2h 1.5cy | D67: MWh/MW | J67: 0 | K67: 0 | L67: 1066.1522 | M67: 1025.5952 | N67: 993.66438 | O67: 959.83229 | P67: 943.12528 | Q67: 918.70683 | R67: 900.67778 | S67: 883.82803 | T67: 863.22479 | U67: 845.1306 | V67: 824.58233 | W67: 804.15381 | X67: 788.51712 | Y67: 774.96736 | Z67: 756.40029 | AA67: 741.3062 | AB67: 732.253 | AC67: 1070.2 | AD67: 1022.0128 | AE67: 989.93879 | AF67: 962.40951 | AG67: 945.47553 | AH67: 917.28875 | AI67: 899.75929 | AJ67: 878.3704 | AK67: 862.76935 | AL67: 842.80061 | AM67: 824.6187 | AN67: 801.44755 | AO67: 790.50749 | AP67: 769.94356 | AQ67: 751.90913 | AR67: 738.21403 | AS67: 713.29026 | AT67: 713.29026 | AU67: 713.29026 | AV67: 713.29026 | AW67: 713.29026
C68: Standalone 2h | D68: MWh/MW | J68: 0 | K68: 0 | L68: 712.52307 | M68: 686.28031 | N68: 661.97949 | O68: 649.41051 | P68: 639.00662 | Q68: 628.87981 | R68: 616.66544 | S68: 604.90699 | T68: 588.70528 | U68: 583.39956 | V68: 580.14484 | W68: 567.939 | X68: 551.91209 | Y68: 545.62323 | Z68: 543.77859 | AA68: 520.78236 | AB68: 518.5894 | AC68: 506.52958 | AD68: 488.34186 | AE68: 483.72635 | AF68: 479.14783 | AG68: 710.4282 | AH68: 689.65961 | AI68: 671.35847 | AJ68: 655.4655 | AK68: 633.5158 | AL68: 621.5539 | AM68: 617.01645 | AN68: 600.18272 | AO68: 593.5401 | AP68: 582.07012 | AQ68: 575.98556 | AR68: 563.01324 | AS68: 554.52858 | AT68: 554.52858 | AU68: 554.52858 | AV68: 554.52858 | AW68: 554.52858
C69: DC 4h 2030 | D69: MWh/MW | J69: 0 | K69: 0 | L69: 0 | M69: 0 | N69: 0 | O69: 1432.9301 | P69: 1381.576 | Q69: 1352.0633 | R69: 1307.3702 | S69: 1281.5431 | T69: 1260.9787 | U69: 1252.4727 | V69: 1222.8934 | W69: 1206.41 | X69: 1182.2123 | Y69: 1167.7608 | Z69: 1139.9153 | AA69: 1129.2583 | AB69: 1115.7535 | AC69: 1100.3738 | AD69: 1086.223 | AE69: 1067.2913 | AF69: 1049.8782 | AG69: 1037.0855 | AH69: 1021.2336 | AI69: 1008.1694 | AJ69: 998.87201 | AK69: 1437.6374 | AL69: 1377.2843 | AM69: 1347.1813 | AN69: 1310.9826 | AO69: 1285.4215 | AP69: 1265.2348 | AQ69: 1237.7721 | AR69: 1222.2864 | AS69: 1209.9598 | AT69: 1209.9598 | AU69: 1209.9598 | AV69: 1209.9598 | AW69: 1209.9598
C70: DC 2h 1.5cy 2030 | D70: MWh/MW | J70: 0 | K70: 0 | L70: 0 | M70: 0 | N70: 0 | O70: 1062.8112 | P70: 1021.0947 | Q70: 987.76315 | R70: 965.97914 | S70: 941.20539 | T70: 922.93639 | U70: 903.56048 | V70: 874.8549 | W70: 861.7215 | X70: 842.52899 | Y70: 818.83583 | Z70: 803.00808 | AA70: 786.45427 | AB70: 768.93891 | AC70: 760.12314 | AD70: 736.18932 | AE70: 728.50435 | AF70: 1069.1758 | AG70: 1023.663 | AH70: 991.38152 | AI70: 964.78191 | AJ70: 947.21719 | AK70: 924.00629 | AL70: 894.7314 | AM70: 878.07872 | AN70: 861.44174 | AO70: 846.79175 | AP70: 819.57956 | AQ70: 804.0606 | AR70: 791.43332 | AS70: 777.84498 | AT70: 777.84498 | AU70: 777.84498 | AV70: 777.84498 | AW70: 777.84498
D71: MWh/MW
D72: MWh/MW
A74: x | C74: BESS charge from PV (s+13, negative; v3: Z) | E74: Aurora Q2-26 Degraded batteries
C75: Year | J75: 2025 | K75: 2026 | L75: 2027 | M75: 2028 | N75: 2029 | O75: 2030 | P75: 2031 | Q75: 2032 | R75: 2033 | S75: 2034 | T75: 2035 | U75: 2036 | V75: 2037 | W75: 2038 | X75: 2039 | Y75: 2040 | Z75: 2041 | AA75: 2042 | AB75: 2043 | AC75: 2044 | AD75: 2045 | AE75: 2046 | AF75: 2047 | AG75: 2048 | AH75: 2049 | AI75: 2050 | AJ75: 2051 | AK75: 2052 | AL75: 2053 | AM75: 2054 | AN75: 2055 | AO75: 2056 | AP75: 2057 | AQ75: 2058 | AR75: 2059 | AS75: 2060 | AT75: 2061 | AU75: 2062 | AV75: 2063 | AW75: 2064
C76: v3 BESS | D76: MWh/MW | J76: 0 | K76: 0 | L76: -992.69 | M76: -1020.72 | N76: -1012.64 | O76: -1008.41 | P76: -990.23 | Q76: -965.73 | R76: -971.99 | S76: -972.86 | T76: -968 | U76: -946.55 | V76: -903.12 | W76: -915.28 | X76: -884.89 | Y76: -884.95 | Z76: -864.13 | AA76: -842.22 | AB76: -840.99 | AC76: -817.13 | AD76: -792.77 | AE76: -779.27 | AF76: -745.07 | AG76: -713.84 | AH76: -1040.09 | AI76: -993.66 | AJ76: -962 | AK76: -930.54 | AL76: -926.41 | AM76: -914.1 | AN76: -891.8 | AO76: -870.14 | AP76: -864.32 | AQ76: -866.71 | AR76: -855.43 | AS76: -841.29 | AT76: -841.29 | AU76: -841.29 | AV76: -841.29 | AW76: -841.29
C77: DC 4h | D77: MWh/MW | J77: 0 | K77: 0 | L77: -992.69296 | M77: -1020.716 | N77: -1012.6381 | O77: -1008.4149 | P77: -990.22906 | Q77: -965.72765 | R77: -971.9878 | S77: -972.86154 | T77: -967.99641 | U77: -946.54846 | V77: -903.12287 | W77: -915.28429 | X77: -884.89008 | Y77: -884.94627 | Z77: -864.12541 | AA77: -842.22332 | AB77: -840.9919 | AC77: -817.1254 | AD77: -792.76727 | AE77: -779.27492 | AF77: -745.06588 | AG77: -713.83809 | AH77: -1040.0928 | AI77: -993.65772 | AJ77: -961.99609 | AK77: -930.5436 | AL77: -926.40611 | AM77: -914.09784 | AN77: -891.80399 | AO77: -870.13693 | AP77: -864.3226 | AQ77: -866.71026 | AR77: -855.4343 | AS77: -841.29448 | AT77: -841.29448 | AU77: -841.29448 | AV77: -841.29448 | AW77: -841.29448
C78: DC 2h | D78: MWh/MW | J78: 0 | K78: 0 | L78: -517.39936 | M78: -503.75826 | N78: -494.19894 | O78: -515.26979 | P78: -504.78772 | Q78: -483.86296 | R78: -489.08415 | S78: -489.72665 | T78: -487.43204 | U78: -465.75252 | V78: -443.86825 | W78: -439.47313 | X78: -428.34504 | Y78: -417.96162 | Z78: -406.94002 | AA78: -383.06172 | AB78: -386.70185 | AC78: -371.93938 | AD78: -360.44081 | AE78: -353.99731 | AF78: -343.14011 | AG78: -484.85582 | AH78: -469.45094 | AI78: -444.4129 | AJ78: -426.23549 | AK78: -414.2078 | AL78: -415.66845 | AM78: -410.54324 | AN78: -394.779 | AO78: -389.49482 | AP78: -392.62927 | AQ78: -390.39303 | AR78: -391.85038 | AS78: -394.13305 | AT78: -394.13305 | AU78: -394.13305 | AV78: -394.13305 | AW78: -394.13305
C79: DC 2h 1.5cy | D79: MWh/MW | J79: 0 | K79: 0 | L79: -650.4299 | M79: -639.8194 | N79: -617.58729 | O79: -597.34503 | P79: -594.61375 | Q79: -578.72148 | R79: -591.21184 | S79: -581.8977 | T79: -581.9003 | U79: -577.28048 | V79: -538.7837 | W79: -537.93051 | X79: -519.67227 | Y79: -524.56808 | Z79: -507.6439 | AA79: -479.07997 | AB79: -487.27326 | AC79: -740.30919 | AD79: -680.23479 | AE79: -665.97215 | AF79: -613.33527 | AG79: -567.89019 | AH79: -554.2333 | AI79: -532.09253 | AJ79: -508.01451 | AK79: -485.7871 | AL79: -489.82707 | AM79: -475.80144 | AN79: -461.7635 | AO79: -446.26794 | AP79: -442.94922 | AQ79: -454.38545 | AR79: -456.79348 | AS79: -441.77614 | AT79: -441.77614 | AU79: -441.77614 | AV79: -441.77614 | AW79: -441.77614
C80: Standalone 2h | D80: MWh/MW | J80: 0 | K80: 0 | L80: 0 | M80: 0 | N80: 0 | O80: 0 | P80: 0 | Q80: 0 | R80: 0 | S80: 0 | T80: 0 | U80: 0 | V80: 0 | W80: 0 | X80: 0 | Y80: 0 | Z80: 0 | AA80: 0 | AB80: 0 | AC80: 0 | AD80: 0 | AE80: 0 | AF80: 0 | AG80: 0 | AH80: 0 | AI80: 0 | AJ80: 0 | AK80: 0 | AL80: 0 | AM80: 0 | AN80: 0 | AO80: 0 | AP80: 0 | AQ80: 0 | AR80: 0 | AS80: 0 | AT80: 0 | AU80: 0 | AV80: 0 | AW80: 0
C81: DC 4h 2030 | D81: MWh/MW | J81: 0 | K81: 0 | L81: 0 | M81: 0 | N81: 0 | O81: -1071.4204 | P81: -1044.757 | Q81: -1014.2627 | R81: -1013.5967 | S81: -1011.5912 | T81: -1007.7716 | U81: -993.89891 | V81: -950.30836 | W81: -957.04167 | X81: -924.40536 | Y81: -919.66365 | Z81: -901.55111 | AA81: -876.61724 | AB81: -875.89181 | AC81: -852.55133 | AD81: -829.91741 | AE81: -816.44176 | AF81: -784.65124 | AG81: -744.11217 | AH81: -736.07488 | AI81: -713.23231 | AJ81: -702.21155 | AK81: -1011.9574 | AL81: -991.54784 | AM81: -972.48363 | AN81: -940.48393 | AO81: -913.08882 | AP81: -915.80674 | AQ81: -908.38009 | AR81: -898.62001 | AS81: -888.02299 | AT81: -888.02299 | AU81: -888.02299 | AV81: -888.02299 | AW81: -888.02299
C82: DC 2h 1.5cy 2030 | D82: MWh/MW | J82: 0 | K82: 0 | L82: 0 | M82: 0 | N82: 0 | O82: -662.6859 | P82: -644.37785 | Q82: -621.50058 | R82: -637.34172 | S82: -625.13008 | T82: -623.79116 | U82: -620.87629 | V82: -574.69615 | W82: -582.8038 | X82: -560.52 | Y82: -556.30179 | Z82: -542.1517 | AA82: -508.58563 | AB82: -515.21259 | AC82: -493.51136 | AD82: -468.12527 | AE82: -471.24877 | AF82: -695.71703 | AG82: -620.24041 | AH82: -603.60355 | AI82: -580.64433 | AJ82: -552.88844 | AK82: -523.36739 | AL82: -523.24905 | AM82: -510.57705 | AN82: -495.13274 | AO82: -479.38508 | AP82: -473.87255 | AQ82: -484.51348 | AR82: -490.50907 | AS82: -477.19206 | AT82: -477.19206 | AU82: -477.19206 | AV82: -477.19206 | AW82: -477.19206
D83: MWh/MW
D84: MWh/MW
A86: x | C86: BESS charge from the grid (s+12, negative) | E86: Aurora Q2-26 Degraded batteries
C87: Year | J87: 2025 | K87: 2026 | L87: 2027 | M87: 2028 | N87: 2029 | O87: 2030 | P87: 2031 | Q87: 2032 | R87: 2033 | S87: 2034 | T87: 2035 | U87: 2036 | V87: 2037 | W87: 2038 | X87: 2039 | Y87: 2040 | Z87: 2041 | AA87: 2042 | AB87: 2043 | AC87: 2044 | AD87: 2045 | AE87: 2046 | AF87: 2047 | AG87: 2048 | AH87: 2049 | AI87: 2050 | AJ87: 2051 | AK87: 2052 | AL87: 2053 | AM87: 2054 | AN87: 2055 | AO87: 2056 | AP87: 2057 | AQ87: 2058 | AR87: 2059 | AS87: 2060 | AT87: 2061 | AU87: 2062 | AV87: 2063 | AW87: 2064
C88: v3 BESS | D88: MWh/MW | J88: 0 | K88: 0 | L88: 0 | M88: 0 | N88: 0 | O88: 0 | P88: 0 | Q88: 0 | R88: 0 | S88: 0 | T88: 0 | U88: 0 | V88: 0 | W88: 0 | X88: 0 | Y88: 0 | Z88: 0 | AA88: 0 | AB88: 0 | AC88: 0 | AD88: 0 | AE88: 0 | AF88: 0 | AG88: 0 | AH88: 0 | AI88: 0 | AJ88: 0 | AK88: 0 | AL88: 0 | AM88: 0 | AN88: 0 | AO88: 0 | AP88: 0 | AQ88: 0 | AR88: 0 | AS88: 0 | AT88: 0 | AU88: 0 | AV88: 0 | AW88: 0
C89: DC 4h | D89: MWh/MW | J89: 0 | K89: 0 | L89: -751.2864 | M89: -663.46514 | N89: -620.42262 | O89: -590.15109 | P89: -581.20382 | Q89: -575.76335 | R89: -541.56006 | S89: -528.87975 | T89: -511.53463 | U89: -508.93701 | V89: -526.89342 | W89: -498.38111 | X89: -514.22704 | Y89: -503.78846 | Z89: -488.23638 | AA89: -508.20078 | AB89: -499.94889 | AC89: -500.04075 | AD89: -503.09869 | AE89: -497.34921 | AF89: -514.43421 | AG89: -548.94787 | AH89: -707.19545 | AI89: -688.10432 | AJ89: -668.95651 | AK89: -681.69469 | AL89: -644.57209 | AM89: -635.13038 | AN89: -635.28835 | AO89: -632.34774 | AP89: -615.02274 | AQ89: -586.07772 | AR89: -576.86721 | AS89: -579.51105 | AT89: -579.51105 | AU89: -579.51105 | AV89: -579.51105 | AW89: -579.51105
C90: DC 2h | D90: MWh/MW | J90: 0 | K90: 0 | L90: -347.67852 | M90: -334.7215 | N90: -317.32045 | O90: -279.99472 | P90: -274.18403 | Q90: -284.64553 | R90: -264.13033 | S90: -252.11476 | T90: -243.3016 | U90: -245.64536 | V90: -269.7053 | W90: -252.99541 | X90: -259.18777 | Y90: -251.40765 | Z90: -260.6881 | AA90: -267.81759 | AB90: -253.53239 | AC90: -263.12163 | AD90: -265.6707 | AE90: -259.73315 | AF90: -258.86703 | AG90: -378.80366 | AH90: -364.70471 | AI90: -367.24234 | AJ90: -368.86086 | AK90: -364.94823 | AL90: -349.60405 | AM90: -343.86618 | AN90: -347.99814 | AO90: -342.31595 | AP90: -329.46696 | AQ90: -314.57883 | AR90: -300.67644 | AS90: -290.7825 | AT90: -290.7825 | AU90: -290.7825 | AV90: -290.7825 | AW90: -290.7825
C91: DC 2h 1.5cy | D91: MWh/MW | J91: 0 | K91: 0 | L91: -648.92762 | M91: -610.54782 | N91: -596.4748 | O91: -577.15028 | P91: -560.95109 | Q91: -547.88403 | R91: -514.98988 | S91: -505.21593 | T91: -481.2368 | U91: -464.26504 | V91: -480.43618 | W91: -457.18984 | X91: -458.00563 | Y91: -437.02661 | Z91: -432.98448 | AA91: -444.46693 | AB91: -426.12136 | AC91: -560.50344 | AD91: -565.22079 | AE91: -541.98678 | AF91: -564.03058 | AG91: -591.31508 | AH91: -572.62726 | AI91: -575.28511 | AJ91: -575.04485 | AK91: -578.99043 | AL91: -552.50183 | AM91: -545.73207 | AN91: -532.61691 | AO91: -535.50369 | AP91: -515.32686 | AQ91: -482.21341 | AR91: -463.77482 | AS91: -448.58832 | AT91: -448.58832 | AU91: -448.58832 | AV91: -448.58832 | AW91: -448.58832
C92: Standalone 2h | D92: MWh/MW | J92: 0 | K92: 0 | L92: -881.31388 | M92: -851.05247 | N92: -822.18191 | O92: -807.10748 | P92: -794.13143 | Q92: -782.76965 | R92: -768.89542 | S92: -756.54772 | T92: -737.15195 | U92: -730.51832 | V92: -729.27165 | W92: -714.42094 | X92: -695.47226 | Y92: -687.84865 | Z92: -687.24116 | AA92: -659.65997 | AB92: -657.89093 | AC92: -642.49726 | AD92: -621.42569 | AE92: -616.3424 | AF92: -611.58161 | AG92: -879.37939 | AH92: -855.17876 | AI92: -833.30145 | AJ92: -814.64775 | AK92: -787.85148 | AL92: -775.12916 | AM92: -770.8944 | AN92: -750.77947 | AO92: -742.15584 | AP92: -730.54804 | AQ92: -723.89189 | AR92: -707.57328 | AS92: -697.50521 | AT92: -697.50521 | AU92: -697.50521 | AV92: -697.50521 | AW92: -697.50521
C93: DC 4h 2030 | D93: MWh/MW | J93: 0 | K93: 0 | L93: 0 | M93: 0 | N93: 0 | O93: -666.9335 | P93: -632.83364 | Q93: -629.87956 | R93: -577.98019 | S93: -551.23901 | T93: -531.71185 | U93: -537.49644 | V93: -547.68806 | W93: -522.45976 | X93: -528.08459 | Y93: -516.5111 | Z93: -503.01606 | AA93: -519.78017 | AB93: -504.93521 | AC93: -511.64624 | AD93: -520.26231 | AE93: -510.35988 | AF93: -524.80808 | AG93: -551.42321 | AH93: -540.35221 | AI93: -549.27301 | AJ93: -550.37748 | AK93: -735.73861 | AL93: -682.37798 | AM93: -668.07666 | AN93: -658.35593 | AO93: -656.32867 | AP93: -632.07407 | AQ93: -607.58423 | AR93: -599.66574 | AS93: -597.56712 | AT93: -597.56712 | AU93: -597.56712 | AV93: -597.56712 | AW93: -597.56712
C94: DC 2h 1.5cy 2030 | D94: MWh/MW | J94: 0 | K94: 0 | L94: 0 | M94: 0 | N94: 0 | O94: -631.87962 | P94: -601.00951 | Q94: -584.34645 | R94: -543.54306 | S94: -527.25621 | T94: -507.61688 | U94: -487.27433 | V94: -501.59162 | W94: -478.44223 | X94: -479.13188 | Y94: -454.9382 | Z94: -451.70158 | AA94: -466.67088 | AB94: -439.57213 | AC94: -451.79608 | AD94: -449.12247 | AE94: -437.81977 | AF94: -605.59638 | AG94: -628.9652 | AH94: -608.54467 | AI94: -600.9962 | AJ94: -609.54125 | AK94: -611.69884 | AL94: -578.11806 | AM94: -572.04733 | AN94: -568.7781 | AO94: -567.39889 | AP94: -541.38685 | AQ94: -512.44466 | AR94: -491.81402 | AS94: -489.45141 | AT94: -489.45141 | AU94: -489.45141 | AV94: -489.45141 | AW94: -489.45141
D95: MWh/MW
D96: MWh/MW
A98: x | C98: Stack kept with PV-only charging: [(s+14+s+16)×MIN(1,−s+13×RTE÷(s+5+s+7))+s+20+s+22]÷s+27 | E98: Aurora s+5…s+27, Inputs C17; v3: scaled
C99: Year | J99: 2025 | K99: 2026 | L99: 2027 | M99: 2028 | N99: 2029 | O99: 2030 | P99: 2031 | Q99: 2032 | R99: 2033 | S99: 2034 | T99: 2035 | U99: 2036 | V99: 2037 | W99: 2038 | X99: 2039 | Y99: 2040 | Z99: 2041 | AA99: 2042 | AB99: 2043 | AC99: 2044 | AD99: 2045 | AE99: 2046 | AF99: 2047 | AG99: 2048 | AH99: 2049 | AI99: 2050 | AJ99: 2051 | AK99: 2052 | AL99: 2053 | AM99: 2054 | AN99: 2055 | AO99: 2056 | AP99: 2057 | AQ99: 2058 | AR99: 2059 | AS99: 2060 | AT99: 2061 | AU99: 2062 | AV99: 2063 | AW99: 2064
C100: v3 BESS | D100: factor | J100: 1 | K100: 1 | L100: 1 | M100: 1 | N100: 1 | O100: 1 | P100: 1 | Q100: 1 | R100: 1 | S100: 1 | T100: 1 | U100: 1 | V100: 1 | W100: 1 | X100: 1 | Y100: 1 | Z100: 1 | AA100: 1 | AB100: 1 | AC100: 1 | AD100: 1 | AE100: 1 | AF100: 1 | AG100: 1 | AH100: 1 | AI100: 1 | AJ100: 1 | AK100: 1 | AL100: 1 | AM100: 1 | AN100: 1 | AO100: 1 | AP100: 1 | AQ100: 1 | AR100: 1 | AS100: 1 | AT100: 1 | AU100: 1 | AV100: 1 | AW100: 1
C101: DC 4h | D101: factor | J101: 1 | K101: 1 | L101: 0.77913121 | M101: 0.83310759 | N101: 0.87953311 | O101: 0.93620913 | P101: 0.93591969 | Q101: 0.91366404 | R101: 0.96268705 | S101: 0.98225316 | T101: 0.96018823 | U101: 0.99842128 | V101: 1.0153679 | W101: 1.0299328 | X101: 1.0052192 | Y101: 0.97384649 | Z101: 0.97115468 | AA101: 0.98764901 | AB101: 1.033289 | AC101: 1.0369333 | AD101: 1.0269507 | AE101: 0.955154 | AF101: 0.96676906 | AG101: 0.91908175 | AH101: 0.96270223 | AI101: 0.92964227 | AJ101: 0.90956446 | AK101: 0.89029109 | AL101: 0.89025823 | AM101: 0.90360474 | AN101: 0.88243113 | AO101: 0.8668363 | AP101: 0.90558892 | AQ101: 0.91541745 | AR101: 0.90722667 | AS101: 0.91178898 | AT101: 0.91178898 | AU101: 0.91178898 | AV101: 0.91178898 | AW101: 0.91178898
C102: DC 2h | D102: factor | J102: 1 | K102: 1 | L102: 0.67482779 | M102: 0.7119263 | N102: 0.73964105 | O102: 0.78681315 | P102: 0.79374569 | Q102: 0.77682003 | R102: 0.83033574 | S102: 0.83859257 | T102: 0.80943608 | U102: 0.8438218 | V102: 0.85827021 | W102: 0.86397922 | X102: 0.83934644 | Y102: 0.8083027 | Z102: 0.80378676 | AA102: 0.80786013 | AB102: 0.83727881 | AC102: 0.85071154 | AD102: 0.853393 | AE102: 0.80398122 | AF102: 0.81312806 | AG102: 0.78975517 | AH102: 0.7844513 | AI102: 0.75812251 | AJ102: 0.74393311 | AK102: 0.72558457 | AL102: 0.73118206 | AM102: 0.74618058 | AN102: 0.73057594 | AO102: 0.72942034 | AP102: 0.76253467 | AQ102: 0.77191935 | AR102: 0.74918241 | AS102: 0.75349377 | AT102: 0.75349377 | AU102: 0.75349377 | AV102: 0.75349377 | AW102: 0.75349377
C103: DC 2h 1.5cy | D103: factor | J103: 1 | K103: 1 | L103: 0.68844264 | M103: 0.73415825 | N103: 0.78542251 | O103: 0.83603954 | P103: 0.85211609 | Q103: 0.81391746 | R103: 0.88463308 | S103: 0.90442482 | T103: 0.88212231 | U103: 0.92852974 | V103: 0.93379701 | W103: 0.95174247 | X103: 0.91827837 | Y103: 0.89806822 | Z103: 0.89574942 | AA103: 0.90306092 | AB103: 0.95027503 | AC103: 0.99697513 | AD103: 0.97339434 | AE103: 0.91518896 | AF103: 0.91008376 | AG103: 0.86361988 | AH103: 0.8637109 | AI103: 0.8410292 | AJ103: 0.82188439 | AK103: 0.79720823 | AL103: 0.8065352 | AM103: 0.8271043 | AN103: 0.80775488 | AO103: 0.79091286 | AP103: 0.83732236 | AQ103: 0.85336354 | AR103: 0.85636042 | AS103: 0.85998526 | AT103: 0.85998526 | AU103: 0.85998526 | AV103: 0.85998526 | AW103: 0.85998526
C104: Standalone 2h | D104: factor | J104: 1 | K104: 1 | L104: 1 | M104: 1 | N104: 1 | O104: 1 | P104: 1 | Q104: 1 | R104: 1 | S104: 1 | T104: 1 | U104: 1 | V104: 1 | W104: 1 | X104: 1 | Y104: 1 | Z104: 1 | AA104: 1 | AB104: 1 | AC104: 1 | AD104: 1 | AE104: 1 | AF104: 1 | AG104: 1 | AH104: 1 | AI104: 1 | AJ104: 1 | AK104: 1 | AL104: 1 | AM104: 1 | AN104: 1 | AO104: 1 | AP104: 1 | AQ104: 1 | AR104: 1 | AS104: 1 | AT104: 1 | AU104: 1 | AV104: 1 | AW104: 1
C105: DC 4h 2030 | D105: factor | J105: 1 | K105: 1 | L105: 1 | M105: 1 | N105: 1 | O105: 0.93643935 | P105: 0.93682145 | Q105: 0.91271523 | R105: 0.96157976 | S105: 0.9797205 | T105: 0.95989754 | U105: 1.0008641 | V105: 1.0132431 | W105: 1.0301504 | X105: 1.0046482 | Y105: 0.97567729 | Z105: 0.97149098 | AA105: 0.99095339 | AB105: 1.0338203 | AC105: 1.0402259 | AD105: 1.0328216 | AE105: 0.96345659 | AF105: 0.97376068 | AG105: 0.91836188 | AH105: 0.91169387 | AI105: 0.87667643 | AJ105: 0.86417969 | AK105: 0.90506689 | AL105: 0.90594701 | AM105: 0.91443856 | AN105: 0.89065824 | AO105: 0.87277889 | AP105: 0.91212741 | AQ105: 0.91833406 | AR105: 0.91451469 | AS105: 0.9201474 | AT105: 0.9201474 | AU105: 0.9201474 | AV105: 0.9201474 | AW105: 0.9201474
C106: DC 2h 1.5cy 2030 | D106: factor | J106: 1 | K106: 1 | L106: 1 | M106: 1 | N106: 1 | O106: 0.85257785 | P106: 0.86557696 | Q106: 0.82291932 | R106: 0.89650545 | S106: 0.9106757 | T106: 0.88914912 | U106: 0.93335057 | V106: 0.93699296 | W106: 0.95663008 | X106: 0.92282365 | Y106: 0.90260356 | Z106: 0.89895947 | AA106: 0.90335065 | AB106: 0.95153312 | AC106: 0.9582056 | AD106: 0.94088824 | AE106: 0.8960882 | AF106: 0.92718805 | AG106: 0.87501924 | AH106: 0.8723902 | AI106: 0.84372582 | AJ106: 0.83469571 | AK106: 0.80275787 | AL106: 0.81379814 | AM106: 0.83262392 | AN106: 0.81670132 | AO106: 0.7962395 | AP106: 0.84200664 | AQ106: 0.85757215 | AR106: 0.85822168 | AS106: 0.86946985 | AT106: 0.86946985 | AU106: 0.86946985 | AV106: 0.86946985 | AW106: 0.86946985
D107: factor
D108: factor
A110: x | C110: aFRR-down and FCR capacity share of the stack: (s+23+s+24)÷s+27 | E110: Aurora s+23, s+24, s+27; v3: 0
C111: Year | J111: 2025 | K111: 2026 | L111: 2027 | M111: 2028 | N111: 2029 | O111: 2030 | P111: 2031 | Q111: 2032 | R111: 2033 | S111: 2034 | T111: 2035 | U111: 2036 | V111: 2037 | W111: 2038 | X111: 2039 | Y111: 2040 | Z111: 2041 | AA111: 2042 | AB111: 2043 | AC111: 2044 | AD111: 2045 | AE111: 2046 | AF111: 2047 | AG111: 2048 | AH111: 2049 | AI111: 2050 | AJ111: 2051 | AK111: 2052 | AL111: 2053 | AM111: 2054 | AN111: 2055 | AO111: 2056 | AP111: 2057 | AQ111: 2058 | AR111: 2059 | AS111: 2060 | AT111: 2061 | AU111: 2062 | AV111: 2063 | AW111: 2064
C112: v3 BESS | D112: factor | J112: 0 | K112: 0 | L112: 0 | M112: 0 | N112: 0 | O112: 0 | P112: 0 | Q112: 0 | R112: 0 | S112: 0 | T112: 0 | U112: 0 | V112: 0 | W112: 0 | X112: 0 | Y112: 0 | Z112: 0 | AA112: 0 | AB112: 0 | AC112: 0 | AD112: 0 | AE112: 0 | AF112: 0 | AG112: 0 | AH112: 0 | AI112: 0 | AJ112: 0 | AK112: 0 | AL112: 0 | AM112: 0 | AN112: 0 | AO112: 0 | AP112: 0 | AQ112: 0 | AR112: 0 | AS112: 0 | AT112: 0 | AU112: 0 | AV112: 0 | AW112: 0
...

Sheet Calc_1
A1: 1 | C1: Bid number
B2: =Dashboard!$C$3&" – Calculations – "&INDEX(Bid_Labels,1,$A$1) -> Project Zalahaláp – Calculations – A Original
C3: Period start | D3: date | J3: =I$4+1 -> 45931 | K3: =J$4+1 -> 46023 | L3: =K$4+1 -> 46113 | M3: =L$4+1 -> 46204 | N3: =M$4+1 -> 46296 | O3: =N$4+1 -> 46388 | P3: =O$4+1 -> 46478 | Q3: =P$4+1 -> 46569 | ... FH3: =FG$4+1 -> 59993
C4: Period end | D4: date | I4: =In_Model_Start-1 -> 45930 | J4: =EOMONTH(J$3,Months_Per_Period-1) -> 46022 | K4: =EOMONTH(K$3,Months_Per_Period-1) -> 46112 | L4: =EOMONTH(L$3,Months_Per_Period-1) -> 46203 | M4: =EOMONTH(M$3,Months_Per_Period-1) -> 46295 | N4: =EOMONTH(N$3,Months_Per_Period-1) -> 46387 | O4: =EOMONTH(O$3,Months_Per_Period-1) -> 46477 | P4: =EOMONTH(P$3,Months_Per_Period-1) -> 46568 | Q4: =EOMONTH(Q$3,Months_Per_Period-1) -> 46660 | ... FH4: =EOMONTH(FH$3,Months_Per_Period-1) -> 60083
C5: Days in period | D5: days | J5: =J$4-J$3+1 -> 92 | K5: =K$4-K$3+1 -> 90 | L5: =L$4-L$3+1 -> 91 | M5: =M$4-M$3+1 -> 92 | N5: =N$4-N$3+1 -> 92 | O5: =O$4-O$3+1 -> 90 | P5: =P$4-P$3+1 -> 91 | Q5: =Q$4-Q$3+1 -> 92 | ... FH5: =FH$4-FH$3+1 -> 91
C6: Year fraction | D6: factor | J6: =J$5/Days_In_Year -> 0.25205479 | K6: =K$5/Days_In_Year -> 0.24657534 | L6: =L$5/Days_In_Year -> 0.24931507 | M6: =M$5/Days_In_Year -> 0.25205479 | N6: =N$5/Days_In_Year -> 0.25205479 | O6: =O$5/Days_In_Year -> 0.24657534 | P6: =P$5/Days_In_Year -> 0.24931507 | Q6: =Q$5/Days_In_Year -> 0.25205479 | ... FH6: =FH$5/Days_In_Year -> 0.24931507
C7: Year | D7: year | J7: =YEAR(J$4) -> 2025 | K7: =YEAR(K$4) -> 2026 | L7: =YEAR(L$4) -> 2026 | M7: =YEAR(M$4) -> 2026 | N7: =YEAR(N$4) -> 2026 | O7: =YEAR(O$4) -> 2027 | P7: =YEAR(P$4) -> 2027 | Q7: =YEAR(Q$4) -> 2027 | ... FH7: =YEAR(FH$4) -> 2064
C8: Period counter | D8: # | J8: =I$8+1 -> 1 | K8: =J$8+1 -> 2 | L8: =K$8+1 -> 3 | M8: =L$8+1 -> 4 | N8: =M$8+1 -> 5 | O8: =N$8+1 -> 6 | P8: =O$8+1 -> 7 | Q8: =P$8+1 -> 8 | ... FH8: =FG$8+1 -> 155
A11: x | C11: Case and timing
C12: Revenue case (E: lever, F: column of the case table) | D12: text | E12: =INDEX(Dash_Case,1,$A$1) -> A | F12: =MATCH($E12,Case_Names,0) -> 1
C13: PV capacity (E: MWp) and grid export (F: MVA) | D13: MW | E13: =INDEX(Case_MWp,1,$F12) -> 61 | F13: =INDEX(Case_MVA,1,$F12) -> 50
C14: Specific yield (E: case, F: after the yield set) | D14: MWh/MWp | E14: =INDEX(Case_Yield,1,$F12) -> 1250 | F14: =$E14*(1+In_Yield_Adj) -> 1250
C15: RtB (E) and RtB exit (F) | D15: date | E15: =INDEX(Case_RtB,1,$F12) -> 46234 | F15: =INDEX(Case_Exit,1,$F12) -> 46326
C16: NTP (E) and COD (F) | D16: date | E16: =INDEX(Case_NTP,1,$F12) -> 46477 | F16: =EOMONTH(INDEX(Case_COD,1,$F12),In_COD_Delay) -> 46843
C17: Clipping, share of DC energy (case table) | D17: % | E17: =INDEX(Case_Clip,1,$F12) -> 0.02
C18: BESS built (E: MW, F: MWh) | D18: MW | E18: =In_BESS_MW*In_BESS_On -> 50 | F18: =$E18*In_BESS_Hours -> 200
C19: Acquisition and JV start | D19: flag | E19: =In_Acq -> 45991 | I19: =SUM(J19:FH19) -> 1 | J19: =N(AND(J$3<=$E19,J$4>=$E19)) -> 1 | K19: =N(AND(K$3<=$E19,K$4>=$E19)) -> 0 | L19: =N(AND(L$3<=$E19,L$4>=$E19)) -> 0 | M19: =N(AND(M$3<=$E19,M$4>=$E19)) -> 0 | N19: =N(AND(N$3<=$E19,N$4>=$E19)) -> 0 | O19: =N(AND(O$3<=$E19,O$4>=$E19)) -> 0 | P19: =N(AND(P$3<=$E19,P$4>=$E19)) -> 0 | Q19: =N(AND(Q$3<=$E19,Q$4>=$E19)) -> 0 | ... FH19: =N(AND(FH$3<=$E19,FH$4>=$E19)) -> 0
C20: RtB exit (sale closing) | D20: flag | E20: =$F15 -> 46326 | I20: =SUM(J20:FH20) -> 1 | J20: =N(AND(J$3<=$E20,J$4>=$E20)) -> 0 | K20: =N(AND(K$3<=$E20,K$4>=$E20)) -> 0 | L20: =N(AND(L$3<=$E20,L$4>=$E20)) -> 0 | M20: =N(AND(M$3<=$E20,M$4>=$E20)) -> 0 | N20: =N(AND(N$3<=$E20,N$4>=$E20)) -> 1 | O20: =N(AND(O$3<=$E20,O$4>=$E20)) -> 0 | P20: =N(AND(P$3<=$E20,P$4>=$E20)) -> 0 | Q20: =N(AND(Q$3<=$E20,Q$4>=$E20)) -> 0 | ... FH20: =N(AND(FH$3<=$E20,FH$4>=$E20)) -> 0
C21: NTP | D21: flag | E21: =$E16 -> 46477 | I21: =SUM(J21:FH21) -> 1 | J21: =N(AND(J$3<=$E21,J$4>=$E21)) -> 0 | K21: =N(AND(K$3<=$E21,K$4>=$E21)) -> 0 | L21: =N(AND(L$3<=$E21,L$4>=$E21)) -> 0 | M21: =N(AND(M$3<=$E21,M$4>=$E21)) -> 0 | N21: =N(AND(N$3<=$E21,N$4>=$E21)) -> 0 | O21: =N(AND(O$3<=$E21,O$4>=$E21)) -> 1 | P21: =N(AND(P$3<=$E21,P$4>=$E21)) -> 0 | Q21: =N(AND(Q$3<=$E21,Q$4>=$E21)) -> 0 | ... FH21: =N(AND(FH$3<=$E21,FH$4>=$E21)) -> 0
C22: COD | D22: flag | E22: =$F16 -> 46843 | I22: =SUM(J22:FH22) -> 1 | J22: =N(AND(J$3<=$E22,J$4>=$E22)) -> 0 | K22: =N(AND(K$3<=$E22,K$4>=$E22)) -> 0 | L22: =N(AND(L$3<=$E22,L$4>=$E22)) -> 0 | M22: =N(AND(M$3<=$E22,M$4>=$E22)) -> 0 | N22: =N(AND(N$3<=$E22,N$4>=$E22)) -> 0 | O22: =N(AND(O$3<=$E22,O$4>=$E22)) -> 0 | P22: =N(AND(P$3<=$E22,P$4>=$E22)) -> 0 | Q22: =N(AND(Q$3<=$E22,Q$4>=$E22)) -> 0 | ... FH22: =N(AND(FH$3<=$E22,FH$4>=$E22)) -> 0
C23: Exit column on the timeline (buyer view at RtB) | D23: # | E23: =MATCH($E20-1,$J$4:$FH$4,1)+1 -> 5
C24: COD column on the timeline (buyer view at COD) | D24: # | E24: =MATCH($E22,$J$4:$FH$4,0) -> 10
C25: After the exit period | D25: flag | J25: =N(J$3>$E20) -> 0 | K25: =N(K$3>$E20) -> 0 | L25: =N(L$3>$E20) -> 0 | M25: =N(M$3>$E20) -> 0 | N25: =N(N$3>$E20) -> 0 | O25: =N(O$3>$E20) -> 1 | P25: =N(P$3>$E20) -> 1 | Q25: =N(Q$3>$E20) -> 1 | ... FH25: =N(FH$3>$E20) -> 1
C26: After COD | D26: flag | J26: =N(J$4>$E22) -> 0 | K26: =N(K$4>$E22) -> 0 | L26: =N(L$4>$E22) -> 0 | M26: =N(M$4>$E22) -> 0 | N26: =N(N$4>$E22) -> 0 | O26: =N(O$4>$E22) -> 0 | P26: =N(P$4>$E22) -> 0 | Q26: =N(Q$4>$E22) -> 0 | ... FH26: =N(FH$4>$E22) -> 1
C27: Construction spread (NTP → COD) | D27: factor | E27: =$E16+1 -> 46478 | F27: =$F16 -> 46843 | I27: =SUM(J27:FH27) -> 1 | J27: =MAX(0,MIN($F27,J$4)-MAX($E27,J$3)+1)/($F27-$E27+1) -> 0 | K27: =MAX(0,MIN($F27,K$4)-MAX($E27,K$3)+1)/($F27-$E27+1) -> 0 | L27: =MAX(0,MIN($F27,L$4)-MAX($E27,L$3)+1)/($F27-$E27+1) -> 0 | M27: =MAX(0,MIN($F27,M$4)-MAX($E27,M$3)+1)/($F27-$E27+1) -> 0 | N27: =MAX(0,MIN($F27,N$4)-MAX($E27,N$3)+1)/($F27-$E27+1) -> 0 | O27: =MAX(0,MIN($F27,O$4)-MAX($E27,O$3)+1)/($F27-$E27+1) -> 0 | P27: =MAX(0,MIN($F27,P$4)-MAX($E27,P$3)+1)/($F27-$E27+1) -> 0.24863388 | Q27: =MAX(0,MIN($F27,Q$4)-MAX($E27,Q$3)+1)/($F27-$E27+1) -> 0.25136612 | ... FH27: =MAX(0,MIN($F27,FH$4)-MAX($E27,FH$3)+1)/($F27-$E27+1) -> 0
C28: Operations (COD → end of life) | D28: flag | E28: =$F16+1 -> 46844 | F28: =EDATE($F16,In_Life*Months_In_Year) -> 59626 | J28: =MAX(0,(MIN($F28,J$4)-MAX($E28,J$3)+1)/J$5) -> 0 | K28: =MAX(0,(MIN($F28,K$4)-MAX($E28,K$3)+1)/K$5) -> 0 | L28: =MAX(0,(MIN($F28,L$4)-MAX($E28,L$3)+1)/L$5) -> 0 | M28: =MAX(0,(MIN($F28,M$4)-MAX($E28,M$3)+1)/M$5) -> 0 | N28: =MAX(0,(MIN($F28,N$4)-MAX($E28,N$3)+1)/N$5) -> 0 | O28: =MAX(0,(MIN($F28,O$4)-MAX($E28,O$3)+1)/O$5) -> 0 | P28: =MAX(0,(MIN($F28,P$4)-MAX($E28,P$3)+1)/P$5) -> 0 | Q28: =MAX(0,(MIN($F28,Q$4)-MAX($E28,Q$3)+1)/Q$5) -> 0 | ... FH28: =MAX(0,(MIN($F28,FH$4)-MAX($E28,FH$3)+1)/FH$5) -> 0
C29: Operating years elapsed at the period start | D29: years | J29: =MAX(0,J$3-1-$F16)/Days_In_Year -> 0 | K29: =MAX(0,K$3-1-$F16)/Days_In_Year -> 0 | L29: =MAX(0,L$3-1-$F16)/Days_In_Year -> 0 | M29: =MAX(0,M$3-1-$F16)/Days_In_Year -> 0 | N29: =MAX(0,N$3-1-$F16)/Days_In_Year -> 0 | O29: =MAX(0,O$3-1-$F16)/Days_In_Year -> 0 | P29: =MAX(0,P$3-1-$F16)/Days_In_Year -> 0 | Q29: =MAX(0,Q$3-1-$F16)/Days_In_Year -> 0 | ... FH29: =MAX(0,FH$3-1-$F16)/Days_In_Year -> 36.024658
C30: DSA loan spread (acquisition → RtB) | D30: factor | E30: =In_Acq+1 -> 45992 | F30: =$E15 -> 46234 | I30: =SUM(J30:FH30) -> 1 | J30: =MAX(0,MIN($F30,J$4)-MAX($E30,J$3)+1)/($F30-$E30+1) -> 0.12757202 | K30: =MAX(0,MIN($F30,K$4)-MAX($E30,K$3)+1)/($F30-$E30+1) -> 0.37037037 | L30: =MAX(0,MIN($F30,L$4)-MAX($E30,L$3)+1)/($F30-$E30+1) -> 0.3744856 | M30: =MAX(0,MIN($F30,M$4)-MAX($E30,M$3)+1)/($F30-$E30+1) -> 0.12757202 | N30: =MAX(0,MIN($F30,N$4)-MAX($E30,N$3)+1)/($F30-$E30+1) -> 0 | O30: =MAX(0,MIN($F30,O$4)-MAX($E30,O$3)+1)/($F30-$E30+1) -> 0 | P30: =MAX(0,MIN($F30,P$4)-MAX($E30,P$3)+1)/($F30-$E30+1) -> 0 | Q30: =MAX(0,MIN($F30,Q$4)-MAX($E30,Q$3)+1)/($F30-$E30+1) -> 0 | ... FH30: =MAX(0,MIN($F30,FH$4)-MAX($E30,FH$3)+1)/($F30-$E30+1) -> 0
C31: Pre-RtB development cost spread | D31: factor | E31: =EOMONTH(In_PreRtB_First,-1)+1 -> 46296 | F31: =In_PreRtB_Last -> 46477 | I31: =SUM(J31:FH31) -> 1 | J31: =MAX(0,MIN($F31,J$4)-MAX($E31,J$3)+1)/($F31-$E31+1) -> 0 | K31: =MAX(0,MIN($F31,K$4)-MAX($E31,K$3)+1)/($F31-$E31+1) -> 0 | L31: =MAX(0,MIN($F31,L$4)-MAX($E31,L$3)+1)/($F31-$E31+1) -> 0 | M31: =MAX(0,MIN($F31,M$4)-MAX($E31,M$3)+1)/($F31-$E31+1) -> 0 | N31: =MAX(0,MIN($F31,N$4)-MAX($E31,N$3)+1)/($F31-$E31+1) -> 0.50549451 | O31: =MAX(0,MIN($F31,O$4)-MAX($E31,O$3)+1)/($F31-$E31+1) -> 0.49450549 | P31: =MAX(0,MIN($F31,P$4)-MAX($E31,P$3)+1)/($F31-$E31+1) -> 0 | Q31: =MAX(0,MIN($F31,Q$4)-MAX($E31,Q$3)+1)/($F31-$E31+1) -> 0 | ... FH31: =MAX(0,MIN($F31,FH$4)-MAX($E31,FH$3)+1)/($F31-$E31+1) -> 0
C32: Debt repayment period | D32: flag | E32: =$F16+1 -> 46844 | F32: =EDATE($F16,In_Debt_Tenor*Months_In_Year) -> 52321 | J32: =MAX(0,(MIN($F32,J$4)-MAX($E32,J$3)+1)/J$5) -> 0 | K32: =MAX(0,(MIN($F32,K$4)-MAX($E32,K$3)+1)/K$5) -> 0 | L32: =MAX(0,(MIN($F32,L$4)-MAX($E32,L$3)+1)/L$5) -> 0 | M32: =MAX(0,(MIN($F32,M$4)-MAX($E32,M$3)+1)/M$5) -> 0 | N32: =MAX(0,(MIN($F32,N$4)-MAX($E32,N$3)+1)/N$5) -> 0 | O32: =MAX(0,(MIN($F32,O$4)-MAX($E32,O$3)+1)/O$5) -> 0 | P32: =MAX(0,(MIN($F32,P$4)-MAX($E32,P$3)+1)/P$5) -> 0 | Q32: =MAX(0,(MIN($F32,Q$4)-MAX($E32,Q$3)+1)/Q$5) -> 0 | ... FH32: =MAX(0,(MIN($F32,FH$4)-MAX($E32,FH$3)+1)/FH$5) -> 0
C33: Last debt repayment | D33: flag | E33: =EDATE($F16,In_Debt_Tenor*Months_In_Year) -> 52321 | I33: =SUM(J33:FH33) -> 1 | J33: =N(AND(J$3<=$E33,J$4>=$E33)) -> 0 | K33: =N(AND(K$3<=$E33,K$4>=$E33)) -> 0 | L33: =N(AND(L$3<=$E33,L$4>=$E33)) -> 0 | M33: =N(AND(M$3<=$E33,M$4>=$E33)) -> 0 | N33: =N(AND(N$3<=$E33,N$4>=$E33)) -> 0 | O33: =N(AND(O$3<=$E33,O$4>=$E33)) -> 0 | P33: =N(AND(P$3<=$E33,P$4>=$E33)) -> 0 | Q33: =N(AND(Q$3<=$E33,Q$4>=$E33)) -> 0 | ... FH33: =N(AND(FH$3<=$E33,FH$4>=$E33)) -> 0
C34: Tax depreciation spread: PV, grid, development | D34: factor | E34: =$F16+1 -> 46844 | F34: =EDATE($F16,In_Dep_Years*Months_In_Year) -> 57800 | I34: =SUM(J34:FH34) -> 1 | J34: =MAX(0,MIN($F34,J$4)-MAX($E34,J$3)+1)/($F34-$E34+1) -> 0 | K34: =MAX(0,MIN($F34,K$4)-MAX($E34,K$3)+1)/($F34-$E34+1) -> 0 | L34: =MAX(0,MIN($F34,L$4)-MAX($E34,L$3)+1)/($F34-$E34+1) -> 0 | M34: =MAX(0,MIN($F34,M$4)-MAX($E34,M$3)+1)/($F34-$E34+1) -> 0 | N34: =MAX(0,MIN($F34,N$4)-MAX($E34,N$3)+1)/($F34-$E34+1) -> 0 | O34: =MAX(0,MIN($F34,O$4)-MAX($E34,O$3)+1)/($F34-$E34+1) -> 0 | P34: =MAX(0,MIN($F34,P$4)-MAX($E34,P$3)+1)/($F34-$E34+1) -> 0 | Q34: =MAX(0,MIN($F34,Q$4)-MAX($E34,Q$3)+1)/($F34-$E34+1) -> 0 | ... FH34: =MAX(0,MIN($F34,FH$4)-MAX($E34,FH$3)+1)/($F34-$E34+1) -> 0
C35: Tax depreciation spread: BESS | D35: factor | E35: =$F16+1 -> 46844 | F35: =EDATE($F16,In_Dep_BESS_Years*Months_In_Year) -> 50495 | I35: =SUM(J35:FH35) -> 1 | J35: =MAX(0,MIN($F35,J$4)-MAX($E35,J$3)+1)/($F35-$E35+1) -> 0 | K35: =MAX(0,MIN($F35,K$4)-MAX($E35,K$3)+1)/($F35-$E35+1) -> 0 | L35: =MAX(0,MIN($F35,L$4)-MAX($E35,L$3)+1)/($F35-$E35+1) -> 0 | M35: =MAX(0,MIN($F35,M$4)-MAX($E35,M$3)+1)/($F35-$E35+1) -> 0 | N35: =MAX(0,MIN($F35,N$4)-MAX($E35,N$3)+1)/($F35-$E35+1) -> 0 | O35: =MAX(0,MIN($F35,O$4)-MAX($E35,O$3)+1)/($F35-$E35+1) -> 0 | P35: =MAX(0,MIN($F35,P$4)-MAX($E35,P$3)+1)/($F35-$E35+1) -> 0 | Q35: =MAX(0,MIN($F35,Q$4)-MAX($E35,Q$3)+1)/($F35-$E35+1) -> 0 | ... FH35: =MAX(0,MIN($F35,FH$4)-MAX($E35,FH$3)+1)/($F35-$E35+1) -> 0
C36: Debt compounding index (E: at COD, F: rate per period) | D36: factor | E36: =SUMIF($J$4:$FH$4,$F16,$J36:$FH36) -> 1.1322708 | F36: =In_Debt_Rate*Months_Per_Period/Months_In_Year -> 0.0125 | J36: =(1+$F36)^J$8 -> 1.0125 | K36: =(1+$F36)^K$8 -> 1.0251562 | L36: =(1+$F36)^L$8 -> 1.0379707 | M36: =(1+$F36)^M$8 -> 1.0509453 | N36: =(1+$F36)^N$8 -> 1.0640822 | O36: =(1+$F36)^O$8 -> 1.0773832 | P36: =(1+$F36)^P$8 -> 1.0908505 | Q36: =(1+$F36)^Q$8 -> 1.1044861 | ... FH36: =(1+$F36)^FH$8 -> 6.8585126
C37: 31-Dec capitalisation | D37: flag | J37: =N(MONTH(J$4)=Months_In_Year) -> 1 | K37: =N(MONTH(K$4)=Months_In_Year) -> 0 | L37: =N(MONTH(L$4)=Months_In_Year) -> 0 | M37: =N(MONTH(M$4)=Months_In_Year) -> 0 | N37: =N(MONTH(N$4)=Months_In_Year) -> 1 | O37: =N(MONTH(O$4)=Months_In_Year) -> 0 | P37: =N(MONTH(P$4)=Months_In_Year) -> 0 | Q37: =N(MONTH(Q$4)=Months_In_Year) -> 0 | ... FH37: =N(MONTH(FH$4)=Months_In_Year) -> 0
C38: First quarter of the year | D38: flag | J38: =N(MONTH(J$4)<=Months_Per_Period) -> 0 | K38: =N(MONTH(K$4)<=Months_Per_Period) -> 1 | L38: =N(MONTH(L$4)<=Months_Per_Period) -> 0 | M38: =N(MONTH(M$4)<=Months_Per_Period) -> 0 | N38: =N(MONTH(N$4)<=Months_Per_Period) -> 0 | O38: =N(MONTH(O$4)<=Months_Per_Period) -> 1 | P38: =N(MONTH(P$4)<=Months_Per_Period) -> 0 | Q38: =N(MONTH(Q$4)<=Months_Per_Period) -> 0 | ... FH38: =N(MONTH(FH$4)<=Months_Per_Period) -> 0
A40: x | C40: Prices (real 2025 curves × Aurora euro index)
C41: Aurora euro index | D41: factor | J41: =INDEX(Euro_Index,MATCH(J$7,Price_Years,0)) -> 1 | K41: =INDEX(Euro_Index,MATCH(K$7,Price_Years,0)) -> 1.01897 | L41: =INDEX(Euro_Index,MATCH(L$7,Price_Years,0)) -> 1.01897 | M41: =INDEX(Euro_Index,MATCH(M$7,Price_Years,0)) -> 1.01897 | N41: =INDEX(Euro_Index,MATCH(N$7,Price_Years,0)) -> 1.01897 | O41: =INDEX(Euro_Index,MATCH(O$7,Price_Years,0)) -> 1.040399 | P41: =INDEX(Euro_Index,MATCH(P$7,Price_Years,0)) -> 1.040399 | Q41: =INDEX(Euro_Index,MATCH(Q$7,Price_Years,0)) -> 1.040399 | ... FH41: =INDEX(Euro_Index,MATCH(FH$7,Price_Years,0)) -> 2.1668863
C42: PV price, direct export, real 2025 (E: curve) | D42: EUR/MWh | E42: =INDEX(Case_PV_Curve,1,$F12) -> v3 capture | J42: =INDEX(Price_Data,MATCH($E42,Price_Labels,0),MATCH(J$7,Price_Years,0)) -> 0 | K42: =INDEX(Price_Data,MATCH($E42,Price_Labels,0),MATCH(K$7,Price_Years,0)) -> 78.3445 | L42: =INDEX(Price_Data,MATCH($E42,Price_Labels,0),MATCH(L$7,Price_Years,0)) -> 78.3445 | M42: =INDEX(Price_Data,MATCH($E42,Price_Labels,0),MATCH(M$7,Price_Years,0)) -> 78.3445 | N42: =INDEX(Price_Data,MATCH($E42,Price_Labels,0),MATCH(N$7,Price_Years,0)) -> 78.3445 | O42: =INDEX(Price_Data,MATCH($E42,Price_Labels,0),MATCH(O$7,Price_Years,0)) -> 77.571 | P42: =INDEX(Price_Data,MATCH($E42,Price_Labels,0),MATCH(P$7,Price_Years,0)) -> 77.571 | Q42: =INDEX(Price_Data,MATCH($E42,Price_Labels,0),MATCH(Q$7,Price_Years,0)) -> 77.571 | ... FH42: =INDEX(Price_Data,MATCH($E42,Price_Labels,0),MATCH(FH$7,Price_Years,0)) -> 60.2615
C43: PV price, energy sent to the BESS, real 2025 (E: curve) | D43: EUR/MWh | E43: =INDEX(Case_PV_Transfer,1,$F12) -> v3 capture | J43: =INDEX(Price_Data,MATCH($E43,Price_Labels,0),MATCH(J$7,Price_Years,0)) -> 0 | K43: =INDEX(Price_Data,MATCH($E43,Price_Labels,0),MATCH(K$7,Price_Years,0)) -> 78.3445 | L43: =INDEX(Price_Data,MATCH($E43,Price_Labels,0),MATCH(L$7,Price_Years,0)) -> 78.3445 | M43: =INDEX(Price_Data,MATCH($E43,Price_Labels,0),MATCH(M$7,Price_Years,0)) -> 78.3445 | N43: =INDEX(Price_Data,MATCH($E43,Price_Labels,0),MATCH(N$7,Price_Years,0)) -> 78.3445 | O43: =INDEX(Price_Data,MATCH($E43,Price_Labels,0),MATCH(O$7,Price_Years,0)) -> 77.571 | P43: =INDEX(Price_Data,MATCH($E43,Price_Labels,0),MATCH(P$7,Price_Years,0)) -> 77.571 | Q43: =INDEX(Price_Data,MATCH($E43,Price_Labels,0),MATCH(Q$7,Price_Years,0)) -> 77.571 | ... FH43: =INDEX(Price_Data,MATCH($E43,Price_Labels,0),MATCH(FH$7,Price_Years,0)) -> 60.2615
C44: PV merchant price, direct export, nominal (price set applied) | D44: EUR/MWh | J44: =J42*J41*(1+In_PV_Price_Adj) -> 0 | K44: =K42*K41*(1+In_PV_Price_Adj) -> 79.830695 | L44: =L42*L41*(1+In_PV_Price_Adj) -> 79.830695 | M44: =M42*M41*(1+In_PV_Price_Adj) -> 79.830695 | N44: =N42*N41*(1+In_PV_Price_Adj) -> 79.830695 | O44: =O42*O41*(1+In_PV_Price_Adj) -> 80.704791 | P44: =P42*P41*(1+In_PV_Price_Adj) -> 80.704791 | Q44: =Q42*Q41*(1+In_PV_Price_Adj) -> 80.704791 | ... FH44: =FH42*FH41*(1+In_PV_Price_Adj) -> 130.57982
C45: PV transfer price to the BESS, nominal (price set applied) | D45: EUR/MWh | J45: =J43*J41*(1+In_PV_Price_Adj) -> 0 | K45: =K43*K41*(1+In_PV_Price_Adj) -> 79.830695 | L45: =L43*L41*(1+In_PV_Price_Adj) -> 79.830695 | M45: =M43*M41*(1+In_PV_Price_Adj) -> 79.830695 | N45: =N43*N41*(1+In_PV_Price_Adj) -> 79.830695 | O45: =O43*O41*(1+In_PV_Price_Adj) -> 80.704791 | P45: =P43*P41*(1+In_PV_Price_Adj) -> 80.704791 | Q45: =Q43*Q41*(1+In_PV_Price_Adj) -> 80.704791 | ... FH45: =FH43*FH41*(1+In_PV_Price_Adj) -> 130.57982
C46: Guarantee of origin price, nominal | D46: EUR/MWh | J46: =In_GoO*J41 -> 1.75 | K46: =In_GoO*K41 -> 1.7831975 | L46: =In_GoO*L41 -> 1.7831975 | M46: =In_GoO*M41 -> 1.7831975 | N46: =In_GoO*N41 -> 1.7831975 | O46: =In_GoO*O41 -> 1.8206982 | P46: =In_GoO*P41 -> 1.8206982 | Q46: =In_GoO*Q41 -> 1.8206982 | ... FH46: =In_GoO*FH41 -> 3.792051
C47: BESS storage total cashflow, real 2025 (E: curve) | D47: EUR k/MW | E47: =INDEX(Case_BESS_Curve,1,$F12) -> DC 4h | J47: =INDEX(Stack_Data,MATCH($E47,Stack_Labels,0),MATCH(J$7,Stack_Years,0)) -> 0 | K47: =INDEX(Stack_Data,MATCH($E47,Stack_Labels,0),MATCH(K$7,Stack_Years,0)) -> 0 | L47: =INDEX(Stack_Data,MATCH($E47,Stack_Labels,0),MATCH(L$7,Stack_Years,0)) -> 0 | M47: =INDEX(Stack_Data,MATCH($E47,Stack_Labels,0),MATCH(M$7,Stack_Years,0)) -> 0 | N47: =INDEX(Stack_Data,MATCH($E47,Stack_Labels,0),MATCH(N$7,Stack_Years,0)) -> 0 | O47: =INDEX(Stack_Data,MATCH($E47,Stack_Labels,0),MATCH(O$7,Stack_Years,0)) -> 186.97508 | P47: =INDEX(Stack_Data,MATCH($E47,Stack_Labels,0),MATCH(P$7,Stack_Years,0)) -> 186.97508 | Q47: =INDEX(Stack_Data,MATCH($E47,Stack_Labels,0),MATCH(Q$7,Stack_Years,0)) -> 186.97508 | ... FH47: =INDEX(Stack_Data,MATCH($E47,Stack_Labels,0),MATCH(FH$7,Stack_Years,0)) -> 91.148957
C48: Stack kept with PV-only charging (E: curve) | D48: factor | E48: =$E47 -> DC 4h | J48: =INDEX(PVOnly_Data,MATCH($E48,PVOnly_Labels,0),MATCH(J$7,PVOnly_Years,0)) -> 1 | K48: =INDEX(PVOnly_Data,MATCH($E48,PVOnly_Labels,0),MATCH(K$7,PVOnly_Years,0)) -> 1 | L48: =INDEX(PVOnly_Data,MATCH($E48,PVOnly_Labels,0),MATCH(L$7,PVOnly_Years,0)) -> 1 | M48: =INDEX(PVOnly_Data,MATCH($E48,PVOnly_Labels,0),MATCH(M$7,PVOnly_Years,0)) -> 1 | N48: =INDEX(PVOnly_Data,MATCH($E48,PVOnly_Labels,0),MATCH(N$7,PVOnly_Years,0)) -> 1 | O48: =INDEX(PVOnly_Data,MATCH($E48,PVOnly_Labels,0),MATCH(O$7,PVOnly_Years,0)) -> 0.77913121 | P48: =INDEX(PVOnly_Data,MATCH($E48,PVOnly_Labels,0),MATCH(P$7,PVOnly_Years,0)) -> 0.77913121 | Q48: =INDEX(PVOnly_Data,MATCH($E48,PVOnly_Labels,0),MATCH(Q$7,PVOnly_Years,0)) -> 0.77913121 | ... FH48: =INDEX(PVOnly_Data,MATCH($E48,PVOnly_Labels,0),MATCH(FH$7,PVOnly_Years,0)) -> 0.91178898
C49: aFRR-down and FCR share of the stack (E: curve) | D49: factor | E49: =$E47 -> DC 4h | J49: =INDEX(DownCap_Data,MATCH($E49,DownCap_Labels,0),MATCH(J$7,DownCap_Years,0)) -> 0 | K49: =INDEX(DownCap_Data,MATCH($E49,DownCap_Labels,0),MATCH(K$7,DownCap_Years,0)) -> 0 | L49: =INDEX(DownCap_Data,MATCH($E49,DownCap_Labels,0),MATCH(L$7,DownCap_Years,0)) -> 0 | M49: =INDEX(DownCap_Data,MATCH($E49,DownCap_Labels,0),MATCH(M$7,DownCap_Years,0)) -> 0 | N49: =INDEX(DownCap_Data,MATCH($E49,DownCap_Labels,0),MATCH(N$7,DownCap_Years,0)) -> 0 | O49: =INDEX(DownCap_Data,MATCH($E49,DownCap_Labels,0),MATCH(O$7,DownCap_Years,0)) -> 0.16712104 | P49: =INDEX(DownCap_Data,MATCH($E49,DownCap_Labels,0),MATCH(P$7,DownCap_Years,0)) -> 0.16712104 | Q49: =INDEX(DownCap_Data,MATCH($E49,DownCap_Labels,0),MATCH(Q$7,DownCap_Years,0)) -> 0.16712104 | ... FH49: =INDEX(DownCap_Data,MATCH($E49,DownCap_Labels,0),MATCH(FH$7,DownCap_Years,0)) -> 0.13527975
C50: Stack kept without grid charging | D50: factor | J50: =MIN(1,J48+In_AFRR_Down_Share*J49) -> 1 | K50: =MIN(1,K48+In_AFRR_Down_Share*K49) -> 1 | L50: =MIN(1,L48+In_AFRR_Down_Share*L49) -> 1 | M50: =MIN(1,M48+In_AFRR_Down_Share*M49) -> 1 | N50: =MIN(1,N48+In_AFRR_Down_Share*N49) -> 1 | O50: =MIN(1,O48+In_AFRR_Down_Share*O49) -> 0.77913121 | P50: =MIN(1,P48+In_AFRR_Down_Share*P49) -> 0.77913121 | Q50: =MIN(1,Q48+In_AFRR_Down_Share*Q49) -> 0.77913121 | ... FH50: =MIN(1,FH48+In_AFRR_Down_Share*FH49) -> 0.91178898
C51: Grid charging allowed: import ÷ BESS MW (E) | D51: % | E51: =MIN(1,In_Grid_Import_MW/MAX(1,$E18)) -> 0
C52: BESS merchant revenue per MW-year, nominal (haircut, availability, charging) | D52: EUR k/MW | J52: =J47*J41*(1-In_BESS_Haircut)*(J50+(1-J50)*$E51) -> 0 | K52: =K47*K41*(1-In_BESS_Haircut)*(K50+(1-K50)*$E51) -> 0 | L52: =L47*L41*(1-In_BESS_Haircut)*(L50+(1-L50)*$E51) -> 0 | M52: =M47*M41*(1-In_BESS_Haircut)*(M50+(1-M50)*$E51) -> 0 | N52: =N47*N41*(1-In_BESS_Haircut)*(N50+(1-N50)*$E51) -> 0 | O52: =O47*O41*(1-In_BESS_Haircut)*(O50+(1-O50)*$E51) -> 151.56337 | P52: =P47*P41*(1-In_BESS_Haircut)*(P50+(1-P50)*$E51) -> 151.56337 | Q52: =Q47*Q41*(1-In_BESS_Haircut)*(Q50+(1-Q50)*$E51) -> 151.56337 | ... FH52: =FH47*FH41*(1-In_BESS_Haircut)*(FH50+(1-FH50)*$E51) -> 180.08692
C53: BESS repower year (E: used, F: repower year of the curve) | D53: year | E53: =IF(In_Fix_Augment=0,In_Augment_Year_v3,IF(In_Augment_Year>0,In_Augment_Year,$F53)) -> 2048 | F53: =INDEX(Block_Repower,MATCH($E47,Block_Names,0)) -> 2048
C54: BESS in service (0 from the repower year if not repowered) | D54: flag | J54: =1-(1-In_Repower)*(J$7>=$E53) -> 1 | K54: =1-(1-In_Repower)*(K$7>=$E53) -> 1 | L54: =1-(1-In_Repower)*(L$7>=$E53) -> 1 | M54: =1-(1-In_Repower)*(M$7>=$E53) -> 1 | N54: =1-(1-In_Repower)*(N$7>=$E53) -> 1 | O54: =1-(1-In_Repower)*(O$7>=$E53) -> 1 | P54: =1-(1-In_Repower)*(P$7>=$E53) -> 1 | Q54: =1-(1-In_Repower)*(Q$7>=$E53) -> 1 | ... FH54: =1-(1-In_Repower)*(FH$7>=$E53) -> 1
A56: x | C56: Offtake offers (case C; merchant tail after the tenor)
C57: Offer applies on this sheet (case table) | D57: flag | E57: =INDEX(Case_Offer,1,$F12) -> 0
C58: PV offer: column (E), fixed price (F: 1 = yes) | D58: # | E58: =MATCH(In_Offer_PV,OPV_Names,0) -> 2 | F58: =INDEX(OPV_Type,$E58) -> 1
C59: PV offer handling fee: share (E), floor (F) | D59: EUR/MWh | E59: =INDEX(OPV_Fee,$E58) -> 0 | F59: =INDEX(OPV_Fee_Min,$E58) -> 0
C60: PV offer: fee cap (E), fixed price (F) | D60: EUR/MWh | E60: =INDEX(OPV_Fee_Max,$E58) -> 0 | F60: =INDEX(OPV_Price,$E58) -> 43.96
C61: PV offer in force (E: start, F: end) | D61: factor | E61: =IF(INDEX(OPV_Start,$E58)>0,INDEX(OPV_Start,$E58),$F16+1) -> 46753 | F61: =EDATE($E61,INDEX(OPV_Tenor,$E58)*Months_In_Year)-1 -> 47848 | J61: =$E57*MAX(0,MIN($F61,J$4)-MAX($E61,J$3)+1)/J$5 -> 0 | K61: =$E57*MAX(0,MIN($F61,K$4)-MAX($E61,K$3)+1)/K$5 -> 0 | L61: =$E57*MAX(0,MIN($F61,L$4)-MAX($E61,L$3)+1)/L$5 -> 0 | M61: =$E57*MAX(0,MIN($F61,M$4)-MAX($E61,M$3)+1)/M$5 -> 0 | N61: =$E57*MAX(0,MIN($F61,N$4)-MAX($E61,N$3)+1)/N$5 -> 0 | O61: =$E57*MAX(0,MIN($F61,O$4)-MAX($E61,O$3)+1)/O$5 -> 0 | P61: =$E57*MAX(0,MIN($F61,P$4)-MAX($E61,P$3)+1)/P$5 -> 0 | Q61: =$E57*MAX(0,MIN($F61,Q$4)-MAX($E61,Q$3)+1)/Q$5 -> 0 | ... FH61: =$E57*MAX(0,MIN($F61,FH$4)-MAX($E61,FH$3)+1)/FH$5 -> 0
C62: PV offer handling fee | D62: EUR/MWh | J62: =MIN($E60,MAX($E59*J44,$F59)) -> 0 | K62: =MIN($E60,MAX($E59*K44,$F59)) -> 0 | L62: =MIN($E60,MAX($E59*L44,$F59)) -> 0 | M62: =MIN($E60,MAX($E59*M44,$F59)) -> 0 | N62: =MIN($E60,MAX($E59*N44,$F59)) -> 0 | O62: =MIN($E60,MAX($E59*O44,$F59)) -> 0 | P62: =MIN($E60,MAX($E59*P44,$F59)) -> 0 | Q62: =MIN($E60,MAX($E59*Q44,$F59)) -> 0 | ... FH62: =MIN($E60,MAX($E59*FH44,$F59)) -> 0
C63: PV price received on direct export (offer in force, else merchant) | D63: EUR/MWh | J63: =J44+J61*(IF($F58=1,$F60,J44-J62)-J44) -> 0 | K63: =K44+K61*(IF($F58=1,$F60,K44-K62)-K44) -> 79.830695 | L63: =L44+L61*(IF($F58=1,$F60,L44-L62)-L44) -> 79.830695 | M63: =M44+M61*(IF($F58=1,$F60,M44-M62)-M44) -> 79.830695 | N63: =N44+N61*(IF($F58=1,$F60,N44-N62)-N44) -> 79.830695 | O63: =O44+O61*(IF($F58=1,$F60,O44-O62)-O44) -> 80.704791 | P63: =P44+P61*(IF($F58=1,$F60,P44-P62)-P44) -> 80.704791 | Q63: =Q44+Q61*(IF($F58=1,$F60,Q44-Q62)-Q44) -> 80.704791 | ... FH63: =FH44+FH61*(IF($F58=1,$F60,FH44-FH62)-FH44) -> 130.57982
C64: BESS offer: column (E), fixed fee per MW-year, not scaled above the offer (F) | D64: EUR k/MW | E64: =MATCH(In_Offer_BESS,OB_Names,0) -> 3 | F64: =INDEX(OB_Fixed,$E64)*MIN(1,In_BESS_Hours/INDEX(OB_Hours,$E64)) -> 49.7
C65: BESS offer duration ≠ built duration (E: 1 = yes) | D65: flag | E65: =$E57*(INDEX(OB_Tenor,$E64)>0)*N(INDEX(OB_Hours,$E64)<>In_BESS_Hours) -> 0
C66: BESS offer: owner share (E), grid charge deducted (F) | D66: EUR k/MW | E66: =INDEX(OB_Share,$E64) -> 0 | F66: =INDEX(OB_Grid,$E64)*In_BESS_Grid_Charge -> 0
C67: BESS offer in force (E: start, F: end) | D67: factor | E67: =IF(INDEX(OB_Start,$E64)>0,INDEX(OB_Start,$E64),$F16+1) -> 46753 | F67: =EDATE($E67,INDEX(OB_Tenor,$E64)*Months_In_Year)-1 -> 47848 | J67: =$E57*MAX(0,MIN($F67,J$4)-MAX($E67,J$3)+1)/J$5 -> 0 | K67: =$E57*MAX(0,MIN($F67,K$4)-MAX($E67,K$3)+1)/K$5 -> 0 | L67: =$E57*MAX(0,MIN($F67,L$4)-MAX($E67,L$3)+1)/L$5 -> 0 | M67: =$E57*MAX(0,MIN($F67,M$4)-MAX($E67,M$3)+1)/M$5 -> 0 | N67: =$E57*MAX(0,MIN($F67,N$4)-MAX($E67,N$3)+1)/N$5 -> 0 | O67: =$E57*MAX(0,MIN($F67,O$4)-MAX($E67,O$3)+1)/O$5 -> 0 | P67: =$E57*MAX(0,MIN($F67,P$4)-MAX($E67,P$3)+1)/P$5 -> 0 | Q67: =$E57*MAX(0,MIN($F67,Q$4)-MAX($E67,Q$3)+1)/Q$5 -> 0 | ... FH67: =$E57*MAX(0,MIN($F67,FH$4)-MAX($E67,FH$3)+1)/FH$5 -> 0
C68: E.ON band table row this year (0 = none; E: bands apply) | D68: # | E68: =INDEX(OB_Bands,$E64) -> 0 | J68: =$E68*SUMIF(EB_Years,J$7,EB_Row) -> 0 | K68: =$E68*SUMIF(EB_Years,K$7,EB_Row) -> 0 | L68: =$E68*SUMIF(EB_Years,L$7,EB_Row) -> 0 | M68: =$E68*SUMIF(EB_Years,M$7,EB_Row) -> 0 | N68: =$E68*SUMIF(EB_Years,N$7,EB_Row) -> 0 | O68: =$E68*SUMIF(EB_Years,O$7,EB_Row) -> 0 | P68: =$E68*SUMIF(EB_Years,P$7,EB_Row) -> 0 | Q68: =$E68*SUMIF(EB_Years,Q$7,EB_Row) -> 0 | ... FH68: =$E68*SUMIF(EB_Years,FH$7,EB_Row) -> 0
C69: Band table row looked up | D69: # | J69: =MAX(1,J68) -> 1 | K69: =MAX(1,K68) -> 1 | L69: =MAX(1,L68) -> 1 | M69: =MAX(1,M68) -> 1 | N69: =MAX(1,N68) -> 1 | O69: =MAX(1,O68) -> 1 | P69: =MAX(1,P68) -> 1 | Q69: =MAX(1,Q68) -> 1 | ... FH69: =MAX(1,FH68) -> 1
C70: E.ON fee on the stack, by band | D70: EUR k/MW | J70: =(J68>0)*SUMPRODUCT((J52>INDEX(EB_LB,J69,0))*(J52-INDEX(EB_LB,J69,0)),INDEX(EB_dR,J69,0)) -> 0 | K70: =(K68>0)*SUMPRODUCT((K52>INDEX(EB_LB,K69,0))*(K52-INDEX(EB_LB,K69,0)),INDEX(EB_dR,K69,0)) -> 0 | L70: =(L68>0)*SUMPRODUCT((L52>INDEX(EB_LB,L69,0))*(L52-INDEX(EB_LB,L69,0)),INDEX(EB_dR,L69,0)) -> 0 | M70: =(M68>0)*SUMPRODUCT((M52>INDEX(EB_LB,M69,0))*(M52-INDEX(EB_LB,M69,0)),INDEX(EB_dR,M69,0)) -> 0 | N70: =(N68>0)*SUMPRODUCT((N52>INDEX(EB_LB,N69,0))*(N52-INDEX(EB_LB,N69,0)),INDEX(EB_dR,N69,0)) -> 0 | O70: =(O68>0)*SUMPRODUCT((O52>INDEX(EB_LB,O69,0))*(O52-INDEX(EB_LB,O69,0)),INDEX(EB_dR,O69,0)) -> 0 | P70: =(P68>0)*SUMPRODUCT((P52>INDEX(EB_LB,P69,0))*(P52-INDEX(EB_LB,P69,0)),INDEX(EB_dR,P69,0)) -> 0 | Q70: =(Q68>0)*SUMPRODUCT((Q52>INDEX(EB_LB,Q69,0))*(Q52-INDEX(EB_LB,Q69,0)),INDEX(EB_dR,Q69,0)) -> 0 | ... FH70: =(FH68>0)*SUMPRODUCT((FH52>INDEX(EB_LB,FH69,0))*(FH52-INDEX(EB_LB,FH69,0)),INDEX(EB_dR,FH69,0)) -> 0
C71: Guaranteed floor in band years | D71: EUR k/MW | J71: =(J68>0)*INDEX(EB_Floor,J69) -> 0 | K71: =(K68>0)*INDEX(EB_Floor,K69) -> 0 | L71: =(L68>0)*INDEX(EB_Floor,L69) -> 0 | M71: =(M68>0)*INDEX(EB_Floor,M69) -> 0 | N71: =(N68>0)*INDEX(EB_Floor,N69) -> 0 | O71: =(O68>0)*INDEX(EB_Floor,O69) -> 0 | P71: =(P68>0)*INDEX(EB_Floor,P69) -> 0 | Q71: =(Q68>0)*INDEX(EB_Floor,Q69) -> 0 | ... FH71: =(FH68>0)*INDEX(EB_Floor,FH69) -> 0
C72: Owner share of the stack above the fixed fee | D72: % | J72: =IF(J68>0,1,$E66) -> 0 | K72: =IF(K68>0,1,$E66) -> 0 | L72: =IF(L68>0,1,$E66) -> 0 | M72: =IF(M68>0,1,$E66) -> 0 | N72: =IF(N68>0,1,$E66) -> 0 | O72: =IF(O68>0,1,$E66) -> 0 | P72: =IF(P68>0,1,$E66) -> 0 | Q72: =IF(Q68>0,1,$E66) -> 0 | ... FH72: =IF(FH68>0,1,$E66) -> 0
C73: Owner BESS revenue per MW-year under the offer | D73: EUR k/MW | J73: =MAX(J71,$F64+J72*MAX(0,J52-$F66-$F64)-J70) -> 49.7 | K73: =MAX(K71,$F64+K72*MAX(0,K52-$F66-$F64)-K70) -> 49.7 | L73: =MAX(L71,$F64+L72*MAX(0,L52-$F66-$F64)-L70) -> 49.7 | M73: =MAX(M71,$F64+M72*MAX(0,M52-$F66-$F64)-M70) -> 49.7 | N73: =MAX(N71,$F64+N72*MAX(0,N52-$F66-$F64)-N70) -> 49.7 | O73: =MAX(O71,$F64+O72*MAX(0,O52-$F66-$F64)-O70) -> 49.7 | P73: =MAX(P71,$F64+P72*MAX(0,P52-$F66-$F64)-P70) -> 49.7 | Q73: =MAX(Q71,$F64+Q72*MAX(0,Q52-$F66-$F64)-Q70) -> 49.7 | ... FH73: =MAX(FH71,$F64+FH72*MAX(0,FH52-$F66-$F64)-FH70) -> 49.7
C74: BESS revenue per MW-year received | D74: EUR k/MW | J74: =J52+J67*(J73-J52) -> 0 | K74: =K52+K67*(K73-K52) -> 0 | L74: =L52+L67*(L73-L52) -> 0 | M74: =M52+M67*(M73-M52) -> 0 | N74: =N52+N67*(N73-N52) -> 0 | O74: =O52+O67*(O73-O52) -> 151.56337 | P74: =P52+P67*(P73-P52) -> 151.56337 | Q74: =Q52+Q67*(Q73-Q52) -> 151.56337 | ... FH74: =FH52+FH67*(FH73-FH52) -> 180.08692
A76: x | C76: Capacity and energy (annual balance; hourly limits inside Aurora's dispatch)
C77: PV generation after availability and degradation (E: first full year) | D77: MWh | E77: =SUMIF($J$7:$FH$7,YEAR($F16)+1,$J77:$FH77) -> 75611.992 | I77: =SUM(J77:FH77) -> 2523000.7 | J77: =$E13*$F14*In_PV_Avail*(1-In_Degradation)^J29*J28*J$6 -> 0 | K77: =$E13*$F14*In_PV_Avail*(1-In_Degradation)^K29*K28*K$6 -> 0 | L77: =$E13*$F14*In_PV_Avail*(1-In_Degradation)^L29*L28*L$6 -> 0 | M77: =$E13*$F14*In_PV_Avail*(1-In_Degradation)^M29*M28*M$6 -> 0 | N77: =$E13*$F14*In_PV_Avail*(1-In_Degradation)^N29*N28*N$6 -> 0 | O77: =$E13*$F14*In_PV_Avail*(1-In_Degradation)^O29*O28*O$6 -> 0 | P77: =$E13*$F14*In_PV_Avail*(1-In_Degradation)^P29*P28*P$6 -> 0 | Q77: =$E13*$F14*In_PV_Avail*(1-In_Degradation)^Q29*Q28*Q$6 -> 0 | ... FH77: =$E13*$F14*In_PV_Avail*(1-In_Degradation)^FH29*FH28*FH$6 -> 0
C78: Clipped (case table: v3 + fix 5 in A, DC-coupled 0 in B, C) | D78: MWh | I78: =SUM(J78:FH78) -> -50460.014 | J78: =-J77*$E17 -> 0 | K78: =-K77*$E17 -> 0 | L78: =-L77*$E17 -> 0 | M78: =-M77*$E17 -> 0 | N78: =-N77*$E17 -> 0 | O78: =-O77*$E17 -> 0 | P78: =-P77*$E17 -> 0 | Q78: =-Q77*$E17 -> 0 | ... FH78: =-FH77*$E17 -> 0
C79: Aurora block: charge from PV per MW (E: curve) | D79: MWh | E79: =$E47 -> DC 4h | J79: =INDEX(ChargeRES_Data,MATCH($E79,ChargeRES_Labels,0),MATCH(J$7,ChargeRES_Years,0)) -> 0 | K79: =INDEX(ChargeRES_Data,MATCH($E79,ChargeRES_Labels,0),MATCH(K$7,ChargeRES_Years,0)) -> 0 | L79: =INDEX(ChargeRES_Data,MATCH($E79,ChargeRES_Labels,0),MATCH(L$7,ChargeRES_Years,0)) -> 0 | M79: =INDEX(ChargeRES_Data,MATCH($E79,ChargeRES_Labels,0),MATCH(M$7,ChargeRES_Years,0)) -> 0 | N79: =INDEX(ChargeRES_Data,MATCH($E79,ChargeRES_Labels,0),MATCH(N$7,ChargeRES_Years,0)) -> 0 | O79: =INDEX(ChargeRES_Data,MATCH($E79,ChargeRES_Labels,0),MATCH(O$7,ChargeRES_Years,0)) -> -992.69296 | P79: =INDEX(ChargeRES_Data,MATCH($E79,ChargeRES_Labels,0),MATCH(P$7,ChargeRES_Years,0)) -> -992.69296 | Q79: =INDEX(ChargeRES_Data,MATCH($E79,ChargeRES_Labels,0),MATCH(Q$7,ChargeRES_Years,0)) -> -992.69296 | ... FH79: =INDEX(ChargeRES_Data,MATCH($E79,ChargeRES_Labels,0),MATCH(FH$7,ChargeRES_Years,0)) -> -841.29448
C80: Aurora block: charge from the grid per MW | D80: MWh | E80: =$E47 -> DC 4h | J80: =INDEX(ChargeGrid_Data,MATCH($E80,ChargeGrid_Labels,0),MATCH(J$7,ChargeGrid_Years,0)) -> 0 | K80: =INDEX(ChargeGrid_Data,MATCH($E80,ChargeGrid_Labels,0),MATCH(K$7,ChargeGrid_Years,0)) -> 0 | L80: =INDEX(ChargeGrid_Data,MATCH($E80,ChargeGrid_Labels,0),MATCH(L$7,ChargeGrid_Years,0)) -> 0 | M80: =INDEX(ChargeGrid_Data,MATCH($E80,ChargeGrid_Labels,0),MATCH(M$7,ChargeGrid_Years,0)) -> 0 | N80: =INDEX(ChargeGrid_Data,MATCH($E80,ChargeGrid_Labels,0),MATCH(N$7,ChargeGrid_Years,0)) -> 0 | O80: =INDEX(ChargeGrid_Data,MATCH($E80,ChargeGrid_Labels,0),MATCH(O$7,ChargeGrid_Years,0)) -> -751.2864 | P80: =INDEX(ChargeGrid_Data,MATCH($E80,ChargeGrid_Labels,0),MATCH(P$7,ChargeGrid_Years,0)) -> -751.2864 | Q80: =INDEX(ChargeGrid_Data,MATCH($E80,ChargeGrid_Labels,0),MATCH(Q$7,ChargeGrid_Years,0)) -> -751.2864 | ... FH80: =INDEX(ChargeGrid_Data,MATCH($E80,ChargeGrid_Labels,0),MATCH(FH$7,ChargeGrid_Years,0)) -> -579.51105
C81: Aurora block: discharge per MW | D81: MWh | E81: =$E47 -> DC 4h | J81: =INDEX(Discharge_Data,MATCH($E81,Discharge_Labels,0),MATCH(J$7,Discharge_Years,0)) -> 0 | K81: =INDEX(Discharge_Data,MATCH($E81,Discharge_Labels,0),MATCH(K$7,Discharge_Years,0)) -> 0 | L81: =INDEX(Discharge_Data,MATCH($E81,Discharge_Labels,0),MATCH(L$7,Discharge_Years,0)) -> 0 | M81: =INDEX(Discharge_Data,MATCH($E81,Discharge_Labels,0),MATCH(M$7,Discharge_Years,0)) -> 0 | N81: =INDEX(Discharge_Data,MATCH($E81,Discharge_Labels,0),MATCH(N$7,Discharge_Years,0)) -> 0 | O81: =INDEX(Discharge_Data,MATCH($E81,Discharge_Labels,0),MATCH(O$7,Discharge_Years,0)) -> 1434.7848 | P81: =INDEX(Discharge_Data,MATCH($E81,Discharge_Labels,0),MATCH(P$7,Discharge_Years,0)) -> 1434.7848 | Q81: =INDEX(Discharge_Data,MATCH($E81,Discharge_Labels,0),MATCH(Q$7,Discharge_Years,0)) -> 1434.7848 | ... FH81: =INDEX(Discharge_Data,MATCH($E81,Discharge_Labels,0),MATCH(FH$7,Discharge_Years,0)) -> 1151.9674
C82: Aurora block: discharge per MW coverable by PV charging | D82: MWh | J82: =MIN(J81,-J79*In_BESS_RTE) -> 0 | K82: =MIN(K81,-K79*In_BESS_RTE) -> 0 | L82: =MIN(L81,-L79*In_BESS_RTE) -> 0 | M82: =MIN(M81,-M79*In_BESS_RTE) -> 0 | N82: =MIN(N81,-N79*In_BESS_RTE) -> 0 | O82: =MIN(O81,-O79*In_BESS_RTE) -> 853.71595 | P82: =MIN(P81,-P79*In_BESS_RTE) -> 853.71595 | Q82: =MIN(Q81,-Q79*In_BESS_RTE) -> 853.71595 | ... FH82: =MIN(FH81,-FH79*In_BESS_RTE) -> 723.51325
C83: PV energy sent to the BESS | D83: MWh | I83: =SUM(J83:FH83) -> 1572735.8 | J83: =MIN(J77+J78,-J79*$E18*J28*J$6*J54) -> 0 | K83: =MIN(K77+K78,-K79*$E18*K28*K$6*K54) -> 0 | L83: =MIN(L77+L78,-L79*$E18*L28*L$6*L54) -> 0 | M83: =MIN(M77+M78,-M79*$E18*M28*M$6*M54) -> 0 | N83: =MIN(N77+N78,-N79*$E18*N28*N$6*N54) -> 0 | O83: =MIN(O77+O78,-O79*$E18*O28*O$6*O54) -> 0 | P83: =MIN(P77+P78,-P79*$E18*P28*P$6*P54) -> 0 | Q83: =MIN(Q77+Q78,-Q79*$E18*Q28*Q$6*Q54) -> 0 | ... FH83: =MIN(FH77+FH78,-FH79*$E18*FH28*FH$6*FH54) -> 0
C84: PV energy exported directly | D84: MWh | I84: =SUM(J84:FH84) -> 899804.84 | J84: =J77+J78-J83 -> 0 | K84: =K77+K78-K83 -> 0 | L84: =L77+L78-L83 -> 0 | M84: =M77+M78-M83 -> 0 | N84: =N77+N78-N83 -> 0 | O84: =O77+O78-O83 -> 0 | P84: =P77+P78-P83 -> 0 | Q84: =Q77+Q78-Q83 -> 0 | ... FH84: =FH77+FH78-FH83 -> 0
C85: BESS discharge (scaled to the charging allowed) | D85: MWh | I85: =SUM(J85:FH85) -> 1352552.8 | J85: =$E18*J28*J$6*J54*($E51*J81+(1-$E51)*J82) -> 0 | K85: =$E18*K28*K$6*K54*($E51*K81+(1-$E51)*K82) -> 0 | L85: =$E18*L28*L$6*L54*($E51*L81+(1-$E51)*L82) -> 0 | M85: =$E18*M28*M$6*M54*($E51*M81+(1-$E51)*M82) -> 0 | N85: =$E18*N28*N$6*N54*($E51*N81+(1-$E51)*N82) -> 0 | O85: =$E18*O28*O$6*O54*($E51*O81+(1-$E51)*O82) -> 0 | P85: =$E18*P28*P$6*P54*($E51*P81+(1-$E51)*P82) -> 0 | Q85: =$E18*Q28*Q$6*Q54*($E51*Q81+(1-$E51)*Q82) -> 0 | ... FH85: =$E18*FH28*FH$6*FH54*($E51*FH81+(1-$E51)*FH82) -> 0
C86: BESS charge from the grid (within the import allowed) | D86: MWh | I86: =SUM(J86:FH86) -> 0 | J86: =-J80*$E18*J28*J$6*J54*$E51 -> 0 | K86: =-K80*$E18*K28*K$6*K54*$E51 -> 0 | L86: =-L80*$E18*L28*L$6*L54*$E51 -> 0 | M86: =-M80*$E18*M28*M$6*M54*$E51 -> 0 | N86: =-N80*$E18*N28*N$6*N54*$E51 -> 0 | O86: =-O80*$E18*O28*O$6*O54*$E51 -> 0 | P86: =-P80*$E18*P28*P$6*P54*$E51 -> 0 | Q86: =-Q80*$E18*Q28*Q$6*Q54*$E51 -> 0 | ... FH86: =-FH80*$E18*FH28*FH$6*FH54*$E51 -> 0
C87: Energy exported (E: first full year) | D87: MWh | E87: =SUMIF($J$7:$FH$7,YEAR($F16)+1,$J87:$FH87) -> 67011.285 | I87: =SUM(J87:FH87) -> 2252357.7 | J87: =J84+J85 -> 0 | K87: =K84+K85 -> 0 | L87: =L84+L85 -> 0 | M87: =M84+M85 -> 0 | N87: =N84+N85 -> 0 | O87: =O84+O85 -> 0 | P87: =P84+P85 -> 0 | Q87: =Q84+Q85 -> 0 | ... FH87: =FH84+FH85 -> 0
A89: x | C89: Revenue, opex and EBITDA
C90: PV revenue: direct export and energy sent to the BESS (E: first full year) | D90: EUR k | E90: =SUMIF($J$7:$FH$7,YEAR($F16)+1,$J90:$FH90) -> 5377.0417 | I90: =SUM(J90:FH90) -> 227966.84 | J90: =(J84*J63+J83*J45)/Thousand -> 0 | K90: =(K84*K63+K83*K45)/Thousand -> 0 | L90: =(L84*L63+L83*L45)/Thousand -> 0 | M90: =(M84*M63+M83*M45)/Thousand -> 0 | N90: =(N84*N63+N83*N45)/Thousand -> 0 | O90: =(O84*O63+O83*O45)/Thousand -> 0 | P90: =(P84*P63+P83*P45)/Thousand -> 0 | Q90: =(Q84*Q63+Q83*Q45)/Thousand -> 0 | ... FH90: =(FH84*FH63+FH83*FH45)/Thousand -> 0
C91: Guarantee of origin revenue | D91: EUR k | I91: =SUM(J91:FH91) -> 6558.0115 | J91: =(J77+J78)*J46/Thousand -> 0 | K91: =(K77+K78)*K46/Thousand -> 0 | L91: =(L77+L78)*L46/Thousand -> 0 | M91: =(M77+M78)*M46/Thousand -> 0 | N91: =(N77+N78)*N46/Thousand -> 0 | O91: =(O77+O78)*O46/Thousand -> 0 | P91: =(P77+P78)*P46/Thousand -> 0 | Q91: =(Q77+Q78)*Q46/Thousand -> 0 | ... FH91: =(FH77+FH78)*FH46/Thousand -> 0
C92: BESS revenue (E: first full year) | D92: EUR k | E92: =SUMIF($J$7:$FH$7,YEAR($F16)+1,$J92:$FH92) -> 6010.5746 | I92: =SUM(J92:FH92) -> 237435.68 | J92: =J74*$E18*J28*J$6*J54 -> 0 | K92: =K74*$E18*K28*K$6*K54 -> 0 | L92: =L74*$E18*L28*L$6*L54 -> 0 | M92: =M74*$E18*M28*M$6*M54 -> 0 | N92: =N74*$E18*N28*N$6*N54 -> 0 | O92: =O74*$E18*O28*O$6*O54 -> 0 | P92: =P74*$E18*P28*P$6*P54 -> 0 | Q92: =Q74*$E18*Q28*Q$6*Q54 -> 0 | ... FH92: =FH74*$E18*FH28*FH$6*FH54 -> 0
C93: Revenue (E: first full year) | D93: EUR k | E93: =SUMIF($J$7:$FH$7,YEAR($F16)+1,$J93:$FH93) -> 11528.057 | I93: =SUM(J93:FH93) -> 471960.53 | J93: =J90+J91+J92 -> 0 | K93: =K90+K91+K92 -> 0 | L93: =L90+L91+L92 -> 0 | M93: =M90+M91+M92 -> 0 | N93: =N90+N91+N92 -> 0 | O93: =O90+O91+O92 -> 0 | P93: =P90+P91+P92 -> 0 | Q93: =Q90+Q91+Q92 -> 0 | ... FH93: =FH90+FH91+FH92 -> 0
C94: Of which contracted (fixed-price PV offer, BESS fixed fee) | D94: EUR k | I94: =SUM(J94:FH94) -> 0 | J94: =J61*$F58*J84*J63/Thousand+J67*$F64*$E18*J28*J$6*J54 -> 0 | K94: =K61*$F58*K84*K63/Thousand+K67*$F64*$E18*K28*K$6*K54 -> 0 | L94: =L61*$F58*L84*L63/Thousand+L67*$F64*$E18*L28*L$6*L54 -> 0 | M94: =M61*$F58*M84*M63/Thousand+M67*$F64*$E18*M28*M$6*M54 -> 0 | N94: =N61*$F58*N84*N63/Thousand+N67*$F64*$E18*N28*N$6*N54 -> 0 | O94: =O61*$F58*O84*O63/Thousand+O67*$F64*$E18*O28*O$6*O54 -> 0 | P94: =P61*$F58*P84*P63/Thousand+P67*$F64*$E18*P28*P$6*P54 -> 0 | Q94: =Q61*$F58*Q84*Q63/Thousand+Q67*$F64*$E18*Q28*Q$6*Q54 -> 0 | ... FH94: =FH61*$F58*FH84*FH63/Thousand+FH67*$F64*$E18*FH28*FH$6*FH54 -> 0
C95: O&M and MV cable O&M | D95: EUR k | I95: =SUM(J95:FH95) -> -65019.617 | J95: =-(In_OM+In_Cable_OM)*$E13*J41*(1+In_Opex_Adj)*J28*J$6 -> 0 | K95: =-(In_OM+In_Cable_OM)*$E13*K41*(1+In_Opex_Adj)*K28*K$6 -> 0 | L95: =-(In_OM+In_Cable_OM)*$E13*L41*(1+In_Opex_Adj)*L28*L$6 -> 0 | M95: =-(In_OM+In_Cable_OM)*$E13*M41*(1+In_Opex_Adj)*M28*M$6 -> 0 | N95: =-(In_OM+In_Cable_OM)*$E13*N41*(1+In_Opex_Adj)*N28*N$6 -> 0 | O95: =-(In_OM+In_Cable_OM)*$E13*O41*(1+In_Opex_Adj)*O28*O$6 -> 0 | P95: =-(In_OM+In_Cable_OM)*$E13*P41*(1+In_Opex_Adj)*P28*P$6 -> 0 | Q95: =-(In_OM+In_Cable_OM)*$E13*Q41*(1+In_Opex_Adj)*Q28*Q$6 -> 0 | ... FH95: =-(In_OM+In_Cable_OM)*$E13*FH41*(1+In_Opex_Adj)*FH28*FH$6 -> 0
C96: Balancing | D96: EUR k | I96: =SUM(J96:FH96) -> -18737.176 | J96: =-In_Balancing*(J77+J78)/Thousand*J41*(1+In_Opex_Adj) -> 0 | K96: =-In_Balancing*(K77+K78)/Thousand*K41*(1+In_Opex_Adj) -> 0 | L96: =-In_Balancing*(L77+L78)/Thousand*L41*(1+In_Opex_Adj) -> 0 | M96: =-In_Balancing*(M77+M78)/Thousand*M41*(1+In_Opex_Adj) -> 0 | N96: =-In_Balancing*(N77+N78)/Thousand*N41*(1+In_Opex_Adj) -> 0 | O96: =-In_Balancing*(O77+O78)/Thousand*O41*(1+In_Opex_Adj) -> 0 | P96: =-In_Balancing*(P77+P78)/Thousand*P41*(1+In_Opex_Adj) -> 0 | Q96: =-In_Balancing*(Q77+Q78)/Thousand*Q41*(1+In_Opex_Adj) -> 0 | ... FH96: =-In_Balancing*(FH77+FH78)/Thousand*FH41*(1+In_Opex_Adj) -> 0
C97: Land lease | D97: EUR k | I97: =SUM(J97:FH97) -> -5126.5509 | J97: =-In_Lease*J41*(1+In_Opex_Adj)*J28*J$6 -> 0 | K97: =-In_Lease*K41*(1+In_Opex_Adj)*K28*K$6 -> 0 | L97: =-In_Lease*L41*(1+In_Opex_Adj)*L28*L$6 -> 0 | M97: =-In_Lease*M41*(1+In_Opex_Adj)*M28*M$6 -> 0 | N97: =-In_Lease*N41*(1+In_Opex_Adj)*N28*N$6 -> 0 | O97: =-In_Lease*O41*(1+In_Opex_Adj)*O28*O$6 -> 0 | P97: =-In_Lease*P41*(1+In_Opex_Adj)*P28*P$6 -> 0 | Q97: =-In_Lease*Q41*(1+In_Opex_Adj)*Q28*Q$6 -> 0 | ... FH97: =-In_Lease*FH41*(1+In_Opex_Adj)*FH28*FH$6 -> 0
C98: BESS fixed opex | D98: EUR k | I98: =SUM(J98:FH98) -> -82238.42 | J98: =-In_BESS_Opex*$E18*J41*(1+In_Opex_Adj)*J28*J$6*J54 -> 0 | K98: =-In_BESS_Opex*$E18*K41*(1+In_Opex_Adj)*K28*K$6*K54 -> 0 | L98: =-In_BESS_Opex*$E18*L41*(1+In_Opex_Adj)*L28*L$6*L54 -> 0 | M98: =-In_BESS_Opex*$E18*M41*(1+In_Opex_Adj)*M28*M$6*M54 -> 0 | N98: =-In_BESS_Opex*$E18*N41*(1+In_Opex_Adj)*N28*N$6*N54 -> 0 | O98: =-In_BESS_Opex*$E18*O41*(1+In_Opex_Adj)*O28*O$6*O54 -> 0 | P98: =-In_BESS_Opex*$E18*P41*(1+In_Opex_Adj)*P28*P$6*P54 -> 0 | Q98: =-In_BESS_Opex*$E18*Q41*(1+In_Opex_Adj)*Q28*Q$6*Q54 -> 0 | ... FH98: =-In_BESS_Opex*$E18*FH41*(1+In_Opex_Adj)*FH28*FH$6*FH54 -> 0
C99: Route-to-market and offer fees | D99: EUR k | I99: =SUM(J99:FH99) -> 0 | J99: =-In_RTM*J90-INDEX(OPV_Cost,$E58)*J61*J$6 -> 0 | K99: =-In_RTM*K90-INDEX(OPV_Cost,$E58)*K61*K$6 -> 0 | L99: =-In_RTM*L90-INDEX(OPV_Cost,$E58)*L61*L$6 -> 0 | M99: =-In_RTM*M90-INDEX(OPV_Cost,$E58)*M61*M$6 -> 0 | N99: =-In_RTM*N90-INDEX(OPV_Cost,$E58)*N61*N$6 -> 0 | O99: =-In_RTM*O90-INDEX(OPV_Cost,$E58)*O61*O$6 -> 0 | P99: =-In_RTM*P90-INDEX(OPV_Cost,$E58)*P61*P$6 -> 0 | Q99: =-In_RTM*Q90-INDEX(OPV_Cost,$E58)*Q61*Q$6 -> 0 | ... FH99: =-In_RTM*FH90-INDEX(OPV_Cost,$E58)*FH61*FH$6 -> 0
C100: HIPA and innovation contribution | D100: EUR k | I100: =SUM(J100:FH100) -> -10855.092 | J100: =-J93*(In_HIPA+In_Innovation) -> 0 | K100: =-K93*(In_HIPA+In_Innovation) -> 0 | L100: =-L93*(In_HIPA+In_Innovation) -> 0 | M100: =-M93*(In_HIPA+In_Innovation) -> 0 | N100: =-N93*(In_HIPA+In_Innovation) -> 0 | O100: =-O93*(In_HIPA+In_Innovation) -> 0 | P100: =-P93*(In_HIPA+In_Innovation) -> 0 | Q100: =-Q93*(In_HIPA+In_Innovation) -> 0 | ... FH100: =-FH93*(In_HIPA+In_Innovation) -> 0
C101: EBITDA (E: first full year) | D101: EUR k | E101: =SUMIF($J$7:$FH$7,YEAR($F16)+1,$J101:$FH101) -> 7771.1724 | I101: =SUM(J101:FH101) -> 289983.68 | J101: =J93+SUM(J95:J100) -> 0 | K101: =K93+SUM(K95:K100) -> 0 | L101: =L93+SUM(L95:L100) -> 0 | M101: =M93+SUM(M95:M100) -> 0 | N101: =N93+SUM(N95:N100) -> 0 | O101: =O93+SUM(O95:O100) -> 0 | P101: =P93+SUM(P95:P100) -> 0 | Q101: =Q93+SUM(Q95:Q100) -> 0 | ... FH101: =FH93+SUM(FH95:FH100) -> 0
A103: x | C103: Development, early works, deposits and guarantees (E: to the exit, F: to COD)
C104: FEP SPV acquisition price / connection rights | D104: EUR k | I104: =SUM(J104:FH104) -> -549 | J104: =-In_SPV_Price*J19 -> -549 | K104: =-In_SPV_Price*K19 -> 0 | L104: =-In_SPV_Price*L19 -> 0 | M104: =-In_SPV_Price*M19 -> 0 | N104: =-In_SPV_Price*N19 -> 0 | O104: =-In_SPV_Price*O19 -> 0 | P104: =-In_SPV_Price*P19 -> 0 | Q104: =-In_SPV_Price*Q19 -> 0 | ... FH104: =-In_SPV_Price*FH19 -> 0
C105: Transaction costs (FEP) | D105: EUR k | I105: =SUM(J105:FH105) -> -200 | J105: =-In_Transaction*J19 -> -200 | K105: =-In_Transaction*K19 -> 0 | L105: =-In_Transaction*L19 -> 0 | M105: =-In_Transaction*M19 -> 0 | N105: =-In_Transaction*N19 -> 0 | O105: =-In_Transaction*O19 -> 0 | P105: =-In_Transaction*P19 -> 0 | Q105: =-In_Transaction*Q19 -> 0 | ... FH105: =-In_Transaction*FH19 -> 0
C106: DSA loan to PSH | D106: EUR k | I106: =SUM(J106:FH106) -> -915 | J106: =-In_DSA_Per_MWp*$E13*J30 -> -116.7284 | K106: =-In_DSA_Per_MWp*$E13*K30 -> -338.88889 | L106: =-In_DSA_Per_MWp*$E13*L30 -> -342.65432 | M106: =-In_DSA_Per_MWp*$E13*M30 -> -116.7284 | N106: =-In_DSA_Per_MWp*$E13*N30 -> 0 | O106: =-In_DSA_Per_MWp*$E13*O30 -> 0 | P106: =-In_DSA_Per_MWp*$E13*P30 -> 0 | Q106: =-In_DSA_Per_MWp*$E13*Q30 -> 0 | ... FH106: =-In_DSA_Per_MWp*$E13*FH30 -> 0
C107: Early works paid in development (lines in scope) | D107: EUR k | E107: =SUMIF($J$3:$FH$3,"<="&$E20,$J107:$FH107) -> -785 | I107: =SUM(J107:FH107) -> -785 | J107: =-SUMIFS(EW_Keur,EW_Date,">="&J$3,EW_Date,"<="&J$4,EW_Rank,"<="&In_Milestones_Scope) -> -150 | K107: =-SUMIFS(EW_Keur,EW_Date,">="&K$3,EW_Date,"<="&K$4,EW_Rank,"<="&In_Milestones_Scope) -> -175 | L107: =-SUMIFS(EW_Keur,EW_Date,">="&L$3,EW_Date,"<="&L$4,EW_Rank,"<="&In_Milestones_Scope) -> -460 | M107: =-SUMIFS(EW_Keur,EW_Date,">="&M$3,EW_Date,"<="&M$4,EW_Rank,"<="&In_Milestones_Scope) -> 0 | N107: =-SUMIFS(EW_Keur,EW_Date,">="&N$3,EW_Date,"<="&N$4,EW_Rank,"<="&In_Milestones_Scope) -> 0 | O107: =-SUMIFS(EW_Keur,EW_Date,">="&O$3,EW_Date,"<="&O$4,EW_Rank,"<="&In_Milestones_Scope) -> 0 | P107: =-SUMIFS(EW_Keur,EW_Date,">="&P$3,EW_Date,"<="&P$4,EW_Rank,"<="&In_Milestones_Scope) -> 0 | Q107: =-SUMIFS(EW_Keur,EW_Date,">="&Q$3,EW_Date,"<="&Q$4,EW_Rank,"<="&In_Milestones_Scope) -> 0 | ... FH107: =-SUMIFS(EW_Keur,EW_Date,">="&FH$3,EW_Date,"<="&FH$4,EW_Rank,"<="&In_Milestones_Scope) -> 0
...

Sheet Calc_2
A1: 2 | C1: Bid number
B2: =Dashboard!$C$3&" – Calculations – "&INDEX(Bid_Labels,1,$A$1) -> Project Zalahaláp – Calculations – B Aurora
C3: Period start | D3: date | J3: =I$4+1 -> 45931 | K3: =J$4+1 -> 46023 | L3: =K$4+1 -> 46113 | M3: =L$4+1 -> 46204 | N3: =M$4+1 -> 46296 | O3: =N$4+1 -> 46388 | P3: =O$4+1 -> 46478 | Q3: =P$4+1 -> 46569 | ... FH3: =FG$4+1 -> 59993
C4: Period end | D4: date | I4: =In_Model_Start-1 -> 45930 | J4: =EOMONTH(J$3,Months_Per_Period-1) -> 46022 | K4: =EOMONTH(K$3,Months_Per_Period-1) -> 46112 | L4: =EOMONTH(L$3,Months_Per_Period-1) -> 46203 | M4: =EOMONTH(M$3,Months_Per_Period-1) -> 46295 | N4: =EOMONTH(N$3,Months_Per_Period-1) -> 46387 | O4: =EOMONTH(O$3,Months_Per_Period-1) -> 46477 | P4: =EOMONTH(P$3,Months_Per_Period-1) -> 46568 | Q4: =EOMONTH(Q$3,Months_Per_Period-1) -> 46660 | ... FH4: =EOMONTH(FH$3,Months_Per_Period-1) -> 60083
C5: Days in period | D5: days | J5: =J$4-J$3+1 -> 92 | K5: =K$4-K$3+1 -> 90 | L5: =L$4-L$3+1 -> 91 | M5: =M$4-M$3+1 -> 92 | N5: =N$4-N$3+1 -> 92 | O5: =O$4-O$3+1 -> 90 | P5: =P$4-P$3+1 -> 91 | Q5: =Q$4-Q$3+1 -> 92 | ... FH5: =FH$4-FH$3+1 -> 91
C6: Year fraction | D6: factor | J6: =J$5/Days_In_Year -> 0.25205479 | K6: =K$5/Days_In_Year -> 0.24657534 | L6: =L$5/Days_In_Year -> 0.24931507 | M6: =M$5/Days_In_Year -> 0.25205479 | N6: =N$5/Days_In_Year -> 0.25205479 | O6: =O$5/Days_In_Year -> 0.24657534 | P6: =P$5/Days_In_Year -> 0.24931507 | Q6: =Q$5/Days_In_Year -> 0.25205479 | ... FH6: =FH$5/Days_In_Year -> 0.24931507
C7: Year | D7: year | J7: =YEAR(J$4) -> 2025 | K7: =YEAR(K$4) -> 2026 | L7: =YEAR(L$4) -> 2026 | M7: =YEAR(M$4) -> 2026 | N7: =YEAR(N$4) -> 2026 | O7: =YEAR(O$4) -> 2027 | P7: =YEAR(P$4) -> 2027 | Q7: =YEAR(Q$4) -> 2027 | ... FH7: =YEAR(FH$4) -> 2064
C8: Period counter | D8: # | J8: =I$8+1 -> 1 | K8: =J$8+1 -> 2 | L8: =K$8+1 -> 3 | M8: =L$8+1 -> 4 | N8: =M$8+1 -> 5 | O8: =N$8+1 -> 6 | P8: =O$8+1 -> 7 | Q8: =P$8+1 -> 8 | ... FH8: =FG$8+1 -> 155
A11: x | C11: Case and timing
C12: Revenue case (E: lever, F: column of the case table) | D12: text | E12: =INDEX(Dash_Case,1,$A$1) -> B | F12: =MATCH($E12,Case_Names,0) -> 2
C13: PV capacity (E: MWp) and grid export (F: MVA) | D13: MW | E13: =INDEX(Case_MWp,1,$F12) -> 63 | F13: =INDEX(Case_MVA,1,$F12) -> 49.9
C14: Specific yield (E: case, F: after the yield set) | D14: MWh/MWp | E14: =INDEX(Case_Yield,1,$F12) -> 1265 | F14: =$E14*(1+In_Yield_Adj) -> 1265
C15: RtB (E) and RtB exit (F) | D15: date | E15: =INDEX(Case_RtB,1,$F12) -> 46387 | F15: =INDEX(Case_Exit,1,$F12) -> 46477
C16: NTP (E) and COD (F) | D16: date | E16: =INDEX(Case_NTP,1,$F12) -> 46568 | F16: =EOMONTH(INDEX(Case_COD,1,$F12),In_COD_Delay) -> 46843
C17: Clipping, share of DC energy (case table) | D17: % | E17: =INDEX(Case_Clip,1,$F12) -> 0
C18: BESS built (E: MW, F: MWh) | D18: MW | E18: =In_BESS_MW*In_BESS_On -> 50 | F18: =$E18*In_BESS_Hours -> 200
C19: Acquisition and JV start | D19: flag | E19: =In_Acq -> 45991 | I19: =SUM(J19:FH19) -> 1 | J19: =N(AND(J$3<=$E19,J$4>=$E19)) -> 1 | K19: =N(AND(K$3<=$E19,K$4>=$E19)) -> 0 | L19: =N(AND(L$3<=$E19,L$4>=$E19)) -> 0 | M19: =N(AND(M$3<=$E19,M$4>=$E19)) -> 0 | N19: =N(AND(N$3<=$E19,N$4>=$E19)) -> 0 | O19: =N(AND(O$3<=$E19,O$4>=$E19)) -> 0 | P19: =N(AND(P$3<=$E19,P$4>=$E19)) -> 0 | Q19: =N(AND(Q$3<=$E19,Q$4>=$E19)) -> 0 | ... FH19: =N(AND(FH$3<=$E19,FH$4>=$E19)) -> 0
C20: RtB exit (sale closing) | D20: flag | E20: =$F15 -> 46477 | I20: =SUM(J20:FH20) -> 1 | J20: =N(AND(J$3<=$E20,J$4>=$E20)) -> 0 | K20: =N(AND(K$3<=$E20,K$4>=$E20)) -> 0 | L20: =N(AND(L$3<=$E20,L$4>=$E20)) -> 0 | M20: =N(AND(M$3<=$E20,M$4>=$E20)) -> 0 | N20: =N(AND(N$3<=$E20,N$4>=$E20)) -> 0 | O20: =N(AND(O$3<=$E20,O$4>=$E20)) -> 1 | P20: =N(AND(P$3<=$E20,P$4>=$E20)) -> 0 | Q20: =N(AND(Q$3<=$E20,Q$4>=$E20)) -> 0 | ... FH20: =N(AND(FH$3<=$E20,FH$4>=$E20)) -> 0
C21: NTP | D21: flag | E21: =$E16 -> 46568 | I21: =SUM(J21:FH21) -> 1 | J21: =N(AND(J$3<=$E21,J$4>=$E21)) -> 0 | K21: =N(AND(K$3<=$E21,K$4>=$E21)) -> 0 | L21: =N(AND(L$3<=$E21,L$4>=$E21)) -> 0 | M21: =N(AND(M$3<=$E21,M$4>=$E21)) -> 0 | N21: =N(AND(N$3<=$E21,N$4>=$E21)) -> 0 | O21: =N(AND(O$3<=$E21,O$4>=$E21)) -> 0 | P21: =N(AND(P$3<=$E21,P$4>=$E21)) -> 1 | Q21: =N(AND(Q$3<=$E21,Q$4>=$E21)) -> 0 | ... FH21: =N(AND(FH$3<=$E21,FH$4>=$E21)) -> 0
C22: COD | D22: flag | E22: =$F16 -> 46843 | I22: =SUM(J22:FH22) -> 1 | J22: =N(AND(J$3<=$E22,J$4>=$E22)) -> 0 | K22: =N(AND(K$3<=$E22,K$4>=$E22)) -> 0 | L22: =N(AND(L$3<=$E22,L$4>=$E22)) -> 0 | M22: =N(AND(M$3<=$E22,M$4>=$E22)) -> 0 | N22: =N(AND(N$3<=$E22,N$4>=$E22)) -> 0 | O22: =N(AND(O$3<=$E22,O$4>=$E22)) -> 0 | P22: =N(AND(P$3<=$E22,P$4>=$E22)) -> 0 | Q22: =N(AND(Q$3<=$E22,Q$4>=$E22)) -> 0 | ... FH22: =N(AND(FH$3<=$E22,FH$4>=$E22)) -> 0
C23: Exit column on the timeline (buyer view at RtB) | D23: # | E23: =MATCH($E20-1,$J$4:$FH$4,1)+1 -> 6
C24: COD column on the timeline (buyer view at COD) | D24: # | E24: =MATCH($E22,$J$4:$FH$4,0) -> 10
C25: After the exit period | D25: flag | J25: =N(J$3>$E20) -> 0 | K25: =N(K$3>$E20) -> 0 | L25: =N(L$3>$E20) -> 0 | M25: =N(M$3>$E20) -> 0 | N25: =N(N$3>$E20) -> 0 | O25: =N(O$3>$E20) -> 0 | P25: =N(P$3>$E20) -> 1 | Q25: =N(Q$3>$E20) -> 1 | ... FH25: =N(FH$3>$E20) -> 1
C26: After COD | D26: flag | J26: =N(J$4>$E22) -> 0 | K26: =N(K$4>$E22) -> 0 | L26: =N(L$4>$E22) -> 0 | M26: =N(M$4>$E22) -> 0 | N26: =N(N$4>$E22) -> 0 | O26: =N(O$4>$E22) -> 0 | P26: =N(P$4>$E22) -> 0 | Q26: =N(Q$4>$E22) -> 0 | ... FH26: =N(FH$4>$E22) -> 1
C27: Construction spread (NTP → COD) | D27: factor | E27: =$E16+1 -> 46569 | F27: =$F16 -> 46843 | I27: =SUM(J27:FH27) -> 1 | J27: =MAX(0,MIN($F27,J$4)-MAX($E27,J$3)+1)/($F27-$E27+1) -> 0 | K27: =MAX(0,MIN($F27,K$4)-MAX($E27,K$3)+1)/($F27-$E27+1) -> 0 | L27: =MAX(0,MIN($F27,L$4)-MAX($E27,L$3)+1)/($F27-$E27+1) -> 0 | M27: =MAX(0,MIN($F27,M$4)-MAX($E27,M$3)+1)/($F27-$E27+1) -> 0 | N27: =MAX(0,MIN($F27,N$4)-MAX($E27,N$3)+1)/($F27-$E27+1) -> 0 | O27: =MAX(0,MIN($F27,O$4)-MAX($E27,O$3)+1)/($F27-$E27+1) -> 0 | P27: =MAX(0,MIN($F27,P$4)-MAX($E27,P$3)+1)/($F27-$E27+1) -> 0 | Q27: =MAX(0,MIN($F27,Q$4)-MAX($E27,Q$3)+1)/($F27-$E27+1) -> 0.33454545 | ... FH27: =MAX(0,MIN($F27,FH$4)-MAX($E27,FH$3)+1)/($F27-$E27+1) -> 0
C28: Operations (COD → end of life) | D28: flag | E28: =$F16+1 -> 46844 | F28: =EDATE($F16,In_Life*Months_In_Year) -> 59626 | J28: =MAX(0,(MIN($F28,J$4)-MAX($E28,J$3)+1)/J$5) -> 0 | K28: =MAX(0,(MIN($F28,K$4)-MAX($E28,K$3)+1)/K$5) -> 0 | L28: =MAX(0,(MIN($F28,L$4)-MAX($E28,L$3)+1)/L$5) -> 0 | M28: =MAX(0,(MIN($F28,M$4)-MAX($E28,M$3)+1)/M$5) -> 0 | N28: =MAX(0,(MIN($F28,N$4)-MAX($E28,N$3)+1)/N$5) -> 0 | O28: =MAX(0,(MIN($F28,O$4)-MAX($E28,O$3)+1)/O$5) -> 0 | P28: =MAX(0,(MIN($F28,P$4)-MAX($E28,P$3)+1)/P$5) -> 0 | Q28: =MAX(0,(MIN($F28,Q$4)-MAX($E28,Q$3)+1)/Q$5) -> 0 | ... FH28: =MAX(0,(MIN($F28,FH$4)-MAX($E28,FH$3)+1)/FH$5) -> 0
C29: Operating years elapsed at the period start | D29: years | J29: =MAX(0,J$3-1-$F16)/Days_In_Year -> 0 | K29: =MAX(0,K$3-1-$F16)/Days_In_Year -> 0 | L29: =MAX(0,L$3-1-$F16)/Days_In_Year -> 0 | M29: =MAX(0,M$3-1-$F16)/Days_In_Year -> 0 | N29: =MAX(0,N$3-1-$F16)/Days_In_Year -> 0 | O29: =MAX(0,O$3-1-$F16)/Days_In_Year -> 0 | P29: =MAX(0,P$3-1-$F16)/Days_In_Year -> 0 | Q29: =MAX(0,Q$3-1-$F16)/Days_In_Year -> 0 | ... FH29: =MAX(0,FH$3-1-$F16)/Days_In_Year -> 36.024658
C30: DSA loan spread (acquisition → RtB) | D30: factor | E30: =In_Acq+1 -> 45992 | F30: =$E15 -> 46387 | I30: =SUM(J30:FH30) -> 1 | J30: =MAX(0,MIN($F30,J$4)-MAX($E30,J$3)+1)/($F30-$E30+1) -> 0.078282828 | K30: =MAX(0,MIN($F30,K$4)-MAX($E30,K$3)+1)/($F30-$E30+1) -> 0.22727273 | L30: =MAX(0,MIN($F30,L$4)-MAX($E30,L$3)+1)/($F30-$E30+1) -> 0.22979798 | M30: =MAX(0,MIN($F30,M$4)-MAX($E30,M$3)+1)/($F30-$E30+1) -> 0.23232323 | N30: =MAX(0,MIN($F30,N$4)-MAX($E30,N$3)+1)/($F30-$E30+1) -> 0.23232323 | O30: =MAX(0,MIN($F30,O$4)-MAX($E30,O$3)+1)/($F30-$E30+1) -> 0 | P30: =MAX(0,MIN($F30,P$4)-MAX($E30,P$3)+1)/($F30-$E30+1) -> 0 | Q30: =MAX(0,MIN($F30,Q$4)-MAX($E30,Q$3)+1)/($F30-$E30+1) -> 0 | ... FH30: =MAX(0,MIN($F30,FH$4)-MAX($E30,FH$3)+1)/($F30-$E30+1) -> 0
C31: Pre-RtB development cost spread | D31: factor | E31: =EOMONTH(In_PreRtB_First,-1)+1 -> 46296 | F31: =In_PreRtB_Last -> 46477 | I31: =SUM(J31:FH31) -> 1 | J31: =MAX(0,MIN($F31,J$4)-MAX($E31,J$3)+1)/($F31-$E31+1) -> 0 | K31: =MAX(0,MIN($F31,K$4)-MAX($E31,K$3)+1)/($F31-$E31+1) -> 0 | L31: =MAX(0,MIN($F31,L$4)-MAX($E31,L$3)+1)/($F31-$E31+1) -> 0 | M31: =MAX(0,MIN($F31,M$4)-MAX($E31,M$3)+1)/($F31-$E31+1) -> 0 | N31: =MAX(0,MIN($F31,N$4)-MAX($E31,N$3)+1)/($F31-$E31+1) -> 0.50549451 | O31: =MAX(0,MIN($F31,O$4)-MAX($E31,O$3)+1)/($F31-$E31+1) -> 0.49450549 | P31: =MAX(0,MIN($F31,P$4)-MAX($E31,P$3)+1)/($F31-$E31+1) -> 0 | Q31: =MAX(0,MIN($F31,Q$4)-MAX($E31,Q$3)+1)/($F31-$E31+1) -> 0 | ... FH31: =MAX(0,MIN($F31,FH$4)-MAX($E31,FH$3)+1)/($F31-$E31+1) -> 0
C32: Debt repayment period | D32: flag | E32: =$F16+1 -> 46844 | F32: =EDATE($F16,In_Debt_Tenor*Months_In_Year) -> 52321 | J32: =MAX(0,(MIN($F32,J$4)-MAX($E32,J$3)+1)/J$5) -> 0 | K32: =MAX(0,(MIN($F32,K$4)-MAX($E32,K$3)+1)/K$5) -> 0 | L32: =MAX(0,(MIN($F32,L$4)-MAX($E32,L$3)+1)/L$5) -> 0 | M32: =MAX(0,(MIN($F32,M$4)-MAX($E32,M$3)+1)/M$5) -> 0 | N32: =MAX(0,(MIN($F32,N$4)-MAX($E32,N$3)+1)/N$5) -> 0 | O32: =MAX(0,(MIN($F32,O$4)-MAX($E32,O$3)+1)/O$5) -> 0 | P32: =MAX(0,(MIN($F32,P$4)-MAX($E32,P$3)+1)/P$5) -> 0 | Q32: =MAX(0,(MIN($F32,Q$4)-MAX($E32,Q$3)+1)/Q$5) -> 0 | ... FH32: =MAX(0,(MIN($F32,FH$4)-MAX($E32,FH$3)+1)/FH$5) -> 0
C33: Last debt repayment | D33: flag | E33: =EDATE($F16,In_Debt_Tenor*Months_In_Year) -> 52321 | I33: =SUM(J33:FH33) -> 1 | J33: =N(AND(J$3<=$E33,J$4>=$E33)) -> 0 | K33: =N(AND(K$3<=$E33,K$4>=$E33)) -> 0 | L33: =N(AND(L$3<=$E33,L$4>=$E33)) -> 0 | M33: =N(AND(M$3<=$E33,M$4>=$E33)) -> 0 | N33: =N(AND(N$3<=$E33,N$4>=$E33)) -> 0 | O33: =N(AND(O$3<=$E33,O$4>=$E33)) -> 0 | P33: =N(AND(P$3<=$E33,P$4>=$E33)) -> 0 | Q33: =N(AND(Q$3<=$E33,Q$4>=$E33)) -> 0 | ... FH33: =N(AND(FH$3<=$E33,FH$4>=$E33)) -> 0
C34: Tax depreciation spread: PV, grid, development | D34: factor | E34: =$F16+1 -> 46844 | F34: =EDATE($F16,In_Dep_Years*Months_In_Year) -> 57800 | I34: =SUM(J34:FH34) -> 1 | J34: =MAX(0,MIN($F34,J$4)-MAX($E34,J$3)+1)/($F34-$E34+1) -> 0 | K34: =MAX(0,MIN($F34,K$4)-MAX($E34,K$3)+1)/($F34-$E34+1) -> 0 | L34: =MAX(0,MIN($F34,L$4)-MAX($E34,L$3)+1)/($F34-$E34+1) -> 0 | M34: =MAX(0,MIN($F34,M$4)-MAX($E34,M$3)+1)/($F34-$E34+1) -> 0 | N34: =MAX(0,MIN($F34,N$4)-MAX($E34,N$3)+1)/($F34-$E34+1) -> 0 | O34: =MAX(0,MIN($F34,O$4)-MAX($E34,O$3)+1)/($F34-$E34+1) -> 0 | P34: =MAX(0,MIN($F34,P$4)-MAX($E34,P$3)+1)/($F34-$E34+1) -> 0 | Q34: =MAX(0,MIN($F34,Q$4)-MAX($E34,Q$3)+1)/($F34-$E34+1) -> 0 | ... FH34: =MAX(0,MIN($F34,FH$4)-MAX($E34,FH$3)+1)/($F34-$E34+1) -> 0
C35: Tax depreciation spread: BESS | D35: factor | E35: =$F16+1 -> 46844 | F35: =EDATE($F16,In_Dep_BESS_Years*Months_In_Year) -> 50495 | I35: =SUM(J35:FH35) -> 1 | J35: =MAX(0,MIN($F35,J$4)-MAX($E35,J$3)+1)/($F35-$E35+1) -> 0 | K35: =MAX(0,MIN($F35,K$4)-MAX($E35,K$3)+1)/($F35-$E35+1) -> 0 | L35: =MAX(0,MIN($F35,L$4)-MAX($E35,L$3)+1)/($F35-$E35+1) -> 0 | M35: =MAX(0,MIN($F35,M$4)-MAX($E35,M$3)+1)/($F35-$E35+1) -> 0 | N35: =MAX(0,MIN($F35,N$4)-MAX($E35,N$3)+1)/($F35-$E35+1) -> 0 | O35: =MAX(0,MIN($F35,O$4)-MAX($E35,O$3)+1)/($F35-$E35+1) -> 0 | P35: =MAX(0,MIN($F35,P$4)-MAX($E35,P$3)+1)/($F35-$E35+1) -> 0 | Q35: =MAX(0,MIN($F35,Q$4)-MAX($E35,Q$3)+1)/($F35-$E35+1) -> 0 | ... FH35: =MAX(0,MIN($F35,FH$4)-MAX($E35,FH$3)+1)/($F35-$E35+1) -> 0
C36: Debt compounding index (E: at COD, F: rate per period) | D36: factor | E36: =SUMIF($J$4:$FH$4,$F16,$J36:$FH36) -> 1.1322708 | F36: =In_Debt_Rate*Months_Per_Period/Months_In_Year -> 0.0125 | J36: =(1+$F36)^J$8 -> 1.0125 | K36: =(1+$F36)^K$8 -> 1.0251562 | L36: =(1+$F36)^L$8 -> 1.0379707 | M36: =(1+$F36)^M$8 -> 1.0509453 | N36: =(1+$F36)^N$8 -> 1.0640822 | O36: =(1+$F36)^O$8 -> 1.0773832 | P36: =(1+$F36)^P$8 -> 1.0908505 | Q36: =(1+$F36)^Q$8 -> 1.1044861 | ... FH36: =(1+$F36)^FH$8 -> 6.8585126
C37: 31-Dec capitalisation | D37: flag | J37: =N(MONTH(J$4)=Months_In_Year) -> 1 | K37: =N(MONTH(K$4)=Months_In_Year) -> 0 | L37: =N(MONTH(L$4)=Months_In_Year) -> 0 | M37: =N(MONTH(M$4)=Months_In_Year) -> 0 | N37: =N(MONTH(N$4)=Months_In_Year) -> 1 | O37: =N(MONTH(O$4)=Months_In_Year) -> 0 | P37: =N(MONTH(P$4)=Months_In_Year) -> 0 | Q37: =N(MONTH(Q$4)=Months_In_Year) -> 0 | ... FH37: =N(MONTH(FH$4)=Months_In_Year) -> 0
C38: First quarter of the year | D38: flag | J38: =N(MONTH(J$4)<=Months_Per_Period) -> 0 | K38: =N(MONTH(K$4)<=Months_Per_Period) -> 1 | L38: =N(MONTH(L$4)<=Months_Per_Period) -> 0 | M38: =N(MONTH(M$4)<=Months_Per_Period) -> 0 | N38: =N(MONTH(N$4)<=Months_Per_Period) -> 0 | O38: =N(MONTH(O$4)<=Months_Per_Period) -> 1 | P38: =N(MONTH(P$4)<=Months_Per_Period) -> 0 | Q38: =N(MONTH(Q$4)<=Months_Per_Period) -> 0 | ... FH38: =N(MONTH(FH$4)<=Months_Per_Period) -> 0
A40: x | C40: Prices (real 2025 curves × Aurora euro index)
C41: Aurora euro index | D41: factor | J41: =INDEX(Euro_Index,MATCH(J$7,Price_Years,0)) -> 1 | K41: =INDEX(Euro_Index,MATCH(K$7,Price_Years,0)) -> 1.01897 | L41: =INDEX(Euro_Index,MATCH(L$7,Price_Years,0)) -> 1.01897 | M41: =INDEX(Euro_Index,MATCH(M$7,Price_Years,0)) -> 1.01897 | N41: =INDEX(Euro_Index,MATCH(N$7,Price_Years,0)) -> 1.01897 | O41: =INDEX(Euro_Index,MATCH(O$7,Price_Years,0)) -> 1.040399 | P41: =INDEX(Euro_Index,MATCH(P$7,Price_Years,0)) -> 1.040399 | Q41: =INDEX(Euro_Index,MATCH(Q$7,Price_Years,0)) -> 1.040399 | ... FH41: =INDEX(Euro_Index,MATCH(FH$7,Price_Years,0)) -> 2.1668863
C42: PV price, direct export, real 2025 (E: curve) | D42: EUR/MWh | E42: =INDEX(Case_PV_Curve,1,$F12) -> DC 4h direct | J42: =INDEX(Price_Data,MATCH($E42,Price_Labels,0),MATCH(J$7,Price_Years,0)) -> 0 | K42: =INDEX(Price_Data,MATCH($E42,Price_Labels,0),MATCH(K$7,Price_Years,0)) -> 0 | L42: =INDEX(Price_Data,MATCH($E42,Price_Labels,0),MATCH(L$7,Price_Years,0)) -> 0 | M42: =INDEX(Price_Data,MATCH($E42,Price_Labels,0),MATCH(M$7,Price_Years,0)) -> 0 | N42: =INDEX(Price_Data,MATCH($E42,Price_Labels,0),MATCH(N$7,Price_Years,0)) -> 0 | O42: =INDEX(Price_Data,MATCH($E42,Price_Labels,0),MATCH(O$7,Price_Years,0)) -> 107.45398 | P42: =INDEX(Price_Data,MATCH($E42,Price_Labels,0),MATCH(P$7,Price_Years,0)) -> 107.45398 | Q42: =INDEX(Price_Data,MATCH($E42,Price_Labels,0),MATCH(Q$7,Price_Years,0)) -> 107.45398 | ... FH42: =INDEX(Price_Data,MATCH($E42,Price_Labels,0),MATCH(FH$7,Price_Years,0)) -> 56.585236
C43: PV price, energy sent to the BESS, real 2025 (E: curve) | D43: EUR/MWh | E43: =INDEX(Case_PV_Transfer,1,$F12) -> DC 4h transfer | J43: =INDEX(Price_Data,MATCH($E43,Price_Labels,0),MATCH(J$7,Price_Years,0)) -> 0 | K43: =INDEX(Price_Data,MATCH($E43,Price_Labels,0),MATCH(K$7,Price_Years,0)) -> 0 | L43: =INDEX(Price_Data,MATCH($E43,Price_Labels,0),MATCH(L$7,Price_Years,0)) -> 0 | M43: =INDEX(Price_Data,MATCH($E43,Price_Labels,0),MATCH(M$7,Price_Years,0)) -> 0 | N43: =INDEX(Price_Data,MATCH($E43,Price_Labels,0),MATCH(N$7,Price_Years,0)) -> 0 | O43: =INDEX(Price_Data,MATCH($E43,Price_Labels,0),MATCH(O$7,Price_Years,0)) -> 36.551423 | P43: =INDEX(Price_Data,MATCH($E43,Price_Labels,0),MATCH(P$7,Price_Years,0)) -> 36.551423 | Q43: =INDEX(Price_Data,MATCH($E43,Price_Labels,0),MATCH(Q$7,Price_Years,0)) -> 36.551423 | ... FH43: =INDEX(Price_Data,MATCH($E43,Price_Labels,0),MATCH(FH$7,Price_Years,0)) -> 20.340431
C44: PV merchant price, direct export, nominal (price set applied) | D44: EUR/MWh | J44: =J42*J41*(1+In_PV_Price_Adj) -> 0 | K44: =K42*K41*(1+In_PV_Price_Adj) -> 0 | L44: =L42*L41*(1+In_PV_Price_Adj) -> 0 | M44: =M42*M41*(1+In_PV_Price_Adj) -> 0 | N44: =N42*N41*(1+In_PV_Price_Adj) -> 0 | O44: =O42*O41*(1+In_PV_Price_Adj) -> 111.79501 | P44: =P42*P41*(1+In_PV_Price_Adj) -> 111.79501 | Q44: =Q42*Q41*(1+In_PV_Price_Adj) -> 111.79501 | ... FH44: =FH42*FH41*(1+In_PV_Price_Adj) -> 122.61377
C45: PV transfer price to the BESS, nominal (price set applied) | D45: EUR/MWh | J45: =J43*J41*(1+In_PV_Price_Adj) -> 0 | K45: =K43*K41*(1+In_PV_Price_Adj) -> 0 | L45: =L43*L41*(1+In_PV_Price_Adj) -> 0 | M45: =M43*M41*(1+In_PV_Price_Adj) -> 0 | N45: =N43*N41*(1+In_PV_Price_Adj) -> 0 | O45: =O43*O41*(1+In_PV_Price_Adj) -> 38.028064 | P45: =P43*P41*(1+In_PV_Price_Adj) -> 38.028064 | Q45: =Q43*Q41*(1+In_PV_Price_Adj) -> 38.028064 | ... FH45: =FH43*FH41*(1+In_PV_Price_Adj) -> 44.075402
C46: Guarantee of origin price, nominal | D46: EUR/MWh | J46: =In_GoO*J41 -> 1.75 | K46: =In_GoO*K41 -> 1.7831975 | L46: =In_GoO*L41 -> 1.7831975 | M46: =In_GoO*M41 -> 1.7831975 | N46: =In_GoO*N41 -> 1.7831975 | O46: =In_GoO*O41 -> 1.8206982 | P46: =In_GoO*P41 -> 1.8206982 | Q46: =In_GoO*Q41 -> 1.8206982 | ... FH46: =In_GoO*FH41 -> 3.792051
C47: BESS storage total cashflow, real 2025 (E: curve) | D47: EUR k/MW | E47: =INDEX(Case_BESS_Curve,1,$F12) -> DC 4h | J47: =INDEX(Stack_Data,MATCH($E47,Stack_Labels,0),MATCH(J$7,Stack_Years,0)) -> 0 | K47: =INDEX(Stack_Data,MATCH($E47,Stack_Labels,0),MATCH(K$7,Stack_Years,0)) -> 0 | L47: =INDEX(Stack_Data,MATCH($E47,Stack_Labels,0),MATCH(L$7,Stack_Years,0)) -> 0 | M47: =INDEX(Stack_Data,MATCH($E47,Stack_Labels,0),MATCH(M$7,Stack_Years,0)) -> 0 | N47: =INDEX(Stack_Data,MATCH($E47,Stack_Labels,0),MATCH(N$7,Stack_Years,0)) -> 0 | O47: =INDEX(Stack_Data,MATCH($E47,Stack_Labels,0),MATCH(O$7,Stack_Years,0)) -> 186.97508 | P47: =INDEX(Stack_Data,MATCH($E47,Stack_Labels,0),MATCH(P$7,Stack_Years,0)) -> 186.97508 | Q47: =INDEX(Stack_Data,MATCH($E47,Stack_Labels,0),MATCH(Q$7,Stack_Years,0)) -> 186.97508 | ... FH47: =INDEX(Stack_Data,MATCH($E47,Stack_Labels,0),MATCH(FH$7,Stack_Years,0)) -> 91.148957
C48: Stack kept with PV-only charging (E: curve) | D48: factor | E48: =$E47 -> DC 4h | J48: =INDEX(PVOnly_Data,MATCH($E48,PVOnly_Labels,0),MATCH(J$7,PVOnly_Years,0)) -> 1 | K48: =INDEX(PVOnly_Data,MATCH($E48,PVOnly_Labels,0),MATCH(K$7,PVOnly_Years,0)) -> 1 | L48: =INDEX(PVOnly_Data,MATCH($E48,PVOnly_Labels,0),MATCH(L$7,PVOnly_Years,0)) -> 1 | M48: =INDEX(PVOnly_Data,MATCH($E48,PVOnly_Labels,0),MATCH(M$7,PVOnly_Years,0)) -> 1 | N48: =INDEX(PVOnly_Data,MATCH($E48,PVOnly_Labels,0),MATCH(N$7,PVOnly_Years,0)) -> 1 | O48: =INDEX(PVOnly_Data,MATCH($E48,PVOnly_Labels,0),MATCH(O$7,PVOnly_Years,0)) -> 0.77913121 | P48: =INDEX(PVOnly_Data,MATCH($E48,PVOnly_Labels,0),MATCH(P$7,PVOnly_Years,0)) -> 0.77913121 | Q48: =INDEX(PVOnly_Data,MATCH($E48,PVOnly_Labels,0),MATCH(Q$7,PVOnly_Years,0)) -> 0.77913121 | ... FH48: =INDEX(PVOnly_Data,MATCH($E48,PVOnly_Labels,0),MATCH(FH$7,PVOnly_Years,0)) -> 0.91178898
C49: aFRR-down and FCR share of the stack (E: curve) | D49: factor | E49: =$E47 -> DC 4h | J49: =INDEX(DownCap_Data,MATCH($E49,DownCap_Labels,0),MATCH(J$7,DownCap_Years,0)) -> 0 | K49: =INDEX(DownCap_Data,MATCH($E49,DownCap_Labels,0),MATCH(K$7,DownCap_Years,0)) -> 0 | L49: =INDEX(DownCap_Data,MATCH($E49,DownCap_Labels,0),MATCH(L$7,DownCap_Years,0)) -> 0 | M49: =INDEX(DownCap_Data,MATCH($E49,DownCap_Labels,0),MATCH(M$7,DownCap_Years,0)) -> 0 | N49: =INDEX(DownCap_Data,MATCH($E49,DownCap_Labels,0),MATCH(N$7,DownCap_Years,0)) -> 0 | O49: =INDEX(DownCap_Data,MATCH($E49,DownCap_Labels,0),MATCH(O$7,DownCap_Years,0)) -> 0.16712104 | P49: =INDEX(DownCap_Data,MATCH($E49,DownCap_Labels,0),MATCH(P$7,DownCap_Years,0)) -> 0.16712104 | Q49: =INDEX(DownCap_Data,MATCH($E49,DownCap_Labels,0),MATCH(Q$7,DownCap_Years,0)) -> 0.16712104 | ... FH49: =INDEX(DownCap_Data,MATCH($E49,DownCap_Labels,0),MATCH(FH$7,DownCap_Years,0)) -> 0.13527975
C50: Stack kept without grid charging | D50: factor | J50: =MIN(1,J48+In_AFRR_Down_Share*J49) -> 1 | K50: =MIN(1,K48+In_AFRR_Down_Share*K49) -> 1 | L50: =MIN(1,L48+In_AFRR_Down_Share*L49) -> 1 | M50: =MIN(1,M48+In_AFRR_Down_Share*M49) -> 1 | N50: =MIN(1,N48+In_AFRR_Down_Share*N49) -> 1 | O50: =MIN(1,O48+In_AFRR_Down_Share*O49) -> 0.77913121 | P50: =MIN(1,P48+In_AFRR_Down_Share*P49) -> 0.77913121 | Q50: =MIN(1,Q48+In_AFRR_Down_Share*Q49) -> 0.77913121 | ... FH50: =MIN(1,FH48+In_AFRR_Down_Share*FH49) -> 0.91178898
C51: Grid charging allowed: import ÷ BESS MW (E) | D51: % | E51: =MIN(1,In_Grid_Import_MW/MAX(1,$E18)) -> 0
C52: BESS merchant revenue per MW-year, nominal (haircut, availability, charging) | D52: EUR k/MW | J52: =J47*J41*(1-In_BESS_Haircut)*(J50+(1-J50)*$E51) -> 0 | K52: =K47*K41*(1-In_BESS_Haircut)*(K50+(1-K50)*$E51) -> 0 | L52: =L47*L41*(1-In_BESS_Haircut)*(L50+(1-L50)*$E51) -> 0 | M52: =M47*M41*(1-In_BESS_Haircut)*(M50+(1-M50)*$E51) -> 0 | N52: =N47*N41*(1-In_BESS_Haircut)*(N50+(1-N50)*$E51) -> 0 | O52: =O47*O41*(1-In_BESS_Haircut)*(O50+(1-O50)*$E51) -> 151.56337 | P52: =P47*P41*(1-In_BESS_Haircut)*(P50+(1-P50)*$E51) -> 151.56337 | Q52: =Q47*Q41*(1-In_BESS_Haircut)*(Q50+(1-Q50)*$E51) -> 151.56337 | ... FH52: =FH47*FH41*(1-In_BESS_Haircut)*(FH50+(1-FH50)*$E51) -> 180.08692
C53: BESS repower year (E: used, F: repower year of the curve) | D53: year | E53: =IF(In_Fix_Augment=0,In_Augment_Year_v3,IF(In_Augment_Year>0,In_Augment_Year,$F53)) -> 2048 | F53: =INDEX(Block_Repower,MATCH($E47,Block_Names,0)) -> 2048
C54: BESS in service (0 from the repower year if not repowered) | D54: flag | J54: =1-(1-In_Repower)*(J$7>=$E53) -> 1 | K54: =1-(1-In_Repower)*(K$7>=$E53) -> 1 | L54: =1-(1-In_Repower)*(L$7>=$E53) -> 1 | M54: =1-(1-In_Repower)*(M$7>=$E53) -> 1 | N54: =1-(1-In_Repower)*(N$7>=$E53) -> 1 | O54: =1-(1-In_Repower)*(O$7>=$E53) -> 1 | P54: =1-(1-In_Repower)*(P$7>=$E53) -> 1 | Q54: =1-(1-In_Repower)*(Q$7>=$E53) -> 1 | ... FH54: =1-(1-In_Repower)*(FH$7>=$E53) -> 1
A56: x | C56: Offtake offers (case C; merchant tail after the tenor)
C57: Offer applies on this sheet (case table) | D57: flag | E57: =INDEX(Case_Offer,1,$F12) -> 0
C58: PV offer: column (E), fixed price (F: 1 = yes) | D58: # | E58: =MATCH(In_Offer_PV,OPV_Names,0) -> 2 | F58: =INDEX(OPV_Type,$E58) -> 1
C59: PV offer handling fee: share (E), floor (F) | D59: EUR/MWh | E59: =INDEX(OPV_Fee,$E58) -> 0 | F59: =INDEX(OPV_Fee_Min,$E58) -> 0
C60: PV offer: fee cap (E), fixed price (F) | D60: EUR/MWh | E60: =INDEX(OPV_Fee_Max,$E58) -> 0 | F60: =INDEX(OPV_Price,$E58) -> 43.96
C61: PV offer in force (E: start, F: end) | D61: factor | E61: =IF(INDEX(OPV_Start,$E58)>0,INDEX(OPV_Start,$E58),$F16+1) -> 46753 | F61: =EDATE($E61,INDEX(OPV_Tenor,$E58)*Months_In_Year)-1 -> 47848 | J61: =$E57*MAX(0,MIN($F61,J$4)-MAX($E61,J$3)+1)/J$5 -> 0 | K61: =$E57*MAX(0,MIN($F61,K$4)-MAX($E61,K$3)+1)/K$5 -> 0 | L61: =$E57*MAX(0,MIN($F61,L$4)-MAX($E61,L$3)+1)/L$5 -> 0 | M61: =$E57*MAX(0,MIN($F61,M$4)-MAX($E61,M$3)+1)/M$5 -> 0 | N61: =$E57*MAX(0,MIN($F61,N$4)-MAX($E61,N$3)+1)/N$5 -> 0 | O61: =$E57*MAX(0,MIN($F61,O$4)-MAX($E61,O$3)+1)/O$5 -> 0 | P61: =$E57*MAX(0,MIN($F61,P$4)-MAX($E61,P$3)+1)/P$5 -> 0 | Q61: =$E57*MAX(0,MIN($F61,Q$4)-MAX($E61,Q$3)+1)/Q$5 -> 0 | ... FH61: =$E57*MAX(0,MIN($F61,FH$4)-MAX($E61,FH$3)+1)/FH$5 -> 0
C62: PV offer handling fee | D62: EUR/MWh | J62: =MIN($E60,MAX($E59*J44,$F59)) -> 0 | K62: =MIN($E60,MAX($E59*K44,$F59)) -> 0 | L62: =MIN($E60,MAX($E59*L44,$F59)) -> 0 | M62: =MIN($E60,MAX($E59*M44,$F59)) -> 0 | N62: =MIN($E60,MAX($E59*N44,$F59)) -> 0 | O62: =MIN($E60,MAX($E59*O44,$F59)) -> 0 | P62: =MIN($E60,MAX($E59*P44,$F59)) -> 0 | Q62: =MIN($E60,MAX($E59*Q44,$F59)) -> 0 | ... FH62: =MIN($E60,MAX($E59*FH44,$F59)) -> 0
C63: PV price received on direct export (offer in force, else merchant) | D63: EUR/MWh | J63: =J44+J61*(IF($F58=1,$F60,J44-J62)-J44) -> 0 | K63: =K44+K61*(IF($F58=1,$F60,K44-K62)-K44) -> 0 | L63: =L44+L61*(IF($F58=1,$F60,L44-L62)-L44) -> 0 | M63: =M44+M61*(IF($F58=1,$F60,M44-M62)-M44) -> 0 | N63: =N44+N61*(IF($F58=1,$F60,N44-N62)-N44) -> 0 | O63: =O44+O61*(IF($F58=1,$F60,O44-O62)-O44) -> 111.79501 | P63: =P44+P61*(IF($F58=1,$F60,P44-P62)-P44) -> 111.79501 | Q63: =Q44+Q61*(IF($F58=1,$F60,Q44-Q62)-Q44) -> 111.79501 | ... FH63: =FH44+FH61*(IF($F58=1,$F60,FH44-FH62)-FH44) -> 122.61377
C64: BESS offer: column (E), fixed fee per MW-year, not scaled above the offer (F) | D64: EUR k/MW | E64: =MATCH(In_Offer_BESS,OB_Names,0) -> 3 | F64: =INDEX(OB_Fixed,$E64)*MIN(1,In_BESS_Hours/INDEX(OB_Hours,$E64)) -> 49.7
C65: BESS offer duration ≠ built duration (E: 1 = yes) | D65: flag | E65: =$E57*(INDEX(OB_Tenor,$E64)>0)*N(INDEX(OB_Hours,$E64)<>In_BESS_Hours) -> 0
C66: BESS offer: owner share (E), grid charge deducted (F) | D66: EUR k/MW | E66: =INDEX(OB_Share,$E64) -> 0 | F66: =INDEX(OB_Grid,$E64)*In_BESS_Grid_Charge -> 0
C67: BESS offer in force (E: start, F: end) | D67: factor | E67: =IF(INDEX(OB_Start,$E64)>0,INDEX(OB_Start,$E64),$F16+1) -> 46753 | F67: =EDATE($E67,INDEX(OB_Tenor,$E64)*Months_In_Year)-1 -> 47848 | J67: =$E57*MAX(0,MIN($F67,J$4)-MAX($E67,J$3)+1)/J$5 -> 0 | K67: =$E57*MAX(0,MIN($F67,K$4)-MAX($E67,K$3)+1)/K$5 -> 0 | L67: =$E57*MAX(0,MIN($F67,L$4)-MAX($E67,L$3)+1)/L$5 -> 0 | M67: =$E57*MAX(0,MIN($F67,M$4)-MAX($E67,M$3)+1)/M$5 -> 0 | N67: =$E57*MAX(0,MIN($F67,N$4)-MAX($E67,N$3)+1)/N$5 -> 0 | O67: =$E57*MAX(0,MIN($F67,O$4)-MAX($E67,O$3)+1)/O$5 -> 0 | P67: =$E57*MAX(0,MIN($F67,P$4)-MAX($E67,P$3)+1)/P$5 -> 0 | Q67: =$E57*MAX(0,MIN($F67,Q$4)-MAX($E67,Q$3)+1)/Q$5 -> 0 | ... FH67: =$E57*MAX(0,MIN($F67,FH$4)-MAX($E67,FH$3)+1)/FH$5 -> 0
C68: E.ON band table row this year (0 = none; E: bands apply) | D68: # | E68: =INDEX(OB_Bands,$E64) -> 0 | J68: =$E68*SUMIF(EB_Years,J$7,EB_Row) -> 0 | K68: =$E68*SUMIF(EB_Years,K$7,EB_Row) -> 0 | L68: =$E68*SUMIF(EB_Years,L$7,EB_Row) -> 0 | M68: =$E68*SUMIF(EB_Years,M$7,EB_Row) -> 0 | N68: =$E68*SUMIF(EB_Years,N$7,EB_Row) -> 0 | O68: =$E68*SUMIF(EB_Years,O$7,EB_Row) -> 0 | P68: =$E68*SUMIF(EB_Years,P$7,EB_Row) -> 0 | Q68: =$E68*SUMIF(EB_Years,Q$7,EB_Row) -> 0 | ... FH68: =$E68*SUMIF(EB_Years,FH$7,EB_Row) -> 0
C69: Band table row looked up | D69: # | J69: =MAX(1,J68) -> 1 | K69: =MAX(1,K68) -> 1 | L69: =MAX(1,L68) -> 1 | M69: =MAX(1,M68) -> 1 | N69: =MAX(1,N68) -> 1 | O69: =MAX(1,O68) -> 1 | P69: =MAX(1,P68) -> 1 | Q69: =MAX(1,Q68) -> 1 | ... FH69: =MAX(1,FH68) -> 1
C70: E.ON fee on the stack, by band | D70: EUR k/MW | J70: =(J68>0)*SUMPRODUCT((J52>INDEX(EB_LB,J69,0))*(J52-INDEX(EB_LB,J69,0)),INDEX(EB_dR,J69,0)) -> 0 | K70: =(K68>0)*SUMPRODUCT((K52>INDEX(EB_LB,K69,0))*(K52-INDEX(EB_LB,K69,0)),INDEX(EB_dR,K69,0)) -> 0 | L70: =(L68>0)*SUMPRODUCT((L52>INDEX(EB_LB,L69,0))*(L52-INDEX(EB_LB,L69,0)),INDEX(EB_dR,L69,0)) -> 0 | M70: =(M68>0)*SUMPRODUCT((M52>INDEX(EB_LB,M69,0))*(M52-INDEX(EB_LB,M69,0)),INDEX(EB_dR,M69,0)) -> 0 | N70: =(N68>0)*SUMPRODUCT((N52>INDEX(EB_LB,N69,0))*(N52-INDEX(EB_LB,N69,0)),INDEX(EB_dR,N69,0)) -> 0 | O70: =(O68>0)*SUMPRODUCT((O52>INDEX(EB_LB,O69,0))*(O52-INDEX(EB_LB,O69,0)),INDEX(EB_dR,O69,0)) -> 0 | P70: =(P68>0)*SUMPRODUCT((P52>INDEX(EB_LB,P69,0))*(P52-INDEX(EB_LB,P69,0)),INDEX(EB_dR,P69,0)) -> 0 | Q70: =(Q68>0)*SUMPRODUCT((Q52>INDEX(EB_LB,Q69,0))*(Q52-INDEX(EB_LB,Q69,0)),INDEX(EB_dR,Q69,0)) -> 0 | ... FH70: =(FH68>0)*SUMPRODUCT((FH52>INDEX(EB_LB,FH69,0))*(FH52-INDEX(EB_LB,FH69,0)),INDEX(EB_dR,FH69,0)) -> 0
C71: Guaranteed floor in band years | D71: EUR k/MW | J71: =(J68>0)*INDEX(EB_Floor,J69) -> 0 | K71: =(K68>0)*INDEX(EB_Floor,K69) -> 0 | L71: =(L68>0)*INDEX(EB_Floor,L69) -> 0 | M71: =(M68>0)*INDEX(EB_Floor,M69) -> 0 | N71: =(N68>0)*INDEX(EB_Floor,N69) -> 0 | O71: =(O68>0)*INDEX(EB_Floor,O69) -> 0 | P71: =(P68>0)*INDEX(EB_Floor,P69) -> 0 | Q71: =(Q68>0)*INDEX(EB_Floor,Q69) -> 0 | ... FH71: =(FH68>0)*INDEX(EB_Floor,FH69) -> 0
C72: Owner share of the stack above the fixed fee | D72: % | J72: =IF(J68>0,1,$E66) -> 0 | K72: =IF(K68>0,1,$E66) -> 0 | L72: =IF(L68>0,1,$E66) -> 0 | M72: =IF(M68>0,1,$E66) -> 0 | N72: =IF(N68>0,1,$E66) -> 0 | O72: =IF(O68>0,1,$E66) -> 0 | P72: =IF(P68>0,1,$E66) -> 0 | Q72: =IF(Q68>0,1,$E66) -> 0 | ... FH72: =IF(FH68>0,1,$E66) -> 0
C73: Owner BESS revenue per MW-year under the offer | D73: EUR k/MW | J73: =MAX(J71,$F64+J72*MAX(0,J52-$F66-$F64)-J70) -> 49.7 | K73: =MAX(K71,$F64+K72*MAX(0,K52-$F66-$F64)-K70) -> 49.7 | L73: =MAX(L71,$F64+L72*MAX(0,L52-$F66-$F64)-L70) -> 49.7 | M73: =MAX(M71,$F64+M72*MAX(0,M52-$F66-$F64)-M70) -> 49.7 | N73: =MAX(N71,$F64+N72*MAX(0,N52-$F66-$F64)-N70) -> 49.7 | O73: =MAX(O71,$F64+O72*MAX(0,O52-$F66-$F64)-O70) -> 49.7 | P73: =MAX(P71,$F64+P72*MAX(0,P52-$F66-$F64)-P70) -> 49.7 | Q73: =MAX(Q71,$F64+Q72*MAX(0,Q52-$F66-$F64)-Q70) -> 49.7 | ... FH73: =MAX(FH71,$F64+FH72*MAX(0,FH52-$F66-$F64)-FH70) -> 49.7
C74: BESS revenue per MW-year received | D74: EUR k/MW | J74: =J52+J67*(J73-J52) -> 0 | K74: =K52+K67*(K73-K52) -> 0 | L74: =L52+L67*(L73-L52) -> 0 | M74: =M52+M67*(M73-M52) -> 0 | N74: =N52+N67*(N73-N52) -> 0 | O74: =O52+O67*(O73-O52) -> 151.56337 | P74: =P52+P67*(P73-P52) -> 151.56337 | Q74: =Q52+Q67*(Q73-Q52) -> 151.56337 | ... FH74: =FH52+FH67*(FH73-FH52) -> 180.08692
A76: x | C76: Capacity and energy (annual balance; hourly limits inside Aurora's dispatch)
C77: PV generation after availability and degradation (E: first full year) | D77: MWh | E77: =SUMIF($J$7:$FH$7,YEAR($F16)+1,$J77:$FH77) -> 79028.166 | I77: =SUM(J77:FH77) -> 2636990.7 | J77: =$E13*$F14*In_PV_Avail*(1-In_Degradation)^J29*J28*J$6 -> 0 | K77: =$E13*$F14*In_PV_Avail*(1-In_Degradation)^K29*K28*K$6 -> 0 | L77: =$E13*$F14*In_PV_Avail*(1-In_Degradation)^L29*L28*L$6 -> 0 | M77: =$E13*$F14*In_PV_Avail*(1-In_Degradation)^M29*M28*M$6 -> 0 | N77: =$E13*$F14*In_PV_Avail*(1-In_Degradation)^N29*N28*N$6 -> 0 | O77: =$E13*$F14*In_PV_Avail*(1-In_Degradation)^O29*O28*O$6 -> 0 | P77: =$E13*$F14*In_PV_Avail*(1-In_Degradation)^P29*P28*P$6 -> 0 | Q77: =$E13*$F14*In_PV_Avail*(1-In_Degradation)^Q29*Q28*Q$6 -> 0 | ... FH77: =$E13*$F14*In_PV_Avail*(1-In_Degradation)^FH29*FH28*FH$6 -> 0
C78: Clipped (case table: v3 + fix 5 in A, DC-coupled 0 in B, C) | D78: MWh | I78: =SUM(J78:FH78) -> 0 | J78: =-J77*$E17 -> 0 | K78: =-K77*$E17 -> 0 | L78: =-L77*$E17 -> 0 | M78: =-M77*$E17 -> 0 | N78: =-N77*$E17 -> 0 | O78: =-O77*$E17 -> 0 | P78: =-P77*$E17 -> 0 | Q78: =-Q77*$E17 -> 0 | ... FH78: =-FH77*$E17 -> 0
C79: Aurora block: charge from PV per MW (E: curve) | D79: MWh | E79: =$E47 -> DC 4h | J79: =INDEX(ChargeRES_Data,MATCH($E79,ChargeRES_Labels,0),MATCH(J$7,ChargeRES_Years,0)) -> 0 | K79: =INDEX(ChargeRES_Data,MATCH($E79,ChargeRES_Labels,0),MATCH(K$7,ChargeRES_Years,0)) -> 0 | L79: =INDEX(ChargeRES_Data,MATCH($E79,ChargeRES_Labels,0),MATCH(L$7,ChargeRES_Years,0)) -> 0 | M79: =INDEX(ChargeRES_Data,MATCH($E79,ChargeRES_Labels,0),MATCH(M$7,ChargeRES_Years,0)) -> 0 | N79: =INDEX(ChargeRES_Data,MATCH($E79,ChargeRES_Labels,0),MATCH(N$7,ChargeRES_Years,0)) -> 0 | O79: =INDEX(ChargeRES_Data,MATCH($E79,ChargeRES_Labels,0),MATCH(O$7,ChargeRES_Years,0)) -> -992.69296 | P79: =INDEX(ChargeRES_Data,MATCH($E79,ChargeRES_Labels,0),MATCH(P$7,ChargeRES_Years,0)) -> -992.69296 | Q79: =INDEX(ChargeRES_Data,MATCH($E79,ChargeRES_Labels,0),MATCH(Q$7,ChargeRES_Years,0)) -> -992.69296 | ... FH79: =INDEX(ChargeRES_Data,MATCH($E79,ChargeRES_Labels,0),MATCH(FH$7,ChargeRES_Years,0)) -> -841.29448
C80: Aurora block: charge from the grid per MW | D80: MWh | E80: =$E47 -> DC 4h | J80: =INDEX(ChargeGrid_Data,MATCH($E80,ChargeGrid_Labels,0),MATCH(J$7,ChargeGrid_Years,0)) -> 0 | K80: =INDEX(ChargeGrid_Data,MATCH($E80,ChargeGrid_Labels,0),MATCH(K$7,ChargeGrid_Years,0)) -> 0 | L80: =INDEX(ChargeGrid_Data,MATCH($E80,ChargeGrid_Labels,0),MATCH(L$7,ChargeGrid_Years,0)) -> 0 | M80: =INDEX(ChargeGrid_Data,MATCH($E80,ChargeGrid_Labels,0),MATCH(M$7,ChargeGrid_Years,0)) -> 0 | N80: =INDEX(ChargeGrid_Data,MATCH($E80,ChargeGrid_Labels,0),MATCH(N$7,ChargeGrid_Years,0)) -> 0 | O80: =INDEX(ChargeGrid_Data,MATCH($E80,ChargeGrid_Labels,0),MATCH(O$7,ChargeGrid_Years,0)) -> -751.2864 | P80: =INDEX(ChargeGrid_Data,MATCH($E80,ChargeGrid_Labels,0),MATCH(P$7,ChargeGrid_Years,0)) -> -751.2864 | Q80: =INDEX(ChargeGrid_Data,MATCH($E80,ChargeGrid_Labels,0),MATCH(Q$7,ChargeGrid_Years,0)) -> -751.2864 | ... FH80: =INDEX(ChargeGrid_Data,MATCH($E80,ChargeGrid_Labels,0),MATCH(FH$7,ChargeGrid_Years,0)) -> -579.51105
C81: Aurora block: discharge per MW | D81: MWh | E81: =$E47 -> DC 4h | J81: =INDEX(Discharge_Data,MATCH($E81,Discharge_Labels,0),MATCH(J$7,Discharge_Years,0)) -> 0 | K81: =INDEX(Discharge_Data,MATCH($E81,Discharge_Labels,0),MATCH(K$7,Discharge_Years,0)) -> 0 | L81: =INDEX(Discharge_Data,MATCH($E81,Discharge_Labels,0),MATCH(L$7,Discharge_Years,0)) -> 0 | M81: =INDEX(Discharge_Data,MATCH($E81,Discharge_Labels,0),MATCH(M$7,Discharge_Years,0)) -> 0 | N81: =INDEX(Discharge_Data,MATCH($E81,Discharge_Labels,0),MATCH(N$7,Discharge_Years,0)) -> 0 | O81: =INDEX(Discharge_Data,MATCH($E81,Discharge_Labels,0),MATCH(O$7,Discharge_Years,0)) -> 1434.7848 | P81: =INDEX(Discharge_Data,MATCH($E81,Discharge_Labels,0),MATCH(P$7,Discharge_Years,0)) -> 1434.7848 | Q81: =INDEX(Discharge_Data,MATCH($E81,Discharge_Labels,0),MATCH(Q$7,Discharge_Years,0)) -> 1434.7848 | ... FH81: =INDEX(Discharge_Data,MATCH($E81,Discharge_Labels,0),MATCH(FH$7,Discharge_Years,0)) -> 1151.9674
C82: Aurora block: discharge per MW coverable by PV charging | D82: MWh | J82: =MIN(J81,-J79*In_BESS_RTE) -> 0 | K82: =MIN(K81,-K79*In_BESS_RTE) -> 0 | L82: =MIN(L81,-L79*In_BESS_RTE) -> 0 | M82: =MIN(M81,-M79*In_BESS_RTE) -> 0 | N82: =MIN(N81,-N79*In_BESS_RTE) -> 0 | O82: =MIN(O81,-O79*In_BESS_RTE) -> 853.71595 | P82: =MIN(P81,-P79*In_BESS_RTE) -> 853.71595 | Q82: =MIN(Q81,-Q79*In_BESS_RTE) -> 853.71595 | ... FH82: =MIN(FH81,-FH79*In_BESS_RTE) -> 723.51325
C83: PV energy sent to the BESS | D83: MWh | I83: =SUM(J83:FH83) -> 1572735.8 | J83: =MIN(J77+J78,-J79*$E18*J28*J$6*J54) -> 0 | K83: =MIN(K77+K78,-K79*$E18*K28*K$6*K54) -> 0 | L83: =MIN(L77+L78,-L79*$E18*L28*L$6*L54) -> 0 | M83: =MIN(M77+M78,-M79*$E18*M28*M$6*M54) -> 0 | N83: =MIN(N77+N78,-N79*$E18*N28*N$6*N54) -> 0 | O83: =MIN(O77+O78,-O79*$E18*O28*O$6*O54) -> 0 | P83: =MIN(P77+P78,-P79*$E18*P28*P$6*P54) -> 0 | Q83: =MIN(Q77+Q78,-Q79*$E18*Q28*Q$6*Q54) -> 0 | ... FH83: =MIN(FH77+FH78,-FH79*$E18*FH28*FH$6*FH54) -> 0
C84: PV energy exported directly | D84: MWh | I84: =SUM(J84:FH84) -> 1064254.9 | J84: =J77+J78-J83 -> 0 | K84: =K77+K78-K83 -> 0 | L84: =L77+L78-L83 -> 0 | M84: =M77+M78-M83 -> 0 | N84: =N77+N78-N83 -> 0 | O84: =O77+O78-O83 -> 0 | P84: =P77+P78-P83 -> 0 | Q84: =Q77+Q78-Q83 -> 0 | ... FH84: =FH77+FH78-FH83 -> 0
C85: BESS discharge (scaled to the charging allowed) | D85: MWh | I85: =SUM(J85:FH85) -> 1352552.8 | J85: =$E18*J28*J$6*J54*($E51*J81+(1-$E51)*J82) -> 0 | K85: =$E18*K28*K$6*K54*($E51*K81+(1-$E51)*K82) -> 0 | L85: =$E18*L28*L$6*L54*($E51*L81+(1-$E51)*L82) -> 0 | M85: =$E18*M28*M$6*M54*($E51*M81+(1-$E51)*M82) -> 0 | N85: =$E18*N28*N$6*N54*($E51*N81+(1-$E51)*N82) -> 0 | O85: =$E18*O28*O$6*O54*($E51*O81+(1-$E51)*O82) -> 0 | P85: =$E18*P28*P$6*P54*($E51*P81+(1-$E51)*P82) -> 0 | Q85: =$E18*Q28*Q$6*Q54*($E51*Q81+(1-$E51)*Q82) -> 0 | ... FH85: =$E18*FH28*FH$6*FH54*($E51*FH81+(1-$E51)*FH82) -> 0
C86: BESS charge from the grid (within the import allowed) | D86: MWh | I86: =SUM(J86:FH86) -> 0 | J86: =-J80*$E18*J28*J$6*J54*$E51 -> 0 | K86: =-K80*$E18*K28*K$6*K54*$E51 -> 0 | L86: =-L80*$E18*L28*L$6*L54*$E51 -> 0 | M86: =-M80*$E18*M28*M$6*M54*$E51 -> 0 | N86: =-N80*$E18*N28*N$6*N54*$E51 -> 0 | O86: =-O80*$E18*O28*O$6*O54*$E51 -> 0 | P86: =-P80*$E18*P28*P$6*P54*$E51 -> 0 | Q86: =-Q80*$E18*Q28*Q$6*Q54*$E51 -> 0 | ... FH86: =-FH80*$E18*FH28*FH$6*FH54*$E51 -> 0
C87: Energy exported (E: first full year) | D87: MWh | E87: =SUMIF($J$7:$FH$7,YEAR($F16)+1,$J87:$FH87) -> 71939.699 | I87: =SUM(J87:FH87) -> 2416807.7 | J87: =J84+J85 -> 0 | K87: =K84+K85 -> 0 | L87: =L84+L85 -> 0 | M87: =M84+M85 -> 0 | N87: =N84+N85 -> 0 | O87: =O84+O85 -> 0 | P87: =P84+P85 -> 0 | Q87: =Q84+Q85 -> 0 | ... FH87: =FH84+FH85 -> 0
A89: x | C89: Revenue, opex and EBITDA
C90: PV revenue: direct export and energy sent to the BESS (E: first full year) | D90: EUR k | E90: =SUMIF($J$7:$FH$7,YEAR($F16)+1,$J90:$FH90) -> 4759.4522 | I90: =SUM(J90:FH90) -> 160794.98 | J90: =(J84*J63+J83*J45)/Thousand -> 0 | K90: =(K84*K63+K83*K45)/Thousand -> 0 | L90: =(L84*L63+L83*L45)/Thousand -> 0 | M90: =(M84*M63+M83*M45)/Thousand -> 0 | N90: =(N84*N63+N83*N45)/Thousand -> 0 | O90: =(O84*O63+O83*O45)/Thousand -> 0 | P90: =(P84*P63+P83*P45)/Thousand -> 0 | Q90: =(Q84*Q63+Q83*Q45)/Thousand -> 0 | ... FH90: =(FH84*FH63+FH83*FH45)/Thousand -> 0
C91: Guarantee of origin revenue | D91: EUR k | I91: =SUM(J91:FH91) -> 6994.1883 | J91: =(J77+J78)*J46/Thousand -> 0 | K91: =(K77+K78)*K46/Thousand -> 0 | L91: =(L77+L78)*L46/Thousand -> 0 | M91: =(M77+M78)*M46/Thousand -> 0 | N91: =(N77+N78)*N46/Thousand -> 0 | O91: =(O77+O78)*O46/Thousand -> 0 | P91: =(P77+P78)*P46/Thousand -> 0 | Q91: =(Q77+Q78)*Q46/Thousand -> 0 | ... FH91: =(FH77+FH78)*FH46/Thousand -> 0
C92: BESS revenue (E: first full year) | D92: EUR k | E92: =SUMIF($J$7:$FH$7,YEAR($F16)+1,$J92:$FH92) -> 6010.5746 | I92: =SUM(J92:FH92) -> 237435.68 | J92: =J74*$E18*J28*J$6*J54 -> 0 | K92: =K74*$E18*K28*K$6*K54 -> 0 | L92: =L74*$E18*L28*L$6*L54 -> 0 | M92: =M74*$E18*M28*M$6*M54 -> 0 | N92: =N74*$E18*N28*N$6*N54 -> 0 | O92: =O74*$E18*O28*O$6*O54 -> 0 | P92: =P74*$E18*P28*P$6*P54 -> 0 | Q92: =Q74*$E18*Q28*Q$6*Q54 -> 0 | ... FH92: =FH74*$E18*FH28*FH$6*FH54 -> 0
C93: Revenue (E: first full year) | D93: EUR k | E93: =SUMIF($J$7:$FH$7,YEAR($F16)+1,$J93:$FH93) -> 10919.808 | I93: =SUM(J93:FH93) -> 405224.85 | J93: =J90+J91+J92 -> 0 | K93: =K90+K91+K92 -> 0 | L93: =L90+L91+L92 -> 0 | M93: =M90+M91+M92 -> 0 | N93: =N90+N91+N92 -> 0 | O93: =O90+O91+O92 -> 0 | P93: =P90+P91+P92 -> 0 | Q93: =Q90+Q91+Q92 -> 0 | ... FH93: =FH90+FH91+FH92 -> 0
C94: Of which contracted (fixed-price PV offer, BESS fixed fee) | D94: EUR k | I94: =SUM(J94:FH94) -> 0 | J94: =J61*$F58*J84*J63/Thousand+J67*$F64*$E18*J28*J$6*J54 -> 0 | K94: =K61*$F58*K84*K63/Thousand+K67*$F64*$E18*K28*K$6*K54 -> 0 | L94: =L61*$F58*L84*L63/Thousand+L67*$F64*$E18*L28*L$6*L54 -> 0 | M94: =M61*$F58*M84*M63/Thousand+M67*$F64*$E18*M28*M$6*M54 -> 0 | N94: =N61*$F58*N84*N63/Thousand+N67*$F64*$E18*N28*N$6*N54 -> 0 | O94: =O61*$F58*O84*O63/Thousand+O67*$F64*$E18*O28*O$6*O54 -> 0 | P94: =P61*$F58*P84*P63/Thousand+P67*$F64*$E18*P28*P$6*P54 -> 0 | Q94: =Q61*$F58*Q84*Q63/Thousand+Q67*$F64*$E18*Q28*Q$6*Q54 -> 0 | ... FH94: =FH61*$F58*FH84*FH63/Thousand+FH67*$F64*$E18*FH28*FH$6*FH54 -> 0
C95: O&M and MV cable O&M | D95: EUR k | I95: =SUM(J95:FH95) -> -67151.408 | J95: =-(In_OM+In_Cable_OM)*$E13*J41*(1+In_Opex_Adj)*J28*J$6 -> 0 | K95: =-(In_OM+In_Cable_OM)*$E13*K41*(1+In_Opex_Adj)*K28*K$6 -> 0 | L95: =-(In_OM+In_Cable_OM)*$E13*L41*(1+In_Opex_Adj)*L28*L$6 -> 0 | M95: =-(In_OM+In_Cable_OM)*$E13*M41*(1+In_Opex_Adj)*M28*M$6 -> 0 | N95: =-(In_OM+In_Cable_OM)*$E13*N41*(1+In_Opex_Adj)*N28*N$6 -> 0 | O95: =-(In_OM+In_Cable_OM)*$E13*O41*(1+In_Opex_Adj)*O28*O$6 -> 0 | P95: =-(In_OM+In_Cable_OM)*$E13*P41*(1+In_Opex_Adj)*P28*P$6 -> 0 | Q95: =-(In_OM+In_Cable_OM)*$E13*Q41*(1+In_Opex_Adj)*Q28*Q$6 -> 0 | ... FH95: =-(In_OM+In_Cable_OM)*$E13*FH41*(1+In_Opex_Adj)*FH28*FH$6 -> 0
C96: Balancing | D96: EUR k | I96: =SUM(J96:FH96) -> -19983.395 | J96: =-In_Balancing*(J77+J78)/Thousand*J41*(1+In_Opex_Adj) -> 0 | K96: =-In_Balancing*(K77+K78)/Thousand*K41*(1+In_Opex_Adj) -> 0 | L96: =-In_Balancing*(L77+L78)/Thousand*L41*(1+In_Opex_Adj) -> 0 | M96: =-In_Balancing*(M77+M78)/Thousand*M41*(1+In_Opex_Adj) -> 0 | N96: =-In_Balancing*(N77+N78)/Thousand*N41*(1+In_Opex_Adj) -> 0 | O96: =-In_Balancing*(O77+O78)/Thousand*O41*(1+In_Opex_Adj) -> 0 | P96: =-In_Balancing*(P77+P78)/Thousand*P41*(1+In_Opex_Adj) -> 0 | Q96: =-In_Balancing*(Q77+Q78)/Thousand*Q41*(1+In_Opex_Adj) -> 0 | ... FH96: =-In_Balancing*(FH77+FH78)/Thousand*FH41*(1+In_Opex_Adj) -> 0
C97: Land lease | D97: EUR k | I97: =SUM(J97:FH97) -> -5126.5509 | J97: =-In_Lease*J41*(1+In_Opex_Adj)*J28*J$6 -> 0 | K97: =-In_Lease*K41*(1+In_Opex_Adj)*K28*K$6 -> 0 | L97: =-In_Lease*L41*(1+In_Opex_Adj)*L28*L$6 -> 0 | M97: =-In_Lease*M41*(1+In_Opex_Adj)*M28*M$6 -> 0 | N97: =-In_Lease*N41*(1+In_Opex_Adj)*N28*N$6 -> 0 | O97: =-In_Lease*O41*(1+In_Opex_Adj)*O28*O$6 -> 0 | P97: =-In_Lease*P41*(1+In_Opex_Adj)*P28*P$6 -> 0 | Q97: =-In_Lease*Q41*(1+In_Opex_Adj)*Q28*Q$6 -> 0 | ... FH97: =-In_Lease*FH41*(1+In_Opex_Adj)*FH28*FH$6 -> 0
C98: BESS fixed opex | D98: EUR k | I98: =SUM(J98:FH98) -> -82238.42 | J98: =-In_BESS_Opex*$E18*J41*(1+In_Opex_Adj)*J28*J$6*J54 -> 0 | K98: =-In_BESS_Opex*$E18*K41*(1+In_Opex_Adj)*K28*K$6*K54 -> 0 | L98: =-In_BESS_Opex*$E18*L41*(1+In_Opex_Adj)*L28*L$6*L54 -> 0 | M98: =-In_BESS_Opex*$E18*M41*(1+In_Opex_Adj)*M28*M$6*M54 -> 0 | N98: =-In_BESS_Opex*$E18*N41*(1+In_Opex_Adj)*N28*N$6*N54 -> 0 | O98: =-In_BESS_Opex*$E18*O41*(1+In_Opex_Adj)*O28*O$6*O54 -> 0 | P98: =-In_BESS_Opex*$E18*P41*(1+In_Opex_Adj)*P28*P$6*P54 -> 0 | Q98: =-In_BESS_Opex*$E18*Q41*(1+In_Opex_Adj)*Q28*Q$6*Q54 -> 0 | ... FH98: =-In_BESS_Opex*$E18*FH41*(1+In_Opex_Adj)*FH28*FH$6*FH54 -> 0
C99: Route-to-market and offer fees | D99: EUR k | I99: =SUM(J99:FH99) -> 0 | J99: =-In_RTM*J90-INDEX(OPV_Cost,$E58)*J61*J$6 -> 0 | K99: =-In_RTM*K90-INDEX(OPV_Cost,$E58)*K61*K$6 -> 0 | L99: =-In_RTM*L90-INDEX(OPV_Cost,$E58)*L61*L$6 -> 0 | M99: =-In_RTM*M90-INDEX(OPV_Cost,$E58)*M61*M$6 -> 0 | N99: =-In_RTM*N90-INDEX(OPV_Cost,$E58)*N61*N$6 -> 0 | O99: =-In_RTM*O90-INDEX(OPV_Cost,$E58)*O61*O$6 -> 0 | P99: =-In_RTM*P90-INDEX(OPV_Cost,$E58)*P61*P$6 -> 0 | Q99: =-In_RTM*Q90-INDEX(OPV_Cost,$E58)*Q61*Q$6 -> 0 | ... FH99: =-In_RTM*FH90-INDEX(OPV_Cost,$E58)*FH61*FH$6 -> 0
C100: HIPA and innovation contribution | D100: EUR k | I100: =SUM(J100:FH100) -> -9320.1716 | J100: =-J93*(In_HIPA+In_Innovation) -> 0 | K100: =-K93*(In_HIPA+In_Innovation) -> 0 | L100: =-L93*(In_HIPA+In_Innovation) -> 0 | M100: =-M93*(In_HIPA+In_Innovation) -> 0 | N100: =-N93*(In_HIPA+In_Innovation) -> 0 | O100: =-O93*(In_HIPA+In_Innovation) -> 0 | P100: =-P93*(In_HIPA+In_Innovation) -> 0 | Q100: =-Q93*(In_HIPA+In_Innovation) -> 0 | ... FH100: =-FH93*(In_HIPA+In_Innovation) -> 0
C101: EBITDA (E: first full year) | D101: EUR k | E101: =SUMIF($J$7:$FH$7,YEAR($F16)+1,$J101:$FH101) -> 7106.991 | I101: =SUM(J101:FH101) -> 221404.91 | J101: =J93+SUM(J95:J100) -> 0 | K101: =K93+SUM(K95:K100) -> 0 | L101: =L93+SUM(L95:L100) -> 0 | M101: =M93+SUM(M95:M100) -> 0 | N101: =N93+SUM(N95:N100) -> 0 | O101: =O93+SUM(O95:O100) -> 0 | P101: =P93+SUM(P95:P100) -> 0 | Q101: =Q93+SUM(Q95:Q100) -> 0 | ... FH101: =FH93+SUM(FH95:FH100) -> 0
A103: x | C103: Development, early works, deposits and guarantees (E: to the exit, F: to COD)
C104: FEP SPV acquisition price / connection rights | D104: EUR k | I104: =SUM(J104:FH104) -> -549 | J104: =-In_SPV_Price*J19 -> -549 | K104: =-In_SPV_Price*K19 -> 0 | L104: =-In_SPV_Price*L19 -> 0 | M104: =-In_SPV_Price*M19 -> 0 | N104: =-In_SPV_Price*N19 -> 0 | O104: =-In_SPV_Price*O19 -> 0 | P104: =-In_SPV_Price*P19 -> 0 | Q104: =-In_SPV_Price*Q19 -> 0 | ... FH104: =-In_SPV_Price*FH19 -> 0
C105: Transaction costs (FEP) | D105: EUR k | I105: =SUM(J105:FH105) -> -200 | J105: =-In_Transaction*J19 -> -200 | K105: =-In_Transaction*K19 -> 0 | L105: =-In_Transaction*L19 -> 0 | M105: =-In_Transaction*M19 -> 0 | N105: =-In_Transaction*N19 -> 0 | O105: =-In_Transaction*O19 -> 0 | P105: =-In_Transaction*P19 -> 0 | Q105: =-In_Transaction*Q19 -> 0 | ... FH105: =-In_Transaction*FH19 -> 0
C106: DSA loan to PSH | D106: EUR k | I106: =SUM(J106:FH106) -> -945 | J106: =-In_DSA_Per_MWp*$E13*J30 -> -73.977273 | K106: =-In_DSA_Per_MWp*$E13*K30 -> -214.77273 | L106: =-In_DSA_Per_MWp*$E13*L30 -> -217.15909 | M106: =-In_DSA_Per_MWp*$E13*M30 -> -219.54545 | N106: =-In_DSA_Per_MWp*$E13*N30 -> -219.54545 | O106: =-In_DSA_Per_MWp*$E13*O30 -> 0 | P106: =-In_DSA_Per_MWp*$E13*P30 -> 0 | Q106: =-In_DSA_Per_MWp*$E13*Q30 -> 0 | ... FH106: =-In_DSA_Per_MWp*$E13*FH30 -> 0
C107: Early works paid in development (lines in scope) | D107: EUR k | E107: =SUMIF($J$3:$FH$3,"<="&$E20,$J107:$FH107) -> -785 | I107: =SUM(J107:FH107) -> -785 | J107: =-SUMIFS(EW_Keur,EW_Date,">="&J$3,EW_Date,"<="&J$4,EW_Rank,"<="&In_Milestones_Scope) -> -150 | K107: =-SUMIFS(EW_Keur,EW_Date,">="&K$3,EW_Date,"<="&K$4,EW_Rank,"<="&In_Milestones_Scope) -> -175 | L107: =-SUMIFS(EW_Keur,EW_Date,">="&L$3,EW_Date,"<="&L$4,EW_Rank,"<="&In_Milestones_Scope) -> -460 | M107: =-SUMIFS(EW_Keur,EW_Date,">="&M$3,EW_Date,"<="&M$4,EW_Rank,"<="&In_Milestones_Scope) -> 0 | N107: =-SUMIFS(EW_Keur,EW_Date,">="&N$3,EW_Date,"<="&N$4,EW_Rank,"<="&In_Milestones_Scope) -> 0 | O107: =-SUMIFS(EW_Keur,EW_Date,">="&O$3,EW_Date,"<="&O$4,EW_Rank,"<="&In_Milestones_Scope) -> 0 | P107: =-SUMIFS(EW_Keur,EW_Date,">="&P$3,EW_Date,"<="&P$4,EW_Rank,"<="&In_Milestones_Scope) -> 0 | Q107: =-SUMIFS(EW_Keur,EW_Date,">="&Q$3,EW_Date,"<="&Q$4,EW_Rank,"<="&In_Milestones_Scope) -> 0 | ... FH107: =-SUMIFS(EW_Keur,EW_Date,">="&FH$3,EW_Date,"<="&FH$4,EW_Rank,"<="&In_Milestones_Scope) -> 0
...

Sheet Calc_3
A1: 3 | C1: Bid number
B2: =Dashboard!$C$3&" – Calculations – "&INDEX(Bid_Labels,1,$A$1) -> Project Zalahaláp – Calculations – C Offer
C3: Period start | D3: date | J3: =I$4+1 -> 45931 | K3: =J$4+1 -> 46023 | L3: =K$4+1 -> 46113 | M3: =L$4+1 -> 46204 | N3: =M$4+1 -> 46296 | O3: =N$4+1 -> 46388 | P3: =O$4+1 -> 46478 | Q3: =P$4+1 -> 46569 | ... FH3: =FG$4+1 -> 59993
C4: Period end | D4: date | I4: =In_Model_Start-1 -> 45930 | J4: =EOMONTH(J$3,Months_Per_Period-1) -> 46022 | K4: =EOMONTH(K$3,Months_Per_Period-1) -> 46112 | L4: =EOMONTH(L$3,Months_Per_Period-1) -> 46203 | M4: =EOMONTH(M$3,Months_Per_Period-1) -> 46295 | N4: =EOMONTH(N$3,Months_Per_Period-1) -> 46387 | O4: =EOMONTH(O$3,Months_Per_Period-1) -> 46477 | P4: =EOMONTH(P$3,Months_Per_Period-1) -> 46568 | Q4: =EOMONTH(Q$3,Months_Per_Period-1) -> 46660 | ... FH4: =EOMONTH(FH$3,Months_Per_Period-1) -> 60083
C5: Days in period | D5: days | J5: =J$4-J$3+1 -> 92 | K5: =K$4-K$3+1 -> 90 | L5: =L$4-L$3+1 -> 91 | M5: =M$4-M$3+1 -> 92 | N5: =N$4-N$3+1 -> 92 | O5: =O$4-O$3+1 -> 90 | P5: =P$4-P$3+1 -> 91 | Q5: =Q$4-Q$3+1 -> 92 | ... FH5: =FH$4-FH$3+1 -> 91
C6: Year fraction | D6: factor | J6: =J$5/Days_In_Year -> 0.25205479 | K6: =K$5/Days_In_Year -> 0.24657534 | L6: =L$5/Days_In_Year -> 0.24931507 | M6: =M$5/Days_In_Year -> 0.25205479 | N6: =N$5/Days_In_Year -> 0.25205479 | O6: =O$5/Days_In_Year -> 0.24657534 | P6: =P$5/Days_In_Year -> 0.24931507 | Q6: =Q$5/Days_In_Year -> 0.25205479 | ... FH6: =FH$5/Days_In_Year -> 0.24931507
C7: Year | D7: year | J7: =YEAR(J$4) -> 2025 | K7: =YEAR(K$4) -> 2026 | L7: =YEAR(L$4) -> 2026 | M7: =YEAR(M$4) -> 2026 | N7: =YEAR(N$4) -> 2026 | O7: =YEAR(O$4) -> 2027 | P7: =YEAR(P$4) -> 2027 | Q7: =YEAR(Q$4) -> 2027 | ... FH7: =YEAR(FH$4) -> 2064
C8: Period counter | D8: # | J8: =I$8+1 -> 1 | K8: =J$8+1 -> 2 | L8: =K$8+1 -> 3 | M8: =L$8+1 -> 4 | N8: =M$8+1 -> 5 | O8: =N$8+1 -> 6 | P8: =O$8+1 -> 7 | Q8: =P$8+1 -> 8 | ... FH8: =FG$8+1 -> 155
A11: x | C11: Case and timing
C12: Revenue case (E: lever, F: column of the case table) | D12: text | E12: =INDEX(Dash_Case,1,$A$1) -> C | F12: =MATCH($E12,Case_Names,0) -> 3
C13: PV capacity (E: MWp) and grid export (F: MVA) | D13: MW | E13: =INDEX(Case_MWp,1,$F12) -> 63 | F13: =INDEX(Case_MVA,1,$F12) -> 49.9
C14: Specific yield (E: case, F: after the yield set) | D14: MWh/MWp | E14: =INDEX(Case_Yield,1,$F12) -> 1265 | F14: =$E14*(1+In_Yield_Adj) -> 1265
C15: RtB (E) and RtB exit (F) | D15: date | E15: =INDEX(Case_RtB,1,$F12) -> 46387 | F15: =INDEX(Case_Exit,1,$F12) -> 46477
C16: NTP (E) and COD (F) | D16: date | E16: =INDEX(Case_NTP,1,$F12) -> 46568 | F16: =EOMONTH(INDEX(Case_COD,1,$F12),In_COD_Delay) -> 46843
C17: Clipping, share of DC energy (case table) | D17: % | E17: =INDEX(Case_Clip,1,$F12) -> 0
C18: BESS built (E: MW, F: MWh) | D18: MW | E18: =In_BESS_MW*In_BESS_On -> 50 | F18: =$E18*In_BESS_Hours -> 200
C19: Acquisition and JV start | D19: flag | E19: =In_Acq -> 45991 | I19: =SUM(J19:FH19) -> 1 | J19: =N(AND(J$3<=$E19,J$4>=$E19)) -> 1 | K19: =N(AND(K$3<=$E19,K$4>=$E19)) -> 0 | L19: =N(AND(L$3<=$E19,L$4>=$E19)) -> 0 | M19: =N(AND(M$3<=$E19,M$4>=$E19)) -> 0 | N19: =N(AND(N$3<=$E19,N$4>=$E19)) -> 0 | O19: =N(AND(O$3<=$E19,O$4>=$E19)) -> 0 | P19: =N(AND(P$3<=$E19,P$4>=$E19)) -> 0 | Q19: =N(AND(Q$3<=$E19,Q$4>=$E19)) -> 0 | ... FH19: =N(AND(FH$3<=$E19,FH$4>=$E19)) -> 0
C20: RtB exit (sale closing) | D20: flag | E20: =$F15 -> 46477 | I20: =SUM(J20:FH20) -> 1 | J20: =N(AND(J$3<=$E20,J$4>=$E20)) -> 0 | K20: =N(AND(K$3<=$E20,K$4>=$E20)) -> 0 | L20: =N(AND(L$3<=$E20,L$4>=$E20)) -> 0 | M20: =N(AND(M$3<=$E20,M$4>=$E20)) -> 0 | N20: =N(AND(N$3<=$E20,N$4>=$E20)) -> 0 | O20: =N(AND(O$3<=$E20,O$4>=$E20)) -> 1 | P20: =N(AND(P$3<=$E20,P$4>=$E20)) -> 0 | Q20: =N(AND(Q$3<=$E20,Q$4>=$E20)) -> 0 | ... FH20: =N(AND(FH$3<=$E20,FH$4>=$E20)) -> 0
C21: NTP | D21: flag | E21: =$E16 -> 46568 | I21: =SUM(J21:FH21) -> 1 | J21: =N(AND(J$3<=$E21,J$4>=$E21)) -> 0 | K21: =N(AND(K$3<=$E21,K$4>=$E21)) -> 0 | L21: =N(AND(L$3<=$E21,L$4>=$E21)) -> 0 | M21: =N(AND(M$3<=$E21,M$4>=$E21)) -> 0 | N21: =N(AND(N$3<=$E21,N$4>=$E21)) -> 0 | O21: =N(AND(O$3<=$E21,O$4>=$E21)) -> 0 | P21: =N(AND(P$3<=$E21,P$4>=$E21)) -> 1 | Q21: =N(AND(Q$3<=$E21,Q$4>=$E21)) -> 0 | ... FH21: =N(AND(FH$3<=$E21,FH$4>=$E21)) -> 0
C22: COD | D22: flag | E22: =$F16 -> 46843 | I22: =SUM(J22:FH22) -> 1 | J22: =N(AND(J$3<=$E22,J$4>=$E22)) -> 0 | K22: =N(AND(K$3<=$E22,K$4>=$E22)) -> 0 | L22: =N(AND(L$3<=$E22,L$4>=$E22)) -> 0 | M22: =N(AND(M$3<=$E22,M$4>=$E22)) -> 0 | N22: =N(AND(N$3<=$E22,N$4>=$E22)) -> 0 | O22: =N(AND(O$3<=$E22,O$4>=$E22)) -> 0 | P22: =N(AND(P$3<=$E22,P$4>=$E22)) -> 0 | Q22: =N(AND(Q$3<=$E22,Q$4>=$E22)) -> 0 | ... FH22: =N(AND(FH$3<=$E22,FH$4>=$E22)) -> 0
C23: Exit column on the timeline (buyer view at RtB) | D23: # | E23: =MATCH($E20-1,$J$4:$FH$4,1)+1 -> 6
C24: COD column on the timeline (buyer view at COD) | D24: # | E24: =MATCH($E22,$J$4:$FH$4,0) -> 10
C25: After the exit period | D25: flag | J25: =N(J$3>$E20) -> 0 | K25: =N(K$3>$E20) -> 0 | L25: =N(L$3>$E20) -> 0 | M25: =N(M$3>$E20) -> 0 | N25: =N(N$3>$E20) -> 0 | O25: =N(O$3>$E20) -> 0 | P25: =N(P$3>$E20) -> 1 | Q25: =N(Q$3>$E20) -> 1 | ... FH25: =N(FH$3>$E20) -> 1
C26: After COD | D26: flag | J26: =N(J$4>$E22) -> 0 | K26: =N(K$4>$E22) -> 0 | L26: =N(L$4>$E22) -> 0 | M26: =N(M$4>$E22) -> 0 | N26: =N(N$4>$E22) -> 0 | O26: =N(O$4>$E22) -> 0 | P26: =N(P$4>$E22) -> 0 | Q26: =N(Q$4>$E22) -> 0 | ... FH26: =N(FH$4>$E22) -> 1
C27: Construction spread (NTP → COD) | D27: factor | E27: =$E16+1 -> 46569 | F27: =$F16 -> 46843 | I27: =SUM(J27:FH27) -> 1 | J27: =MAX(0,MIN($F27,J$4)-MAX($E27,J$3)+1)/($F27-$E27+1) -> 0 | K27: =MAX(0,MIN($F27,K$4)-MAX($E27,K$3)+1)/($F27-$E27+1) -> 0 | L27: =MAX(0,MIN($F27,L$4)-MAX($E27,L$3)+1)/($F27-$E27+1) -> 0 | M27: =MAX(0,MIN($F27,M$4)-MAX($E27,M$3)+1)/($F27-$E27+1) -> 0 | N27: =MAX(0,MIN($F27,N$4)-MAX($E27,N$3)+1)/($F27-$E27+1) -> 0 | O27: =MAX(0,MIN($F27,O$4)-MAX($E27,O$3)+1)/($F27-$E27+1) -> 0 | P27: =MAX(0,MIN($F27,P$4)-MAX($E27,P$3)+1)/($F27-$E27+1) -> 0 | Q27: =MAX(0,MIN($F27,Q$4)-MAX($E27,Q$3)+1)/($F27-$E27+1) -> 0.33454545 | ... FH27: =MAX(0,MIN($F27,FH$4)-MAX($E27,FH$3)+1)/($F27-$E27+1) -> 0
C28: Operations (COD → end of life) | D28: flag | E28: =$F16+1 -> 46844 | F28: =EDATE($F16,In_Life*Months_In_Year) -> 59626 | J28: =MAX(0,(MIN($F28,J$4)-MAX($E28,J$3)+1)/J$5) -> 0 | K28: =MAX(0,(MIN($F28,K$4)-MAX($E28,K$3)+1)/K$5) -> 0 | L28: =MAX(0,(MIN($F28,L$4)-MAX($E28,L$3)+1)/L$5) -> 0 | M28: =MAX(0,(MIN($F28,M$4)-MAX($E28,M$3)+1)/M$5) -> 0 | N28: =MAX(0,(MIN($F28,N$4)-MAX($E28,N$3)+1)/N$5) -> 0 | O28: =MAX(0,(MIN($F28,O$4)-MAX($E28,O$3)+1)/O$5) -> 0 | P28: =MAX(0,(MIN($F28,P$4)-MAX($E28,P$3)+1)/P$5) -> 0 | Q28: =MAX(0,(MIN($F28,Q$4)-MAX($E28,Q$3)+1)/Q$5) -> 0 | ... FH28: =MAX(0,(MIN($F28,FH$4)-MAX($E28,FH$3)+1)/FH$5) -> 0
C29: Operating years elapsed at the period start | D29: years | J29: =MAX(0,J$3-1-$F16)/Days_In_Year -> 0 | K29: =MAX(0,K$3-1-$F16)/Days_In_Year -> 0 | L29: =MAX(0,L$3-1-$F16)/Days_In_Year -> 0 | M29: =MAX(0,M$3-1-$F16)/Days_In_Year -> 0 | N29: =MAX(0,N$3-1-$F16)/Days_In_Year -> 0 | O29: =MAX(0,O$3-1-$F16)/Days_In_Year -> 0 | P29: =MAX(0,P$3-1-$F16)/Days_In_Year -> 0 | Q29: =MAX(0,Q$3-1-$F16)/Days_In_Year -> 0 | ... FH29: =MAX(0,FH$3-1-$F16)/Days_In_Year -> 36.024658
C30: DSA loan spread (acquisition → RtB) | D30: factor | E30: =In_Acq+1 -> 45992 | F30: =$E15 -> 46387 | I30: =SUM(J30:FH30) -> 1 | J30: =MAX(0,MIN($F30,J$4)-MAX($E30,J$3)+1)/($F30-$E30+1) -> 0.078282828 | K30: =MAX(0,MIN($F30,K$4)-MAX($E30,K$3)+1)/($F30-$E30+1) -> 0.22727273 | L30: =MAX(0,MIN($F30,L$4)-MAX($E30,L$3)+1)/($F30-$E30+1) -> 0.22979798 | M30: =MAX(0,MIN($F30,M$4)-MAX($E30,M$3)+1)/($F30-$E30+1) -> 0.23232323 | N30: =MAX(0,MIN($F30,N$4)-MAX($E30,N$3)+1)/($F30-$E30+1) -> 0.23232323 | O30: =MAX(0,MIN($F30,O$4)-MAX($E30,O$3)+1)/($F30-$E30+1) -> 0 | P30: =MAX(0,MIN($F30,P$4)-MAX($E30,P$3)+1)/($F30-$E30+1) -> 0 | Q30: =MAX(0,MIN($F30,Q$4)-MAX($E30,Q$3)+1)/($F30-$E30+1) -> 0 | ... FH30: =MAX(0,MIN($F30,FH$4)-MAX($E30,FH$3)+1)/($F30-$E30+1) -> 0
C31: Pre-RtB development cost spread | D31: factor | E31: =EOMONTH(In_PreRtB_First,-1)+1 -> 46296 | F31: =In_PreRtB_Last -> 46477 | I31: =SUM(J31:FH31) -> 1 | J31: =MAX(0,MIN($F31,J$4)-MAX($E31,J$3)+1)/($F31-$E31+1) -> 0 | K31: =MAX(0,MIN($F31,K$4)-MAX($E31,K$3)+1)/($F31-$E31+1) -> 0 | L31: =MAX(0,MIN($F31,L$4)-MAX($E31,L$3)+1)/($F31-$E31+1) -> 0 | M31: =MAX(0,MIN($F31,M$4)-MAX($E31,M$3)+1)/($F31-$E31+1) -> 0 | N31: =MAX(0,MIN($F31,N$4)-MAX($E31,N$3)+1)/($F31-$E31+1) -> 0.50549451 | O31: =MAX(0,MIN($F31,O$4)-MAX($E31,O$3)+1)/($F31-$E31+1) -> 0.49450549 | P31: =MAX(0,MIN($F31,P$4)-MAX($E31,P$3)+1)/($F31-$E31+1) -> 0 | Q31: =MAX(0,MIN($F31,Q$4)-MAX($E31,Q$3)+1)/($F31-$E31+1) -> 0 | ... FH31: =MAX(0,MIN($F31,FH$4)-MAX($E31,FH$3)+1)/($F31-$E31+1) -> 0
C32: Debt repayment period | D32: flag | E32: =$F16+1 -> 46844 | F32: =EDATE($F16,In_Debt_Tenor*Months_In_Year) -> 52321 | J32: =MAX(0,(MIN($F32,J$4)-MAX($E32,J$3)+1)/J$5) -> 0 | K32: =MAX(0,(MIN($F32,K$4)-MAX($E32,K$3)+1)/K$5) -> 0 | L32: =MAX(0,(MIN($F32,L$4)-MAX($E32,L$3)+1)/L$5) -> 0 | M32: =MAX(0,(MIN($F32,M$4)-MAX($E32,M$3)+1)/M$5) -> 0 | N32: =MAX(0,(MIN($F32,N$4)-MAX($E32,N$3)+1)/N$5) -> 0 | O32: =MAX(0,(MIN($F32,O$4)-MAX($E32,O$3)+1)/O$5) -> 0 | P32: =MAX(0,(MIN($F32,P$4)-MAX($E32,P$3)+1)/P$5) -> 0 | Q32: =MAX(0,(MIN($F32,Q$4)-MAX($E32,Q$3)+1)/Q$5) -> 0 | ... FH32: =MAX(0,(MIN($F32,FH$4)-MAX($E32,FH$3)+1)/FH$5) -> 0
C33: Last debt repayment | D33: flag | E33: =EDATE($F16,In_Debt_Tenor*Months_In_Year) -> 52321 | I33: =SUM(J33:FH33) -> 1 | J33: =N(AND(J$3<=$E33,J$4>=$E33)) -> 0 | K33: =N(AND(K$3<=$E33,K$4>=$E33)) -> 0 | L33: =N(AND(L$3<=$E33,L$4>=$E33)) -> 0 | M33: =N(AND(M$3<=$E33,M$4>=$E33)) -> 0 | N33: =N(AND(N$3<=$E33,N$4>=$E33)) -> 0 | O33: =N(AND(O$3<=$E33,O$4>=$E33)) -> 0 | P33: =N(AND(P$3<=$E33,P$4>=$E33)) -> 0 | Q33: =N(AND(Q$3<=$E33,Q$4>=$E33)) -> 0 | ... FH33: =N(AND(FH$3<=$E33,FH$4>=$E33)) -> 0
C34: Tax depreciation spread: PV, grid, development | D34: factor | E34: =$F16+1 -> 46844 | F34: =EDATE($F16,In_Dep_Years*Months_In_Year) -> 57800 | I34: =SUM(J34:FH34) -> 1 | J34: =MAX(0,MIN($F34,J$4)-MAX($E34,J$3)+1)/($F34-$E34+1) -> 0 | K34: =MAX(0,MIN($F34,K$4)-MAX($E34,K$3)+1)/($F34-$E34+1) -> 0 | L34: =MAX(0,MIN($F34,L$4)-MAX($E34,L$3)+1)/($F34-$E34+1) -> 0 | M34: =MAX(0,MIN($F34,M$4)-MAX($E34,M$3)+1)/($F34-$E34+1) -> 0 | N34: =MAX(0,MIN($F34,N$4)-MAX($E34,N$3)+1)/($F34-$E34+1) -> 0 | O34: =MAX(0,MIN($F34,O$4)-MAX($E34,O$3)+1)/($F34-$E34+1) -> 0 | P34: =MAX(0,MIN($F34,P$4)-MAX($E34,P$3)+1)/($F34-$E34+1) -> 0 | Q34: =MAX(0,MIN($F34,Q$4)-MAX($E34,Q$3)+1)/($F34-$E34+1) -> 0 | ... FH34: =MAX(0,MIN($F34,FH$4)-MAX($E34,FH$3)+1)/($F34-$E34+1) -> 0
C35: Tax depreciation spread: BESS | D35: factor | E35: =$F16+1 -> 46844 | F35: =EDATE($F16,In_Dep_BESS_Years*Months_In_Year) -> 50495 | I35: =SUM(J35:FH35) -> 1 | J35: =MAX(0,MIN($F35,J$4)-MAX($E35,J$3)+1)/($F35-$E35+1) -> 0 | K35: =MAX(0,MIN($F35,K$4)-MAX($E35,K$3)+1)/($F35-$E35+1) -> 0 | L35: =MAX(0,MIN($F35,L$4)-MAX($E35,L$3)+1)/($F35-$E35+1) -> 0 | M35: =MAX(0,MIN($F35,M$4)-MAX($E35,M$3)+1)/($F35-$E35+1) -> 0 | N35: =MAX(0,MIN($F35,N$4)-MAX($E35,N$3)+1)/($F35-$E35+1) -> 0 | O35: =MAX(0,MIN($F35,O$4)-MAX($E35,O$3)+1)/($F35-$E35+1) -> 0 | P35: =MAX(0,MIN($F35,P$4)-MAX($E35,P$3)+1)/($F35-$E35+1) -> 0 | Q35: =MAX(0,MIN($F35,Q$4)-MAX($E35,Q$3)+1)/($F35-$E35+1) -> 0 | ... FH35: =MAX(0,MIN($F35,FH$4)-MAX($E35,FH$3)+1)/($F35-$E35+1) -> 0
C36: Debt compounding index (E: at COD, F: rate per period) | D36: factor | E36: =SUMIF($J$4:$FH$4,$F16,$J36:$FH36) -> 1.1322708 | F36: =In_Debt_Rate*Months_Per_Period/Months_In_Year -> 0.0125 | J36: =(1+$F36)^J$8 -> 1.0125 | K36: =(1+$F36)^K$8 -> 1.0251562 | L36: =(1+$F36)^L$8 -> 1.0379707 | M36: =(1+$F36)^M$8 -> 1.0509453 | N36: =(1+$F36)^N$8 -> 1.0640822 | O36: =(1+$F36)^O$8 -> 1.0773832 | P36: =(1+$F36)^P$8 -> 1.0908505 | Q36: =(1+$F36)^Q$8 -> 1.1044861 | ... FH36: =(1+$F36)^FH$8 -> 6.8585126
C37: 31-Dec capitalisation | D37: flag | J37: =N(MONTH(J$4)=Months_In_Year) -> 1 | K37: =N(MONTH(K$4)=Months_In_Year) -> 0 | L37: =N(MONTH(L$4)=Months_In_Year) -> 0 | M37: =N(MONTH(M$4)=Months_In_Year) -> 0 | N37: =N(MONTH(N$4)=Months_In_Year) -> 1 | O37: =N(MONTH(O$4)=Months_In_Year) -> 0 | P37: =N(MONTH(P$4)=Months_In_Year) -> 0 | Q37: =N(MONTH(Q$4)=Months_In_Year) -> 0 | ... FH37: =N(MONTH(FH$4)=Months_In_Year) -> 0
C38: First quarter of the year | D38: flag | J38: =N(MONTH(J$4)<=Months_Per_Period) -> 0 | K38: =N(MONTH(K$4)<=Months_Per_Period) -> 1 | L38: =N(MONTH(L$4)<=Months_Per_Period) -> 0 | M38: =N(MONTH(M$4)<=Months_Per_Period) -> 0 | N38: =N(MONTH(N$4)<=Months_Per_Period) -> 0 | O38: =N(MONTH(O$4)<=Months_Per_Period) -> 1 | P38: =N(MONTH(P$4)<=Months_Per_Period) -> 0 | Q38: =N(MONTH(Q$4)<=Months_Per_Period) -> 0 | ... FH38: =N(MONTH(FH$4)<=Months_Per_Period) -> 0
A40: x | C40: Prices (real 2025 curves × Aurora euro index)
C41: Aurora euro index | D41: factor | J41: =INDEX(Euro_Index,MATCH(J$7,Price_Years,0)) -> 1 | K41: =INDEX(Euro_Index,MATCH(K$7,Price_Years,0)) -> 1.01897 | L41: =INDEX(Euro_Index,MATCH(L$7,Price_Years,0)) -> 1.01897 | M41: =INDEX(Euro_Index,MATCH(M$7,Price_Years,0)) -> 1.01897 | N41: =INDEX(Euro_Index,MATCH(N$7,Price_Years,0)) -> 1.01897 | O41: =INDEX(Euro_Index,MATCH(O$7,Price_Years,0)) -> 1.040399 | P41: =INDEX(Euro_Index,MATCH(P$7,Price_Years,0)) -> 1.040399 | Q41: =INDEX(Euro_Index,MATCH(Q$7,Price_Years,0)) -> 1.040399 | ... FH41: =INDEX(Euro_Index,MATCH(FH$7,Price_Years,0)) -> 2.1668863
C42: PV price, direct export, real 2025 (E: curve) | D42: EUR/MWh | E42: =INDEX(Case_PV_Curve,1,$F12) -> DC 4h direct | J42: =INDEX(Price_Data,MATCH($E42,Price_Labels,0),MATCH(J$7,Price_Years,0)) -> 0 | K42: =INDEX(Price_Data,MATCH($E42,Price_Labels,0),MATCH(K$7,Price_Years,0)) -> 0 | L42: =INDEX(Price_Data,MATCH($E42,Price_Labels,0),MATCH(L$7,Price_Years,0)) -> 0 | M42: =INDEX(Price_Data,MATCH($E42,Price_Labels,0),MATCH(M$7,Price_Years,0)) -> 0 | N42: =INDEX(Price_Data,MATCH($E42,Price_Labels,0),MATCH(N$7,Price_Years,0)) -> 0 | O42: =INDEX(Price_Data,MATCH($E42,Price_Labels,0),MATCH(O$7,Price_Years,0)) -> 107.45398 | P42: =INDEX(Price_Data,MATCH($E42,Price_Labels,0),MATCH(P$7,Price_Years,0)) -> 107.45398 | Q42: =INDEX(Price_Data,MATCH($E42,Price_Labels,0),MATCH(Q$7,Price_Years,0)) -> 107.45398 | ... FH42: =INDEX(Price_Data,MATCH($E42,Price_Labels,0),MATCH(FH$7,Price_Years,0)) -> 56.585236
C43: PV price, energy sent to the BESS, real 2025 (E: curve) | D43: EUR/MWh | E43: =INDEX(Case_PV_Transfer,1,$F12) -> DC 4h transfer | J43: =INDEX(Price_Data,MATCH($E43,Price_Labels,0),MATCH(J$7,Price_Years,0)) -> 0 | K43: =INDEX(Price_Data,MATCH($E43,Price_Labels,0),MATCH(K$7,Price_Years,0)) -> 0 | L43: =INDEX(Price_Data,MATCH($E43,Price_Labels,0),MATCH(L$7,Price_Years,0)) -> 0 | M43: =INDEX(Price_Data,MATCH($E43,Price_Labels,0),MATCH(M$7,Price_Years,0)) -> 0 | N43: =INDEX(Price_Data,MATCH($E43,Price_Labels,0),MATCH(N$7,Price_Years,0)) -> 0 | O43: =INDEX(Price_Data,MATCH($E43,Price_Labels,0),MATCH(O$7,Price_Years,0)) -> 36.551423 | P43: =INDEX(Price_Data,MATCH($E43,Price_Labels,0),MATCH(P$7,Price_Years,0)) -> 36.551423 | Q43: =INDEX(Price_Data,MATCH($E43,Price_Labels,0),MATCH(Q$7,Price_Years,0)) -> 36.551423 | ... FH43: =INDEX(Price_Data,MATCH($E43,Price_Labels,0),MATCH(FH$7,Price_Years,0)) -> 20.340431
C44: PV merchant price, direct export, nominal (price set applied) | D44: EUR/MWh | J44: =J42*J41*(1+In_PV_Price_Adj) -> 0 | K44: =K42*K41*(1+In_PV_Price_Adj) -> 0 | L44: =L42*L41*(1+In_PV_Price_Adj) -> 0 | M44: =M42*M41*(1+In_PV_Price_Adj) -> 0 | N44: =N42*N41*(1+In_PV_Price_Adj) -> 0 | O44: =O42*O41*(1+In_PV_Price_Adj) -> 111.79501 | P44: =P42*P41*(1+In_PV_Price_Adj) -> 111.79501 | Q44: =Q42*Q41*(1+In_PV_Price_Adj) -> 111.79501 | ... FH44: =FH42*FH41*(1+In_PV_Price_Adj) -> 122.61377
C45: PV transfer price to the BESS, nominal (price set applied) | D45: EUR/MWh | J45: =J43*J41*(1+In_PV_Price_Adj) -> 0 | K45: =K43*K41*(1+In_PV_Price_Adj) -> 0 | L45: =L43*L41*(1+In_PV_Price_Adj) -> 0 | M45: =M43*M41*(1+In_PV_Price_Adj) -> 0 | N45: =N43*N41*(1+In_PV_Price_Adj) -> 0 | O45: =O43*O41*(1+In_PV_Price_Adj) -> 38.028064 | P45: =P43*P41*(1+In_PV_Price_Adj) -> 38.028064 | Q45: =Q43*Q41*(1+In_PV_Price_Adj) -> 38.028064 | ... FH45: =FH43*FH41*(1+In_PV_Price_Adj) -> 44.075402
C46: Guarantee of origin price, nominal | D46: EUR/MWh | J46: =In_GoO*J41 -> 1.75 | K46: =In_GoO*K41 -> 1.7831975 | L46: =In_GoO*L41 -> 1.7831975 | M46: =In_GoO*M41 -> 1.7831975 | N46: =In_GoO*N41 -> 1.7831975 | O46: =In_GoO*O41 -> 1.8206982 | P46: =In_GoO*P41 -> 1.8206982 | Q46: =In_GoO*Q41 -> 1.8206982 | ... FH46: =In_GoO*FH41 -> 3.792051
C47: BESS storage total cashflow, real 2025 (E: curve) | D47: EUR k/MW | E47: =INDEX(Case_BESS_Curve,1,$F12) -> DC 4h | J47: =INDEX(Stack_Data,MATCH($E47,Stack_Labels,0),MATCH(J$7,Stack_Years,0)) -> 0 | K47: =INDEX(Stack_Data,MATCH($E47,Stack_Labels,0),MATCH(K$7,Stack_Years,0)) -> 0 | L47: =INDEX(Stack_Data,MATCH($E47,Stack_Labels,0),MATCH(L$7,Stack_Years,0)) -> 0 | M47: =INDEX(Stack_Data,MATCH($E47,Stack_Labels,0),MATCH(M$7,Stack_Years,0)) -> 0 | N47: =INDEX(Stack_Data,MATCH($E47,Stack_Labels,0),MATCH(N$7,Stack_Years,0)) -> 0 | O47: =INDEX(Stack_Data,MATCH($E47,Stack_Labels,0),MATCH(O$7,Stack_Years,0)) -> 186.97508 | P47: =INDEX(Stack_Data,MATCH($E47,Stack_Labels,0),MATCH(P$7,Stack_Years,0)) -> 186.97508 | Q47: =INDEX(Stack_Data,MATCH($E47,Stack_Labels,0),MATCH(Q$7,Stack_Years,0)) -> 186.97508 | ... FH47: =INDEX(Stack_Data,MATCH($E47,Stack_Labels,0),MATCH(FH$7,Stack_Years,0)) -> 91.148957
C48: Stack kept with PV-only charging (E: curve) | D48: factor | E48: =$E47 -> DC 4h | J48: =INDEX(PVOnly_Data,MATCH($E48,PVOnly_Labels,0),MATCH(J$7,PVOnly_Years,0)) -> 1 | K48: =INDEX(PVOnly_Data,MATCH($E48,PVOnly_Labels,0),MATCH(K$7,PVOnly_Years,0)) -> 1 | L48: =INDEX(PVOnly_Data,MATCH($E48,PVOnly_Labels,0),MATCH(L$7,PVOnly_Years,0)) -> 1 | M48: =INDEX(PVOnly_Data,MATCH($E48,PVOnly_Labels,0),MATCH(M$7,PVOnly_Years,0)) -> 1 | N48: =INDEX(PVOnly_Data,MATCH($E48,PVOnly_Labels,0),MATCH(N$7,PVOnly_Years,0)) -> 1 | O48: =INDEX(PVOnly_Data,MATCH($E48,PVOnly_Labels,0),MATCH(O$7,PVOnly_Years,0)) -> 0.77913121 | P48: =INDEX(PVOnly_Data,MATCH($E48,PVOnly_Labels,0),MATCH(P$7,PVOnly_Years,0)) -> 0.77913121 | Q48: =INDEX(PVOnly_Data,MATCH($E48,PVOnly_Labels,0),MATCH(Q$7,PVOnly_Years,0)) -> 0.77913121 | ... FH48: =INDEX(PVOnly_Data,MATCH($E48,PVOnly_Labels,0),MATCH(FH$7,PVOnly_Years,0)) -> 0.91178898
C49: aFRR-down and FCR share of the stack (E: curve) | D49: factor | E49: =$E47 -> DC 4h | J49: =INDEX(DownCap_Data,MATCH($E49,DownCap_Labels,0),MATCH(J$7,DownCap_Years,0)) -> 0 | K49: =INDEX(DownCap_Data,MATCH($E49,DownCap_Labels,0),MATCH(K$7,DownCap_Years,0)) -> 0 | L49: =INDEX(DownCap_Data,MATCH($E49,DownCap_Labels,0),MATCH(L$7,DownCap_Years,0)) -> 0 | M49: =INDEX(DownCap_Data,MATCH($E49,DownCap_Labels,0),MATCH(M$7,DownCap_Years,0)) -> 0 | N49: =INDEX(DownCap_Data,MATCH($E49,DownCap_Labels,0),MATCH(N$7,DownCap_Years,0)) -> 0 | O49: =INDEX(DownCap_Data,MATCH($E49,DownCap_Labels,0),MATCH(O$7,DownCap_Years,0)) -> 0.16712104 | P49: =INDEX(DownCap_Data,MATCH($E49,DownCap_Labels,0),MATCH(P$7,DownCap_Years,0)) -> 0.16712104 | Q49: =INDEX(DownCap_Data,MATCH($E49,DownCap_Labels,0),MATCH(Q$7,DownCap_Years,0)) -> 0.16712104 | ... FH49: =INDEX(DownCap_Data,MATCH($E49,DownCap_Labels,0),MATCH(FH$7,DownCap_Years,0)) -> 0.13527975
C50: Stack kept without grid charging | D50: factor | J50: =MIN(1,J48+In_AFRR_Down_Share*J49) -> 1 | K50: =MIN(1,K48+In_AFRR_Down_Share*K49) -> 1 | L50: =MIN(1,L48+In_AFRR_Down_Share*L49) -> 1 | M50: =MIN(1,M48+In_AFRR_Down_Share*M49) -> 1 | N50: =MIN(1,N48+In_AFRR_Down_Share*N49) -> 1 | O50: =MIN(1,O48+In_AFRR_Down_Share*O49) -> 0.77913121 | P50: =MIN(1,P48+In_AFRR_Down_Share*P49) -> 0.77913121 | Q50: =MIN(1,Q48+In_AFRR_Down_Share*Q49) -> 0.77913121 | ... FH50: =MIN(1,FH48+In_AFRR_Down_Share*FH49) -> 0.91178898
C51: Grid charging allowed: import ÷ BESS MW (E) | D51: % | E51: =MIN(1,In_Grid_Import_MW/MAX(1,$E18)) -> 0
C52: BESS merchant revenue per MW-year, nominal (haircut, availability, charging) | D52: EUR k/MW | J52: =J47*J41*(1-In_BESS_Haircut)*(J50+(1-J50)*$E51) -> 0 | K52: =K47*K41*(1-In_BESS_Haircut)*(K50+(1-K50)*$E51) -> 0 | L52: =L47*L41*(1-In_BESS_Haircut)*(L50+(1-L50)*$E51) -> 0 | M52: =M47*M41*(1-In_BESS_Haircut)*(M50+(1-M50)*$E51) -> 0 | N52: =N47*N41*(1-In_BESS_Haircut)*(N50+(1-N50)*$E51) -> 0 | O52: =O47*O41*(1-In_BESS_Haircut)*(O50+(1-O50)*$E51) -> 151.56337 | P52: =P47*P41*(1-In_BESS_Haircut)*(P50+(1-P50)*$E51) -> 151.56337 | Q52: =Q47*Q41*(1-In_BESS_Haircut)*(Q50+(1-Q50)*$E51) -> 151.56337 | ... FH52: =FH47*FH41*(1-In_BESS_Haircut)*(FH50+(1-FH50)*$E51) -> 180.08692
C53: BESS repower year (E: used, F: repower year of the curve) | D53: year | E53: =IF(In_Fix_Augment=0,In_Augment_Year_v3,IF(In_Augment_Year>0,In_Augment_Year,$F53)) -> 2048 | F53: =INDEX(Block_Repower,MATCH($E47,Block_Names,0)) -> 2048
C54: BESS in service (0 from the repower year if not repowered) | D54: flag | J54: =1-(1-In_Repower)*(J$7>=$E53) -> 1 | K54: =1-(1-In_Repower)*(K$7>=$E53) -> 1 | L54: =1-(1-In_Repower)*(L$7>=$E53) -> 1 | M54: =1-(1-In_Repower)*(M$7>=$E53) -> 1 | N54: =1-(1-In_Repower)*(N$7>=$E53) -> 1 | O54: =1-(1-In_Repower)*(O$7>=$E53) -> 1 | P54: =1-(1-In_Repower)*(P$7>=$E53) -> 1 | Q54: =1-(1-In_Repower)*(Q$7>=$E53) -> 1 | ... FH54: =1-(1-In_Repower)*(FH$7>=$E53) -> 1
A56: x | C56: Offtake offers (case C; merchant tail after the tenor)
C57: Offer applies on this sheet (case table) | D57: flag | E57: =INDEX(Case_Offer,1,$F12) -> 1
C58: PV offer: column (E), fixed price (F: 1 = yes) | D58: # | E58: =MATCH(In_Offer_PV,OPV_Names,0) -> 2 | F58: =INDEX(OPV_Type,$E58) -> 1
C59: PV offer handling fee: share (E), floor (F) | D59: EUR/MWh | E59: =INDEX(OPV_Fee,$E58) -> 0 | F59: =INDEX(OPV_Fee_Min,$E58) -> 0
C60: PV offer: fee cap (E), fixed price (F) | D60: EUR/MWh | E60: =INDEX(OPV_Fee_Max,$E58) -> 0 | F60: =INDEX(OPV_Price,$E58) -> 43.96
C61: PV offer in force (E: start, F: end) | D61: factor | E61: =IF(INDEX(OPV_Start,$E58)>0,INDEX(OPV_Start,$E58),$F16+1) -> 46753 | F61: =EDATE($E61,INDEX(OPV_Tenor,$E58)*Months_In_Year)-1 -> 47848 | J61: =$E57*MAX(0,MIN($F61,J$4)-MAX($E61,J$3)+1)/J$5 -> 0 | K61: =$E57*MAX(0,MIN($F61,K$4)-MAX($E61,K$3)+1)/K$5 -> 0 | L61: =$E57*MAX(0,MIN($F61,L$4)-MAX($E61,L$3)+1)/L$5 -> 0 | M61: =$E57*MAX(0,MIN($F61,M$4)-MAX($E61,M$3)+1)/M$5 -> 0 | N61: =$E57*MAX(0,MIN($F61,N$4)-MAX($E61,N$3)+1)/N$5 -> 0 | O61: =$E57*MAX(0,MIN($F61,O$4)-MAX($E61,O$3)+1)/O$5 -> 0 | P61: =$E57*MAX(0,MIN($F61,P$4)-MAX($E61,P$3)+1)/P$5 -> 0 | Q61: =$E57*MAX(0,MIN($F61,Q$4)-MAX($E61,Q$3)+1)/Q$5 -> 0 | ... FH61: =$E57*MAX(0,MIN($F61,FH$4)-MAX($E61,FH$3)+1)/FH$5 -> 0
C62: PV offer handling fee | D62: EUR/MWh | J62: =MIN($E60,MAX($E59*J44,$F59)) -> 0 | K62: =MIN($E60,MAX($E59*K44,$F59)) -> 0 | L62: =MIN($E60,MAX($E59*L44,$F59)) -> 0 | M62: =MIN($E60,MAX($E59*M44,$F59)) -> 0 | N62: =MIN($E60,MAX($E59*N44,$F59)) -> 0 | O62: =MIN($E60,MAX($E59*O44,$F59)) -> 0 | P62: =MIN($E60,MAX($E59*P44,$F59)) -> 0 | Q62: =MIN($E60,MAX($E59*Q44,$F59)) -> 0 | ... FH62: =MIN($E60,MAX($E59*FH44,$F59)) -> 0
C63: PV price received on direct export (offer in force, else merchant) | D63: EUR/MWh | J63: =J44+J61*(IF($F58=1,$F60,J44-J62)-J44) -> 0 | K63: =K44+K61*(IF($F58=1,$F60,K44-K62)-K44) -> 0 | L63: =L44+L61*(IF($F58=1,$F60,L44-L62)-L44) -> 0 | M63: =M44+M61*(IF($F58=1,$F60,M44-M62)-M44) -> 0 | N63: =N44+N61*(IF($F58=1,$F60,N44-N62)-N44) -> 0 | O63: =O44+O61*(IF($F58=1,$F60,O44-O62)-O44) -> 111.79501 | P63: =P44+P61*(IF($F58=1,$F60,P44-P62)-P44) -> 111.79501 | Q63: =Q44+Q61*(IF($F58=1,$F60,Q44-Q62)-Q44) -> 111.79501 | ... FH63: =FH44+FH61*(IF($F58=1,$F60,FH44-FH62)-FH44) -> 122.61377
C64: BESS offer: column (E), fixed fee per MW-year, not scaled above the offer (F) | D64: EUR k/MW | E64: =MATCH(In_Offer_BESS,OB_Names,0) -> 3 | F64: =INDEX(OB_Fixed,$E64)*MIN(1,In_BESS_Hours/INDEX(OB_Hours,$E64)) -> 49.7
C65: BESS offer duration ≠ built duration (E: 1 = yes) | D65: flag | E65: =$E57*(INDEX(OB_Tenor,$E64)>0)*N(INDEX(OB_Hours,$E64)<>In_BESS_Hours) -> 1
C66: BESS offer: owner share (E), grid charge deducted (F) | D66: EUR k/MW | E66: =INDEX(OB_Share,$E64) -> 0 | F66: =INDEX(OB_Grid,$E64)*In_BESS_Grid_Charge -> 0
C67: BESS offer in force (E: start, F: end) | D67: factor | E67: =IF(INDEX(OB_Start,$E64)>0,INDEX(OB_Start,$E64),$F16+1) -> 46753 | F67: =EDATE($E67,INDEX(OB_Tenor,$E64)*Months_In_Year)-1 -> 47848 | J67: =$E57*MAX(0,MIN($F67,J$4)-MAX($E67,J$3)+1)/J$5 -> 0 | K67: =$E57*MAX(0,MIN($F67,K$4)-MAX($E67,K$3)+1)/K$5 -> 0 | L67: =$E57*MAX(0,MIN($F67,L$4)-MAX($E67,L$3)+1)/L$5 -> 0 | M67: =$E57*MAX(0,MIN($F67,M$4)-MAX($E67,M$3)+1)/M$5 -> 0 | N67: =$E57*MAX(0,MIN($F67,N$4)-MAX($E67,N$3)+1)/N$5 -> 0 | O67: =$E57*MAX(0,MIN($F67,O$4)-MAX($E67,O$3)+1)/O$5 -> 0 | P67: =$E57*MAX(0,MIN($F67,P$4)-MAX($E67,P$3)+1)/P$5 -> 0 | Q67: =$E57*MAX(0,MIN($F67,Q$4)-MAX($E67,Q$3)+1)/Q$5 -> 0 | ... FH67: =$E57*MAX(0,MIN($F67,FH$4)-MAX($E67,FH$3)+1)/FH$5 -> 0
C68: E.ON band table row this year (0 = none; E: bands apply) | D68: # | E68: =INDEX(OB_Bands,$E64) -> 0 | J68: =$E68*SUMIF(EB_Years,J$7,EB_Row) -> 0 | K68: =$E68*SUMIF(EB_Years,K$7,EB_Row) -> 0 | L68: =$E68*SUMIF(EB_Years,L$7,EB_Row) -> 0 | M68: =$E68*SUMIF(EB_Years,M$7,EB_Row) -> 0 | N68: =$E68*SUMIF(EB_Years,N$7,EB_Row) -> 0 | O68: =$E68*SUMIF(EB_Years,O$7,EB_Row) -> 0 | P68: =$E68*SUMIF(EB_Years,P$7,EB_Row) -> 0 | Q68: =$E68*SUMIF(EB_Years,Q$7,EB_Row) -> 0 | ... FH68: =$E68*SUMIF(EB_Years,FH$7,EB_Row) -> 0
C69: Band table row looked up | D69: # | J69: =MAX(1,J68) -> 1 | K69: =MAX(1,K68) -> 1 | L69: =MAX(1,L68) -> 1 | M69: =MAX(1,M68) -> 1 | N69: =MAX(1,N68) -> 1 | O69: =MAX(1,O68) -> 1 | P69: =MAX(1,P68) -> 1 | Q69: =MAX(1,Q68) -> 1 | ... FH69: =MAX(1,FH68) -> 1
C70: E.ON fee on the stack, by band | D70: EUR k/MW | J70: =(J68>0)*SUMPRODUCT((J52>INDEX(EB_LB,J69,0))*(J52-INDEX(EB_LB,J69,0)),INDEX(EB_dR,J69,0)) -> 0 | K70: =(K68>0)*SUMPRODUCT((K52>INDEX(EB_LB,K69,0))*(K52-INDEX(EB_LB,K69,0)),INDEX(EB_dR,K69,0)) -> 0 | L70: =(L68>0)*SUMPRODUCT((L52>INDEX(EB_LB,L69,0))*(L52-INDEX(EB_LB,L69,0)),INDEX(EB_dR,L69,0)) -> 0 | M70: =(M68>0)*SUMPRODUCT((M52>INDEX(EB_LB,M69,0))*(M52-INDEX(EB_LB,M69,0)),INDEX(EB_dR,M69,0)) -> 0 | N70: =(N68>0)*SUMPRODUCT((N52>INDEX(EB_LB,N69,0))*(N52-INDEX(EB_LB,N69,0)),INDEX(EB_dR,N69,0)) -> 0 | O70: =(O68>0)*SUMPRODUCT((O52>INDEX(EB_LB,O69,0))*(O52-INDEX(EB_LB,O69,0)),INDEX(EB_dR,O69,0)) -> 0 | P70: =(P68>0)*SUMPRODUCT((P52>INDEX(EB_LB,P69,0))*(P52-INDEX(EB_LB,P69,0)),INDEX(EB_dR,P69,0)) -> 0 | Q70: =(Q68>0)*SUMPRODUCT((Q52>INDEX(EB_LB,Q69,0))*(Q52-INDEX(EB_LB,Q69,0)),INDEX(EB_dR,Q69,0)) -> 0 | ... FH70: =(FH68>0)*SUMPRODUCT((FH52>INDEX(EB_LB,FH69,0))*(FH52-INDEX(EB_LB,FH69,0)),INDEX(EB_dR,FH69,0)) -> 0
C71: Guaranteed floor in band years | D71: EUR k/MW | J71: =(J68>0)*INDEX(EB_Floor,J69) -> 0 | K71: =(K68>0)*INDEX(EB_Floor,K69) -> 0 | L71: =(L68>0)*INDEX(EB_Floor,L69) -> 0 | M71: =(M68>0)*INDEX(EB_Floor,M69) -> 0 | N71: =(N68>0)*INDEX(EB_Floor,N69) -> 0 | O71: =(O68>0)*INDEX(EB_Floor,O69) -> 0 | P71: =(P68>0)*INDEX(EB_Floor,P69) -> 0 | Q71: =(Q68>0)*INDEX(EB_Floor,Q69) -> 0 | ... FH71: =(FH68>0)*INDEX(EB_Floor,FH69) -> 0
C72: Owner share of the stack above the fixed fee | D72: % | J72: =IF(J68>0,1,$E66) -> 0 | K72: =IF(K68>0,1,$E66) -> 0 | L72: =IF(L68>0,1,$E66) -> 0 | M72: =IF(M68>0,1,$E66) -> 0 | N72: =IF(N68>0,1,$E66) -> 0 | O72: =IF(O68>0,1,$E66) -> 0 | P72: =IF(P68>0,1,$E66) -> 0 | Q72: =IF(Q68>0,1,$E66) -> 0 | ... FH72: =IF(FH68>0,1,$E66) -> 0
C73: Owner BESS revenue per MW-year under the offer | D73: EUR k/MW | J73: =MAX(J71,$F64+J72*MAX(0,J52-$F66-$F64)-J70) -> 49.7 | K73: =MAX(K71,$F64+K72*MAX(0,K52-$F66-$F64)-K70) -> 49.7 | L73: =MAX(L71,$F64+L72*MAX(0,L52-$F66-$F64)-L70) -> 49.7 | M73: =MAX(M71,$F64+M72*MAX(0,M52-$F66-$F64)-M70) -> 49.7 | N73: =MAX(N71,$F64+N72*MAX(0,N52-$F66-$F64)-N70) -> 49.7 | O73: =MAX(O71,$F64+O72*MAX(0,O52-$F66-$F64)-O70) -> 49.7 | P73: =MAX(P71,$F64+P72*MAX(0,P52-$F66-$F64)-P70) -> 49.7 | Q73: =MAX(Q71,$F64+Q72*MAX(0,Q52-$F66-$F64)-Q70) -> 49.7 | ... FH73: =MAX(FH71,$F64+FH72*MAX(0,FH52-$F66-$F64)-FH70) -> 49.7
C74: BESS revenue per MW-year received | D74: EUR k/MW | J74: =J52+J67*(J73-J52) -> 0 | K74: =K52+K67*(K73-K52) -> 0 | L74: =L52+L67*(L73-L52) -> 0 | M74: =M52+M67*(M73-M52) -> 0 | N74: =N52+N67*(N73-N52) -> 0 | O74: =O52+O67*(O73-O52) -> 151.56337 | P74: =P52+P67*(P73-P52) -> 151.56337 | Q74: =Q52+Q67*(Q73-Q52) -> 151.56337 | ... FH74: =FH52+FH67*(FH73-FH52) -> 180.08692
A76: x | C76: Capacity and energy (annual balance; hourly limits inside Aurora's dispatch)
C77: PV generation after availability and degradation (E: first full year) | D77: MWh | E77: =SUMIF($J$7:$FH$7,YEAR($F16)+1,$J77:$FH77) -> 79028.166 | I77: =SUM(J77:FH77) -> 2636990.7 | J77: =$E13*$F14*In_PV_Avail*(1-In_Degradation)^J29*J28*J$6 -> 0 | K77: =$E13*$F14*In_PV_Avail*(1-In_Degradation)^K29*K28*K$6 -> 0 | L77: =$E13*$F14*In_PV_Avail*(1-In_Degradation)^L29*L28*L$6 -> 0 | M77: =$E13*$F14*In_PV_Avail*(1-In_Degradation)^M29*M28*M$6 -> 0 | N77: =$E13*$F14*In_PV_Avail*(1-In_Degradation)^N29*N28*N$6 -> 0 | O77: =$E13*$F14*In_PV_Avail*(1-In_Degradation)^O29*O28*O$6 -> 0 | P77: =$E13*$F14*In_PV_Avail*(1-In_Degradation)^P29*P28*P$6 -> 0 | Q77: =$E13*$F14*In_PV_Avail*(1-In_Degradation)^Q29*Q28*Q$6 -> 0 | ... FH77: =$E13*$F14*In_PV_Avail*(1-In_Degradation)^FH29*FH28*FH$6 -> 0
C78: Clipped (case table: v3 + fix 5 in A, DC-coupled 0 in B, C) | D78: MWh | I78: =SUM(J78:FH78) -> 0 | J78: =-J77*$E17 -> 0 | K78: =-K77*$E17 -> 0 | L78: =-L77*$E17 -> 0 | M78: =-M77*$E17 -> 0 | N78: =-N77*$E17 -> 0 | O78: =-O77*$E17 -> 0 | P78: =-P77*$E17 -> 0 | Q78: =-Q77*$E17 -> 0 | ... FH78: =-FH77*$E17 -> 0
C79: Aurora block: charge from PV per MW (E: curve) | D79: MWh | E79: =$E47 -> DC 4h | J79: =INDEX(ChargeRES_Data,MATCH($E79,ChargeRES_Labels,0),MATCH(J$7,ChargeRES_Years,0)) -> 0 | K79: =INDEX(ChargeRES_Data,MATCH($E79,ChargeRES_Labels,0),MATCH(K$7,ChargeRES_Years,0)) -> 0 | L79: =INDEX(ChargeRES_Data,MATCH($E79,ChargeRES_Labels,0),MATCH(L$7,ChargeRES_Years,0)) -> 0 | M79: =INDEX(ChargeRES_Data,MATCH($E79,ChargeRES_Labels,0),MATCH(M$7,ChargeRES_Years,0)) -> 0 | N79: =INDEX(ChargeRES_Data,MATCH($E79,ChargeRES_Labels,0),MATCH(N$7,ChargeRES_Years,0)) -> 0 | O79: =INDEX(ChargeRES_Data,MATCH($E79,ChargeRES_Labels,0),MATCH(O$7,ChargeRES_Years,0)) -> -992.69296 | P79: =INDEX(ChargeRES_Data,MATCH($E79,ChargeRES_Labels,0),MATCH(P$7,ChargeRES_Years,0)) -> -992.69296 | Q79: =INDEX(ChargeRES_Data,MATCH($E79,ChargeRES_Labels,0),MATCH(Q$7,ChargeRES_Years,0)) -> -992.69296 | ... FH79: =INDEX(ChargeRES_Data,MATCH($E79,ChargeRES_Labels,0),MATCH(FH$7,ChargeRES_Years,0)) -> -841.29448
C80: Aurora block: charge from the grid per MW | D80: MWh | E80: =$E47 -> DC 4h | J80: =INDEX(ChargeGrid_Data,MATCH($E80,ChargeGrid_Labels,0),MATCH(J$7,ChargeGrid_Years,0)) -> 0 | K80: =INDEX(ChargeGrid_Data,MATCH($E80,ChargeGrid_Labels,0),MATCH(K$7,ChargeGrid_Years,0)) -> 0 | L80: =INDEX(ChargeGrid_Data,MATCH($E80,ChargeGrid_Labels,0),MATCH(L$7,ChargeGrid_Years,0)) -> 0 | M80: =INDEX(ChargeGrid_Data,MATCH($E80,ChargeGrid_Labels,0),MATCH(M$7,ChargeGrid_Years,0)) -> 0 | N80: =INDEX(ChargeGrid_Data,MATCH($E80,ChargeGrid_Labels,0),MATCH(N$7,ChargeGrid_Years,0)) -> 0 | O80: =INDEX(ChargeGrid_Data,MATCH($E80,ChargeGrid_Labels,0),MATCH(O$7,ChargeGrid_Years,0)) -> -751.2864 | P80: =INDEX(ChargeGrid_Data,MATCH($E80,ChargeGrid_Labels,0),MATCH(P$7,ChargeGrid_Years,0)) -> -751.2864 | Q80: =INDEX(ChargeGrid_Data,MATCH($E80,ChargeGrid_Labels,0),MATCH(Q$7,ChargeGrid_Years,0)) -> -751.2864 | ... FH80: =INDEX(ChargeGrid_Data,MATCH($E80,ChargeGrid_Labels,0),MATCH(FH$7,ChargeGrid_Years,0)) -> -579.51105
C81: Aurora block: discharge per MW | D81: MWh | E81: =$E47 -> DC 4h | J81: =INDEX(Discharge_Data,MATCH($E81,Discharge_Labels,0),MATCH(J$7,Discharge_Years,0)) -> 0 | K81: =INDEX(Discharge_Data,MATCH($E81,Discharge_Labels,0),MATCH(K$7,Discharge_Years,0)) -> 0 | L81: =INDEX(Discharge_Data,MATCH($E81,Discharge_Labels,0),MATCH(L$7,Discharge_Years,0)) -> 0 | M81: =INDEX(Discharge_Data,MATCH($E81,Discharge_Labels,0),MATCH(M$7,Discharge_Years,0)) -> 0 | N81: =INDEX(Discharge_Data,MATCH($E81,Discharge_Labels,0),MATCH(N$7,Discharge_Years,0)) -> 0 | O81: =INDEX(Discharge_Data,MATCH($E81,Discharge_Labels,0),MATCH(O$7,Discharge_Years,0)) -> 1434.7848 | P81: =INDEX(Discharge_Data,MATCH($E81,Discharge_Labels,0),MATCH(P$7,Discharge_Years,0)) -> 1434.7848 | Q81: =INDEX(Discharge_Data,MATCH($E81,Discharge_Labels,0),MATCH(Q$7,Discharge_Years,0)) -> 1434.7848 | ... FH81: =INDEX(Discharge_Data,MATCH($E81,Discharge_Labels,0),MATCH(FH$7,Discharge_Years,0)) -> 1151.9674
C82: Aurora block: discharge per MW coverable by PV charging | D82: MWh | J82: =MIN(J81,-J79*In_BESS_RTE) -> 0 | K82: =MIN(K81,-K79*In_BESS_RTE) -> 0 | L82: =MIN(L81,-L79*In_BESS_RTE) -> 0 | M82: =MIN(M81,-M79*In_BESS_RTE) -> 0 | N82: =MIN(N81,-N79*In_BESS_RTE) -> 0 | O82: =MIN(O81,-O79*In_BESS_RTE) -> 853.71595 | P82: =MIN(P81,-P79*In_BESS_RTE) -> 853.71595 | Q82: =MIN(Q81,-Q79*In_BESS_RTE) -> 853.71595 | ... FH82: =MIN(FH81,-FH79*In_BESS_RTE) -> 723.51325
C83: PV energy sent to the BESS | D83: MWh | I83: =SUM(J83:FH83) -> 1572735.8 | J83: =MIN(J77+J78,-J79*$E18*J28*J$6*J54) -> 0 | K83: =MIN(K77+K78,-K79*$E18*K28*K$6*K54) -> 0 | L83: =MIN(L77+L78,-L79*$E18*L28*L$6*L54) -> 0 | M83: =MIN(M77+M78,-M79*$E18*M28*M$6*M54) -> 0 | N83: =MIN(N77+N78,-N79*$E18*N28*N$6*N54) -> 0 | O83: =MIN(O77+O78,-O79*$E18*O28*O$6*O54) -> 0 | P83: =MIN(P77+P78,-P79*$E18*P28*P$6*P54) -> 0 | Q83: =MIN(Q77+Q78,-Q79*$E18*Q28*Q$6*Q54) -> 0 | ... FH83: =MIN(FH77+FH78,-FH79*$E18*FH28*FH$6*FH54) -> 0
C84: PV energy exported directly | D84: MWh | I84: =SUM(J84:FH84) -> 1064254.9 | J84: =J77+J78-J83 -> 0 | K84: =K77+K78-K83 -> 0 | L84: =L77+L78-L83 -> 0 | M84: =M77+M78-M83 -> 0 | N84: =N77+N78-N83 -> 0 | O84: =O77+O78-O83 -> 0 | P84: =P77+P78-P83 -> 0 | Q84: =Q77+Q78-Q83 -> 0 | ... FH84: =FH77+FH78-FH83 -> 0
